Workbook

Sheet DM  Programa de Auditoria
A1: OBLIGACIONES FISCALES
A3: Programa
A4: Nombre del cliente | D4: Periodo terminado
A6: Preparado por: | C6: Fecha: | D6: Referencia
D7: DM
A8: Revisado por: | C8: Fecha:
A13: 1. Naturaleza de la cuenta.- Al efectuar la revisión de impuestos se combinan cuentas de activo y pasivo, por lo tanto en esta revisión tenemos cuenta con saldo deudor y cuentas con saldo acreedor.
A14: Se debita.- Las compras realizadas por la Compañía y el Iva en Compras
A15: Se acredita.- Las retenciones de renta e Iva efectuadas por la Compañía, Las ventas realizadas por la Compañía,el Iva en Ventas
A16: II.- OBJETIVOS
A17: 1. Analizar los riesgos inherentes respecto al no cumplimiento de las Obligaciones Fiscales
A18: 2. Analizar el control interno sobre las Obligaciones Fiscales
A19: 4. Confirmar la integridad de la Información Tributaria
A20: 5. Determinar si las declaraciones y anexos tributarios efectuadas están realizadas correctamente
A21: 7. Determinar el cumplimiento adecuado y oportuno de las obligaciones fiscales
A23: Nº | B23: Procedimiento | C23: Referencia | D23: Fecha | E23: Elaborado por | F23: Observación
A24: 1 | B24: Evalué los procedimientos de control interno mediante la aplicación del cuestionario de control interno, determine el alcance del trabajo y determine el riesgo de control. | C24: DM1
A25: 2 | B25: Realice la sumaria para esta cuenta | C25: DM2 | D25: =+D24 | E25: =+E24
A26: 4 | B26: Elaboramos una prueba de saldos globales a la fecha de corte. | C26: DM3 | D26: =+D25 | E26: =+E25
A27: 5 | B27: Conciliar el valor en libros de compras 12, 0% e IVA compras con el formulario 104 | C27: DM4 | D27: =+D26 | E27: =+E26
A28: 6 | B28: Conciliar el valor en libros de Ventas e IVA ventas respecto al formulario 104 | C28: DM5 | D28: =+D27 | E28: =+E27
A29: 7 | B29: Elaborar el cuadro de conciliación de compras, ventas, retenciones en la fuente libros respecto a los valores declarados en el formulario 104 | C29: DM6 | D29: =+D28 | E29: =+E28
A30: 8 | B30: Conciliar los valores de retenciones en la fuente de IVA por pagar libros respecto formulario 104 | C30: DM7 | D30: =+D29 | E30: =+E29
A31: 9 | B31: Conciliar los valores de retenciones en la fuente de renta por pagar libros respecto formulario 103 | C31: DM7 | D31: =+D30 | E31: =+E30
A32: 10 | B32: Conciliar los anexos ATS con los formularios 103 y 104 | C32: DM8 | D32: =+D31 | E32: =+E31
A33: 11 | B33: Elaborar la Hoja de Hallazgos con las observaciones determinadas | C33: DM9 | D33: =+D32 | E33: =+E32

Sheet DM1 Cuestionario de Auditoria 
A1: OBLIGACIONES FISCALES
A3: Cuestionario
A4: Nombre del cliente | D4: Periodo terminado
A5: =+'DM Programa de Auditoria'!A5:C5 | D5: =+'DM Programa de Auditoria'!D5:E5
A6: Preparado por: | C6: Fecha: | D6: Referencia
A7: =+'DM Programa de Auditoria'!A7:B7 | C7: =+'DM Programa de Auditoria'!C7 | D7: DM1
A8: Revisado por: | C8: Fecha:
C9: =+'DM Programa de Auditoria'!C9
A12: N. | B12: Pregunta | C12: SI | D12: NO | E12: N/A | F12: EVAL | G12: Observación
A13: 1 | B13: ¿Existe una persona que determine los impuestos que deben causarse ? | C13: X | F13: 10
B14: ¿Existe una persona que autorice el pago de impuestos? | C14: X | F14: 10
A15: =+A13+1 | B15: Se tienen calendarizadas las obligaciones fiscales y monitoreado su cumplimiento? | C15: X | F15: 10
A16: =+A15+1 | B16: Las declaraciones son conciliadas con registros contables | C16: X | F16: 10
A17: =+A16+1 | B17: Se realiza la comparación de declaraciones con anexos transaccionales. | C17: X | F17: 10
A18: =+A17+1 | B18: Las declaraciones de impuestos son presentadas oportunamente | C18: X | F18: 10
A19: =+A18+1 | B19: Se lleva un debido archivo de las declaraciones, anexos,y de los detalles necesarios para la declaración. | C19: X | F19: 10
A20: =+A19+1 | B20: Existe una persona que revise que las declaraciones y anexos esten debidamente realizadas y tengan su respectivo soporte de documentación | C20: X | F20: 10
A21: =+A20+1 | B21: Existe un archivo completo y ordenado de declaraciones y comprobantes de pago; y otros requerimientos fiscales | C21: X | F21: 10
B24: TOTAL CALIFICACION | F24: =COUNTIF(F13:F21,">9")
B25: N° PREGUNTAS | F25: =+COUNT(A13:A21)
B26: CUMPLIMIENTO CONTRO INTERNO | F26: =+((F24/F25)*100)
B27: CALIFICACION DEL RIESGO | F27: =IF(F26<=30,"ALTO",IF(AND(F26>30,F26<75),"MODERADO",IF(AND(F26>90<100),"MODERADO","BAJO")))

Sheet DM2 Cédula Sumaria
A1: OBLIGACIONES FISCALES
A3: Sumaria
A4: Nombre del cliente | D4: Periodo terminado
A5: =+'DM1 Cuestionario de Auditoria '!A5:C5 | D5: =+'DM1 Cuestionario de Auditoria '!D5:E5
A6: Preparado por: | C6: Fecha: | D6: Referencia
A7: =+'DM1 Cuestionario de Auditoria '!A7:B7 | C7: =+'DM1 Cuestionario de Auditoria '!C7 | D7: DM2
A8: Revisado por: | C8: Fecha:
A12: Código | B12: Descripción | C12: Saldo | D12: Variación | E12: Porcentaje % | F12: Saldo | H12: Ajustes y/o reclasificaciones | K12: Saldo | M12: Referencia
H13: Debe | I13: Haber | K13: Auditado
A14: 1.01.05.01.01 | B14: IVA Compras 12% | C14: 0 | D14: =+F14-C14 | E14: =+D14/C14 | F14: 0 | G14: ü | H14: 0 | I14: 0 | J14: ü | K14: =+F14+H14-I14 | L14: ü | M14: DM4
A15: 1.01.05.02.01 | B15: Retencion IVA 30% | C15: 0 | D15: =+F15-C15 | E15: =+D15/C15 | F15: 0 | G15: ü | H15: 0 | I15: 0 | J15: ü | K15: =+F15+H15-I15 | L15: ü | M15: DM4
A16: 1.01.05.02.04 | B16: Ret. Fte. IVA Clientes | C16: 0 | D16: =+F16-C16 | E16: =+D16/C16 | F16: 0 | G16: ü | H16: 0 | I16: 0 | J16: ü | K16: =+F16+H16-I16 | L16: ü | M16: DM4
A17: 1.01.05.02.05 | B17: Retencion IVA 10% | C17: 0 | D17: =+F17-C17 | E17: =+D17/C17 | F17: 0 | G17: ü | H17: 0 | I17: 0 | J17: ü | K17: =+F17+H17-I17 | L17: ü | M17: DM6
A18: 1.01.05.03.01 | B18: Crédito Tributario Adquisiciones | C18: 0 | D18: =+F18-C18 | E18: =+D18/C18 | F18: 0 | G18: ü | H18: 0 | I18: 0 | J18: ü | K18: =+F18+H18-I18 | L18: ü | M18: DM6
A19: 1.01.05.04.01 | B19: Credito Tributario Retenciones IVA | C19: 0 | D19: =+F19-C19 | E19: =+D19/C19 | G19: ü | H19: 0 | I19: 0 | J19: ü | K19: =+F19+H19-I19 | L19: ü | M19: DM6
A20: 1.01.05.05.01 | B20: Retenciones en la Fuente IR 2023 | D20: =+F20-C20 | E20: =+D20/C20 | F20: 0 | G20: ü | H20: 0 | I20: 0 | J20: ü | K20: =+F20+H20-I20 | L20: ü | M20: DM6
A21: 1.01.05.05.13 | B21: Retenciones en la fuente IR 2024 | D21: =+F21-C21 | E21: =+D21/C21 | G21: ü | H21: 0 | I21: 0 | J21: ü | K21: =+F21+H21-I21 | L21: ü | M21: DM6
A22: 1.01.05.05.14 | B22: Retenciones en la Fuente IR 2025 | C22: 0 | D22: =+F22-C22 | E22: =+D22/C22 | G22: ü | H22: 0 | I22: 0 | J22: ü | K22: =+F22+H22-I22 | L22: ü | M22: DM6
A23: 1.01.05.05.15 | B23: Credito Tributario Utilidades no distribuidas | C23: 0 | D23: =+F23-C23 | E23: =+D23/C23 | G23: ü | H23: 0 | I23: 0 | J23: ü | K23: =+F23+H23-I23 | L23: ü | M23: DM6
A24: Total | C24: =SUM(C14:C23) | D24: =SUM(D14:D23) | E24: =+E14+E18 | F24: =SUM(F14:F23) | G24: Σ | H24: =+H14+H18 | I24: =+I14+I18 | J24: Σ | K24: =+K14+K18
A26: 2.01.10.04.01 | B26: SRI Impuesto por Liquidar | D26: =+F26-C26 | E26: =+D26/C26 | G26: ü | H26: 0 | I26: 0 | J26: ü | K26: =+F26+H26-I26 | L26: ü | M26: DM7
A27: 2.01.10.05.01 | B27: IR Por Pagar Ejercicio Anterior | C27: 0 | D27: =+F27-C27 | E27: =+D27/C27 | F27: 0 | G27: ü | H27: 0 | I27: 0 | J27: ü | K27: =+F27+H27-I27 | L27: ü | M27: DM7
A29: Total | C29: =SUM(C26:C28) | D29: =SUM(D26:D28) | E29: =SUM(E26:E28) | F29: =SUM(F26:F28) | G29: Σ | H29: =SUM(H26:H28) | I29: =SUM(I26:I28) | J29: Σ | K29: =SUM(K26:K28)
A32: Marcas:
A33: ü | B33: Verificado, comprobado, cotejado (con libros).
A34: Σ | B34: Sumado, totalizado
A39: Conclusiones: En conclusión, al observar el recorrido de la cuenta de obligaciones fiscales de la información es razonable.

Sheet DM3 Revisión de saldos
A1: OBLIGACIONES FISCALES
A3: Saldo globales
A4: Nombre del cliente | D4: Periodo terminado
A5: =+'DM2 Cédula Sumaria'!A5:C5 | D5: =+'DM2 Cédula Sumaria'!D5:E5
A6: Preparado por: | C6: Fecha: | D6: Referencia
A7: =+'DM2 Cédula Sumaria'!A7:B7 | C7: =+'DM2 Cédula Sumaria'!C7 | D7: DM3
A8: Revisado por: | C8: Fecha:
A13: Código | B13: Cuenta | C13: Valor US$
B18: Según libros | C18: =+C14+C16+C15 | D18: ü
B20: Según F104 casillero 529 | C20: 0
B21: Diferencia | C21: =+C18-C19-C20 | D21: ‡
A24: Código | B24: Cuenta | C24: Valor US$
B28: Según libros | C28: =+C25+C26 | D28: ü
B30: Según F104 casillero 429 | C30: 0
B31: Diferencia | C31: =+C28+C30 | D31: ‡
A34: Código | B34: Cuenta | C34: Valor US$
A35: 1.01.02.04.01.50 | B35: Crédito Tributario acumulado por Retenciones | C35: =+'DM2 Cédula Sumaria'!F19
A36: 1.01.02.04.01.51 | B36: Retenciones de IVA | C36: 0
B38: Según libros | C38: =+C35+C36 | D38: ü
B40: Según F 104 casillero 615+617 | C40: =+'DM6 IVA'!Z31
B41: Diferencia | C41: =+C38-C40 | D41: ‡
A45: Código | B45: Cuenta | C45: Valor US$
A46: 2.01.10.04.01 | B46: SRI Impuesto por Liquidar | C46: =-'DM2 Cédula Sumaria'!F26
A47: 2.01.01.04.02.99 | B47: Retenciones en la Fuente por Pagar | C47: =-'DM2 Cédula Sumaria'!#REF!
B49: Según libros | C49: =SUM(C46:C48) | D49: ü
B51: Según F 103 | C51: =+'DM7 Retenciones x pagar'!N32+'DM7 Retenciones x pagar'!U56
B52: Diferencia | C52: =+C49-C51 | D52: ‡ | E52: Facilidades de pago IR 2022
A55: Código | B55: Cuenta | C55: Valor US$
B56: =+'DM2 Cédula Sumaria'!#REF! | C56: 0
B59: Según libros | C59: =SUM(C56:C58) | D59: ü
B61: Según F 103 | C61: =+'DM7 Retenciones x pagar'!U56
B62: Diferencia | C62: =+C59-C61 | D62: ‡
A65: Código | B65: Cuenta | C65: Valor US$
B66: =+'DM2 Cédula Sumaria'!#REF! | C66: 0
B69: Según libros | C69: =SUM(C66:C68) | D69: ü
B71: Según Formulario 104 | C71: =+'DM7 Retenciones x pagar'!G32
B72: Diferencia | C72: =+C69-C71 | D72: ‡
A75: Código | B75: Cuenta | C75: Valor US$
A76: 1.01.05.03.01 | B76: Anticipo de impuesto a la renta | C76: 0
B78: Según libros | C78: =SUM(C76:C77)
B80: Según F 115 07 | C80: 0
B81: Según F 115 09 | C81: 0
B82: Diferencia | C82: =+C78-C80-C81
A86: Código | B86: Cuenta | C86: Valor US$
B92: Según libros | C92: =SUM(C87:C91) | D92: ü
B94: Según F 104 | C94: =+'DM7 Retenciones x pagar'!N29
B95: Diferencia | C95: =+C92+C94 | D95: ‡
A100: Marcas:
A101: ü | B101: Verificado, comprobado, cotejado (con libros).
A102: ‡ | B102: Diferencia determinada.

Sheet DM4 Compras 
A1: OBLIGACIONES FISCALES
A3: Compras e IVA en compras
A5: Nombre del cliente | D5: Periodo terminado
A6: =+'DM3 Revisión de saldos'!A5:C5 | D6: =+'DM3 Revisión de saldos'!D5:E5
A7: Preparado por: | C7: Fecha: | D7: Referencia
A8: =+'DM3 Revisión de saldos'!A7:B7 | C8: =+'DM3 Revisión de saldos'!C7 | D8: DM4
A9: Revisado por: | C9: Fecha:
A10: =+'DM3 Revisión de saldos'!A9:B9
A15: IVA EN COMPRAS | B15: Cuenta | C15: Enero | D15: Febrero | E15: Marzo | F15: Abril | G15: Mayo | H15: Junio | I15: Julio | J15: Agosto | K15: Septiembre | L15: Octubre | M15: Noviembre | N15: Diciembre | O15: Total
B16: IVA Activos Fijos | C16: 0 | D16: 0 | E16: 0 | F16: 0 | G16: 0 | H16: 0 | I16: 0 | J16: 0 | K16: 0 | L16: 0 | M16: 0 | N16: 0 | O16: =SUM(C16:N16)
B17: IVA Compras | O17: =SUM(C17:N17)
B18: IVA Compras 5% | C18: 0 | F18: 0 | H18: 0 | I18: 0 | J18: 0 | K18: 0 | L18: 0 | M18: 0 | O18: =SUM(C18:N18)
B19: IVA que se carga al Gasto | C19: 0 | D19: 0 | E19: 0 | F19: 0 | G19: 0 | H19: 0 | I19: 0 | J19: 0 | K19: 0 | L19: 0 | M19: 0 | N19: 0 | O19: =SUM(C19:N19)
B20: Según libros | C20: =SUM(C16:C19) | D20: =SUM(D16:D19) | E20: =SUM(E16:E19) | F20: =SUM(F16:F19) | G20: =SUM(G16:G19) | H20: =SUM(H16:H19) | I20: =SUM(I16:I19) | J20: =SUM(J16:J19) | ... O20: =SUM(O16:O19)
B22: Casillero 520 | O22: =SUM(C22:N22)
B23: Casillero 521 | E23: 0 | F23: 0 | H23: 0 | I23: 0 | J23: 0 | L23: 0 | O23: =SUM(C23:N23)
B24: Casillero 522 | O24: =SUM(C24:N24)
B25: Casillero 523 | C25: 0 | D25: 0 | E25: 0 | F25: 0 | G25: 0 | H25: 0 | I25: 0 | J25: 0 | K25: 0 | L25: 0 | M25: 0 | N25: 0 | O25: =SUM(C25:N25)
B26: Casillero 524 | C26: 0 | D26: 0 | E26: 0 | F26: 0 | G26: 0 | H26: 0 | I26: 0 | J26: 0 | K26: 0 | L26: 0 | M26: 0 | N26: 0 | O26: =SUM(C26:N26)
B27: Casillero 525 | C27: 0 | D27: 0 | E27: 0 | F27: 0 | G27: 0 | H27: 0 | I27: 0 | J27: 0 | K27: 0 | L27: 0 | M27: 0 | N27: 0 | O27: =SUM(C27:N27)
B28: Casillero 526 | C28: 0 | D28: 0 | E28: 0 | F28: 0 | G28: 0 | H28: 0 | I28: 0 | J28: 0 | K28: 0 | L28: 0 | M28: 0 | N28: 0 | O28: =SUM(C28:N28)
B29: Casillero 560 | C29: 0 | F29: 0 | H29: 0 | I29: 0 | J29: 0 | K29: 0 | L29: 0 | M29: 0 | O29: =SUM(C29:N29)
B30: Casillero 555 | C30: 0 | D30: 0 | E30: 0 | F30: 0 | G30: 0 | H30: 0 | I30: 0 | J30: 0 | K30: 0 | L30: 0 | M30: 0 | N30: 0 | O30: =SUM(C30:N30)
B31: Según declaraciones | C31: =SUM(C22:C30)-C24 | D31: =SUM(D22:D30)-D24 | E31: =SUM(E22:E30)-E24 | F31: =SUM(F22:F30)-F24 | G31: =SUM(G22:G30)-G24 | H31: =SUM(H22:H30)-H24 | I31: =SUM(I22:I30)-I24 | J31: =SUM(J22:J30)-J24 | ... N31: =SUM(N22:N30)-N24 | O31: =SUM(O22:O30)
B33: Diferencia | C33: =+C20-C31 | D33: =+D20-D31 | E33: =+E20-E31 | F33: =+F20-F31 | G33: =+G20-G31 | H33: =+H20-H31 | I33: =+I20-I31 | J33: =+J20-J31 | ... N33: =+N20-N31 | O33: =SUM(C33:N33)
A37: BASE DE IVA COMPRAS 12% | B37: Cuenta | C37: Enero | D37: Febrero | E37: Marzo | F37: Abril | G37: Mayo | H37: Junio | I37: Julio | J37: Agosto | K37: Septiembre | L37: Octubre | M37: Noviembre | N37: Diciembre | O37: Total
B38: Compras 15% | C38: =C17/0.15 | D38: =D17/0.15 | E38: =E17/0.15 | F38: =F17/0.15 | G38: =G17/0.15 | H38: =H17/0.15 | I38: =I17/0.15 | J38: =J17/0.15 | ... N38: =N17/0.15 | O38: =SUM(C38:N38)
B39: Compras 5% | C39: =C18/0.05 | D39: =D18/0.05 | E39: =E18/0.05 | F39: =F18/0.05 | G39: =G18/0.05 | H39: =H18/0.05 | I39: =I18/0.05 | J39: =J18/0.05 | ... N39: =N18/0.05 | O39: =SUM(C39:N39)
B40: Según libros | C40: =+C38+C39 | D40: =+D38+D39 | E40: =+E38+E39 | F40: =+F38+F39 | G40: =+G38+G39 | H40: =+H38+H39 | I40: =+I38+I39 | J40: =+J38+J39 | ... O40: =+O38+O39
B42: Casillero 510 | O42: =SUM(C42:N42)
B43: Casillero 511 | E43: 0 | F43: 0 | H43: 0 | I43: 0 | J43: 0 | L43: 0 | O43: =SUM(C43:N43)
B44: Casillero 512 | O44: =SUM(C44:N44)
B45: Casillero 513 | C45: 0 | D45: 0 | E45: 0 | F45: 0 | G45: 0 | H45: 0 | I45: 0 | J45: 0 | K45: 0 | L45: 0 | M45: 0 | N45: 0 | O45: =SUM(C45:N45)
B46: Casillero 514 | C46: 0 | D46: 0 | E46: 0 | F46: 0 | G46: 0 | H46: 0 | I46: 0 | J46: 0 | K46: 0 | L46: 0 | M46: 0 | N46: 0 | O46: =SUM(C46:N46)
B47: Casillero 515 | C47: 0 | D47: 0 | E47: 0 | F47: 0 | G47: 0 | H47: 0 | I47: 0 | J47: 0 | K47: 0 | L47: 0 | M47: 0 | N47: 0 | O47: =SUM(C47:N47)
B48: Casillero 550 | C48: 0 | F48: 0 | H48: 0 | I48: 0 | J48: 0 | K48: 0 | L48: 0 | M48: 0 | O48: =SUM(C48:N48)
B49: Casillero 545 | C49: 0 | D49: 0 | E49: 0 | F49: 0 | G49: 0 | H49: 0 | I49: 0 | J49: 0 | K49: 0 | L49: 0 | M49: 0 | N49: 0 | O49: =SUM(C49:N49)
B50: Según declaraciones | C50: =SUM(C42:C49)-C44 | D50: =SUM(D42:D49)-D44 | E50: =SUM(E42:E49)-E44 | F50: =SUM(F42:F49)-F44 | G50: =SUM(G42:G49)-G44 | H50: =SUM(H42:H49)-H44 | I50: =SUM(I42:I49)-I44 | J50: =SUM(J42:J49)-J44 | ... N50: =SUM(N42:N49)-N44 | O50: =SUM(C50:N50)
B52: Diferencias | C52: =+C40-C50 | D52: =+D40-D50 | E52: =+E40-E50 | F52: =+F40-F50 | G52: =+G40-G50 | H52: =+H40-H50 | I52: =+I40-I50 | J52: =+J40-J50 | ... N52: =+N40-N50 | O52: =SUM(C52:N52)
A55: COMPRAS 0% | B55: Cuenta | C55: Enero | D55: Febrero | E55: Marzo | F55: Abril | G55: Mayo | H55: Junio | I55: Julio | J55: Agosto | K55: Septiembre | L55: Octubre | M55: Noviembre | N55: Diciembre | O55: Total
B56: Compras 0% | C56: 0 | D56: 0 | E56: 0 | F56: 0 | G56: 0 | H56: 0 | I56: 0 | J56: 0 | K56: 0 | L56: 0 | M56: 0 | N56: 0 | O56: =SUM(C56:N56)
B58: Total compras 0% | C58: =+C56 | D58: =+D56 | E58: =+E56 | F58: =+F56 | G58: =+G56 | H58: =+H56 | I58: =+I56 | J58: =+J56 | ... N58: =+N56 | O58: =SUM(C58:N58)
B60: Casillero 516 | C60: 0 | D60: 0 | E60: 0 | F60: 0 | G60: 0 | H60: 0 | I60: 0 | J60: 0 | K60: 0 | L60: 0 | M60: 0 | N60: 0 | O60: =SUM(C60:N60)
B61: Casillero 517 | O61: =SUM(C61:N61)
B62: Casillero 518 | O62: =SUM(C62:N62)
B63: Casillero 541 | C63: 0 | D63: 0 | E63: 0 | F63: 0 | G63: 0 | H63: 0 | I63: 0 | J63: 0 | K63: 0 | L63: 0 | M63: 0 | N63: 0 | O63: =SUM(C63:N63)
B64: Según declaraciones | C64: =+C60+C61+C62 | D64: =+D60+D61+D62 | E64: =+E60+E61+E62 | F64: =+F60+F61+F62 | G64: =+G60+G61+G62 | H64: =+H60+H61+H62 | I64: =+I60+I61+I62 | J64: =+J60+J61+J62 | ... N64: =+N60+N61+N62 | O64: =SUM(C64:N64)
B66: Diferencia | C66: =+C58-C64 | D66: =+D58-D64 | E66: =+E58-E64 | F66: =+F58-F64 | G66: =+G58-G64 | H66: =+H58-H64 | I66: =+I58-I64 | J66: =+J58-J64 | ... N66: =+N58-N64 | O66: =SUM(C66:N66)
B68: Casillero 519+555 | O68: =SUM(C68:N68)
B69: Total compras según libros | C69: =+C56+C40 | D69: =+D56+D40 | E69: =+E56+E40 | F69: =+F56+F40 | G69: =+G56+G40 | H69: =+H56+H40 | I69: =+I56+I40 | J69: =+J56+J40 | ... N69: =+N56+N40 | O69: =SUM(C69:N69)
B70: Diferencia | C70: =+C68-C69 | D70: =+D68-D69 | E70: =+E68-E69 | F70: =+F68-F69 | G70: =+G68-G69 | H70: =+H68-H69 | I70: =+I68-I69 | J70: =+J68-J69 | ... N70: =+N68-N69 | O70: =SUM(C70:N70)
B74: Marcas:
B75: Cotejado según libros
B76: Cotejado según formularios 104
B77: Diferencia determinada.
B78: Sumado, totalizado

Sheet DM5 Ventas 
A1: OBLIGACIONES FISCALES
A3: Ventas e IVA en ventas
A5: Nombre del cliente | D5: Periodo terminado
A6: =+'DM3 Revisión de saldos'!A5:C5 | D6: =+'DM3 Revisión de saldos'!D5:E5
A7: Preparado por: | C7: Fecha: | D7: Referencia
A8: =+'DM3 Revisión de saldos'!A7:B7 | C8: =+'DM4 Compras '!C8 | D8: DM5
A9: Revisado por: | C9: Fecha:
A10: =+'DM3 Revisión de saldos'!A9:B9
A13: VENTAS 12% | B13: Cuenta | C13: Enero | D13: Febrero | E13: Marzo | F13: Abril | G13: Mayo | H13: Junio | I13: Julio | J13: Agosto | K13: Septiembre | L13: Octubre | M13: Noviembre | N13: Diciembre | O13: Total
B15: Ventas según anexo | E15: =0-50 | O15: =SUM(C15:N15)
O16: =SUM(C16:N16)
B17: Descuentos según anexo | O17: =SUM(C17:N17)
O18: =SUM(C18:N18)
B19: Ventas según libros | C19: =+C15+C17 | D19: =+D15+D17 | E19: =+E15+E17 | F19: =+F15+F17 | G19: =+G15+G17 | H19: =+H15+H17 | I19: =+I15+I17 | J19: =+J15+J17 | ... N19: =+N15+N17 | O19: =+O15+O16-O17-O18
B21: Casillero 411 declaraciones 12% | O21: =SUM(C21:N21)
B22: Casillero 412 declaraciones 12% | D22: 0 | E22: 0 | G22: 0 | H22: 0 | I22: 0 | L22: 0 | M22: 0 | N22: 0 | O22: =SUM(C22:N22)
B23: Casillero 444 declaraciones 12% | C23: 0 | D23: 0 | E23: 0 | F23: 0 | G23: 0 | H23: 0 | I23: 0 | J23: 0 | K23: 0 | L23: 0 | M23: 0 | N23: 0 | O23: =SUM(C23:N23)
B24: Diferencia | C24: =+C19-C21-C22-C23 | D24: =+D19-D21-D22-D23 | E24: =+E19-E21-E22-E23 | F24: =+F19-F21-F22-F23 | G24: =+G19-G21-G22-G23 | H24: =+H19-H21-H22-H23 | I24: =+I19-I21-I22-I23 | J24: =+J19-J21-J22-J23 | K24: =+K19-K21-K22 | L24: =+L19-L21-L22 | M24: =+M19-M21-M22 | N24: =+N19-N21-N22 | O24: =O19-O21-O22-O23 | P24: ‡
A27: VENTAS 0% | B27: Cuenta | C27: Enero | D27: Febrero | E27: Marzo | F27: Abril | G27: Mayo | H27: Junio | I27: Julio | J27: Agosto | K27: Septiembre | L27: Octubre | M27: Noviembre | N27: Diciembre | O27: Total
O28: =SUM(C28:N28)
B29: Ventas 0% | C29: 0 | D29: 0 | E29: 0 | F29: 0 | G29: 0 | H29: 0 | I29: 0 | J29: 0 | K29: 0 | L29: 0 | M29: 0 | N29: 0 | O29: =SUM(C29:N29)
O30: =SUM(C30:N30)
B31: Ventas 0% Según libros | C31: =SUM(C28:C30) | D31: =SUM(D28:D30) | E31: =SUM(E28:E29) | F31: =SUM(F28:F29) | G31: =SUM(G28:G29) | H31: =SUM(H28:H29) | I31: =SUM(I28:I29) | J31: =SUM(J28:J29) | K31: =SUM(K28:K29) | L31: =SUM(L28:L29) | ... N31: =SUM(N28:N29) | O31: =+SUM(C31:N31)
B33: Casillero 412 Ventas de Activos Fijos | C33: 0 | D33: 0 | E33: 0 | F33: 0 | G33: 0 | H33: 0 | I33: 0 | J33: 0 | K33: 0 | L33: 0 | M33: 0 | N33: 0 | O33: =SUM(C33:N33)
B34: Casillero 413 declaraciones 0% no crédito tributario | C34: 0 | D34: 0 | E34: 0 | F34: 0 | G34: 0 | H34: 0 | I34: 0 | J34: 0 | K34: 0 | L34: 0 | M34: 0 | N34: 0 | O34: =SUM(C34:N34)
B35: Casillero 414 declaraciones 0% | C35: 0 | D35: 0 | E35: 0 | F35: 0 | G35: 0 | H35: 0 | I35: 0 | J35: 0 | K35: 0 | L35: 0 | M35: 0 | N35: 0 | O35: =SUM(C35:N35)
B36: Casillero 415 declaraciones 0% | C36: 0 | D36: 0 | E36: 0 | F36: 0 | G36: 0 | H36: 0 | I36: 0 | J36: 0 | K36: 0 | L36: 0 | M36: 0 | N36: 0 | O36: =SUM(C36:N36)
B37: Casillero 418 Exportaciones de servicios | C37: 0 | D37: 0 | E37: 0 | F37: 0 | G37: 0 | H37: 0 | I37: 0 | J37: 0 | K37: 0 | L37: 0 | M37: 0 | N37: 0 | O37: =SUM(C37:N37)
B38: Casillero 444 declaraciones 0% | C38: 0 | D38: 0 | E38: 0 | F38: 0 | G38: 0 | H38: 0 | I38: 0 | J38: 0 | K38: 0 | L38: 0 | M38: 0 | N38: 0 | O38: =SUM(C38:N38)
B39: Según declaración | C39: =SUM(C33:C38) | D39: =SUM(D33:D38) | E39: =SUM(E33:E38) | F39: =SUM(F33:F38) | G39: =SUM(G33:G38) | H39: =SUM(H33:H38) | I39: =SUM(I33:I38) | J39: =SUM(J33:J38) | ... N39: =SUM(N33:N38) | O39: =SUM(C39:N39) | P39: Σ
B41: Diferencia | C41: =+C31-C39 | D41: =+D31-D39 | E41: =+E31-E39 | F41: =+F31-F39 | G41: =+G31-G39 | H41: =+H31-H39 | I41: =+I31-I39 | J41: =+J31-J39 | ... N41: =+N31-N39 | O41: =SUM(C41:N41) | P41: ‡
B43: Total ventas declaradas | C43: =C21+C22+C39 | D43: =D21+D22+D39 | E43: =E21+E22+E39 | F43: =F21+F22+F39 | G43: =G21+G22+G39 | H43: =H21+H22+H39 | I43: =I21+I22+I39 | J43: =J21+J22+J39 | ... N43: =N21+N22+N39 | O43: =SUM(C43:N43) | S43: =+O43-R43 | T43: =+S43-O22
W44: =+W43-O43
A46: IVA EN VENTAS 12% | B46: Cuenta | C46: Enero | D46: Febrero | E46: Marzo | F46: Abril | G46: Mayo | H46: Junio | I46: Julio | J46: Agosto | K46: Septiembre | L46: Octubre | M46: Noviembre | N46: Diciembre | O46: Total
B47: IVA EN VENTAS | O47: =SUM(C47:N47)
B48: Según libros | C48: =+C47 | D48: =+D47 | E48: =+E47 | F48: =+F47 | G48: =+G47 | H48: =+H47 | I48: =+I47 | J48: =+J47 | ... O48: =+O47
B50: Casillero 421 | O50: =SUM(C50:N50)
B51: Casillero 422 | D51: 0 | E51: 0 | G51: 0 | H51: 0 | I51: 0 | L51: 0 | M51: 0 | N51: 0 | O51: =SUM(C51:N51)
B52: Casillero 423 | C52: 0 | D52: 0 | E52: 0 | F52: 0 | G52: 0 | H52: 0 | I52: 0 | J52: 0 | K52: 0 | L52: 0 | M52: 0 | N52: 0 | O52: =SUM(C52:N52)
B53: Casillero 454 | C53: 0 | D53: 0 | E53: 0 | F53: 0 | G53: 0 | H53: 0 | I53: 0 | J53: 0 | K53: 0 | L53: 0 | M53: 0 | N53: 0 | O53: =SUM(C53:N53)
B54: Según declaración | C54: =SUM(C50:C53) | D54: =SUM(D50:D53) | E54: =SUM(E50:E53) | F54: =SUM(F50:F53) | G54: =SUM(G50:G53) | H54: =SUM(H50:H53) | I54: =SUM(I50:I53) | J54: =SUM(J50:J53) | ... N54: =SUM(N50:N53) | O54: =SUM(C54:N54)
B56: Diferencia | C56: =+C48-C54 | D56: =+D48-D54 | E56: =+E48-E54 | F56: =+F48-F54 | G56: =+G48-G54 | H56: =+H48-H54 | I56: =+I48-I54 | J56: =+J48-J54 | ... O56: =+O48-O54
B59: Marcas:
A60: ü | B60: Cotejado según libros
A61: £ | B61: Cotejado según formularios 104
A62: ‡ | B62: Diferencia determinada.
A63: Σ | B63: Sumado, totalizado
B65: Notas:

Sheet DM6 IVA
A1: OBLIGACIONES FISCALES
A3: IVA
A4: Nombre del cliente | D4: Periodo terminado
A5: =+'DM3 Revisión de saldos'!A5:C5 | D5: =+'DM3 Revisión de saldos'!D5:E5
A6: Preparado por: | C6: Fecha: | D6: Referencia
A7: =+'DM3 Revisión de saldos'!A7:B7 | C7: =+'DM5 Ventas '!C8 | D7: DM6
A8: Revisado por: | C8: Fecha:
A9: =+'DM3 Revisión de saldos'!A9:B9
A12: IMPUESTO AL VALOR AGREGADO Y RETENCIONES EN LA FUENTE DE IVA
A14: Conciliación del Impuesto al Valor Agregado declarado vs. Libros
A16: Mes | B16: Según los libros contables del contribuyente | Y16: Según las declaraciones de IVA (j) | AB16: Diferencias (k)
B17: Ventas según Libros | G17: Liquidación del IVA en Ventas según Libros | N17: Adquisiciones, importaciones e IVA según Libros | S17: Liquidación del IVA según Libros | Y17: Ventas según declaraciones | Z17: Liquidación del IVA según declaraciones
B18: Ventas netas gravadas con tarifa diferente de 0% (a) | C18: Ventas netas gravadas con tarifa 0% (con derecho a crédito tributario) (b) | D18: Ventas netas gravadas con tarifa 0% (sin derecho a crédito tributario) (c) | E18: Exportaciones de bienes y servicios | F18: Ventas netas gravadas con tarifa diferente de 0% al contado | G18: Tarifa de IVA vigente (d) | H18: Impuesto generado en ventas | I18: IVA generado en la diferencia entre ventas y notas de crédito con distinta tarifa | J18: Impuesto a liquidar del mes anterior (e) | K18: Impuesto a liquidar en este mes (f) | L18: Impuesto a liquidar en el próximo mes (g) | M18: Total impuesto a liquidar en este mes | N18: Adquisiciones e importaciones netas gravadas con tarifa diferente de 0% (con derecho a crédito tributario) | O18: Impuesto causado en adquisiciones e importaciones (con derecho a crédito tributario) | P18: IVA generado en la diferencia entre adquisiciones y notas de crédito con distinta tarifa | Q18: Factor de proporcionalidad (h) | R18: Crédito tributario en compras | S18: Compensaciones de IVA (ventas en medio electrónico y ventas en zonas afectadas - Ley de Solidaridad) | T18: Saldo de crédito tributario del mes anterior (i) | U18: Retenciones en la fuente de IVA del periodo (casillero 609) | V18: Ajustes por IVA devuelto o descontado e IVA rechazado | W18: Saldo de crédito tributario para el próximo mes | X18: Total impuesto a pagar | Y18: Valor neto - total ventas y otras operaciones (casillero 419) | Z18: Total crédito tributario para el próximo mes (casilleros 615+617+618+619) | AA18: Total impuesto a pagar por percepción (casillero 699) | AB18: Diferencia en ventas y exportaciones | AC18: Diferencia en crédito tributario | AD18: Diferencia en impuesto | AI18: Valor de IVA no considerado como crédito tributario por factor de proporcionalidad Casillero 565
B19: {1} | C19: {2} | D19: {3} | E19: {4} | F19: {5} | G19: {6} | H19: {7}={1*6} | I19: {8} | J19: {9}={11} | K19: {10}={{5*6}+8} | L19: {11}=-{7+8}-10} | M19: {12}={9+10} | N19: {13} | O19: {14}={13*6} | P19: {15} | Q19: {16}={1+2+4} / {1+2+3+4} | R19: {17}={14+15}*16} | S19: {18} | T19: {19}={22} | U19: {20} | V19: {21} | W19: {22} | X19: {23} | Y19: {24} | Z19: {25} | AA19: {26} | AB19: {27}={24-1-2-3-4} | AC19: {28}={25-22} | AD19: {29}={26-23} | AF19: CASILLERO 609 | AI19: {29}={26-23}
A20: Enero | B20: =+'DM5 Ventas '!C19 | C20: 0 | D20: 0 | E20: 0 | F20: =+B20 | G20: 0.15 | H20: =+F20*G20 | I20: 0 | J20: 0 | K20: =+H20 | L20: =+(H20+I20)-K20 | M20: =+J20+K20 | N20: =+'DM4 Compras '!C42+'DM4 Compras '!C43 | O20: =+N20*G20 | P20: 0 | Q20: =IF(SUM(B20:E20)=0,0%,+(B20+C20+E20)/(B20+C20+D20+E20)) | R20: =+(O20+P20)*Q20 | S20: 0 | T20: 0 | V20: 0 | W20: =ABS(IF((M20-R20-S20-T20-U20+V20)<0,(M20-R20-S20-T20-U20+V20),0)) | X20: =+IF((M20-R20-S20-T20-U20+V20)>0,(M20-R20-S20-T20-U20+V20),0) | Y20: =+'DM5 Ventas '!C43 | Z20: 0 | AB20: =+Y20-B20-C20-D20-E20 | AC20: =Z20-W20 | AD20: =AA20-X20 | AF20: 0 | AG20: =+U20-AF20
A21: Febrero | B21: =+'DM5 Ventas '!D19 | C21: 0 | D21: 0 | E21: 0 | F21: =+B21 | G21: 0.15 | H21: =+F21*G21 | I21: 0 | J21: 0 | K21: =+H21 | L21: =+(H21+I21)-K21 | M21: =+J21+K21 | N21: =+'DM4 Compras '!D42+'DM4 Compras '!D43 | O21: =+N21*G21 | P21: 0 | Q21: =IF(SUM(B21:E21)=0,0%,+(B21+C21+E21)/(B21+C21+D21+E21)) | R21: =+(O21+P21)*Q21 | S21: 0 | T21: =+W20 | V21: 0 | W21: =ABS(IF((M21-R21-S21-T21-U21+V21)<0,(M21-R21-S21-T21-U21+V21),0)) | X21: =+IF((M21-R21-S21-T21-U21+V21)>0,(M21-R21-S21-T21-U21+V21),0) | Y21: =+'DM5 Ventas '!D43 | Z21: 0 | AB21: =+Y21-B21-C21-D21-E21 | AC21: =Z21-W21 | AD21: =AA21-X21 | AF21: 0 | AG21: =+U21-AF21
A22: Marzo | B22: =+'DM5 Ventas '!E19 | C22: 0 | D22: 0 | E22: 0 | F22: =+B22 | G22: 0.15 | H22: =+F22*G22 | I22: 0 | J22: 0 | K22: =+H22 | L22: =+(H22+I22)-K22 | M22: =+J22+K22 | N22: =+'DM4 Compras '!E42+'DM4 Compras '!E43 | O22: =+N22*G22 | P22: 0 | Q22: =IF(SUM(B22:E22)=0,0%,+(B22+C22+E22)/(B22+C22+D22+E22)) | R22: =+(O22+P22)*Q22 | S22: 0 | T22: =+W21 | V22: 0 | W22: =ABS(IF((M22-R22-S22-T22-U22+V22)<0,(M22-R22-S22-T22-U22+V22),0)) | X22: =+IF((M22-R22-S22-T22-U22+V22)>0,(M22-R22-S22-T22-U22+V22),0) | Y22: =+'DM5 Ventas '!E43 | Z22: =0+0 | AA22: 0 | AB22: =+Y22-B22-C22-D22-E22 | AC22: =Z22-W22 | AD22: =AA22-X22 | AF22: 0 | AG22: =+U22-AF22
A23: Abril | B23: =+'DM5 Ventas '!F19 | C23: 0 | D23: 0 | E23: 0 | F23: =+B23 | G23: 0.15 | H23: =+F23*G23 | I23: 0 | J23: 0 | K23: =+H23 | L23: =+(H23+I23)-K23 | M23: =+J23+K23 | N23: =+'DM4 Compras '!F42+'DM4 Compras '!F43 | O23: =+N23*G23 | P23: 0 | Q23: =IF(SUM(B23:E23)=0,0%,+(B23+C23+E23)/(B23+C23+D23+E23)) | R23: =+(O23+P23)*Q23 | S23: 0 | T23: =+W22 | V23: 0 | W23: =ABS(IF((M23-R23-S23-T23-U23+V23)<0,(M23-R23-S23-T23-U23+V23),0)) | X23: =+IF((M23-R23-S23-T23-U23+V23)>0,(M23-R23-S23-T23-U23+V23),0) | Y23: =+'DM5 Ventas '!F43 | Z23: 0 | AB23: =+Y23-B23-C23-D23-E23 | AC23: =Z23-W23 | AD23: =AA23-X23 | AF23: 0 | AG23: =+U23-AF23
A24: Mayo | B24: =+'DM5 Ventas '!G19 | C24: 0 | D24: 0 | E24: 0 | F24: =+B24 | G24: 0.15 | H24: =+F24*G24 | I24: 0 | J24: 0 | K24: =+H24 | L24: =+(H24+I24)-K24 | M24: =+J24+K24 | N24: =+'DM4 Compras '!G42+'DM4 Compras '!G43 | O24: =+N24*G24 | P24: 0 | Q24: =IF(SUM(B24:E24)=0,0%,+(B24+C24+E24)/(B24+C24+D24+E24)) | R24: =+(O24+P24)*Q24 | S24: 0 | T24: =+W23 | V24: 0 | W24: =ABS(IF((M24-R24-S24-T24-U24+V24)<0,(M24-R24-S24-T24-U24+V24),0)) | X24: =+IF((M24-R24-S24-T24-U24+V24)>0,(M24-R24-S24-T24-U24+V24),0) | Y24: =+'DM5 Ventas '!G43 | Z24: 0 | AB24: =+Y24-B24-C24-D24-E24 | AC24: =Z24-W24 | AD24: =AA24-X24 | AF24: 0 | AG24: =+U24-AF24
A25: Junio | B25: =+'DM5 Ventas '!H19 | C25: 0 | D25: 0 | E25: 0 | F25: =+B25 | G25: 0.15 | H25: =+F25*G25 | I25: 0 | J25: 0 | K25: =+H25 | L25: =+(H25+I25)-K25 | M25: =+J25+K25 | N25: =+'DM4 Compras '!H42+'DM4 Compras '!H43 | O25: =+N25*G25 | P25: 0 | Q25: =IF(SUM(B25:E25)=0,0%,+(B25+C25+E25)/(B25+C25+D25+E25)) | R25: =+(O25+P25)*Q25 | S25: 0 | T25: =+W24 | V25: 0 | W25: =ABS(IF((M25-R25-S25-T25-U25+V25)<0,(M25-R25-S25-T25-U25+V25),0)) | X25: =+IF((M25-R25-S25-T25-U25+V25)>0,(M25-R25-S25-T25-U25+V25),0) | Y25: =+'DM5 Ventas '!H43 | Z25: 0 | AB25: =+Y25-B25-C25-D25-E25 | AC25: =Z25-W25 | AD25: =AA25-X25 | AF25: 0 | AG25: =+U25-AF25
A26: Julio | B26: =+'DM5 Ventas '!I19 | C26: 0 | D26: 0 | E26: 0 | F26: =+B26 | G26: 0.15 | H26: =+F26*G26 | I26: 0 | J26: 0 | K26: =+H26 | L26: =+(H26+I26)-K26 | M26: =+J26+K26 | N26: =+'DM4 Compras '!I42+'DM4 Compras '!I43 | O26: =+N26*G26 | P26: 0 | Q26: =IF(SUM(B26:E26)=0,0%,+(B26+C26+E26)/(B26+C26+D26+E26)) | R26: =+(O26+P26)*Q26 | S26: 0 | T26: =+W25 | V26: 0 | W26: =ABS(IF((M26-R26-S26-T26-U26+V26)<0,(M26-R26-S26-T26-U26+V26),0)) | X26: =+IF((M26-R26-S26-T26-U26+V26)>0,(M26-R26-S26-T26-U26+V26),0) | Y26: =+'DM5 Ventas '!I43 | Z26: =0+0 | AA26: 0 | AB26: =+Y26-B26-C26-D26-E26 | AC26: =Z26-W26 | AD26: =AA26-X26 | AF26: 0 | AG26: =+U26-AF26
A27: Agosto | B27: =+'DM5 Ventas '!J19 | C27: 0 | D27: 0 | E27: 0 | F27: =+B27 | G27: 0.15 | H27: =+F27*G27 | I27: 0 | J27: 0 | K27: =+H27 | L27: =+(H27+I27)-K27 | M27: =+J27+K27 | N27: =+'DM4 Compras '!J42+'DM4 Compras '!J43 | O27: =+N27*G27 | P27: 0 | Q27: =IF(SUM(B27:E27)=0,0%,+(B27+C27+E27)/(B27+C27+D27+E27)) | R27: =+(O27+P27)*Q27 | S27: 0 | T27: =+W26 | V27: 0 | W27: =ABS(IF((M27-R27-S27-T27-U27+V27)<0,(M27-R27-S27-T27-U27+V27),0)) | X27: =+IF((M27-R27-S27-T27-U27+V27)>0,(M27-R27-S27-T27-U27+V27),0) | Y27: =+'DM5 Ventas '!J43 | Z27: =0+0 | AA27: 0 | AB27: =+Y27-B27-C27-D27-E27 | AC27: =Z27-W27 | AD27: =AA27-X27 | AF27: 0 | AG27: =+U27-AF27
A28: Septiembre | B28: =+'DM5 Ventas '!K19 | C28: 0 | D28: 0 | E28: 0 | F28: =+B28 | G28: 0.15 | H28: =+F28*G28 | I28: 0 | J28: 0 | K28: =+H28 | L28: =+(H28+I28)-K28 | M28: =+J28+K28 | N28: =+'DM4 Compras '!K42+'DM4 Compras '!K43 | O28: =+N28*G28 | P28: 0 | Q28: =IF(SUM(B28:E28)=0,0%,+(B28+C28+E28)/(B28+C28+D28+E28)) | R28: =+(O28+P28)*Q28 | S28: 0 | T28: =+W27 | V28: 0 | W28: =ABS(IF((M28-R28-S28-T28-U28+V28)<0,(M28-R28-S28-T28-U28+V28),0)) | X28: =+IF((M28-R28-S28-T28-U28+V28)>0,(M28-R28-S28-T28-U28+V28),0) | Y28: =+'DM5 Ventas '!K43 | Z28: 0 | AB28: =+Y28-B28-C28-D28-E28 | AC28: =Z28-W28 | AD28: =AA28-X28 | AF28: 0 | AG28: =+U28-AF28
A29: Octubre | B29: =+'DM5 Ventas '!L19 | C29: 0 | D29: 0 | E29: 0 | F29: =+B29 | G29: 0.15 | H29: =+F29*G29 | I29: 0 | J29: 0 | K29: =+H29 | L29: =+(H29+I29)-K29 | M29: =+J29+K29 | N29: =+'DM4 Compras '!L42+'DM4 Compras '!L43 | O29: =+N29*G29 | P29: 0 | Q29: =IF(SUM(B29:E29)=0,0%,+(B29+C29+E29)/(B29+C29+D29+E29)) | R29: =+(O29+P29)*Q29 | S29: 0 | T29: =+W28 | V29: 0 | W29: =ABS(IF((M29-R29-S29-T29-U29+V29)<0,(M29-R29-S29-T29-U29+V29),0)) | X29: =+IF((M29-R29-S29-T29-U29+V29)>0,(M29-R29-S29-T29-U29+V29),0) | Y29: =+'DM5 Ventas '!L43 | Z29: =0+0 | AA29: 0 | AB29: =+Y29-B29-C29-D29-E29 | AC29: =Z29-W29 | AD29: 0 | AF29: 0 | AG29: =+U29-AF29
A30: Noviembre | B30: =+'DM5 Ventas '!M19 | C30: 0 | D30: 0 | E30: 0 | F30: =+B30 | G30: 0.15 | H30: =+F30*G30 | I30: 0 | J30: =+L29 | K30: =+H30 | L30: =+(H30+I30)-K30 | M30: =+J30+K30 | N30: =+'DM4 Compras '!M42+'DM4 Compras '!M43 | O30: =+N30*G30 | P30: 0 | Q30: =IF(SUM(B30:E30)=0,0%,+(B30+C30+E30)/(B30+C30+D30+E30)) | R30: =+(O30+P30)*Q30 | S30: 0 | T30: =+W29 | V30: 0 | W30: =ABS(IF((M30-R30-S30-T30-U30+V30)<0,(M30-R30-S30-T30-U30+V30),0)) | X30: =+IF((M30-R30-S30-T30-U30+V30)>0,(M30-R30-S30-T30-U30+V30),0) | Y30: =+'DM5 Ventas '!M43 | Z30: =0+0 | AA30: 0 | AB30: =+Y30-B30-C30-D30-E30 | AC30: =Z30-W30 | AD30: =AA30-X30 | AF30: 0 | AG30: =+U30-AF30
A31: Diciembre | B31: =+'DM5 Ventas '!N19 | C31: 0 | D31: 0 | E31: 0 | F31: =+B31 | G31: 0.15 | H31: =+F31*G31 | I31: 0 | J31: 0 | K31: =+H31 | L31: =+(H31+I31)-K31 | M31: =+J31+K31 | N31: =+'DM4 Compras '!N42+'DM4 Compras '!N43 | O31: =+N31*G31 | P31: 0 | Q31: =IF(SUM(B31:E31)=0,0%,+(B31+C31+E31)/(B31+C31+D31+E31)) | R31: =+(O31+P31)*Q31 | S31: 0 | T31: =+W30 | V31: 0 | W31: =ABS(IF((M31-R31-S31-T31-U31+V31)<0,(M31-R31-S31-T31-U31+V31),0)) | X31: =+IF((M31-R31-S31-T31-U31+V31)>0,(M31-R31-S31-T31-U31+V31),0) | Y31: =+'DM5 Ventas '!N43 | AA31: 0 | AB31: =+Y31-B31-C31-D31-E31 | AC31: =Z31-W31 | AD31: =AA31-X31 | AF31: 0 | AG31: =+U31-AF31
A32: TOTAL | B32: =+SUM(B20:B31) | C32: =+SUM(C20:C31) | D32: =+SUM(D20:D31) | E32: =+SUM(E20:E31) | F32: =+SUM(F20:F31) | H32: =+SUM(H20:H31) | I32: =+SUM(I20:I31) | J32: =+SUM(J20:J31) | K32: =+SUM(K20:K31) | L32: =+SUM(L20:L31) | M32: =+SUM(M20:M31) | N32: =+SUM(N20:N31) | O32: =+SUM(O20:O31) | ... V32: =+SUM(V20:V31) | X32: =+SUM(X20:X31) | Y32: =+SUM(Y20:Y31) | Z32: =+SUM(Z20:Z31) | AA32: =+SUM(AA20:AA31) | AB32: =+SUM(AB20:AB31) | AC32: =+SUM(AC20:AC31) | AD32: =+SUM(AD20:AD31) | AF32: =+SUM(AF20:AF31) | AG32: =+U32-AF32 | AI32: =+SUM(AI20:AI31)

Sheet DM7 Retenciones x pagar
A1: OBLIGACIONES FISCALES
A3: Retenciones por pagar de IVA Y FUENTE
A4: Nombre del cliente | D4: Periodo terminado
A5: =+'DM3 Revisión de saldos'!A5:C5 | D5: =+'DM3 Revisión de saldos'!D5:E5
A6: Preparado por: | C6: Fecha: | D6: Referencia
A7: =+'DM3 Revisión de saldos'!A7:B7 | C7: =+'DM5 Ventas '!C8 | D7: DM7
A8: Revisado por: | C8: Fecha:
A9: =+'DM3 Revisión de saldos'!A9:B9
A12: ANEXO No. 20
A13: RETENCIONES EN LA FUENTE
A16: Conciliación de Retenciones en la Fuente del Impuesto al Valor Agregado declaradas vs. Libros
A18: Mes | B18: Valores según los libros contables del contribuyente | H18: Valores según las declaraciones de IVA del contribuyente (a) | O18: Diferencias (c)
B19: Retención del 10% | C19: Retención del 20% | D19: Retención del 30% | E19: Retención del 70% | F19: Retención del 100% | G19: Total retenciones de IVA | H19: Retención del 10% (casillero 721) | I19: Retención del 20% (casillero 723) | J19: Retención del 30% (casillero 725) | K19: Retención del 70% (casillero 729) | L19: Retención del 100% (casillero 731) | M19: Retención del 50% (casillero 727) | N19: Total IVA retenido (casillero 799) | O19: Diferencia en retención del 10% | P19: Diferencia en retención del 20% | Q19: Diferencia en retención del 30% | R19: Diferencia en retención del 70% | S19: Diferencia en retención del 100% | T19: Total diferencia en IVA retenido
B20: {1} | C20: {2} | D20: 725 | E20: 727 | F20: 729 | G20: {6}={1+2+3+4+5} | H20: {7} | I20: {8} | J20: {9} | K20: {10} | L20: {11} | M20: {12} | N20: {13} | O20: {13}={7-1} | P20: {14}={8-2} | Q20: {15}={9-3} | R20: {16}={10-4} | S20: {17}={11-5} | T20: {18}={12-6}
A21: Enero | G21: =SUM(B21:F21) | M21: 0 | N21: =SUM(H21:M21) | O21: =+B21-H21 | P21: =+C21-I21 | Q21: =+D21-J21 | R21: =+E21-K21 | S21: =+F21-L21 | T21: =+G21-N21
A22: Febrero | G22: =SUM(B22:F22) | M22: 0 | N22: =SUM(H22:M22) | O22: =+B22-H22 | P22: =+C22-I22 | Q22: =+D22-J22 | R22: =+E22-K22 | S22: =+F22-L22 | T22: =+G22-N22
A23: Marzo | G23: =SUM(B23:F23) | M23: 0 | N23: =SUM(H23:M23) | O23: =+B23-H23 | P23: =+C23-I23 | Q23: =+D23-J23 | R23: =+E23-K23 | S23: =+F23-L23 | T23: =+G23-N23
A24: Abril | G24: =SUM(B24:F24) | M24: 0 | N24: =SUM(H24:M24) | O24: =+B24-H24 | P24: =+C24-I24 | Q24: =+D24-J24 | R24: =+E24-K24 | S24: =+F24-L24 | T24: =+G24-N24
A25: Mayo | G25: =SUM(B25:F25) | M25: 0 | N25: =SUM(H25:M25) | O25: =+B25-H25 | P25: =+C25-I25 | Q25: =+D25-J25 | R25: =+E25-K25 | S25: =+F25-L25 | T25: =+G25-N25
A26: Junio | G26: =SUM(B26:F26) | M26: 0 | N26: =SUM(H26:M26) | O26: =+B26-H26 | P26: =+C26-I26 | Q26: =+D26-J26 | R26: =+E26-K26 | S26: =+F26-L26 | T26: =+G26-N26
A27: Julio | G27: =SUM(B27:F27) | M27: 0 | N27: =SUM(H27:M27) | O27: =+B27-H27 | P27: =+C27-I27 | Q27: =+D27-J27 | R27: =+E27-K27 | S27: =+F27-L27 | T27: =+G27-N27
A28: Agosto | G28: =SUM(B28:F28) | M28: 0 | N28: =SUM(H28:M28) | O28: =+B28-H28 | P28: =+C28-I28 | Q28: =+D28-J28 | R28: =+E28-K28 | S28: =+F28-L28 | T28: =+G28-N28
A29: Septiembre | G29: =SUM(B29:F29) | M29: 0 | N29: =SUM(H29:M29) | O29: =+B29-H29 | P29: =+C29-I29 | Q29: =+D29-J29 | R29: =+E29-K29 | S29: =+F29-L29 | T29: =+G29-N29
A30: Octubre | G30: =SUM(B30:F30) | M30: 0 | N30: =SUM(H30:M30) | O30: =+B30-H30 | P30: =+C30-I30 | Q30: =+D30-J30 | R30: =+E30-K30 | S30: =+F30-L30 | T30: =+G30-N30
A31: Noviembre | F31: 0 | G31: =SUM(B31:F31) | L31: 0 | M31: 0 | N31: =SUM(H31:M31) | O31: =+B31-H31 | P31: =+C31-I31 | Q31: =+D31-J31 | R31: =+E31-K31 | S31: =+F31-L31 | T31: =+G31-N31
A32: Diciembre | G32: =SUM(B32:F32) | M32: 0 | N32: =SUM(H32:M32) | O32: =+B32-H32 | P32: =+C32-I32 | Q32: =+D32-J32 | R32: =+E32-K32 | S32: =+F32-L32 | T32: =+G32-N32
A33: TOTAL | B33: =+SUM(B21:B32) | C33: =+SUM(C21:C32) | D33: =+SUM(D21:D32) | E33: =+SUM(E21:E32) | F33: =+SUM(F21:F32) | G33: =+SUM(G21:G32) | H33: =+SUM(H21:H32) | I33: =+SUM(I21:I32) | ... R33: =+SUM(R21:R32) | S33: =SUM(S21:S32) | T33: =+SUM(T21:T32)
B34: ü | C34: ü | D34: ü | E34: ü | F34: ü | G34: Σ | H34: £ | I34: £ | J34: £ | K34: £ | L34: £ | M34: £ | N34: Σ | O34: ‡ | P34: ‡ | Q34: ‡ | R34: ‡ | S34: ‡ | T34: Σ
A36: Conciliación de Retenciones en la Fuente del Impuesto a la Renta declaradas vs. Libros
A38: Descripción | J38: Valores según los libros contables del contribuyente
J39: Enero | K39: Febrero | L39: Marzo | M39: Abril | N39: Mayo | O39: Junio | P39: Julio | Q39: Agosto | R39: Septiembre | S39: Octubre | T39: Noviembre | U39: Diciembre | V39: Total
J40: {1} | K40: {2} | L40: {3} | M40: {4} | N40: {5} | O40: {6} | P40: {7} | Q40: {8} | R40: {9} | S40: {10} | T40: {11} | U40: {12} | V40: {12}
A41: 2.01.10.03.01 | B41: Retención Impuestos 1% | S41: 0 | V41: =SUM(J41:U41) | IZ41: =+J41*-1 | JA41: =+K41*-1 | JB41: =+L41*-1 | JC41: =+M41*-1 | JD41: =+N41*-1 | JE41: =+O41*-1 | JF41: =+P41*-1 | JG41: =+Q41*-1 | ... JK41: =+U41*-1
A42: 2.01.10.03.02 | B42: Retención Impuestos 2% | V42: =SUM(J42:U42) | IZ42: =+J42*-1 | JA42: =+K42*-1 | JB42: =+L42*-1 | JC42: =+M42*-1 | JD42: =+N42*-1 | JE42: =+O42*-1 | JF42: =+P42*-1 | JG42: =+Q42*-1 | ... JK42: =+U42*-1
A43: 2.01.10.03.03 | B43: Retención Impuestos 10% | V43: =SUM(J43:U43) | IZ43: =+J43*-1 | JA43: =+K43*-1 | JB43: =+L43*-1 | JC43: =+M43*-1 | JD43: =+N43*-1 | JE43: =+O43*-1 | JF43: =+P43*-1 | JG43: =+Q43*-1 | ... JK43: =+U43*-1
A44: 2.01.10.03.04 | B44: Retencion Impuestos 1.75% | V44: =SUM(J44:U44) | IZ44: =+J44*-1 | JA44: =+K44*-1 | JB44: =+L44*-1 | JC44: =+M44*-1 | JD44: =+N44*-1 | JE44: =+O44*-1 | JF44: =+P44*-1 | JG44: =+Q44*-1 | ... JK44: =+U44*-1
A45: 2.01.10.03.05 | B45: Retencion Impuestos 2.75% | V45: =SUM(J45:U45) | IZ45: =+J45*-1 | JA45: =+K45*-1 | JB45: =+L45*-1 | JC45: =+M45*-1 | JD45: =+N45*-1 | JE45: =+O45*-1 | JF45: =+P45*-1 | JG45: =+Q45*-1 | ... JK45: =+U45*-1
A46: 2.01.10.03.07 | B46: Retencion impuestos 1% Rimpe | V46: =SUM(J46:U46) | IZ46: =+J46*-1 | JA46: =+K46*-1 | JB46: =+L46*-1 | JC46: =+M46*-1 | JD46: =+N46*-1 | JE46: =+O46*-1 | JF46: =+P46*-1 | JG46: =+Q46*-1 | ... JK46: =+U46*-1
A47: 2.01.10.03.08 | B47: Retencion Impuestos 3% | J47: 0 | O47: 0 | R47: 0 | T47: 0 | U47: 0 | V47: =SUM(J47:U47) | IZ47: =+J47*-1 | JA47: =+K47*-1 | JB47: =+L47*-1 | JC47: =+M47*-1 | JD47: =+N47*-1 | JE47: =+O47*-1 | JF47: =+P47*-1 | JG47: =+Q47*-1 | ... JK47: =+U47*-1
R48: 0 | S48: 0 | T48: 0 | U48: 0 | V48: =SUM(J48:U48)
R49: 0 | S49: 0 | T49: 0 | U49: 0 | V49: =SUM(J49:U49)
R50: 0 | S50: 0 | T50: 0 | U50: 0 | V50: =SUM(J50:U50)
R51: 0 | S51: 0 | T51: 0 | U51: 0 | V51: =SUM(J51:U51)
R52: 0 | S52: 0 | T52: 0 | U52: 0 | V52: =SUM(J52:U52)
R53: 0 | S53: 0 | T53: 0 | U53: 0 | V53: =SUM(J53:U53)
B54: Retenciones en Relacion de Dependen | J54: 0 | K54: 0 | L54: 0 | M54: 0 | N54: 0 | O54: 0 | P54: 0 | Q54: 0 | R54: 0 | S54: 0 | T54: 0 | V54: =SUM(J54:U54)
A55: Total de retenciones de impuesto a la renta según libros | J55: =+SUM(J41:J54) | K55: =+SUM(K41:K54) | L55: =+SUM(L41:L54) | M55: =+SUM(M41:M54) | N55: =+SUM(N41:N54) | O55: =+SUM(O41:O54) | P55: =+SUM(P41:P54) | Q55: =+SUM(Q41:Q54) | ... V55: =+SUM(V41:V54) | W55: ü
A56: Total de retenciones de impuesto a la renta según declaraciones (casillero No. 499de103) (b) | V56: =SUM(J56:U56) | W56: £
A57: Diferencias (c) | J57: =+J56-J55 | K57: =+K56-K55 | L57: =+L56-L55 | M57: =+M56-M55 | N57: =+N56-N55 | O57: =+O56-O55 | P57: =+P56-P55 | Q57: =+Q56-Q55 | ... V57: =+V56-V55 | W57: ‡
B62: Marcas:
A63: ü | B63: Cotejado según libros
A64: £ | B64: Cotejado según formularios 104 y 103
A65: ‡ | B65: Diferencia determinada.
A66: Σ | B66: Sumado, totalizado
B68: Notas:
A69: (i) | B69: Diferencia en declaración de relacion de dependencia.
A75: Elaborado por:
A76: Revisado por:
A77: Fecha:

Sheet DM8 ATS
A1: Ventas | B1: Enero | C1: Febrero | D1: Marzo | E1: Abril | F1: Mayo | G1: Junio | H1: Julio | I1: Agosto | J1: Septiembre | K1: Octubre | L1: Noviembre | M1: Diciembre | N1: Total
A2: Casillero 419 (F 104) | B2: =+'DM5 Ventas '!C43 | C2: =+'DM5 Ventas '!D43 | D2: =+'DM5 Ventas '!E43 | E2: =+'DM5 Ventas '!F43 | F2: =+'DM5 Ventas '!G43 | G2: =+'DM5 Ventas '!H43 | I2: =+'DM5 Ventas '!J43 | J2: =+'DM5 Ventas '!K43 | K2: =+'DM5 Ventas '!L43 | L2: =+'DM5 Ventas '!M43 | M2: =+'DM5 Ventas '!N43 | N2: =+SUM(B2:M2) | O2: Σ
A3: Según ATS | B3: 0 | C3: 0 | D3: 0 | E3: 0 | F3: 0 | G3: 0 | H3: 0 | I3: 0 | J3: 0 | K3: 0 | L3: 0 | M3: 0 | N3: =+SUM(B3:M3) | O3: Σ
A4: Rembolso | B4: 0 | C4: 0 | D4: 0 | E4: 0 | F4: 0 | G4: 0 | H4: 0 | I4: 0 | J4: 0 | K4: 0 | L4: 0 | M4: 0 | N4: =+SUM(B4:M4)
B5: =+B2-B3 | C5: =+C2-C3+C4 | D5: =+D2-D3 | E5: =+E2-E3 | F5: =+F2-F3 | G5: =+G2-G3 | H5: =+H2-H3 | I5: =+I2-I3 | J5: =+J2-J3 | K5: =+K2-K3 | ... M5: =+M2-M3 | N5: =+SUM(B5:M5) | O5: ‡
A7: Casillero 429 (F 104) | B7: =HLOOKUP($B$1:$M$1,'DM5 Ventas '!$C$46:$N$54,9,0) | C7: =HLOOKUP($B$1:$M$1,'DM5 Ventas '!$C$46:$N$54,9,0) | D7: =HLOOKUP($B$1:$M$1,'DM5 Ventas '!$C$46:$N$54,9,0) | E7: =HLOOKUP($B$1:$M$1,'DM5 Ventas '!$C$46:$N$54,9,0) | F7: =HLOOKUP($B$1:$M$1,'DM5 Ventas '!$C$46:$N$54,9,0) | G7: =HLOOKUP($B$1:$M$1,'DM5 Ventas '!$C$46:$N$54,9,0) | I7: =HLOOKUP($B$1:$M$1,'DM5 Ventas '!$C$46:$N$54,9,0) | J7: =HLOOKUP($B$1:$M$1,'DM5 Ventas '!$C$46:$N$54,9,0) | K7: =HLOOKUP($B$1:$M$1,'DM5 Ventas '!$C$46:$N$54,9,0) | L7: =HLOOKUP($B$1:$M$1,'DM5 Ventas '!$C$46:$N$54,9,0) | M7: =HLOOKUP($B$1:$M$1,'DM5 Ventas '!$C$46:$N$54,9,0) | N7: =+SUM(B7:M7) | O7: Σ
A8: Según ATS | B8: 0 | C8: 0 | D8: 0 | E8: 0 | F8: 0 | G8: 0 | H8: 0 | I8: 0 | J8: 0 | L8: 0 | M8: 0 | N8: =+SUM(B8:M8) | O8: Σ
A9: Rembolso | B9: 0 | C9: 0 | D9: 0 | E9: 0 | F9: 0 | G9: 0 | H9: 0 | I9: 0 | J9: 0 | K9: 0 | L9: 0 | M9: 0 | N9: =+SUM(B9:M9) | O9: Σ
A10: Diferencia iva ventas | B10: =+B7-B8 | C10: =+C7-C8+C9 | D10: =+D7-D8 | E10: =+E7-E8 | F10: =+F7-F8 | G10: =+G7-G8 | H10: =+H7-H8 | I10: =+I7-I8 | J10: =+J7-J8 | K10: =+K7-K8 | ... M10: =+M7-M8 | N10: =+SUM(B10:M10) | O10: ‡
A12: OBLIGACIONES FISCALES
A14: ATS VS FORMULARIOS 103 Y 104
A15: Nombre del cliente | D15: Periodo terminado
A16: =+'DM7 Retenciones x pagar'!A5:C5 | D16: =+'DM7 Retenciones x pagar'!D5:E5
A17: Preparado por: | C17: Fecha: | D17: Referencia
A18: =+'DM7 Retenciones x pagar'!A7:B7 | C18: =+'DM7 Retenciones x pagar'!C7 | D18: DM8
A19: Revisado por: | C19: Fecha:
A20: =+'DM7 Retenciones x pagar'!A9:B9 | C20: XXXX
A24: Compras | B24: Enero | C24: Febrero | D24: Marzo | E24: Abril | F24: Mayo | G24: Junio | H24: Julio | I24: Agosto | J24: Septiembre | K24: Octubre | L24: Noviembre | M24: Diciembre | N24: Total
A25: Casillero 519 (F 104) | B25: =+'DM4 Compras '!C50+'DM4 Compras '!C64 | C25: =+'DM4 Compras '!D50+'DM4 Compras '!D64 | D25: =+'DM4 Compras '!E50+'DM4 Compras '!E64 | E25: =+'DM4 Compras '!F50+'DM4 Compras '!F64 | F25: =+'DM4 Compras '!G50+'DM4 Compras '!G64 | G25: =+'DM4 Compras '!H50+'DM4 Compras '!H64 | H25: =+'DM4 Compras '!I50+'DM4 Compras '!I64 | I25: =+'DM4 Compras '!J50+'DM4 Compras '!J64 | ... M25: =+'DM4 Compras '!N50+'DM4 Compras '!N64 | N25: =+SUM(B25:M25) | O25: Σ
A26: Según ATS (Compras) 0 y 12 | B26: =0+0 | C26: =0+0 | D26: =0+0 | E26: =0+0 | F26: =0+0 | G26: =0+0 | H26: =0+0 | I26: =0+0 | ... M26: =0+0 | N26: =+SUM(B26:M26) | O26: Σ
A27: Importaciones | B27: =+'DM4 Compras '!C46 | C27: =+'DM4 Compras '!D46 | D27: =+'DM4 Compras '!E46 | E27: =+'DM4 Compras '!F46 | F27: =+'DM4 Compras '!G46 | G27: =+'DM4 Compras '!H46 | H27: =+'DM4 Compras '!I46 | I27: =+'DM4 Compras '!J46 | ... M27: =+'DM4 Compras '!N46 | N27: =+SUM(B27:M27) | O27: Σ
A28: =+'DM4 Compras '!B44 | B28: =+'DM4 Compras '!C44 | C28: =+'DM4 Compras '!D44 | D28: =+'DM4 Compras '!E44 | E28: =+'DM4 Compras '!F44 | F28: =+'DM4 Compras '!G44 | G28: =+'DM4 Compras '!H44 | H28: =+'DM4 Compras '!I44 | ... M28: =+'DM4 Compras '!N44 | N28: =+SUM(B28:M28) | O28: Σ
A29: Diferencia compras | B29: =+B25-B26-B27+B28 | C29: =+C25-C26-C27+C28 | D29: =+D25-D26-D27+D28 | E29: =+E25-E26-E27+E28 | F29: =+F25-F26-F27+F28 | G29: =+G25-G26-G27+G28 | H29: =+H25-H26-H27+H28 | I29: =+I25-I26-I27+I28 | ... M29: =+M25-M26-M27+M28 | N29: =+SUM(B29:M29) | O29: ‡
A31: Casillero 529 (F 104) | B31: =+'DM4 Compras '!C31 | C31: =+'DM4 Compras '!D31 | D31: =+'DM4 Compras '!E31 | E31: =+'DM4 Compras '!F31 | F31: =+'DM4 Compras '!G31 | G31: =+'DM4 Compras '!H31 | H31: =+'DM4 Compras '!I31 | I31: =+'DM4 Compras '!J31 | ... M31: =+'DM4 Compras '!N31 | N31: =+SUM(B31:M31) | O31: Σ
A32: Según ATS (Compras) IVA compras | N32: =+SUM(B32:M32) | O32: Σ
A33: Importaciones | B33: =+'DM4 Compras '!C26 | C33: =+'DM4 Compras '!D26 | D33: =+'DM4 Compras '!E26 | E33: =+'DM4 Compras '!F26 | F33: =+'DM4 Compras '!G26 | G33: =+'DM4 Compras '!H26 | H33: =+'DM4 Compras '!I26 | I33: =+'DM4 Compras '!J26 | ... M33: =+'DM4 Compras '!N26 | N33: =+SUM(B33:M33) | O33: Σ
A34: =+'DM4 Compras '!B24 | B34: =+'DM4 Compras '!C24 | C34: =+'DM4 Compras '!D24 | D34: =+'DM4 Compras '!E24 | E34: =+'DM4 Compras '!F24 | F34: =+'DM4 Compras '!G24 | G34: =+'DM4 Compras '!H24 | H34: =+'DM4 Compras '!I24 | ... M34: =+'DM4 Compras '!N24 | N34: =+SUM(B34:M34) | O34: Σ
A35: Diferencia IVA compras | B35: =+B31-B32-B33+B34 | C35: =+C31-C32-C33+C34 | D35: =+D31-D32-D33+D34 | E35: =+E31-E32-E33+E34 | F35: =+F31-F32-F33+F34 | G35: =+G31-G32-G33+G34 | H35: =+H31-H32-H33+H34 | I35: =+I31-I32-I33+I34 | ... M35: =+M31-M32-M33+M34 | N35: =+SUM(B35:M35) | O35: ‡
A38: Retenciones en la fuente del impuesto a la renta | B38: Enero | C38: Febrero | D38: Marzo | E38: Abril | F38: Mayo | G38: Junio | H38: Julio | I38: Agosto | J38: Septiembre | K38: Octubre | L38: Noviembre | M38: Diciembre | N38: Total
A39: Casillero (349-302+429+421) (F 103) | B39: =0-0 | C39: =0-0 | D39: =0-0 | E39: =0-0 | F39: =0-0 | G39: =0-0 | H39: =0-0 | I39: =0-0 | ... M39: =0-0 | N39: =+SUM(B39:M39) | O39: Σ
A40: Base Ret. Fte. IR. ATS (Retenciones - Agente de Retención) | N40: =+SUM(B40:M40) | O40: Σ
A41: Notas de crèdito | B41: 0 | C41: 0 | D41: 0 | E41: 0 | F41: 0 | G41: 0 | H41: 0 | I41: 0 | J41: 0 | K41: 0 | L41: 0 | M41: 0 | N41: =+SUM(B41:M41) | O41: Σ
A42: Diferencia bases | B42: =+B39-B40-B41 | C42: =+C39-C40-C41 | D42: =+D39-D40-D41 | E42: =+E39-E40-E41 | F42: =+F39-F40-F41 | G42: =+G39-G40-G41 | H42: =+H39-H40-H41 | I42: =+I39-I40-I41 | ... L42: =+L39-L40-L41 | M42: =+M39-M40-M41+M43 | N42: =+SUM(B42:M42) | O42: ‡
N43: R
A45: Casillero (399-352+498) (F 103) | M45: =0-0 | N45: =+SUM(B45:M45) | O45: Σ
A46: Valor retenido ATS IMP Renta | N46: =+SUM(B46:M46) | O46: Σ
A47: Diferencia valor retenido | B47: =+B45-B46 | C47: =+C45-C46 | D47: =+D45-D46 | E47: =+E45-E46 | F47: =+F45-F46 | G47: =+G45-G46 | H47: =+H45-H46 | I47: =+I45-I46 | ... L47: =+L45-L46 | M47: =+M45-M46+M48 | N47: =+SUM(B47:M47) | O47: ‡
A50: Retenciones de iva | B50: Enero | C50: Febrero | D50: Marzo | E50: Abril | F50: Mayo | G50: Junio | H50: Julio | I50: Agosto | J50: Septiembre | K50: Octubre | L50: Noviembre | M50: Diciembre | N50: Total
A51: Retenciones del 30% (F 104) | B51: =+'DM7 Retenciones x pagar'!J21 | C51: =+'DM7 Retenciones x pagar'!J22 | D51: =+'DM7 Retenciones x pagar'!J23 | E51: =+'DM7 Retenciones x pagar'!J24 | F51: =+'DM7 Retenciones x pagar'!J25 | G51: =+'DM7 Retenciones x pagar'!J26 | H51: =+'DM7 Retenciones x pagar'!J27 | I51: =+'DM7 Retenciones x pagar'!J28 | J51: =+'DM7 Retenciones x pagar'!J29 | K51: =+'DM7 Retenciones x pagar'!J30 | L51: =+'DM7 Retenciones x pagar'!J31 | M51: =+'DM7 Retenciones x pagar'!J32 | N51: =+SUM(B51:M51) | O51: Σ
A52: Retenciones del 70% (F 104) | B52: =+'DM7 Retenciones x pagar'!K21 | C52: =+'DM7 Retenciones x pagar'!K22 | D52: =+'DM7 Retenciones x pagar'!K23 | E52: =+'DM7 Retenciones x pagar'!K24 | F52: =+'DM7 Retenciones x pagar'!K25 | G52: =+'DM7 Retenciones x pagar'!K26 | H52: =+'DM7 Retenciones x pagar'!K27 | I52: =+'DM7 Retenciones x pagar'!K28 | J52: =+'DM7 Retenciones x pagar'!K29 | K52: =+'DM7 Retenciones x pagar'!K30 | L52: =+'DM7 Retenciones x pagar'!K31 | M52: =+'DM7 Retenciones x pagar'!K32 | N52: =+SUM(B52:M52) | O52: Σ
A53: Retenciones del 100% (F 104) | B53: =+'DM7 Retenciones x pagar'!L21 | C53: =+'DM7 Retenciones x pagar'!L22 | D53: =+'DM7 Retenciones x pagar'!L23 | E53: =+'DM7 Retenciones x pagar'!L24 | F53: =+'DM7 Retenciones x pagar'!L25 | G53: =+'DM7 Retenciones x pagar'!L26 | H53: =+'DM7 Retenciones x pagar'!L27 | I53: =+'DM7 Retenciones x pagar'!L28 | J53: =+'DM7 Retenciones x pagar'!L29 | K53: =+'DM7 Retenciones x pagar'!L30 | L53: =+'DM7 Retenciones x pagar'!L31 | M53: =+'DM7 Retenciones x pagar'!L32 | N53: =+SUM(B53:M53) | O53: Σ
A54: Retenciones del 10% (F 104) | B54: =+'DM7 Retenciones x pagar'!H21 | C54: =+'DM7 Retenciones x pagar'!H22 | D54: =+'DM7 Retenciones x pagar'!H23 | E54: =+'DM7 Retenciones x pagar'!H24 | F54: =+'DM7 Retenciones x pagar'!H25 | G54: =+'DM7 Retenciones x pagar'!H26 | H54: =+'DM7 Retenciones x pagar'!H27 | I54: =+'DM7 Retenciones x pagar'!H28 | J54: =+'DM7 Retenciones x pagar'!H29 | K54: =+'DM7 Retenciones x pagar'!H30 | L54: =+'DM7 Retenciones x pagar'!H31 | M54: =+'DM7 Retenciones x pagar'!H32 | N54: =+SUM(B54:M54) | O54: Σ
A55: Retenciones del 20% (F 104) | B55: =+'DM7 Retenciones x pagar'!I21 | C55: =+'DM7 Retenciones x pagar'!I22 | D55: =+'DM7 Retenciones x pagar'!I23 | E55: =+'DM7 Retenciones x pagar'!I24 | F55: =+'DM7 Retenciones x pagar'!I25 | G55: =+'DM7 Retenciones x pagar'!I26 | H55: =+'DM7 Retenciones x pagar'!I27 | I55: =+'DM7 Retenciones x pagar'!I28 | J55: =+'DM7 Retenciones x pagar'!I29 | K55: =+'DM7 Retenciones x pagar'!I30 | L55: =+'DM7 Retenciones x pagar'!I31 | M55: =+'DM7 Retenciones x pagar'!I32 | N55: =+SUM(B55:M55) | O55: Σ
A56: Según formulario 104 | B56: =SUM(B51:B55) | C56: =SUM(C51:C55) | D56: =SUM(D51:D55) | E56: =SUM(E51:E55) | F56: =SUM(F51:F55) | G56: =SUM(G51:G55) | H56: =SUM(H51:H55) | I56: =SUM(I51:I55) | ... N56: =SUM(N51:N55)
A58: Retenciones del 30% ATS | N58: =+SUM(B58:M58) | O58: Σ
A59: Retenciones del 70% ATS | N59: =+SUM(B59:M59) | O59: Σ
A60: Retenciones del 100% ATS | L60: 0 | N60: =+SUM(B60:M60) | O60: Σ
A61: Retenciones del 10% ATS | N61: =+SUM(B61:M61) | O61: Σ
A62: Retenciones del 20% ATS | N62: =+SUM(B62:M62) | O62: Σ
A63: Según ATS | B63: =SUM(B58:B62) | C63: =SUM(C58:C62) | D63: =SUM(D58:D62) | E63: =SUM(E58:E62) | F63: =SUM(F58:F62) | G63: =SUM(G58:G62) | H63: =SUM(H58:H62) | I63: =SUM(I58:I62) | ... N63: =SUM(N58:N62)
A65: Retenciones del 30% | B65: =+B51-B58 | C65: =+C51-C58 | D65: =+D51-D58 | E65: =+E51-E58 | F65: =+F51-F58 | G65: =+G51-G58 | H65: =+H51-H58 | I65: =+I51-I58 | ... M65: =+M51-M58 | N65: =+SUM(B65:M65) | O65: Σ
A66: Retenciones del 70% | B66: =+B52-B59 | C66: =+C52-C59 | D66: =+D52-D59 | E66: =+E52-E59 | F66: =+F52-F59 | G66: =+G52-G59 | H66: =+H52-H59 | I66: =+I52-I59 | ... M66: =+M52-M59 | N66: =+SUM(B66:M66) | O66: Σ
A67: Reteciones del 100% | B67: =+B53-B60 | C67: =+C53-C60 | D67: =+D53-D60 | E67: =+E53-E60 | F67: =+F53-F60 | G67: =+G53-G60 | H67: =+H53-H60 | I67: =+I53-I60 | ... M67: =+M53-M60 | N67: =+SUM(B67:M67) | O67: Σ
A68: Reteciones del 10% | B68: =+B54-B61 | C68: =+C54-C61 | D68: =+D54-D61 | E68: =+E54-E61 | F68: =+F54-F61 | G68: =+G54-G61 | H68: =+H54-H61 | I68: =+I54-I61 | ... M68: =+M54-M61 | N68: =+SUM(B68:M68) | O68: Σ
A69: Reteciones del 20% | B69: =+B55-B62 | C69: =+C55-C62 | D69: =+D55-D62 | E69: =+E55-E62 | F69: =+F55-F62 | G69: =+G55-G62 | H69: =+H55-H62 | I69: =+I55-I62 | ... M69: =+M55-M62 | N69: =+SUM(B69:M69) | O69: Σ
A70: Diferencia | B70: =SUM(B65:B69) | C70: =SUM(C65:C69) | D70: =SUM(D65:D69) | E70: =SUM(E65:E69) | F70: =SUM(F65:F69) | G70: =SUM(G65:G69) | H70: =SUM(H65:H69) | I70: =SUM(I65:I69) | ... N70: =SUM(N65:N69) | O70: ‡
A72: IVA RETENIDO X VENTAS según libros | B72: =+'DM6 IVA'!U20 | C72: =+'DM6 IVA'!U21 | D72: =+'DM6 IVA'!U22 | E72: =+'DM6 IVA'!U23 | F72: =+'DM6 IVA'!U24 | G72: =+'DM6 IVA'!U25 | H72: =+'DM6 IVA'!U26 | I72: =+'DM6 IVA'!U27 | J72: =+'DM6 IVA'!U28 | K72: =+'DM6 IVA'!U29 | L72: =+'DM6 IVA'!U30 | M72: =+'DM6 IVA'!U31 | N72: =+SUM(B72:M72)
A73: Ret. Iva. Recibidas según formulario 104 (casillero 609) | B73: 0 | D73: 0 | G73: 0 | H73: 0 | I73: 0 | J73: 0 | K73: 0 | L73: 0 | M73: 0 | N73: =+SUM(B73:M73) | O73: Σ
A74: Diferencia | B74: =B72-B73 | C74: =C72-C73 | D74: =D72-D73 | E74: =E72-E73 | F74: =F72-F73 | G74: =G72-G73 | H74: =H72-H73 | I74: =I72-I73 | ... M74: =M72-M73 | N74: =+SUM(B74:M74) | O74: ‡
A76: Ret. IVA Recibidas según formularios | B76: =+'DM6 IVA'!AE20 | C76: =+'DM6 IVA'!AE21 | D76: =+'DM6 IVA'!AE22 | E76: =+'DM6 IVA'!AE23 | F76: =+'DM6 IVA'!AE24 | G76: =+'DM6 IVA'!AE25 | H76: =+'DM6 IVA'!AE26 | I76: =+'DM6 IVA'!AE27 | J76: ='DM6 IVA'!AE28 | K76: ='DM6 IVA'!U29 | L76: ='DM6 IVA'!U30 | M76: ='DM6 IVA'!U31 | N76: =+SUM(B76:M76)
A77: Ret. Iva. Recibidas según ATS | B77: 0 | C77: 0 | D77: 0 | E77: 0 | F77: 0 | G77: 0 | H77: 0 | I77: 0 | J77: 0 | K77: ='DM6 IVA'!U33 | L77: ='DM6 IVA'!U34 | M77: 0 | N77: =+SUM(B77:M77) | O77: Σ
A78: Diferencia | B78: =B76-B77 | C78: =C76-C77 | D78: =D76-D77 | E78: =E76-E77 | F78: =F76-F77 | G78: =G76-G77 | H78: =H76-H77 | I78: =I76-I77 | ... M78: =M76-M77 | N78: =+SUM(B78:M78) | O78: ‡
A80: Retenciones fuentes recibidas según libros | F80: 0 | J80: 0 | K80: 0 | L80: 0 | M80: 0 | N80: =+SUM(B80:M80) | O80: Σ
A81: Valor de Renta que han retenido ATS | B81: 0 | C81: 0 | D81: 0 | E81: 0 | F81: 0 | G81: 0 | H81: 0 | I81: 0 | J81: 0 | K81: 0 | L81: 0 | M81: 0 | N81: =+SUM(B81:M81) | O81: Σ
A82: Diferencia | B82: =B80-B81 | C82: =C80-C81 | D82: =D80-D81 | E82: =E80-E81 | F82: =F80-F81 | G82: =G80-G81 | H82: =H80-H81 | I82: =I80-I81 | ... M82: =M80-M81 | N82: =+N80-N81 | O82: ‡
B86: Diferencia en las Bases Imponibles del formualrio 103 y formulario 104
C88: Según
B89: Mes | C89: Formulario 104 | D89: Importaciones 15% | E89: Formulario 103 | F89: Diferencia
B90: Enero | D90: 0 | E90: =+B39 | F90: =+C90-D90-E90
B91: Febrero | D91: 0 | E91: =+C39 | F91: =+C91-D91-E91
B92: Marzo | D92: 0 | E92: =+D39 | F92: =+C92-D92-E92
B93: Abril | D93: 0 | E93: =+E39 | F93: =+C93-D93-E93
B94: Mayo | D94: 0 | E94: =+F39 | F94: =+C94-D94-E94
B95: Junio | D95: 0 | E95: =+G39 | F95: =+C95-D95-E95
B96: Julio | D96: 0 | E96: =+H39 | F96: =+C96-D96-E96
B97: Agosto | D97: 0 | E97: =+I39 | F97: =+C97-D97-E97
B98: Septiembre | D98: 0 | E98: =+J39 | F98: =+C98-D98-E98
B99: Octubre | D99: 0 | E99: =+K39 | F99: =+C99-D99-E99
B100: Noviembre | D100: 0 | E100: =+L39 | F100: =+C100-D100-E100
B101: Diciembre | D101: 0 | E101: =+M39 | F101: =+C101-D101-E101-H101
B102: Total | C102: =SUM(C90:C101) | D102: =SUM(D90:D101) | E102: =SUM(E90:E101) | F102: =SUM(F90:F101)
C103: Σ | E103: Σ
B108: Marcas:
A110: ü | B110: Cotejado según declaracion
A111: £ | B111: Cotejado según ATS
A112: ‡ | B112: Sumado, totalizado
A113: Σ | B113: Diferencia determinada.

Sheet DM9 Límite costos y gastos
A1: OBLIGACIONES FISCALES
A3: REVISIÓN GENERAL DE LÍMITES DE COSTOS Y GASTOS
A4: Nombre del cliente | D4: Periodo terminado
A6: Preparado por: | C6: Fecha: | D6: Referencia
D7: DM9
A8: Revisado por: | C8: Fecha:
A12: REVISIÓN GENERAL DE LÍMITES DE COSTOS Y GASTOS
A14: GASTOS DE GESTIÓN
A15: Cálculo del valor máximo de deducibilidad de gastos de gestión
A17: No. Casillero declaración de I. Renta (a) | B17: Descripción | E17: Referencia | F17: Valor | G17: Observaciones
A18: 7992 | B18: Total gastos declarados | E18: {1}
A19: 7185 | B19: Gastos de gestión declarados | E19: {2}
A20: - | B20: Total gastos generales (base para el cálculo del valor máximo de deducibilidad de gastos de gestión) | E20: {3}={1-2} | F20: =+F18-F19
A21: - | B21: Porcentaje máximo de deducibilidad de gastos de gestión (b) | E21: {4}
A22: - | B22: Valor máximo de deducibilidad de gastos de gestión | E22: {5}={3*4} | F22: =F20*F21
A24: 7185 | B24: Gastos de gestión declarados | E24: {6}
A25: 7186 | B25: Gastos de gestión declarados como no deducibles | E25: {7}
A26: - | B26: Gastos de gestión declarados como deducibles | E26: {8}={6-7} | F26: =+F24-F25
A28: - | B28: Diferencia en el valor máximo de deducibilidad de gastos de gestión (c) | E28: {9}={8-5} | F28: =IF((F26-F22)<=0,0,(F26-F22))
A31: GASTOS DE VIAJE
A32: Cálculo del valor máximo de deducibilidad de gastos de viaje
A34: No. Casillero declaración de I. Renta (a) | B34: Descripción | E34: Referencia | F34: Valor | G34: Observaciones
A35: 6999 | B35: Total Ingresos | E35: {1}
A36: 804 | B36: Dividendos exentos y efectos por método de participación | E36: {2}
A37: 805 | B37: Otras rentas exentas e ingresos no objeto de impuesto a la renta | E37: {3}
A38: 812 | B38: Ingresos sujetos a impuesto a la renta único | E38: {4}
A39: 1116 | B39: Diferencias temporarias - Por contratos de construcción (generación) | E39: {5}
A40: 828 | B40: Diferencias temporarias - Por mediciones de activos biológicos al valor razonable menos costos de venta / Ingresos (generación) | E40: {6}
A41: 834 | B41: Diferencias temporarias - Por otras diferencias temporarias (generación) (d) | E41: {7}
A42: 1117 | B42: Diferencias temporarias - Por contratos de construcción (reversión) | E42: {8}
A43: 829 | B43: Diferencias temporarias - Por mediciones de activos biológicos al valor razonable menos costos de venta / Ingresos (reversión) | E43: {9}
A44: 835 | B44: Diferencias temporarias - Por otras diferencias temporarias (reversión) (d) | E44: {10}
A45: - | B45: Total ingresos gravados (base para el cálculo del valor máximo de deducibilidad de gastos de viaje) | E45: {11}={1-2-3-4-5-6-7+8+9+10} | F45: =+F35-F36-F37-F38-F39-F40-F41+F42+F43+F44
A46: - | B46: Porcentaje máximo de deducibilidad de gastos de viaje (e) | E46: {12}
A47: - | B47: Valor máximo de deducibilidad de gastos de viaje | E47: {13}={11*12} | F47: =+F45*F46
A49: 7182 | B49: Gastos de viaje declarados | E49: {14}
B50: Gastos de viaje declarados como no deducibles | E50: {15}
A51: - | B51: Gastos de viaje declarados como deducibles | E51: {16}={14-15} | F51: =+F49-F50
A53: - | B53: Diferencia en el valor máximo de deducibilidad de gastos de viaje (f) | E53: {17}={16-13} | F53: =IF((F51-F47)<=0,0,(F51-F47))
A56: GASTOS INDIRECTOS ASIGNADOS DESDE EL EXTERIOR POR PARTES RELACIONADAS
A57: Cálculo del valor máximo de deducibilidad de gastos indirectos asignados desde el exterior por partes relacionadas
A59: No. Casillero declaración de I. Renta (a) | B59: Descripción | E59: Referencia | F59: Valor | G59: Observaciones
A60: - | B60: Utilidad gravable (base imponible) sin incluir límites (g) | E60: {1}
A61: 7205+7206 | B61: Costos y gastos indirectos asignados desde el exterior por partes relacionadas declarados | E61: {2}
A62: - | B62: Base imponible más el valor de los gastos indirectos asignados desde el exterior por partes relacionadas (base para el cálculo del valor máximo de deducibilidad de los gastos indirectos asignados desde el exterior por partes relacionadas) | E62: {3}={1+2} | F62: =+F60+F61
A63: - | B63: Porcentaje máximo de deducibilidad de gastos indirectos asignados desde el exterior por partes relacionadas (h) | E63: {4}
A64: - | B64: Valor máximo de deducibilidad de gastos indirectos asignados desde el exterior por partes relacionadas (i) | E64: {5}={3*4} | F64: =+IF(F60<=0,0,F62*F63)
A66: 7205+7206 | B66: Costos y gastos indirectos asignados desde el exterior por partes relacionadas declarados | E66: {6}
B67: Costos y gastos indirectos asignados desde el exterior por partes relacionadas declarados como no deducibles | E67: {7}
A68: - | B68: Costos y gastos indirectos asignados desde el exterior por partes relacionadas declarados como deducibles | E68: {8}={6-7} | F68: =+F66-F67
A70: - | B70: Diferencia en el valor máximo de deducibilidad de gastos indirectos asignados desde el exterior por partes relacionadas (j) | E70: {9}={8-5} | F70: =IF((F68-F64)<=0,0,(F68-F64))
A72: Nota: | B72: No aplica, ya que la Compañía no ha registrado gastos indirectos asigandos desde el exterior por partes relacionadas
A74: GASTOS DE PROMOCIÓN Y PUBLICIDAD
A75: Cálculo del valor máximo de deducibilidad de gastos de promoción y publicidad
A77: No. Casillero declaración de I. Renta (a) | B77: Descripción | E77: Referencia | F77: Valor | G77: Observaciones
B78: Total Ingresos | E78: {1}
B79: Dividendos exentos y efectos por método de participación | E79: {2}
B80: Otras rentas exentas e ingresos no objeto de impuesto a la renta | E80: {3}
B81: Ingresos sujetos a impuesto a la renta único | E81: {4}
B82: Diferencias temporarias - Por contratos de construcción (generación) | E82: {5}
B83: Diferencias temporarias - Por mediciones de activos biológicos al valor razonable menos costos de venta / Ingresos (generación) | E83: {6}
B84: Diferencias temporarias - Por otras diferencias temporarias (generación) (d) | E84: {7}
B85: Diferencias temporarias - Por contratos de construcción (reversión) | E85: {8}
B86: Diferencias temporarias - Por mediciones de activos biológicos al valor razonable menos costos de venta / Ingresos (reversión) | E86: {9}
B87: Diferencias temporarias - Por otras diferencias temporarias (reversión) (d) | E87: {10}
A88: - | B88: Total ingresos gravados (base para el cálculo del valor máximo de deducibilidad de gastos de promoción y publicidad) | E88: {11}={1-2-3-4-5-6-7+8+9+10} | F88: =+F78-F79-F80-F81-F82-F83-F84+F85+F86+F87
A89: - | B89: Porcentaje máximo de deducibilidad de gastos de promoción y publicidad (k) | E89: {12}
A90: - | B90: Valor máximo de deducibilidad de gastos de promoción y publicidad | E90: {13}={11*12} | F90: =+F88*F89
B92: Gastos de promoción y publicidad declarados | E92: {14}
B93: Gastos de promoción y publicidad declarados como no deducibles | E93: {15}
A94: - | B94: Gastos de promoción y publicidad declarados como deducibles | E94: {16}={14-15} | F94: =+F92-F93
A96: - | B96: Diferencia en el valor máximo de deducibilidad de gastos de promoción y publicidad (l) | E96: {17}={16-13} | F96: =IF((F94-F90)<=0,0,(F94-F90))
A99: GASTOS DE INTERESES POR CRÉDITOS DEL EXTERIOR CON PARTES RELACIONADAS
A100: Cálculo del valor máximo de deducibilidad de gastos de intereses por créditos del exterior con partes relacionadas
A102: No. Casillero declaración de I. Renta (a) | B102: Descripción | E102: Referencia | F102: Valor | G102: Observaciones
A103: - | B103: Valor total del endeudamiento externo (m) | E103: {1}
B104: Total Patrimonio | E104: {2}
A105: - | B105: Relación entre el total del endeudamiento externo y el patrimonio del contribuyente | E105: {3}={1/2} | F105: =+F103/F104
A106: - | B106: Porcentaje máximo de la relación entre el total del endeudamiento externo y el patrimonio para la deducibilidad de intereses por créditos del exterior con partes relacionadas (n) | E106: {4}
A107: - | B107: Valor de intereses por créditos del exterior con partes relacionadas según el contribuyente | E107: {5}
A108: - | B108: Valor máximo de deducibilidad de gastos de intereses por créditos del exterior con partes relacionadas (o) | E108: {6}={(5*4) / 3} | F108: =IF(F105>F106,((F107*F106)/F105),F107)
A110: 7278+7290 | B110: Gastos de intereses por créditos del exterior con partes relacionadas declarados | E110: {7}
A111: 7279+7291 | B111: Gastos de intereses por créditos del exterior con por partes relacionadas declarados como no deducibles | E111: {8}
A112: - | B112: Gastos de intereses por créditos del exterior con partes relacionadas declarados como deducibles | E112: {9}={7-8} | F112: =+F110-F111
A114: - | B114: Diferencia en el valor máximo de deducibilidad de gastos de intereses por créditos del exterior con partes relacionadas (p) | E114: {10}={9-6} | F114: =IF((F112-F108)<=0,0,(F112-F108))
A116: Nota: | B116: No aplica, ya que la Compañía no ha registrado intereses por créditos del exterior por partes relacionadas
A118: GASTOS DE INSTALACIÓN, ORGANIZACIÓN Y SIMILARES
A119: Cálculo del valor máximo de deducibilidad de gastos de instalación, organización y similares
A121: No. Casillero declaración de I. Renta (a) | B121: Descripción | E121: Referencia | F121: Valor | G121: Observaciones
A122: - | B122: Utilidad gravable (base imponible) | E122: {1}
A123: 7235+7236 | B123: Costos y gastos de instalación, organización y similares | E123: {2}
A124: - | B124: Base imponible más el valor de los gastos de instalación, organización y similares | E124: {3}={1+2} | F124: =+F122+F123
A125: - | B125: Porcentaje máximo de deducibilidad de gastos de instalación, organización y similares (q) | E125: {4}
A126: - | B126: Valor máximo de deducibilidad de gastos de instalación, organización y similares | E126: {5}={3*4} | F126: =+F124*F125
A128: 7235+7236 | B128: Costos y gastos de instalación, organización y similares declarados | E128: {6}
B129: Costos y gastos de instalación, organización y similares declarados como no deducibles | E129: {7}
A130: - | B130: Costos y gastos de instalación, organización y similares declarados como deducibles | E130: {8}={6-7} | F130: =+F128-F129
A132: - | B132: Diferencia en el valor máximo de deducibilidad de gastos de instalación, organización y similares (r) | E132: {9}={8-5} | F132: =IF((F130-F126)<=0,0,(F130-F126))
A134: Nota: | B134: No aplica, ya que la Compañía no ha registrado gastos de instalación, organización y similares
A137: NOTAS :
...

Sheet DM10 Hoja de hallazgos
A1: OBLIGACIONES ACUMULADAS
A3: Hoja de Hallazgos
A4: Nombre del cliente: | C4: Período terminado: | D4: =+'DM8 ATS'!D16:E16 | E4: Referencia de PT | F4: DM9
A5: Preparado por: | C5: Revisado por: | E5: Fecha | F5: =+'DM8 ATS'!C18
A7: No. | B7: Observación | C7: Referencia de PT | D7: Recomendación
A8: 1 | B8: Diferencia en ats vs anexos | C8: DM3
A10: Prodecimiento:
A11: Detallar las observaciones encontradas en cada uno de los análisis, detallando el problema encontrado, la causa y el efecto. (Mencionar el valor en USD$ de las diferencias determinadas)
