Workbook

Sheet 00_Inicio
B2: AuditConsulting Auditores Cía. Ltda. · AUDIT-IA
B4: Arrendamientos
B6: Cliente | C6: Cliente de muestra S.A. | D6: RUC | E6: 1790000000001
B7: Marco contable | C7: NIIF completas | D7: Fecha de corte | E7: 2025-12-31
B8: Preparó | C8: Ejercicio modelo | D8: Revisó | E8: Pendiente
B10: INDICADORES CLAVE
B11: Ajuste propuesto al pasivo | C11: Problemas encontrados
B12: 87220.64 | C12: 25
B15: IR A LA CÉDULA
B16: Carátula | C16: Programa | D16: Base técnica | E16: Resumen
B17: Parámetros | C17: Universo de contratos | D17: Identificación, clasificación y exenciones | E17: Plazo y opciones
B18: Medición inicial: pasivo y activo | C18: Pago base, componente indexado y pagos variables | D18: Remedición y modificaciones | E18: Tabla de amortización
B19: Pasivo al corte: corriente y no corriente | C19: Depreciación y deterioro del activo | D19: Gasto lineal: exentos y operativos | E19: Venta con arrendamiento posterior: medición inicial
B20: Venta con arrendamiento posterior: medición posterior | C20: Conciliación y ajuste | D20: Problemas encontrados | E20: Conclusión
B21: Control de revisión
B23: PANORAMA | N23: Datos de los gráficos (fórmulas a las cédulas)
N24: Cifras del resumen | O24: Importe (USD)
N25: ='01_Resumen'!A5 | O25: ='01_Resumen'!B5
N26: ='01_Resumen'!A6 | O26: ='01_Resumen'!B6
N27: ='01_Resumen'!A7 | O27: ='01_Resumen'!B7
N28: ='01_Resumen'!A8 | O28: ='01_Resumen'!B8
N29: ='01_Resumen'!A9 | O29: ='01_Resumen'!B9
N30: ='01_Resumen'!A10 | O30: ='01_Resumen'!B10
N31: ='01_Resumen'!A11 | O31: ='01_Resumen'!B11
N32: ='01_Resumen'!A12 | O32: ='01_Resumen'!B12
N33: ='01_Resumen'!A13 | O33: ='01_Resumen'!B13
N34: ='01_Resumen'!A14 | O34: ='01_Resumen'!B14
N35: ='01_Resumen'!A15 | O35: ='01_Resumen'!B15
N36: ='01_Resumen'!A16 | O36: ='01_Resumen'!B16
... N38: ='01_Resumen'!A18 | O38: ='01_Resumen'!B18
N40: Hallazgos de mayor impacto | O40: Importe (USD)
N41: Venta ganancia | O41: =SUMIFS('16_Problemas'!$C$5:$C$29,'16_Problemas'!$A$5:$A$29,"VENTA_GANANCIA",'16_Problemas'!$C$5:$C$29,">0")-SUMIFS('16_Problemas'!$C$5:$C$29,'16_Problemas'!$A$5:$A$29,"VENTA_GANANCIA",'16_Problemas'!$C$5:$C$29,"<0")
N42: Activo diferencia (×6) | O42: =SUMIFS('16_Problemas'!$C$5:$C$29,'16_Problemas'!$A$5:$A$29,"ACTIVO_DIFERENCIA",'16_Problemas'!$C$5:$C$29,">0")-SUMIFS('16_Problemas'!$C$5:$C$29,'16_Problemas'!$A$5:$A$29,"ACTIVO_DIFERENCIA",'16_Problemas'!$C$5:$C$29,"<0")
N43: Pasivo diferencia (×5) | O43: =SUMIFS('16_Problemas'!$C$5:$C$29,'16_Problemas'!$A$5:$A$29,"PASIVO_DIFERENCIA",'16_Problemas'!$C$5:$C$29,">0")-SUMIFS('16_Problemas'!$C$5:$C$29,'16_Problemas'!$A$5:$A$29,"PASIVO_DIFERENCIA",'16_Problemas'!$C$5:$C$29,"<0")
N44: Deterioro | O44: =SUMIFS('16_Problemas'!$C$5:$C$29,'16_Problemas'!$A$5:$A$29,"DETERIORO",'16_Problemas'!$C$5:$C$29,">0")-SUMIFS('16_Problemas'!$C$5:$C$29,'16_Problemas'!$A$5:$A$29,"DETERIORO",'16_Problemas'!$C$5:$C$29,"<0")
N45: Bajo valor vehiculo | O45: =SUMIFS('16_Problemas'!$C$5:$C$29,'16_Problemas'!$A$5:$A$29,"BAJO_VALOR_VEHICULO",'16_Problemas'!$C$5:$C$29,">0")-SUMIFS('16_Problemas'!$C$5:$C$29,'16_Problemas'!$A$5:$A$29,"BAJO_VALOR_VEHICULO",'16_Problemas'!$C$5:$C$29,"<0")
N46: Exencion mal aplicada | O46: =SUMIFS('16_Problemas'!$C$5:$C$29,'16_Problemas'!$A$5:$A$29,"EXENCION_MAL_APLICADA",'16_Problemas'!$C$5:$C$29,">0")-SUMIFS('16_Problemas'!$C$5:$C$29,'16_Problemas'!$A$5:$A$29,"EXENCION_MAL_APLICADA",'16_Problemas'!$C$5:$C$29,"<0")
N47: Venta ganancia posterior | O47: =SUMIFS('16_Problemas'!$C$5:$C$29,'16_Problemas'!$A$5:$A$29,"VENTA_GANANCIA_POSTERIOR",'16_Problemas'!$C$5:$C$29,">0")-SUMIFS('16_Problemas'!$C$5:$C$29,'16_Problemas'!$A$5:$A$29,"VENTA_GANANCIA_POSTERIOR",'16_Problemas'!$C$5:$C$29,"<0")
N48: Otros (4 tipos) | O48: =SUMIF('16_Problemas'!$C$5:$C$29,">0")-SUMIF('16_Problemas'!$C$5:$C$29,"<0")-((SUMIFS('16_Problemas'!$C$5:$C$29,'16_Problemas'!$A$5:$A$29,"VENTA_GANANCIA",'16_Problemas'!$C$5:$C$29,">0")-SUMIFS('16_Problemas'!$C$5:$C$29,'16_Problemas'!$A$5:$A$29,"VENTA_GANANCIA",'16_Problemas'!$C$5:$C$29,"<0"))+(SUMIFS('16_Problemas'!$C$5:$C$29,'16_Problemas'!$A$5:$A$29,"ACTIVO_DIFERENCIA",'16_Problemas'!$C$5:$C$29,">0")-SUMIFS('16_Problemas'!$C$5:$C$29,'16_Problemas'!$A$5:$A$29,"ACTIVO_DIFERENCIA",'16_Problemas'!$C$5:$C$29,"<0"))+(SUMIFS('16_Problemas'!$C$5:$C$29,'16_Problemas'!$A$5:$A$29,"PASIVO_DIFERENCIA",'16_Problemas'!$C$5:$C$29,">0")-SUMIFS('16_Problemas'!$C$5:$C$29,'16_Problemas'!$A$5:$A$29,"PASIVO_DIFERENCIA",'16_Problemas'!$C$5:$C$29,"<0"))+(SUMIFS('16_Problemas'!$C$5:$C$29,'16_Problemas'!$A$5:$A$29,"DETERIORO",'16_Problemas'!$C$5:$C$29,">0")-SUMIFS('16_Problemas'!$C$5:$C$29,'16_Problemas'!$A$5:$A$29,"DETERIORO",'16_Problemas'!$C$5:$C$29,"<0"))+(SUMIFS('16_Problemas'!$C$5:$C$29,'16_Problemas'!$A$5:$A$29,"BAJO_VALOR_VEHICULO",'16_Problemas'!$C$5:$C$29,">0")-SUMIFS('16_Problemas'!$C$5:$C$29,'16_Problemas'!$A$5:$A$29,"BAJO_VALOR_VEHICULO",'16_Problemas'!$C$5:$C$29,"<0"))+(SUMIFS('16_Problemas'!$C$5:$C$29,'16_Problemas'!$A$5:$A$29,"EXENCION_MAL_APLICADA",'16_Problemas'!$C$5:$C$29,">0")-SUMIFS('16_Problemas'!$C$5:$C$29,'16_Problemas'!$A$5:$A$29,"EXENCION_MAL_APLICADA",'16_Problemas'!$C$5:$C$29,"<0"))+(SUMIFS('16_Problemas'!$C$5:$C$29,'16_Problemas'!$A$5:$A$29,"VENTA_GANANCIA_POSTERIOR",'16_Problemas'!$C$5:$C$29,">0")-SUMIFS('16_Problemas'!$C$5:$C$29,'16_Problemas'!$A$5:$A$29,"VENTA_GANANCIA_POSTERIOR",'16_Problemas'!$C$5:$C$29,"<0")))

Sheet 00_Caratula
A1: Carátula | H1: ⟵ Inicio | J1: Siguiente ▶
A2: Arrendamientos · Cliente de muestra S.A. · corte 2025-12-31
A4: Concepto | B4: Detalle
A5: Firma | B5: AuditConsulting Auditores Cía. Ltda.
A6: Cliente | B6: Cliente de muestra S.A.
A7: RUC | B7: 1790000000001
A8: Ejercicio | B8: 2025
A9: Fecha de corte | B9: 2025-12-31
A10: Marco contable | B10: NIIF completas
A11: Herramienta | B11: Arrendamientos
A12: Rubro | B12: Arrendamientos
A13: Motor | B13: arrendamientos 1.0
A14: Versión del papel | B14: v1
A15: Estado | B15: MUESTRA
... A17: Revisó | B17: Pendiente
A18: Aprobó
A19: Fecha de aprobación
A20: Huella de la ejecución (SHA-256)

Sheet 00_Programa
A1: Programa | H1: ⟵ Inicio | I1: ◀ Anterior | J1: Siguiente ▶
A2: Arrendamientos · Cliente de muestra S.A. · corte 2025-12-31
A4: Código | B4: Objetivo | C4: Afirmación | D4: Procedimiento | E4: Evidencia | F4: Criterio | G4: Referencia
A5: ARR-01 | B5: Integridad del universo de contratos | C5: Integridad | D5: Conciliar el anexo con el mayor; revisar contratos de servicios, actas y gastos de alquiler para identificar arrendamientos (9, B9–B31) | E5: Anexo de contratos, contratos firmados, mayor de gastos de alquiler | F5: Universo completo y conciliado | G5: NIIF 16 párr. 9 · NIA 500
A6: ARR-02 | B6: Exenciones y clasificación | C6: Presentación | D6: Evaluar plazo, opción de compra, valor del activo nuevo (B3) y las condiciones de B5 a B7 (uso independiente, no automóvil, sin subarriendo); en PYMES, los indicadores de 20.5 | E6: Contratos, cotizaciones del activo nuevo, contratos de subarriendo | F6: Tratamiento conforme a 5–8, B3–B8 / 20.4–20.8 | G6: NIIF 16 párr. 5–8, B3–B8 · Sección 20.4–20.8
A7: ARR-03 | B7: Plazo y opciones | C7: Valoración | D7: Evaluar incentivos económicos para renovar o comprar (mejoras, penalidades, importancia del activo) | E7: Contratos, presupuestos, historial de renovaciones | F7: Plazo conforme a 18–21 y B37 | G7: NIIF 16 párr. 18–21, 27 d, B34–B41
A8: ARR-04 | B8: Tasa de descuento | C8: Valoración | D8: Verificar la tasa implícita o la incremental con préstamos recientes y plazos comparables | E8: Contratos de préstamo, cotizaciones bancarias | F8: Tasa sustentada | G8: NIIF 16 párr. 26 · Sección 20.10 · NIA 540
A9: ARR-05 | B9: Medición del pasivo y del activo | C9: Valoración | D9: Recalcular VP, tabla de amortización, interés, depreciación y compararlos con lo registrado | E9: Cédulas 06, 08, 09 y 10 | F9: Diferencias cuantificadas | G9: NIIF 16 párr. 23–38 · Sección 20.9–20.12
A10: ARR-06 | B10: Presentación corriente / no corriente | C10: Presentación | D10: Recalcular el capital que se paga en los 12 meses siguientes al corte | E10: Tabla de amortización | F10: Clasificación conforme a NIC 1 párr. 69 | G10: NIIF 16 párr. 47 · NIC 1 párr. 69
A11: ARR-07 | B11: Modificaciones y remediciones | C11: Valoración | D11: Revisar adendas y cambios de índice; recalcular el pasivo remedido y el ajuste al derecho de uso | E11: Adendas, comunicaciones del arrendador | F11: Remedición conforme a 39–46 | G11: NIIF 16 párr. 39–46 · NIA 560
A12: ARR-08 | B12: Deterioro del activo | C12: Valoración | D12: Evaluar indicios y comparar el neto con el importe recuperable | E12: Evaluación de deterioro del cliente | F12: Deterioro reconocido | G12: NIIF 16 párr. 33 · NIC 36 · Sección 20.12 y 27
A13: ARR-09 | B13: Venta con arrendamiento posterior | C13: Ocurrencia | D13: Verificar que la transferencia es venta (NIIF 15), medir el derecho de uso conservado y la ganancia de los derechos transferidos | E13: Contrato de compraventa, tasación, contrato de arrendamiento | F13: Ganancia conforme a 99–103 / 20.32–20.34 | G13: NIIF 16 párr. 98–103 · Sección 20.32–20.34
A14: ARR-10 | B14: Pago base y componente ligado a un índice de inflación | C14: Valoración | D14: Separar en la factura o liquidación del período la renta base del reajuste por índice; comprobar que en NIIF completas el componente se midió con el índice de la fecha de comienzo y que en PYMES se cargó como gasto del período | E14: Facturas y liquidaciones de renta, cláusula de revisión del contrato, índice publicado (INEC u organismo oficial) | F14: Componente medido o expensado según el marco y revelado | G14: NIIF 16 párr. 27 b, 28, 38 b, 42 b y 43 · Sección 20.11, 20.13 c, 20.15 b y 20.16 c
A15: ARR-11 | B15: Medición posterior de la venta con arrendamiento posterior | C15: Valoración | D15: Recorrer el movimiento del pasivo (saldo inicial, interés, pagos fijos y variables, remedición, saldo final) y del derecho de uso conservado (costo, depreciación, neto); revisar los asientos posteriores a la venta que afecten resultados | E15: Mayor del pasivo y del derecho de uso, asientos de remedición, contrato de arrendamiento | F15: Sin ganancia ni pérdida sobre el derecho de uso conservado, salvo terminación (46 a) | G15: NIIF 16 párr. 102A, 29–35 y 36–46

Sheet 00_Fuentes
A1: Base técnica | H1: ⟵ Inicio | I1: ◀ Anterior | J1: Siguiente ▶
A2: Arrendamientos · Cliente de muestra S.A. · corte 2025-12-31
A4: Categoría | B4: Documento | C4: Párrafos | D4: URL | E4: Verificada
A5: NIA · NIA 540 (Revisada) | B5: Estimación contable: evaluar método (VP, tabla), datos (contratos) y supuestos (tasa incremental, plazo, opciones). | C5: párr. 13, 16–17, 18–27 y 28–30 (28: el recálculo del auditor es una estimación puntual propia; 30: NIA 500)
A6: NIA · NIA 500 | B6: Exactitud e integridad del anexo de contratos contra el mayor y los contratos firmados. | C6: párr. 9
A7: NIA · NIA 505 | B7: Confirmar con arrendadores condiciones y pagos cuando sea significativo. | C7: párr. 7 (decisión de confirmar: NIA 330 párr. 19)
A8: NIA · NIA 560 | B8: Modificaciones, renovaciones o terminaciones posteriores al cierre. | C8: párr. 6

Sheet 01_Resumen
A1: Resumen | H1: ⟵ Inicio | I1: ◀ Anterior | J1: Siguiente ▶
A2: Arrendamientos · Cliente de muestra S.A. · corte 2025-12-31
A4: Concepto | B4: Importe
A5: Pasivo por arrendamiento registrado (mayor) | B5: ='15_Conciliacion'!C16
A6: Pasivo por arrendamiento recalculado | B6: ='15_Conciliacion'!B16
A7: Ajuste propuesto al pasivo | B7: =B6-B5
A8: Pasivo corriente recalculado | B8: =SUM('10_Pasivo_corte'!O5:O15)
A9: Pasivo no corriente recalculado | B9: =SUM('10_Pasivo_corte'!P5:P15)
A10: Derecho de uso neto recalculado | B10: ='15_Conciliacion'!E16
A11: Activo registrado neto | B11: ='15_Conciliacion'!F16
A12: Ajuste propuesto al activo | B12: =B10-B11
A13: Depreciación del ejercicio | B13: ='15_Conciliacion'!H16
A14: Interés del ejercicio | B14: ='15_Conciliacion'!I16
A15: Deterioro del activo | B15: =SUM('11_Derecho_uso'!N5:N15)
A16: Gasto lineal (exentos / operativos) | B16: =SUM('12_Gasto_lineal'!F5:F15)
A17: Gasto del ejercicio por pagos variables (38 b / 20.11 y 20.15 b) | B17: =SUM('07_Pagos_variables'!L5:L15)
A18: Remedición del pasivo | B18: =SUM('08_Remedicion'!L5:L15)
A20: ⓘ Cómo se calcula esta hoja
A21: Columna | B21: Fórmula (Excel) | C21: Cómo se calcula (sencillo) | D21: Ejemplo con números reales | E21: De dónde viene | F21: Norma
A22: Importe | B22: '='15_Conciliacion'!C16 | C22: Trae cada importe de su hoja de origen, concepto por concepto: pasivo, activo, depreciación e interés de la fila TOTAL de la hoja 15 (Conciliación y ajuste); corriente y no corriente de la hoja 10; deterioro de la hoja 11; gasto lineal de la hoja 12; pagos variables de la hoja 07 y remedición de la hoja 08. Los ajustes son recalculado menos registrado. | D22: Fila 1: 1.594.538,08 → 1.594.538,08 | E22: hoja «Conciliación y ajuste» | F22: —

Sheet 02_Parametros
A1: Parámetros | H1: ⟵ Inicio | I1: ◀ Anterior | J1: Siguiente ▶
A2: Arrendamientos · Cliente de muestra S.A. · corte 2025-12-31
A4: Parámetro | B4: Valor | C4: Sustento
A5: Fecha de corte | B5: 46022 | C5: Ficha del encargo
A6: Tasa anual del contrato | B6: Efectiva anual | C6: Efectiva: (1 + r)^(meses/12) − 1 · Nominal: r × meses/12
A7: PYMES: plazo ≥ % de la vida económica | B7: 75 | C7: Indicador 20.5 c; umbral de juicio del auditor; la Sección 20 no fija porcentajes
A8: PYMES: VP de los pagos mínimos ≥ % del valor razonable | B8: 90 | C8: Indicador 20.5 d; umbral de juicio del auditor; la Sección 20 no fija porcentajes
A9: Límite de bajo valor del activo nuevo (USD) | B9: 5000 | C9: NIIF 16 B3–B8 no fija importe; el IASB pensó en activos de unos USD 5.000 o menos cuando son nuevos (Fundamentos BC100, no forman parte de la norma). Además de no pasar del límite, el bajo valor exige el valor del activo nuevo (B3), que el arrendatario pueda usarlo por sí solo o con recursos disponibles y que no dependa ni esté interrelacionado con otros activos (B5), que no sea un automóvil (coche nuevo, B6) y que no se subarriende (B7).
A10: Marco y ruta de cálculo | B10: NIIF completas · NIIF 16 (modelo único del arrendatario) | C10: NIIF 16 párr. 22–46

Sheet 03_Contratos
A1: Universo de contratos | H1: ⟵ Inicio | I1: ◀ Anterior | J1: Siguiente ▶
A2: Arrendamientos · Cliente de muestra S.A. · corte 2025-12-31
A4: Contrato | B4: Activo subyacente | C4: Fecha de comienzo | D4: Plazo no cancelable (meses) | E4: Meses de la opción de renovación | F4: Renovación razonablemente cierta (sí/no) | G4: Plazo usado por el cliente (meses) | H4: Pago periódico total del contrato (incluye el componente indexado) | I4: Periodicidad (mensual/trimestral/semestral/anual) | J4: Pago al inicio o al final del período | K4: El pago se ajusta por un índice de inflación (sí/no) | L4: Componente del pago ligado al índice (importe por período) | M4: Índice o referencia del ajuste | N4: Pago variable del período no ligado a un índice | O4: Tasa anual (%) | P4: Tipo de tasa (implícita/incremental) | Q4: Pagos anticipados antes del comienzo | R4: Costos directos iniciales | S4: Costo estimado de desmantelamiento | T4: Incentivos recibidos | U4: Precio de la opción de compra | V4: Compra razonablemente cierta (sí/no) | W4: Vida útil del activo (meses) | X4: Valor razonable del activo (nuevo) | Y4: Activo de bajo valor (sí/no) | Z4: Bajo valor: se usa por sí solo, no depende de otros activos y no se subarrienda (B5, B7) (sí/no) | AA4: El cliente aplicó la exención (sí/no) | AB4: Clasificación PYMES del cliente (financiero/operativo) | AC4: Pasivo por arrendamiento registrado al corte | AD4: Pasivo corriente registrado | AE4: Derecho de uso / activo registrado neto | AF4: Depreciación registrada del ejercicio | AG4: Interés registrado del ejercicio | AH4: Fecha de modificación o nueva evaluación | AI4: Tipo de evento (modificación/índice/plazo) | AJ4: Nuevo pago periódico | AK4: Tasa anual revisada (%) | AL4: Plazo total revisado (meses desde el comienzo) | AM4: El cliente remidió el pasivo (sí/no) | AN4: Importe recuperable del activo | AO4: Venta con arrendamiento posterior (sí/no) | AP4: Precio de venta | AQ4: Importe en libros antes de la venta | AR4: Ganancia registrada en la venta | AS4: Ganancia o pérdida reconocida después de la venta por la medición posterior del arrendamiento
A5: C-01 | B5: Local comercial matriz | C5: 45292 | D5: 36 | E5: 24 | F5: Sí | G5: 36 | H5: 1500 | I5: Mensual | J5: Final | O5: 12 | P5: Incremental | AB5: Operativo | AC5: 17000 | AD5: 17000 | AE5: 16500 | AG5: 2600
A6: C-02 | B6: Bodega norte | C6: 44927 | D6: 60 | H6: 10000 | I6: Anual | J6: Final | O6: 10 | P6: Incremental | R6: 500 | X6: 40000 | AB6: Operativo | AC6: 17355.37 | AD6: 10000 | AE6: 15363.15 | AF6: 7681.57 | AG6: 2486.85
A7: C-03 | B7: Vehículo de gerencia | C7: 45748 | D7: 36 | H7: 900 | I7: Mensual | J7: Inicio | O7: 11 | X7: 45000 | Y7: Sí | AA7: Sí | AB7: Operativo | AC7: 0 | AE7: 0
A8: C-04 | B8: Computadores portátiles | C8: 45658 | D8: 24 | H8: 80 | I8: Mensual | J8: Final | O8: 12 | X8: 1200 | Y8: Sí | AA8: Sí | AB8: Operativo | AC8: 0 | AE8: 0
A9: C-05 | B9: Parqueadero temporal | C9: 45839 | D9: 12 | H9: 300 | I9: Mensual | J9: Final | O9: 10 | AA9: Sí | AB9: Operativo | AC9: 0 | AE9: 0
A10: C-06 | B10: Montacargas con opción de compra | C10: 45474 | D10: 48 | H10: 6000 | I10: Trimestral | J10: Final | O10: 9 | P10: Implícita | U10: 5000 | V10: Sí | W10: 120 | X10: 85000 | AB10: Financiero | AC10: 57428.43 | AD10: 19626.9 | AE10: 71291.6 | AF10: 8387.25 | AG10: 5993.67
A11: C-07 | B11: Oficina sucursal | C11: 44927 | D11: 60 | H11: 12000 | I11: Anual | J11: Final | O11: 8 | AB11: Operativo | AC11: 19925.16 | AE11: 19165.01 | AG11: 2474.01 | AH11: 45658 | AI11: Modificación | AJ11: 13500 | AK11: 9 | AM11: No
A12: C-08 | B12: Edificio administrativo (venta con arrendamiento posterior) | C12: 45658 | D12: 216 | H12: 120000 | I12: Anual | J12: Final | O12: 4.5 | X12: 1800000 | AB12: Operativo | AC12: 1404863 | AE12: 660690.84 | AO12: Sí | AP12: 2000000 | AQ12: 1000000 | AR12: 800000 | AS12: 18500
A13: C-09 | B13: Local cerrado en centro comercial | C13: 45292 | D13: 60 | H13: 2500 | I13: Mensual | J13: Final | O13: 10 | AB13: Operativo | AC13: 77966.15 | AE13: 71307.75 | AN13: 50000
A14: C-10 | B14: Bodega sur con renta ajustada por inflación | C14: 45292 | D14: 36 | H14: 2000 | I14: Mensual | J14: Final | K14: Sí | L14: 200 | M14: IPC del INEC (Ecuador) | N14: 50 | O14: 12 | AB14: Operativo | AC14: 0 | AE14: 0
A15: C-11 | B15: Oficina regional con reajuste sin detalle | C15: 45658 | D15: 24 | H15: 1000 | I15: Mensual | J15: Final | K15: Sí | M15: Índice de precios del contrato | O15: 10 | AB15: Operativo | AC15: 0 | AE15: 0

Sheet 04_Identificacion
A1: Identificación, clasificación y exenciones | H1: ⟵ Inicio | I1: ◀ Anterior | J1: Siguiente ▶
A2: Arrendamientos · Cliente de muestra S.A. · corte 2025-12-31
A4: Contrato | B4: Activo | C4: Plazo (meses) | D4: Opción de compra | E4: Corto plazo (≤ 12 m, sin opción) | F4: Bajo valor declarado | G4: Valor del activo nuevo (B3) | H4: Automóvil (B6) | I4: Uso independiente y sin subarriendo (B5, B7) | J4: Bajo valor elegible (B3, B5–B7) | K4: Exención elegible (5) | L4: Exención aplicada por el cliente | M4: Reconoce pasivo | N4: Tipo de tasa (26)
A5: C-01 | B5: Local comercial matriz | C5: ='05_Plazo'!E5 | D5: =IF(N('03_Contratos'!U5)>0,"Sí","No") | E5: =IF(AND(C5<=12,D5="No"),"Sí","No") | F5: =IF('03_Contratos'!Y5="","No",'03_Contratos'!Y5) | G5: =IF('03_Contratos'!X5="","",'03_Contratos'!X5) | H5: =IF(OR(ISNUMBER(SEARCH("automovil",B5)),ISNUMBER(SEARCH("automóvil",B5)),ISNUMBER(SEARCH("vehiculo",B5)),ISNUMBER(SEARCH("vehículo",B5)),ISNUMBER(SEARCH("camioneta",B5)),ISNUMBER(SEARCH("coche",B5)),ISNUMBER(SEARCH("furgoneta",B5))),"Sí","No") | I5: =IF('03_Contratos'!Z5="","",'03_Contratos'!Z5) | J5: =IF(OR(F5="No",G5="",G5>'02_Parametros'!$B$9,H5="Sí",I5="No"),"No","Sí") | K5: =IF(OR(E5="Sí",J5="Sí"),"Sí","No") | L5: =IF('03_Contratos'!AA5="","No",'03_Contratos'!AA5) | M5: =IF(AND(L5="Sí",K5="Sí"),"No","Sí") | N5: =IF('03_Contratos'!P5="","",'03_Contratos'!P5)
A6: C-02 | B6: Bodega norte | C6: ='05_Plazo'!E6 | D6: =IF(N('03_Contratos'!U6)>0,"Sí","No") | E6: =IF(AND(C6<=12,D6="No"),"Sí","No") | F6: =IF('03_Contratos'!Y6="","No",'03_Contratos'!Y6) | G6: =IF('03_Contratos'!X6="","",'03_Contratos'!X6) | H6: =IF(OR(ISNUMBER(SEARCH("automovil",B6)),ISNUMBER(SEARCH("automóvil",B6)),ISNUMBER(SEARCH("vehiculo",B6)),ISNUMBER(SEARCH("vehículo",B6)),ISNUMBER(SEARCH("camioneta",B6)),ISNUMBER(SEARCH("coche",B6)),ISNUMBER(SEARCH("furgoneta",B6))),"Sí","No") | I6: =IF('03_Contratos'!Z6="","",'03_Contratos'!Z6) | J6: =IF(OR(F6="No",G6="",G6>'02_Parametros'!$B$9,H6="Sí",I6="No"),"No","Sí") | K6: =IF(OR(E6="Sí",J6="Sí"),"Sí","No") | L6: =IF('03_Contratos'!AA6="","No",'03_Contratos'!AA6) | M6: =IF(AND(L6="Sí",K6="Sí"),"No","Sí") | N6: =IF('03_Contratos'!P6="","",'03_Contratos'!P6)
A7: C-03 | B7: Vehículo de gerencia | C7: ='05_Plazo'!E7 | D7: =IF(N('03_Contratos'!U7)>0,"Sí","No") | E7: =IF(AND(C7<=12,D7="No"),"Sí","No") | F7: =IF('03_Contratos'!Y7="","No",'03_Contratos'!Y7) | G7: =IF('03_Contratos'!X7="","",'03_Contratos'!X7) | H7: =IF(OR(ISNUMBER(SEARCH("automovil",B7)),ISNUMBER(SEARCH("automóvil",B7)),ISNUMBER(SEARCH("vehiculo",B7)),ISNUMBER(SEARCH("vehículo",B7)),ISNUMBER(SEARCH("camioneta",B7)),ISNUMBER(SEARCH("coche",B7)),ISNUMBER(SEARCH("furgoneta",B7))),"Sí","No") | I7: =IF('03_Contratos'!Z7="","",'03_Contratos'!Z7) | J7: =IF(OR(F7="No",G7="",G7>'02_Parametros'!$B$9,H7="Sí",I7="No"),"No","Sí") | K7: =IF(OR(E7="Sí",J7="Sí"),"Sí","No") | L7: =IF('03_Contratos'!AA7="","No",'03_Contratos'!AA7) | M7: =IF(AND(L7="Sí",K7="Sí"),"No","Sí") | N7: =IF('03_Contratos'!P7="","",'03_Contratos'!P7)
A8: C-04 | B8: Computadores portátiles | C8: ='05_Plazo'!E8 | D8: =IF(N('03_Contratos'!U8)>0,"Sí","No") | E8: =IF(AND(C8<=12,D8="No"),"Sí","No") | F8: =IF('03_Contratos'!Y8="","No",'03_Contratos'!Y8) | G8: =IF('03_Contratos'!X8="","",'03_Contratos'!X8) | H8: =IF(OR(ISNUMBER(SEARCH("automovil",B8)),ISNUMBER(SEARCH("automóvil",B8)),ISNUMBER(SEARCH("vehiculo",B8)),ISNUMBER(SEARCH("vehículo",B8)),ISNUMBER(SEARCH("camioneta",B8)),ISNUMBER(SEARCH("coche",B8)),ISNUMBER(SEARCH("furgoneta",B8))),"Sí","No") | I8: =IF('03_Contratos'!Z8="","",'03_Contratos'!Z8) | J8: =IF(OR(F8="No",G8="",G8>'02_Parametros'!$B$9,H8="Sí",I8="No"),"No","Sí") | K8: =IF(OR(E8="Sí",J8="Sí"),"Sí","No") | L8: =IF('03_Contratos'!AA8="","No",'03_Contratos'!AA8) | M8: =IF(AND(L8="Sí",K8="Sí"),"No","Sí") | N8: =IF('03_Contratos'!P8="","",'03_Contratos'!P8)
A9: C-05 | B9: Parqueadero temporal | C9: ='05_Plazo'!E9 | D9: =IF(N('03_Contratos'!U9)>0,"Sí","No") | E9: =IF(AND(C9<=12,D9="No"),"Sí","No") | F9: =IF('03_Contratos'!Y9="","No",'03_Contratos'!Y9) | G9: =IF('03_Contratos'!X9="","",'03_Contratos'!X9) | H9: =IF(OR(ISNUMBER(SEARCH("automovil",B9)),ISNUMBER(SEARCH("automóvil",B9)),ISNUMBER(SEARCH("vehiculo",B9)),ISNUMBER(SEARCH("vehículo",B9)),ISNUMBER(SEARCH("camioneta",B9)),ISNUMBER(SEARCH("coche",B9)),ISNUMBER(SEARCH("furgoneta",B9))),"Sí","No") | I9: =IF('03_Contratos'!Z9="","",'03_Contratos'!Z9) | J9: =IF(OR(F9="No",G9="",G9>'02_Parametros'!$B$9,H9="Sí",I9="No"),"No","Sí") | K9: =IF(OR(E9="Sí",J9="Sí"),"Sí","No") | L9: =IF('03_Contratos'!AA9="","No",'03_Contratos'!AA9) | M9: =IF(AND(L9="Sí",K9="Sí"),"No","Sí") | N9: =IF('03_Contratos'!P9="","",'03_Contratos'!P9)
A10: C-06 | B10: Montacargas con opción de compra | C10: ='05_Plazo'!E10 | D10: =IF(N('03_Contratos'!U10)>0,"Sí","No") | E10: =IF(AND(C10<=12,D10="No"),"Sí","No") | F10: =IF('03_Contratos'!Y10="","No",'03_Contratos'!Y10) | G10: =IF('03_Contratos'!X10="","",'03_Contratos'!X10) | H10: =IF(OR(ISNUMBER(SEARCH("automovil",B10)),ISNUMBER(SEARCH("automóvil",B10)),ISNUMBER(SEARCH("vehiculo",B10)),ISNUMBER(SEARCH("vehículo",B10)),ISNUMBER(SEARCH("camioneta",B10)),ISNUMBER(SEARCH("coche",B10)),ISNUMBER(SEARCH("furgoneta",B10))),"Sí","No") | I10: =IF('03_Contratos'!Z10="","",'03_Contratos'!Z10) | J10: =IF(OR(F10="No",G10="",G10>'02_Parametros'!$B$9,H10="Sí",I10="No"),"No","Sí") | K10: =IF(OR(E10="Sí",J10="Sí"),"Sí","No") | L10: =IF('03_Contratos'!AA10="","No",'03_Contratos'!AA10) | M10: =IF(AND(L10="Sí",K10="Sí"),"No","Sí") | N10: =IF('03_Contratos'!P10="","",'03_Contratos'!P10)
A11: C-07 | B11: Oficina sucursal | C11: ='05_Plazo'!E11 | D11: =IF(N('03_Contratos'!U11)>0,"Sí","No") | E11: =IF(AND(C11<=12,D11="No"),"Sí","No") | F11: =IF('03_Contratos'!Y11="","No",'03_Contratos'!Y11) | G11: =IF('03_Contratos'!X11="","",'03_Contratos'!X11) | H11: =IF(OR(ISNUMBER(SEARCH("automovil",B11)),ISNUMBER(SEARCH("automóvil",B11)),ISNUMBER(SEARCH("vehiculo",B11)),ISNUMBER(SEARCH("vehículo",B11)),ISNUMBER(SEARCH("camioneta",B11)),ISNUMBER(SEARCH("coche",B11)),ISNUMBER(SEARCH("furgoneta",B11))),"Sí","No") | I11: =IF('03_Contratos'!Z11="","",'03_Contratos'!Z11) | J11: =IF(OR(F11="No",G11="",G11>'02_Parametros'!$B$9,H11="Sí",I11="No"),"No","Sí") | K11: =IF(OR(E11="Sí",J11="Sí"),"Sí","No") | L11: =IF('03_Contratos'!AA11="","No",'03_Contratos'!AA11) | M11: =IF(AND(L11="Sí",K11="Sí"),"No","Sí") | N11: =IF('03_Contratos'!P11="","",'03_Contratos'!P11)
A12: C-08 | B12: Edificio administrativo (venta con arrendamiento posterior) | C12: ='05_Plazo'!E12 | D12: =IF(N('03_Contratos'!U12)>0,"Sí","No") | E12: =IF(AND(C12<=12,D12="No"),"Sí","No") | F12: =IF('03_Contratos'!Y12="","No",'03_Contratos'!Y12) | G12: =IF('03_Contratos'!X12="","",'03_Contratos'!X12) | H12: =IF(OR(ISNUMBER(SEARCH("automovil",B12)),ISNUMBER(SEARCH("automóvil",B12)),ISNUMBER(SEARCH("vehiculo",B12)),ISNUMBER(SEARCH("vehículo",B12)),ISNUMBER(SEARCH("camioneta",B12)),ISNUMBER(SEARCH("coche",B12)),ISNUMBER(SEARCH("furgoneta",B12))),"Sí","No") | I12: =IF('03_Contratos'!Z12="","",'03_Contratos'!Z12) | J12: =IF(OR(F12="No",G12="",G12>'02_Parametros'!$B$9,H12="Sí",I12="No"),"No","Sí") | K12: =IF(OR(E12="Sí",J12="Sí"),"Sí","No") | L12: =IF('03_Contratos'!AA12="","No",'03_Contratos'!AA12) | M12: =IF(AND(L12="Sí",K12="Sí"),"No","Sí") | N12: =IF('03_Contratos'!P12="","",'03_Contratos'!P12)
A13: C-09 | B13: Local cerrado en centro comercial | C13: ='05_Plazo'!E13 | D13: =IF(N('03_Contratos'!U13)>0,"Sí","No") | E13: =IF(AND(C13<=12,D13="No"),"Sí","No") | F13: =IF('03_Contratos'!Y13="","No",'03_Contratos'!Y13) | G13: =IF('03_Contratos'!X13="","",'03_Contratos'!X13) | H13: =IF(OR(ISNUMBER(SEARCH("automovil",B13)),ISNUMBER(SEARCH("automóvil",B13)),ISNUMBER(SEARCH("vehiculo",B13)),ISNUMBER(SEARCH("vehículo",B13)),ISNUMBER(SEARCH("camioneta",B13)),ISNUMBER(SEARCH("coche",B13)),ISNUMBER(SEARCH("furgoneta",B13))),"Sí","No") | I13: =IF('03_Contratos'!Z13="","",'03_Contratos'!Z13) | J13: =IF(OR(F13="No",G13="",G13>'02_Parametros'!$B$9,H13="Sí",I13="No"),"No","Sí") | K13: =IF(OR(E13="Sí",J13="Sí"),"Sí","No") | L13: =IF('03_Contratos'!AA13="","No",'03_Contratos'!AA13) | M13: =IF(AND(L13="Sí",K13="Sí"),"No","Sí") | N13: =IF('03_Contratos'!P13="","",'03_Contratos'!P13)
A14: C-10 | B14: Bodega sur con renta ajustada por inflación | C14: ='05_Plazo'!E14 | D14: =IF(N('03_Contratos'!U14)>0,"Sí","No") | E14: =IF(AND(C14<=12,D14="No"),"Sí","No") | F14: =IF('03_Contratos'!Y14="","No",'03_Contratos'!Y14) | G14: =IF('03_Contratos'!X14="","",'03_Contratos'!X14) | H14: =IF(OR(ISNUMBER(SEARCH("automovil",B14)),ISNUMBER(SEARCH("automóvil",B14)),ISNUMBER(SEARCH("vehiculo",B14)),ISNUMBER(SEARCH("vehículo",B14)),ISNUMBER(SEARCH("camioneta",B14)),ISNUMBER(SEARCH("coche",B14)),ISNUMBER(SEARCH("furgoneta",B14))),"Sí","No") | I14: =IF('03_Contratos'!Z14="","",'03_Contratos'!Z14) | J14: =IF(OR(F14="No",G14="",G14>'02_Parametros'!$B$9,H14="Sí",I14="No"),"No","Sí") | K14: =IF(OR(E14="Sí",J14="Sí"),"Sí","No") | L14: =IF('03_Contratos'!AA14="","No",'03_Contratos'!AA14) | M14: =IF(AND(L14="Sí",K14="Sí"),"No","Sí") | N14: =IF('03_Contratos'!P14="","",'03_Contratos'!P14)
A15: C-11 | B15: Oficina regional con reajuste sin detalle | C15: ='05_Plazo'!E15 | D15: =IF(N('03_Contratos'!U15)>0,"Sí","No") | E15: =IF(AND(C15<=12,D15="No"),"Sí","No") | F15: =IF('03_Contratos'!Y15="","No",'03_Contratos'!Y15) | G15: =IF('03_Contratos'!X15="","",'03_Contratos'!X15) | H15: =IF(OR(ISNUMBER(SEARCH("automovil",B15)),ISNUMBER(SEARCH("automóvil",B15)),ISNUMBER(SEARCH("vehiculo",B15)),ISNUMBER(SEARCH("vehículo",B15)),ISNUMBER(SEARCH("camioneta",B15)),ISNUMBER(SEARCH("coche",B15)),ISNUMBER(SEARCH("furgoneta",B15))),"Sí","No") | I15: =IF('03_Contratos'!Z15="","",'03_Contratos'!Z15) | J15: =IF(OR(F15="No",G15="",G15>'02_Parametros'!$B$9,H15="Sí",I15="No"),"No","Sí") | K15: =IF(OR(E15="Sí",J15="Sí"),"Sí","No") | L15: =IF('03_Contratos'!AA15="","No",'03_Contratos'!AA15) | M15: =IF(AND(L15="Sí",K15="Sí"),"No","Sí") | N15: =IF('03_Contratos'!P15="","",'03_Contratos'!P15)
A17: ⓘ Cómo se calcula esta hoja
A18: Columna | B18: Fórmula (Excel) | C18: Cómo se calcula (sencillo) | D18: Ejemplo con números reales | E18: De dónde viene | F18: Norma
A19: Plazo (meses) | B19: '='05_Plazo'!E5 | C19: Trae el plazo del arrendamiento (plazo no cancelable más la renovación razonablemente cierta) calculado en la hoja 05 (Plazo y opciones). | D19: Fila 1: 60 → 60 | E19: hoja «Plazo y opciones» | F19: —
A20: Opción de compra | B20: '=IF(N('03_Contratos'!U5)>0,"Sí","No") | C20: Marca «Sí» si el contrato tiene un precio de opción de compra mayor que cero en la hoja 03 (Universo de contratos); si no, «No». | D20: Fila 1: IF(N((vacío))>0; "Sí"; "No") → No | E20: hoja «Universo de contratos» | F20: —
A21: Corto plazo (≤ 12 m, sin opción) | B21: '=IF(AND(C5<=12,D5="No"),"Sí","No") | C21: Marca «Sí» cuando el plazo del arrendamiento es de 12 meses o menos y el contrato no tiene opción de compra; de lo contrario, «No». | D21: Fila 1: IF(AND(60<=12; «No»="No"); "Sí"; "No") → No | E21: «Plazo (meses)» (esta hoja), «Opción de compra» (esta hoja) | F21: —
A22: Bajo valor declarado | B22: '=IF('03_Contratos'!Y5="","No",'03_Contratos'!Y5) | C22: Trae de la hoja 03 (Universo de contratos) si el cliente declaró el activo como de bajo valor; si no lo indicó, se toma «No». | D22: Fila 1: IF((vacío)=""; "No"; (vacío)) → No | E22: hoja «Universo de contratos» | F22: —
A23: Valor del activo nuevo (B3) | B23: '=IF('03_Contratos'!X5="","",'03_Contratos'!X5) | C23: Trae de la hoja 03 el valor del activo en estado nuevo; si falta queda en blanco y el contrato no puede calificar como de bajo valor. | D23: Fila 1: IF((vacío)=""; ""; (vacío)) → (en blanco) | E23: hoja «Universo de contratos» | F23: —
A24: Automóvil (B6) | B24: '=IF(OR(ISNUMBER(SEARCH("automovil",B5)),ISNUMBER(SEARCH("automóvil",B5)),ISNUMBER(SEARCH("vehiculo",B5)),ISNUMBER(SEARCH("vehículo",B5)),ISNUMBER(SEARCH("camioneta",B5)),ISNUMBER(SEARCH("coche",B5)),ISNUMBER(SEARCH("furgoneta",B5))),"Sí","No") | C24: Marca «Sí» si la descripción del activo contiene palabras como automóvil, vehículo, camioneta, coche o furgoneta; esos activos no califican como de bajo valor. | D24: Fila 1: IF(OR(ISNUMBER(SEARCH("automovil"; «Local comercial matriz»)); ISNUMBER(SEARCH("automóvil"; «Local comercial matriz»)); ISNUMBER(SEARCH("vehiculo"; «Local comercial matriz»)); ISNUMBER(SEARCH("vehículo"; «Local comercial matriz»)); ISNUMBER(SEARCH("camioneta"; «Local comercial matriz»)); ISNUMBER(SEARCH("coche"; «Local comercial matriz»)); ISNUMBER(SEARCH("furgoneta"; «Local comercial matriz»))); "Sí"; "No") → No | E24: «Activo» (esta hoja) | F24: —
A25: Uso independiente y sin subarriendo (B5, B7) | B25: '=IF('03_Contratos'!Z5="","",'03_Contratos'!Z5) | C25: Trae la respuesta del cliente en la hoja 03 sobre si el activo se usa por sí solo, sin depender de otros activos, y no se subarrienda; en blanco si no respondió. | D25: Fila 1: IF((vacío)=""; ""; (vacío)) → (en blanco) | E25: hoja «Universo de contratos» | F25: —
A26: Bajo valor elegible (B3, B5–B7) | B26: '=IF(OR(F5="No",G5="",G5>'02_Parametros'!$B$9,H5="Sí",I5="No"),"No","Sí") | C26: Es «Sí» solo si el cliente lo declaró de bajo valor, informó el valor del activo nuevo, ese valor no pasa del límite de la hoja 02 (Parámetros), no es un automóvil y el uso independiente no es «No». | D26: Fila 1: IF(OR(«No»="No"; (vacío)=""; (vacío)>5.000,00; «No»="Sí"; (vacío)="No"); "No"; "Sí") → No | E26: «Bajo valor declarado» (esta hoja), «Valor del activo nuevo (B3)» (esta hoja), «Automóvil (B6)» (esta hoja), «Uso independiente y sin subarriendo (B5, B7)» (esta hoja), hoja «Parámetros» | F26: —
A27: Exención elegible (5) | B27: '=IF(OR(E5="Sí",J5="Sí"),"Sí","No") | C27: Marca «Sí» si el contrato califica como de corto plazo o como de bajo valor elegible; si no califica por ninguna de las dos vías, «No». | D27: Fila 1: IF(OR(«No»="Sí"; «No»="Sí"); "Sí"; "No") → No | E27: «Corto plazo (≤ 12 m, sin opción)» (esta hoja), «Bajo valor elegible (B3, B5–B7)» (esta hoja) | F27: —
A28: Exención aplicada por el cliente | B28: '=IF('03_Contratos'!AA5="","No",'03_Contratos'!AA5) | C28: Trae de la hoja 03 (Universo de contratos) si el cliente aplicó la exención y no reconoció el arrendamiento; si no lo indicó, se toma «No». | D28: Fila 1: IF((vacío)=""; "No"; (vacío)) → No | E28: hoja «Universo de contratos» | F28: —
A29: Reconoce pasivo | B29: '=IF(AND(L5="Sí",K5="Sí"),"No","Sí") | C29: Solo es «No» cuando el cliente aplicó la exención y además es elegible; en cualquier otro caso el contrato debe reconocerse en balance («Sí»). | D29: Fila 1: IF(AND(«No»="Sí"; «No»="Sí"); "No"; "Sí") → Sí | E29: «Exención aplicada por el cliente» (esta hoja), «Exención elegible (5)» (esta hoja) | F29: —
A30: Tipo de tasa (26) | B30: '=IF('03_Contratos'!P5="","",'03_Contratos'!P5) | C30: Trae de la hoja 03 (Universo de contratos) si la tasa del contrato es implícita o incremental; en blanco si no se informó. | D30: Fila 1: IF(«Incremental»=""; ""; «Incremental») → Incremental | E30: hoja «Universo de contratos» | F30: —

Sheet 05_Plazo
A1: Plazo y opciones | H1: ⟵ Inicio | I1: ◀ Anterior | J1: Siguiente ▶
A2: Arrendamientos · Cliente de muestra S.A. · corte 2025-12-31
A4: Contrato | B4: Plazo no cancelable (meses) | C4: Renovación razonablemente cierta | D4: Meses de renovación | E4: Plazo del arrendamiento (18) | F4: Plazo usado por el cliente | G4: Meses por período | H4: Períodos | I4: Meses transcurridos al corte | J4: Meses de depreciación (32 / 20.12)
A5: C-01 | B5: ='03_Contratos'!D5 | C5: =IF('03_Contratos'!F5="","",'03_Contratos'!F5) | D5: =N('03_Contratos'!E5) | E5: =B5+IF(C5="Sí",D5,0) | F5: =IF('03_Contratos'!G5="","",'03_Contratos'!G5) | G5: =IF('03_Contratos'!I5="Mensual",1,IF('03_Contratos'!I5="Trimestral",3,IF('03_Contratos'!I5="Semestral",6,12))) | H5: =E5/G5 | I5: =DATEDIF('03_Contratos'!C5,'02_Parametros'!$B$5+1,"m") | J5: =IF('03_Contratos'!V5="Sí",IF('03_Contratos'!W5="",E5,'03_Contratos'!W5),IF('03_Contratos'!W5="",E5,MIN(E5,'03_Contratos'!W5)))
A6: C-02 | B6: ='03_Contratos'!D6 | C6: =IF('03_Contratos'!F6="","",'03_Contratos'!F6) | D6: =N('03_Contratos'!E6) | E6: =B6+IF(C6="Sí",D6,0) | F6: =IF('03_Contratos'!G6="","",'03_Contratos'!G6) | G6: =IF('03_Contratos'!I6="Mensual",1,IF('03_Contratos'!I6="Trimestral",3,IF('03_Contratos'!I6="Semestral",6,12))) | H6: =E6/G6 | I6: =DATEDIF('03_Contratos'!C6,'02_Parametros'!$B$5+1,"m") | J6: =IF('03_Contratos'!V6="Sí",IF('03_Contratos'!W6="",E6,'03_Contratos'!W6),IF('03_Contratos'!W6="",E6,MIN(E6,'03_Contratos'!W6)))
A7: C-03 | B7: ='03_Contratos'!D7 | C7: =IF('03_Contratos'!F7="","",'03_Contratos'!F7) | D7: =N('03_Contratos'!E7) | E7: =B7+IF(C7="Sí",D7,0) | F7: =IF('03_Contratos'!G7="","",'03_Contratos'!G7) | G7: =IF('03_Contratos'!I7="Mensual",1,IF('03_Contratos'!I7="Trimestral",3,IF('03_Contratos'!I7="Semestral",6,12))) | H7: =E7/G7 | I7: =DATEDIF('03_Contratos'!C7,'02_Parametros'!$B$5+1,"m") | J7: =IF('03_Contratos'!V7="Sí",IF('03_Contratos'!W7="",E7,'03_Contratos'!W7),IF('03_Contratos'!W7="",E7,MIN(E7,'03_Contratos'!W7)))
A8: C-04 | B8: ='03_Contratos'!D8 | C8: =IF('03_Contratos'!F8="","",'03_Contratos'!F8) | D8: =N('03_Contratos'!E8) | E8: =B8+IF(C8="Sí",D8,0) | F8: =IF('03_Contratos'!G8="","",'03_Contratos'!G8) | G8: =IF('03_Contratos'!I8="Mensual",1,IF('03_Contratos'!I8="Trimestral",3,IF('03_Contratos'!I8="Semestral",6,12))) | H8: =E8/G8 | I8: =DATEDIF('03_Contratos'!C8,'02_Parametros'!$B$5+1,"m") | J8: =IF('03_Contratos'!V8="Sí",IF('03_Contratos'!W8="",E8,'03_Contratos'!W8),IF('03_Contratos'!W8="",E8,MIN(E8,'03_Contratos'!W8)))
A9: C-05 | B9: ='03_Contratos'!D9 | C9: =IF('03_Contratos'!F9="","",'03_Contratos'!F9) | D9: =N('03_Contratos'!E9) | E9: =B9+IF(C9="Sí",D9,0) | F9: =IF('03_Contratos'!G9="","",'03_Contratos'!G9) | G9: =IF('03_Contratos'!I9="Mensual",1,IF('03_Contratos'!I9="Trimestral",3,IF('03_Contratos'!I9="Semestral",6,12))) | H9: =E9/G9 | I9: =DATEDIF('03_Contratos'!C9,'02_Parametros'!$B$5+1,"m") | J9: =IF('03_Contratos'!V9="Sí",IF('03_Contratos'!W9="",E9,'03_Contratos'!W9),IF('03_Contratos'!W9="",E9,MIN(E9,'03_Contratos'!W9)))
A10: C-06 | B10: ='03_Contratos'!D10 | C10: =IF('03_Contratos'!F10="","",'03_Contratos'!F10) | D10: =N('03_Contratos'!E10) | E10: =B10+IF(C10="Sí",D10,0) | F10: =IF('03_Contratos'!G10="","",'03_Contratos'!G10) | G10: =IF('03_Contratos'!I10="Mensual",1,IF('03_Contratos'!I10="Trimestral",3,IF('03_Contratos'!I10="Semestral",6,12))) | H10: =E10/G10 | I10: =DATEDIF('03_Contratos'!C10,'02_Parametros'!$B$5+1,"m") | J10: =IF('03_Contratos'!V10="Sí",IF('03_Contratos'!W10="",E10,'03_Contratos'!W10),IF('03_Contratos'!W10="",E10,MIN(E10,'03_Contratos'!W10)))
A11: C-07 | B11: ='03_Contratos'!D11 | C11: =IF('03_Contratos'!F11="","",'03_Contratos'!F11) | D11: =N('03_Contratos'!E11) | E11: =B11+IF(C11="Sí",D11,0) | F11: =IF('03_Contratos'!G11="","",'03_Contratos'!G11) | G11: =IF('03_Contratos'!I11="Mensual",1,IF('03_Contratos'!I11="Trimestral",3,IF('03_Contratos'!I11="Semestral",6,12))) | H11: =E11/G11 | I11: =DATEDIF('03_Contratos'!C11,'02_Parametros'!$B$5+1,"m") | J11: =IF('03_Contratos'!V11="Sí",IF('03_Contratos'!W11="",E11,'03_Contratos'!W11),IF('03_Contratos'!W11="",E11,MIN(E11,'03_Contratos'!W11)))
A12: C-08 | B12: ='03_Contratos'!D12 | C12: =IF('03_Contratos'!F12="","",'03_Contratos'!F12) | D12: =N('03_Contratos'!E12) | E12: =B12+IF(C12="Sí",D12,0) | F12: =IF('03_Contratos'!G12="","",'03_Contratos'!G12) | G12: =IF('03_Contratos'!I12="Mensual",1,IF('03_Contratos'!I12="Trimestral",3,IF('03_Contratos'!I12="Semestral",6,12))) | H12: =E12/G12 | I12: =DATEDIF('03_Contratos'!C12,'02_Parametros'!$B$5+1,"m") | J12: =IF('03_Contratos'!V12="Sí",IF('03_Contratos'!W12="",E12,'03_Contratos'!W12),IF('03_Contratos'!W12="",E12,MIN(E12,'03_Contratos'!W12)))
A13: C-09 | B13: ='03_Contratos'!D13 | C13: =IF('03_Contratos'!F13="","",'03_Contratos'!F13) | D13: =N('03_Contratos'!E13) | E13: =B13+IF(C13="Sí",D13,0) | F13: =IF('03_Contratos'!G13="","",'03_Contratos'!G13) | G13: =IF('03_Contratos'!I13="Mensual",1,IF('03_Contratos'!I13="Trimestral",3,IF('03_Contratos'!I13="Semestral",6,12))) | H13: =E13/G13 | I13: =DATEDIF('03_Contratos'!C13,'02_Parametros'!$B$5+1,"m") | J13: =IF('03_Contratos'!V13="Sí",IF('03_Contratos'!W13="",E13,'03_Contratos'!W13),IF('03_Contratos'!W13="",E13,MIN(E13,'03_Contratos'!W13)))
A14: C-10 | B14: ='03_Contratos'!D14 | C14: =IF('03_Contratos'!F14="","",'03_Contratos'!F14) | D14: =N('03_Contratos'!E14) | E14: =B14+IF(C14="Sí",D14,0) | F14: =IF('03_Contratos'!G14="","",'03_Contratos'!G14) | G14: =IF('03_Contratos'!I14="Mensual",1,IF('03_Contratos'!I14="Trimestral",3,IF('03_Contratos'!I14="Semestral",6,12))) | H14: =E14/G14 | I14: =DATEDIF('03_Contratos'!C14,'02_Parametros'!$B$5+1,"m") | J14: =IF('03_Contratos'!V14="Sí",IF('03_Contratos'!W14="",E14,'03_Contratos'!W14),IF('03_Contratos'!W14="",E14,MIN(E14,'03_Contratos'!W14)))
A15: C-11 | B15: ='03_Contratos'!D15 | C15: =IF('03_Contratos'!F15="","",'03_Contratos'!F15) | D15: =N('03_Contratos'!E15) | E15: =B15+IF(C15="Sí",D15,0) | F15: =IF('03_Contratos'!G15="","",'03_Contratos'!G15) | G15: =IF('03_Contratos'!I15="Mensual",1,IF('03_Contratos'!I15="Trimestral",3,IF('03_Contratos'!I15="Semestral",6,12))) | H15: =E15/G15 | I15: =DATEDIF('03_Contratos'!C15,'02_Parametros'!$B$5+1,"m") | J15: =IF('03_Contratos'!V15="Sí",IF('03_Contratos'!W15="",E15,'03_Contratos'!W15),IF('03_Contratos'!W15="",E15,MIN(E15,'03_Contratos'!W15)))
A17: ⓘ Cómo se calcula esta hoja
A18: Columna | B18: Fórmula (Excel) | C18: Cómo se calcula (sencillo) | D18: Ejemplo con números reales | E18: De dónde viene | F18: Norma
A19: Plazo no cancelable (meses) | B19: '='03_Contratos'!D5 | C19: Trae el plazo no cancelable del contrato, en meses, de la hoja 03 (Universo de contratos). | D19: Fila 1: 36,00 → 36 | E19: hoja «Universo de contratos» | F19: —
A20: Renovación razonablemente cierta | B20: '=IF('03_Contratos'!F5="","",'03_Contratos'!F5) | C20: Trae de la hoja 03 (Universo de contratos) si es razonablemente cierto que se ejercerá la renovación; en blanco si no se informó. | D20: Fila 1: IF(«Sí»=""; ""; «Sí») → Sí | E20: hoja «Universo de contratos» | F20: —
A21: Meses de renovación | B21: '=N('03_Contratos'!E5) | C21: Trae los meses de la opción de renovación de la hoja 03 (Universo de contratos); si no hay dato, cuenta cero. | D21: Fila 1: N(24,00) → 24 | E21: hoja «Universo de contratos» | F21: —
A22: Plazo del arrendamiento (18) | B22: '=B5+IF(C5="Sí",D5,0) | C22: Suma al plazo no cancelable los meses de renovación solo cuando la renovación es razonablemente cierta («Sí»); si no, el plazo es solo el no cancelable. | D22: Fila 1: 36+IF(«Sí»="Sí"; 24; 0) → 60 | E22: «Plazo no cancelable (meses)» (esta hoja), «Renovación razonablemente cierta» (esta hoja), «Meses de renovación» (esta hoja) | F22: —
A23: Plazo usado por el cliente | B23: '=IF('03_Contratos'!G5="","",'03_Contratos'!G5) | C23: Trae de la hoja 03 (Universo de contratos) el plazo en meses que usó el cliente, para compararlo con el recalculado; en blanco si no se informó. | D23: Fila 1: IF(36,00=""; ""; 36,00) → 36 | E23: hoja «Universo de contratos» | F23: —
A24: Meses por período | B24: '=IF('03_Contratos'!I5="Mensual",1,IF('03_Contratos'!I5="Trimestral",3,IF('03_Contratos'!I5="Semestral",6,12))) | C24: Convierte la periodicidad de pago de la hoja 03 en meses: mensual 1, trimestral 3, semestral 6 y cualquier otra (anual) 12. | D24: Fila 1: IF(«Mensual»="Mensual"; 1; IF(«Mensual»="Trimestral"; 3; IF(«Mensual»="Semestral"; 6; 12))) → 1 | E24: hoja «Universo de contratos» | F24: —
A25: Períodos | B25: '=E5/G5 | C25: Divide el plazo del arrendamiento entre los meses por período: es el número de cuotas del contrato. | D25: Fila 1: 60/1 → 60 | E25: «Plazo del arrendamiento (18)» (esta hoja), «Meses por período» (esta hoja) | F25: —
A26: Meses transcurridos al corte | B26: '=DATEDIF('03_Contratos'!C5,'02_Parametros'!$B$5+1,"m") | C26: Cuenta los meses completos desde la fecha de comienzo (hoja 03) hasta el día siguiente a la fecha de corte de la hoja 02 (Parámetros). | D26: Fila 1: DATEDIF(«2024-01-01»; «2025-12-31»+1; "m") → 24 | E26: hoja «Universo de contratos», hoja «Parámetros» | F26: —
A27: Meses de depreciación (32 / 20.12) | B27: '=IF('03_Contratos'!V5="Sí",IF('03_Contratos'!W5="",E5,'03_Contratos'!W5),IF('03_Contratos'!W5="",E5,MIN(E5,'03_Contratos'!W5))) | C27: Si la compra es razonablemente cierta, usa la vida útil del activo (o el plazo si falta); si no, el menor entre el plazo del arrendamiento y la vida útil (o el plazo si no hay vida útil). | D27: Fila 1: IF((vacío)="Sí"; IF((vacío)=""; 60; (vacío)); IF((vacío)=""; 60; MIN(60; (vacío)))) → 60 | E27: «Plazo del arrendamiento (18)» (esta hoja), hoja «Universo de contratos» | F27: —

Sheet 06_Medicion_inicial
A1: Medición inicial: pasivo y activo | H1: ⟵ Inicio | I1: ◀ Anterior | J1: Siguiente ▶
A2: Arrendamientos · Cliente de muestra S.A. · corte 2025-12-31
A4: Contrato | B4: Tipo de tasa | C4: Tasa anual (%) | D4: Tasa periódica | E4: Pago al inicio (1) / al final (0) | F4: Opción de compra incluida (27 d) | G4: VP de los pagos | H4: Valor razonable | I4: Base de medición (26) | J4: Tasa usada en la tabla | K4: Pago en el comienzo | L4: Pasivo inicial | M4: Pagos anticipados | N4: Costos directos iniciales | O4: Desmantelamiento | P4: Incentivos | Q4: Derecho de uso (24)
A5: C-01 | B5: =IF('03_Contratos'!P5="","",'03_Contratos'!P5) | C5: ='03_Contratos'!O5 | D5: =IF('02_Parametros'!$B$6="Nominal anual",C5/100*'05_Plazo'!G5/12,(1+C5/100)^('05_Plazo'!G5/12)-1) | E5: =IF('03_Contratos'!J5="Inicio",1,0) | F5: =IF('03_Contratos'!V5="Sí",N('03_Contratos'!U5),0) | G5: =PV(D5,'05_Plazo'!H5,-'07_Pagos_variables'!G5,-F5,E5) | H5: =IF('03_Contratos'!X5="","",'03_Contratos'!X5) | I5: =G5 | J5: =D5 | K5: =E5*'07_Pagos_variables'!G5 | L5: =I5-K5 | M5: =N('03_Contratos'!Q5) | N5: =N('03_Contratos'!R5) | O5: =N('03_Contratos'!S5) | P5: =N('03_Contratos'!T5) | Q5: =L5+K5+M5+N5+O5-P5
A6: C-02 | B6: =IF('03_Contratos'!P6="","",'03_Contratos'!P6) | C6: ='03_Contratos'!O6 | D6: =IF('02_Parametros'!$B$6="Nominal anual",C6/100*'05_Plazo'!G6/12,(1+C6/100)^('05_Plazo'!G6/12)-1) | E6: =IF('03_Contratos'!J6="Inicio",1,0) | F6: =IF('03_Contratos'!V6="Sí",N('03_Contratos'!U6),0) | G6: =PV(D6,'05_Plazo'!H6,-'07_Pagos_variables'!G6,-F6,E6) | H6: =IF('03_Contratos'!X6="","",'03_Contratos'!X6) | I6: =G6 | J6: =D6 | K6: =E6*'07_Pagos_variables'!G6 | L6: =I6-K6 | M6: =N('03_Contratos'!Q6) | N6: =N('03_Contratos'!R6) | O6: =N('03_Contratos'!S6) | P6: =N('03_Contratos'!T6) | Q6: =L6+K6+M6+N6+O6-P6
A7: C-03 | B7: =IF('03_Contratos'!P7="","",'03_Contratos'!P7) | C7: ='03_Contratos'!O7 | D7: =IF('02_Parametros'!$B$6="Nominal anual",C7/100*'05_Plazo'!G7/12,(1+C7/100)^('05_Plazo'!G7/12)-1) | E7: =IF('03_Contratos'!J7="Inicio",1,0) | F7: =IF('03_Contratos'!V7="Sí",N('03_Contratos'!U7),0) | G7: =PV(D7,'05_Plazo'!H7,-'07_Pagos_variables'!G7,-F7,E7) | H7: =IF('03_Contratos'!X7="","",'03_Contratos'!X7) | I7: =G7 | J7: =D7 | K7: =E7*'07_Pagos_variables'!G7 | L7: =I7-K7 | M7: =N('03_Contratos'!Q7) | N7: =N('03_Contratos'!R7) | O7: =N('03_Contratos'!S7) | P7: =N('03_Contratos'!T7) | Q7: =L7+K7+M7+N7+O7-P7
A8: C-04 | B8: =IF('03_Contratos'!P8="","",'03_Contratos'!P8) | C8: ='03_Contratos'!O8 | D8: =IF('02_Parametros'!$B$6="Nominal anual",C8/100*'05_Plazo'!G8/12,(1+C8/100)^('05_Plazo'!G8/12)-1) | E8: =IF('03_Contratos'!J8="Inicio",1,0) | F8: =IF('03_Contratos'!V8="Sí",N('03_Contratos'!U8),0) | G8: =PV(D8,'05_Plazo'!H8,-'07_Pagos_variables'!G8,-F8,E8) | H8: =IF('03_Contratos'!X8="","",'03_Contratos'!X8) | I8: =G8 | J8: =D8 | K8: =E8*'07_Pagos_variables'!G8 | L8: =I8-K8 | M8: =N('03_Contratos'!Q8) | N8: =N('03_Contratos'!R8) | O8: =N('03_Contratos'!S8) | P8: =N('03_Contratos'!T8) | Q8: =L8+K8+M8+N8+O8-P8
A9: C-05 | B9: =IF('03_Contratos'!P9="","",'03_Contratos'!P9) | C9: ='03_Contratos'!O9 | D9: =IF('02_Parametros'!$B$6="Nominal anual",C9/100*'05_Plazo'!G9/12,(1+C9/100)^('05_Plazo'!G9/12)-1) | E9: =IF('03_Contratos'!J9="Inicio",1,0) | F9: =IF('03_Contratos'!V9="Sí",N('03_Contratos'!U9),0) | G9: =PV(D9,'05_Plazo'!H9,-'07_Pagos_variables'!G9,-F9,E9) | H9: =IF('03_Contratos'!X9="","",'03_Contratos'!X9) | I9: =G9 | J9: =D9 | K9: =E9*'07_Pagos_variables'!G9 | L9: =I9-K9 | M9: =N('03_Contratos'!Q9) | N9: =N('03_Contratos'!R9) | O9: =N('03_Contratos'!S9) | P9: =N('03_Contratos'!T9) | Q9: =L9+K9+M9+N9+O9-P9
A10: C-06 | B10: =IF('03_Contratos'!P10="","",'03_Contratos'!P10) | C10: ='03_Contratos'!O10 | D10: =IF('02_Parametros'!$B$6="Nominal anual",C10/100*'05_Plazo'!G10/12,(1+C10/100)^('05_Plazo'!G10/12)-1) | E10: =IF('03_Contratos'!J10="Inicio",1,0) | F10: =IF('03_Contratos'!V10="Sí",N('03_Contratos'!U10),0) | G10: =PV(D10,'05_Plazo'!H10,-'07_Pagos_variables'!G10,-F10,E10) | H10: =IF('03_Contratos'!X10="","",'03_Contratos'!X10) | I10: =G10 | J10: =D10 | K10: =E10*'07_Pagos_variables'!G10 | L10: =I10-K10 | M10: =N('03_Contratos'!Q10) | N10: =N('03_Contratos'!R10) | O10: =N('03_Contratos'!S10) | P10: =N('03_Contratos'!T10) | Q10: =L10+K10+M10+N10+O10-P10
A11: C-07 | B11: =IF('03_Contratos'!P11="","",'03_Contratos'!P11) | C11: ='03_Contratos'!O11 | D11: =IF('02_Parametros'!$B$6="Nominal anual",C11/100*'05_Plazo'!G11/12,(1+C11/100)^('05_Plazo'!G11/12)-1) | E11: =IF('03_Contratos'!J11="Inicio",1,0) | F11: =IF('03_Contratos'!V11="Sí",N('03_Contratos'!U11),0) | G11: =PV(D11,'05_Plazo'!H11,-'07_Pagos_variables'!G11,-F11,E11) | H11: =IF('03_Contratos'!X11="","",'03_Contratos'!X11) | I11: =G11 | J11: =D11 | K11: =E11*'07_Pagos_variables'!G11 | L11: =I11-K11 | M11: =N('03_Contratos'!Q11) | N11: =N('03_Contratos'!R11) | O11: =N('03_Contratos'!S11) | P11: =N('03_Contratos'!T11) | Q11: =L11+K11+M11+N11+O11-P11
A12: C-08 | B12: =IF('03_Contratos'!P12="","",'03_Contratos'!P12) | C12: ='03_Contratos'!O12 | D12: =IF('02_Parametros'!$B$6="Nominal anual",C12/100*'05_Plazo'!G12/12,(1+C12/100)^('05_Plazo'!G12/12)-1) | E12: =IF('03_Contratos'!J12="Inicio",1,0) | F12: =IF('03_Contratos'!V12="Sí",N('03_Contratos'!U12),0) | G12: =PV(D12,'05_Plazo'!H12,-'07_Pagos_variables'!G12,-F12,E12) | H12: =IF('03_Contratos'!X12="","",'03_Contratos'!X12) | I12: =G12 | J12: =D12 | K12: =E12*'07_Pagos_variables'!G12 | L12: =I12-K12 | M12: =N('03_Contratos'!Q12) | N12: =N('03_Contratos'!R12) | O12: =N('03_Contratos'!S12) | P12: =N('03_Contratos'!T12) | Q12: ='13_Venta_arr_posterior'!I12
A13: C-09 | B13: =IF('03_Contratos'!P13="","",'03_Contratos'!P13) | C13: ='03_Contratos'!O13 | D13: =IF('02_Parametros'!$B$6="Nominal anual",C13/100*'05_Plazo'!G13/12,(1+C13/100)^('05_Plazo'!G13/12)-1) | E13: =IF('03_Contratos'!J13="Inicio",1,0) | F13: =IF('03_Contratos'!V13="Sí",N('03_Contratos'!U13),0) | G13: =PV(D13,'05_Plazo'!H13,-'07_Pagos_variables'!G13,-F13,E13) | H13: =IF('03_Contratos'!X13="","",'03_Contratos'!X13) | I13: =G13 | J13: =D13 | K13: =E13*'07_Pagos_variables'!G13 | L13: =I13-K13 | M13: =N('03_Contratos'!Q13) | N13: =N('03_Contratos'!R13) | O13: =N('03_Contratos'!S13) | P13: =N('03_Contratos'!T13) | Q13: =L13+K13+M13+N13+O13-P13
A14: C-10 | B14: =IF('03_Contratos'!P14="","",'03_Contratos'!P14) | C14: ='03_Contratos'!O14 | D14: =IF('02_Parametros'!$B$6="Nominal anual",C14/100*'05_Plazo'!G14/12,(1+C14/100)^('05_Plazo'!G14/12)-1) | E14: =IF('03_Contratos'!J14="Inicio",1,0) | F14: =IF('03_Contratos'!V14="Sí",N('03_Contratos'!U14),0) | G14: =PV(D14,'05_Plazo'!H14,-'07_Pagos_variables'!G14,-F14,E14) | H14: =IF('03_Contratos'!X14="","",'03_Contratos'!X14) | I14: =G14 | J14: =D14 | K14: =E14*'07_Pagos_variables'!G14 | L14: =I14-K14 | M14: =N('03_Contratos'!Q14) | N14: =N('03_Contratos'!R14) | O14: =N('03_Contratos'!S14) | P14: =N('03_Contratos'!T14) | Q14: =L14+K14+M14+N14+O14-P14
A15: C-11 | B15: =IF('03_Contratos'!P15="","",'03_Contratos'!P15) | C15: ='03_Contratos'!O15 | D15: =IF('02_Parametros'!$B$6="Nominal anual",C15/100*'05_Plazo'!G15/12,(1+C15/100)^('05_Plazo'!G15/12)-1) | E15: =IF('03_Contratos'!J15="Inicio",1,0) | F15: =IF('03_Contratos'!V15="Sí",N('03_Contratos'!U15),0) | G15: =PV(D15,'05_Plazo'!H15,-'07_Pagos_variables'!G15,-F15,E15) | H15: =IF('03_Contratos'!X15="","",'03_Contratos'!X15) | I15: =G15 | J15: =D15 | K15: =E15*'07_Pagos_variables'!G15 | L15: =I15-K15 | M15: =N('03_Contratos'!Q15) | N15: =N('03_Contratos'!R15) | O15: =N('03_Contratos'!S15) | P15: =N('03_Contratos'!T15) | Q15: =L15+K15+M15+N15+O15-P15
A16: TOTAL | G16: =SUM(G5:G15) | L16: =SUM(L5:L15) | Q16: =SUM(Q5:Q15)
A18: ⓘ Cómo se calcula esta hoja
A19: Columna | B19: Fórmula (Excel) | C19: Cómo se calcula (sencillo) | D19: Ejemplo con números reales | E19: De dónde viene | F19: Norma
A20: Tipo de tasa | B20: '=IF('03_Contratos'!P5="","",'03_Contratos'!P5) | C20: Trae de la hoja 03 (Universo de contratos) si la tasa del contrato es implícita o incremental; en blanco si no se informó. | D20: Fila 1: IF(«Incremental»=""; ""; «Incremental») → Incremental | E20: hoja «Universo de contratos» | F20: —
A21: Tasa anual (%) | B21: '='03_Contratos'!O5 | C21: Trae la tasa anual del contrato, en porcentaje, de la hoja 03 (Universo de contratos). | D21: Fila 1: 12,00 → 12,00 | E21: hoja «Universo de contratos» | F21: —
A22: Tasa periódica | B22: '=IF('02_Parametros'!$B$6="Nominal anual",C5/100*'05_Plazo'!G5/12,(1+C5/100)^('05_Plazo'!G5/12)-1) | C22: Convierte la tasa anual en la tasa de cada período de pago con la convención de la hoja 02: nominal = tasa × meses ÷ 12; efectiva = (1 + tasa)^(meses ÷ 12) − 1, con los meses por período de la hoja 05. | D22: Fila 1: IF(«Efectiva anual»="Nominal anual"; 12,00/100*1/12; (1+12,00/100)^(1/12)-1) → 0,95 % | E22: «Tasa anual (%)» (esta hoja), hoja «Parámetros», hoja «Plazo y opciones» | F22: —
A23: Pago al inicio (1) / al final (0) | B23: '=IF('03_Contratos'!J5="Inicio",1,0) | C23: Pone 1 si el contrato se paga al inicio de cada período, según la hoja 03 (Universo de contratos), y 0 si se paga al final. | D23: Fila 1: IF(«Final»="Inicio"; 1; 0) → 0 | E23: hoja «Universo de contratos» | F23: —
A24: Opción de compra incluida (27 d) | B24: '=IF('03_Contratos'!V5="Sí",N('03_Contratos'!U5),0) | C24: Si la compra es razonablemente cierta, incluye el precio de la opción de compra de la hoja 03 (Universo de contratos); si no, pone 0. | D24: Fila 1: IF((vacío)="Sí"; N((vacío)); 0) → 0,00 | E24: hoja «Universo de contratos» | F24: —
A25: VP de los pagos | B25: '=PV(D5,'05_Plazo'!H5,-'07_Pagos_variables'!G5,-F5,E5) | C25: Descuenta con la tasa periódica (función VA de Excel) el pago usado en la medición (hoja 07) durante los períodos de la hoja 05, más la opción de compra incluida, según se pague al inicio o al final. | D25: Fila 1: PV(0,95 %; 60; -1.500,00; -0,00; 0) → 68.381,69 | E25: «Tasa periódica» (esta hoja), «Opción de compra incluida (27 d)» (esta hoja), «Pago al inicio (1) / al final (0)» (esta hoja), hoja «Plazo y opciones», hoja «Pago base, componente indexado y pagos variables» | F25: —
A26: Valor razonable | B26: '=IF('03_Contratos'!X5="","",'03_Contratos'!X5) | C26: Trae el valor razonable del activo de la hoja 03 (Universo de contratos); en blanco si no se informó. | D26: Fila 1: IF((vacío)=""; ""; (vacío)) → (en blanco) | E26: hoja «Universo de contratos» | F26: —
A27: Base de medición (26) | B27: '=G5 | C27: En NIIF completas la base de medición es directamente el VP de los pagos calculado en esta misma hoja. | D27: Fila 1: 68.381,69 → 68.381,69 | E27: «VP de los pagos» (esta hoja) | F27: —
A28: Tasa usada en la tabla | B28: '=D5 | C28: Es la misma tasa periódica del contrato; con ella se calcula el interés en la hoja 09 (Tabla de amortización). | D28: Fila 1: 0,95 % → 0,95 % | E28: «Tasa periódica» (esta hoja) | F28: —
A29: Pago en el comienzo | B29: '=E5*'07_Pagos_variables'!G5 | C29: Si el pago es al inicio del período, es el primer pago (el usado en la medición, hoja 07), que se paga el mismo día del comienzo; si es al final, es 0. | D29: Fila 1: 0*1.500,00 → 0,00 | E29: «Pago al inicio (1) / al final (0)» (esta hoja), hoja «Pago base, componente indexado y pagos variables» | F29: —
A30: Pasivo inicial | B30: '=I5-K5 | C30: Resta a la base de medición el pago hecho en el comienzo: es el pasivo que queda por pagar al inicio del contrato. | D30: Fila 1: 68.381,69-0,00 → 68.381,69 | E30: «Base de medición (26)» (esta hoja), «Pago en el comienzo» (esta hoja) | F30: —
... A35: Derecho de uso (24) | B35: '=L5+K5+M5+N5+O5-P5 | C35: Pasivo inicial + pago en el comienzo + pagos anticipados + costos directos + desmantelamiento − incentivos. En una venta con arrendamiento posterior que se reconoce, trae en su lugar el derecho de uso conservado de la hoja 13. | D35: Fila 1: 68.381,69+0,00+0,00+0,00+0,00-0,00 → 68.381,69 | E35: «Pasivo inicial» (esta hoja), «Pago en el comienzo» (esta hoja), «Pagos anticipados» (esta hoja), «Costos directos iniciales» (esta hoja), «Desmantelamiento» (esta hoja), «Incentivos» (esta hoja) | F35: —

Sheet 07_Pagos_variables
A1: Pago base, componente indexado y pagos variables | H1: ⟵ Inicio | I1: ◀ Anterior | J1: Siguiente ▶
A2: Arrendamientos · Cliente de muestra S.A. · corte 2025-12-31
A4: Contrato | B4: Pago periódico total del contrato | C4: Ligado a un índice de inflación | D4: Índice o referencia | E4: Componente ligado al índice | F4: Pago base | G4: Pago usado en la medición del pasivo | H4: Tratamiento del componente indexado | I4: Marco que lo manda | J4: Pago variable no ligado a un índice (38 b) | K4: Períodos del ejercicio | L4: Gasto del ejercicio por pagos variables
A5: C-01 | B5: ='03_Contratos'!H5 | C5: =IF(OR('03_Contratos'!K5="Sí",'03_Contratos'!L5<>""),"Sí","No") | D5: =IF('03_Contratos'!M5="","",'03_Contratos'!M5) | E5: =IF(C5="No",0,IF('03_Contratos'!L5="","",'03_Contratos'!L5)) | F5: =IF(E5="","",B5-E5) | G5: =B5 | H5: Sin componente ligado a un índice | J5: =IF('03_Contratos'!N5="","",'03_Contratos'!N5) | K5: ='10_Pasivo_corte'!E5-'10_Pasivo_corte'!F5 | L5: =N(J5)*K5
A6: C-02 | B6: ='03_Contratos'!H6 | C6: =IF(OR('03_Contratos'!K6="Sí",'03_Contratos'!L6<>""),"Sí","No") | D6: =IF('03_Contratos'!M6="","",'03_Contratos'!M6) | E6: =IF(C6="No",0,IF('03_Contratos'!L6="","",'03_Contratos'!L6)) | F6: =IF(E6="","",B6-E6) | G6: =B6 | H6: Sin componente ligado a un índice | J6: =IF('03_Contratos'!N6="","",'03_Contratos'!N6) | K6: ='10_Pasivo_corte'!E6-'10_Pasivo_corte'!F6 | L6: =N(J6)*K6
A7: C-03 | B7: ='03_Contratos'!H7 | C7: =IF(OR('03_Contratos'!K7="Sí",'03_Contratos'!L7<>""),"Sí","No") | D7: =IF('03_Contratos'!M7="","",'03_Contratos'!M7) | E7: =IF(C7="No",0,IF('03_Contratos'!L7="","",'03_Contratos'!L7)) | F7: =IF(E7="","",B7-E7) | G7: =B7 | H7: Sin componente ligado a un índice | J7: =IF('03_Contratos'!N7="","",'03_Contratos'!N7) | K7: ='10_Pasivo_corte'!E7-'10_Pasivo_corte'!F7 | L7: =N(J7)*K7
A8: C-04 | B8: ='03_Contratos'!H8 | C8: =IF(OR('03_Contratos'!K8="Sí",'03_Contratos'!L8<>""),"Sí","No") | D8: =IF('03_Contratos'!M8="","",'03_Contratos'!M8) | E8: =IF(C8="No",0,IF('03_Contratos'!L8="","",'03_Contratos'!L8)) | F8: =IF(E8="","",B8-E8) | G8: =B8 | H8: Sin componente ligado a un índice | J8: =IF('03_Contratos'!N8="","",'03_Contratos'!N8) | K8: ='12_Gasto_lineal'!E8/'05_Plazo'!G8 | L8: =N(J8)*K8
A9: C-05 | B9: ='03_Contratos'!H9 | C9: =IF(OR('03_Contratos'!K9="Sí",'03_Contratos'!L9<>""),"Sí","No") | D9: =IF('03_Contratos'!M9="","",'03_Contratos'!M9) | E9: =IF(C9="No",0,IF('03_Contratos'!L9="","",'03_Contratos'!L9)) | F9: =IF(E9="","",B9-E9) | G9: =B9 | H9: Sin componente ligado a un índice | J9: =IF('03_Contratos'!N9="","",'03_Contratos'!N9) | K9: ='12_Gasto_lineal'!E9/'05_Plazo'!G9 | L9: =N(J9)*K9
A10: C-06 | B10: ='03_Contratos'!H10 | C10: =IF(OR('03_Contratos'!K10="Sí",'03_Contratos'!L10<>""),"Sí","No") | D10: =IF('03_Contratos'!M10="","",'03_Contratos'!M10) | E10: =IF(C10="No",0,IF('03_Contratos'!L10="","",'03_Contratos'!L10)) | F10: =IF(E10="","",B10-E10) | G10: =B10 | H10: Sin componente ligado a un índice | J10: =IF('03_Contratos'!N10="","",'03_Contratos'!N10) | K10: ='10_Pasivo_corte'!E10-'10_Pasivo_corte'!F10 | L10: =N(J10)*K10
A11: C-07 | B11: ='03_Contratos'!H11 | C11: =IF(OR('03_Contratos'!K11="Sí",'03_Contratos'!L11<>""),"Sí","No") | D11: =IF('03_Contratos'!M11="","",'03_Contratos'!M11) | E11: =IF(C11="No",0,IF('03_Contratos'!L11="","",'03_Contratos'!L11)) | F11: =IF(E11="","",B11-E11) | G11: =B11 | H11: Sin componente ligado a un índice | J11: =IF('03_Contratos'!N11="","",'03_Contratos'!N11) | K11: ='10_Pasivo_corte'!E11-'10_Pasivo_corte'!F11 | L11: =N(J11)*K11
A12: C-08 | B12: ='03_Contratos'!H12 | C12: =IF(OR('03_Contratos'!K12="Sí",'03_Contratos'!L12<>""),"Sí","No") | D12: =IF('03_Contratos'!M12="","",'03_Contratos'!M12) | E12: =IF(C12="No",0,IF('03_Contratos'!L12="","",'03_Contratos'!L12)) | F12: =IF(E12="","",B12-E12) | G12: =B12 | H12: Sin componente ligado a un índice | J12: =IF('03_Contratos'!N12="","",'03_Contratos'!N12) | K12: ='10_Pasivo_corte'!E12-'10_Pasivo_corte'!F12 | L12: =N(J12)*K12
A13: C-09 | B13: ='03_Contratos'!H13 | C13: =IF(OR('03_Contratos'!K13="Sí",'03_Contratos'!L13<>""),"Sí","No") | D13: =IF('03_Contratos'!M13="","",'03_Contratos'!M13) | E13: =IF(C13="No",0,IF('03_Contratos'!L13="","",'03_Contratos'!L13)) | F13: =IF(E13="","",B13-E13) | G13: =B13 | H13: Sin componente ligado a un índice | J13: =IF('03_Contratos'!N13="","",'03_Contratos'!N13) | K13: ='10_Pasivo_corte'!E13-'10_Pasivo_corte'!F13 | L13: =N(J13)*K13
A14: C-10 | B14: ='03_Contratos'!H14 | C14: =IF(OR('03_Contratos'!K14="Sí",'03_Contratos'!L14<>""),"Sí","No") | D14: =IF('03_Contratos'!M14="","",'03_Contratos'!M14) | E14: =IF(C14="No",0,IF('03_Contratos'!L14="","",'03_Contratos'!L14)) | F14: =IF(E14="","",B14-E14) | G14: =B14 | H14: Incluido en la medición del pasivo con el índice de la fecha de comienzo | I14: NIIF completas · NIIF 16 párr. 27 b y 28; se remide solo cuando cambian los flujos (42 b), con la tasa de descuento sin cambios (43) | J14: =IF('03_Contratos'!N14="","",'03_Contratos'!N14) | K14: ='10_Pasivo_corte'!E14-'10_Pasivo_corte'!F14 | L14: =N(J14)*K14
A15: C-11 | B15: ='03_Contratos'!H15 | C15: =IF(OR('03_Contratos'!K15="Sí",'03_Contratos'!L15<>""),"Sí","No") | D15: =IF('03_Contratos'!M15="","",'03_Contratos'!M15) | E15: =IF(C15="No",0,IF('03_Contratos'!L15="","",'03_Contratos'!L15)) | F15: =IF(E15="","",B15-E15) | G15: =B15 | H15: No medible: falta el importe del componente | I15: El pago base y el componente quedan vacíos hasta que el cliente informe el importe | J15: =IF('03_Contratos'!N15="","",'03_Contratos'!N15) | K15: ='10_Pasivo_corte'!E15-'10_Pasivo_corte'!F15 | L15: =N(J15)*K15
A16: TOTAL | B16: =SUM(B5:B15) | E16: =SUM(E5:E15) | F16: =SUM(F5:F15) | G16: =SUM(G5:G15) | J16: =SUM(J5:J15) | L16: =SUM(L5:L15)
A18: ⓘ Cómo se calcula esta hoja
A19: Columna | B19: Fórmula (Excel) | C19: Cómo se calcula (sencillo) | D19: Ejemplo con números reales | E19: De dónde viene | F19: Norma
A20: Pago periódico total del contrato | B20: '='03_Contratos'!H5 | C20: Trae de la hoja 03 (Universo de contratos) el pago periódico total, que incluye el componente ligado al índice. | D20: Fila 1: 1.500,00 → 1.500,00 | E20: hoja «Universo de contratos» | F20: —
A21: Ligado a un índice de inflación | B21: '=IF(OR('03_Contratos'!K5="Sí",'03_Contratos'!L5<>""),"Sí","No") | C21: Marca «Sí» si el cliente declaró en la hoja 03 que el pago se ajusta por un índice de inflación o informó el importe del componente indexado; si no, «No». | D21: Fila 1: IF(OR((vacío)="Sí"; (vacío)<>""); "Sí"; "No") → No | E21: hoja «Universo de contratos» | F21: —
A22: Índice o referencia | B22: '=IF('03_Contratos'!M5="","",'03_Contratos'!M5) | C22: Trae el nombre del índice o referencia del reajuste, de la hoja 03 (Universo de contratos); en blanco si no se informó. | D22: Fila 1: IF((vacío)=""; ""; (vacío)) → (en blanco) | E22: hoja «Universo de contratos» | F22: —
A23: Componente ligado al índice | B23: '=IF(C5="No",0,IF('03_Contratos'!L5="","",'03_Contratos'!L5)) | C23: Si el pago no está ligado a un índice es 0; si lo está, trae de la hoja 03 el importe por período del componente indexado, y queda en blanco si el cliente no lo informó. | D23: Fila 1: IF(«No»="No"; 0; IF((vacío)=""; ""; (vacío))) → 0,00 | E23: «Ligado a un índice de inflación» (esta hoja), hoja «Universo de contratos» | F23: —
A24: Pago base | B24: '=IF(E5="","",B5-E5) | C24: Resta del pago periódico total el componente ligado al índice; en blanco cuando ese componente no se pudo medir. | D24: Fila 1: IF(0,00=""; ""; 1.500,00-0,00) → 1.500,00 | E24: «Componente ligado al índice» (esta hoja), «Pago periódico total del contrato» (esta hoja) | F24: —
A25: Pago usado en la medición del pasivo | B25: '=B5 | C25: En NIIF completas el pasivo se mide con el pago periódico total, incluido el componente ligado al índice. | D25: Fila 1: 1.500,00 → 1.500,00 | E25: «Pago periódico total del contrato» (esta hoja) | F25: —
A26: Pago variable no ligado a un índice (38 b) | B26: '=IF('03_Contratos'!N5="","",'03_Contratos'!N5) | C26: Trae de la hoja 03 el pago variable del período que no depende de un índice (por ejemplo, por ventas o por uso); en blanco si no hay. | D26: Fila 1: IF((vacío)=""; ""; (vacío)) → (en blanco) | E26: hoja «Universo de contratos» | F26: —
A27: Períodos del ejercicio | B27: '='10_Pasivo_corte'!E5-'10_Pasivo_corte'!F5 | C27: Cuenta los períodos de pago del ejercicio: si el contrato se reconoce, períodos vencidos al corte menos los vencidos al inicio del año (hoja 10); si no, meses del contrato en el año (hoja 12) entre meses por período (hoja 05). | D27: Fila 1: 24-12 → 12,00 | E27: hoja «Pasivo al corte: corriente y no corriente» | F27: —
A28: Gasto del ejercicio por pagos variables | B28: '=N(J5)*K5 | C28: Multiplica el pago variable no ligado a un índice por los períodos del ejercicio (sin dato cuenta cero): es el gasto del año por pagos variables. | D28: Fila 1: N((vacío))*12,00 → 0,00 | E28: «Pago variable no ligado a un índice (38 b)» (esta hoja), «Períodos del ejercicio» (esta hoja) | F28: —

Sheet 08_Remedicion
A1: Remedición y modificaciones | H1: ⟵ Inicio | I1: ◀ Anterior | J1: Siguiente ▶
A2: Arrendamientos · Cliente de muestra S.A. · corte 2025-12-31
A4: Contrato | B4: Fecha del evento | C4: Tipo / nota | D4: Períodos al evento | E4: Plazo revisado (meses) | F4: Períodos revisados | G4: Pago revisado | H4: Tasa anual revisada (%) | I4: Tasa periódica revisada | J4: Pasivo antes del evento | K4: Pasivo remedido (40–45) | L4: Ajuste al pasivo y al derecho de uso | M4: Remedido por el cliente
A5: C-01 | C5: Sin evento
A6: C-02 | C6: Sin evento
A7: C-03 | C7: Sin evento
A8: C-04 | C8: Sin evento
A9: C-05 | C9: Sin evento
A10: C-06 | C10: Sin evento
A11: C-07 | B11: 45658 | C11: Modificación | D11: =INT(DATEDIF('03_Contratos'!C11,B11,"m")/'05_Plazo'!G11) | E11: =IF('03_Contratos'!AL11="",'05_Plazo'!E11,'03_Contratos'!AL11) | F11: =E11/'05_Plazo'!G11 | G11: =IF('03_Contratos'!AJ11="",'07_Pagos_variables'!G11,'03_Contratos'!AJ11) | H11: =IF('03_Contratos'!AK11="",'06_Medicion_inicial'!C11,'03_Contratos'!AK11) | I11: =IF('02_Parametros'!$B$6="Nominal anual",H11/100*'05_Plazo'!G11/12,(1+H11/100)^('05_Plazo'!G11/12)-1) | J11: =SUMIFS('09_Tabla_amortizacion'!$H$5:$H$264,'09_Tabla_amortizacion'!$A$5:$A$264,A11,'09_Tabla_amortizacion'!$B$5:$B$264,D11) | K11: =PV(I11,F11-D11,-G11,-'06_Medicion_inicial'!F11,'06_Medicion_inicial'!E11)-'06_Medicion_inicial'!E11*G11 | L11: =K11-J11 | M11: =IF('03_Contratos'!AM11="","",'03_Contratos'!AM11)
A12: C-08 | C12: Sin evento
A13: C-09 | C13: Sin evento
A14: C-10 | C14: Sin evento
A15: C-11 | C15: Sin evento
A16: TOTAL | L16: =SUM(L5:L15)
A18: ⓘ Cómo se calcula esta hoja
A19: Columna | B19: Fórmula (Excel) | C19: Cómo se calcula (sencillo) | D19: Ejemplo con números reales | E19: De dónde viene | F19: Norma
A20: Períodos al evento | B20: '=INT(DATEDIF('03_Contratos'!C11,B11,"m")/'05_Plazo'!G11) | C20: Cuenta los meses completos desde el comienzo (hoja 03) hasta la fecha del evento y los divide entre los meses por período (hoja 05), sin decimales: son las cuotas ya transcurridas. | D20: Fila 7: INT(DATEDIF(«2023-01-01»; «2025-01-01»; "m")/12) → 2 | E20: «Fecha del evento» (esta hoja), hoja «Universo de contratos», hoja «Plazo y opciones» | F20: —
A21: Plazo revisado (meses) | B21: '=IF('03_Contratos'!AL11="",'05_Plazo'!E11,'03_Contratos'!AL11) | C21: Toma el nuevo plazo total informado en la hoja 03; si no hay, mantiene el plazo del arrendamiento de la hoja 05. | D21: Fila 7: IF((vacío)=""; 60; (vacío)) → 60 | E21: hoja «Universo de contratos», hoja «Plazo y opciones» | F21: —
A22: Períodos revisados | B22: '=E11/'05_Plazo'!G11 | C22: Divide el plazo revisado entre los meses por período de la hoja 05: número total de cuotas después del evento. | D22: Fila 7: 60/12 → 5 | E22: «Plazo revisado (meses)» (esta hoja), hoja «Plazo y opciones» | F22: —
A23: Pago revisado | B23: '=IF('03_Contratos'!AJ11="",'07_Pagos_variables'!G11,'03_Contratos'!AJ11) | C23: Toma el nuevo pago periódico de la hoja 03; si no se informó, mantiene el pago usado en la medición de la hoja 07. | D23: Fila 7: IF(13.500,00=""; 12.000,00; 13.500,00) → 13.500,00 | E23: hoja «Universo de contratos», hoja «Pago base, componente indexado y pagos variables» | F23: —
A24: Tasa anual revisada (%) | B24: '=IF('03_Contratos'!AK11="",'06_Medicion_inicial'!C11,'03_Contratos'!AK11) | C24: Toma la tasa anual revisada de la hoja 03; si no se informó, mantiene la tasa anual original de la hoja 06. | D24: Fila 7: IF(9,00=""; 8,00; 9,00) → 9,00 | E24: hoja «Universo de contratos», hoja «Medición inicial: pasivo y activo» | F24: —
A25: Tasa periódica revisada | B25: '=IF('02_Parametros'!$B$6="Nominal anual",H11/100*'05_Plazo'!G11/12,(1+H11/100)^('05_Plazo'!G11/12)-1) | C25: Convierte la tasa anual revisada en tasa por período con la convención de la hoja 02 (nominal o efectiva) y los meses por período de la hoja 05. | D25: Fila 7: IF(«Efectiva anual»="Nominal anual"; 9,00/100*12/12; (1+9,00/100)^(12/12)-1) → 9,00 % | E25: «Tasa anual revisada (%)» (esta hoja), hoja «Parámetros», hoja «Plazo y opciones» | F25: —
A26: Pasivo antes del evento | B26: '=SUMIFS('09_Tabla_amortizacion'!$H$5:$H$264,'09_Tabla_amortizacion'!$A$5:$A$264,A11,'09_Tabla_amortizacion'!$B$5:$B$264,D11) | C26: Busca en la hoja 09 (Tabla de amortización) el saldo final de este contrato en el período del evento, antes de remedir. | D26: Fila 7: SUMIFS([«Saldo final» de «Tabla de amortización», 260 filas]; [«Contrato» de «Tabla de amortización», 260 filas]; «C-07»; [«Período» de «Tabla de amortización», 260 filas]; 2) → 30.925,16 | E26: «Contrato» (esta hoja), «Períodos al evento» (esta hoja), hoja «Tabla de amortización» | F26: —
A27: Pasivo remedido (40–45) | B27: '=PV(I11,F11-D11,-G11,-'06_Medicion_inicial'!F11,'06_Medicion_inicial'!E11)-'06_Medicion_inicial'!E11*G11 | C27: Descuenta con la tasa revisada las cuotas que faltan (períodos revisados − períodos al evento) con el pago revisado y la opción de compra de la hoja 06; si se paga al inicio, resta el pago que vence ese día. | D27: Fila 7: PV(9,00 %; 5-2; -13.500,00; -0,00; 0)-0*13.500,00 → 34.172,48 | E27: «Tasa periódica revisada» (esta hoja), «Períodos revisados» (esta hoja), «Períodos al evento» (esta hoja), «Pago revisado» (esta hoja), hoja «Medición inicial: pasivo y activo» | F27: —
A28: Ajuste al pasivo y al derecho de uso | B28: '=K11-J11 | C28: Resta el pasivo antes del evento del pasivo remedido: es lo que sube o baja el pasivo, y se lleva contra el derecho de uso. | D28: Fila 7: 34.172,48-30.925,16 → 3.247,31 | E28: «Pasivo remedido (40–45)» (esta hoja), «Pasivo antes del evento» (esta hoja) | F28: —
A29: Remedido por el cliente | B29: '=IF('03_Contratos'!AM11="","",'03_Contratos'!AM11) | C29: Trae de la hoja 03 (Universo de contratos) si el cliente registró la remedición del pasivo; en blanco si no lo indicó. | D29: Fila 7: IF(«No»=""; ""; «No») → No | E29: hoja «Universo de contratos» | F29: —

Sheet 09_Tabla_amortizacion
A1: Tabla de amortización | H1: ⟵ Inicio | I1: ◀ Anterior | J1: Siguiente ▶
A2: Arrendamientos · Cliente de muestra S.A. · corte 2025-12-31
A4: Contrato | B4: Período | C4: Vencimiento | D4: Tasa periódica | E4: Saldo inicial | F4: Interés (37) | G4: Pago | H4: Saldo final | I4: Remedición | J4: Saldo final ajustado
A5: C-01 | B5: 1 | C5: 45323 | D5: ='06_Medicion_inicial'!J5 | E5: ='06_Medicion_inicial'!L5 | F5: =E5*D5 | G5: =IF(B5<'05_Plazo'!H5,'07_Pagos_variables'!G5,IF(B5='05_Plazo'!H5,'06_Medicion_inicial'!F5+(1-'06_Medicion_inicial'!E5)*'07_Pagos_variables'!G5,0)) | H5: =E5+F5-G5 | I5: 0 | J5: =H5+I5
A6: C-01 | B6: 2 | C6: 45352 | D6: ='06_Medicion_inicial'!J5 | E6: =J5 | F6: =E6*D6 | G6: =IF(B6<'05_Plazo'!H5,'07_Pagos_variables'!G5,IF(B6='05_Plazo'!H5,'06_Medicion_inicial'!F5+(1-'06_Medicion_inicial'!E5)*'07_Pagos_variables'!G5,0)) | H6: =E6+F6-G6 | I6: 0 | J6: =H6+I6
A7: C-01 | B7: 3 | C7: 45383 | D7: ='06_Medicion_inicial'!J5 | E7: =J6 | F7: =E7*D7 | G7: =IF(B7<'05_Plazo'!H5,'07_Pagos_variables'!G5,IF(B7='05_Plazo'!H5,'06_Medicion_inicial'!F5+(1-'06_Medicion_inicial'!E5)*'07_Pagos_variables'!G5,0)) | H7: =E7+F7-G7 | I7: 0 | J7: =H7+I7
A8: C-01 | B8: 4 | C8: 45413 | D8: ='06_Medicion_inicial'!J5 | E8: =J7 | F8: =E8*D8 | G8: =IF(B8<'05_Plazo'!H5,'07_Pagos_variables'!G5,IF(B8='05_Plazo'!H5,'06_Medicion_inicial'!F5+(1-'06_Medicion_inicial'!E5)*'07_Pagos_variables'!G5,0)) | H8: =E8+F8-G8 | I8: 0 | J8: =H8+I8
A9: C-01 | B9: 5 | C9: 45444 | D9: ='06_Medicion_inicial'!J5 | E9: =J8 | F9: =E9*D9 | G9: =IF(B9<'05_Plazo'!H5,'07_Pagos_variables'!G5,IF(B9='05_Plazo'!H5,'06_Medicion_inicial'!F5+(1-'06_Medicion_inicial'!E5)*'07_Pagos_variables'!G5,0)) | H9: =E9+F9-G9 | I9: 0 | J9: =H9+I9
A10: C-01 | B10: 6 | C10: 45474 | D10: ='06_Medicion_inicial'!J5 | E10: =J9 | F10: =E10*D10 | G10: =IF(B10<'05_Plazo'!H5,'07_Pagos_variables'!G5,IF(B10='05_Plazo'!H5,'06_Medicion_inicial'!F5+(1-'06_Medicion_inicial'!E5)*'07_Pagos_variables'!G5,0)) | H10: =E10+F10-G10 | I10: 0 | J10: =H10+I10
A11: C-01 | B11: 7 | C11: 45505 | D11: ='06_Medicion_inicial'!J5 | E11: =J10 | F11: =E11*D11 | G11: =IF(B11<'05_Plazo'!H5,'07_Pagos_variables'!G5,IF(B11='05_Plazo'!H5,'06_Medicion_inicial'!F5+(1-'06_Medicion_inicial'!E5)*'07_Pagos_variables'!G5,0)) | H11: =E11+F11-G11 | I11: 0 | J11: =H11+I11
A12: C-01 | B12: 8 | C12: 45536 | D12: ='06_Medicion_inicial'!J5 | E12: =J11 | F12: =E12*D12 | G12: =IF(B12<'05_Plazo'!H5,'07_Pagos_variables'!G5,IF(B12='05_Plazo'!H5,'06_Medicion_inicial'!F5+(1-'06_Medicion_inicial'!E5)*'07_Pagos_variables'!G5,0)) | H12: =E12+F12-G12 | I12: 0 | J12: =H12+I12
A13: C-01 | B13: 9 | C13: 45566 | D13: ='06_Medicion_inicial'!J5 | E13: =J12 | F13: =E13*D13 | G13: =IF(B13<'05_Plazo'!H5,'07_Pagos_variables'!G5,IF(B13='05_Plazo'!H5,'06_Medicion_inicial'!F5+(1-'06_Medicion_inicial'!E5)*'07_Pagos_variables'!G5,0)) | H13: =E13+F13-G13 | I13: 0 | J13: =H13+I13
A14: C-01 | B14: 10 | C14: 45597 | D14: ='06_Medicion_inicial'!J5 | E14: =J13 | F14: =E14*D14 | G14: =IF(B14<'05_Plazo'!H5,'07_Pagos_variables'!G5,IF(B14='05_Plazo'!H5,'06_Medicion_inicial'!F5+(1-'06_Medicion_inicial'!E5)*'07_Pagos_variables'!G5,0)) | H14: =E14+F14-G14 | I14: 0 | J14: =H14+I14
A15: C-01 | B15: 11 | C15: 45627 | D15: ='06_Medicion_inicial'!J5 | E15: =J14 | F15: =E15*D15 | G15: =IF(B15<'05_Plazo'!H5,'07_Pagos_variables'!G5,IF(B15='05_Plazo'!H5,'06_Medicion_inicial'!F5+(1-'06_Medicion_inicial'!E5)*'07_Pagos_variables'!G5,0)) | H15: =E15+F15-G15 | I15: 0 | J15: =H15+I15
A16: C-01 | B16: 12 | C16: 45658 | D16: ='06_Medicion_inicial'!J5 | E16: =J15 | F16: =E16*D16 | G16: =IF(B16<'05_Plazo'!H5,'07_Pagos_variables'!G5,IF(B16='05_Plazo'!H5,'06_Medicion_inicial'!F5+(1-'06_Medicion_inicial'!E5)*'07_Pagos_variables'!G5,0)) | H16: =E16+F16-G16 | I16: 0 | J16: =H16+I16
A17: C-01 | B17: 13 | C17: 45689 | D17: ='06_Medicion_inicial'!J5 | E17: =J16 | F17: =E17*D17 | G17: =IF(B17<'05_Plazo'!H5,'07_Pagos_variables'!G5,IF(B17='05_Plazo'!H5,'06_Medicion_inicial'!F5+(1-'06_Medicion_inicial'!E5)*'07_Pagos_variables'!G5,0)) | H17: =E17+F17-G17 | I17: 0 | J17: =H17+I17
A18: C-01 | B18: 14 | C18: 45717 | D18: ='06_Medicion_inicial'!J5 | E18: =J17 | F18: =E18*D18 | G18: =IF(B18<'05_Plazo'!H5,'07_Pagos_variables'!G5,IF(B18='05_Plazo'!H5,'06_Medicion_inicial'!F5+(1-'06_Medicion_inicial'!E5)*'07_Pagos_variables'!G5,0)) | H18: =E18+F18-G18 | I18: 0 | J18: =H18+I18
A19: C-01 | B19: 15 | C19: 45748 | D19: ='06_Medicion_inicial'!J5 | E19: =J18 | F19: =E19*D19 | G19: =IF(B19<'05_Plazo'!H5,'07_Pagos_variables'!G5,IF(B19='05_Plazo'!H5,'06_Medicion_inicial'!F5+(1-'06_Medicion_inicial'!E5)*'07_Pagos_variables'!G5,0)) | H19: =E19+F19-G19 | I19: 0 | J19: =H19+I19
A20: C-01 | B20: 16 | C20: 45778 | D20: ='06_Medicion_inicial'!J5 | E20: =J19 | F20: =E20*D20 | G20: =IF(B20<'05_Plazo'!H5,'07_Pagos_variables'!G5,IF(B20='05_Plazo'!H5,'06_Medicion_inicial'!F5+(1-'06_Medicion_inicial'!E5)*'07_Pagos_variables'!G5,0)) | H20: =E20+F20-G20 | I20: 0 | J20: =H20+I20
A21: C-01 | B21: 17 | C21: 45809 | D21: ='06_Medicion_inicial'!J5 | E21: =J20 | F21: =E21*D21 | G21: =IF(B21<'05_Plazo'!H5,'07_Pagos_variables'!G5,IF(B21='05_Plazo'!H5,'06_Medicion_inicial'!F5+(1-'06_Medicion_inicial'!E5)*'07_Pagos_variables'!G5,0)) | H21: =E21+F21-G21 | I21: 0 | J21: =H21+I21
A22: C-01 | B22: 18 | C22: 45839 | D22: ='06_Medicion_inicial'!J5 | E22: =J21 | F22: =E22*D22 | G22: =IF(B22<'05_Plazo'!H5,'07_Pagos_variables'!G5,IF(B22='05_Plazo'!H5,'06_Medicion_inicial'!F5+(1-'06_Medicion_inicial'!E5)*'07_Pagos_variables'!G5,0)) | H22: =E22+F22-G22 | I22: 0 | J22: =H22+I22
A23: C-01 | B23: 19 | C23: 45870 | D23: ='06_Medicion_inicial'!J5 | E23: =J22 | F23: =E23*D23 | G23: =IF(B23<'05_Plazo'!H5,'07_Pagos_variables'!G5,IF(B23='05_Plazo'!H5,'06_Medicion_inicial'!F5+(1-'06_Medicion_inicial'!E5)*'07_Pagos_variables'!G5,0)) | H23: =E23+F23-G23 | I23: 0 | J23: =H23+I23
A24: C-01 | B24: 20 | C24: 45901 | D24: ='06_Medicion_inicial'!J5 | E24: =J23 | F24: =E24*D24 | G24: =IF(B24<'05_Plazo'!H5,'07_Pagos_variables'!G5,IF(B24='05_Plazo'!H5,'06_Medicion_inicial'!F5+(1-'06_Medicion_inicial'!E5)*'07_Pagos_variables'!G5,0)) | H24: =E24+F24-G24 | I24: 0 | J24: =H24+I24
A25: C-01 | B25: 21 | C25: 45931 | D25: ='06_Medicion_inicial'!J5 | E25: =J24 | F25: =E25*D25 | G25: =IF(B25<'05_Plazo'!H5,'07_Pagos_variables'!G5,IF(B25='05_Plazo'!H5,'06_Medicion_inicial'!F5+(1-'06_Medicion_inicial'!E5)*'07_Pagos_variables'!G5,0)) | H25: =E25+F25-G25 | I25: 0 | J25: =H25+I25
A26: C-01 | B26: 22 | C26: 45962 | D26: ='06_Medicion_inicial'!J5 | E26: =J25 | F26: =E26*D26 | G26: =IF(B26<'05_Plazo'!H5,'07_Pagos_variables'!G5,IF(B26='05_Plazo'!H5,'06_Medicion_inicial'!F5+(1-'06_Medicion_inicial'!E5)*'07_Pagos_variables'!G5,0)) | H26: =E26+F26-G26 | I26: 0 | J26: =H26+I26
A27: C-01 | B27: 23 | C27: 45992 | D27: ='06_Medicion_inicial'!J5 | E27: =J26 | F27: =E27*D27 | G27: =IF(B27<'05_Plazo'!H5,'07_Pagos_variables'!G5,IF(B27='05_Plazo'!H5,'06_Medicion_inicial'!F5+(1-'06_Medicion_inicial'!E5)*'07_Pagos_variables'!G5,0)) | H27: =E27+F27-G27 | I27: 0 | J27: =H27+I27
A28: C-01 | B28: 24 | C28: 46023 | D28: ='06_Medicion_inicial'!J5 | E28: =J27 | F28: =E28*D28 | G28: =IF(B28<'05_Plazo'!H5,'07_Pagos_variables'!G5,IF(B28='05_Plazo'!H5,'06_Medicion_inicial'!F5+(1-'06_Medicion_inicial'!E5)*'07_Pagos_variables'!G5,0)) | H28: =E28+F28-G28 | I28: 0 | J28: =H28+I28
A29: C-01 | B29: 25 | C29: 46054 | D29: ='06_Medicion_inicial'!J5 | E29: =J28 | F29: =E29*D29 | G29: =IF(B29<'05_Plazo'!H5,'07_Pagos_variables'!G5,IF(B29='05_Plazo'!H5,'06_Medicion_inicial'!F5+(1-'06_Medicion_inicial'!E5)*'07_Pagos_variables'!G5,0)) | H29: =E29+F29-G29 | I29: 0 | J29: =H29+I29
A30: C-01 | B30: 26 | C30: 46082 | D30: ='06_Medicion_inicial'!J5 | E30: =J29 | F30: =E30*D30 | G30: =IF(B30<'05_Plazo'!H5,'07_Pagos_variables'!G5,IF(B30='05_Plazo'!H5,'06_Medicion_inicial'!F5+(1-'06_Medicion_inicial'!E5)*'07_Pagos_variables'!G5,0)) | H30: =E30+F30-G30 | I30: 0 | J30: =H30+I30
A31: C-01 | B31: 27 | C31: 46113 | D31: ='06_Medicion_inicial'!J5 | E31: =J30 | F31: =E31*D31 | G31: =IF(B31<'05_Plazo'!H5,'07_Pagos_variables'!G5,IF(B31='05_Plazo'!H5,'06_Medicion_inicial'!F5+(1-'06_Medicion_inicial'!E5)*'07_Pagos_variables'!G5,0)) | H31: =E31+F31-G31 | I31: 0 | J31: =H31+I31
A32: C-01 | B32: 28 | C32: 46143 | D32: ='06_Medicion_inicial'!J5 | E32: =J31 | F32: =E32*D32 | G32: =IF(B32<'05_Plazo'!H5,'07_Pagos_variables'!G5,IF(B32='05_Plazo'!H5,'06_Medicion_inicial'!F5+(1-'06_Medicion_inicial'!E5)*'07_Pagos_variables'!G5,0)) | H32: =E32+F32-G32 | I32: 0 | J32: =H32+I32
A33: C-01 | B33: 29 | C33: 46174 | D33: ='06_Medicion_inicial'!J5 | E33: =J32 | F33: =E33*D33 | G33: =IF(B33<'05_Plazo'!H5,'07_Pagos_variables'!G5,IF(B33='05_Plazo'!H5,'06_Medicion_inicial'!F5+(1-'06_Medicion_inicial'!E5)*'07_Pagos_variables'!G5,0)) | H33: =E33+F33-G33 | I33: 0 | J33: =H33+I33
A34: C-01 | B34: 30 | C34: 46204 | D34: ='06_Medicion_inicial'!J5 | E34: =J33 | F34: =E34*D34 | G34: =IF(B34<'05_Plazo'!H5,'07_Pagos_variables'!G5,IF(B34='05_Plazo'!H5,'06_Medicion_inicial'!F5+(1-'06_Medicion_inicial'!E5)*'07_Pagos_variables'!G5,0)) | H34: =E34+F34-G34 | I34: 0 | J34: =H34+I34
A35: C-01 | B35: 31 | C35: 46235 | D35: ='06_Medicion_inicial'!J5 | E35: =J34 | F35: =E35*D35 | G35: =IF(B35<'05_Plazo'!H5,'07_Pagos_variables'!G5,IF(B35='05_Plazo'!H5,'06_Medicion_inicial'!F5+(1-'06_Medicion_inicial'!E5)*'07_Pagos_variables'!G5,0)) | H35: =E35+F35-G35 | I35: 0 | J35: =H35+I35
A36: C-01 | B36: 32 | C36: 46266 | D36: ='06_Medicion_inicial'!J5 | E36: =J35 | F36: =E36*D36 | G36: =IF(B36<'05_Plazo'!H5,'07_Pagos_variables'!G5,IF(B36='05_Plazo'!H5,'06_Medicion_inicial'!F5+(1-'06_Medicion_inicial'!E5)*'07_Pagos_variables'!G5,0)) | H36: =E36+F36-G36 | I36: 0 | J36: =H36+I36
A37: C-01 | B37: 33 | C37: 46296 | D37: ='06_Medicion_inicial'!J5 | E37: =J36 | F37: =E37*D37 | G37: =IF(B37<'05_Plazo'!H5,'07_Pagos_variables'!G5,IF(B37='05_Plazo'!H5,'06_Medicion_inicial'!F5+(1-'06_Medicion_inicial'!E5)*'07_Pagos_variables'!G5,0)) | H37: =E37+F37-G37 | I37: 0 | J37: =H37+I37
A38: C-01 | B38: 34 | C38: 46327 | D38: ='06_Medicion_inicial'!J5 | E38: =J37 | F38: =E38*D38 | G38: =IF(B38<'05_Plazo'!H5,'07_Pagos_variables'!G5,IF(B38='05_Plazo'!H5,'06_Medicion_inicial'!F5+(1-'06_Medicion_inicial'!E5)*'07_Pagos_variables'!G5,0)) | H38: =E38+F38-G38 | I38: 0 | J38: =H38+I38
A39: C-01 | B39: 35 | C39: 46357 | D39: ='06_Medicion_inicial'!J5 | E39: =J38 | F39: =E39*D39 | G39: =IF(B39<'05_Plazo'!H5,'07_Pagos_variables'!G5,IF(B39='05_Plazo'!H5,'06_Medicion_inicial'!F5+(1-'06_Medicion_inicial'!E5)*'07_Pagos_variables'!G5,0)) | H39: =E39+F39-G39 | I39: 0 | J39: =H39+I39
A40: C-01 | B40: 36 | C40: 46388 | D40: ='06_Medicion_inicial'!J5 | E40: =J39 | F40: =E40*D40 | G40: =IF(B40<'05_Plazo'!H5,'07_Pagos_variables'!G5,IF(B40='05_Plazo'!H5,'06_Medicion_inicial'!F5+(1-'06_Medicion_inicial'!E5)*'07_Pagos_variables'!G5,0)) | H40: =E40+F40-G40 | I40: 0 | J40: =H40+I40
A41: C-01 | B41: 37 | C41: 46419 | D41: ='06_Medicion_inicial'!J5 | E41: =J40 | F41: =E41*D41 | G41: =IF(B41<'05_Plazo'!H5,'07_Pagos_variables'!G5,IF(B41='05_Plazo'!H5,'06_Medicion_inicial'!F5+(1-'06_Medicion_inicial'!E5)*'07_Pagos_variables'!G5,0)) | H41: =E41+F41-G41 | I41: 0 | J41: =H41+I41
A42: C-01 | B42: 38 | C42: 46447 | D42: ='06_Medicion_inicial'!J5 | E42: =J41 | F42: =E42*D42 | G42: =IF(B42<'05_Plazo'!H5,'07_Pagos_variables'!G5,IF(B42='05_Plazo'!H5,'06_Medicion_inicial'!F5+(1-'06_Medicion_inicial'!E5)*'07_Pagos_variables'!G5,0)) | H42: =E42+F42-G42 | I42: 0 | J42: =H42+I42
A43: C-01 | B43: 39 | C43: 46478 | D43: ='06_Medicion_inicial'!J5 | E43: =J42 | F43: =E43*D43 | G43: =IF(B43<'05_Plazo'!H5,'07_Pagos_variables'!G5,IF(B43='05_Plazo'!H5,'06_Medicion_inicial'!F5+(1-'06_Medicion_inicial'!E5)*'07_Pagos_variables'!G5,0)) | H43: =E43+F43-G43 | I43: 0 | J43: =H43+I43
A44: C-01 | B44: 40 | C44: 46508 | D44: ='06_Medicion_inicial'!J5 | E44: =J43 | F44: =E44*D44 | G44: =IF(B44<'05_Plazo'!H5,'07_Pagos_variables'!G5,IF(B44='05_Plazo'!H5,'06_Medicion_inicial'!F5+(1-'06_Medicion_inicial'!E5)*'07_Pagos_variables'!G5,0)) | H44: =E44+F44-G44 | I44: 0 | J44: =H44+I44
A45: C-01 | B45: 41 | C45: 46539 | D45: ='06_Medicion_inicial'!J5 | E45: =J44 | F45: =E45*D45 | G45: =IF(B45<'05_Plazo'!H5,'07_Pagos_variables'!G5,IF(B45='05_Plazo'!H5,'06_Medicion_inicial'!F5+(1-'06_Medicion_inicial'!E5)*'07_Pagos_variables'!G5,0)) | H45: =E45+F45-G45 | I45: 0 | J45: =H45+I45
A46: C-01 | B46: 42 | C46: 46569 | D46: ='06_Medicion_inicial'!J5 | E46: =J45 | F46: =E46*D46 | G46: =IF(B46<'05_Plazo'!H5,'07_Pagos_variables'!G5,IF(B46='05_Plazo'!H5,'06_Medicion_inicial'!F5+(1-'06_Medicion_inicial'!E5)*'07_Pagos_variables'!G5,0)) | H46: =E46+F46-G46 | I46: 0 | J46: =H46+I46
A47: C-01 | B47: 43 | C47: 46600 | D47: ='06_Medicion_inicial'!J5 | E47: =J46 | F47: =E47*D47 | G47: =IF(B47<'05_Plazo'!H5,'07_Pagos_variables'!G5,IF(B47='05_Plazo'!H5,'06_Medicion_inicial'!F5+(1-'06_Medicion_inicial'!E5)*'07_Pagos_variables'!G5,0)) | H47: =E47+F47-G47 | I47: 0 | J47: =H47+I47
A48: C-01 | B48: 44 | C48: 46631 | D48: ='06_Medicion_inicial'!J5 | E48: =J47 | F48: =E48*D48 | G48: =IF(B48<'05_Plazo'!H5,'07_Pagos_variables'!G5,IF(B48='05_Plazo'!H5,'06_Medicion_inicial'!F5+(1-'06_Medicion_inicial'!E5)*'07_Pagos_variables'!G5,0)) | H48: =E48+F48-G48 | I48: 0 | J48: =H48+I48
A49: C-01 | B49: 45 | C49: 46661 | D49: ='06_Medicion_inicial'!J5 | E49: =J48 | F49: =E49*D49 | G49: =IF(B49<'05_Plazo'!H5,'07_Pagos_variables'!G5,IF(B49='05_Plazo'!H5,'06_Medicion_inicial'!F5+(1-'06_Medicion_inicial'!E5)*'07_Pagos_variables'!G5,0)) | H49: =E49+F49-G49 | I49: 0 | J49: =H49+I49
A50: C-01 | B50: 46 | C50: 46692 | D50: ='06_Medicion_inicial'!J5 | E50: =J49 | F50: =E50*D50 | G50: =IF(B50<'05_Plazo'!H5,'07_Pagos_variables'!G5,IF(B50='05_Plazo'!H5,'06_Medicion_inicial'!F5+(1-'06_Medicion_inicial'!E5)*'07_Pagos_variables'!G5,0)) | H50: =E50+F50-G50 | I50: 0 | J50: =H50+I50
A51: C-01 | B51: 47 | C51: 46722 | D51: ='06_Medicion_inicial'!J5 | E51: =J50 | F51: =E51*D51 | G51: =IF(B51<'05_Plazo'!H5,'07_Pagos_variables'!G5,IF(B51='05_Plazo'!H5,'06_Medicion_inicial'!F5+(1-'06_Medicion_inicial'!E5)*'07_Pagos_variables'!G5,0)) | H51: =E51+F51-G51 | I51: 0 | J51: =H51+I51
A52: C-01 | B52: 48 | C52: 46753 | D52: ='06_Medicion_inicial'!J5 | E52: =J51 | F52: =E52*D52 | G52: =IF(B52<'05_Plazo'!H5,'07_Pagos_variables'!G5,IF(B52='05_Plazo'!H5,'06_Medicion_inicial'!F5+(1-'06_Medicion_inicial'!E5)*'07_Pagos_variables'!G5,0)) | H52: =E52+F52-G52 | I52: 0 | J52: =H52+I52
A53: C-01 | B53: 49 | C53: 46784 | D53: ='06_Medicion_inicial'!J5 | E53: =J52 | F53: =E53*D53 | G53: =IF(B53<'05_Plazo'!H5,'07_Pagos_variables'!G5,IF(B53='05_Plazo'!H5,'06_Medicion_inicial'!F5+(1-'06_Medicion_inicial'!E5)*'07_Pagos_variables'!G5,0)) | H53: =E53+F53-G53 | I53: 0 | J53: =H53+I53
A54: C-01 | B54: 50 | C54: 46813 | D54: ='06_Medicion_inicial'!J5 | E54: =J53 | F54: =E54*D54 | G54: =IF(B54<'05_Plazo'!H5,'07_Pagos_variables'!G5,IF(B54='05_Plazo'!H5,'06_Medicion_inicial'!F5+(1-'06_Medicion_inicial'!E5)*'07_Pagos_variables'!G5,0)) | H54: =E54+F54-G54 | I54: 0 | J54: =H54+I54
A55: C-01 | B55: 51 | C55: 46844 | D55: ='06_Medicion_inicial'!J5 | E55: =J54 | F55: =E55*D55 | G55: =IF(B55<'05_Plazo'!H5,'07_Pagos_variables'!G5,IF(B55='05_Plazo'!H5,'06_Medicion_inicial'!F5+(1-'06_Medicion_inicial'!E5)*'07_Pagos_variables'!G5,0)) | H55: =E55+F55-G55 | I55: 0 | J55: =H55+I55
A56: C-01 | B56: 52 | C56: 46874 | D56: ='06_Medicion_inicial'!J5 | E56: =J55 | F56: =E56*D56 | G56: =IF(B56<'05_Plazo'!H5,'07_Pagos_variables'!G5,IF(B56='05_Plazo'!H5,'06_Medicion_inicial'!F5+(1-'06_Medicion_inicial'!E5)*'07_Pagos_variables'!G5,0)) | H56: =E56+F56-G56 | I56: 0 | J56: =H56+I56
A57: C-01 | B57: 53 | C57: 46905 | D57: ='06_Medicion_inicial'!J5 | E57: =J56 | F57: =E57*D57 | G57: =IF(B57<'05_Plazo'!H5,'07_Pagos_variables'!G5,IF(B57='05_Plazo'!H5,'06_Medicion_inicial'!F5+(1-'06_Medicion_inicial'!E5)*'07_Pagos_variables'!G5,0)) | H57: =E57+F57-G57 | I57: 0 | J57: =H57+I57
A58: C-01 | B58: 54 | C58: 46935 | D58: ='06_Medicion_inicial'!J5 | E58: =J57 | F58: =E58*D58 | G58: =IF(B58<'05_Plazo'!H5,'07_Pagos_variables'!G5,IF(B58='05_Plazo'!H5,'06_Medicion_inicial'!F5+(1-'06_Medicion_inicial'!E5)*'07_Pagos_variables'!G5,0)) | H58: =E58+F58-G58 | I58: 0 | J58: =H58+I58
A59: C-01 | B59: 55 | C59: 46966 | D59: ='06_Medicion_inicial'!J5 | E59: =J58 | F59: =E59*D59 | G59: =IF(B59<'05_Plazo'!H5,'07_Pagos_variables'!G5,IF(B59='05_Plazo'!H5,'06_Medicion_inicial'!F5+(1-'06_Medicion_inicial'!E5)*'07_Pagos_variables'!G5,0)) | H59: =E59+F59-G59 | I59: 0 | J59: =H59+I59
A60: C-01 | B60: 56 | C60: 46997 | D60: ='06_Medicion_inicial'!J5 | E60: =J59 | F60: =E60*D60 | G60: =IF(B60<'05_Plazo'!H5,'07_Pagos_variables'!G5,IF(B60='05_Plazo'!H5,'06_Medicion_inicial'!F5+(1-'06_Medicion_inicial'!E5)*'07_Pagos_variables'!G5,0)) | H60: =E60+F60-G60 | I60: 0 | J60: =H60+I60
A61: C-01 | B61: 57 | C61: 47027 | D61: ='06_Medicion_inicial'!J5 | E61: =J60 | F61: =E61*D61 | G61: =IF(B61<'05_Plazo'!H5,'07_Pagos_variables'!G5,IF(B61='05_Plazo'!H5,'06_Medicion_inicial'!F5+(1-'06_Medicion_inicial'!E5)*'07_Pagos_variables'!G5,0)) | H61: =E61+F61-G61 | I61: 0 | J61: =H61+I61
A62: C-01 | B62: 58 | C62: 47058 | D62: ='06_Medicion_inicial'!J5 | E62: =J61 | F62: =E62*D62 | G62: =IF(B62<'05_Plazo'!H5,'07_Pagos_variables'!G5,IF(B62='05_Plazo'!H5,'06_Medicion_inicial'!F5+(1-'06_Medicion_inicial'!E5)*'07_Pagos_variables'!G5,0)) | H62: =E62+F62-G62 | I62: 0 | J62: =H62+I62
A63: C-01 | B63: 59 | C63: 47088 | D63: ='06_Medicion_inicial'!J5 | E63: =J62 | F63: =E63*D63 | G63: =IF(B63<'05_Plazo'!H5,'07_Pagos_variables'!G5,IF(B63='05_Plazo'!H5,'06_Medicion_inicial'!F5+(1-'06_Medicion_inicial'!E5)*'07_Pagos_variables'!G5,0)) | H63: =E63+F63-G63 | I63: 0 | J63: =H63+I63
A64: C-01 | B64: 60 | C64: 47119 | D64: ='06_Medicion_inicial'!J5 | E64: =J63 | F64: =E64*D64 | G64: =IF(B64<'05_Plazo'!H5,'07_Pagos_variables'!G5,IF(B64='05_Plazo'!H5,'06_Medicion_inicial'!F5+(1-'06_Medicion_inicial'!E5)*'07_Pagos_variables'!G5,0)) | H64: =E64+F64-G64 | I64: 0 | J64: =H64+I64
A65: C-02 | B65: 1 | C65: 45292 | D65: ='06_Medicion_inicial'!J6 | E65: ='06_Medicion_inicial'!L6 | F65: =E65*D65 | G65: =IF(B65<'05_Plazo'!H6,'07_Pagos_variables'!G6,IF(B65='05_Plazo'!H6,'06_Medicion_inicial'!F6+(1-'06_Medicion_inicial'!E6)*'07_Pagos_variables'!G6,0)) | H65: =E65+F65-G65 | I65: 0 | J65: =H65+I65
A66: C-02 | B66: 2 | C66: 45658 | D66: ='06_Medicion_inicial'!J6 | E66: =J65 | F66: =E66*D66 | G66: =IF(B66<'05_Plazo'!H6,'07_Pagos_variables'!G6,IF(B66='05_Plazo'!H6,'06_Medicion_inicial'!F6+(1-'06_Medicion_inicial'!E6)*'07_Pagos_variables'!G6,0)) | H66: =E66+F66-G66 | I66: 0 | J66: =H66+I66
A67: C-02 | B67: 3 | C67: 46023 | D67: ='06_Medicion_inicial'!J6 | E67: =J66 | F67: =E67*D67 | G67: =IF(B67<'05_Plazo'!H6,'07_Pagos_variables'!G6,IF(B67='05_Plazo'!H6,'06_Medicion_inicial'!F6+(1-'06_Medicion_inicial'!E6)*'07_Pagos_variables'!G6,0)) | H67: =E67+F67-G67 | I67: 0 | J67: =H67+I67
A68: C-02 | B68: 4 | C68: 46388 | D68: ='06_Medicion_inicial'!J6 | E68: =J67 | F68: =E68*D68 | G68: =IF(B68<'05_Plazo'!H6,'07_Pagos_variables'!G6,IF(B68='05_Plazo'!H6,'06_Medicion_inicial'!F6+(1-'06_Medicion_inicial'!E6)*'07_Pagos_variables'!G6,0)) | H68: =E68+F68-G68 | I68: 0 | J68: =H68+I68
A69: C-02 | B69: 5 | C69: 46753 | D69: ='06_Medicion_inicial'!J6 | E69: =J68 | F69: =E69*D69 | G69: =IF(B69<'05_Plazo'!H6,'07_Pagos_variables'!G6,IF(B69='05_Plazo'!H6,'06_Medicion_inicial'!F6+(1-'06_Medicion_inicial'!E6)*'07_Pagos_variables'!G6,0)) | H69: =E69+F69-G69 | I69: 0 | J69: =H69+I69
A70: C-03 | B70: 1 | C70: 45778 | D70: ='06_Medicion_inicial'!J7 | E70: ='06_Medicion_inicial'!L7 | F70: =E70*D70 | G70: =IF(B70<'05_Plazo'!H7,'07_Pagos_variables'!G7,IF(B70='05_Plazo'!H7,'06_Medicion_inicial'!F7+(1-'06_Medicion_inicial'!E7)*'07_Pagos_variables'!G7,0)) | H70: =E70+F70-G70 | I70: 0 | J70: =H70+I70
A71: C-03 | B71: 2 | C71: 45809 | D71: ='06_Medicion_inicial'!J7 | E71: =J70 | F71: =E71*D71 | G71: =IF(B71<'05_Plazo'!H7,'07_Pagos_variables'!G7,IF(B71='05_Plazo'!H7,'06_Medicion_inicial'!F7+(1-'06_Medicion_inicial'!E7)*'07_Pagos_variables'!G7,0)) | H71: =E71+F71-G71 | I71: 0 | J71: =H71+I71
A72: C-03 | B72: 3 | C72: 45839 | D72: ='06_Medicion_inicial'!J7 | E72: =J71 | F72: =E72*D72 | G72: =IF(B72<'05_Plazo'!H7,'07_Pagos_variables'!G7,IF(B72='05_Plazo'!H7,'06_Medicion_inicial'!F7+(1-'06_Medicion_inicial'!E7)*'07_Pagos_variables'!G7,0)) | H72: =E72+F72-G72 | I72: 0 | J72: =H72+I72
A73: C-03 | B73: 4 | C73: 45870 | D73: ='06_Medicion_inicial'!J7 | E73: =J72 | F73: =E73*D73 | G73: =IF(B73<'05_Plazo'!H7,'07_Pagos_variables'!G7,IF(B73='05_Plazo'!H7,'06_Medicion_inicial'!F7+(1-'06_Medicion_inicial'!E7)*'07_Pagos_variables'!G7,0)) | H73: =E73+F73-G73 | I73: 0 | J73: =H73+I73
A74: C-03 | B74: 5 | C74: 45901 | D74: ='06_Medicion_inicial'!J7 | E74: =J73 | F74: =E74*D74 | G74: =IF(B74<'05_Plazo'!H7,'07_Pagos_variables'!G7,IF(B74='05_Plazo'!H7,'06_Medicion_inicial'!F7+(1-'06_Medicion_inicial'!E7)*'07_Pagos_variables'!G7,0)) | H74: =E74+F74-G74 | I74: 0 | J74: =H74+I74
A75: C-03 | B75: 6 | C75: 45931 | D75: ='06_Medicion_inicial'!J7 | E75: =J74 | F75: =E75*D75 | G75: =IF(B75<'05_Plazo'!H7,'07_Pagos_variables'!G7,IF(B75='05_Plazo'!H7,'06_Medicion_inicial'!F7+(1-'06_Medicion_inicial'!E7)*'07_Pagos_variables'!G7,0)) | H75: =E75+F75-G75 | I75: 0 | J75: =H75+I75
A76: C-03 | B76: 7 | C76: 45962 | D76: ='06_Medicion_inicial'!J7 | E76: =J75 | F76: =E76*D76 | G76: =IF(B76<'05_Plazo'!H7,'07_Pagos_variables'!G7,IF(B76='05_Plazo'!H7,'06_Medicion_inicial'!F7+(1-'06_Medicion_inicial'!E7)*'07_Pagos_variables'!G7,0)) | H76: =E76+F76-G76 | I76: 0 | J76: =H76+I76
A77: C-03 | B77: 8 | C77: 45992 | D77: ='06_Medicion_inicial'!J7 | E77: =J76 | F77: =E77*D77 | G77: =IF(B77<'05_Plazo'!H7,'07_Pagos_variables'!G7,IF(B77='05_Plazo'!H7,'06_Medicion_inicial'!F7+(1-'06_Medicion_inicial'!E7)*'07_Pagos_variables'!G7,0)) | H77: =E77+F77-G77 | I77: 0 | J77: =H77+I77
A78: C-03 | B78: 9 | C78: 46023 | D78: ='06_Medicion_inicial'!J7 | E78: =J77 | F78: =E78*D78 | G78: =IF(B78<'05_Plazo'!H7,'07_Pagos_variables'!G7,IF(B78='05_Plazo'!H7,'06_Medicion_inicial'!F7+(1-'06_Medicion_inicial'!E7)*'07_Pagos_variables'!G7,0)) | H78: =E78+F78-G78 | I78: 0 | J78: =H78+I78
A79: C-03 | B79: 10 | C79: 46054 | D79: ='06_Medicion_inicial'!J7 | E79: =J78 | F79: =E79*D79 | G79: =IF(B79<'05_Plazo'!H7,'07_Pagos_variables'!G7,IF(B79='05_Plazo'!H7,'06_Medicion_inicial'!F7+(1-'06_Medicion_inicial'!E7)*'07_Pagos_variables'!G7,0)) | H79: =E79+F79-G79 | I79: 0 | J79: =H79+I79
A80: C-03 | B80: 11 | C80: 46082 | D80: ='06_Medicion_inicial'!J7 | E80: =J79 | F80: =E80*D80 | G80: =IF(B80<'05_Plazo'!H7,'07_Pagos_variables'!G7,IF(B80='05_Plazo'!H7,'06_Medicion_inicial'!F7+(1-'06_Medicion_inicial'!E7)*'07_Pagos_variables'!G7,0)) | H80: =E80+F80-G80 | I80: 0 | J80: =H80+I80
A81: C-03 | B81: 12 | C81: 46113 | D81: ='06_Medicion_inicial'!J7 | E81: =J80 | F81: =E81*D81 | G81: =IF(B81<'05_Plazo'!H7,'07_Pagos_variables'!G7,IF(B81='05_Plazo'!H7,'06_Medicion_inicial'!F7+(1-'06_Medicion_inicial'!E7)*'07_Pagos_variables'!G7,0)) | H81: =E81+F81-G81 | I81: 0 | J81: =H81+I81
A82: C-03 | B82: 13 | C82: 46143 | D82: ='06_Medicion_inicial'!J7 | E82: =J81 | F82: =E82*D82 | G82: =IF(B82<'05_Plazo'!H7,'07_Pagos_variables'!G7,IF(B82='05_Plazo'!H7,'06_Medicion_inicial'!F7+(1-'06_Medicion_inicial'!E7)*'07_Pagos_variables'!G7,0)) | H82: =E82+F82-G82 | I82: 0 | J82: =H82+I82
A83: C-03 | B83: 14 | C83: 46174 | D83: ='06_Medicion_inicial'!J7 | E83: =J82 | F83: =E83*D83 | G83: =IF(B83<'05_Plazo'!H7,'07_Pagos_variables'!G7,IF(B83='05_Plazo'!H7,'06_Medicion_inicial'!F7+(1-'06_Medicion_inicial'!E7)*'07_Pagos_variables'!G7,0)) | H83: =E83+F83-G83 | I83: 0 | J83: =H83+I83
A84: C-03 | B84: 15 | C84: 46204 | D84: ='06_Medicion_inicial'!J7 | E84: =J83 | F84: =E84*D84 | G84: =IF(B84<'05_Plazo'!H7,'07_Pagos_variables'!G7,IF(B84='05_Plazo'!H7,'06_Medicion_inicial'!F7+(1-'06_Medicion_inicial'!E7)*'07_Pagos_variables'!G7,0)) | H84: =E84+F84-G84 | I84: 0 | J84: =H84+I84
A85: C-03 | B85: 16 | C85: 46235 | D85: ='06_Medicion_inicial'!J7 | E85: =J84 | F85: =E85*D85 | G85: =IF(B85<'05_Plazo'!H7,'07_Pagos_variables'!G7,IF(B85='05_Plazo'!H7,'06_Medicion_inicial'!F7+(1-'06_Medicion_inicial'!E7)*'07_Pagos_variables'!G7,0)) | H85: =E85+F85-G85 | I85: 0 | J85: =H85+I85
A86: C-03 | B86: 17 | C86: 46266 | D86: ='06_Medicion_inicial'!J7 | E86: =J85 | F86: =E86*D86 | G86: =IF(B86<'05_Plazo'!H7,'07_Pagos_variables'!G7,IF(B86='05_Plazo'!H7,'06_Medicion_inicial'!F7+(1-'06_Medicion_inicial'!E7)*'07_Pagos_variables'!G7,0)) | H86: =E86+F86-G86 | I86: 0 | J86: =H86+I86
A87: C-03 | B87: 18 | C87: 46296 | D87: ='06_Medicion_inicial'!J7 | E87: =J86 | F87: =E87*D87 | G87: =IF(B87<'05_Plazo'!H7,'07_Pagos_variables'!G7,IF(B87='05_Plazo'!H7,'06_Medicion_inicial'!F7+(1-'06_Medicion_inicial'!E7)*'07_Pagos_variables'!G7,0)) | H87: =E87+F87-G87 | I87: 0 | J87: =H87+I87
A88: C-03 | B88: 19 | C88: 46327 | D88: ='06_Medicion_inicial'!J7 | E88: =J87 | F88: =E88*D88 | G88: =IF(B88<'05_Plazo'!H7,'07_Pagos_variables'!G7,IF(B88='05_Plazo'!H7,'06_Medicion_inicial'!F7+(1-'06_Medicion_inicial'!E7)*'07_Pagos_variables'!G7,0)) | H88: =E88+F88-G88 | I88: 0 | J88: =H88+I88
A89: C-03 | B89: 20 | C89: 46357 | D89: ='06_Medicion_inicial'!J7 | E89: =J88 | F89: =E89*D89 | G89: =IF(B89<'05_Plazo'!H7,'07_Pagos_variables'!G7,IF(B89='05_Plazo'!H7,'06_Medicion_inicial'!F7+(1-'06_Medicion_inicial'!E7)*'07_Pagos_variables'!G7,0)) | H89: =E89+F89-G89 | I89: 0 | J89: =H89+I89
A90: C-03 | B90: 21 | C90: 46388 | D90: ='06_Medicion_inicial'!J7 | E90: =J89 | F90: =E90*D90 | G90: =IF(B90<'05_Plazo'!H7,'07_Pagos_variables'!G7,IF(B90='05_Plazo'!H7,'06_Medicion_inicial'!F7+(1-'06_Medicion_inicial'!E7)*'07_Pagos_variables'!G7,0)) | H90: =E90+F90-G90 | I90: 0 | J90: =H90+I90
A91: C-03 | B91: 22 | C91: 46419 | D91: ='06_Medicion_inicial'!J7 | E91: =J90 | F91: =E91*D91 | G91: =IF(B91<'05_Plazo'!H7,'07_Pagos_variables'!G7,IF(B91='05_Plazo'!H7,'06_Medicion_inicial'!F7+(1-'06_Medicion_inicial'!E7)*'07_Pagos_variables'!G7,0)) | H91: =E91+F91-G91 | I91: 0 | J91: =H91+I91
A92: C-03 | B92: 23 | C92: 46447 | D92: ='06_Medicion_inicial'!J7 | E92: =J91 | F92: =E92*D92 | G92: =IF(B92<'05_Plazo'!H7,'07_Pagos_variables'!G7,IF(B92='05_Plazo'!H7,'06_Medicion_inicial'!F7+(1-'06_Medicion_inicial'!E7)*'07_Pagos_variables'!G7,0)) | H92: =E92+F92-G92 | I92: 0 | J92: =H92+I92
A93: C-03 | B93: 24 | C93: 46478 | D93: ='06_Medicion_inicial'!J7 | E93: =J92 | F93: =E93*D93 | G93: =IF(B93<'05_Plazo'!H7,'07_Pagos_variables'!G7,IF(B93='05_Plazo'!H7,'06_Medicion_inicial'!F7+(1-'06_Medicion_inicial'!E7)*'07_Pagos_variables'!G7,0)) | H93: =E93+F93-G93 | I93: 0 | J93: =H93+I93
A94: C-03 | B94: 25 | C94: 46508 | D94: ='06_Medicion_inicial'!J7 | E94: =J93 | F94: =E94*D94 | G94: =IF(B94<'05_Plazo'!H7,'07_Pagos_variables'!G7,IF(B94='05_Plazo'!H7,'06_Medicion_inicial'!F7+(1-'06_Medicion_inicial'!E7)*'07_Pagos_variables'!G7,0)) | H94: =E94+F94-G94 | I94: 0 | J94: =H94+I94
A95: C-03 | B95: 26 | C95: 46539 | D95: ='06_Medicion_inicial'!J7 | E95: =J94 | F95: =E95*D95 | G95: =IF(B95<'05_Plazo'!H7,'07_Pagos_variables'!G7,IF(B95='05_Plazo'!H7,'06_Medicion_inicial'!F7+(1-'06_Medicion_inicial'!E7)*'07_Pagos_variables'!G7,0)) | H95: =E95+F95-G95 | I95: 0 | J95: =H95+I95
A96: C-03 | B96: 27 | C96: 46569 | D96: ='06_Medicion_inicial'!J7 | E96: =J95 | F96: =E96*D96 | G96: =IF(B96<'05_Plazo'!H7,'07_Pagos_variables'!G7,IF(B96='05_Plazo'!H7,'06_Medicion_inicial'!F7+(1-'06_Medicion_inicial'!E7)*'07_Pagos_variables'!G7,0)) | H96: =E96+F96-G96 | I96: 0 | J96: =H96+I96
A97: C-03 | B97: 28 | C97: 46600 | D97: ='06_Medicion_inicial'!J7 | E97: =J96 | F97: =E97*D97 | G97: =IF(B97<'05_Plazo'!H7,'07_Pagos_variables'!G7,IF(B97='05_Plazo'!H7,'06_Medicion_inicial'!F7+(1-'06_Medicion_inicial'!E7)*'07_Pagos_variables'!G7,0)) | H97: =E97+F97-G97 | I97: 0 | J97: =H97+I97
A98: C-03 | B98: 29 | C98: 46631 | D98: ='06_Medicion_inicial'!J7 | E98: =J97 | F98: =E98*D98 | G98: =IF(B98<'05_Plazo'!H7,'07_Pagos_variables'!G7,IF(B98='05_Plazo'!H7,'06_Medicion_inicial'!F7+(1-'06_Medicion_inicial'!E7)*'07_Pagos_variables'!G7,0)) | H98: =E98+F98-G98 | I98: 0 | J98: =H98+I98
A99: C-03 | B99: 30 | C99: 46661 | D99: ='06_Medicion_inicial'!J7 | E99: =J98 | F99: =E99*D99 | G99: =IF(B99<'05_Plazo'!H7,'07_Pagos_variables'!G7,IF(B99='05_Plazo'!H7,'06_Medicion_inicial'!F7+(1-'06_Medicion_inicial'!E7)*'07_Pagos_variables'!G7,0)) | H99: =E99+F99-G99 | I99: 0 | J99: =H99+I99
A100: C-03 | B100: 31 | C100: 46692 | D100: ='06_Medicion_inicial'!J7 | E100: =J99 | F100: =E100*D100 | G100: =IF(B100<'05_Plazo'!H7,'07_Pagos_variables'!G7,IF(B100='05_Plazo'!H7,'06_Medicion_inicial'!F7+(1-'06_Medicion_inicial'!E7)*'07_Pagos_variables'!G7,0)) | H100: =E100+F100-G100 | I100: 0 | J100: =H100+I100
A101: C-03 | B101: 32 | C101: 46722 | D101: ='06_Medicion_inicial'!J7 | E101: =J100 | F101: =E101*D101 | G101: =IF(B101<'05_Plazo'!H7,'07_Pagos_variables'!G7,IF(B101='05_Plazo'!H7,'06_Medicion_inicial'!F7+(1-'06_Medicion_inicial'!E7)*'07_Pagos_variables'!G7,0)) | H101: =E101+F101-G101 | I101: 0 | J101: =H101+I101
...

Sheet 10_Pasivo_corte
A1: Pasivo al corte: corriente y no corriente | H1: ⟵ Inicio | I1: ◀ Anterior | J1: Siguiente ▶
A2: Arrendamientos · Cliente de muestra S.A. · corte 2025-12-31
A4: Contrato | B4: Reconoce | C4: Períodos finales | D4: Meses transcurridos | E4: Períodos vencidos al corte | F4: Períodos vencidos al inicio del año | G4: Pasivo al corte | H4: Pasivo al inicio del año | I4: Altas del año | J4: Interés del ejercicio | K4: Pagos del ejercicio | L4: Remedición del ejercicio | M4: Comprobación (0) | N4: Pasivo dentro de 12 meses | O4: Corriente | P4: No corriente | Q4: Pasivo registrado | R4: Diferencia | S4: Corriente registrado | T4: Diferencia corriente | U4: Interés registrado | V4: Diferencia interés | W4: Interés devengado no vencido (informativo)
A5: C-01 | B5: ='04_Identificacion'!M5 | C5: ='05_Plazo'!H5 | D5: ='05_Plazo'!I5 | E5: =MIN(C5,INT(MAX(D5,0)/'05_Plazo'!G5)) | F5: =MIN(C5,INT(MAX(D5-12,0)/'05_Plazo'!G5)) | G5: =IF(E5=0,'06_Medicion_inicial'!L5,SUMIFS('09_Tabla_amortizacion'!$J$5:$J$264,'09_Tabla_amortizacion'!$A$5:$A$264,A5,'09_Tabla_amortizacion'!$B$5:$B$264,E5)) | H5: =IF(D5<12,0,IF(F5=0,'06_Medicion_inicial'!L5,SUMIFS('09_Tabla_amortizacion'!$J$5:$J$264,'09_Tabla_amortizacion'!$A$5:$A$264,A5,'09_Tabla_amortizacion'!$B$5:$B$264,F5))) | I5: =IF(D5<12,'06_Medicion_inicial'!L5,0) | J5: =SUMIFS('09_Tabla_amortizacion'!$F$5:$F$264,'09_Tabla_amortizacion'!$A$5:$A$264,A5,'09_Tabla_amortizacion'!$B$5:$B$264,">"&F5,'09_Tabla_amortizacion'!$B$5:$B$264,"<="&E5) | K5: =SUMIFS('09_Tabla_amortizacion'!$G$5:$G$264,'09_Tabla_amortizacion'!$A$5:$A$264,A5,'09_Tabla_amortizacion'!$B$5:$B$264,">"&F5,'09_Tabla_amortizacion'!$B$5:$B$264,"<="&E5) | L5: =SUMIFS('09_Tabla_amortizacion'!$I$5:$I$264,'09_Tabla_amortizacion'!$A$5:$A$264,A5,'09_Tabla_amortizacion'!$B$5:$B$264,">"&F5,'09_Tabla_amortizacion'!$B$5:$B$264,"<="&E5) | M5: =H5+I5+J5-K5+L5-G5 | N5: =SUMIFS('09_Tabla_amortizacion'!$J$5:$J$264,'09_Tabla_amortizacion'!$A$5:$A$264,A5,'09_Tabla_amortizacion'!$B$5:$B$264,MIN(E5+12/'05_Plazo'!G5,C5)) | O5: =G5-N5 | P5: =N5 | Q5: =N('03_Contratos'!AC5) | R5: =G5-Q5 | S5: =IF('03_Contratos'!AD5="","",'03_Contratos'!AD5) | T5: =IF(S5="","",O5-S5) | U5: =IF('03_Contratos'!AG5="","",'03_Contratos'!AG5) | V5: =IF(U5="","",J5-U5) | W5: =IF(E5>=C5,0,G5*'06_Medicion_inicial'!J5*(D5-E5*'05_Plazo'!G5)/'05_Plazo'!G5)
A6: C-02 | B6: ='04_Identificacion'!M6 | C6: ='05_Plazo'!H6 | D6: ='05_Plazo'!I6 | E6: =MIN(C6,INT(MAX(D6,0)/'05_Plazo'!G6)) | F6: =MIN(C6,INT(MAX(D6-12,0)/'05_Plazo'!G6)) | G6: =IF(E6=0,'06_Medicion_inicial'!L6,SUMIFS('09_Tabla_amortizacion'!$J$5:$J$264,'09_Tabla_amortizacion'!$A$5:$A$264,A6,'09_Tabla_amortizacion'!$B$5:$B$264,E6)) | H6: =IF(D6<12,0,IF(F6=0,'06_Medicion_inicial'!L6,SUMIFS('09_Tabla_amortizacion'!$J$5:$J$264,'09_Tabla_amortizacion'!$A$5:$A$264,A6,'09_Tabla_amortizacion'!$B$5:$B$264,F6))) | I6: =IF(D6<12,'06_Medicion_inicial'!L6,0) | J6: =SUMIFS('09_Tabla_amortizacion'!$F$5:$F$264,'09_Tabla_amortizacion'!$A$5:$A$264,A6,'09_Tabla_amortizacion'!$B$5:$B$264,">"&F6,'09_Tabla_amortizacion'!$B$5:$B$264,"<="&E6) | K6: =SUMIFS('09_Tabla_amortizacion'!$G$5:$G$264,'09_Tabla_amortizacion'!$A$5:$A$264,A6,'09_Tabla_amortizacion'!$B$5:$B$264,">"&F6,'09_Tabla_amortizacion'!$B$5:$B$264,"<="&E6) | L6: =SUMIFS('09_Tabla_amortizacion'!$I$5:$I$264,'09_Tabla_amortizacion'!$A$5:$A$264,A6,'09_Tabla_amortizacion'!$B$5:$B$264,">"&F6,'09_Tabla_amortizacion'!$B$5:$B$264,"<="&E6) | M6: =H6+I6+J6-K6+L6-G6 | N6: =SUMIFS('09_Tabla_amortizacion'!$J$5:$J$264,'09_Tabla_amortizacion'!$A$5:$A$264,A6,'09_Tabla_amortizacion'!$B$5:$B$264,MIN(E6+12/'05_Plazo'!G6,C6)) | O6: =G6-N6 | P6: =N6 | Q6: =N('03_Contratos'!AC6) | R6: =G6-Q6 | S6: =IF('03_Contratos'!AD6="","",'03_Contratos'!AD6) | T6: =IF(S6="","",O6-S6) | U6: =IF('03_Contratos'!AG6="","",'03_Contratos'!AG6) | V6: =IF(U6="","",J6-U6) | W6: =IF(E6>=C6,0,G6*'06_Medicion_inicial'!J6*(D6-E6*'05_Plazo'!G6)/'05_Plazo'!G6)
A7: C-03 | B7: ='04_Identificacion'!M7 | C7: ='05_Plazo'!H7 | D7: ='05_Plazo'!I7 | E7: =MIN(C7,INT(MAX(D7,0)/'05_Plazo'!G7)) | F7: =MIN(C7,INT(MAX(D7-12,0)/'05_Plazo'!G7)) | G7: =IF(E7=0,'06_Medicion_inicial'!L7,SUMIFS('09_Tabla_amortizacion'!$J$5:$J$264,'09_Tabla_amortizacion'!$A$5:$A$264,A7,'09_Tabla_amortizacion'!$B$5:$B$264,E7)) | H7: =IF(D7<12,0,IF(F7=0,'06_Medicion_inicial'!L7,SUMIFS('09_Tabla_amortizacion'!$J$5:$J$264,'09_Tabla_amortizacion'!$A$5:$A$264,A7,'09_Tabla_amortizacion'!$B$5:$B$264,F7))) | I7: =IF(D7<12,'06_Medicion_inicial'!L7,0) | J7: =SUMIFS('09_Tabla_amortizacion'!$F$5:$F$264,'09_Tabla_amortizacion'!$A$5:$A$264,A7,'09_Tabla_amortizacion'!$B$5:$B$264,">"&F7,'09_Tabla_amortizacion'!$B$5:$B$264,"<="&E7) | K7: =SUMIFS('09_Tabla_amortizacion'!$G$5:$G$264,'09_Tabla_amortizacion'!$A$5:$A$264,A7,'09_Tabla_amortizacion'!$B$5:$B$264,">"&F7,'09_Tabla_amortizacion'!$B$5:$B$264,"<="&E7) | L7: =SUMIFS('09_Tabla_amortizacion'!$I$5:$I$264,'09_Tabla_amortizacion'!$A$5:$A$264,A7,'09_Tabla_amortizacion'!$B$5:$B$264,">"&F7,'09_Tabla_amortizacion'!$B$5:$B$264,"<="&E7) | M7: =H7+I7+J7-K7+L7-G7 | N7: =SUMIFS('09_Tabla_amortizacion'!$J$5:$J$264,'09_Tabla_amortizacion'!$A$5:$A$264,A7,'09_Tabla_amortizacion'!$B$5:$B$264,MIN(E7+12/'05_Plazo'!G7,C7)) | O7: =G7-N7 | P7: =N7 | Q7: =N('03_Contratos'!AC7) | R7: =G7-Q7 | S7: =IF('03_Contratos'!AD7="","",'03_Contratos'!AD7) | T7: =IF(S7="","",O7-S7) | U7: =IF('03_Contratos'!AG7="","",'03_Contratos'!AG7) | V7: =IF(U7="","",J7-U7) | W7: =IF(E7>=C7,0,G7*'06_Medicion_inicial'!J7*(D7-E7*'05_Plazo'!G7)/'05_Plazo'!G7)
A8: C-04 | B8: ='04_Identificacion'!M8 | D8: ='05_Plazo'!I8 | G8: 0 | O8: 0 | P8: 0 | Q8: =N('03_Contratos'!AC8) | R8: =G8-Q8 | S8: =IF('03_Contratos'!AD8="","",'03_Contratos'!AD8)
A9: C-05 | B9: ='04_Identificacion'!M9 | D9: ='05_Plazo'!I9 | G9: 0 | O9: 0 | P9: 0 | Q9: =N('03_Contratos'!AC9) | R9: =G9-Q9 | S9: =IF('03_Contratos'!AD9="","",'03_Contratos'!AD9)
A10: C-06 | B10: ='04_Identificacion'!M10 | C10: ='05_Plazo'!H10 | D10: ='05_Plazo'!I10 | E10: =MIN(C10,INT(MAX(D10,0)/'05_Plazo'!G10)) | F10: =MIN(C10,INT(MAX(D10-12,0)/'05_Plazo'!G10)) | G10: =IF(E10=0,'06_Medicion_inicial'!L10,SUMIFS('09_Tabla_amortizacion'!$J$5:$J$264,'09_Tabla_amortizacion'!$A$5:$A$264,A10,'09_Tabla_amortizacion'!$B$5:$B$264,E10)) | H10: =IF(D10<12,0,IF(F10=0,'06_Medicion_inicial'!L10,SUMIFS('09_Tabla_amortizacion'!$J$5:$J$264,'09_Tabla_amortizacion'!$A$5:$A$264,A10,'09_Tabla_amortizacion'!$B$5:$B$264,F10))) | I10: =IF(D10<12,'06_Medicion_inicial'!L10,0) | J10: =SUMIFS('09_Tabla_amortizacion'!$F$5:$F$264,'09_Tabla_amortizacion'!$A$5:$A$264,A10,'09_Tabla_amortizacion'!$B$5:$B$264,">"&F10,'09_Tabla_amortizacion'!$B$5:$B$264,"<="&E10) | K10: =SUMIFS('09_Tabla_amortizacion'!$G$5:$G$264,'09_Tabla_amortizacion'!$A$5:$A$264,A10,'09_Tabla_amortizacion'!$B$5:$B$264,">"&F10,'09_Tabla_amortizacion'!$B$5:$B$264,"<="&E10) | L10: =SUMIFS('09_Tabla_amortizacion'!$I$5:$I$264,'09_Tabla_amortizacion'!$A$5:$A$264,A10,'09_Tabla_amortizacion'!$B$5:$B$264,">"&F10,'09_Tabla_amortizacion'!$B$5:$B$264,"<="&E10) | M10: =H10+I10+J10-K10+L10-G10 | N10: =SUMIFS('09_Tabla_amortizacion'!$J$5:$J$264,'09_Tabla_amortizacion'!$A$5:$A$264,A10,'09_Tabla_amortizacion'!$B$5:$B$264,MIN(E10+12/'05_Plazo'!G10,C10)) | O10: =G10-N10 | P10: =N10 | Q10: =N('03_Contratos'!AC10) | R10: =G10-Q10 | S10: =IF('03_Contratos'!AD10="","",'03_Contratos'!AD10) | T10: =IF(S10="","",O10-S10) | U10: =IF('03_Contratos'!AG10="","",'03_Contratos'!AG10) | V10: =IF(U10="","",J10-U10) | W10: =IF(E10>=C10,0,G10*'06_Medicion_inicial'!J10*(D10-E10*'05_Plazo'!G10)/'05_Plazo'!G10)
A11: C-07 | B11: ='04_Identificacion'!M11 | C11: ='08_Remedicion'!F11 | D11: ='05_Plazo'!I11 | E11: =MIN(C11,INT(MAX(D11,0)/'05_Plazo'!G11)) | F11: =MIN(C11,INT(MAX(D11-12,0)/'05_Plazo'!G11)) | G11: =IF(E11=0,'06_Medicion_inicial'!L11,SUMIFS('09_Tabla_amortizacion'!$J$5:$J$264,'09_Tabla_amortizacion'!$A$5:$A$264,A11,'09_Tabla_amortizacion'!$B$5:$B$264,E11)) | H11: =IF(D11<12,0,IF(F11=0,'06_Medicion_inicial'!L11,SUMIFS('09_Tabla_amortizacion'!$J$5:$J$264,'09_Tabla_amortizacion'!$A$5:$A$264,A11,'09_Tabla_amortizacion'!$B$5:$B$264,F11))) | I11: =IF(D11<12,'06_Medicion_inicial'!L11,0) | J11: =SUMIFS('09_Tabla_amortizacion'!$F$5:$F$264,'09_Tabla_amortizacion'!$A$5:$A$264,A11,'09_Tabla_amortizacion'!$B$5:$B$264,">"&F11,'09_Tabla_amortizacion'!$B$5:$B$264,"<="&E11) | K11: =SUMIFS('09_Tabla_amortizacion'!$G$5:$G$264,'09_Tabla_amortizacion'!$A$5:$A$264,A11,'09_Tabla_amortizacion'!$B$5:$B$264,">"&F11,'09_Tabla_amortizacion'!$B$5:$B$264,"<="&E11) | L11: =SUMIFS('09_Tabla_amortizacion'!$I$5:$I$264,'09_Tabla_amortizacion'!$A$5:$A$264,A11,'09_Tabla_amortizacion'!$B$5:$B$264,">"&F11,'09_Tabla_amortizacion'!$B$5:$B$264,"<="&E11) | M11: =H11+I11+J11-K11+L11-G11 | N11: =SUMIFS('09_Tabla_amortizacion'!$J$5:$J$264,'09_Tabla_amortizacion'!$A$5:$A$264,A11,'09_Tabla_amortizacion'!$B$5:$B$264,MIN(E11+12/'05_Plazo'!G11,C11)) | O11: =G11-N11 | P11: =N11 | Q11: =N('03_Contratos'!AC11) | R11: =G11-Q11 | S11: =IF('03_Contratos'!AD11="","",'03_Contratos'!AD11) | T11: =IF(S11="","",O11-S11) | U11: =IF('03_Contratos'!AG11="","",'03_Contratos'!AG11) | V11: =IF(U11="","",J11-U11) | W11: =IF(E11>=C11,0,G11*'08_Remedicion'!I11*(D11-E11*'05_Plazo'!G11)/'05_Plazo'!G11)
A12: C-08 | B12: ='04_Identificacion'!M12 | C12: ='05_Plazo'!H12 | D12: ='05_Plazo'!I12 | E12: =MIN(C12,INT(MAX(D12,0)/'05_Plazo'!G12)) | F12: =MIN(C12,INT(MAX(D12-12,0)/'05_Plazo'!G12)) | G12: =IF(E12=0,'06_Medicion_inicial'!L12,SUMIFS('09_Tabla_amortizacion'!$J$5:$J$264,'09_Tabla_amortizacion'!$A$5:$A$264,A12,'09_Tabla_amortizacion'!$B$5:$B$264,E12)) | H12: =IF(D12<12,0,IF(F12=0,'06_Medicion_inicial'!L12,SUMIFS('09_Tabla_amortizacion'!$J$5:$J$264,'09_Tabla_amortizacion'!$A$5:$A$264,A12,'09_Tabla_amortizacion'!$B$5:$B$264,F12))) | I12: =IF(D12<12,'06_Medicion_inicial'!L12,0) | J12: =SUMIFS('09_Tabla_amortizacion'!$F$5:$F$264,'09_Tabla_amortizacion'!$A$5:$A$264,A12,'09_Tabla_amortizacion'!$B$5:$B$264,">"&F12,'09_Tabla_amortizacion'!$B$5:$B$264,"<="&E12) | K12: =SUMIFS('09_Tabla_amortizacion'!$G$5:$G$264,'09_Tabla_amortizacion'!$A$5:$A$264,A12,'09_Tabla_amortizacion'!$B$5:$B$264,">"&F12,'09_Tabla_amortizacion'!$B$5:$B$264,"<="&E12) | L12: =SUMIFS('09_Tabla_amortizacion'!$I$5:$I$264,'09_Tabla_amortizacion'!$A$5:$A$264,A12,'09_Tabla_amortizacion'!$B$5:$B$264,">"&F12,'09_Tabla_amortizacion'!$B$5:$B$264,"<="&E12) | M12: =H12+I12+J12-K12+L12-G12 | N12: =SUMIFS('09_Tabla_amortizacion'!$J$5:$J$264,'09_Tabla_amortizacion'!$A$5:$A$264,A12,'09_Tabla_amortizacion'!$B$5:$B$264,MIN(E12+12/'05_Plazo'!G12,C12)) | O12: =G12-N12 | P12: =N12 | Q12: =N('03_Contratos'!AC12) | R12: =G12-Q12 | S12: =IF('03_Contratos'!AD12="","",'03_Contratos'!AD12) | T12: =IF(S12="","",O12-S12) | U12: =IF('03_Contratos'!AG12="","",'03_Contratos'!AG12) | V12: =IF(U12="","",J12-U12) | W12: =IF(E12>=C12,0,G12*'06_Medicion_inicial'!J12*(D12-E12*'05_Plazo'!G12)/'05_Plazo'!G12)
A13: C-09 | B13: ='04_Identificacion'!M13 | C13: ='05_Plazo'!H13 | D13: ='05_Plazo'!I13 | E13: =MIN(C13,INT(MAX(D13,0)/'05_Plazo'!G13)) | F13: =MIN(C13,INT(MAX(D13-12,0)/'05_Plazo'!G13)) | G13: =IF(E13=0,'06_Medicion_inicial'!L13,SUMIFS('09_Tabla_amortizacion'!$J$5:$J$264,'09_Tabla_amortizacion'!$A$5:$A$264,A13,'09_Tabla_amortizacion'!$B$5:$B$264,E13)) | H13: =IF(D13<12,0,IF(F13=0,'06_Medicion_inicial'!L13,SUMIFS('09_Tabla_amortizacion'!$J$5:$J$264,'09_Tabla_amortizacion'!$A$5:$A$264,A13,'09_Tabla_amortizacion'!$B$5:$B$264,F13))) | I13: =IF(D13<12,'06_Medicion_inicial'!L13,0) | J13: =SUMIFS('09_Tabla_amortizacion'!$F$5:$F$264,'09_Tabla_amortizacion'!$A$5:$A$264,A13,'09_Tabla_amortizacion'!$B$5:$B$264,">"&F13,'09_Tabla_amortizacion'!$B$5:$B$264,"<="&E13) | K13: =SUMIFS('09_Tabla_amortizacion'!$G$5:$G$264,'09_Tabla_amortizacion'!$A$5:$A$264,A13,'09_Tabla_amortizacion'!$B$5:$B$264,">"&F13,'09_Tabla_amortizacion'!$B$5:$B$264,"<="&E13) | L13: =SUMIFS('09_Tabla_amortizacion'!$I$5:$I$264,'09_Tabla_amortizacion'!$A$5:$A$264,A13,'09_Tabla_amortizacion'!$B$5:$B$264,">"&F13,'09_Tabla_amortizacion'!$B$5:$B$264,"<="&E13) | M13: =H13+I13+J13-K13+L13-G13 | N13: =SUMIFS('09_Tabla_amortizacion'!$J$5:$J$264,'09_Tabla_amortizacion'!$A$5:$A$264,A13,'09_Tabla_amortizacion'!$B$5:$B$264,MIN(E13+12/'05_Plazo'!G13,C13)) | O13: =G13-N13 | P13: =N13 | Q13: =N('03_Contratos'!AC13) | R13: =G13-Q13 | S13: =IF('03_Contratos'!AD13="","",'03_Contratos'!AD13) | T13: =IF(S13="","",O13-S13) | U13: =IF('03_Contratos'!AG13="","",'03_Contratos'!AG13) | V13: =IF(U13="","",J13-U13) | W13: =IF(E13>=C13,0,G13*'06_Medicion_inicial'!J13*(D13-E13*'05_Plazo'!G13)/'05_Plazo'!G13)
A14: C-10 | B14: ='04_Identificacion'!M14 | C14: ='05_Plazo'!H14 | D14: ='05_Plazo'!I14 | E14: =MIN(C14,INT(MAX(D14,0)/'05_Plazo'!G14)) | F14: =MIN(C14,INT(MAX(D14-12,0)/'05_Plazo'!G14)) | G14: =IF(E14=0,'06_Medicion_inicial'!L14,SUMIFS('09_Tabla_amortizacion'!$J$5:$J$264,'09_Tabla_amortizacion'!$A$5:$A$264,A14,'09_Tabla_amortizacion'!$B$5:$B$264,E14)) | H14: =IF(D14<12,0,IF(F14=0,'06_Medicion_inicial'!L14,SUMIFS('09_Tabla_amortizacion'!$J$5:$J$264,'09_Tabla_amortizacion'!$A$5:$A$264,A14,'09_Tabla_amortizacion'!$B$5:$B$264,F14))) | I14: =IF(D14<12,'06_Medicion_inicial'!L14,0) | J14: =SUMIFS('09_Tabla_amortizacion'!$F$5:$F$264,'09_Tabla_amortizacion'!$A$5:$A$264,A14,'09_Tabla_amortizacion'!$B$5:$B$264,">"&F14,'09_Tabla_amortizacion'!$B$5:$B$264,"<="&E14) | K14: =SUMIFS('09_Tabla_amortizacion'!$G$5:$G$264,'09_Tabla_amortizacion'!$A$5:$A$264,A14,'09_Tabla_amortizacion'!$B$5:$B$264,">"&F14,'09_Tabla_amortizacion'!$B$5:$B$264,"<="&E14) | L14: =SUMIFS('09_Tabla_amortizacion'!$I$5:$I$264,'09_Tabla_amortizacion'!$A$5:$A$264,A14,'09_Tabla_amortizacion'!$B$5:$B$264,">"&F14,'09_Tabla_amortizacion'!$B$5:$B$264,"<="&E14) | M14: =H14+I14+J14-K14+L14-G14 | N14: =SUMIFS('09_Tabla_amortizacion'!$J$5:$J$264,'09_Tabla_amortizacion'!$A$5:$A$264,A14,'09_Tabla_amortizacion'!$B$5:$B$264,MIN(E14+12/'05_Plazo'!G14,C14)) | O14: =G14-N14 | P14: =N14 | Q14: =N('03_Contratos'!AC14) | R14: =G14-Q14 | S14: =IF('03_Contratos'!AD14="","",'03_Contratos'!AD14) | T14: =IF(S14="","",O14-S14) | U14: =IF('03_Contratos'!AG14="","",'03_Contratos'!AG14) | V14: =IF(U14="","",J14-U14) | W14: =IF(E14>=C14,0,G14*'06_Medicion_inicial'!J14*(D14-E14*'05_Plazo'!G14)/'05_Plazo'!G14)
A15: C-11 | B15: ='04_Identificacion'!M15 | C15: ='05_Plazo'!H15 | D15: ='05_Plazo'!I15 | E15: =MIN(C15,INT(MAX(D15,0)/'05_Plazo'!G15)) | F15: =MIN(C15,INT(MAX(D15-12,0)/'05_Plazo'!G15)) | G15: =IF(E15=0,'06_Medicion_inicial'!L15,SUMIFS('09_Tabla_amortizacion'!$J$5:$J$264,'09_Tabla_amortizacion'!$A$5:$A$264,A15,'09_Tabla_amortizacion'!$B$5:$B$264,E15)) | H15: =IF(D15<12,0,IF(F15=0,'06_Medicion_inicial'!L15,SUMIFS('09_Tabla_amortizacion'!$J$5:$J$264,'09_Tabla_amortizacion'!$A$5:$A$264,A15,'09_Tabla_amortizacion'!$B$5:$B$264,F15))) | I15: =IF(D15<12,'06_Medicion_inicial'!L15,0) | J15: =SUMIFS('09_Tabla_amortizacion'!$F$5:$F$264,'09_Tabla_amortizacion'!$A$5:$A$264,A15,'09_Tabla_amortizacion'!$B$5:$B$264,">"&F15,'09_Tabla_amortizacion'!$B$5:$B$264,"<="&E15) | K15: =SUMIFS('09_Tabla_amortizacion'!$G$5:$G$264,'09_Tabla_amortizacion'!$A$5:$A$264,A15,'09_Tabla_amortizacion'!$B$5:$B$264,">"&F15,'09_Tabla_amortizacion'!$B$5:$B$264,"<="&E15) | L15: =SUMIFS('09_Tabla_amortizacion'!$I$5:$I$264,'09_Tabla_amortizacion'!$A$5:$A$264,A15,'09_Tabla_amortizacion'!$B$5:$B$264,">"&F15,'09_Tabla_amortizacion'!$B$5:$B$264,"<="&E15) | M15: =H15+I15+J15-K15+L15-G15 | N15: =SUMIFS('09_Tabla_amortizacion'!$J$5:$J$264,'09_Tabla_amortizacion'!$A$5:$A$264,A15,'09_Tabla_amortizacion'!$B$5:$B$264,MIN(E15+12/'05_Plazo'!G15,C15)) | O15: =G15-N15 | P15: =N15 | Q15: =N('03_Contratos'!AC15) | R15: =G15-Q15 | S15: =IF('03_Contratos'!AD15="","",'03_Contratos'!AD15) | T15: =IF(S15="","",O15-S15) | U15: =IF('03_Contratos'!AG15="","",'03_Contratos'!AG15) | V15: =IF(U15="","",J15-U15) | W15: =IF(E15>=C15,0,G15*'06_Medicion_inicial'!J15*(D15-E15*'05_Plazo'!G15)/'05_Plazo'!G15)
A16: TOTAL | G16: =SUM(G5:G15) | H16: =SUM(H5:H15) | I16: =SUM(I5:I15) | J16: =SUM(J5:J15) | K16: =SUM(K5:K15) | L16: =SUM(L5:L15) | O16: =SUM(O5:O15) | P16: =SUM(P5:P15) | Q16: =SUM(Q5:Q15) | R16: =SUM(R5:R15) | W16: =SUM(W5:W15)
A18: ⓘ Cómo se calcula esta hoja
A19: Columna | B19: Fórmula (Excel) | C19: Cómo se calcula (sencillo) | D19: Ejemplo con números reales | E19: De dónde viene | F19: Norma
A20: Reconoce | B20: '='04_Identificacion'!M5 | C20: Trae de la hoja 04 (Identificación) si el contrato se reconoce en balance; si no, el resto de la fila queda en cero o en blanco. | D20: Fila 1: «Sí» → Sí | E20: hoja «Identificación, clasificación y exenciones» | F20: —
A21: Períodos finales | B21: '='05_Plazo'!H5 | C21: Número total de cuotas del contrato: los períodos de la hoja 05 o, si hubo remedición, los períodos revisados de la hoja 08. | D21: Fila 1: 60 → 60 | E21: hoja «Plazo y opciones» | F21: —
A22: Meses transcurridos | B22: '='05_Plazo'!I5 | C22: Trae los meses completos transcurridos desde el comienzo hasta el corte, calculados en la hoja 05 (Plazo y opciones). | D22: Fila 1: 24 → 24 | E22: hoja «Plazo y opciones» | F22: —
A23: Períodos vencidos al corte | B23: '=MIN(C5,INT(MAX(D5,0)/'05_Plazo'!G5)) | C23: Divide los meses transcurridos entre los meses por período (hoja 05), sin decimales y sin pasar de los períodos finales: cuotas ya vencidas al corte. | D23: Fila 1: MIN(60; INT(MAX(24; 0)/1)) → 24 | E23: «Períodos finales» (esta hoja), «Meses transcurridos» (esta hoja), hoja «Plazo y opciones» | F23: —
A24: Períodos vencidos al inicio del año | B24: '=MIN(C5,INT(MAX(D5-12,0)/'05_Plazo'!G5)) | C24: Igual que la columna anterior pero con 12 meses menos: las cuotas que ya habían vencido al empezar el ejercicio. | D24: Fila 1: MIN(60; INT(MAX(24-12; 0)/1)) → 12 | E24: «Períodos finales» (esta hoja), «Meses transcurridos» (esta hoja), hoja «Plazo y opciones» | F24: —
A25: Pasivo al corte | B25: '=IF(E5=0,'06_Medicion_inicial'!L5,SUMIFS('09_Tabla_amortizacion'!$J$5:$J$264,'09_Tabla_amortizacion'!$A$5:$A$264,A5,'09_Tabla_amortizacion'!$B$5:$B$264,E5)) | C25: Si no ha vencido ninguna cuota, es el pasivo inicial de la hoja 06; si no, busca en la hoja 09 (Tabla de amortización) el saldo final ajustado del último período vencido al corte. | D25: Fila 1: IF(24=0; 68.381,69; SUMIFS([«Saldo final ajustado» de «Tabla de amortización», 260 filas]; [«Contrato» de «Tabla de amortización», 260 filas]; «C-01»; [«Período» de «Tabla de amortización», 260 filas]; 24)) → 45.562,13 | E25: «Períodos vencidos al corte» (esta hoja), «Contrato» (esta hoja), hoja «Medición inicial: pasivo y activo», hoja «Tabla de amortización» | F25: —
A26: Pasivo al inicio del año | B26: '=IF(D5<12,0,IF(F5=0,'06_Medicion_inicial'!L5,SUMIFS('09_Tabla_amortizacion'!$J$5:$J$264,'09_Tabla_amortizacion'!$A$5:$A$264,A5,'09_Tabla_amortizacion'!$B$5:$B$264,F5))) | C26: Si el contrato empezó hace menos de 12 meses es 0; si no, el pasivo inicial (sin cuotas vencidas) o el saldo de la hoja 09 en el último período vencido al inicio del año. | D26: Fila 1: IF(24<12; 0; IF(12=0; 68.381,69; SUMIFS([«Saldo final ajustado» de «Tabla de amortización», 260 filas]; [«Contrato» de «Tabla de amortización», 260 filas]; «C-01»; [«Período» de «Tabla de amortización», 260 filas]; 12))) → 57.617,75 | E26: «Meses transcurridos» (esta hoja), «Períodos vencidos al inicio del año» (esta hoja), «Contrato» (esta hoja), hoja «Medición inicial: pasivo y activo», hoja «Tabla de amortización» | F26: —
A27: Altas del año | B27: '=IF(D5<12,'06_Medicion_inicial'!L5,0) | C27: Si el contrato comenzó dentro de los últimos 12 meses, su pasivo inicial (hoja 06) es un alta del año; si es anterior, 0. | D27: Fila 1: IF(24<12; 68.381,69; 0) → 0,00 | E27: «Meses transcurridos» (esta hoja), hoja «Medición inicial: pasivo y activo» | F27: —
A28: Interés del ejercicio | B28: '=SUMIFS('09_Tabla_amortizacion'!$F$5:$F$264,'09_Tabla_amortizacion'!$A$5:$A$264,A5,'09_Tabla_amortizacion'!$B$5:$B$264,">"&F5,'09_Tabla_amortizacion'!$B$5:$B$264,"<="&E5) | C28: Suma el interés de la hoja 09 (Tabla de amortización) de los períodos de este contrato que vencen en el ejercicio: después de los vencidos al inicio del año y hasta los vencidos al corte. | D28: Fila 1: SUMIFS([«Interés (37)» de «Tabla de amortización», 260 filas]; [«Contrato» de «Tabla de amortización», 260 filas]; «C-01»; [«Período» de «Tabla de amortización», 260 filas]; ">"&12; [«Período» de «Tabla de amortización», 260 filas]; "<="&24) → 5.944,38 | E28: «Contrato» (esta hoja), «Períodos vencidos al inicio del año» (esta hoja), «Períodos vencidos al corte» (esta hoja), hoja «Tabla de amortización» | F28: —
A29: Pagos del ejercicio | B29: '=SUMIFS('09_Tabla_amortizacion'!$G$5:$G$264,'09_Tabla_amortizacion'!$A$5:$A$264,A5,'09_Tabla_amortizacion'!$B$5:$B$264,">"&F5,'09_Tabla_amortizacion'!$B$5:$B$264,"<="&E5) | C29: Suma los pagos de la hoja 09 (Tabla de amortización) de los períodos de este contrato que vencen dentro del ejercicio. | D29: Fila 1: SUMIFS([«Pago» de «Tabla de amortización», 260 filas]; [«Contrato» de «Tabla de amortización», 260 filas]; «C-01»; [«Período» de «Tabla de amortización», 260 filas]; ">"&12; [«Período» de «Tabla de amortización», 260 filas]; "<="&24) → 18.000,00 | E29: «Contrato» (esta hoja), «Períodos vencidos al inicio del año» (esta hoja), «Períodos vencidos al corte» (esta hoja), hoja «Tabla de amortización» | F29: —
A30: Remedición del ejercicio | B30: '=SUMIFS('09_Tabla_amortizacion'!$I$5:$I$264,'09_Tabla_amortizacion'!$A$5:$A$264,A5,'09_Tabla_amortizacion'!$B$5:$B$264,">"&F5,'09_Tabla_amortizacion'!$B$5:$B$264,"<="&E5) | C30: Suma los ajustes por remedición de la hoja 09 de los períodos de este contrato que caen dentro del ejercicio. | D30: Fila 1: SUMIFS([«Remedición» de «Tabla de amortización», 260 filas]; [«Contrato» de «Tabla de amortización», 260 filas]; «C-01»; [«Período» de «Tabla de amortización», 260 filas]; ">"&12; [«Período» de «Tabla de amortización», 260 filas]; "<="&24) → 0,00 | E30: «Contrato» (esta hoja), «Períodos vencidos al inicio del año» (esta hoja), «Períodos vencidos al corte» (esta hoja), hoja «Tabla de amortización» | F30: —
... A41: Interés devengado no vencido (informativo) | B41: '=IF(E5>=C5,0,G5*'06_Medicion_inicial'!J5*(D5-E5*'05_Plazo'!G5)/'05_Plazo'!G5) | C41: Si quedan cuotas por vencer, estima el interés que corre desde el último vencimiento hasta el corte: pasivo al corte × tasa periódica × meses del período en curso ÷ meses por período. Es informativo y no entra en el recálculo. | D41: Fila 1: IF(24>=60; 0; 45.562,13*0,95 %*(24-24*1)/1) → 0,00 | E41: «Períodos vencidos al corte» (esta hoja), «Períodos finales» (esta hoja), «Pasivo al corte» (esta hoja), «Meses transcurridos» (esta hoja), hoja «Medición inicial: pasivo y activo», hoja «Plazo y opciones» | F41: —

Sheet 11_Derecho_uso
A1: Depreciación y deterioro del activo | H1: ⟵ Inicio | I1: ◀ Anterior | J1: Siguiente ▶
A2: Arrendamientos · Cliente de muestra S.A. · corte 2025-12-31
A4: Contrato | B4: Reconoce | C4: Costo inicial | D4: Meses de depreciación | E4: Meses transcurridos | F4: Meses al evento | G4: Ajuste por remedición | H4: Meses de depreciación revisados | I4: Depreciación acumulada al corte | J4: Depreciación acumulada al inicio del año | K4: Depreciación del ejercicio | L4: Neto antes de deterioro | M4: Importe recuperable | N4: Deterioro (33 / Secc. 27) | O4: Neto recalculado | P4: Registrado neto | Q4: Diferencia | R4: Depreciación registrada | S4: Diferencia depreciación
A5: C-01 | B5: ='04_Identificacion'!M5 | C5: ='06_Medicion_inicial'!Q5 | D5: ='05_Plazo'!J5 | E5: =MAX('05_Plazo'!I5,0) | G5: 0 | I5: =C5*MIN(E5,D5)/D5 | J5: =C5*MIN(MAX(E5-12,0),D5)/D5 | K5: =I5-J5 | L5: =C5+G5-I5 | M5: =IF('03_Contratos'!AN5="","",'03_Contratos'!AN5) | N5: =IF(M5="",0,MAX(0,L5-M5)) | O5: =L5-N5 | P5: =N('03_Contratos'!AE5) | Q5: =O5-P5 | R5: =IF('03_Contratos'!AF5="","",'03_Contratos'!AF5) | S5: =IF(R5="","",K5-R5)
A6: C-02 | B6: ='04_Identificacion'!M6 | C6: ='06_Medicion_inicial'!Q6 | D6: ='05_Plazo'!J6 | E6: =MAX('05_Plazo'!I6,0) | G6: 0 | I6: =C6*MIN(E6,D6)/D6 | J6: =C6*MIN(MAX(E6-12,0),D6)/D6 | K6: =I6-J6 | L6: =C6+G6-I6 | M6: =IF('03_Contratos'!AN6="","",'03_Contratos'!AN6) | N6: =IF(M6="",0,MAX(0,L6-M6)) | O6: =L6-N6 | P6: =N('03_Contratos'!AE6) | Q6: =O6-P6 | R6: =IF('03_Contratos'!AF6="","",'03_Contratos'!AF6) | S6: =IF(R6="","",K6-R6)
A7: C-03 | B7: ='04_Identificacion'!M7 | C7: ='06_Medicion_inicial'!Q7 | D7: ='05_Plazo'!J7 | E7: =MAX('05_Plazo'!I7,0) | G7: 0 | I7: =C7*MIN(E7,D7)/D7 | J7: =C7*MIN(MAX(E7-12,0),D7)/D7 | K7: =I7-J7 | L7: =C7+G7-I7 | M7: =IF('03_Contratos'!AN7="","",'03_Contratos'!AN7) | N7: =IF(M7="",0,MAX(0,L7-M7)) | O7: =L7-N7 | P7: =N('03_Contratos'!AE7) | Q7: =O7-P7 | R7: =IF('03_Contratos'!AF7="","",'03_Contratos'!AF7) | S7: =IF(R7="","",K7-R7)
A8: C-04 | B8: ='04_Identificacion'!M8 | K8: 0 | N8: 0 | O8: 0 | P8: =N('03_Contratos'!AE8) | Q8: =O8-P8
A9: C-05 | B9: ='04_Identificacion'!M9 | K9: 0 | N9: 0 | O9: 0 | P9: =N('03_Contratos'!AE9) | Q9: =O9-P9
A10: C-06 | B10: ='04_Identificacion'!M10 | C10: ='06_Medicion_inicial'!Q10 | D10: ='05_Plazo'!J10 | E10: =MAX('05_Plazo'!I10,0) | G10: 0 | I10: =C10*MIN(E10,D10)/D10 | J10: =C10*MIN(MAX(E10-12,0),D10)/D10 | K10: =I10-J10 | L10: =C10+G10-I10 | M10: =IF('03_Contratos'!AN10="","",'03_Contratos'!AN10) | N10: =IF(M10="",0,MAX(0,L10-M10)) | O10: =L10-N10 | P10: =N('03_Contratos'!AE10) | Q10: =O10-P10 | R10: =IF('03_Contratos'!AF10="","",'03_Contratos'!AF10) | S10: =IF(R10="","",K10-R10)
A11: C-07 | B11: ='04_Identificacion'!M11 | C11: ='06_Medicion_inicial'!Q11 | D11: ='05_Plazo'!J11 | E11: =MAX('05_Plazo'!I11,0) | F11: ='08_Remedicion'!D11*'05_Plazo'!G11 | G11: ='08_Remedicion'!L11 | H11: =IF('03_Contratos'!V11="Sí",D11,IF('03_Contratos'!W11="",'08_Remedicion'!E11,MIN('08_Remedicion'!E11,'03_Contratos'!W11))) | I11: =IF(E11<=F11,C11*MIN(E11,D11)/D11,C11*MIN(F11,D11)/D11+(C11*(1-MIN(F11,D11)/D11)+G11)*MIN(E11-F11,H11-F11)/(H11-F11)) | J11: =IF(MAX(E11-12,0)<=F11,C11*MIN(MAX(E11-12,0),D11)/D11,C11*MIN(F11,D11)/D11+(C11*(1-MIN(F11,D11)/D11)+G11)*MIN(MAX(E11-12,0)-F11,H11-F11)/(H11-F11)) | K11: =I11-J11 | L11: =C11+G11-I11 | M11: =IF('03_Contratos'!AN11="","",'03_Contratos'!AN11) | N11: =IF(M11="",0,MAX(0,L11-M11)) | O11: =L11-N11 | P11: =N('03_Contratos'!AE11) | Q11: =O11-P11 | R11: =IF('03_Contratos'!AF11="","",'03_Contratos'!AF11) | S11: =IF(R11="","",K11-R11)
A12: C-08 | B12: ='04_Identificacion'!M12 | C12: ='06_Medicion_inicial'!Q12 | D12: ='05_Plazo'!J12 | E12: =MAX('05_Plazo'!I12,0) | G12: 0 | I12: =C12*MIN(E12,D12)/D12 | J12: =C12*MIN(MAX(E12-12,0),D12)/D12 | K12: =I12-J12 | L12: =C12+G12-I12 | M12: =IF('03_Contratos'!AN12="","",'03_Contratos'!AN12) | N12: =IF(M12="",0,MAX(0,L12-M12)) | O12: =L12-N12 | P12: =N('03_Contratos'!AE12) | Q12: =O12-P12 | R12: =IF('03_Contratos'!AF12="","",'03_Contratos'!AF12) | S12: =IF(R12="","",K12-R12)
A13: C-09 | B13: ='04_Identificacion'!M13 | C13: ='06_Medicion_inicial'!Q13 | D13: ='05_Plazo'!J13 | E13: =MAX('05_Plazo'!I13,0) | G13: 0 | I13: =C13*MIN(E13,D13)/D13 | J13: =C13*MIN(MAX(E13-12,0),D13)/D13 | K13: =I13-J13 | L13: =C13+G13-I13 | M13: =IF('03_Contratos'!AN13="","",'03_Contratos'!AN13) | N13: =IF(M13="",0,MAX(0,L13-M13)) | O13: =L13-N13 | P13: =N('03_Contratos'!AE13) | Q13: =O13-P13 | R13: =IF('03_Contratos'!AF13="","",'03_Contratos'!AF13) | S13: =IF(R13="","",K13-R13)
A14: C-10 | B14: ='04_Identificacion'!M14 | C14: ='06_Medicion_inicial'!Q14 | D14: ='05_Plazo'!J14 | E14: =MAX('05_Plazo'!I14,0) | G14: 0 | I14: =C14*MIN(E14,D14)/D14 | J14: =C14*MIN(MAX(E14-12,0),D14)/D14 | K14: =I14-J14 | L14: =C14+G14-I14 | M14: =IF('03_Contratos'!AN14="","",'03_Contratos'!AN14) | N14: =IF(M14="",0,MAX(0,L14-M14)) | O14: =L14-N14 | P14: =N('03_Contratos'!AE14) | Q14: =O14-P14 | R14: =IF('03_Contratos'!AF14="","",'03_Contratos'!AF14) | S14: =IF(R14="","",K14-R14)
A15: C-11 | B15: ='04_Identificacion'!M15 | C15: ='06_Medicion_inicial'!Q15 | D15: ='05_Plazo'!J15 | E15: =MAX('05_Plazo'!I15,0) | G15: 0 | I15: =C15*MIN(E15,D15)/D15 | J15: =C15*MIN(MAX(E15-12,0),D15)/D15 | K15: =I15-J15 | L15: =C15+G15-I15 | M15: =IF('03_Contratos'!AN15="","",'03_Contratos'!AN15) | N15: =IF(M15="",0,MAX(0,L15-M15)) | O15: =L15-N15 | P15: =N('03_Contratos'!AE15) | Q15: =O15-P15 | R15: =IF('03_Contratos'!AF15="","",'03_Contratos'!AF15) | S15: =IF(R15="","",K15-R15)
A16: TOTAL | K16: =SUM(K5:K15) | N16: =SUM(N5:N15) | O16: =SUM(O5:O15) | P16: =SUM(P5:P15) | Q16: =SUM(Q5:Q15)
A18: ⓘ Cómo se calcula esta hoja
A19: Columna | B19: Fórmula (Excel) | C19: Cómo se calcula (sencillo) | D19: Ejemplo con números reales | E19: De dónde viene | F19: Norma
A20: Reconoce | B20: '='04_Identificacion'!M5 | C20: Trae de la hoja 04 (Identificación) si el contrato se reconoce; solo los reconocidos tienen un activo que depreciar. | D20: Fila 1: «Sí» → Sí | E20: hoja «Identificación, clasificación y exenciones» | F20: —
A21: Costo inicial | B21: '='06_Medicion_inicial'!Q5 | C21: Trae el costo inicial del activo (derecho de uso o activo arrendado) calculado en la hoja 06 (Medición inicial). | D21: Fila 1: 68.381,69 → 68.381,69 | E21: hoja «Medición inicial: pasivo y activo» | F21: —
A22: Meses de depreciación | B22: '='05_Plazo'!J5 | C22: Trae de la hoja 05 (Plazo y opciones) el número de meses en que se deprecia el activo. | D22: Fila 1: 60 → 60 | E22: hoja «Plazo y opciones» | F22: —
A23: Meses transcurridos | B23: '=MAX('05_Plazo'!I5,0) | C23: Trae de la hoja 05 los meses transcurridos desde el comienzo hasta el corte; si fueran negativos, pone 0. | D23: Fila 1: MAX(24; 0) → 24 | E23: hoja «Plazo y opciones» | F23: —
A24: Meses al evento | B24: '='08_Remedicion'!D11*'05_Plazo'!G11 | C24: Si hubo remedición, multiplica los períodos al evento de la hoja 08 por los meses por período (hoja 05): meses desde el comienzo hasta la remedición. | D24: Fila 7: 2*12 → 24 | E24: hoja «Remedición y modificaciones», hoja «Plazo y opciones» | F24: —
A25: Ajuste por remedición | B25: '='08_Remedicion'!L11 | C25: Trae de la hoja 08 (Remedición) el ajuste del pasivo, que se suma o resta al activo; sin evento es 0. | D25: Fila 7: 3.247,31 → 3.247,31 | E25: hoja «Remedición y modificaciones» | F25: —
A26: Meses de depreciación revisados | B26: '=IF('03_Contratos'!V11="Sí",D11,IF('03_Contratos'!W11="",'08_Remedicion'!E11,MIN('08_Remedicion'!E11,'03_Contratos'!W11))) | C26: Tras la remedición: si la compra es razonablemente cierta, mantiene los meses de depreciación; si no, el menor entre el plazo revisado (hoja 08) y la vida útil (hoja 03), o el plazo revisado si no hay vida útil. | D26: Fila 7: IF((vacío)="Sí"; 60; IF((vacío)=""; 60; MIN(60; (vacío)))) → 60 | E26: «Meses de depreciación» (esta hoja), hoja «Universo de contratos», hoja «Remedición y modificaciones» | F26: —
A27: Depreciación acumulada al corte | B27: '=C5*MIN(E5,D5)/D5 | C27: Deprecia el costo inicial en línea recta por los meses transcurridos, sin pasar de los meses de depreciación. Si hubo remedición, desde el evento reparte lo que faltaba más el ajuste en los meses que quedan hasta los meses revisados. | D27: Fila 1: 68.381,69*MIN(24; 60)/60 → 27.352,68 | E27: «Costo inicial» (esta hoja), «Meses transcurridos» (esta hoja), «Meses de depreciación» (esta hoja) | F27: —
A28: Depreciación acumulada al inicio del año | B28: '=C5*MIN(MAX(E5-12,0),D5)/D5 | C28: Misma cuenta que la depreciación acumulada al corte, pero con 12 meses menos (nunca menos de 0): lo depreciado hasta el inicio del ejercicio. | D28: Fila 1: 68.381,69*MIN(MAX(24-12; 0); 60)/60 → 13.676,34 | E28: «Costo inicial» (esta hoja), «Meses transcurridos» (esta hoja), «Meses de depreciación» (esta hoja) | F28: —
A29: Depreciación del ejercicio | B29: '=I5-J5 | C29: Depreciación acumulada al corte menos la acumulada al inicio del año: el gasto de depreciación del ejercicio. | D29: Fila 1: 27.352,68-13.676,34 → 13.676,34 | E29: «Depreciación acumulada al corte» (esta hoja), «Depreciación acumulada al inicio del año» (esta hoja) | F29: —
A30: Neto antes de deterioro | B30: '=C5+G5-I5 | C30: Costo inicial más el ajuste por remedición menos la depreciación acumulada al corte. | D30: Fila 1: 68.381,69+0,00-27.352,68 → 41.029,02 | E30: «Costo inicial» (esta hoja), «Ajuste por remedición» (esta hoja), «Depreciación acumulada al corte» (esta hoja) | F30: —
... A37: Diferencia depreciación | B37: '=IF(R5="","",K5-R5) | C37: Resta la depreciación registrada de la depreciación del ejercicio recalculada; en blanco si no hay depreciación registrada. | D37: Fila 1: IF((vacío)=""; ""; 13.676,34-(vacío)) → (en blanco) | E37: «Depreciación registrada» (esta hoja), «Depreciación del ejercicio» (esta hoja) | F37: —

Sheet 12_Gasto_lineal
A1: Gasto lineal: exentos y operativos | H1: ⟵ Inicio | I1: ◀ Anterior | J1: Siguiente ▶
A2: Arrendamientos · Cliente de muestra S.A. · corte 2025-12-31
A4: Contrato | B4: Tratamiento | C4: Pagos totales del plazo | D4: Plazo (meses) | E4: Meses del contrato en el año | F4: Gasto lineal del ejercicio (6 / 20.15)
A5: C-01 | B5: Reconocido en balance
A6: C-02 | B6: Reconocido en balance
A7: C-03 | B7: Reconocido en balance
A8: C-04 | B8: Exento: bajo valor | C8: ='07_Pagos_variables'!G8*'05_Plazo'!H8 | D8: ='05_Plazo'!E8 | E8: =MIN(MAX('05_Plazo'!I8,0),D8)-MIN(MAX('05_Plazo'!I8-12,0),D8) | F8: =C8/D8*E8
A9: C-05 | B9: Exento: corto plazo | C9: ='07_Pagos_variables'!G9*'05_Plazo'!H9 | D9: ='05_Plazo'!E9 | E9: =MIN(MAX('05_Plazo'!I9,0),D9)-MIN(MAX('05_Plazo'!I9-12,0),D9) | F9: =C9/D9*E9
A10: C-06 | B10: Reconocido en balance
A11: C-07 | B11: Reconocido en balance
A12: C-08 | B12: Reconocido en balance
A13: C-09 | B13: Reconocido en balance
A14: C-10 | B14: Reconocido en balance
A15: C-11 | B15: Reconocido en balance
A16: TOTAL | F16: =SUM(F5:F15)
A18: ⓘ Cómo se calcula esta hoja
A19: Columna | B19: Fórmula (Excel) | C19: Cómo se calcula (sencillo) | D19: Ejemplo con números reales | E19: De dónde viene | F19: Norma
A20: Pagos totales del plazo | B20: '='07_Pagos_variables'!G8*'05_Plazo'!H8 | C20: Multiplica el pago usado en la medición (hoja 07) por el número de períodos del contrato (hoja 05): total a pagar en todo el plazo. | D20: Fila 4: 80,00*24 → 1.920,00 | E20: hoja «Pago base, componente indexado y pagos variables», hoja «Plazo y opciones» | F20: —
A21: Plazo (meses) | B21: '='05_Plazo'!E8 | C21: Trae el plazo del arrendamiento en meses de la hoja 05 (Plazo y opciones). | D21: Fila 4: 24 → 24 | E21: hoja «Plazo y opciones» | F21: —
A22: Meses del contrato en el año | B22: '=MIN(MAX('05_Plazo'!I8,0),D8)-MIN(MAX('05_Plazo'!I8-12,0),D8) | C22: Meses transcurridos al corte (hoja 05) menos los transcurridos al inicio del año, ambos sin pasar del plazo: los meses del contrato que caen dentro del ejercicio. | D22: Fila 4: MIN(MAX(12; 0); 24)-MIN(MAX(12-12; 0); 24) → 12 | E22: «Plazo (meses)» (esta hoja), hoja «Plazo y opciones» | F22: —
A23: Gasto lineal del ejercicio (6 / 20.15) | B23: '=C8/D8*E8 | C23: Reparte los pagos totales en partes iguales por mes (pagos ÷ plazo) y multiplica por los meses del contrato en el año. | D23: Fila 4: 1.920,00/24*12 → 960,00 | E23: «Pagos totales del plazo» (esta hoja), «Plazo (meses)» (esta hoja), «Meses del contrato en el año» (esta hoja) | F23: —

Sheet 13_Venta_arr_posterior
A1: Venta con arrendamiento posterior: medición inicial | H1: ⟵ Inicio | I1: ◀ Anterior | J1: Siguiente ▶
A2: Arrendamientos · Cliente de muestra S.A. · corte 2025-12-31
A4: Contrato | B4: Precio de venta | C4: Valor razonable | D4: Importe en libros previo | E4: Financiación adicional (101 b) | F4: Pago anticipado (101 a) | G4: Pasivo inicial | H4: Parte del arrendamiento | I4: Derecho de uso conservado (100 a) | J4: Ganancia total | K4: Ganancia reconocida (derechos transferidos) | L4: Ganancia registrada | M4: Diferencia
A5: C-01 | B5: No aplica
A6: C-02 | B6: No aplica
A7: C-03 | B7: No aplica
A8: C-04 | B8: No aplica
A9: C-05 | B9: No aplica
A10: C-06 | B10: No aplica
A11: C-07 | B11: No aplica
A12: C-08 | B12: ='03_Contratos'!AP12 | C12: ='03_Contratos'!X12 | D12: ='03_Contratos'!AQ12 | E12: =MAX(B12-C12,0) | F12: =MAX(C12-B12,0) | G12: ='06_Medicion_inicial'!L12 | H12: =G12-E12+F12 | I12: =D12*H12/C12 | J12: =C12-D12 | K12: =J12*(C12-H12)/C12 | L12: =IF('03_Contratos'!AR12="","",'03_Contratos'!AR12) | M12: =IF(L12="","",K12-L12)
A13: C-09 | B13: No aplica
A14: C-10 | B14: No aplica
A15: C-11 | B15: No aplica
A17: ⓘ Cómo se calcula esta hoja
A18: Columna | B18: Fórmula (Excel) | C18: Cómo se calcula (sencillo) | D18: Ejemplo con números reales | E18: De dónde viene | F18: Norma
A19: Precio de venta | B19: '='03_Contratos'!AP12 | C19: Trae el precio de venta del activo, de la hoja 03 (Universo de contratos). | D19: Fila 8: 2.000.000,00 → 2.000.000,00 | E19: hoja «Universo de contratos» | F19: —
A20: Valor razonable | B20: '='03_Contratos'!X12 | C20: Trae el valor razonable del activo vendido, de la hoja 03 (Universo de contratos). | D20: Fila 8: 1.800.000,00 → 1.800.000,00 | E20: hoja «Universo de contratos» | F20: —
A21: Importe en libros previo | B21: '='03_Contratos'!AQ12 | C21: Trae el importe en libros del activo antes de la venta, de la hoja 03 (Universo de contratos). | D21: Fila 8: 1.000.000,00 → 1.000.000,00 | E21: hoja «Universo de contratos» | F21: —
A22: Financiación adicional (101 b) | B22: '=MAX(B12-C12,0) | C22: Si el precio de venta supera el valor razonable, el exceso es financiación adicional recibida del comprador; si no, 0. | D22: Fila 8: MAX(2.000.000,00-1.800.000,00; 0) → 200.000,00 | E22: «Precio de venta» (esta hoja), «Valor razonable» (esta hoja) | F22: —
A23: Pago anticipado (101 a) | B23: '=MAX(C12-B12,0) | C23: Si el precio de venta es menor que el valor razonable, la diferencia es un pago anticipado del arrendamiento; si no, 0. | D23: Fila 8: MAX(1.800.000,00-2.000.000,00; 0) → 0,00 | E23: «Valor razonable» (esta hoja), «Precio de venta» (esta hoja) | F23: —
A24: Pasivo inicial | B24: '='06_Medicion_inicial'!L12 | C24: Trae el pasivo inicial del arrendamiento posterior calculado en la hoja 06 (Medición inicial). | D24: Fila 8: 1.459.199,02 → 1.459.199,02 | E24: hoja «Medición inicial: pasivo y activo» | F24: —
A25: Parte del arrendamiento | B25: '=G12-E12+F12 | C25: Pasivo inicial menos la financiación adicional más el pago anticipado: el valor de los pagos que corresponde al arrendamiento. | D25: Fila 8: 1.459.199,02-200.000,00+0,00 → 1.259.199,02 | E25: «Pasivo inicial» (esta hoja), «Financiación adicional (101 b)» (esta hoja), «Pago anticipado (101 a)» (esta hoja) | F25: —
A26: Derecho de uso conservado (100 a) | B26: '=D12*H12/C12 | C26: Importe en libros previo × parte del arrendamiento ÷ valor razonable: la porción del importe en libros que se conserva como derecho de uso. | D26: Fila 8: 1.000.000,00*1.259.199,02/1.800.000,00 → 699.555,01 | E26: «Importe en libros previo» (esta hoja), «Parte del arrendamiento» (esta hoja), «Valor razonable» (esta hoja) | F26: —
A27: Ganancia total | B27: '=C12-D12 | C27: Valor razonable menos importe en libros previo: la ganancia total que tendría la venta. | D27: Fila 8: 1.800.000,00-1.000.000,00 → 800.000,00 | E27: «Valor razonable» (esta hoja), «Importe en libros previo» (esta hoja) | F27: —
A28: Ganancia reconocida (derechos transferidos) | B28: '=J12*(C12-H12)/C12 | C28: Ganancia total × (valor razonable − parte del arrendamiento) ÷ valor razonable: solo la ganancia de los derechos transferidos al comprador. | D28: Fila 8: 800.000,00*(1.800.000,00-1.259.199,02)/1.800.000,00 → 240.355,99 | E28: «Ganancia total» (esta hoja), «Valor razonable» (esta hoja), «Parte del arrendamiento» (esta hoja) | F28: —
A29: Ganancia registrada | B29: '=IF('03_Contratos'!AR12="","",'03_Contratos'!AR12) | C29: Trae la ganancia en la venta que registró el cliente, de la hoja 03 (Universo de contratos); en blanco si no se informó. | D29: Fila 8: IF(800.000,00=""; ""; 800.000,00) → 800.000,00 | E29: hoja «Universo de contratos» | F29: —
A30: Diferencia | B30: '=IF(L12="","",K12-L12) | C30: Resta la ganancia registrada de la ganancia reconocida recalculada; en blanco si no hay ganancia registrada. | D30: Fila 8: IF(800.000,00=""; ""; 240.355,99-800.000,00) → -559.644,01 | E30: «Ganancia registrada» (esta hoja), «Ganancia reconocida (derechos transferidos)» (esta hoja) | F30: —

Sheet 14_Venta_medicion_post
A1: Venta con arrendamiento posterior: medición posterior | H1: ⟵ Inicio | I1: ◀ Anterior | J1: Siguiente ▶
A2: Arrendamientos · Cliente de muestra S.A. · corte 2025-12-31
A4: Contrato | B4: Tratamiento y marco | C4: Pasivo al inicio del ejercicio | D4: Altas del ejercicio | E4: Interés del ejercicio (36–37) | F4: Pagos fijos del ejercicio | G4: Pagos variables del ejercicio (38 b) | H4: Remedición del ejercicio (40–43) | I4: Pasivo al corte | J4: Comprobación del pasivo (0) | K4: Derecho de uso conservado inicial (100 a) | L4: Depreciación del ejercicio (29–35) | M4: Derecho de uso neto al corte | N4: Ganancia reconocida en la venta | O4: Ganancia posterior registrada | P4: Control 102A: ganancia sobre el derecho de uso conservado (0)
A5: C-01 | B5: No aplica
A6: C-02 | B6: No aplica
A7: C-03 | B7: No aplica
A8: C-04 | B8: No aplica
A9: C-05 | B9: No aplica
A10: C-06 | B10: No aplica
A11: C-07 | B11: No aplica
A12: C-08 | B12: NIIF 16 párr. 102A: párr. 29–35 al derecho de uso conservado y 36–46 al pasivo | C12: ='10_Pasivo_corte'!H12 | D12: ='10_Pasivo_corte'!I12 | E12: ='10_Pasivo_corte'!J12 | F12: ='10_Pasivo_corte'!K12 | G12: =IF('07_Pagos_variables'!L12="","",'07_Pagos_variables'!L12) | H12: ='10_Pasivo_corte'!L12 | I12: ='10_Pasivo_corte'!G12 | J12: ='10_Pasivo_corte'!M12 | K12: ='11_Derecho_uso'!C12 | L12: ='11_Derecho_uso'!K12 | M12: ='11_Derecho_uso'!O12 | N12: ='13_Venta_arr_posterior'!K12 | O12: =IF('03_Contratos'!AS12="","",'03_Contratos'!AS12) | P12: =IF(O12<>"",O12,"")
A13: C-09 | B13: No aplica
A14: C-10 | B14: No aplica
A15: C-11 | B15: No aplica
A16: TOTAL | I16: =SUM(I5:I15) | M16: =SUM(M5:M15) | P16: =SUM(P5:P15)
A18: ⓘ Cómo se calcula esta hoja
A19: Columna | B19: Fórmula (Excel) | C19: Cómo se calcula (sencillo) | D19: Ejemplo con números reales | E19: De dónde viene | F19: Norma
A20: Pasivo al inicio del ejercicio | B20: '='10_Pasivo_corte'!H12 | C20: Trae el pasivo al inicio del año de este contrato, de la hoja 10 (Pasivo al corte). | D20: Fila 8: 1.459.199,02 → 1.459.199,02 | E20: hoja «Pasivo al corte: corriente y no corriente» | F20: —
A21: Altas del ejercicio | B21: '='10_Pasivo_corte'!I12 | C21: Trae las altas del año de este contrato, de la hoja 10 (Pasivo al corte). | D21: Fila 8: 0,00 → 0,00 | E21: hoja «Pasivo al corte: corriente y no corriente» | F21: —
A22: Interés del ejercicio (36–37) | B22: '='10_Pasivo_corte'!J12 | C22: Trae el interés del ejercicio recalculado en la hoja 10 (Pasivo al corte). | D22: Fila 8: 65.663,96 → 65.663,96 | E22: hoja «Pasivo al corte: corriente y no corriente» | F22: —
A23: Pagos fijos del ejercicio | B23: '='10_Pasivo_corte'!K12 | C23: Trae los pagos del ejercicio de la hoja 10 (Pasivo al corte), según la tabla de amortización. | D23: Fila 8: 120.000,00 → 120.000,00 | E23: hoja «Pasivo al corte: corriente y no corriente» | F23: —
A24: Pagos variables del ejercicio (38 b) | B24: '=IF('07_Pagos_variables'!L12="","",'07_Pagos_variables'!L12) | C24: Trae el gasto del ejercicio por pagos variables de la hoja 07; en blanco si allí quedó en blanco. | D24: Fila 8: IF(0,00=""; ""; 0,00) → 0,00 | E24: hoja «Pago base, componente indexado y pagos variables» | F24: —
A25: Remedición del ejercicio (40–43) | B25: '='10_Pasivo_corte'!L12 | C25: Trae la remedición del ejercicio de la hoja 10 (Pasivo al corte) para este contrato. | D25: Fila 8: 0,00 → 0,00 | E25: hoja «Pasivo al corte: corriente y no corriente» | F25: —
A26: Pasivo al corte | B26: '='10_Pasivo_corte'!G12 | C26: Trae el pasivo al corte recalculado de la hoja 10 (Pasivo al corte). | D26: Fila 8: 1.404.862,97 → 1.404.862,97 | E26: hoja «Pasivo al corte: corriente y no corriente» | F26: —
A27: Comprobación del pasivo (0) | B27: '='10_Pasivo_corte'!M12 | C27: Trae de la hoja 10 la comprobación del movimiento del pasivo del año; debe dar 0. | D27: Fila 8: 0,00 → 0,00 | E27: hoja «Pasivo al corte: corriente y no corriente» | F27: —
A28: Derecho de uso conservado inicial (100 a) | B28: '='11_Derecho_uso'!C12 | C28: Trae de la hoja 11 (Depreciación y deterioro del activo) el costo inicial del activo, que en esta operación es el derecho de uso conservado. | D28: Fila 8: 699.555,01 → 699.555,01 | E28: hoja «Depreciación y deterioro del activo» | F28: —
A29: Depreciación del ejercicio (29–35) | B29: '='11_Derecho_uso'!K12 | C29: Trae la depreciación del ejercicio del activo, de la hoja 11 (Depreciación y deterioro del activo). | D29: Fila 8: 38.864,17 → 38.864,17 | E29: hoja «Depreciación y deterioro del activo» | F29: —
A30: Derecho de uso neto al corte | B30: '='11_Derecho_uso'!O12 | C30: Trae el neto recalculado del activo al corte, de la hoja 11 (Depreciación y deterioro del activo). | D30: Fila 8: 660.690,84 → 660.690,84 | E30: hoja «Depreciación y deterioro del activo» | F30: —
... A33: Control 102A: ganancia sobre el derecho de uso conservado (0) | B33: '=IF(O12<>"",O12,"") | C33: Repite la ganancia posterior registrada cuando existe (en blanco si no): cualquier importe distinto de 0 es una ganancia sobre el derecho de uso conservado que no debió reconocerse. | D33: Fila 8: IF(18.500,00<>""; 18.500,00; "") → 18.500,00 | E33: «Ganancia posterior registrada» (esta hoja) | F33: —

Sheet 15_Conciliacion
A1: Conciliación y ajuste | H1: ⟵ Inicio | I1: ◀ Anterior | J1: Siguiente ▶
A2: Arrendamientos · Cliente de muestra S.A. · corte 2025-12-31
A4: Contrato | B4: Pasivo recalculado | C4: Pasivo registrado | D4: Ajuste pasivo | E4: Activo recalculado | F4: Activo registrado | G4: Ajuste activo | H4: Depreciación del ejercicio | I4: Interés del ejercicio | J4: Pasivo corriente
A5: C-01 | B5: ='10_Pasivo_corte'!G5 | C5: ='10_Pasivo_corte'!Q5 | D5: =B5-C5 | E5: ='11_Derecho_uso'!O5 | F5: ='11_Derecho_uso'!P5 | G5: =E5-F5 | H5: ='11_Derecho_uso'!K5 | I5: ='10_Pasivo_corte'!J5 | J5: ='10_Pasivo_corte'!O5
A6: C-02 | B6: ='10_Pasivo_corte'!G6 | C6: ='10_Pasivo_corte'!Q6 | D6: =B6-C6 | E6: ='11_Derecho_uso'!O6 | F6: ='11_Derecho_uso'!P6 | G6: =E6-F6 | H6: ='11_Derecho_uso'!K6 | I6: ='10_Pasivo_corte'!J6 | J6: ='10_Pasivo_corte'!O6
A7: C-03 | B7: ='10_Pasivo_corte'!G7 | C7: ='10_Pasivo_corte'!Q7 | D7: =B7-C7 | E7: ='11_Derecho_uso'!O7 | F7: ='11_Derecho_uso'!P7 | G7: =E7-F7 | H7: ='11_Derecho_uso'!K7 | I7: ='10_Pasivo_corte'!J7 | J7: ='10_Pasivo_corte'!O7
A8: C-04 | B8: ='10_Pasivo_corte'!G8 | C8: ='10_Pasivo_corte'!Q8 | D8: =B8-C8 | E8: ='11_Derecho_uso'!O8 | F8: ='11_Derecho_uso'!P8 | G8: =E8-F8 | H8: =0 | I8: =0 | J8: =0
A9: C-05 | B9: ='10_Pasivo_corte'!G9 | C9: ='10_Pasivo_corte'!Q9 | D9: =B9-C9 | E9: ='11_Derecho_uso'!O9 | F9: ='11_Derecho_uso'!P9 | G9: =E9-F9 | H9: =0 | I9: =0 | J9: =0
A10: C-06 | B10: ='10_Pasivo_corte'!G10 | C10: ='10_Pasivo_corte'!Q10 | D10: =B10-C10 | E10: ='11_Derecho_uso'!O10 | F10: ='11_Derecho_uso'!P10 | G10: =E10-F10 | H10: ='11_Derecho_uso'!K10 | I10: ='10_Pasivo_corte'!J10 | J10: ='10_Pasivo_corte'!O10
A11: C-07 | B11: ='10_Pasivo_corte'!G11 | C11: ='10_Pasivo_corte'!Q11 | D11: =B11-C11 | E11: ='11_Derecho_uso'!O11 | F11: ='11_Derecho_uso'!P11 | G11: =E11-F11 | H11: ='11_Derecho_uso'!K11 | I11: ='10_Pasivo_corte'!J11 | J11: ='10_Pasivo_corte'!O11
A12: C-08 | B12: ='10_Pasivo_corte'!G12 | C12: ='10_Pasivo_corte'!Q12 | D12: =B12-C12 | E12: ='11_Derecho_uso'!O12 | F12: ='11_Derecho_uso'!P12 | G12: =E12-F12 | H12: ='11_Derecho_uso'!K12 | I12: ='10_Pasivo_corte'!J12 | J12: ='10_Pasivo_corte'!O12
A13: C-09 | B13: ='10_Pasivo_corte'!G13 | C13: ='10_Pasivo_corte'!Q13 | D13: =B13-C13 | E13: ='11_Derecho_uso'!O13 | F13: ='11_Derecho_uso'!P13 | G13: =E13-F13 | H13: ='11_Derecho_uso'!K13 | I13: ='10_Pasivo_corte'!J13 | J13: ='10_Pasivo_corte'!O13
A14: C-10 | B14: ='10_Pasivo_corte'!G14 | C14: ='10_Pasivo_corte'!Q14 | D14: =B14-C14 | E14: ='11_Derecho_uso'!O14 | F14: ='11_Derecho_uso'!P14 | G14: =E14-F14 | H14: ='11_Derecho_uso'!K14 | I14: ='10_Pasivo_corte'!J14 | J14: ='10_Pasivo_corte'!O14
A15: C-11 | B15: ='10_Pasivo_corte'!G15 | C15: ='10_Pasivo_corte'!Q15 | D15: =B15-C15 | E15: ='11_Derecho_uso'!O15 | F15: ='11_Derecho_uso'!P15 | G15: =E15-F15 | H15: ='11_Derecho_uso'!K15 | I15: ='10_Pasivo_corte'!J15 | J15: ='10_Pasivo_corte'!O15
A16: TOTAL | B16: =SUM(B5:B15) | C16: =SUM(C5:C15) | D16: =SUM(D5:D15) | E16: =SUM(E5:E15) | F16: =SUM(F5:F15) | G16: =SUM(G5:G15) | H16: =SUM(H5:H15) | I16: =SUM(I5:I15) | J16: =SUM(J5:J15)
A18: ⓘ Cómo se calcula esta hoja
A19: Columna | B19: Fórmula (Excel) | C19: Cómo se calcula (sencillo) | D19: Ejemplo con números reales | E19: De dónde viene | F19: Norma
A20: Pasivo recalculado | B20: '='10_Pasivo_corte'!G5 | C20: Trae el pasivo al corte recalculado de este contrato, de la hoja 10 (Pasivo al corte). | D20: Fila 1: 45.562,13 → 45.562,13 | E20: hoja «Pasivo al corte: corriente y no corriente» | F20: —
A21: Pasivo registrado | B21: '='10_Pasivo_corte'!Q5 | C21: Trae el pasivo registrado por el cliente para este contrato, de la hoja 10 (Pasivo al corte). | D21: Fila 1: 17.000,00 → 17.000,00 | E21: hoja «Pasivo al corte: corriente y no corriente» | F21: —
A22: Ajuste pasivo | B22: '=B5-C5 | C22: Pasivo recalculado menos pasivo registrado: el ajuste propuesto al pasivo de este contrato. | D22: Fila 1: 45.562,13-17.000,00 → 28.562,13 | E22: «Pasivo recalculado» (esta hoja), «Pasivo registrado» (esta hoja) | F22: —
A23: Activo recalculado | B23: '='11_Derecho_uso'!O5 | C23: Trae el neto recalculado del activo, de la hoja 11 (Depreciación y deterioro del activo). | D23: Fila 1: 41.029,02 → 41.029,02 | E23: hoja «Depreciación y deterioro del activo» | F23: —
A24: Activo registrado | B24: '='11_Derecho_uso'!P5 | C24: Trae el activo registrado neto por el cliente, de la hoja 11 (Depreciación y deterioro del activo). | D24: Fila 1: 16.500,00 → 16.500,00 | E24: hoja «Depreciación y deterioro del activo» | F24: —
A25: Ajuste activo | B25: '=E5-F5 | C25: Activo recalculado menos activo registrado: el ajuste propuesto al activo de este contrato. | D25: Fila 1: 41.029,02-16.500,00 → 24.529,02 | E25: «Activo recalculado» (esta hoja), «Activo registrado» (esta hoja) | F25: —
A26: Depreciación del ejercicio | B26: '='11_Derecho_uso'!K5 | C26: Trae la depreciación del ejercicio de la hoja 11; en los contratos que no se reconocen es 0. | D26: Fila 1: 13.676,34 → 13.676,34 | E26: hoja «Depreciación y deterioro del activo» | F26: —
A27: Interés del ejercicio | B27: '='10_Pasivo_corte'!J5 | C27: Trae el interés del ejercicio de la hoja 10 (Pasivo al corte); en los contratos que no se reconocen es 0. | D27: Fila 1: 5.944,38 → 5.944,38 | E27: hoja «Pasivo al corte: corriente y no corriente» | F27: —
A28: Pasivo corriente | B28: '='10_Pasivo_corte'!O5 | C28: Trae la parte corriente del pasivo de la hoja 10 (Pasivo al corte); en los contratos que no se reconocen es 0. | D28: Fila 1: 13.502,29 → 13.502,29 | E28: hoja «Pasivo al corte: corriente y no corriente» | F28: —

Sheet 16_Problemas
A1: Problemas encontrados | H1: ⟵ Inicio | I1: ◀ Anterior | J1: Siguiente ▶
A2: Arrendamientos · Cliente de muestra S.A. · corte 2025-12-31
A4: Código | B4: Descripción | C4: Importe
A5: PASIVO_DIFERENCIA | B5: C-01: pasivo recalculado 45.562,13 vs registrado 17.000,00. | C5: 28562.13
A6: RENOVACION_NO_INCLUIDA | B6: C-01: la renovación es razonablemente cierta pero el cliente usó 36 meses en vez de 60 (18 a, B37). | C6: 0
A7: CLASIFICACION_CP_LP | B7: C-01: pasivo corriente recalculado 13.502,29 (capital de los próximos 12 meses) vs registrado 17.000,00. | C7: -3497.71
A8: ACTIVO_DIFERENCIA | B8: C-01: derecho de uso recalculado 41.029,02 vs registrado 16.500,00. | C8: 24529.02
A9: INTERES_DIFERENCIA | B9: C-01: interés del ejercicio recalculado 5.944,38 vs registrado 2.600,00. | C9: 3344.38
A10: CLASIFICACION_CP_LP | B10: C-02: pasivo corriente recalculado 8.264,46 (capital de los próximos 12 meses) vs registrado 10.000,00. | C10: -1735.54
A11: PASIVO_DIFERENCIA | B11: C-03: pasivo recalculado 20.852,15 vs registrado 0,00. | C11: 20852.15
A12: BAJO_VALOR_VEHICULO | B12: C-03: «Vehículo de gerencia» se declaró de bajo valor, pero un automóvil (coche nuevo) no tiene habitualmente escaso valor y no puede calificar como tal (B6); reconozca el arrendamiento (22). | C12: 20852.15
A13: EXENCION_MAL_APLICADA | B13: C-03: se trató como exento pero no es de corto plazo (≤ 12 meses y sin opción de compra) ni de bajo valor (5, B3–B8); debe reconocerse (22). | C13: 20852.15
A14: ACTIVO_DIFERENCIA | B14: C-03: derecho de uso recalculado 20.954,69 vs registrado 0,00. | C14: 20954.69
A15: BAJO_VALOR_B5_B7 | B15: C-04: exención de bajo valor sin evidencia de B5 y B7. Confirme que el arrendatario puede beneficiarse del uso del activo por sí solo o junto con recursos fácilmente disponibles, que el activo no depende en medida apreciable de otros ni está estrechamente interrelacionado con ellos (B5) y que no se subarrienda (B7). | C15: 0
A16: PASIVO_DIFERENCIA | B16: C-07: pasivo recalculado 23.748,00 vs registrado 19.925,16. | C16: 3822.84
... A29: INDEXADO_SIN_IMPORTE | B29: C-11: el pago se declaró ajustado por un índice de inflación pero no se informó el importe del componente: el pago base y el componente quedan vacíos. Bajo la NIIF para las PYMES no se puede separar la cuota contingente del pago mínimo (20.11) ni del gasto lineal (20.15 b), y bajo NIIF completas no se puede comprobar la medición con el índice del comienzo (27 b) ni la remedición por cambio de índice (42 b). Pida al cliente el detalle de la factura o liquidación del período que separa la renta base del reajuste. | C29: 0

Sheet 13_Conclusion
A1: Conclusión | H1: ⟵ Inicio | I1: ◀ Anterior | J1: Siguiente ▶
A2: Arrendamientos · Cliente de muestra S.A. · corte 2025-12-31
A4: Concepto | B4: Detalle
A5: Conciliación con el mayor | B5: Población None · mayor None · diferencia None
A6: Evaluación de excepciones
A7: Análisis
A8: Conclusión

Sheet 14_Control_Revision
A1: Control de revisión | H1: ⟵ Inicio | I1: ◀ Anterior
A2: Arrendamientos · Cliente de muestra S.A. · corte 2025-12-31
A4: Fecha | B4: Acción | C4: Estado anterior | D4: Estado nuevo | E4: Actor | F4: Comentario
