Workbook

Sheet 00_Inicio
B2: AuditConsulting Auditores Cía. Ltda. · AUDIT-IA
B4: Cuentas por cobrar y deterioro · cartera, cobros, circularización y costo amortizado
B6: Cliente | C6: Cliente de muestra S.A. | D6: RUC | E6: 1790000000001
B7: Marco contable | C7: NIIF completas | D7: Fecha de corte | E7: 2025-12-31
B8: Preparó | C8: Ejercicio modelo | D8: Revisó | E8: Pendiente
B10: INDICADORES CLAVE
B11: Ajuste de deterioro propuesto | C11: Problemas encontrados
B12: 4143.38 | C12: 7
B15: IR A LA CÉDULA
B16: Carátula | C16: Programa | D16: Base técnica | E16: Resumen
B17: Parámetros | C17: Detalle por factura | D17: Antigüedad de la cartera | E17: Cobros posteriores al cierre
B18: Circularización | C18: Corte de ventas | D18: Costo amortizado e intereses implícitos | E18: Matriz de deterioro
B19: Deterioro requerido vs registrado | C19: Asientos propuestos | D19: Problemas encontrados | E19: Conclusión
B20: Control de revisión
B22: PANORAMA | N22: Datos de los gráficos (fórmulas a las cédulas)
N23: Cifras del resumen | O23: Importe (USD)
N24: ='01_Resumen'!A5 | O24: ='01_Resumen'!B5
N25: ='01_Resumen'!A6 | O25: ='01_Resumen'!B6
N26: ='01_Resumen'!A7 | O26: ='01_Resumen'!B7
N27: ='01_Resumen'!A8 | O27: ='01_Resumen'!B8
N28: ='01_Resumen'!A9 | O28: ='01_Resumen'!B9
N29: ='01_Resumen'!A10 | O29: ='01_Resumen'!B10
N30: ='01_Resumen'!A11 | O30: ='01_Resumen'!B11
N31: ='01_Resumen'!A12 | O31: ='01_Resumen'!B12
N32: ='01_Resumen'!A13 | O32: ='01_Resumen'!B13
N33: ='01_Resumen'!A14 | O33: ='01_Resumen'!B14
N34: ='01_Resumen'!A15 | O34: ='01_Resumen'!B15
N35: ='01_Resumen'!A16 | O35: ='01_Resumen'!B16
N37: Hallazgos de mayor impacto | O37: Importe (USD)
N38: Vencida sin cobro | O38: =SUMIFS('12_Problemas'!$C$5:$C$11,'12_Problemas'!$A$5:$A$11,"VENCIDA_SIN_COBRO",'12_Problemas'!$C$5:$C$11,">0")-SUMIFS('12_Problemas'!$C$5:$C$11,'12_Problemas'!$A$5:$A$11,"VENCIDA_SIN_COBRO",'12_Problemas'!$C$5:$C$11,"<0")
N39: Error corte | O39: =SUMIFS('12_Problemas'!$C$5:$C$11,'12_Problemas'!$A$5:$A$11,"ERROR_CORTE",'12_Problemas'!$C$5:$C$11,">0")-SUMIFS('12_Problemas'!$C$5:$C$11,'12_Problemas'!$A$5:$A$11,"ERROR_CORTE",'12_Problemas'!$C$5:$C$11,"<0")
N40: Cobro no posterior | O40: =SUMIFS('12_Problemas'!$C$5:$C$11,'12_Problemas'!$A$5:$A$11,"COBRO_NO_POSTERIOR",'12_Problemas'!$C$5:$C$11,">0")-SUMIFS('12_Problemas'!$C$5:$C$11,'12_Problemas'!$A$5:$A$11,"COBRO_NO_POSTERIOR",'12_Problemas'!$C$5:$C$11,"<0")
N41: Deterioro insuficiente | O41: =SUMIFS('12_Problemas'!$C$5:$C$11,'12_Problemas'!$A$5:$A$11,"DETERIORO_INSUFICIENTE",'12_Problemas'!$C$5:$C$11,">0")-SUMIFS('12_Problemas'!$C$5:$C$11,'12_Problemas'!$A$5:$A$11,"DETERIORO_INSUFICIENTE",'12_Problemas'!$C$5:$C$11,"<0")
N42: Financiacion no reconocida | O42: =SUMIFS('12_Problemas'!$C$5:$C$11,'12_Problemas'!$A$5:$A$11,"FINANCIACION_NO_RECONOCIDA",'12_Problemas'!$C$5:$C$11,">0")-SUMIFS('12_Problemas'!$C$5:$C$11,'12_Problemas'!$A$5:$A$11,"FINANCIACION_NO_RECONOCIDA",'12_Problemas'!$C$5:$C$11,"<0")
N43: Dif circularizacion | O43: =SUMIFS('12_Problemas'!$C$5:$C$11,'12_Problemas'!$A$5:$A$11,"DIF_CIRCULARIZACION",'12_Problemas'!$C$5:$C$11,">0")-SUMIFS('12_Problemas'!$C$5:$C$11,'12_Problemas'!$A$5:$A$11,"DIF_CIRCULARIZACION",'12_Problemas'!$C$5:$C$11,"<0")
N44: Saldos negativos | O44: =SUMIFS('12_Problemas'!$C$5:$C$11,'12_Problemas'!$A$5:$A$11,"SALDOS_NEGATIVOS",'12_Problemas'!$C$5:$C$11,">0")-SUMIFS('12_Problemas'!$C$5:$C$11,'12_Problemas'!$A$5:$A$11,"SALDOS_NEGATIVOS",'12_Problemas'!$C$5:$C$11,"<0")

Sheet 00_Caratula
A1: Carátula | H1: ⟵ Inicio | J1: Siguiente ▶
A2: Cuentas por cobrar y deterioro · cartera, cobros, circularización y costo amortizado · Cliente de muestra S.A. · corte 2025-12-31
A4: Concepto | B4: Detalle
A5: Firma | B5: AuditConsulting Auditores Cía. Ltda.
A6: Cliente | B6: Cliente de muestra S.A.
A7: RUC | B7: 1790000000001
A8: Ejercicio | B8: 2025
A9: Fecha de corte | B9: 2025-12-31
A10: Marco contable | B10: NIIF completas
A11: Herramienta | B11: Cuentas por cobrar y deterioro · cartera, cobros, circularización y costo amortizado
A12: Rubro | B12: Cuentas por cobrar
A13: Motor | B13: cxc_cartera 1.0
A14: Versión del papel | B14: v1
A15: Estado | B15: MUESTRA
... A17: Revisó | B17: Pendiente
A18: Aprobó
A19: Fecha de aprobación
A20: Huella de la ejecución (SHA-256)

Sheet 00_Programa
A1: Programa | H1: ⟵ Inicio | I1: ◀ Anterior | J1: Siguiente ▶
A2: Cuentas por cobrar y deterioro · cartera, cobros, circularización y costo amortizado · Cliente de muestra S.A. · corte 2025-12-31
A4: Código | B4: Objetivo | C4: Afirmación | D4: Procedimiento | E4: Evidencia | F4: Criterio | G4: Referencia
A5: CXCCAR-01 | B5: Integridad y antigüedad de la cartera | C5: Integridad | D5: Conciliar la cartera por factura con el mayor y recalcular la antigüedad al corte | E5: Cartera por factura y mayor | F5: Diferencia dentro de tolerancia; antigüedad recalculada | G5: NIA 500 párr. 9
A6: CXCCAR-02 | B6: Cobros posteriores | C6: Valoración / Existencia | D6: Cotejar cobros posteriores al cierre con la cartera, en especial la vencida | E6: Estados de cuenta bancarios y recibos posteriores | F6: Vencido sin cobro evaluado en el deterioro | G6: NIA 560 párr. 6 · NIA 540 párr. 21
A7: CXCCAR-03 | B7: Circularización | C7: Existencia | D7: Enviar confirmaciones, comparar saldo confirmado con libros e investigar diferencias | E7: Respuestas de clientes | F7: Diferencias conciliadas o ajustadas | G7: NIA 505
A8: CXCCAR-04 | B8: Corte de ventas | C8: Corte | D8: Comparar fecha de factura con fecha de despacho alrededor del cierre | E8: Guías de remisión, facturas | F8: Ventas en el período de la transferencia del control | G8: NIIF 15 31, 38 · NIA 330
A9: CXCCAR-05 | B9: Costo amortizado e intereses implícitos | C9: Valoración | D9: Identificar facturas con plazo mayor al umbral y medir su valor presente a la tasa de mercado | E9: Contratos, pagarés, tasas de mercado | F9: Componente de financiación reconocido | G9: NIIF 9 5.1.1, B5.1.1 y 5.4.1 (5.1.3 solo sin componente de financiación significativo o con la solución práctica de NIIF 15.63) · NIIF 15 60–63 · PYMES 2015 11.13 / 2025 11.13A–11.13B y 23.38
A10: CXCCAR-06 | B10: Deterioro requerido vs registrado | C10: Valoración | D10: Aplicar la matriz de tasas por tramo y las tasas individuales y comparar con el deterioro registrado | E10: Matriz de tasas, política de crédito | F10: Ajuste cuantificado | G10: NIIF 9 5.5.15 (con componente de financiación significativo, 5.5.15 a) ii) solo si esa es la política de la entidad), B5.5.35 · PYMES 11.21–11.26 (11.22 b, 11.22 e y 11.24) · NIA 540
A11: CXCCAR-07 | B11: Revelación | C11: Presentación | D11: Preparar la antigüedad y el movimiento del deterioro para las notas | E11: Aging, mayor del deterioro | F11: Nota completa | G11: NIIF 7 35H, 35M y 35N

Sheet 00_Fuentes
A1: Base técnica | H1: ⟵ Inicio | I1: ◀ Anterior | J1: Siguiente ▶
A2: Cuentas por cobrar y deterioro · cartera, cobros, circularización y costo amortizado · Cliente de muestra S.A. · corte 2025-12-31
A4: Categoría | B4: Documento | C4: Párrafos | D4: URL | E4: Verificada
A5: NIA · NIA 505 | B5: Confirmaciones externas: controlar las solicitudes, aplicar procedimientos alternativos ante cada no respuesta, investigar las diferencias y evaluar la evidencia obtenida. | C5: párr. 7, 12, 14 y 16
A6: NIA · NIA 500 | B6: Evaluar exactitud e integridad del anexo de cartera contra el mayor. | C6: párr. 9
A7: NIA · NIA 540 (Revisada) | B7: El deterioro es una estimación: evaluar método, datos, supuestos (tasas por tramo, tasa de mercado) y sesgo. | C7: párr. 13, 16–30 y 32
A8: NIA · NIA 560 | B8: Cobros posteriores al cierre como evidencia sobre la recuperabilidad. | C8: párr. 6 y NIA 540 párr. 21
A9: NIA · NIA 330 | B9: Procedimientos sustantivos de corte y existencia sobre saldos materiales. | C9: párr. 18

Sheet 01_Resumen
A1: Resumen | H1: ⟵ Inicio | I1: ◀ Anterior | J1: Siguiente ▶
A2: Cuentas por cobrar y deterioro · cartera, cobros, circularización y costo amortizado · Cliente de muestra S.A. · corte 2025-12-31
A4: Concepto | B4: Importe
A5: Cartera al corte (nominal) | B5: =SUM('03_Detalle'!$E$5:$E$16)
A6: Cartera a costo amortizado | B6: =SUM('03_Detalle'!$K$5:$K$16)
A7: Pérdida crediticia esperada requerida | B7: ='10_Ajuste'!B5
A8: Deterioro registrado (mayor) | B8: ='10_Ajuste'!B6
A9: Ajuste de deterioro propuesto | B9: ='10_Ajuste'!B7
A10: Intereses implícitos por devengar | B10: ='10_Ajuste'!B8
A11: Intereses por devengar registrados | B11: ='10_Ajuste'!B9
A12: Ajuste por financiación implícita | B12: ='10_Ajuste'!B10
A13: Ventas registradas antes del despacho | B13: ='10_Ajuste'!B11
A14: Ventas despachadas sin registrar en el ejercicio | B14: ='10_Ajuste'!B12
A15: Cartera vencida sin cobro posterior | B15: ='10_Ajuste'!B13
A16: Diferencias de circularización (absolutas) | B16: ='10_Ajuste'!B14
A18: ⓘ Cómo se calcula esta hoja
A19: Columna | B19: Fórmula (Excel) | C19: Cómo se calcula (sencillo) | D19: Ejemplo con números reales | E19: De dónde viene | F19: Norma
A20: Importe | B20: '=SUM('03_Detalle'!$E$5:$E$16) | C20: La cartera nominal y a costo amortizado se suman del detalle (hoja 03, Detalle por factura); los demás conceptos se traen, uno por uno, de la hoja 10 (Deterioro requerido vs registrado). | D20: Fila 1: SUM([«Saldo» de «Detalle por factura», 12 filas]) → 67.000,00 | E20: hoja «Detalle por factura» | F20: —

Sheet 02_Parametros
A1: Parámetros | H1: ⟵ Inicio | I1: ◀ Anterior | J1: Siguiente ▶
A2: Cuentas por cobrar y deterioro · cartera, cobros, circularización y costo amortizado · Cliente de muestra S.A. · corte 2025-12-31
A4: Parámetro | B4: Valor | C4: Sustento
A5: Corte del ejercicio | B5: 46022 | C5: Ficha del encargo
A6: Marco contable | B6: NIIF completas | C6: Ficha del encargo: enruta el modelo de deterioro
A7: Modelo de deterioro | B7: Pérdida crediticia esperada · NIIF 9 enfoque simplificado (5.5.15, B5.5.35) | C7: NIIF 9 5.5.15 / PYMES 11.21–11.26
A8: Tasa de mercado anual para el valor presente (%) | B8: 10 | C8: NIIF 9 B5.1.1; PYMES 11.13 — tasa de un instrumento de deuda similar
A9: Plazo que se considera financiación (meses) | B9: 12 | C9: NIIF 15 63 (solución práctica: más de 12 meses habilita evaluar la financiación con NIIF 15.60–62, no la concluye); PYMES 2015 11.13 (pago diferido más allá de los términos comerciales normales) / 2025 11.13A–11.13B y 23.38 (opción: cobro dentro de un año) — juicio
A10: Deterioro registrado al cierre (mayor) | B10: 2000 | C10: Mayor contable
A11: Intereses implícitos por devengar registrados (mayor) | C11: Mayor contable
A12: Tasa · Corriente / por vencer (%) | B12: 1 | C12: Tasa esperada del tramo (B5.5.35)
A13: Tasa · 1 a 30 días (%) | B13: 3 | C13: Tasa esperada del tramo (B5.5.35)
A14: Tasa · 31 a 60 días (%) | B14: 8 | C14: Tasa esperada del tramo (B5.5.35)
A15: Tasa · 61 a 90 días (%) | B15: 15 | C15: Tasa esperada del tramo (B5.5.35)
A16: Tasa · 91 a 180 días (%) | B16: 30 | C16: Tasa esperada del tramo (B5.5.35)
A17: Tasa · 181 a 360 días (%) | B17: 60 | C17: Tasa esperada del tramo (B5.5.35)
A18: Tasa · Más de 360 días (%) | B18: 100 | C18: Tasa esperada del tramo (B5.5.35)

Sheet 03_Detalle
A1: Detalle por factura | H1: ⟵ Inicio | I1: ◀ Anterior | J1: Siguiente ▶
A2: Cuentas por cobrar y deterioro · cartera, cobros, circularización y costo amortizado · Cliente de muestra S.A. · corte 2025-12-31
A4: Factura | B4: Cliente | C4: Emisión | D4: Vencimiento | E4: Saldo | F4: Importe facturado | G4: Días de mora | H4: Tramo | I4: Plazo de crédito (días) | J4: Financiación implícita | K4: Costo amortizado | L4: Interés implícito por devengar | M4: Tasa individual (%) | N4: Tasa aplicada | O4: Deterioro requerido
A5: F-001 | B5: Comercial Alfa | C5: 46001 | D5: 46031 | E5: 12000 | G5: ='02_Parametros'!$B$5-D5 | H5: =IF(G5<=0,"Corriente / por vencer",IF(G5<=30,"1 a 30 días",IF(G5<=60,"31 a 60 días",IF(G5<=90,"61 a 90 días",IF(G5<=180,"91 a 180 días",IF(G5<=360,"181 a 360 días","Más de 360 días")))))) | I5: =D5-C5 | J5: =IF(AND(E5>0,I5>'02_Parametros'!$B$9*365/12),"Sí","No") | K5: =IF(AND(J5="Sí",'02_Parametros'!$B$8<>""),E5/(1+'02_Parametros'!$B$8/100)^(MAX(D5-'02_Parametros'!$B$5,0)/365),E5) | L5: =IF(AND(J5="Sí",'02_Parametros'!$B$8=""),"",E5-K5) | N5: =IF(M5<>"",M5/100,IF(INDEX('09_Matriz_deterioro'!$D$5:$D$11,MATCH(H5,'09_Matriz_deterioro'!$A$5:$A$11,0))="","",INDEX('09_Matriz_deterioro'!$D$5:$D$11,MATCH(H5,'09_Matriz_deterioro'!$A$5:$A$11,0)))) | O5: =IF(N5="","",MAX(K5*N5,0))
A6: F-002 | B6: Distribuidora Beta | C6: 46019 | D6: 46049 | E6: 8000 | F6: 8000 | G6: ='02_Parametros'!$B$5-D6 | H6: =IF(G6<=0,"Corriente / por vencer",IF(G6<=30,"1 a 30 días",IF(G6<=60,"31 a 60 días",IF(G6<=90,"61 a 90 días",IF(G6<=180,"91 a 180 días",IF(G6<=360,"181 a 360 días","Más de 360 días")))))) | I6: =D6-C6 | J6: =IF(AND(E6>0,I6>'02_Parametros'!$B$9*365/12),"Sí","No") | K6: =IF(AND(J6="Sí",'02_Parametros'!$B$8<>""),E6/(1+'02_Parametros'!$B$8/100)^(MAX(D6-'02_Parametros'!$B$5,0)/365),E6) | L6: =IF(AND(J6="Sí",'02_Parametros'!$B$8=""),"",E6-K6) | N6: =IF(M6<>"",M6/100,IF(INDEX('09_Matriz_deterioro'!$D$5:$D$11,MATCH(H6,'09_Matriz_deterioro'!$A$5:$A$11,0))="","",INDEX('09_Matriz_deterioro'!$D$5:$D$11,MATCH(H6,'09_Matriz_deterioro'!$A$5:$A$11,0)))) | O6: =IF(N6="","",MAX(K6*N6,0))
A7: F-003 | B7: Gama Cía. Ltda. | C7: 45976 | D7: 46006 | E7: 5000 | G7: ='02_Parametros'!$B$5-D7 | H7: =IF(G7<=0,"Corriente / por vencer",IF(G7<=30,"1 a 30 días",IF(G7<=60,"31 a 60 días",IF(G7<=90,"61 a 90 días",IF(G7<=180,"91 a 180 días",IF(G7<=360,"181 a 360 días","Más de 360 días")))))) | I7: =D7-C7 | J7: =IF(AND(E7>0,I7>'02_Parametros'!$B$9*365/12),"Sí","No") | K7: =IF(AND(J7="Sí",'02_Parametros'!$B$8<>""),E7/(1+'02_Parametros'!$B$8/100)^(MAX(D7-'02_Parametros'!$B$5,0)/365),E7) | L7: =IF(AND(J7="Sí",'02_Parametros'!$B$8=""),"",E7-K7) | N7: =IF(M7<>"",M7/100,IF(INDEX('09_Matriz_deterioro'!$D$5:$D$11,MATCH(H7,'09_Matriz_deterioro'!$A$5:$A$11,0))="","",INDEX('09_Matriz_deterioro'!$D$5:$D$11,MATCH(H7,'09_Matriz_deterioro'!$A$5:$A$11,0)))) | O7: =IF(N7="","",MAX(K7*N7,0))
A8: F-004 | B8: Delta S.A. | C8: 45931 | D8: 45961 | E8: 4000 | G8: ='02_Parametros'!$B$5-D8 | H8: =IF(G8<=0,"Corriente / por vencer",IF(G8<=30,"1 a 30 días",IF(G8<=60,"31 a 60 días",IF(G8<=90,"61 a 90 días",IF(G8<=180,"91 a 180 días",IF(G8<=360,"181 a 360 días","Más de 360 días")))))) | I8: =D8-C8 | J8: =IF(AND(E8>0,I8>'02_Parametros'!$B$9*365/12),"Sí","No") | K8: =IF(AND(J8="Sí",'02_Parametros'!$B$8<>""),E8/(1+'02_Parametros'!$B$8/100)^(MAX(D8-'02_Parametros'!$B$5,0)/365),E8) | L8: =IF(AND(J8="Sí",'02_Parametros'!$B$8=""),"",E8-K8) | N8: =IF(M8<>"",M8/100,IF(INDEX('09_Matriz_deterioro'!$D$5:$D$11,MATCH(H8,'09_Matriz_deterioro'!$A$5:$A$11,0))="","",INDEX('09_Matriz_deterioro'!$D$5:$D$11,MATCH(H8,'09_Matriz_deterioro'!$A$5:$A$11,0)))) | O8: =IF(N8="","",MAX(K8*N8,0))
A9: F-005 | B9: Épsilon S.A. | C9: 45901 | D9: 45931 | E9: 3000 | G9: ='02_Parametros'!$B$5-D9 | H9: =IF(G9<=0,"Corriente / por vencer",IF(G9<=30,"1 a 30 días",IF(G9<=60,"31 a 60 días",IF(G9<=90,"61 a 90 días",IF(G9<=180,"91 a 180 días",IF(G9<=360,"181 a 360 días","Más de 360 días")))))) | I9: =D9-C9 | J9: =IF(AND(E9>0,I9>'02_Parametros'!$B$9*365/12),"Sí","No") | K9: =IF(AND(J9="Sí",'02_Parametros'!$B$8<>""),E9/(1+'02_Parametros'!$B$8/100)^(MAX(D9-'02_Parametros'!$B$5,0)/365),E9) | L9: =IF(AND(J9="Sí",'02_Parametros'!$B$8=""),"",E9-K9) | M9: 50 | N9: =IF(M9<>"",M9/100,IF(INDEX('09_Matriz_deterioro'!$D$5:$D$11,MATCH(H9,'09_Matriz_deterioro'!$A$5:$A$11,0))="","",INDEX('09_Matriz_deterioro'!$D$5:$D$11,MATCH(H9,'09_Matriz_deterioro'!$A$5:$A$11,0)))) | O9: =IF(N9="","",MAX(K9*N9,0))
A10: F-006 | B10: Zeta Hnos. | C10: 45748 | D10: 45778 | E10: 2500 | G10: ='02_Parametros'!$B$5-D10 | H10: =IF(G10<=0,"Corriente / por vencer",IF(G10<=30,"1 a 30 días",IF(G10<=60,"31 a 60 días",IF(G10<=90,"61 a 90 días",IF(G10<=180,"91 a 180 días",IF(G10<=360,"181 a 360 días","Más de 360 días")))))) | I10: =D10-C10 | J10: =IF(AND(E10>0,I10>'02_Parametros'!$B$9*365/12),"Sí","No") | K10: =IF(AND(J10="Sí",'02_Parametros'!$B$8<>""),E10/(1+'02_Parametros'!$B$8/100)^(MAX(D10-'02_Parametros'!$B$5,0)/365),E10) | L10: =IF(AND(J10="Sí",'02_Parametros'!$B$8=""),"",E10-K10) | N10: =IF(M10<>"",M10/100,IF(INDEX('09_Matriz_deterioro'!$D$5:$D$11,MATCH(H10,'09_Matriz_deterioro'!$A$5:$A$11,0))="","",INDEX('09_Matriz_deterioro'!$D$5:$D$11,MATCH(H10,'09_Matriz_deterioro'!$A$5:$A$11,0)))) | O10: =IF(N10="","",MAX(K10*N10,0))
A11: F-007 | B11: Eta Comercial | C11: 45444 | D11: 45474 | E11: 1500 | G11: ='02_Parametros'!$B$5-D11 | H11: =IF(G11<=0,"Corriente / por vencer",IF(G11<=30,"1 a 30 días",IF(G11<=60,"31 a 60 días",IF(G11<=90,"61 a 90 días",IF(G11<=180,"91 a 180 días",IF(G11<=360,"181 a 360 días","Más de 360 días")))))) | I11: =D11-C11 | J11: =IF(AND(E11>0,I11>'02_Parametros'!$B$9*365/12),"Sí","No") | K11: =IF(AND(J11="Sí",'02_Parametros'!$B$8<>""),E11/(1+'02_Parametros'!$B$8/100)^(MAX(D11-'02_Parametros'!$B$5,0)/365),E11) | L11: =IF(AND(J11="Sí",'02_Parametros'!$B$8=""),"",E11-K11) | N11: =IF(M11<>"",M11/100,IF(INDEX('09_Matriz_deterioro'!$D$5:$D$11,MATCH(H11,'09_Matriz_deterioro'!$A$5:$A$11,0))="","",INDEX('09_Matriz_deterioro'!$D$5:$D$11,MATCH(H11,'09_Matriz_deterioro'!$A$5:$A$11,0)))) | O11: =IF(N11="","",MAX(K11*N11,0))
A12: F-008 | B12: Theta Industrial | C12: 45839 | D12: 46569 | E12: 20000 | G12: ='02_Parametros'!$B$5-D12 | H12: =IF(G12<=0,"Corriente / por vencer",IF(G12<=30,"1 a 30 días",IF(G12<=60,"31 a 60 días",IF(G12<=90,"61 a 90 días",IF(G12<=180,"91 a 180 días",IF(G12<=360,"181 a 360 días","Más de 360 días")))))) | I12: =D12-C12 | J12: =IF(AND(E12>0,I12>'02_Parametros'!$B$9*365/12),"Sí","No") | K12: =IF(AND(J12="Sí",'02_Parametros'!$B$8<>""),E12/(1+'02_Parametros'!$B$8/100)^(MAX(D12-'02_Parametros'!$B$5,0)/365),E12) | L12: =IF(AND(J12="Sí",'02_Parametros'!$B$8=""),"",E12-K12) | N12: =IF(M12<>"",M12/100,IF(INDEX('09_Matriz_deterioro'!$D$5:$D$11,MATCH(H12,'09_Matriz_deterioro'!$A$5:$A$11,0))="","",INDEX('09_Matriz_deterioro'!$D$5:$D$11,MATCH(H12,'09_Matriz_deterioro'!$A$5:$A$11,0)))) | O12: =IF(N12="","",MAX(K12*N12,0))
A13: F-009 | B13: Iota Market | C13: 45981 | D13: 46011 | E13: 6000 | G13: ='02_Parametros'!$B$5-D13 | H13: =IF(G13<=0,"Corriente / por vencer",IF(G13<=30,"1 a 30 días",IF(G13<=60,"31 a 60 días",IF(G13<=90,"61 a 90 días",IF(G13<=180,"91 a 180 días",IF(G13<=360,"181 a 360 días","Más de 360 días")))))) | I13: =D13-C13 | J13: =IF(AND(E13>0,I13>'02_Parametros'!$B$9*365/12),"Sí","No") | K13: =IF(AND(J13="Sí",'02_Parametros'!$B$8<>""),E13/(1+'02_Parametros'!$B$8/100)^(MAX(D13-'02_Parametros'!$B$5,0)/365),E13) | L13: =IF(AND(J13="Sí",'02_Parametros'!$B$8=""),"",E13-K13) | N13: =IF(M13<>"",M13/100,IF(INDEX('09_Matriz_deterioro'!$D$5:$D$11,MATCH(H13,'09_Matriz_deterioro'!$A$5:$A$11,0))="","",INDEX('09_Matriz_deterioro'!$D$5:$D$11,MATCH(H13,'09_Matriz_deterioro'!$A$5:$A$11,0)))) | O13: =IF(N13="","",MAX(K13*N13,0))
A14: F-010 | B14: Kappa Retail | C14: 45962 | D14: 45992 | E14: 2000 | G14: ='02_Parametros'!$B$5-D14 | H14: =IF(G14<=0,"Corriente / por vencer",IF(G14<=30,"1 a 30 días",IF(G14<=60,"31 a 60 días",IF(G14<=90,"61 a 90 días",IF(G14<=180,"91 a 180 días",IF(G14<=360,"181 a 360 días","Más de 360 días")))))) | I14: =D14-C14 | J14: =IF(AND(E14>0,I14>'02_Parametros'!$B$9*365/12),"Sí","No") | K14: =IF(AND(J14="Sí",'02_Parametros'!$B$8<>""),E14/(1+'02_Parametros'!$B$8/100)^(MAX(D14-'02_Parametros'!$B$5,0)/365),E14) | L14: =IF(AND(J14="Sí",'02_Parametros'!$B$8=""),"",E14-K14) | N14: =IF(M14<>"",M14/100,IF(INDEX('09_Matriz_deterioro'!$D$5:$D$11,MATCH(H14,'09_Matriz_deterioro'!$A$5:$A$11,0))="","",INDEX('09_Matriz_deterioro'!$D$5:$D$11,MATCH(H14,'09_Matriz_deterioro'!$A$5:$A$11,0)))) | O14: =IF(N14="","",MAX(K14*N14,0))
A15: F-011 | B15: Lambda S.A. | C15: 45945 | D15: 45975 | E15: 3500 | G15: ='02_Parametros'!$B$5-D15 | H15: =IF(G15<=0,"Corriente / por vencer",IF(G15<=30,"1 a 30 días",IF(G15<=60,"31 a 60 días",IF(G15<=90,"61 a 90 días",IF(G15<=180,"91 a 180 días",IF(G15<=360,"181 a 360 días","Más de 360 días")))))) | I15: =D15-C15 | J15: =IF(AND(E15>0,I15>'02_Parametros'!$B$9*365/12),"Sí","No") | K15: =IF(AND(J15="Sí",'02_Parametros'!$B$8<>""),E15/(1+'02_Parametros'!$B$8/100)^(MAX(D15-'02_Parametros'!$B$5,0)/365),E15) | L15: =IF(AND(J15="Sí",'02_Parametros'!$B$8=""),"",E15-K15) | N15: =IF(M15<>"",M15/100,IF(INDEX('09_Matriz_deterioro'!$D$5:$D$11,MATCH(H15,'09_Matriz_deterioro'!$A$5:$A$11,0))="","",INDEX('09_Matriz_deterioro'!$D$5:$D$11,MATCH(H15,'09_Matriz_deterioro'!$A$5:$A$11,0)))) | O15: =IF(N15="","",MAX(K15*N15,0))
A16: F-012 | B16: Mu Ventas | C16: 45996 | D16: 46026 | E16: -500 | G16: ='02_Parametros'!$B$5-D16 | H16: =IF(G16<=0,"Corriente / por vencer",IF(G16<=30,"1 a 30 días",IF(G16<=60,"31 a 60 días",IF(G16<=90,"61 a 90 días",IF(G16<=180,"91 a 180 días",IF(G16<=360,"181 a 360 días","Más de 360 días")))))) | I16: =D16-C16 | J16: =IF(AND(E16>0,I16>'02_Parametros'!$B$9*365/12),"Sí","No") | K16: =IF(AND(J16="Sí",'02_Parametros'!$B$8<>""),E16/(1+'02_Parametros'!$B$8/100)^(MAX(D16-'02_Parametros'!$B$5,0)/365),E16) | L16: =IF(AND(J16="Sí",'02_Parametros'!$B$8=""),"",E16-K16) | N16: =IF(M16<>"",M16/100,IF(INDEX('09_Matriz_deterioro'!$D$5:$D$11,MATCH(H16,'09_Matriz_deterioro'!$A$5:$A$11,0))="","",INDEX('09_Matriz_deterioro'!$D$5:$D$11,MATCH(H16,'09_Matriz_deterioro'!$A$5:$A$11,0)))) | O16: =IF(N16="","",MAX(K16*N16,0))
A17: TOTAL | E17: =SUM(E5:E16) | K17: =SUM(K5:K16) | L17: =SUM(L5:L16) | O17: =SUM(O5:O16)
A19: ⓘ Cómo se calcula esta hoja
A20: Columna | B20: Fórmula (Excel) | C20: Cómo se calcula (sencillo) | D20: Ejemplo con números reales | E20: De dónde viene | F20: Norma
A21: Días de mora | B21: '='02_Parametros'!$B$5-D5 | C21: Resta la fecha de vencimiento de la fecha de corte de la hoja 02 (Parámetros): positivo son días vencidos; cero o negativo, la factura todavía está por vencer. | D21: Fila 1: «2025-12-31»-«2026-01-09» → -9 | E21: «Vencimiento» (esta hoja), hoja «Parámetros» | F21: —
A22: Tramo | B22: '=IF(G5<=0,"Corriente / por vencer",IF(G5<=30,"1 a 30 días",IF(G5<=60,"31 a 60 días",IF(G5<=90,"61 a 90 días",IF(G5<=180,"91 a 180 días",IF(G5<=360,"181 a 360 días","Más de 360 días")))))) | C22: Clasifica la factura por sus días de mora: corriente/por vencer si no tiene mora, luego 1 a 30, 31 a 60, 61 a 90, 91 a 180, 181 a 360 y más de 360 días. | D22: Fila 1: IF(-9<=0; "Corriente / por vencer"; IF(-9<=30; "1 a 30 días"; IF(-9<=60; "31 a 60 días"; IF(-9<=90; "61 a 90 días"; IF(-9<=180; "91 a 180 días"; IF(-9<=360; "181 a 360 días"; "Más de 360 días")))))) → Corriente / por vencer | E22: «Días de mora» (esta hoja) | F22: —
A23: Plazo de crédito (días) | B23: '=D5-C5 | C23: Cuenta los días que hay entre la emisión y el vencimiento de la factura: es el plazo que se dio al cliente. | D23: Fila 1: «2026-01-09»-«2025-12-10» → 30 | E23: «Vencimiento» (esta hoja), «Emisión» (esta hoja) | F23: —
A24: Financiación implícita | B24: '=IF(AND(E5>0,I5>'02_Parametros'!$B$9*365/12),"Sí","No") | C24: Marca «Sí» si la factura tiene saldo y su plazo de crédito supera los meses que la hoja 02 (Parámetros) considera financiación, convertidos a días; si no, «No». | D24: Fila 1: IF(AND(12.000,00>0; 30>12,00*365/12); "Sí"; "No") → No | E24: «Saldo» (esta hoja), «Plazo de crédito (días)» (esta hoja), hoja «Parámetros» | F24: —
A25: Costo amortizado | B25: '=IF(AND(J5="Sí",'02_Parametros'!$B$8<>""),E5/(1+'02_Parametros'!$B$8/100)^(MAX(D5-'02_Parametros'!$B$5,0)/365),E5) | C25: Si la factura tiene financiación implícita y hay tasa de mercado en la hoja 02, descuenta el saldo por los días que faltan desde el corte hasta el vencimiento; si no, deja el saldo nominal. | D25: Fila 1: IF(AND(«No»="Sí"; 10,00<>""); 12.000,00/(1+10,00/100)^(MAX(«2026-01-09»-«2025-12-31»; 0)/365); 12.000,00) → 12.000,00 | E25: «Financiación implícita» (esta hoja), «Saldo» (esta hoja), «Vencimiento» (esta hoja), hoja «Parámetros» | F25: —
A26: Interés implícito por devengar | B26: '=IF(AND(J5="Sí",'02_Parametros'!$B$8=""),"",E5-K5) | C26: Resta al saldo nominal su costo amortizado: el interés implícito que aún no se gana. Si hay financiación pero falta la tasa de mercado, queda en blanco. | D26: Fila 1: IF(AND(«No»="Sí"; 10,00=""); ""; 12.000,00-12.000,00) → 0,00 | E26: «Financiación implícita» (esta hoja), «Saldo» (esta hoja), «Costo amortizado» (esta hoja), hoja «Parámetros» | F26: —
A27: Tasa aplicada | B27: '=IF(M5<>"",M5/100,IF(INDEX('09_Matriz_deterioro'!$D$5:$D$11,MATCH(H5,'09_Matriz_deterioro'!$A$5:$A$11,0))="","",INDEX('09_Matriz_deterioro'!$D$5:$D$11,MATCH(H5,'09_Matriz_deterioro'!$A$5:$A$11,0)))) | C27: Si la factura tiene tasa individual, usa esa tasa dividida para 100; si no, busca la tasa de su tramo en la hoja 09 (Matriz de deterioro). Si el tramo no tiene tasa, queda en blanco. | D27: Fila 1: IF((vacío)<>""; (vacío)/100; IF(INDEX([«Tasa del tramo» de «Matriz de deterioro», 7 filas]; MATCH(«Corriente / por vencer»; [«Tramo» de «Matriz de deterioro», 7 filas]; 0))=""; ""; INDEX([«Tasa del tramo» de «Matriz de deterioro», 7 filas]; MATCH(«Corriente / por vencer»; [«Tramo» de «Matriz de deterioro», 7 filas]; 0)))) → 1,00 % | E27: «Tasa individual (%)» (esta hoja), «Tramo» (esta hoja), hoja «Matriz de deterioro» | F27: —
A28: Deterioro requerido | B28: '=IF(N5="","",MAX(K5*N5,0)) | C28: Multiplica el costo amortizado de la factura por la tasa aplicada; nunca es negativo. Sin tasa, queda en blanco. | D28: Fila 1: IF(1,00 %=""; ""; MAX(12.000,00*1,00 %; 0)) → 120,00 | E28: «Tasa aplicada» (esta hoja), «Costo amortizado» (esta hoja) | F28: —

Sheet 04_Aging
A1: Antigüedad de la cartera | H1: ⟵ Inicio | I1: ◀ Anterior | J1: Siguiente ▶
A2: Cuentas por cobrar y deterioro · cartera, cobros, circularización y costo amortizado · Cliente de muestra S.A. · corte 2025-12-31
A4: Tramo | B4: Facturas | C4: Saldo | D4: % de la cartera | E4: Vencido
A5: Corriente / por vencer | B5: =COUNTIF('03_Detalle'!$H$5:$H$16,A5) | C5: =SUMIF('03_Detalle'!$H$5:$H$16,A5,'03_Detalle'!$E$5:$E$16) | D5: =IF(SUM('03_Detalle'!$E$5:$E$16)=0,"",C5/SUM('03_Detalle'!$E$5:$E$16)) | E5: No
A6: 1 a 30 días | B6: =COUNTIF('03_Detalle'!$H$5:$H$16,A6) | C6: =SUMIF('03_Detalle'!$H$5:$H$16,A6,'03_Detalle'!$E$5:$E$16) | D6: =IF(SUM('03_Detalle'!$E$5:$E$16)=0,"",C6/SUM('03_Detalle'!$E$5:$E$16)) | E6: Sí
A7: 31 a 60 días | B7: =COUNTIF('03_Detalle'!$H$5:$H$16,A7) | C7: =SUMIF('03_Detalle'!$H$5:$H$16,A7,'03_Detalle'!$E$5:$E$16) | D7: =IF(SUM('03_Detalle'!$E$5:$E$16)=0,"",C7/SUM('03_Detalle'!$E$5:$E$16)) | E7: Sí
A8: 61 a 90 días | B8: =COUNTIF('03_Detalle'!$H$5:$H$16,A8) | C8: =SUMIF('03_Detalle'!$H$5:$H$16,A8,'03_Detalle'!$E$5:$E$16) | D8: =IF(SUM('03_Detalle'!$E$5:$E$16)=0,"",C8/SUM('03_Detalle'!$E$5:$E$16)) | E8: Sí
A9: 91 a 180 días | B9: =COUNTIF('03_Detalle'!$H$5:$H$16,A9) | C9: =SUMIF('03_Detalle'!$H$5:$H$16,A9,'03_Detalle'!$E$5:$E$16) | D9: =IF(SUM('03_Detalle'!$E$5:$E$16)=0,"",C9/SUM('03_Detalle'!$E$5:$E$16)) | E9: Sí
A10: 181 a 360 días | B10: =COUNTIF('03_Detalle'!$H$5:$H$16,A10) | C10: =SUMIF('03_Detalle'!$H$5:$H$16,A10,'03_Detalle'!$E$5:$E$16) | D10: =IF(SUM('03_Detalle'!$E$5:$E$16)=0,"",C10/SUM('03_Detalle'!$E$5:$E$16)) | E10: Sí
A11: Más de 360 días | B11: =COUNTIF('03_Detalle'!$H$5:$H$16,A11) | C11: =SUMIF('03_Detalle'!$H$5:$H$16,A11,'03_Detalle'!$E$5:$E$16) | D11: =IF(SUM('03_Detalle'!$E$5:$E$16)=0,"",C11/SUM('03_Detalle'!$E$5:$E$16)) | E11: Sí
A12: TOTAL | B12: =SUM(B5:B11) | C12: =SUM(C5:C11)
A14: ⓘ Cómo se calcula esta hoja
A15: Columna | B15: Fórmula (Excel) | C15: Cómo se calcula (sencillo) | D15: Ejemplo con números reales | E15: De dónde viene | F15: Norma
A16: Facturas | B16: '=COUNTIF('03_Detalle'!$H$5:$H$16,A5) | C16: Cuenta cuántas facturas del detalle (hoja 03, Detalle por factura) caen en este tramo de antigüedad. | D16: Fila 1: COUNTIF([«Tramo» de «Detalle por factura», 12 filas]; «Corriente / por vencer») → 4 | E16: «Tramo» (esta hoja), hoja «Detalle por factura» | F16: —
A17: Saldo | B17: '=SUMIF('03_Detalle'!$H$5:$H$16,A5,'03_Detalle'!$E$5:$E$16) | C17: Suma el saldo nominal de las facturas del detalle (hoja 03) que caen en este tramo de antigüedad. | D17: Fila 1: SUMIF([«Tramo» de «Detalle por factura», 12 filas]; «Corriente / por vencer»; [«Saldo» de «Detalle por factura», 12 filas]) → 39.500,00 | E17: «Tramo» (esta hoja), hoja «Detalle por factura» | F17: —
A18: % de la cartera | B18: '=IF(SUM('03_Detalle'!$E$5:$E$16)=0,"",C5/SUM('03_Detalle'!$E$5:$E$16)) | C18: Divide el saldo del tramo para el saldo total de la cartera de la hoja 03 (Detalle por factura); si la cartera total es cero, queda en blanco. | D18: Fila 1: IF(SUM([«Saldo» de «Detalle por factura», 12 filas])=0; ""; 39.500,00/SUM([«Saldo» de «Detalle por factura», 12 filas])) → 58,96 % | E18: «Saldo» (esta hoja), hoja «Detalle por factura» | F18: —

Sheet 05_Cobros_posteriores
A1: Cobros posteriores al cierre | H1: ⟵ Inicio | I1: ◀ Anterior | J1: Siguiente ▶
A2: Cuentas por cobrar y deterioro · cartera, cobros, circularización y costo amortizado · Cliente de muestra S.A. · corte 2025-12-31
A4: Factura | B4: Cliente | C4: Días de mora | D4: Saldo al corte | E4: Cobro informado | F4: Fecha del cobro | G4: Cobro posterior aplicable | H4: Saldo sin cobro posterior | I4: Vencida sin cobro | J4: Vencido sin cobro
A5: F-001 | B5: Comercial Alfa | C5: ='03_Detalle'!G5 | D5: ='03_Detalle'!E5 | E5: 12000 | F5: 46030 | G5: =IF(OR(E5="",F5=""),0,IF(F5>'02_Parametros'!$B$5,MIN(E5,D5),0)) | H5: =D5-G5 | I5: =IF(AND(C5>0,H5>0),"Sí","No") | J5: =IF(I5="Sí",H5,0)
A6: F-002 | B6: Distribuidora Beta | C6: ='03_Detalle'!G6 | D6: ='03_Detalle'!E6 | G6: =IF(OR(E6="",F6=""),0,IF(F6>'02_Parametros'!$B$5,MIN(E6,D6),0)) | H6: =D6-G6 | I6: =IF(AND(C6>0,H6>0),"Sí","No") | J6: =IF(I6="Sí",H6,0)
A7: F-003 | B7: Gama Cía. Ltda. | C7: ='03_Detalle'!G7 | D7: ='03_Detalle'!E7 | E7: 5000 | F7: 46042 | G7: =IF(OR(E7="",F7=""),0,IF(F7>'02_Parametros'!$B$5,MIN(E7,D7),0)) | H7: =D7-G7 | I7: =IF(AND(C7>0,H7>0),"Sí","No") | J7: =IF(I7="Sí",H7,0)
A8: F-004 | B8: Delta S.A. | C8: ='03_Detalle'!G8 | D8: ='03_Detalle'!E8 | E8: 1000 | F8: 46063 | G8: =IF(OR(E8="",F8=""),0,IF(F8>'02_Parametros'!$B$5,MIN(E8,D8),0)) | H8: =D8-G8 | I8: =IF(AND(C8>0,H8>0),"Sí","No") | J8: =IF(I8="Sí",H8,0)
A9: F-005 | B9: Épsilon S.A. | C9: ='03_Detalle'!G9 | D9: ='03_Detalle'!E9 | G9: =IF(OR(E9="",F9=""),0,IF(F9>'02_Parametros'!$B$5,MIN(E9,D9),0)) | H9: =D9-G9 | I9: =IF(AND(C9>0,H9>0),"Sí","No") | J9: =IF(I9="Sí",H9,0)
A10: F-006 | B10: Zeta Hnos. | C10: ='03_Detalle'!G10 | D10: ='03_Detalle'!E10 | G10: =IF(OR(E10="",F10=""),0,IF(F10>'02_Parametros'!$B$5,MIN(E10,D10),0)) | H10: =D10-G10 | I10: =IF(AND(C10>0,H10>0),"Sí","No") | J10: =IF(I10="Sí",H10,0)
A11: F-007 | B11: Eta Comercial | C11: ='03_Detalle'!G11 | D11: ='03_Detalle'!E11 | G11: =IF(OR(E11="",F11=""),0,IF(F11>'02_Parametros'!$B$5,MIN(E11,D11),0)) | H11: =D11-G11 | I11: =IF(AND(C11>0,H11>0),"Sí","No") | J11: =IF(I11="Sí",H11,0)
A12: F-008 | B12: Theta Industrial | C12: ='03_Detalle'!G12 | D12: ='03_Detalle'!E12 | G12: =IF(OR(E12="",F12=""),0,IF(F12>'02_Parametros'!$B$5,MIN(E12,D12),0)) | H12: =D12-G12 | I12: =IF(AND(C12>0,H12>0),"Sí","No") | J12: =IF(I12="Sí",H12,0)
A13: F-009 | B13: Iota Market | C13: ='03_Detalle'!G13 | D13: ='03_Detalle'!E13 | E13: 6000 | F13: 46021 | G13: =IF(OR(E13="",F13=""),0,IF(F13>'02_Parametros'!$B$5,MIN(E13,D13),0)) | H13: =D13-G13 | I13: =IF(AND(C13>0,H13>0),"Sí","No") | J13: =IF(I13="Sí",H13,0)
A14: F-010 | B14: Kappa Retail | C14: ='03_Detalle'!G14 | D14: ='03_Detalle'!E14 | G14: =IF(OR(E14="",F14=""),0,IF(F14>'02_Parametros'!$B$5,MIN(E14,D14),0)) | H14: =D14-G14 | I14: =IF(AND(C14>0,H14>0),"Sí","No") | J14: =IF(I14="Sí",H14,0)
A15: F-011 | B15: Lambda S.A. | C15: ='03_Detalle'!G15 | D15: ='03_Detalle'!E15 | E15: 3500 | F15: 46037 | G15: =IF(OR(E15="",F15=""),0,IF(F15>'02_Parametros'!$B$5,MIN(E15,D15),0)) | H15: =D15-G15 | I15: =IF(AND(C15>0,H15>0),"Sí","No") | J15: =IF(I15="Sí",H15,0)
A16: F-012 | B16: Mu Ventas | C16: ='03_Detalle'!G16 | D16: ='03_Detalle'!E16 | G16: =IF(OR(E16="",F16=""),0,IF(F16>'02_Parametros'!$B$5,MIN(E16,D16),0)) | H16: =D16-G16 | I16: =IF(AND(C16>0,H16>0),"Sí","No") | J16: =IF(I16="Sí",H16,0)
A17: TOTAL | D17: =SUM(D5:D16) | G17: =SUM(G5:G16) | H17: =SUM(H5:H16) | J17: =SUM(J5:J16)
A19: ⓘ Cómo se calcula esta hoja
A20: Columna | B20: Fórmula (Excel) | C20: Cómo se calcula (sencillo) | D20: Ejemplo con números reales | E20: De dónde viene | F20: Norma
A21: Días de mora | B21: '='03_Detalle'!G5 | C21: Trae los días de mora de la misma factura desde la hoja 03 (Detalle por factura). | D21: Fila 1: -9 → -9 | E21: hoja «Detalle por factura» | F21: —
A22: Saldo al corte | B22: '='03_Detalle'!E5 | C22: Trae el saldo al corte de la misma factura desde la hoja 03 (Detalle por factura). | D22: Fila 1: 12.000,00 → 12.000,00 | E22: hoja «Detalle por factura» | F22: —
A23: Cobro posterior aplicable | B23: '=IF(OR(E5="",F5=""),0,IF(F5>'02_Parametros'!$B$5,MIN(E5,D5),0)) | C23: Si el cobro informado tiene fecha posterior al corte de la hoja 02 (Parámetros), toma ese cobro sin pasar del saldo al corte; si falta el cobro o la fecha, o es anterior al corte, es cero. | D23: Fila 1: IF(OR(12.000,00=""; «2026-01-08»=""); 0; IF(«2026-01-08»>«2025-12-31»; MIN(12.000,00; 12.000,00); 0)) → 12.000,00 | E23: «Cobro informado» (esta hoja), «Fecha del cobro» (esta hoja), «Saldo al corte» (esta hoja), hoja «Parámetros» | F23: —
A24: Saldo sin cobro posterior | B24: '=D5-G5 | C24: Resta al saldo al corte el cobro posterior aplicable: lo que queda sin evidencia de cobro. | D24: Fila 1: 12.000,00-12.000,00 → 0,00 | E24: «Saldo al corte» (esta hoja), «Cobro posterior aplicable» (esta hoja) | F24: —
A25: Vencida sin cobro | B25: '=IF(AND(C5>0,H5>0),"Sí","No") | C25: Marca «Sí» si la factura está vencida (días de mora mayores que cero) y le queda saldo sin cobro posterior; si no, «No». | D25: Fila 1: IF(AND(-9>0; 0,00>0); "Sí"; "No") → No | E25: «Días de mora» (esta hoja), «Saldo sin cobro posterior» (esta hoja) | F25: —
A26: Vencido sin cobro | B26: '=IF(I5="Sí",H5,0) | C26: Si la factura está marcada como vencida sin cobro, toma su saldo sin cobro posterior; si no, pone cero. | D26: Fila 1: IF(«No»="Sí"; 0,00; 0) → 0,00 | E26: «Vencida sin cobro» (esta hoja), «Saldo sin cobro posterior» (esta hoja) | F26: —

Sheet 06_Circularizacion
A1: Circularización | H1: ⟵ Inicio | I1: ◀ Anterior | J1: Siguiente ▶
A2: Cuentas por cobrar y deterioro · cartera, cobros, circularización y costo amortizado · Cliente de muestra S.A. · corte 2025-12-31
A4: Factura | B4: Cliente | C4: Saldo en libros | D4: Saldo confirmado | E4: Diferencia | F4: Diferencia absoluta | G4: Estado
A5: F-001 | B5: Comercial Alfa | C5: ='03_Detalle'!E5 | D5: 12000 | E5: =D5-C5 | F5: =ABS(E5) | G5: =IF(ABS(E5)<=0.005,"Conforme","Diferencia")
A6: F-004 | B6: Delta S.A. | C6: ='03_Detalle'!E8 | D6: 3500 | E6: =D6-C6 | F6: =ABS(E6) | G6: =IF(ABS(E6)<=0.005,"Conforme","Diferencia")
A7: F-008 | B7: Theta Industrial | C7: ='03_Detalle'!E12 | D7: 20000 | E7: =D7-C7 | F7: =ABS(E7) | G7: =IF(ABS(E7)<=0.005,"Conforme","Diferencia")
A8: TOTAL | C8: =SUM(C5:C7) | D8: =SUM(D5:D7) | E8: =SUM(E5:E7) | F8: =SUM(F5:F7)
A10: ⓘ Cómo se calcula esta hoja
A11: Columna | B11: Fórmula (Excel) | C11: Cómo se calcula (sencillo) | D11: Ejemplo con números reales | E11: De dónde viene | F11: Norma
A12: Saldo en libros | B12: '='03_Detalle'!E5 | C12: Trae el saldo en libros de la misma factura desde la hoja 03 (Detalle por factura). | D12: Fila 1: 12.000,00 → 12.000,00 | E12: hoja «Detalle por factura» | F12: —
A13: Diferencia | B13: '=D5-C5 | C13: Resta al saldo que confirmó el cliente el saldo en libros: positivo si el cliente confirma más que los libros. | D13: Fila 1: 12.000,00-12.000,00 → 0,00 | E13: «Saldo confirmado» (esta hoja), «Saldo en libros» (esta hoja) | F13: —
A14: Diferencia absoluta | B14: '=ABS(E5) | C14: Toma la diferencia sin signo, para sumar las diferencias sin que se compensen entre sí. | D14: Fila 1: ABS(0,00) → 0,00 | E14: «Diferencia» (esta hoja) | F14: —
A15: Estado | B15: '=IF(ABS(E5)<=0.005,"Conforme","Diferencia") | C15: Dice «Conforme» si la diferencia no pasa de medio centavo y «Diferencia» en caso contrario. | D15: Fila 1: IF(ABS(0,00)<=0.005; "Conforme"; "Diferencia") → Conforme | E15: «Diferencia» (esta hoja) | F15: —

Sheet 07_Corte_ventas
A1: Corte de ventas | H1: ⟵ Inicio | I1: ◀ Anterior | J1: Siguiente ▶
A2: Cuentas por cobrar y deterioro · cartera, cobros, circularización y costo amortizado · Cliente de muestra S.A. · corte 2025-12-31
A4: Factura | B4: Cliente | C4: Emisión (registro) | D4: Despacho | E4: Importe | F4: Registrada en el ejercicio | G4: Despachada en el ejercicio | H4: Registrada antes del despacho | I4: Despachada sin registrar
A5: F-001 | B5: Comercial Alfa | C5: 46001 | D5: 46001 | E5: =IF('03_Detalle'!F5<>"",'03_Detalle'!F5,'03_Detalle'!E5) | F5: =IF(C5<='02_Parametros'!$B$5,"Sí","No") | G5: =IF(D5<='02_Parametros'!$B$5,"Sí","No") | H5: =IF(AND(F5="Sí",G5="No"),E5,0) | I5: =IF(AND(F5="No",G5="Sí"),E5,0)
A6: F-002 | B6: Distribuidora Beta | C6: 46019 | D6: 46027 | E6: =IF('03_Detalle'!F6<>"",'03_Detalle'!F6,'03_Detalle'!E6) | F6: =IF(C6<='02_Parametros'!$B$5,"Sí","No") | G6: =IF(D6<='02_Parametros'!$B$5,"Sí","No") | H6: =IF(AND(F6="Sí",G6="No"),E6,0) | I6: =IF(AND(F6="No",G6="Sí"),E6,0)
A7: F-008 | B7: Theta Industrial | C7: 45839 | D7: 45838 | E7: =IF('03_Detalle'!F12<>"",'03_Detalle'!F12,'03_Detalle'!E12) | F7: =IF(C7<='02_Parametros'!$B$5,"Sí","No") | G7: =IF(D7<='02_Parametros'!$B$5,"Sí","No") | H7: =IF(AND(F7="Sí",G7="No"),E7,0) | I7: =IF(AND(F7="No",G7="Sí"),E7,0)
A8: TOTAL | E8: =SUM(E5:E7) | H8: =SUM(H5:H7) | I8: =SUM(I5:I7)
A10: ⓘ Cómo se calcula esta hoja
A11: Columna | B11: Fórmula (Excel) | C11: Cómo se calcula (sencillo) | D11: Ejemplo con números reales | E11: De dónde viene | F11: Norma
A12: Importe | B12: '=IF('03_Detalle'!F5<>"",'03_Detalle'!F5,'03_Detalle'!E5) | C12: Trae el importe facturado de la misma factura desde la hoja 03 (Detalle por factura); si no se informó, usa su saldo. | D12: Fila 1: IF((vacío)<>""; (vacío); 12.000,00) → 12.000,00 | E12: hoja «Detalle por factura» | F12: —
A13: Registrada en el ejercicio | B13: '=IF(C5<='02_Parametros'!$B$5,"Sí","No") | C13: Marca «Sí» si la fecha de emisión (registro) es igual o anterior a la fecha de corte de la hoja 02 (Parámetros). | D13: Fila 1: IF(«2025-12-10»<=«2025-12-31»; "Sí"; "No") → Sí | E13: «Emisión (registro)» (esta hoja), hoja «Parámetros» | F13: —
A14: Despachada en el ejercicio | B14: '=IF(D5<='02_Parametros'!$B$5,"Sí","No") | C14: Marca «Sí» si la fecha de despacho es igual o anterior a la fecha de corte de la hoja 02 (Parámetros). | D14: Fila 1: IF(«2025-12-10»<=«2025-12-31»; "Sí"; "No") → Sí | E14: «Despacho» (esta hoja), hoja «Parámetros» | F14: —
A15: Registrada antes del despacho | B15: '=IF(AND(F5="Sí",G5="No"),E5,0) | C15: Si la venta se registró en el ejercicio pero se despachó después del corte, toma su importe; si no, cero. | D15: Fila 1: IF(AND(«Sí»="Sí"; «Sí»="No"); 12.000,00; 0) → 0,00 | E15: «Registrada en el ejercicio» (esta hoja), «Despachada en el ejercicio» (esta hoja), «Importe» (esta hoja) | F15: —
A16: Despachada sin registrar | B16: '=IF(AND(F5="No",G5="Sí"),E5,0) | C16: Si la mercadería se despachó en el ejercicio pero la venta se registró después del corte, toma su importe; si no, cero. | D16: Fila 1: IF(AND(«Sí»="No"; «Sí»="Sí"); 12.000,00; 0) → 0,00 | E16: «Registrada en el ejercicio» (esta hoja), «Despachada en el ejercicio» (esta hoja), «Importe» (esta hoja) | F16: —

Sheet 08_Costo_amortizado
A1: Costo amortizado e intereses implícitos | H1: ⟵ Inicio | I1: ◀ Anterior | J1: Siguiente ▶
A2: Cuentas por cobrar y deterioro · cartera, cobros, circularización y costo amortizado · Cliente de muestra S.A. · corte 2025-12-31
A4: Factura | B4: Cliente | C4: Emisión | D4: Vencimiento | E4: Nominal | F4: Plazo (días) | G4: Días por vencer | H4: TIE = tasa de mercado | I4: Valor presente inicial (ingreso) | J4: Componente de financiación | K4: Costo amortizado al corte | L4: Interés devengado al corte | M4: Interés por devengar
A5: F-008 | B5: Theta Industrial | C5: 45839 | D5: 46569 | E5: ='03_Detalle'!E12 | F5: =D5-C5 | G5: =MAX(D5-'02_Parametros'!$B$5,0) | H5: =IF('02_Parametros'!$B$8="","",'02_Parametros'!$B$8/100) | I5: =IF(H5="","",E5/(1+H5)^(F5/365)) | J5: =IF(H5="","",E5-I5) | K5: =IF(H5="","",E5/(1+H5)^(G5/365)) | L5: =IF(H5="","",K5-I5) | M5: =IF(H5="","",E5-K5)
A6: TOTAL | E6: =SUM(E5:E5) | I6: =SUM(I5:I5) | J6: =SUM(J5:J5) | K6: =SUM(K5:K5) | L6: =SUM(L5:L5) | M6: =SUM(M5:M5)
A8: ⓘ Cómo se calcula esta hoja
A9: Columna | B9: Fórmula (Excel) | C9: Cómo se calcula (sencillo) | D9: Ejemplo con números reales | E9: De dónde viene | F9: Norma
A10: Nominal | B10: '='03_Detalle'!E12 | C10: Trae el saldo nominal de la misma factura desde la hoja 03 (Detalle por factura). | D10: Fila 1: 20.000,00 → 20.000,00 | E10: hoja «Detalle por factura» | F10: —
A11: Plazo (días) | B11: '=D5-C5 | C11: Cuenta los días entre la emisión y el vencimiento de la factura. | D11: Fila 1: «2027-07-01»-«2025-07-01» → 730 | E11: «Vencimiento» (esta hoja), «Emisión» (esta hoja) | F11: —
A12: Días por vencer | B12: '=MAX(D5-'02_Parametros'!$B$5,0) | C12: Cuenta los días que faltan desde la fecha de corte de la hoja 02 (Parámetros) hasta el vencimiento; si ya venció, es cero. | D12: Fila 1: MAX(«2027-07-01»-«2025-12-31»; 0) → 547 | E12: «Vencimiento» (esta hoja), hoja «Parámetros» | F12: —
A13: TIE = tasa de mercado | B13: '=IF('02_Parametros'!$B$8="","",'02_Parametros'!$B$8/100) | C13: Toma la tasa de mercado anual de la hoja 02 (Parámetros) dividida para 100; si no se indicó, queda en blanco. | D13: Fila 1: IF(10,00=""; ""; 10,00/100) → 10,00 % | E13: hoja «Parámetros» | F13: —
A14: Valor presente inicial (ingreso) | B14: '=IF(H5="","",E5/(1+H5)^(F5/365)) | C14: Descuenta el nominal con la tasa de mercado por todo el plazo de la factura: es el ingreso por la venta sin el componente financiero. Sin tasa, en blanco. | D14: Fila 1: IF(10,00 %=""; ""; 20.000,00/(1+10,00 %)^(730/365)) → 16.528,93 | E14: «TIE = tasa de mercado» (esta hoja), «Nominal» (esta hoja), «Plazo (días)» (esta hoja) | F14: —
A15: Componente de financiación | B15: '=IF(H5="","",E5-I5) | C15: Resta al nominal su valor presente inicial: el interés implícito total de la factura. Sin tasa, queda en blanco. | D15: Fila 1: IF(10,00 %=""; ""; 20.000,00-16.528,93) → 3.471,07 | E15: «TIE = tasa de mercado» (esta hoja), «Nominal» (esta hoja), «Valor presente inicial (ingreso)» (esta hoja) | F15: —
A16: Costo amortizado al corte | B16: '=IF(H5="","",E5/(1+H5)^(G5/365)) | C16: Descuenta el nominal con la tasa de mercado solo por los días que faltan para el vencimiento: el valor de la factura al corte. Sin tasa, en blanco. | D16: Fila 1: IF(10,00 %=""; ""; 20.000,00/(1+10,00 %)^(547/365)) → 17.337,95 | E16: «TIE = tasa de mercado» (esta hoja), «Nominal» (esta hoja), «Días por vencer» (esta hoja) | F16: —
A17: Interés devengado al corte | B17: '=IF(H5="","",K5-I5) | C17: Resta al costo amortizado al corte el valor presente inicial: el interés implícito ya ganado hasta el corte. Sin tasa, queda en blanco. | D17: Fila 1: IF(10,00 %=""; ""; 17.337,95-16.528,93) → 809,02 | E17: «TIE = tasa de mercado» (esta hoja), «Costo amortizado al corte» (esta hoja), «Valor presente inicial (ingreso)» (esta hoja) | F17: —
A18: Interés por devengar | B18: '=IF(H5="","",E5-K5) | C18: Resta al nominal el costo amortizado al corte: el interés implícito que falta ganar después del corte. Sin tasa, queda en blanco. | D18: Fila 1: IF(10,00 %=""; ""; 20.000,00-17.337,95) → 2.662,05 | E18: «TIE = tasa de mercado» (esta hoja), «Nominal» (esta hoja), «Costo amortizado al corte» (esta hoja) | F18: —

Sheet 09_Matriz_deterioro
A1: Matriz de deterioro | H1: ⟵ Inicio | I1: ◀ Anterior | J1: Siguiente ▶
A2: Cuentas por cobrar y deterioro · cartera, cobros, circularización y costo amortizado · Cliente de muestra S.A. · corte 2025-12-31
A4: Tramo | B4: Facturas | C4: Costo amortizado | D4: Tasa del tramo | E4: Deterioro requerido | F4: Tasa promedio aplicada
A5: Corriente / por vencer | B5: =COUNTIF('03_Detalle'!$H$5:$H$16,A5) | C5: =SUMIF('03_Detalle'!$H$5:$H$16,A5,'03_Detalle'!$K$5:$K$16) | D5: =IF('02_Parametros'!$B$12="","",'02_Parametros'!$B$12/100) | E5: =SUMIF('03_Detalle'!$H$5:$H$16,A5,'03_Detalle'!$O$5:$O$16) | F5: =IF(C5=0,"",E5/C5)
A6: 1 a 30 días | B6: =COUNTIF('03_Detalle'!$H$5:$H$16,A6) | C6: =SUMIF('03_Detalle'!$H$5:$H$16,A6,'03_Detalle'!$K$5:$K$16) | D6: =IF('02_Parametros'!$B$13="","",'02_Parametros'!$B$13/100) | E6: =SUMIF('03_Detalle'!$H$5:$H$16,A6,'03_Detalle'!$O$5:$O$16) | F6: =IF(C6=0,"",E6/C6)
A7: 31 a 60 días | B7: =COUNTIF('03_Detalle'!$H$5:$H$16,A7) | C7: =SUMIF('03_Detalle'!$H$5:$H$16,A7,'03_Detalle'!$K$5:$K$16) | D7: =IF('02_Parametros'!$B$14="","",'02_Parametros'!$B$14/100) | E7: =SUMIF('03_Detalle'!$H$5:$H$16,A7,'03_Detalle'!$O$5:$O$16) | F7: =IF(C7=0,"",E7/C7)
A8: 61 a 90 días | B8: =COUNTIF('03_Detalle'!$H$5:$H$16,A8) | C8: =SUMIF('03_Detalle'!$H$5:$H$16,A8,'03_Detalle'!$K$5:$K$16) | D8: =IF('02_Parametros'!$B$15="","",'02_Parametros'!$B$15/100) | E8: =SUMIF('03_Detalle'!$H$5:$H$16,A8,'03_Detalle'!$O$5:$O$16) | F8: =IF(C8=0,"",E8/C8)
A9: 91 a 180 días | B9: =COUNTIF('03_Detalle'!$H$5:$H$16,A9) | C9: =SUMIF('03_Detalle'!$H$5:$H$16,A9,'03_Detalle'!$K$5:$K$16) | D9: =IF('02_Parametros'!$B$16="","",'02_Parametros'!$B$16/100) | E9: =SUMIF('03_Detalle'!$H$5:$H$16,A9,'03_Detalle'!$O$5:$O$16) | F9: =IF(C9=0,"",E9/C9)
A10: 181 a 360 días | B10: =COUNTIF('03_Detalle'!$H$5:$H$16,A10) | C10: =SUMIF('03_Detalle'!$H$5:$H$16,A10,'03_Detalle'!$K$5:$K$16) | D10: =IF('02_Parametros'!$B$17="","",'02_Parametros'!$B$17/100) | E10: =SUMIF('03_Detalle'!$H$5:$H$16,A10,'03_Detalle'!$O$5:$O$16) | F10: =IF(C10=0,"",E10/C10)
A11: Más de 360 días | B11: =COUNTIF('03_Detalle'!$H$5:$H$16,A11) | C11: =SUMIF('03_Detalle'!$H$5:$H$16,A11,'03_Detalle'!$K$5:$K$16) | D11: =IF('02_Parametros'!$B$18="","",'02_Parametros'!$B$18/100) | E11: =SUMIF('03_Detalle'!$H$5:$H$16,A11,'03_Detalle'!$O$5:$O$16) | F11: =IF(C11=0,"",E11/C11)
A12: TOTAL | C12: =SUM(C5:C11) | E12: =SUM(E5:E11)
A14: ⓘ Cómo se calcula esta hoja
A15: Columna | B15: Fórmula (Excel) | C15: Cómo se calcula (sencillo) | D15: Ejemplo con números reales | E15: De dónde viene | F15: Norma
A16: Facturas | B16: '=COUNTIF('03_Detalle'!$H$5:$H$16,A5) | C16: Cuenta cuántas facturas del detalle (hoja 03, Detalle por factura) están en este tramo. | D16: Fila 1: COUNTIF([«Tramo» de «Detalle por factura», 12 filas]; «Corriente / por vencer») → 4 | E16: «Tramo» (esta hoja), hoja «Detalle por factura» | F16: —
A17: Costo amortizado | B17: '=SUMIF('03_Detalle'!$H$5:$H$16,A5,'03_Detalle'!$K$5:$K$16) | C17: Suma el costo amortizado de las facturas del detalle (hoja 03) que caen en este tramo. | D17: Fila 1: SUMIF([«Tramo» de «Detalle por factura», 12 filas]; «Corriente / por vencer»; [«Costo amortizado» de «Detalle por factura», 12 filas]) → 36.837,95 | E17: «Tramo» (esta hoja), hoja «Detalle por factura» | F17: —
A18: Tasa del tramo | B18: '=IF('02_Parametros'!$B$12="","",'02_Parametros'!$B$12/100) | C18: Toma la tasa del tramo de la hoja 02 (Parámetros) y la divide para 100; si no se fijó, queda en blanco. | D18: Fila 1: IF(1,00=""; ""; 1,00/100) → 1,00 % | E18: hoja «Parámetros» | F18: —
A19: Deterioro requerido | B19: '=SUMIF('03_Detalle'!$H$5:$H$16,A5,'03_Detalle'!$O$5:$O$16) | C19: Suma el deterioro requerido calculado factura por factura en la hoja 03 para este tramo, incluidas las facturas con tasa individual. | D19: Fila 1: SUMIF([«Tramo» de «Detalle por factura», 12 filas]; «Corriente / por vencer»; [«Deterioro requerido» de «Detalle por factura», 12 filas]) → 373,38 | E19: «Tramo» (esta hoja), hoja «Detalle por factura» | F19: —
A20: Tasa promedio aplicada | B20: '=IF(C5=0,"",E5/C5) | C20: Divide el deterioro requerido del tramo para su costo amortizado; si el tramo no tiene costo amortizado, queda en blanco. | D20: Fila 1: IF(36.837,95=0; ""; 373,38/36.837,95) → 1,01 % | E20: «Costo amortizado» (esta hoja), «Deterioro requerido» (esta hoja) | F20: —

Sheet 10_Ajuste
A1: Deterioro requerido vs registrado | H1: ⟵ Inicio | I1: ◀ Anterior | J1: Siguiente ▶
A2: Cuentas por cobrar y deterioro · cartera, cobros, circularización y costo amortizado · Cliente de muestra S.A. · corte 2025-12-31
A4: Concepto | B4: Importe | C4: Referencia
A5: Pérdida crediticia esperada requerida (NIIF 9) | B5: ='09_Matriz_deterioro'!E12 | C5: Matriz de deterioro + tasas individuales
A6: Deterioro registrado (mayor) | B6: ='02_Parametros'!$B$10 | C6: Parámetros
A7: Ajuste de deterioro propuesto | B7: =B5-B6 | C7: Positivo: falta deterioro; negativo: exceso
A8: Intereses implícitos por devengar requeridos | B8: =SUM('03_Detalle'!$L$5:$L$16) | C8: NIIF 9 5.1.1 y B5.1.1; PYMES 11.13
A9: Intereses por devengar registrados (mayor) | B9: ='02_Parametros'!$B$11 | C9: Parámetros
A10: Ajuste por financiación implícita | B10: =B8-B9 | C10: Menor valor de la cartera
A11: Ventas registradas antes del despacho | B11: ='07_Corte_ventas'!H8 | C11: NIIF 15 31, 38
A12: Ventas despachadas sin registrar en el ejercicio | B12: ='07_Corte_ventas'!I8 | C12: NIIF 15 31, 38
A13: Cartera vencida sin cobro posterior | B13: ='05_Cobros_posteriores'!J17 | C13: Evidencia sobre la estimación (NIA 540)
A14: Diferencias de circularización (absolutas) | B14: ='06_Circularizacion'!F8 | C14: NIA 505
A16: ⓘ Cómo se calcula esta hoja
A17: Columna | B17: Fórmula (Excel) | C17: Cómo se calcula (sencillo) | D17: Ejemplo con números reales | E17: De dónde viene | F17: Norma
A18: Importe | B18: '='09_Matriz_deterioro'!E12 | C18: El deterioro requerido sale del total de la hoja 09 (Matriz de deterioro); lo registrado, de la hoja 02 (Parámetros); los ajustes son requerido − registrado; los intereses se suman de la hoja 03; el corte, la cartera sin cobro y la circularización son los totales de las hojas 07, 05 y 06. | D18: Fila 1: 6.143,38 → 6.143,38 | E18: hoja «Matriz de deterioro» | F18: —

Sheet 11_Asientos
A1: Asientos propuestos | H1: ⟵ Inicio | I1: ◀ Anterior | J1: Siguiente ▶
A2: Cuentas por cobrar y deterioro · cartera, cobros, circularización y costo amortizado · Cliente de muestra S.A. · corte 2025-12-31
A4: Asiento | B4: Cuenta | C4: Debe | D4: Haber
A5: 1 · Deterioro faltante | B5: Gasto por pérdidas crediticias esperadas | C5: =ABS('10_Ajuste'!B7)
B6: (-) Deterioro de cuentas por cobrar | D6: =ABS('10_Ajuste'!B7)
A7: 2 · Componente de financiación no reconocido | B7: Ingresos de actividades ordinarias (componente de financiación) | C7: ='08_Costo_amortizado'!J6
B8: (-) Intereses implícitos por devengar (cartera) | D8: ='08_Costo_amortizado'!M6
B9: Ingresos financieros por intereses devengados | D9: ='08_Costo_amortizado'!L6
A10: 3 · Reverso de ventas no despachadas al corte | B10: Ingresos de actividades ordinarias | C10: ='10_Ajuste'!B11
B11: Cuentas por cobrar comerciales | D11: ='10_Ajuste'!B11
A13: ⓘ Cómo se calcula esta hoja
A14: Columna | B14: Fórmula (Excel) | C14: Cómo se calcula (sencillo) | D14: Ejemplo con números reales | E14: De dónde viene | F14: Norma
A15: Debe | B15: '=ABS('10_Ajuste'!B7) | C15: Toma cada importe de la hoja 10 (Deterioro requerido vs registrado) —ajuste de deterioro, de financiación o de corte— o, para el componente de financiación, de los totales de la hoja 08 (Costo amortizado e intereses implícitos). | D15: Fila 1: ABS(4.143,38) → 4.143,38 | E15: hoja «Deterioro requerido vs registrado» | F15: —
A16: Haber | B16: '=ABS('10_Ajuste'!B7) | C16: Lleva a la contrapartida los importes del asiento, tomados de la hoja 10 o de los totales de la hoja 08 (interés por devengar e interés devengado), para que debe y haber cuadren. | D16: Fila 2: ABS(4.143,38) → 4.143,38 | E16: hoja «Deterioro requerido vs registrado» | F16: —

Sheet 12_Problemas
A1: Problemas encontrados | H1: ⟵ Inicio | I1: ◀ Anterior | J1: Siguiente ▶
A2: Cuentas por cobrar y deterioro · cartera, cobros, circularización y costo amortizado · Cliente de muestra S.A. · corte 2025-12-31
A4: Código | B4: Descripción | C4: Importe
A5: VENCIDA_SIN_COBRO | B5: 6 factura(s) vencidas al corte sin cobro posterior suficiente: 18.000,00. Evalúe su recuperabilidad y la tasa aplicada (NIA 540, NIA 560). | C5: 18000
A6: COBRO_NO_POSTERIOR | B6: F-009: el cobro informado no tiene fecha posterior al corte; no se toma como cobro posterior. | C6: 6000
A7: DIF_CIRCULARIZACION | B7: 1 confirmación(es) con diferencia contra libros: F-004 -500,00. Investigue y concilie (NIA 505 párr. 14). | C7: 500
A8: ERROR_CORTE | B8: F-002: venta registrada en el ejercicio y despachada después del corte (NIIF 15 31 y 38). | C8: 8000
A9: FINANCIACION_NO_RECONOCIDA | B9: Intereses implícitos por devengar 2.662,05 frente a 0,00 registrados (dato del mayor no informado): cartera de plazo largo medida por su nominal (NIIF 9 5.1.1 y B5.1.1; NIIF 15 60–63; PYMES 11.13). | C9: 2662.05
A10: SALDOS_NEGATIVOS | B10: Saldos acreedores en la cartera -500,00 (anticipos o notas de crédito): evalúe su reclasificación al pasivo. | C10: -500
A11: DETERIORO_INSUFICIENTE | B11: La pérdida crediticia esperada requerida (6.143,38) supera el deterioro registrado (2.000,00). | C11: 4143.38

Sheet 13_Conclusion
A1: Conclusión | H1: ⟵ Inicio | I1: ◀ Anterior | J1: Siguiente ▶
A2: Cuentas por cobrar y deterioro · cartera, cobros, circularización y costo amortizado · Cliente de muestra S.A. · corte 2025-12-31
A4: Concepto | B4: Detalle
A5: Conciliación con el mayor | B5: Población None · mayor None · diferencia None
A6: Evaluación de excepciones
A7: Análisis
A8: Conclusión

Sheet 14_Control_Revision
A1: Control de revisión | H1: ⟵ Inicio | I1: ◀ Anterior
A2: Cuentas por cobrar y deterioro · cartera, cobros, circularización y costo amortizado · Cliente de muestra S.A. · corte 2025-12-31
A4: Fecha | B4: Acción | C4: Estado anterior | D4: Estado nuevo | E4: Actor | F4: Comentario
