Workbook

Sheet 00_Inicio
B2: AuditConsulting Auditores Cía. Ltda. · AUDIT-IA
B4: Efectivo y equivalentes de efectivo
B6: Cliente | C6: Cliente de muestra S.A. | D6: RUC | E6: 1790000000001
B7: Marco contable | C7: NIIF completas | D7: Fecha de corte | E7: 2025-12-31
B8: Preparó | C8: Ejercicio modelo | D8: Revisó | E8: Pendiente
B10: INDICADORES CLAVE
B11: Ajuste propuesto (auditado − libros) | C11: Problemas encontrados
B12: -39820 | C12: 17
B15: IR A LA CÉDULA
B16: Carátula | C16: Programa | D16: Base técnica | E16: Resumen
B17: Parámetros | C17: Conciliación bancaria por cuenta | D17: Partidas conciliatorias | E17: Antigüedad de partidas
B18: Confirmación bancaria | C18: Prueba de corte | D18: Efectivo restringido | E18: Equivalentes de efectivo (definición)
B19: Efectivo auditado y ajuste | C19: Asientos propuestos | D19: Problemas encontrados | E19: Conclusión
B20: Control de revisión
B22: PANORAMA | N22: Datos de los gráficos (fórmulas a las cédulas)
N23: Cifras del resumen | O23: Importe (USD)
N24: ='01_Resumen'!A5 | O24: ='01_Resumen'!B5
N25: ='01_Resumen'!A6 | O25: ='01_Resumen'!B6
N26: ='01_Resumen'!A7 | O26: ='01_Resumen'!B7
N27: ='01_Resumen'!A8 | O27: ='01_Resumen'!B8
N28: ='01_Resumen'!A9 | O28: ='01_Resumen'!B9
N29: ='01_Resumen'!A10 | O29: ='01_Resumen'!B10
N30: ='01_Resumen'!A11 | O30: ='01_Resumen'!B11
N31: ='01_Resumen'!A12 | O31: ='01_Resumen'!B12
N32: ='01_Resumen'!A13 | O32: ='01_Resumen'!B13
N33: ='01_Resumen'!A14 | O33: ='01_Resumen'!B14
N35: Hallazgos de mayor impacto | O35: Importe (USD)
N36: Equivalente presuncion | O36: =SUMIFS('12_Problemas'!$C$5:$C$21,'12_Problemas'!$A$5:$A$21,"EQUIVALENTE_PRESUNCION",'12_Problemas'!$C$5:$C$21,">0")-SUMIFS('12_Problemas'!$C$5:$C$21,'12_Problemas'!$A$5:$A$21,"EQUIVALENTE_PRESUNCION",'12_Problemas'!$C$5:$C$21,"<0")
N37: No es equivalente | O37: =SUMIFS('12_Problemas'!$C$5:$C$21,'12_Problemas'!$A$5:$A$21,"NO_ES_EQUIVALENTE",'12_Problemas'!$C$5:$C$21,">0")-SUMIFS('12_Problemas'!$C$5:$C$21,'12_Problemas'!$A$5:$A$21,"NO_ES_EQUIVALENTE",'12_Problemas'!$C$5:$C$21,"<0")
N38: Restringido revelar (×2) | O38: =SUMIFS('12_Problemas'!$C$5:$C$21,'12_Problemas'!$A$5:$A$21,"RESTRINGIDO_REVELAR",'12_Problemas'!$C$5:$C$21,">0")-SUMIFS('12_Problemas'!$C$5:$C$21,'12_Problemas'!$A$5:$A$21,"RESTRINGIDO_REVELAR",'12_Problemas'!$C$5:$C$21,"<0")
N39: Restringido como disponible | O39: =SUMIFS('12_Problemas'!$C$5:$C$21,'12_Problemas'!$A$5:$A$21,"RESTRINGIDO_COMO_DISPONIBLE",'12_Problemas'!$C$5:$C$21,">0")-SUMIFS('12_Problemas'!$C$5:$C$21,'12_Problemas'!$A$5:$A$21,"RESTRINGIDO_COMO_DISPONIBLE",'12_Problemas'!$C$5:$C$21,"<0")
N40: Saldo acreedor | O40: =SUMIFS('12_Problemas'!$C$5:$C$21,'12_Problemas'!$A$5:$A$21,"SALDO_ACREEDOR",'12_Problemas'!$C$5:$C$21,">0")-SUMIFS('12_Problemas'!$C$5:$C$21,'12_Problemas'!$A$5:$A$21,"SALDO_ACREEDOR",'12_Problemas'!$C$5:$C$21,"<0")
N41: Partida antigua (×2) | O41: =SUMIFS('12_Problemas'!$C$5:$C$21,'12_Problemas'!$A$5:$A$21,"PARTIDA_ANTIGUA",'12_Problemas'!$C$5:$C$21,">0")-SUMIFS('12_Problemas'!$C$5:$C$21,'12_Problemas'!$A$5:$A$21,"PARTIDA_ANTIGUA",'12_Problemas'!$C$5:$C$21,"<0")
N42: Partida no depurada (×2) | O42: =SUMIFS('12_Problemas'!$C$5:$C$21,'12_Problemas'!$A$5:$A$21,"PARTIDA_NO_DEPURADA",'12_Problemas'!$C$5:$C$21,">0")-SUMIFS('12_Problemas'!$C$5:$C$21,'12_Problemas'!$A$5:$A$21,"PARTIDA_NO_DEPURADA",'12_Problemas'!$C$5:$C$21,"<0")
N43: Otros (7 tipos) | O43: =SUMIF('12_Problemas'!$C$5:$C$21,">0")-SUMIF('12_Problemas'!$C$5:$C$21,"<0")-((SUMIFS('12_Problemas'!$C$5:$C$21,'12_Problemas'!$A$5:$A$21,"EQUIVALENTE_PRESUNCION",'12_Problemas'!$C$5:$C$21,">0")-SUMIFS('12_Problemas'!$C$5:$C$21,'12_Problemas'!$A$5:$A$21,"EQUIVALENTE_PRESUNCION",'12_Problemas'!$C$5:$C$21,"<0"))+(SUMIFS('12_Problemas'!$C$5:$C$21,'12_Problemas'!$A$5:$A$21,"NO_ES_EQUIVALENTE",'12_Problemas'!$C$5:$C$21,">0")-SUMIFS('12_Problemas'!$C$5:$C$21,'12_Problemas'!$A$5:$A$21,"NO_ES_EQUIVALENTE",'12_Problemas'!$C$5:$C$21,"<0"))+(SUMIFS('12_Problemas'!$C$5:$C$21,'12_Problemas'!$A$5:$A$21,"RESTRINGIDO_REVELAR",'12_Problemas'!$C$5:$C$21,">0")-SUMIFS('12_Problemas'!$C$5:$C$21,'12_Problemas'!$A$5:$A$21,"RESTRINGIDO_REVELAR",'12_Problemas'!$C$5:$C$21,"<0"))+(SUMIFS('12_Problemas'!$C$5:$C$21,'12_Problemas'!$A$5:$A$21,"RESTRINGIDO_COMO_DISPONIBLE",'12_Problemas'!$C$5:$C$21,">0")-SUMIFS('12_Problemas'!$C$5:$C$21,'12_Problemas'!$A$5:$A$21,"RESTRINGIDO_COMO_DISPONIBLE",'12_Problemas'!$C$5:$C$21,"<0"))+(SUMIFS('12_Problemas'!$C$5:$C$21,'12_Problemas'!$A$5:$A$21,"SALDO_ACREEDOR",'12_Problemas'!$C$5:$C$21,">0")-SUMIFS('12_Problemas'!$C$5:$C$21,'12_Problemas'!$A$5:$A$21,"SALDO_ACREEDOR",'12_Problemas'!$C$5:$C$21,"<0"))+(SUMIFS('12_Problemas'!$C$5:$C$21,'12_Problemas'!$A$5:$A$21,"PARTIDA_ANTIGUA",'12_Problemas'!$C$5:$C$21,">0")-SUMIFS('12_Problemas'!$C$5:$C$21,'12_Problemas'!$A$5:$A$21,"PARTIDA_ANTIGUA",'12_Problemas'!$C$5:$C$21,"<0"))+(SUMIFS('12_Problemas'!$C$5:$C$21,'12_Problemas'!$A$5:$A$21,"PARTIDA_NO_DEPURADA",'12_Problemas'!$C$5:$C$21,">0")-SUMIFS('12_Problemas'!$C$5:$C$21,'12_Problemas'!$A$5:$A$21,"PARTIDA_NO_DEPURADA",'12_Problemas'!$C$5:$C$21,"<0")))

Sheet 00_Caratula
A1: Carátula | H1: ⟵ Inicio | J1: Siguiente ▶
A2: Efectivo y equivalentes de efectivo · Cliente de muestra S.A. · corte 2025-12-31
A4: Concepto | B4: Detalle
A5: Firma | B5: AuditConsulting Auditores Cía. Ltda.
A6: Cliente | B6: Cliente de muestra S.A.
A7: RUC | B7: 1790000000001
A8: Ejercicio | B8: 2025
A9: Fecha de corte | B9: 2025-12-31
A10: Marco contable | B10: NIIF completas
A11: Herramienta | B11: Efectivo y equivalentes de efectivo
A12: Rubro | B12: Caja y bancos
A13: Motor | B13: efectivo_equivalentes 1.0
A14: Versión del papel | B14: v1
A15: Estado | B15: MUESTRA
... A17: Revisó | B17: Pendiente
A18: Aprobó
A19: Fecha de aprobación
A20: Huella de la ejecución (SHA-256)

Sheet 00_Programa
A1: Programa | H1: ⟵ Inicio | I1: ◀ Anterior | J1: Siguiente ▶
A2: Efectivo y equivalentes de efectivo · Cliente de muestra S.A. · corte 2025-12-31
A4: Código | B4: Objetivo | C4: Afirmación | D4: Procedimiento | E4: Evidencia | F4: Criterio | G4: Referencia
A5: CAJ-01 | B5: Integridad y exactitud del saldo | C5: Integridad | D5: Conciliar el anexo de cuentas con el mayor y el balance de comprobación | E5: Anexo de cuentas, mayor, balance | F5: Diferencia dentro de tolerancia | G5: NIA 500 párr. 9 · NIC 7.45
A6: CAJ-02 | B6: Conciliación bancaria | C6: Existencia | D6: Reejecutar la conciliación de cada cuenta con el estado bancario y las partidas conciliatorias | E6: Conciliaciones y estados bancarios del mes de corte | F6: Diferencia no explicada = 0 | G6: NIA 500 · NIA 330
A7: CAJ-03 | B7: Partidas conciliatorias y antigüedad | C7: Existencia | D7: Cotejar cada partida con su liquidación en el estado bancario posterior y medir su antigüedad | E7: Estados bancarios posteriores al corte | F7: Partidas liquidadas y no antiguas | G7: NIA 500 párr. 6 · NIA 330 párr. 18 (NIA 560 párr. 6 solo si la partida revela un hecho posterior)
A8: CAJ-04 | B8: Confirmación bancaria | C8: Existencia / Derechos | D8: Confirmar saldos, restricciones y garantías con cada banco bajo control del auditor | E8: Respuestas de los bancos | F8: Confirmado = estado bancario | G8: NIA 505
A9: CAJ-05 | B9: Corte | C9: Corte | D9: Comparar fechas en libros y en el banco de depósitos en tránsito y cheques alrededor del cierre | E9: Libro bancos y estados bancarios de diciembre y enero | F9: Acreditación dentro de la ventana | G9: NIA 240 párr. 31 y Anexo 2 · NIA 330
A10: CAJ-06 | B10: Efectivo restringido | C10: Presentación | D10: Identificar restricciones, garantías y embargos; clasificar y revelar | E10: Contratos, respuestas bancarias, actas | F10: Restringido revelado; no corriente el de al menos doce meses | G10: NIC 7.48 · NIC 1.66 d) · PYMES 7.21 y 4.5 d)
A11: CAJ-07 | B11: Definición de equivalentes | C11: Clasificación | D11: Evaluar plazo desde la adquisición, liquidez y riesgo de cada inversión | E11: Certificados y contratos de inversión | F11: Vence en tres meses o menos desde la adquisición, con gran liquidez y riesgo poco significativo; si no, reclasificar | G11: NIC 7.6–7.7 · PYMES 7.2
A12: CAJ-08 | B12: Presentación y revelación | C12: Presentación | D12: Cotejar la nota de efectivo con la composición auditada y la política de composición | E12: Estados financieros y nota | F12: Nota completa | G12: NIC 7.45–7.46 · PYMES 7.20

Sheet 00_Fuentes
A1: Base técnica | H1: ⟵ Inicio | I1: ◀ Anterior | J1: Siguiente ▶
A2: Efectivo y equivalentes de efectivo · Cliente de muestra S.A. · corte 2025-12-31
A4: Categoría | B4: Documento | C4: Párrafos | D4: URL | E4: Verificada
A5: NIA · NIA 505 | B5: Confirmación bancaria bajo control del auditor; sin respuesta, procedimientos alternativos. | C5: párr. 7 y 12
A6: NIA · NIA 500 | B6: Exactitud e integridad de la información del cliente (conciliaciones y anexos). | C6: párr. 9
A7: NIA · NIA 330 | B7: Conciliar los estados financieros con los registros contables. | C7: párr. 20 a)
A8: NIA · NIA 240 | B8: Corte y movimientos alrededor del cierre como riesgo de fraude (numeración del Manual IAASB 2023-2024; la NIA 240 revisada de 2025 cambia la numeración). | C8: párr. 27, 31 y Anexo 2 (corte)
A9: NIA · NIA 450 | B9: Acumular y evaluar las diferencias no explicadas y los ajustes. | C9: párr. 5 y 11

Sheet 01_Resumen
A1: Resumen | H1: ⟵ Inicio | I1: ◀ Anterior | J1: Siguiente ▶
A2: Efectivo y equivalentes de efectivo · Cliente de muestra S.A. · corte 2025-12-31
A4: Concepto | B4: Importe
A5: Efectivo y equivalentes según libros | B5: ='10_Efectivo_auditado'!B5
A6: Notas bancarias no registradas (crédito − débito) | B6: ='10_Efectivo_auditado'!B8
A7: Reclasificación a no corriente (restricción ≥ 12 meses) | B7: ='10_Efectivo_auditado'!B9
A8: Reclasificación de inversiones que no son equivalentes | B8: ='10_Efectivo_auditado'!B11
A9: Efectivo y equivalentes auditado | B9: ='10_Efectivo_auditado'!B12
A10: Ajuste propuesto (auditado − libros) | B10: ='10_Efectivo_auditado'!B13
A11: Diferencias de conciliación no explicadas (absolutas) | B11: ='10_Efectivo_auditado'!B17
A12: Diferencias de confirmación (absolutas) | B12: ='10_Efectivo_auditado'!B18
A13: Partidas conciliatorias antiguas | B13: ='10_Efectivo_auditado'!B19
A14: Partidas no depuradas después del corte | B14: ='10_Efectivo_auditado'!B20
A16: ⓘ Cómo se calcula esta hoja
A17: Columna | B17: Fórmula (Excel) | C17: Cómo se calcula (sencillo) | D17: Ejemplo con números reales | E17: De dónde viene | F17: Norma
A18: Importe | B18: '='10_Efectivo_auditado'!B5 | C18: Trae cada importe, concepto por concepto, de la hoja 10 (Efectivo auditado y ajuste), donde se calcula el efectivo auditado, las reclasificaciones y las diferencias encontradas. | D18: Fila 1: 274.630,50 → 274.630,50 | E18: hoja «Efectivo auditado y ajuste» | F18: —

Sheet 02_Parametros
A1: Parámetros | H1: ⟵ Inicio | I1: ◀ Anterior | J1: Siguiente ▶
A2: Efectivo y equivalentes de efectivo · Cliente de muestra S.A. · corte 2025-12-31
A4: Parámetro | B4: Valor | C4: Sustento
A5: Fecha de corte | B5: 46022 | C5: Ficha del encargo
A6: Partida antigua desde (días al corte) | B6: 90 | C6: Juicio del auditor (antigüedad de partidas conciliatorias)
A7: Días para que el banco acredite un depósito en tránsito | B7: 5 | C7: Juicio del auditor (prueba de corte, NIA 240 párr. 31 y Anexo 2)
A8: Plazo de un equivalente (meses desde la adquisición) | B8: 3 | C8: NIC 7.6–7.7: «tres meses o menos desde la fecha de adquisición» (presunción: la definición exige además gran liquidez y riesgo poco significativo de cambios de valor)
A9: Meses de restricción que la hacen no corriente | B9: 12 | C9: NIC 7.48 y NIC 1.66 d) (al corte 2025 aplica la NIC 1; la NIIF 18 rige para ejercicios desde el 1-1-2027; desde 2027 el requisito pasa a NIIF 18 párr. 99 d))
A10: Tolerancia de diferencias (USD) | B10: 0 | C10: Juicio del auditor; 0 = toda diferencia se reporta
A11: Marco del encargo | B11: NIIF completas | C11: El cálculo es el mismo en ambos marcos; cambian las referencias citadas
A12: Definición de equivalentes | B12: NIC 7.6–7.7 | C12: Inversión a corto plazo, gran liquidez, riesgo poco significativo de cambios de valor
A13: Composición y conciliación con el estado de situación | B13: NIC 7.45–7.46 | C13: Revelar componentes y política de composición
A14: Límite de la restricción (corte + meses) | B14: 46387 | C14: EDATE(corte; meses): después de esta fecha → no corriente

Sheet 03_Conciliacion
A1: Conciliación bancaria por cuenta | H1: ⟵ Inicio | I1: ◀ Anterior | J1: Siguiente ▶
A2: Efectivo y equivalentes de efectivo · Cliente de muestra S.A. · corte 2025-12-31
A4: Cuenta | B4: Banco / caja | C4: Tipo | D4: Saldo estado bancario / arqueo | E4: (+) Depósitos en tránsito | F4: (−) Cheques pendientes | G4: (−) Notas de crédito no registradas | H4: (+) Notas de débito no registradas | I4: (±) Otras partidas | J4: Saldo que explica la conciliación | K4: Saldo según libros | L4: Diferencia no explicada | M4: Saldo ajustado de libros | N4: Efectivo auditado
A5: 1.1.01.01 | B5: Caja general | C5: Caja | D5: 500 | E5: =SUMIFS('04_Partidas'!$F$5:$F$13,'04_Partidas'!$B$5:$B$13,A5,'04_Partidas'!$C$5:$C$13,"Depósito en tránsito") | F5: =SUMIFS('04_Partidas'!$F$5:$F$13,'04_Partidas'!$B$5:$B$13,A5,'04_Partidas'!$C$5:$C$13,"Cheque pendiente") | G5: =SUMIFS('04_Partidas'!$F$5:$F$13,'04_Partidas'!$B$5:$B$13,A5,'04_Partidas'!$C$5:$C$13,"Nota de crédito") | H5: =SUMIFS('04_Partidas'!$F$5:$F$13,'04_Partidas'!$B$5:$B$13,A5,'04_Partidas'!$C$5:$C$13,"Nota de débito") | I5: =SUMIFS('04_Partidas'!$F$5:$F$13,'04_Partidas'!$B$5:$B$13,A5,'04_Partidas'!$C$5:$C$13,"Otra partida") | J5: =IF(D5="","",D5+E5-F5-G5+H5+I5) | K5: 500 | L5: =IF(J5="","",ROUND(K5-J5,2)) | M5: =K5+G5-H5 | N5: =M5-SUMIF('08_Restringido'!$A$5:$A$6,A5,'08_Restringido'!$I$5:$I$6)-SUMIF('09_Equivalentes'!$A$5:$A$6,A5,'09_Equivalentes'!$I$5:$I$6)
A6: 1.1.01.02 | B6: Caja chica | C6: Caja | D6: 300 | E6: =SUMIFS('04_Partidas'!$F$5:$F$13,'04_Partidas'!$B$5:$B$13,A6,'04_Partidas'!$C$5:$C$13,"Depósito en tránsito") | F6: =SUMIFS('04_Partidas'!$F$5:$F$13,'04_Partidas'!$B$5:$B$13,A6,'04_Partidas'!$C$5:$C$13,"Cheque pendiente") | G6: =SUMIFS('04_Partidas'!$F$5:$F$13,'04_Partidas'!$B$5:$B$13,A6,'04_Partidas'!$C$5:$C$13,"Nota de crédito") | H6: =SUMIFS('04_Partidas'!$F$5:$F$13,'04_Partidas'!$B$5:$B$13,A6,'04_Partidas'!$C$5:$C$13,"Nota de débito") | I6: =SUMIFS('04_Partidas'!$F$5:$F$13,'04_Partidas'!$B$5:$B$13,A6,'04_Partidas'!$C$5:$C$13,"Otra partida") | J6: =IF(D6="","",D6+E6-F6-G6+H6+I6) | K6: 300 | L6: =IF(J6="","",ROUND(K6-J6,2)) | M6: =K6+G6-H6 | N6: =M6-SUMIF('08_Restringido'!$A$5:$A$6,A6,'08_Restringido'!$I$5:$I$6)-SUMIF('09_Equivalentes'!$A$5:$A$6,A6,'09_Equivalentes'!$I$5:$I$6)
A7: 1.1.02.01 | B7: Banco Pichincha Cte. ***4521 | C7: Banco | D7: 131210.5 | E7: =SUMIFS('04_Partidas'!$F$5:$F$13,'04_Partidas'!$B$5:$B$13,A7,'04_Partidas'!$C$5:$C$13,"Depósito en tránsito") | F7: =SUMIFS('04_Partidas'!$F$5:$F$13,'04_Partidas'!$B$5:$B$13,A7,'04_Partidas'!$C$5:$C$13,"Cheque pendiente") | G7: =SUMIFS('04_Partidas'!$F$5:$F$13,'04_Partidas'!$B$5:$B$13,A7,'04_Partidas'!$C$5:$C$13,"Nota de crédito") | H7: =SUMIFS('04_Partidas'!$F$5:$F$13,'04_Partidas'!$B$5:$B$13,A7,'04_Partidas'!$C$5:$C$13,"Nota de débito") | I7: =SUMIFS('04_Partidas'!$F$5:$F$13,'04_Partidas'!$B$5:$B$13,A7,'04_Partidas'!$C$5:$C$13,"Otra partida") | J7: =IF(D7="","",D7+E7-F7-G7+H7+I7) | K7: 125680.5 | L7: =IF(J7="","",ROUND(K7-J7,2)) | M7: =K7+G7-H7 | N7: =M7-SUMIF('08_Restringido'!$A$5:$A$6,A7,'08_Restringido'!$I$5:$I$6)-SUMIF('09_Equivalentes'!$A$5:$A$6,A7,'09_Equivalentes'!$I$5:$I$6)
A8: 1.1.02.02 | B8: Banco Guayaquil Aho. ***7788 | C8: Banco | D8: 45900 | E8: =SUMIFS('04_Partidas'!$F$5:$F$13,'04_Partidas'!$B$5:$B$13,A8,'04_Partidas'!$C$5:$C$13,"Depósito en tránsito") | F8: =SUMIFS('04_Partidas'!$F$5:$F$13,'04_Partidas'!$B$5:$B$13,A8,'04_Partidas'!$C$5:$C$13,"Cheque pendiente") | G8: =SUMIFS('04_Partidas'!$F$5:$F$13,'04_Partidas'!$B$5:$B$13,A8,'04_Partidas'!$C$5:$C$13,"Nota de crédito") | H8: =SUMIFS('04_Partidas'!$F$5:$F$13,'04_Partidas'!$B$5:$B$13,A8,'04_Partidas'!$C$5:$C$13,"Nota de débito") | I8: =SUMIFS('04_Partidas'!$F$5:$F$13,'04_Partidas'!$B$5:$B$13,A8,'04_Partidas'!$C$5:$C$13,"Otra partida") | J8: =IF(D8="","",D8+E8-F8-G8+H8+I8) | K8: 47700 | L8: =IF(J8="","",ROUND(K8-J8,2)) | M8: =K8+G8-H8 | N8: =M8-SUMIF('08_Restringido'!$A$5:$A$6,A8,'08_Restringido'!$I$5:$I$6)-SUMIF('09_Equivalentes'!$A$5:$A$6,A8,'09_Equivalentes'!$I$5:$I$6)
A9: 1.1.02.03 | B9: Produbanco Cte. ***3390 | C9: Banco | D9: 22000 | E9: =SUMIFS('04_Partidas'!$F$5:$F$13,'04_Partidas'!$B$5:$B$13,A9,'04_Partidas'!$C$5:$C$13,"Depósito en tránsito") | F9: =SUMIFS('04_Partidas'!$F$5:$F$13,'04_Partidas'!$B$5:$B$13,A9,'04_Partidas'!$C$5:$C$13,"Cheque pendiente") | G9: =SUMIFS('04_Partidas'!$F$5:$F$13,'04_Partidas'!$B$5:$B$13,A9,'04_Partidas'!$C$5:$C$13,"Nota de crédito") | H9: =SUMIFS('04_Partidas'!$F$5:$F$13,'04_Partidas'!$B$5:$B$13,A9,'04_Partidas'!$C$5:$C$13,"Nota de débito") | I9: =SUMIFS('04_Partidas'!$F$5:$F$13,'04_Partidas'!$B$5:$B$13,A9,'04_Partidas'!$C$5:$C$13,"Otra partida") | J9: =IF(D9="","",D9+E9-F9-G9+H9+I9) | K9: 22000 | L9: =IF(J9="","",ROUND(K9-J9,2)) | M9: =K9+G9-H9 | N9: =M9-SUMIF('08_Restringido'!$A$5:$A$6,A9,'08_Restringido'!$I$5:$I$6)-SUMIF('09_Equivalentes'!$A$5:$A$6,A9,'09_Equivalentes'!$I$5:$I$6)
A10: 1.1.02.04 | B10: Banco Internacional Cte. ***1102 | C10: Banco | D10: 1200 | E10: =SUMIFS('04_Partidas'!$F$5:$F$13,'04_Partidas'!$B$5:$B$13,A10,'04_Partidas'!$C$5:$C$13,"Depósito en tránsito") | F10: =SUMIFS('04_Partidas'!$F$5:$F$13,'04_Partidas'!$B$5:$B$13,A10,'04_Partidas'!$C$5:$C$13,"Cheque pendiente") | G10: =SUMIFS('04_Partidas'!$F$5:$F$13,'04_Partidas'!$B$5:$B$13,A10,'04_Partidas'!$C$5:$C$13,"Nota de crédito") | H10: =SUMIFS('04_Partidas'!$F$5:$F$13,'04_Partidas'!$B$5:$B$13,A10,'04_Partidas'!$C$5:$C$13,"Nota de débito") | I10: =SUMIFS('04_Partidas'!$F$5:$F$13,'04_Partidas'!$B$5:$B$13,A10,'04_Partidas'!$C$5:$C$13,"Otra partida") | J10: =IF(D10="","",D10+E10-F10-G10+H10+I10) | K10: 1650 | L10: =IF(J10="","",ROUND(K10-J10,2)) | M10: =K10+G10-H10 | N10: =M10-SUMIF('08_Restringido'!$A$5:$A$6,A10,'08_Restringido'!$I$5:$I$6)-SUMIF('09_Equivalentes'!$A$5:$A$6,A10,'09_Equivalentes'!$I$5:$I$6)
A11: 1.1.02.05 | B11: Banco Bolivariano Cte. ***5566 | C11: Banco | D11: -3200 | E11: =SUMIFS('04_Partidas'!$F$5:$F$13,'04_Partidas'!$B$5:$B$13,A11,'04_Partidas'!$C$5:$C$13,"Depósito en tránsito") | F11: =SUMIFS('04_Partidas'!$F$5:$F$13,'04_Partidas'!$B$5:$B$13,A11,'04_Partidas'!$C$5:$C$13,"Cheque pendiente") | G11: =SUMIFS('04_Partidas'!$F$5:$F$13,'04_Partidas'!$B$5:$B$13,A11,'04_Partidas'!$C$5:$C$13,"Nota de crédito") | H11: =SUMIFS('04_Partidas'!$F$5:$F$13,'04_Partidas'!$B$5:$B$13,A11,'04_Partidas'!$C$5:$C$13,"Nota de débito") | I11: =SUMIFS('04_Partidas'!$F$5:$F$13,'04_Partidas'!$B$5:$B$13,A11,'04_Partidas'!$C$5:$C$13,"Otra partida") | J11: =IF(D11="","",D11+E11-F11-G11+H11+I11) | K11: -3200 | L11: =IF(J11="","",ROUND(K11-J11,2)) | M11: =K11+G11-H11 | N11: =M11-SUMIF('08_Restringido'!$A$5:$A$6,A11,'08_Restringido'!$I$5:$I$6)-SUMIF('09_Equivalentes'!$A$5:$A$6,A11,'09_Equivalentes'!$I$5:$I$6)
A12: 1.1.03.01 | B12: Póliza de acumulación Pichincha 60 días | C12: Inversión | D12: 50000 | E12: =SUMIFS('04_Partidas'!$F$5:$F$13,'04_Partidas'!$B$5:$B$13,A12,'04_Partidas'!$C$5:$C$13,"Depósito en tránsito") | F12: =SUMIFS('04_Partidas'!$F$5:$F$13,'04_Partidas'!$B$5:$B$13,A12,'04_Partidas'!$C$5:$C$13,"Cheque pendiente") | G12: =SUMIFS('04_Partidas'!$F$5:$F$13,'04_Partidas'!$B$5:$B$13,A12,'04_Partidas'!$C$5:$C$13,"Nota de crédito") | H12: =SUMIFS('04_Partidas'!$F$5:$F$13,'04_Partidas'!$B$5:$B$13,A12,'04_Partidas'!$C$5:$C$13,"Nota de débito") | I12: =SUMIFS('04_Partidas'!$F$5:$F$13,'04_Partidas'!$B$5:$B$13,A12,'04_Partidas'!$C$5:$C$13,"Otra partida") | J12: =IF(D12="","",D12+E12-F12-G12+H12+I12) | K12: 50000 | L12: =IF(J12="","",ROUND(K12-J12,2)) | M12: =K12+G12-H12 | N12: =M12-SUMIF('08_Restringido'!$A$5:$A$6,A12,'08_Restringido'!$I$5:$I$6)-SUMIF('09_Equivalentes'!$A$5:$A$6,A12,'09_Equivalentes'!$I$5:$I$6)
A13: 1.1.03.02 | B13: Certificado de depósito Produbanco 180 días | C13: Inversión | D13: 30000 | E13: =SUMIFS('04_Partidas'!$F$5:$F$13,'04_Partidas'!$B$5:$B$13,A13,'04_Partidas'!$C$5:$C$13,"Depósito en tránsito") | F13: =SUMIFS('04_Partidas'!$F$5:$F$13,'04_Partidas'!$B$5:$B$13,A13,'04_Partidas'!$C$5:$C$13,"Cheque pendiente") | G13: =SUMIFS('04_Partidas'!$F$5:$F$13,'04_Partidas'!$B$5:$B$13,A13,'04_Partidas'!$C$5:$C$13,"Nota de crédito") | H13: =SUMIFS('04_Partidas'!$F$5:$F$13,'04_Partidas'!$B$5:$B$13,A13,'04_Partidas'!$C$5:$C$13,"Nota de débito") | I13: =SUMIFS('04_Partidas'!$F$5:$F$13,'04_Partidas'!$B$5:$B$13,A13,'04_Partidas'!$C$5:$C$13,"Otra partida") | J13: =IF(D13="","",D13+E13-F13-G13+H13+I13) | K13: 30000 | L13: =IF(J13="","",ROUND(K13-J13,2)) | M13: =K13+G13-H13 | N13: =M13-SUMIF('08_Restringido'!$A$5:$A$6,A13,'08_Restringido'!$I$5:$I$6)-SUMIF('09_Equivalentes'!$A$5:$A$6,A13,'09_Equivalentes'!$I$5:$I$6)
A14: TOTAL | E14: =SUM(E5:E13) | F14: =SUM(F5:F13) | G14: =SUM(G5:G13) | H14: =SUM(H5:H13) | I14: =SUM(I5:I13) | K14: =SUM(K5:K13) | M14: =SUM(M5:M13) | N14: =SUM(N5:N13)
A16: ⓘ Cómo se calcula esta hoja
A17: Columna | B17: Fórmula (Excel) | C17: Cómo se calcula (sencillo) | D17: Ejemplo con números reales | E17: De dónde viene | F17: Norma
A18: (+) Depósitos en tránsito | B18: '=SUMIFS('04_Partidas'!$F$5:$F$13,'04_Partidas'!$B$5:$B$13,A5,'04_Partidas'!$C$5:$C$13,"Depósito en tránsito") | C18: Suma el importe de las partidas conciliatorias de esta cuenta que en la hoja 04 (Partidas conciliatorias) están clasificadas como «Depósito en tránsito». | D18: Fila 1: SUMIFS([«Importe» de «Partidas conciliatorias», 9 filas]; [«Cuenta» de «Partidas conciliatorias», 9 filas]; «1.1.01.01»; [«Tipo» de «Partidas conciliatorias», 9 filas]; "Depósito en tránsito") → 0,00 | E18: «Cuenta» (esta hoja), hoja «Partidas conciliatorias» | F18: —
A19: (−) Cheques pendientes | B19: '=SUMIFS('04_Partidas'!$F$5:$F$13,'04_Partidas'!$B$5:$B$13,A5,'04_Partidas'!$C$5:$C$13,"Cheque pendiente") | C19: Suma el importe de las partidas conciliatorias de esta cuenta que en la hoja 04 (Partidas conciliatorias) están clasificadas como «Cheque pendiente». | D19: Fila 1: SUMIFS([«Importe» de «Partidas conciliatorias», 9 filas]; [«Cuenta» de «Partidas conciliatorias», 9 filas]; «1.1.01.01»; [«Tipo» de «Partidas conciliatorias», 9 filas]; "Cheque pendiente") → 0,00 | E19: «Cuenta» (esta hoja), hoja «Partidas conciliatorias» | F19: —
A20: (−) Notas de crédito no registradas | B20: '=SUMIFS('04_Partidas'!$F$5:$F$13,'04_Partidas'!$B$5:$B$13,A5,'04_Partidas'!$C$5:$C$13,"Nota de crédito") | C20: Suma el importe de las partidas conciliatorias de esta cuenta que en la hoja 04 (Partidas conciliatorias) están clasificadas como «Nota de crédito». | D20: Fila 1: SUMIFS([«Importe» de «Partidas conciliatorias», 9 filas]; [«Cuenta» de «Partidas conciliatorias», 9 filas]; «1.1.01.01»; [«Tipo» de «Partidas conciliatorias», 9 filas]; "Nota de crédito") → 0,00 | E20: «Cuenta» (esta hoja), hoja «Partidas conciliatorias» | F20: —
A21: (+) Notas de débito no registradas | B21: '=SUMIFS('04_Partidas'!$F$5:$F$13,'04_Partidas'!$B$5:$B$13,A5,'04_Partidas'!$C$5:$C$13,"Nota de débito") | C21: Suma el importe de las partidas conciliatorias de esta cuenta que en la hoja 04 (Partidas conciliatorias) están clasificadas como «Nota de débito». | D21: Fila 1: SUMIFS([«Importe» de «Partidas conciliatorias», 9 filas]; [«Cuenta» de «Partidas conciliatorias», 9 filas]; «1.1.01.01»; [«Tipo» de «Partidas conciliatorias», 9 filas]; "Nota de débito") → 0,00 | E21: «Cuenta» (esta hoja), hoja «Partidas conciliatorias» | F21: —
A22: (±) Otras partidas | B22: '=SUMIFS('04_Partidas'!$F$5:$F$13,'04_Partidas'!$B$5:$B$13,A5,'04_Partidas'!$C$5:$C$13,"Otra partida") | C22: Suma el importe de las partidas conciliatorias de esta cuenta que en la hoja 04 (Partidas conciliatorias) están clasificadas como «Otra partida». | D22: Fila 1: SUMIFS([«Importe» de «Partidas conciliatorias», 9 filas]; [«Cuenta» de «Partidas conciliatorias», 9 filas]; «1.1.01.01»; [«Tipo» de «Partidas conciliatorias», 9 filas]; "Otra partida") → 0,00 | E22: «Cuenta» (esta hoja), hoja «Partidas conciliatorias» | F22: —
A23: Saldo que explica la conciliación | B23: '=IF(D5="","",D5+E5-F5-G5+H5+I5) | C23: Parte del saldo del estado bancario o arqueo, suma los depósitos en tránsito, resta los cheques pendientes y las notas de crédito, y suma las notas de débito y otras partidas. Sin saldo bancario, queda en blanco. | D23: Fila 1: IF(500,00=""; ""; 500,00+0,00-0,00-0,00+0,00+0,00) → 500,00 | E23: «Saldo estado bancario / arqueo» (esta hoja), «(+) Depósitos en tránsito» (esta hoja), «(−) Cheques pendientes» (esta hoja), «(−) Notas de crédito no registradas» (esta hoja), «(+) Notas de débito no registradas» (esta hoja), «(±) Otras partidas» (esta hoja) | F23: —
A24: Diferencia no explicada | B24: '=IF(J5="","",ROUND(K5-J5,2)) | C24: Resta al saldo según libros el saldo que explica la conciliación, redondeado a centavos: lo que la conciliación no alcanza a justificar. Sin saldo bancario, queda en blanco. | D24: Fila 1: IF(500,00=""; ""; ROUND(500,00-500,00; 2)) → 0,00 | E24: «Saldo que explica la conciliación» (esta hoja), «Saldo según libros» (esta hoja) | F24: —
A25: Saldo ajustado de libros | B25: '=K5+G5-H5 | C25: Parte del saldo según libros, suma las notas de crédito y resta las notas de débito que el banco registró y los libros todavía no. | D25: Fila 1: 500,00+0,00-0,00 → 500,00 | E25: «Saldo según libros» (esta hoja), «(−) Notas de crédito no registradas» (esta hoja), «(+) Notas de débito no registradas» (esta hoja) | F25: —
A26: Efectivo auditado | B26: '=M5-SUMIF('08_Restringido'!$A$5:$A$6,A5,'08_Restringido'!$I$5:$I$6)-SUMIF('09_Equivalentes'!$A$5:$A$6,A5,'09_Equivalentes'!$I$5:$I$6) | C26: Al saldo ajustado de libros le resta lo que se reclasifica por restricción (hoja 08, Efectivo restringido) y por inversiones que no son equivalentes (hoja 09) para esta cuenta. | D26: Fila 1: 500,00-SUMIF([«Cuenta» de «Efectivo restringido», 2 filas]; «1.1.01.01»; [«Reclasificación propuesta» de «Efectivo restringido», 2 filas])-SUMIF([«Cuenta» de «Equivalentes de efectivo (definición)», 2 filas]; «1.1.01.01»; [«Reclasificación propuesta» de «Equivalentes de efectivo (definición)», 2 filas]) → 500,00 | E26: «Saldo ajustado de libros» (esta hoja), «Cuenta» (esta hoja), hoja «Efectivo restringido», hoja «Equivalentes de efectivo (definición)» | F26: —

Sheet 04_Partidas
A1: Partidas conciliatorias | H1: ⟵ Inicio | I1: ◀ Anterior | J1: Siguiente ▶
A2: Efectivo y equivalentes de efectivo · Cliente de muestra S.A. · corte 2025-12-31
A4: Partida | B4: Cuenta | C4: Tipo | D4: Referencia | E4: Fecha de origen | F4: Importe | G4: Liquidación posterior | H4: Días al corte | I4: Días hasta la liquidación | J4: Antigua | K4: Depurada | L4: Cuenta en el anexo
A5: P-01 | B5: 1.1.02.01 | C5: Depósito en tránsito | D5: Depósito cobranza clientes | E5: 46021 | F5: 8500 | G5: 46024 | H5: =IF(E5="","",'02_Parametros'!$B$5-E5) | I5: =IF(OR(G5="",E5=""),"",G5-E5) | J5: =IF(H5="","No",IF(H5>'02_Parametros'!$B$6,"Sí","No")) | K5: =IF(G5="","No","Sí") | L5: =IF(COUNTIF('03_Conciliacion'!$A$5:$A$13,B5)>0,"Sí","No")
A6: P-02 | B6: 1.1.02.01 | C6: Cheque pendiente | D6: Cheque 1520 proveedor | E6: 46019 | F6: 12000 | G6: 46027 | H6: =IF(E6="","",'02_Parametros'!$B$5-E6) | I6: =IF(OR(G6="",E6=""),"",G6-E6) | J6: =IF(H6="","No",IF(H6>'02_Parametros'!$B$6,"Sí","No")) | K6: =IF(G6="","No","Sí") | L6: =IF(COUNTIF('03_Conciliacion'!$A$5:$A$13,B6)>0,"Sí","No")
A7: P-03 | B7: 1.1.02.01 | C7: Cheque pendiente | D7: Cheque 1311 anulado sin reversar | E7: 45884 | F7: 1850 | H7: =IF(E7="","",'02_Parametros'!$B$5-E7) | I7: =IF(OR(G7="",E7=""),"",G7-E7) | J7: =IF(H7="","No",IF(H7>'02_Parametros'!$B$6,"Sí","No")) | K7: =IF(G7="","No","Sí") | L7: =IF(COUNTIF('03_Conciliacion'!$A$5:$A$13,B7)>0,"Sí","No")
A8: P-04 | B8: 1.1.02.01 | C8: Nota de débito | D8: Comisiones bancarias diciembre | E8: 46022 | F8: 120 | G8: 46032 | H8: =IF(E8="","",'02_Parametros'!$B$5-E8) | I8: =IF(OR(G8="",E8=""),"",G8-E8) | J8: =IF(H8="","No",IF(H8>'02_Parametros'!$B$6,"Sí","No")) | K8: =IF(G8="","No","Sí") | L8: =IF(COUNTIF('03_Conciliacion'!$A$5:$A$13,B8)>0,"Sí","No")
A9: P-05 | B9: 1.1.02.01 | C9: Nota de crédito | D9: Intereses ganados diciembre | E9: 46022 | F9: 300 | G9: 46032 | H9: =IF(E9="","",'02_Parametros'!$B$5-E9) | I9: =IF(OR(G9="",E9=""),"",G9-E9) | J9: =IF(H9="","No",IF(H9>'02_Parametros'!$B$6,"Sí","No")) | K9: =IF(G9="","No","Sí") | L9: =IF(COUNTIF('03_Conciliacion'!$A$5:$A$13,B9)>0,"Sí","No")
A10: P-06 | B10: 1.1.02.02 | C10: Depósito en tránsito | D10: Depósito en efectivo | E10: 46022 | F10: 2100 | G10: 46034 | H10: =IF(E10="","",'02_Parametros'!$B$5-E10) | I10: =IF(OR(G10="",E10=""),"",G10-E10) | J10: =IF(H10="","No",IF(H10>'02_Parametros'!$B$6,"Sí","No")) | K10: =IF(G10="","No","Sí") | L10: =IF(COUNTIF('03_Conciliacion'!$A$5:$A$13,B10)>0,"Sí","No")
A11: P-07 | B11: 1.1.02.02 | C11: Cheque pendiente | D11: Cheque 0870 | E11: 46011 | F11: 300 | G11: 46025 | H11: =IF(E11="","",'02_Parametros'!$B$5-E11) | I11: =IF(OR(G11="",E11=""),"",G11-E11) | J11: =IF(H11="","No",IF(H11>'02_Parametros'!$B$6,"Sí","No")) | K11: =IF(G11="","No","Sí") | L11: =IF(COUNTIF('03_Conciliacion'!$A$5:$A$13,B11)>0,"Sí","No")
A12: P-08 | B12: 1.1.02.02 | C12: Cheque pendiente | D12: Cheque 0876 fechado en enero | E12: 46024 | F12: 550 | G12: 46028 | H12: =IF(E12="","",'02_Parametros'!$B$5-E12) | I12: =IF(OR(G12="",E12=""),"",G12-E12) | J12: =IF(H12="","No",IF(H12>'02_Parametros'!$B$6,"Sí","No")) | K12: =IF(G12="","No","Sí") | L12: =IF(COUNTIF('03_Conciliacion'!$A$5:$A$13,B12)>0,"Sí","No")
A13: P-09 | B13: 1.1.02.04 | C13: Depósito en tránsito | D13: Depósito no acreditado | E13: 45910 | F13: 450 | H13: =IF(E13="","",'02_Parametros'!$B$5-E13) | I13: =IF(OR(G13="",E13=""),"",G13-E13) | J13: =IF(H13="","No",IF(H13>'02_Parametros'!$B$6,"Sí","No")) | K13: =IF(G13="","No","Sí") | L13: =IF(COUNTIF('03_Conciliacion'!$A$5:$A$13,B13)>0,"Sí","No")
A14: TOTAL | F14: =SUM(F5:F13)
A16: ⓘ Cómo se calcula esta hoja
A17: Columna | B17: Fórmula (Excel) | C17: Cómo se calcula (sencillo) | D17: Ejemplo con números reales | E17: De dónde viene | F17: Norma
A18: Días al corte | B18: '=IF(E5="","",'02_Parametros'!$B$5-E5) | C18: Resta la fecha de origen de la partida de la fecha de corte de la hoja 02 (Parámetros). Negativo significa que se originó después del corte; sin fecha de origen, queda en blanco. | D18: Fila 1: IF(«2025-12-30»=""; ""; «2025-12-31»-«2025-12-30») → 1 | E18: «Fecha de origen» (esta hoja), hoja «Parámetros» | F18: —
A19: Días hasta la liquidación | B19: '=IF(OR(G5="",E5=""),"",G5-E5) | C19: Cuenta los días entre la fecha de origen y la liquidación posterior de la partida; si falta cualquiera de las dos fechas, queda en blanco. | D19: Fila 1: IF(OR(«2026-01-02»=""; «2025-12-30»=""); ""; «2026-01-02»-«2025-12-30») → 3 | E19: «Liquidación posterior» (esta hoja), «Fecha de origen» (esta hoja) | F19: —
A20: Antigua | B20: '=IF(H5="","No",IF(H5>'02_Parametros'!$B$6,"Sí","No")) | C20: Marca «Sí» si los días al corte superan el umbral de antigüedad de la hoja 02 (Parámetros); sin días al corte, o dentro del umbral, marca «No». | D20: Fila 1: IF(1=""; "No"; IF(1>90,00; "Sí"; "No")) → No | E20: «Días al corte» (esta hoja), hoja «Parámetros» | F20: —
A21: Depurada | B21: '=IF(G5="","No","Sí") | C21: Marca «Sí» si la partida tiene fecha de liquidación posterior al corte y «No» si todavía no se ha liquidado. | D21: Fila 1: IF(«2026-01-02»=""; "No"; "Sí") → Sí | E21: «Liquidación posterior» (esta hoja) | F21: —
A22: Cuenta en el anexo | B22: '=IF(COUNTIF('03_Conciliacion'!$A$5:$A$13,B5)>0,"Sí","No") | C22: Marca «Sí» si la cuenta de la partida figura en la hoja 03 (Conciliación bancaria por cuenta) y «No» si no está en el anexo de cuentas. | D22: Fila 1: IF(COUNTIF([«Cuenta» de «Conciliación bancaria por cuenta», 9 filas]; «1.1.02.01»)>0; "Sí"; "No") → Sí | E22: «Cuenta» (esta hoja), hoja «Conciliación bancaria por cuenta» | F22: —

Sheet 05_Antiguedad
A1: Antigüedad de partidas | H1: ⟵ Inicio | I1: ◀ Anterior | J1: Siguiente ▶
A2: Efectivo y equivalentes de efectivo · Cliente de muestra S.A. · corte 2025-12-31
A4: Tramo (días al corte) | B4: Partidas | C4: Importe | D4: No depurado
A5: Posterior al corte | B5: =COUNTIFS('04_Partidas'!$H$5:$H$13,"<0") | C5: =SUMIFS('04_Partidas'!$F$5:$F$13,'04_Partidas'!$H$5:$H$13,"<0") | D5: =SUMIFS('04_Partidas'!$F$5:$F$13,'04_Partidas'!$H$5:$H$13,"<0",'04_Partidas'!$K$5:$K$13,"No")
A6: 0 a 30 días | B6: =COUNTIFS('04_Partidas'!$H$5:$H$13,">=0",'04_Partidas'!$H$5:$H$13,"<=30") | C6: =SUMIFS('04_Partidas'!$F$5:$F$13,'04_Partidas'!$H$5:$H$13,">=0",'04_Partidas'!$H$5:$H$13,"<=30") | D6: =SUMIFS('04_Partidas'!$F$5:$F$13,'04_Partidas'!$H$5:$H$13,">=0",'04_Partidas'!$H$5:$H$13,"<=30",'04_Partidas'!$K$5:$K$13,"No")
A7: 31 a 60 días | B7: =COUNTIFS('04_Partidas'!$H$5:$H$13,">=31",'04_Partidas'!$H$5:$H$13,"<=60") | C7: =SUMIFS('04_Partidas'!$F$5:$F$13,'04_Partidas'!$H$5:$H$13,">=31",'04_Partidas'!$H$5:$H$13,"<=60") | D7: =SUMIFS('04_Partidas'!$F$5:$F$13,'04_Partidas'!$H$5:$H$13,">=31",'04_Partidas'!$H$5:$H$13,"<=60",'04_Partidas'!$K$5:$K$13,"No")
A8: 61 a 90 días | B8: =COUNTIFS('04_Partidas'!$H$5:$H$13,">=61",'04_Partidas'!$H$5:$H$13,"<=90") | C8: =SUMIFS('04_Partidas'!$F$5:$F$13,'04_Partidas'!$H$5:$H$13,">=61",'04_Partidas'!$H$5:$H$13,"<=90") | D8: =SUMIFS('04_Partidas'!$F$5:$F$13,'04_Partidas'!$H$5:$H$13,">=61",'04_Partidas'!$H$5:$H$13,"<=90",'04_Partidas'!$K$5:$K$13,"No")
A9: 91 a 180 días | B9: =COUNTIFS('04_Partidas'!$H$5:$H$13,">=91",'04_Partidas'!$H$5:$H$13,"<=180") | C9: =SUMIFS('04_Partidas'!$F$5:$F$13,'04_Partidas'!$H$5:$H$13,">=91",'04_Partidas'!$H$5:$H$13,"<=180") | D9: =SUMIFS('04_Partidas'!$F$5:$F$13,'04_Partidas'!$H$5:$H$13,">=91",'04_Partidas'!$H$5:$H$13,"<=180",'04_Partidas'!$K$5:$K$13,"No")
A10: Más de 180 días | B10: =COUNTIFS('04_Partidas'!$H$5:$H$13,">180") | C10: =SUMIFS('04_Partidas'!$F$5:$F$13,'04_Partidas'!$H$5:$H$13,">180") | D10: =SUMIFS('04_Partidas'!$F$5:$F$13,'04_Partidas'!$H$5:$H$13,">180",'04_Partidas'!$K$5:$K$13,"No")
A11: TOTAL | B11: =SUM(B5:B10) | C11: =SUM(C5:C10) | D11: =SUM(D5:D10)
A13: ⓘ Cómo se calcula esta hoja
A14: Columna | B14: Fórmula (Excel) | C14: Cómo se calcula (sencillo) | D14: Ejemplo con números reales | E14: De dónde viene | F14: Norma
A15: Partidas | B15: '=COUNTIFS('04_Partidas'!$H$5:$H$13,"<0") | C15: Cuenta cuántas partidas de la hoja 04 (Partidas conciliatorias) tienen días al corte dentro de este tramo; «Posterior al corte» son las de días negativos. | D15: Fila 1: COUNTIFS([«Días al corte» de «Partidas conciliatorias», 9 filas]; "<0") → 1 | E15: hoja «Partidas conciliatorias» | F15: —
A16: Importe | B16: '=SUMIFS('04_Partidas'!$F$5:$F$13,'04_Partidas'!$H$5:$H$13,"<0") | C16: Suma el importe de las partidas de la hoja 04 (Partidas conciliatorias) cuyos días al corte caen en este tramo. | D16: Fila 1: SUMIFS([«Importe» de «Partidas conciliatorias», 9 filas]; [«Días al corte» de «Partidas conciliatorias», 9 filas]; "<0") → 550,00 | E16: hoja «Partidas conciliatorias» | F16: —
A17: No depurado | B17: '=SUMIFS('04_Partidas'!$F$5:$F$13,'04_Partidas'!$H$5:$H$13,"<0",'04_Partidas'!$K$5:$K$13,"No") | C17: Suma solo el importe de las partidas de este tramo que en la hoja 04 siguen marcadas como no depuradas (sin liquidación posterior). | D17: Fila 1: SUMIFS([«Importe» de «Partidas conciliatorias», 9 filas]; [«Días al corte» de «Partidas conciliatorias», 9 filas]; "<0"; [«Depurada» de «Partidas conciliatorias», 9 filas]; "No") → 0,00 | E17: hoja «Partidas conciliatorias» | F17: —

Sheet 06_Confirmaciones
A1: Confirmación bancaria | H1: ⟵ Inicio | I1: ◀ Anterior | J1: Siguiente ▶
A2: Efectivo y equivalentes de efectivo · Cliente de muestra S.A. · corte 2025-12-31
A4: Cuenta | B4: Banco | C4: Saldo según estado bancario | D4: Saldo confirmado por el banco | E4: Diferencia (confirmado − estado) | F4: Resultado
A5: 1.1.02.01 | B5: Banco Pichincha Cte. ***4521 | C5: =IF('03_Conciliacion'!D7="","",'03_Conciliacion'!D7) | D5: 131210.5 | E5: =IF(OR(C5="",D5=""),"",ROUND(D5-C5,2)) | F5: =IF(D5="","Sin respuesta: procedimiento alternativo",IF(E5="","Sin estado bancario",IF(ABS(E5)<='02_Parametros'!$B$10,"Coincide","No coincide")))
A6: 1.1.02.02 | B6: Banco Guayaquil Aho. ***7788 | C6: =IF('03_Conciliacion'!D8="","",'03_Conciliacion'!D8) | D6: 45900 | E6: =IF(OR(C6="",D6=""),"",ROUND(D6-C6,2)) | F6: =IF(D6="","Sin respuesta: procedimiento alternativo",IF(E6="","Sin estado bancario",IF(ABS(E6)<='02_Parametros'!$B$10,"Coincide","No coincide")))
A7: 1.1.02.03 | B7: Produbanco Cte. ***3390 | C7: =IF('03_Conciliacion'!D9="","",'03_Conciliacion'!D9) | D7: 21500 | E7: =IF(OR(C7="",D7=""),"",ROUND(D7-C7,2)) | F7: =IF(D7="","Sin respuesta: procedimiento alternativo",IF(E7="","Sin estado bancario",IF(ABS(E7)<='02_Parametros'!$B$10,"Coincide","No coincide")))
A8: 1.1.02.04 | B8: Banco Internacional Cte. ***1102 | C8: =IF('03_Conciliacion'!D10="","",'03_Conciliacion'!D10) | E8: =IF(OR(C8="",D8=""),"",ROUND(D8-C8,2)) | F8: =IF(D8="","Sin respuesta: procedimiento alternativo",IF(E8="","Sin estado bancario",IF(ABS(E8)<='02_Parametros'!$B$10,"Coincide","No coincide")))
A9: 1.1.02.05 | B9: Banco Bolivariano Cte. ***5566 | C9: =IF('03_Conciliacion'!D11="","",'03_Conciliacion'!D11) | D9: -3200 | E9: =IF(OR(C9="",D9=""),"",ROUND(D9-C9,2)) | F9: =IF(D9="","Sin respuesta: procedimiento alternativo",IF(E9="","Sin estado bancario",IF(ABS(E9)<='02_Parametros'!$B$10,"Coincide","No coincide")))
A10: 1.1.03.01 | B10: Póliza de acumulación Pichincha 60 días | C10: =IF('03_Conciliacion'!D12="","",'03_Conciliacion'!D12) | D10: 50000 | E10: =IF(OR(C10="",D10=""),"",ROUND(D10-C10,2)) | F10: =IF(D10="","Sin respuesta: procedimiento alternativo",IF(E10="","Sin estado bancario",IF(ABS(E10)<='02_Parametros'!$B$10,"Coincide","No coincide")))
A11: 1.1.03.02 | B11: Certificado de depósito Produbanco 180 días | C11: =IF('03_Conciliacion'!D13="","",'03_Conciliacion'!D13) | D11: 30000 | E11: =IF(OR(C11="",D11=""),"",ROUND(D11-C11,2)) | F11: =IF(D11="","Sin respuesta: procedimiento alternativo",IF(E11="","Sin estado bancario",IF(ABS(E11)<='02_Parametros'!$B$10,"Coincide","No coincide")))
A13: ⓘ Cómo se calcula esta hoja
A14: Columna | B14: Fórmula (Excel) | C14: Cómo se calcula (sencillo) | D14: Ejemplo con números reales | E14: De dónde viene | F14: Norma
A15: Saldo según estado bancario | B15: '=IF('03_Conciliacion'!D7="","",'03_Conciliacion'!D7) | C15: Trae el saldo del estado bancario de la misma cuenta desde la hoja 03 (Conciliación bancaria por cuenta); si no hay, queda en blanco. | D15: Fila 1: IF(131.210,50=""; ""; 131.210,50) → 131.210,50 | E15: hoja «Conciliación bancaria por cuenta» | F15: —
A16: Diferencia (confirmado − estado) | B16: '=IF(OR(C5="",D5=""),"",ROUND(D5-C5,2)) | C16: Resta al saldo que confirmó el banco el saldo del estado bancario, redondeado a centavos; si falta cualquiera de los dos, queda en blanco. | D16: Fila 1: IF(OR(131.210,50=""; 131.210,50=""); ""; ROUND(131.210,50-131.210,50; 2)) → 0,00 | E16: «Saldo según estado bancario» (esta hoja), «Saldo confirmado por el banco» (esta hoja) | F16: —
A17: Resultado | B17: '=IF(D5="","Sin respuesta: procedimiento alternativo",IF(E5="","Sin estado bancario",IF(ABS(E5)<='02_Parametros'!$B$10,"Coincide","No coincide"))) | C17: Sin respuesta del banco indica aplicar un procedimiento alternativo; sin estado bancario lo avisa; si la diferencia está dentro de la tolerancia de la hoja 02 (Parámetros) dice «Coincide» y, si no, «No coincide». | D17: Fila 1: IF(131.210,50=""; "Sin respuesta: procedimiento alternativo"; IF(0,00=""; "Sin estado bancario"; IF(ABS(0,00)<=0,00; "Coincide"; "No coincide"))) → Coincide | E17: «Saldo confirmado por el banco» (esta hoja), «Diferencia (confirmado − estado)» (esta hoja), hoja «Parámetros» | F17: —

Sheet 07_Corte
A1: Prueba de corte | H1: ⟵ Inicio | I1: ◀ Anterior | J1: Siguiente ▶
A2: Efectivo y equivalentes de efectivo · Cliente de muestra S.A. · corte 2025-12-31
A4: Partida | B4: Cuenta | C4: Tipo | D4: Fecha en libros | E4: Fecha en el banco | F4: Días después del corte | G4: Resultado | H4: Importe
A5: P-01 | B5: 1.1.02.01 | C5: Depósito en tránsito | D5: 46021 | E5: 46024 | F5: =IF(E5="","",E5-'02_Parametros'!$B$5) | G5: =IF(AND(D5<>"",D5>'02_Parametros'!$B$5),"Registrada después del corte",IF(E5="","Sin liquidación posterior",IF(AND(C5="Depósito en tránsito",F5>'02_Parametros'!$B$7),"Depósito acreditado tarde","Correcto"))) | H5: ='04_Partidas'!F5
A6: P-02 | B6: 1.1.02.01 | C6: Cheque pendiente | D6: 46019 | E6: 46027 | F6: =IF(E6="","",E6-'02_Parametros'!$B$5) | G6: =IF(AND(D6<>"",D6>'02_Parametros'!$B$5),"Registrada después del corte",IF(E6="","Sin liquidación posterior",IF(AND(C6="Depósito en tránsito",F6>'02_Parametros'!$B$7),"Depósito acreditado tarde","Correcto"))) | H6: ='04_Partidas'!F6
A7: P-03 | B7: 1.1.02.01 | C7: Cheque pendiente | D7: 45884 | F7: =IF(E7="","",E7-'02_Parametros'!$B$5) | G7: =IF(AND(D7<>"",D7>'02_Parametros'!$B$5),"Registrada después del corte",IF(E7="","Sin liquidación posterior",IF(AND(C7="Depósito en tránsito",F7>'02_Parametros'!$B$7),"Depósito acreditado tarde","Correcto"))) | H7: ='04_Partidas'!F7
A8: P-06 | B8: 1.1.02.02 | C8: Depósito en tránsito | D8: 46022 | E8: 46034 | F8: =IF(E8="","",E8-'02_Parametros'!$B$5) | G8: =IF(AND(D8<>"",D8>'02_Parametros'!$B$5),"Registrada después del corte",IF(E8="","Sin liquidación posterior",IF(AND(C8="Depósito en tránsito",F8>'02_Parametros'!$B$7),"Depósito acreditado tarde","Correcto"))) | H8: ='04_Partidas'!F10
A9: P-07 | B9: 1.1.02.02 | C9: Cheque pendiente | D9: 46011 | E9: 46025 | F9: =IF(E9="","",E9-'02_Parametros'!$B$5) | G9: =IF(AND(D9<>"",D9>'02_Parametros'!$B$5),"Registrada después del corte",IF(E9="","Sin liquidación posterior",IF(AND(C9="Depósito en tránsito",F9>'02_Parametros'!$B$7),"Depósito acreditado tarde","Correcto"))) | H9: ='04_Partidas'!F11
A10: P-08 | B10: 1.1.02.02 | C10: Cheque pendiente | D10: 46024 | E10: 46028 | F10: =IF(E10="","",E10-'02_Parametros'!$B$5) | G10: =IF(AND(D10<>"",D10>'02_Parametros'!$B$5),"Registrada después del corte",IF(E10="","Sin liquidación posterior",IF(AND(C10="Depósito en tránsito",F10>'02_Parametros'!$B$7),"Depósito acreditado tarde","Correcto"))) | H10: ='04_Partidas'!F12
A11: P-09 | B11: 1.1.02.04 | C11: Depósito en tránsito | D11: 45910 | F11: =IF(E11="","",E11-'02_Parametros'!$B$5) | G11: =IF(AND(D11<>"",D11>'02_Parametros'!$B$5),"Registrada después del corte",IF(E11="","Sin liquidación posterior",IF(AND(C11="Depósito en tránsito",F11>'02_Parametros'!$B$7),"Depósito acreditado tarde","Correcto"))) | H11: ='04_Partidas'!F13
A12: TOTAL | H12: =SUM(H5:H11)
A14: ⓘ Cómo se calcula esta hoja
A15: Columna | B15: Fórmula (Excel) | C15: Cómo se calcula (sencillo) | D15: Ejemplo con números reales | E15: De dónde viene | F15: Norma
A16: Días después del corte | B16: '=IF(E5="","",E5-'02_Parametros'!$B$5) | C16: Resta la fecha de corte de la hoja 02 (Parámetros) de la fecha en que el banco registró la partida; sin fecha en el banco, queda en blanco. | D16: Fila 1: IF(«2026-01-02»=""; ""; «2026-01-02»-«2025-12-31») → 2 | E16: «Fecha en el banco» (esta hoja), hoja «Parámetros» | F16: —
A17: Resultado | B17: '=IF(AND(D5<>"",D5>'02_Parametros'!$B$5),"Registrada después del corte",IF(E5="","Sin liquidación posterior",IF(AND(C5="Depósito en tránsito",F5>'02_Parametros'!$B$7),"Depósito acreditado tarde","Correcto"))) | C17: Si la partida se registró en libros después del corte lo marca; si el banco no la registró después, dice «Sin liquidación posterior»; un depósito en tránsito acreditado después de los días permitidos en la hoja 02 es «Depósito acreditado tarde»; lo demás es «Correcto». | D17: Fila 1: IF(AND(«2025-12-30»<>""; «2025-12-30»>«2025-12-31»); "Registrada después del corte"; IF(«2026-01-02»=""; "Sin liquidación posterior"; IF(AND(«Depósito en tránsito»="Depósito en tránsito"; 2>5,00); "Depósito acreditado tarde"; "Correcto"))) → Correcto | E17: «Fecha en libros» (esta hoja), «Fecha en el banco» (esta hoja), «Tipo» (esta hoja), «Días después del corte» (esta hoja), hoja «Parámetros» | F17: —
A18: Importe | B18: '='04_Partidas'!F5 | C18: Trae el importe de la misma partida desde la hoja 04 (Partidas conciliatorias). | D18: Fila 1: 8.500,00 → 8.500,00 | E18: hoja «Partidas conciliatorias» | F18: —

Sheet 08_Restringido
A1: Efectivo restringido | H1: ⟵ Inicio | I1: ◀ Anterior | J1: Siguiente ▶
A2: Efectivo y equivalentes de efectivo · Cliente de muestra S.A. · corte 2025-12-31
A4: Cuenta | B4: Banco | C4: Saldo ajustado | D4: Monto restringido | E4: Motivo | F4: Fin de la restricción | G4: Clasificación | H4: Ya presentado aparte | I4: Reclasificación propuesta
A5: 1.1.02.02 | B5: Banco Guayaquil Aho. ***7788 | C5: ='03_Conciliacion'!M8 | D5: 10000 | E5: Garantía de préstamo (pignoración) | F5: 46568 | G5: =IF(F5="","Sin fecha de fin: revisar el soporte",IF(F5>=EDATE('02_Parametros'!$B$5,'02_Parametros'!$B$9),"No corriente","Corriente")) | H5: No | I5: =IF(OR(H5="Sí",G5<>"No corriente"),0,IF(D5="","",D5))
A6: 1.1.02.04 | B6: Banco Internacional Cte. ***1102 | C6: ='03_Conciliacion'!M10 | D6: 1650 | E6: Embargo judicial | G6: =IF(F6="","Sin fecha de fin: revisar el soporte",IF(F6>=EDATE('02_Parametros'!$B$5,'02_Parametros'!$B$9),"No corriente","Corriente")) | H6: No | I6: =IF(OR(H6="Sí",G6<>"No corriente"),0,IF(D6="","",D6))
A7: TOTAL | I7: =SUM(I5:I6)
A9: ⓘ Cómo se calcula esta hoja
A10: Columna | B10: Fórmula (Excel) | C10: Cómo se calcula (sencillo) | D10: Ejemplo con números reales | E10: De dónde viene | F10: Norma
A11: Saldo ajustado | B11: '='03_Conciliacion'!M8 | C11: Trae el saldo ajustado de libros de la misma cuenta desde la hoja 03 (Conciliación bancaria por cuenta). | D11: Fila 1: 47.700,00 → 47.700,00 | E11: hoja «Conciliación bancaria por cuenta» | F11: —
A12: Clasificación | B12: '=IF(F5="","Sin fecha de fin: revisar el soporte",IF(F5>=EDATE('02_Parametros'!$B$5,'02_Parametros'!$B$9),"No corriente","Corriente")) | C12: Sin fecha de fin pide revisar el soporte; si la restricción termina en la fecha límite (corte más los meses de la hoja 02, Parámetros) o después, es «No corriente»; si termina antes, «Corriente». | D12: Fila 1: IF(«2027-06-30»=""; "Sin fecha de fin: revisar el soporte"; IF(«2027-06-30»>=EDATE(«2025-12-31»; 12,00); "No corriente"; "Corriente")) → No corriente | E12: «Fin de la restricción» (esta hoja), hoja «Parámetros» | F12: —
A13: Reclasificación propuesta | B13: '=IF(OR(H5="Sí",G5<>"No corriente"),0,IF(D5="","",D5)) | C13: Propone reclasificar el monto restringido solo si es no corriente y todavía no se presenta aparte; en los demás casos es cero. | D13: Fila 1: IF(OR(«No»="Sí"; «No corriente»<>"No corriente"); 0; IF(10.000,00=""; ""; 10.000,00)) → 10.000,00 | E13: «Ya presentado aparte» (esta hoja), «Clasificación» (esta hoja), «Monto restringido» (esta hoja) | F13: —

Sheet 09_Equivalentes
A1: Equivalentes de efectivo (definición) | H1: ⟵ Inicio | I1: ◀ Anterior | J1: Siguiente ▶
A2: Efectivo y equivalentes de efectivo · Cliente de muestra S.A. · corte 2025-12-31
A4: Cuenta | B4: Instrumento | C4: Adquisición | D4: Vencimiento | E4: Plazo original (días) | F4: Vence en tres meses o menos (presunción) | G4: Saldo ajustado | H4: Ya reclasificado por restricción | I4: Reclasificación propuesta
A5: 1.1.03.01 | B5: Póliza de acumulación Pichincha 60 días | C5: 45976 | D5: 46036 | E5: =IF(OR(C5="",D5=""),"",D5-C5) | F5: =IF(OR(C5="",D5=""),"Sin fechas: revisar el soporte",IF(D5<=EDATE(C5,'02_Parametros'!$B$8),"Sí","No")) | G5: ='03_Conciliacion'!M12 | H5: =SUMIF('08_Restringido'!$A$5:$A$6,A5,'08_Restringido'!$I$5:$I$6) | I5: =IF(F5="No",MAX(G5-H5,0),0)
A6: 1.1.03.02 | B6: Certificado de depósito Produbanco 180 días | C6: 45931 | D6: 46111 | E6: =IF(OR(C6="",D6=""),"",D6-C6) | F6: =IF(OR(C6="",D6=""),"Sin fechas: revisar el soporte",IF(D6<=EDATE(C6,'02_Parametros'!$B$8),"Sí","No")) | G6: ='03_Conciliacion'!M13 | H6: =SUMIF('08_Restringido'!$A$5:$A$6,A6,'08_Restringido'!$I$5:$I$6) | I6: =IF(F6="No",MAX(G6-H6,0),0)
A7: TOTAL | G7: =SUM(G5:G6) | I7: =SUM(I5:I6)
A9: ⓘ Cómo se calcula esta hoja
A10: Columna | B10: Fórmula (Excel) | C10: Cómo se calcula (sencillo) | D10: Ejemplo con números reales | E10: De dónde viene | F10: Norma
A11: Plazo original (días) | B11: '=IF(OR(C5="",D5=""),"",D5-C5) | C11: Cuenta los días entre la adquisición y el vencimiento de la inversión; si falta alguna de las dos fechas, queda en blanco. | D11: Fila 1: IF(OR(«2025-11-15»=""; «2026-01-14»=""); ""; «2026-01-14»-«2025-11-15») → 60 | E11: «Adquisición» (esta hoja), «Vencimiento» (esta hoja) | F11: —
A12: Vence en tres meses o menos (presunción) | B12: '=IF(OR(C5="",D5=""),"Sin fechas: revisar el soporte",IF(D5<=EDATE(C5,'02_Parametros'!$B$8),"Sí","No")) | C12: Marca «Sí» si el vencimiento no pasa de los meses de la hoja 02 (Parámetros) contados desde la adquisición y «No» si pasa; sin fechas, pide revisar el soporte. | D12: Fila 1: IF(OR(«2025-11-15»=""; «2026-01-14»=""); "Sin fechas: revisar el soporte"; IF(«2026-01-14»<=EDATE(«2025-11-15»; 3,00); "Sí"; "No")) → Sí | E12: «Adquisición» (esta hoja), «Vencimiento» (esta hoja), hoja «Parámetros» | F12: —
A13: Saldo ajustado | B13: '='03_Conciliacion'!M12 | C13: Trae el saldo ajustado de libros de la misma inversión desde la hoja 03 (Conciliación bancaria por cuenta). | D13: Fila 1: 50.000,00 → 50.000,00 | E13: hoja «Conciliación bancaria por cuenta» | F13: —
A14: Ya reclasificado por restricción | B14: '=SUMIF('08_Restringido'!$A$5:$A$6,A5,'08_Restringido'!$I$5:$I$6) | C14: Suma lo que la hoja 08 (Efectivo restringido) ya propone reclasificar para esta misma cuenta, para no reclasificarlo dos veces. | D14: Fila 1: SUMIF([«Cuenta» de «Efectivo restringido», 2 filas]; «1.1.03.01»; [«Reclasificación propuesta» de «Efectivo restringido», 2 filas]) → 0,00 | E14: «Cuenta» (esta hoja), hoja «Efectivo restringido» | F14: —
A15: Reclasificación propuesta | B15: '=IF(F5="No",MAX(G5-H5,0),0) | C15: Si la inversión no vence dentro del plazo, propone reclasificar su saldo ajustado menos lo ya reclasificado por restricción (nunca negativo); si califica, es cero. | D15: Fila 1: IF(«Sí»="No"; MAX(50.000,00-0,00; 0); 0) → 0,00 | E15: «Vence en tres meses o menos (presunción)» (esta hoja), «Saldo ajustado» (esta hoja), «Ya reclasificado por restricción» (esta hoja) | F15: —

Sheet 10_Efectivo_auditado
A1: Efectivo auditado y ajuste | H1: ⟵ Inicio | I1: ◀ Anterior | J1: Siguiente ▶
A2: Efectivo y equivalentes de efectivo · Cliente de muestra S.A. · corte 2025-12-31
A4: Concepto | B4: Importe
A5: Efectivo y equivalentes según libros | B5: =SUM('03_Conciliacion'!$K$5:$K$13)
A6: Notas de crédito no registradas en libros | B6: =SUM('03_Conciliacion'!$G$5:$G$13)
A7: Notas de débito no registradas en libros | B7: =SUM('03_Conciliacion'!$H$5:$H$13)
A8: Ajuste por notas bancarias (crédito − débito) | B8: ='10_Efectivo_auditado'!$B$6-'10_Efectivo_auditado'!$B$7
A9: (−) Reclasificación a no corriente (restricción ≥ 12 meses) (NIC 7.48 y NIC 1.66 d)) | B9: =SUM('08_Restringido'!$I$5:$I$6)
A10: de lo cual, no corriente | B10: =SUMIF('08_Restringido'!$G$5:$G$6,"No corriente",'08_Restringido'!$I$5:$I$6)
A11: (−) Inversiones que no cumplen el plazo de tres meses (NIC 7.6–7.7) | B11: =SUM('09_Equivalentes'!$I$5:$I$6)
A12: Efectivo y equivalentes auditado | B12: ='10_Efectivo_auditado'!$B$5+'10_Efectivo_auditado'!$B$8-'10_Efectivo_auditado'!$B$9-'10_Efectivo_auditado'!$B$11
A13: Ajuste propuesto (auditado − libros) | B13: ='10_Efectivo_auditado'!$B$12-'10_Efectivo_auditado'!$B$5
A14: Composición (NIC 7.45–7.46): caja | B14: =SUMIF('03_Conciliacion'!$C$5:$C$13,"Caja",'03_Conciliacion'!$N$5:$N$13)
A15: Composición: bancos (incluye sobregiros) | B15: =SUMIF('03_Conciliacion'!$C$5:$C$13,"Banco",'03_Conciliacion'!$N$5:$N$13)
A16: Composición: equivalentes de efectivo | B16: =SUMIF('03_Conciliacion'!$C$5:$C$13,"Inversión",'03_Conciliacion'!$N$5:$N$13)
A17: Diferencias de conciliación no explicadas (absolutas) | B17: =SUMIF('03_Conciliacion'!$L$5:$L$13,">0")-SUMIF('03_Conciliacion'!$L$5:$L$13,"<0")
A18: Diferencias de confirmación (absolutas) | B18: =SUMIF('06_Confirmaciones'!$E$5:$E$11,">0")-SUMIF('06_Confirmaciones'!$E$5:$E$11,"<0")
A19: Partidas conciliatorias antiguas | B19: =SUMIF('04_Partidas'!$J$5:$J$13,"Sí",'04_Partidas'!$F$5:$F$13)
A20: Partidas no depuradas después del corte | B20: =SUMIF('04_Partidas'!$K$5:$K$13,"No",'04_Partidas'!$F$5:$F$13)
A22: ⓘ Cómo se calcula esta hoja
A23: Columna | B23: Fórmula (Excel) | C23: Cómo se calcula (sencillo) | D23: Ejemplo con números reales | E23: De dónde viene | F23: Norma
A24: Importe | B24: '=SUM('03_Conciliacion'!$K$5:$K$13) | C24: Cada concepto tiene su cálculo: libros y notas bancarias se suman de la hoja 03 (Conciliación); las reclasificaciones, de las hojas 08 y 09; el auditado es libros + notas − reclasificaciones y el ajuste, auditado − libros; la composición suma el efectivo auditado por tipo de cuenta; las diferencias y partidas salen de las hojas 03, 04 y 06. | D24: Fila 1: SUM([«Saldo según libros» de «Conciliación bancaria por cuenta», 9 filas]) → 274.630,50 | E24: hoja «Conciliación bancaria por cuenta» | F24: —

Sheet 11_Asientos
A1: Asientos propuestos | H1: ⟵ Inicio | I1: ◀ Anterior | J1: Siguiente ▶
A2: Efectivo y equivalentes de efectivo · Cliente de muestra S.A. · corte 2025-12-31
A4: Asiento | B4: Cuenta | C4: Debe | D4: Haber
A5: 1 · Notas de crédito del banco no registradas | B5: Bancos | C5: ='10_Efectivo_auditado'!$B$6
B6: Otros ingresos (identificar la cuenta con el soporte) | D6: ='10_Efectivo_auditado'!$B$6
A7: 2 · Notas de débito del banco no registradas | B7: Gastos bancarios (identificar la cuenta con el soporte) | C7: ='10_Efectivo_auditado'!$B$7
B8: Bancos | D8: ='10_Efectivo_auditado'!$B$7
A9: 3 · Reclasificación del efectivo restringido a no corriente | B9: Efectivo restringido — activo no corriente | C9: ='10_Efectivo_auditado'!$B$10
B10: Efectivo y equivalentes de efectivo | D10: ='10_Efectivo_auditado'!$B$9
A11: 4 · Reclasificación de inversiones que no son equivalentes | B11: Inversiones a plazo (activos financieros a costo amortizado) | C11: ='10_Efectivo_auditado'!$B$11
B12: Efectivo y equivalentes de efectivo | D12: ='10_Efectivo_auditado'!$B$11
A14: ⓘ Cómo se calcula esta hoja
A15: Columna | B15: Fórmula (Excel) | C15: Cómo se calcula (sencillo) | D15: Ejemplo con números reales | E15: De dónde viene | F15: Norma
A16: Debe | B16: '='10_Efectivo_auditado'!$B$6 | C16: Toma cada importe de la hoja 10 (Efectivo auditado y ajuste): notas de crédito y de débito no registradas y las reclasificaciones por restricción y por inversiones que no son equivalentes. | D16: Fila 1: 300,00 → 300,00 | E16: hoja «Efectivo auditado y ajuste» | F16: —
A17: Haber | B17: '='10_Efectivo_auditado'!$B$6 | C17: Lleva a la contrapartida el mismo importe del asiento, tomado de la hoja 10 (Efectivo auditado y ajuste), para que debe y haber cuadren. | D17: Fila 2: 300,00 → 300,00 | E17: hoja «Efectivo auditado y ajuste» | F17: —

Sheet 12_Problemas
A1: Problemas encontrados | H1: ⟵ Inicio | I1: ◀ Anterior | J1: Siguiente ▶
A2: Efectivo y equivalentes de efectivo · Cliente de muestra S.A. · corte 2025-12-31
A4: Código | B4: Descripción | C4: Importe
A5: DIFERENCIA_NO_EXPLICADA | B5: 1.1.02.02 Banco Guayaquil Aho. ***7788: los libros (47.700,00) difieren en 550,00 del saldo que explica la conciliación (47.150,00). Investigue y evalúe como incorrección (NIA 450). | C5: 550
A6: RESTRINGIDO_REVELAR | B6: 1.1.02.02 Banco Guayaquil Aho. ***7788: 10.000,00 restringidos (Garantía de préstamo (pignoración)). La restricción no los saca del efectivo y equivalentes, pero debe revelarse el importe no disponible junto con un comentario de la gerencia (NIC 7.48). | C6: 10000
A7: RESTRINGIDO_COMO_DISPONIBLE | B7: 1.1.02.02 Banco Guayaquil Aho. ***7788: 10.000,00 restringidos por al menos 12 meses (hasta el 2027-06-30) presentados como efectivo disponible. Reclasificar a no corriente y revelar (NIC 7.48 y NIC 1.66 d)). | C7: 10000
A8: CONFIRMACION_NO_COINCIDE | B8: 1.1.02.03 Produbanco Cte. ***3390: el banco confirma 21.500,00 y el estado bancario muestra 22.000,00. Obtenga explicación del banco y del cliente (NIA 505 párr. 14). | C8: -500
A9: SIN_CONFIRMACION | B9: 1.1.02.04 Banco Internacional Cte. ***1102: sin respuesta del banco; aplique procedimientos alternativos (NIA 505). | C9: 1650
A10: RESTRINGIDO_REVELAR | B10: 1.1.02.04 Banco Internacional Cte. ***1102: 1.650,00 restringidos (Embargo judicial). La restricción no los saca del efectivo y equivalentes, pero debe revelarse el importe no disponible junto con un comentario de la gerencia (NIC 7.48). | C10: 1650
A11: RESTRICCION_SIN_FECHA | B11: 1.1.02.04 Banco Internacional Cte. ***1102: restricción sin fecha de fin; indique hasta cuándo dura para decidir si es corriente o no corriente (NIC 7.48 y NIC 1.66 d)). Mientras tanto no se reclasifica nada. | C11: 1650
A12: SALDO_ACREEDOR | B12: 1.1.02.05 Banco Bolivariano Cte. ***5566: saldo acreedor (sobregiro). Solo integra el efectivo si es exigible a la vista y parte integrante de la gestión del efectivo (NIC 7.8); si no, presentarlo como pasivo financiero. | C12: -3200
A13: EQUIVALENTE_PRESUNCION | B13: 1.1.03.01 Póliza de acumulación Pichincha 60 días: vence dentro de los 3 meses desde la adquisición, lo que es solo una presunción. La definición exige además que sea de gran liquidez, fácilmente convertible en importes determinados de efectivo y sujeto a un riesgo poco significativo de cambios de valor (NIC 7.6–7.7): documéntelo. | C13: 50000
A14: NO_ES_EQUIVALENTE | B14: 1.1.03.02 Certificado de depósito Produbanco 180 días: vence el 2026-03-30, después de los 3 meses desde la adquisición (hasta el 2026-01-01); no es equivalente de efectivo (NIC 7.6–7.7). Reclasificar a inversiones. | C14: 30000
A15: NOTAS_NO_REGISTRADAS | B15: Notas bancarias no registradas en libros: crédito 300,00 y débito 120,00. Ajustar los libros. | C15: 180
A16: PARTIDA_ANTIGUA | B16: P-03 (Cheque pendiente, cuenta 1.1.02.01): 138 días al corte (más de 90). Evalúe su reverso o ajuste. | C16: 1850
... A21: PARTIDA_NO_DEPURADA | B21: P-09 (Depósito en tránsito, cuenta 1.1.02.04): sin liquidación posterior al corte; obtenga soporte de su existencia. | C21: 450

Sheet 13_Conclusion
A1: Conclusión | H1: ⟵ Inicio | I1: ◀ Anterior | J1: Siguiente ▶
A2: Efectivo y equivalentes de efectivo · Cliente de muestra S.A. · corte 2025-12-31
A4: Concepto | B4: Detalle
A5: Conciliación con el mayor | B5: Población None · mayor None · diferencia None
A6: Evaluación de excepciones
A7: Análisis
A8: Conclusión

Sheet 14_Control_Revision
A1: Control de revisión | H1: ⟵ Inicio | I1: ◀ Anterior
A2: Efectivo y equivalentes de efectivo · Cliente de muestra S.A. · corte 2025-12-31
A4: Fecha | B4: Acción | C4: Estado anterior | D4: Estado nuevo | E4: Actor | F4: Comentario
