Workbook

Sheet 00_Inicio
B2: AuditConsulting Auditores Cía. Ltda. · AUDIT-IA
B4: Ingresos · contratos con clientes (existencia, precio, asignación, satisfacción, corte y devoluciones)
B6: Cliente | C6: Cliente de muestra S.A. | D6: RUC | E6: 1790000000001
B7: Marco contable | C7: NIIF completas | D7: Fecha de corte | E7: 2025-12-31
B8: Preparó | C8: Ejercicio modelo | D8: Revisó | E8: Pendiente
B10: INDICADORES CLAVE
B11: Ajuste propuesto a ingresos | C11: Problemas encontrados
B12: -114620 | C12: 21
B15: IR A LA CÉDULA
B16: Carátula | C16: Programa | D16: Base técnica | E16: Resumen
B17: Parámetros | C17: Detalle por obligación | D17: Precio y contraprestación variable | E17: Asignación del precio
B18: Satisfacción y porcentaje de avance | C18: Devoluciones y notas de crédito | D18: Componente de financiación | E18: Ingreso reconocible vs registrado
B19: Activo y pasivo del contrato | C19: Corte de ingresos | D19: Modificaciones de contratos | E19: Conciliación y ajustes
B20: Asientos propuestos | C20: Problemas encontrados | D20: Conclusión | E20: Control de revisión
B22: PANORAMA | N22: Datos de los gráficos (fórmulas a las cédulas)
N23: Cifras del resumen | O23: Importe (USD)
N24: ='01_Resumen'!A5 | O24: ='01_Resumen'!B5
N25: ='01_Resumen'!A6 | O25: ='01_Resumen'!B6
N26: ='01_Resumen'!A7 | O26: ='01_Resumen'!B7
N27: ='01_Resumen'!A8 | O27: ='01_Resumen'!B8
N28: ='01_Resumen'!A9 | O28: ='01_Resumen'!B9
N29: ='01_Resumen'!A10 | O29: ='01_Resumen'!B10
N30: ='01_Resumen'!A11 | O30: ='01_Resumen'!B11
N31: ='01_Resumen'!A12 | O31: ='01_Resumen'!B12
N32: ='01_Resumen'!A13 | O32: ='01_Resumen'!B13
N33: ='01_Resumen'!A14 | O33: ='01_Resumen'!B14
N34: ='01_Resumen'!A15 | O34: ='01_Resumen'!B15
N35: ='01_Resumen'!A16 | O35: ='01_Resumen'!B16
... N43: ='01_Resumen'!A24 | O43: ='01_Resumen'!B24
N45: Hallazgos de mayor impacto | O45: Importe (USD)
N46: Ajuste ingresos | O46: =SUMIFS('15_Problemas'!$C$5:$C$25,'15_Problemas'!$A$5:$A$25,"AJUSTE_INGRESOS",'15_Problemas'!$C$5:$C$25,">0")-SUMIFS('15_Problemas'!$C$5:$C$25,'15_Problemas'!$A$5:$A$25,"AJUSTE_INGRESOS",'15_Problemas'!$C$5:$C$25,"<0")
N47: Pasivo contrato no presentado | O47: =SUMIFS('15_Problemas'!$C$5:$C$25,'15_Problemas'!$A$5:$A$25,"PASIVO_CONTRATO_NO_PRESENTADO",'15_Problemas'!$C$5:$C$25,">0")-SUMIFS('15_Problemas'!$C$5:$C$25,'15_Problemas'!$A$5:$A$25,"PASIVO_CONTRATO_NO_PRESENTADO",'15_Problemas'!$C$5:$C$25,"<0")
N48: Variable sin restriccion (×2) | O48: =SUMIFS('15_Problemas'!$C$5:$C$25,'15_Problemas'!$A$5:$A$25,"VARIABLE_SIN_RESTRICCION",'15_Problemas'!$C$5:$C$25,">0")-SUMIFS('15_Problemas'!$C$5:$C$25,'15_Problemas'!$A$5:$A$25,"VARIABLE_SIN_RESTRICCION",'15_Problemas'!$C$5:$C$25,"<0")
N49: Error corte (×2) | O49: =SUMIFS('15_Problemas'!$C$5:$C$25,'15_Problemas'!$A$5:$A$25,"ERROR_CORTE",'15_Problemas'!$C$5:$C$25,">0")-SUMIFS('15_Problemas'!$C$5:$C$25,'15_Problemas'!$A$5:$A$25,"ERROR_CORTE",'15_Problemas'!$C$5:$C$25,"<0")
N50: Avance mal calculado | O50: =SUMIFS('15_Problemas'!$C$5:$C$25,'15_Problemas'!$A$5:$A$25,"AVANCE_MAL_CALCULADO",'15_Problemas'!$C$5:$C$25,">0")-SUMIFS('15_Problemas'!$C$5:$C$25,'15_Problemas'!$A$5:$A$25,"AVANCE_MAL_CALCULADO",'15_Problemas'!$C$5:$C$25,"<0")
N51: Activo contrato no presentado | O51: =SUMIFS('15_Problemas'!$C$5:$C$25,'15_Problemas'!$A$5:$A$25,"ACTIVO_CONTRATO_NO_PRESENTADO",'15_Problemas'!$C$5:$C$25,">0")-SUMIFS('15_Problemas'!$C$5:$C$25,'15_Problemas'!$A$5:$A$25,"ACTIVO_CONTRATO_NO_PRESENTADO",'15_Problemas'!$C$5:$C$25,"<0")
N52: Financiacion no separada | O52: =SUMIFS('15_Problemas'!$C$5:$C$25,'15_Problemas'!$A$5:$A$25,"FINANCIACION_NO_SEPARADA",'15_Problemas'!$C$5:$C$25,">0")-SUMIFS('15_Problemas'!$C$5:$C$25,'15_Problemas'!$A$5:$A$25,"FINANCIACION_NO_SEPARADA",'15_Problemas'!$C$5:$C$25,"<0")
N53: Otros (7 tipos) | O53: =SUMIF('15_Problemas'!$C$5:$C$25,">0")-SUMIF('15_Problemas'!$C$5:$C$25,"<0")-((SUMIFS('15_Problemas'!$C$5:$C$25,'15_Problemas'!$A$5:$A$25,"AJUSTE_INGRESOS",'15_Problemas'!$C$5:$C$25,">0")-SUMIFS('15_Problemas'!$C$5:$C$25,'15_Problemas'!$A$5:$A$25,"AJUSTE_INGRESOS",'15_Problemas'!$C$5:$C$25,"<0"))+(SUMIFS('15_Problemas'!$C$5:$C$25,'15_Problemas'!$A$5:$A$25,"PASIVO_CONTRATO_NO_PRESENTADO",'15_Problemas'!$C$5:$C$25,">0")-SUMIFS('15_Problemas'!$C$5:$C$25,'15_Problemas'!$A$5:$A$25,"PASIVO_CONTRATO_NO_PRESENTADO",'15_Problemas'!$C$5:$C$25,"<0"))+(SUMIFS('15_Problemas'!$C$5:$C$25,'15_Problemas'!$A$5:$A$25,"VARIABLE_SIN_RESTRICCION",'15_Problemas'!$C$5:$C$25,">0")-SUMIFS('15_Problemas'!$C$5:$C$25,'15_Problemas'!$A$5:$A$25,"VARIABLE_SIN_RESTRICCION",'15_Problemas'!$C$5:$C$25,"<0"))+(SUMIFS('15_Problemas'!$C$5:$C$25,'15_Problemas'!$A$5:$A$25,"ERROR_CORTE",'15_Problemas'!$C$5:$C$25,">0")-SUMIFS('15_Problemas'!$C$5:$C$25,'15_Problemas'!$A$5:$A$25,"ERROR_CORTE",'15_Problemas'!$C$5:$C$25,"<0"))+(SUMIFS('15_Problemas'!$C$5:$C$25,'15_Problemas'!$A$5:$A$25,"AVANCE_MAL_CALCULADO",'15_Problemas'!$C$5:$C$25,">0")-SUMIFS('15_Problemas'!$C$5:$C$25,'15_Problemas'!$A$5:$A$25,"AVANCE_MAL_CALCULADO",'15_Problemas'!$C$5:$C$25,"<0"))+(SUMIFS('15_Problemas'!$C$5:$C$25,'15_Problemas'!$A$5:$A$25,"ACTIVO_CONTRATO_NO_PRESENTADO",'15_Problemas'!$C$5:$C$25,">0")-SUMIFS('15_Problemas'!$C$5:$C$25,'15_Problemas'!$A$5:$A$25,"ACTIVO_CONTRATO_NO_PRESENTADO",'15_Problemas'!$C$5:$C$25,"<0"))+(SUMIFS('15_Problemas'!$C$5:$C$25,'15_Problemas'!$A$5:$A$25,"FINANCIACION_NO_SEPARADA",'15_Problemas'!$C$5:$C$25,">0")-SUMIFS('15_Problemas'!$C$5:$C$25,'15_Problemas'!$A$5:$A$25,"FINANCIACION_NO_SEPARADA",'15_Problemas'!$C$5:$C$25,"<0")))

Sheet 00_Caratula
A1: Carátula | H1: ⟵ Inicio | J1: Siguiente ▶
A2: Ingresos · contratos con clientes (existencia, precio, asignación, satisfacción, corte y devoluciones) · Cliente de muestra S.A. · corte 2025-12-31
A4: Concepto | B4: Detalle
A5: Firma | B5: AuditConsulting Auditores Cía. Ltda.
A6: Cliente | B6: Cliente de muestra S.A.
A7: RUC | B7: 1790000000001
A8: Ejercicio | B8: 2025
A9: Fecha de corte | B9: 2025-12-31
A10: Marco contable | B10: NIIF completas
A11: Herramienta | B11: Ingresos · contratos con clientes (existencia, precio, asignación, satisfacción, corte y devoluciones)
A12: Rubro | B12: Ingresos
A13: Motor | B13: ingresos_contratos 1.0
A14: Versión del papel | B14: v1
A15: Estado | B15: MUESTRA
... A17: Revisó | B17: Pendiente
A18: Aprobó
A19: Fecha de aprobación
A20: Huella de la ejecución (SHA-256)

Sheet 00_Programa
A1: Programa | H1: ⟵ Inicio | I1: ◀ Anterior | J1: Siguiente ▶
A2: Ingresos · contratos con clientes (existencia, precio, asignación, satisfacción, corte y devoluciones) · Cliente de muestra S.A. · corte 2025-12-31
A4: Código | B4: Objetivo | C4: Afirmación | D4: Procedimiento | E4: Evidencia | F4: Criterio | G4: Referencia
A5: ING-01 | B5: Existencia del contrato (REV-FULL-01 / REV-SME25-01) | C5: Ocurrencia | D5: Obtener contratos u órdenes aprobadas y evaluar los criterios de existencia | E5: Contratos, órdenes de compra, adendas | F5: Ingreso solo con contrato válido | G5: NIIF 15 9 · PYMES 2025 23.7 · PYMES 2015 23.10 a)-e) y 23.14 a)-d)
A6: ING-02 | B6: Obligaciones y asignación (REV-FULL-02, 06 / REV-SME25-02, 04) | C6: Exactitud | D6: Identificar obligaciones diferenciadas y recalcular la asignación por precio de venta independiente relativo | E6: Listas de precios, cotizaciones | F6: Diferencia de asignación cuantificada | G6: NIIF 15 22-30, 73-80 · PYMES 2025 23.14-23.22, 23.42
A7: ING-03 | B7: Precio y contraprestación variable (REV-FULL-03, 04 / REV-SME25-03, 06 / REV-SME15-05) | C7: Exactitud / Valoración | D7: Revisar bonos, descuentos y rappels y su probabilidad; aplicar la restricción | E7: Contratos, historia de cumplimiento | F7: Variable altamente probable | G7: NIIF 15 50-59 · PYMES 2025 23.26-23.31 · PYMES 2015 23.3
A8: ING-04 | B8: Satisfacción y avance (REV-FULL-07, 08 / REV-SME25-05 / REV-SME15-01..03) | C8: Ocurrencia / Exactitud | D8: Recalcular el avance por costos y verificar la transferencia del control | E8: Presupuestos, costos incurridos, actas de entrega | F8: Avance y transferencia recalculados | G8: NIIF 15 31-45 · PYMES 2025 23.49-23.66 · PYMES 2015 23.10-23.22
A9: ING-05 | B9: Corte (REV-03) | C9: Corte | D9: Comparar fecha de registro con fecha de transferencia alrededor del cierre | E9: Guías de remisión, actas, facturas | F9: Ingreso en el período de la transferencia | G9: NIIF 15 38 · NIA 330
A10: ING-06 | B10: Devoluciones y notas de crédito (REV-04 / REV-FULL-11 / REV-SME15-07) | C10: Valoración | D10: Evaluar la tasa de devolución esperada, recalcular el pasivo por reembolso y el activo por el derecho a recuperar los productos (con su ajuste al costo de ventas) y cotejar notas de crédito posteriores al cierre | E10: Estadística de devoluciones, costo de ventas, NC posteriores | F10: Pasivo por reembolso y activo por recuperar reconocidos | G10: NIIF 15 B20-B27 (B21 c, B25) · PYMES 2025 23.33-23.35 y 23A.23-23A.27 (23A.24 c) · NIA 560
A11: ING-07 | B11: Componente de financiación (REV-FULL-05 / REV-SME15-06) | C11: Clasificación | D11: Identificar cobros diferidos más allá del umbral y descontar a la tasa de mercado | E11: Contratos, tasas de mercado | F11: Interés separado del ingreso | G11: NIIF 15 60-65 · PYMES 2025 23.36-23.38 · PYMES 2015 23.5
A12: ING-08 | B12: Activo y pasivo del contrato (REV-FULL-12) | C12: Presentación | D12: Determinar por contrato la posición reconocido − facturado y compararla con el mayor | E12: Facturación, mayor | F12: Activo/pasivo presentados | G12: NIIF 15 105-109 · PYMES 2025 23.77-23.80
A13: ING-09 | B13: Modificaciones (REV-FULL-09) | C13: Exactitud | D13: Revisar adendas y su tratamiento (separado, prospectivo, acumulativo) | E13: Adendas, órdenes de cambio | F13: Tratamiento documentado | G13: NIIF 15 18-21 · PYMES 2025 23.12, 23A.2-23A.4
A14: ING-10 | B14: Sumaria e integridad (REV-01, REV-02) | C14: Integridad | D14: Conciliar el anexo de contratos con los ingresos del mayor | E14: Mayor de ingresos | F14: Diferencia explicada | G14: NIA 500 párr. 9

Sheet 00_Fuentes
A1: Base técnica | H1: ⟵ Inicio | I1: ◀ Anterior | J1: Siguiente ▶
A2: Ingresos · contratos con clientes (existencia, precio, asignación, satisfacción, corte y devoluciones) · Cliente de muestra S.A. · corte 2025-12-31
A4: Categoría | B4: Documento | C4: Párrafos | D4: URL | E4: Verificada
A5: NIA · NIA 240 | B5: Presunción de riesgo de fraude en el reconocimiento de ingresos. | C5: párr. 26-27 (la NIA 240 Revisada rige para períodos que empiecen desde el 15-12-2026 y cambia la numeración; se permite su aplicación anticipada)
A6: NIA · NIA 500 | B6: Exactitud e integridad del anexo de contratos contra el mayor. | C6: párr. 9
A7: NIA · NIA 540 (Revisada) | B7: Estimaciones: variable, avance por costos, devoluciones y tasa de descuento. | C7: párr. 13 y 17-30
A8: NIA · NIA 560 | B8: Notas de crédito y devoluciones posteriores al cierre. | C8: párr. 6
A9: NIA · NIA 330 | B9: Procedimientos sustantivos de corte y ocurrencia. | C9: párr. 18-20

Sheet 01_Resumen
A1: Resumen | H1: ⟵ Inicio | I1: ◀ Anterior | J1: Siguiente ▶
A2: Ingresos · contratos con clientes (existencia, precio, asignación, satisfacción, corte y devoluciones) · Cliente de muestra S.A. · corte 2025-12-31
A4: Concepto | B4: Importe
A5: Ingreso reconocible del año (líneas medidas) | B5: ='13_Conciliacion'!B8
A6: Ingreso registrado en el año (anexo) | B6: ='13_Conciliacion'!B5
A7: Ingresos según el mayor | B7: ='13_Conciliacion'!B6
A8: Diferencia anexo − mayor | B8: ='13_Conciliacion'!B7
A9: Ajuste propuesto a ingresos | B9: ='13_Conciliacion'!B9
A10: Corte: registrado antes de la transferencia | B10: ='13_Conciliacion'!B10
A11: Corte: transferido sin registrar en el ejercicio | B11: ='13_Conciliacion'!B11
A12: Componente de financiación a separar | B12: ='13_Conciliacion'!B12
A13: Interés devengado al corte | B13: ='13_Conciliacion'!B13
A14: Pasivo por reembolso (devoluciones esperadas) | B14: ='13_Conciliacion'!B14
A15: Activo por el derecho a recuperar los productos (contra el costo de ventas) | B15: ='13_Conciliacion'!B15
A16: Notas de crédito posteriores no provisionadas | B16: ='13_Conciliacion'!B16
A17: Activo del contrato requerido | B17: ='13_Conciliacion'!B17
A18: Activo del contrato registrado | B18: ='13_Conciliacion'!B18
A19: Activo del contrato: diferencia | B19: ='13_Conciliacion'!B19
A20: Pasivo del contrato (ingreso diferido) requerido | B20: ='13_Conciliacion'!B20
... A24: Variable incluida sin cumplir la restricción | B24: ='13_Conciliacion'!B24
A26: ⓘ Cómo se calcula esta hoja
A27: Columna | B27: Fórmula (Excel) | C27: Cómo se calcula (sencillo) | D27: Ejemplo con números reales | E27: De dónde viene | F27: Norma
A28: Importe | B28: '='13_Conciliacion'!B8 | C28: Trae cada importe de la hoja 13 (Conciliación y ajustes), concepto por concepto, para que el resumen muestre siempre las mismas cifras que la conciliación. | D28: Fila 1: 544.546,67 → 544.546,67 | E28: hoja «Conciliación y ajustes» | F28: —

Sheet 02_Parametros
A1: Parámetros | H1: ⟵ Inicio | I1: ◀ Anterior | J1: Siguiente ▶
A2: Ingresos · contratos con clientes (existencia, precio, asignación, satisfacción, corte y devoluciones) · Cliente de muestra S.A. · corte 2025-12-31
A4: Parámetro | B4: Valor | C4: Sustento
A5: Corte del ejercicio | B5: 46022 | C5: Ficha del encargo
A6: Marco contable | B6: NIIF completas | C6: Ficha del encargo: enruta el modelo de reconocimiento
A7: Modelo aplicado | B7: NIIF 15 · modelo de cinco pasos | C7: Paso 1 contrato · 2 obligaciones · 3 precio · 4 asignación · 5 satisfacción
A8: Tasa de descuento anual para la financiación (%) | B8: 10 | C8: NIIF 15 60-65 — tasa de una financiación separada con el cliente al inicio del contrato
A9: Plazo de cobro que se considera financiación significativa (meses) | B9: 12 | C9: NIIF 15 63 / PYMES 2025 23.38: solución práctica de un año; más de 12 meses habilita evaluar (NIIF 15.61-62); no es concluyente por sí solo; PYMES 2015: plazo mayor al normal (11.13)
A10: Probabilidad mínima para incluir la variable «altamente probable» (%) | B10: 75 | C10: «Altamente probable» (NIIF 15 56: que no ocurra una reversión significativa; PYMES 2025 23.30: que la entidad tenga derecho al importe; criterios distintos): ninguna fija un porcentaje; umbral de juicio del auditor. Simplificación: la variable se incluye si su probabilidad supera el umbral; la NIIF 15.56 exige que sea altamente probable que no haya reversión significativa
A11: Método de estimación de la variable (Importe más probable / Valor esperado) | B11: Importe más probable | C11: NIIF 15 53; PYMES 2025 23.28
A12: Ingresos de actividades ordinarias según el mayor | B12: 670000 | C12: Mayor contable (en blanco: se toma el anexo)
A13: Activo del contrato registrado (mayor) | B13: 20000 | C13: Mayor contable
A14: Pasivo del contrato / ingreso diferido registrado (mayor) | C14: Mayor contable
A15: Activo por derecho a recuperar productos | B15: Sí | C15: NIIF 15 B21 c) y B25 / PYMES 2025 23A.24 c): activo por el derecho a recuperar los productos, medido al importe en libros anterior menos los costos de recuperación, con el ajuste correlativo al costo de ventas

Sheet 03_Detalle
A1: Detalle por obligación | H1: ⟵ Inicio | I1: ◀ Anterior | J1: Siguiente ▶
A2: Ingresos · contratos con clientes (existencia, precio, asignación, satisfacción, corte y devoluciones) · Cliente de muestra S.A. · corte 2025-12-31
A4: Línea | B4: Contrato | C4: Cliente | D4: Obligación | E4: Evidencia del contrato | F4: Modo | G4: Transferencia del control | H4: Registro del ingreso | I4: Precio de venta independiente | J4: Precio del contrato | K4: Variable estimada | L4: Probabilidad (%) | M4: Variable del cliente | N4: Costos incurridos | O4: Costos totales | P4: Avance del cliente (%) | Q4: Registrado en el año | R4: Reconocido años anteriores | S4: Facturado acumulado | T4: Cobrado acumulado | U4: Plazo de cobro (meses) | V4: Devoluciones esperadas (%) | W4: NC posteriores | X4: Modificación | Y4: Importe modificación | Z4: Variable que supera la restricción | AA4: Costo de los bienes vendidos | AB4: Contrato válido
A5: C-01-1 | B5: C-01 | C5: Comercial Andina | D5: Equipo | E5: Sí | F5: En un momento | G5: 45976 | H5: 45976 | I5: 100000 | J5: 90000 | Q5: 90000 | S5: 90000 | T5: 60000 | AB5: =IF(E5="No","No",IF(E5="","Sin dato","Sí"))
A6: C-01-2 | B6: C-01 | C6: Comercial Andina | D6: Mantenimiento 12 meses | E6: Sí | F6: A lo largo del tiempo | I6: 25000 | J6: 10000 | N6: 3000 | O6: 12000 | P6: 25 | Q6: 2500 | S6: 10000 | AB6: =IF(E6="No","No",IF(E6="","Sin dato","Sí"))
A7: C-02-1 | B7: C-02 | C7: Constructora Sur | D7: Obra civil | E7: Sí | F7: A lo largo del tiempo | I7: 500000 | J7: 500000 | K7: 50000 | L7: 60 | M7: 50000 | N7: 180000 | O7: 400000 | P7: 50 | Q7: 275000 | S7: 200000 | T7: 150000 | AB7: =IF(E7="No","No",IF(E7="","Sin dato","Sí"))
A8: C-03-1 | B8: C-03 | C8: Distribuidora Norte | D8: Mercadería | E8: Sí | F8: En un momento | G8: 46027 | H8: 46019 | J8: 30000 | Q8: 30000 | S8: 30000 | AB8: =IF(E8="No","No",IF(E8="","Sin dato","Sí"))
A9: C-04-1 | B9: C-04 | C9: Retail Express | D9: Mercadería con derecho a devolución | E9: Sí | F9: En un momento | G9: 46001 | H9: 46001 | J9: 40000 | Q9: 40000 | S9: 40000 | T9: 20000 | V9: 5 | W9: 3500 | AA9: 24000 | AB9: =IF(E9="No","No",IF(E9="","Sin dato","Sí"))
A10: C-05-1 | B10: C-05 | C10: Agro Plazo | D10: Maquinaria a 24 meses | E10: Sí | F10: En un momento | G10: 45839 | H10: 45839 | J10: 121000 | Q10: 121000 | S10: 121000 | U10: 24 | AB10: =IF(E10="No","No",IF(E10="","Sin dato","Sí"))
A11: C-06-1 | B11: C-06 | C11: Servicios Beta | D11: Consultoría | E11: No | F11: A lo largo del tiempo | J11: 15000 | N11: 5000 | O11: 5000 | Q11: 15000 | S11: 15000 | T11: 15000 | AB11: =IF(E11="No","No",IF(E11="","Sin dato","Sí"))
A12: C-07-1 | B12: C-07 | C12: Tecnología Gama | D12: Equipos | E12: Sí | F12: En un momento | G12: 46011 | H12: 46025 | J12: 12000 | Q12: 0 | AB12: =IF(E12="No","No",IF(E12="","Sin dato","Sí"))
A13: C-08-1 | B13: C-08 | C13: Software Delta | D13: Implementación | F13: A lo largo del tiempo | J13: 48000 | N13: 24000 | O13: 32000 | P13: 75 | Q13: 26000 | R13: 10000 | S13: 40000 | T13: 40000 | X13: Prospectivo | Y13: 8000 | AB13: =IF(E13="No","No",IF(E13="","Sin dato","Sí"))
A14: C-09-1 | B14: C-09 | C14: Mantenimientos Épsilon | D14: Repuestos | E14: Sí | F14: En un momento | G14: 45992 | H14: 45992 | J14: 6000 | Q14: 6000 | S14: 6000 | T14: 6000 | V14: 2 | X14: Adenda de precio | Y14: 1000 | AB14: =IF(E14="No","No",IF(E14="","Sin dato","Sí"))
A15: C-09-2 | B15: C-09 | C15: Mantenimientos Épsilon | D15: Servicio técnico | E15: Sí | F15: A lo largo del tiempo | I15: 4000 | J15: 4000 | N15: 1000 | O15: 2000 | Q15: 2000 | S15: 4000 | T15: 4000 | AB15: =IF(E15="No","No",IF(E15="","Sin dato","Sí"))
A16: C-10-1 | B16: C-10 | C16: Obra Zeta | D16: Obra menor | E16: Sí | F16: A lo largo del tiempo | I16: 80000 | J16: 80000 | N16: 30000 | O16: 90000 | Q16: 26666.67 | S16: 20000 | AB16: =IF(E16="No","No",IF(E16="","Sin dato","Sí"))
A17: C-11-1 | B17: C-11 | C17: Servicios Theta | D17: Entrega con bono | E17: Sí | F17: En un momento | G17: 45931 | H17: 45931 | J17: 20000 | K17: 5000 | L17: 90 | M17: 5000 | Q17: 25000 | S17: 25000 | T17: 25000 | Z17: 1000 | AB17: =IF(E17="No","No",IF(E17="","Sin dato","Sí"))
A18: C-12-1 | B18: C-12 | C18: Comercial Iota | D18: Mercadería | E18: Sí | F18: En un momento | J18: 9000 | Q18: 9000 | S18: 9000 | AB18: =IF(E18="No","No",IF(E18="","Sin dato","Sí"))
A19: TOTAL | J19: =SUM(J5:J18) | Q19: =SUM(Q5:Q18) | S19: =SUM(S5:S18) | T19: =SUM(T5:T18)
A21: ⓘ Cómo se calcula esta hoja
A22: Columna | B22: Fórmula (Excel) | C22: Cómo se calcula (sencillo) | D22: Ejemplo con números reales | E22: De dónde viene | F22: Norma
A23: Contrato válido | B23: '=IF(E5="No","No",IF(E5="","Sin dato","Sí")) | C23: Lee la evidencia del contrato informada por el cliente en esta hoja: «No» si dijo que no hay contrato aprobado, «Sin dato» si la dejó vacía y «Sí» en los demás casos. | D23: Fila 1: IF(«Sí»="No"; "No"; IF(«Sí»=""; "Sin dato"; "Sí")) → Sí | E23: «Evidencia del contrato» (esta hoja) | F23: —

Sheet 04_Precio_variable
A1: Precio y contraprestación variable | H1: ⟵ Inicio | I1: ◀ Anterior | J1: Siguiente ▶
A2: Ingresos · contratos con clientes (existencia, precio, asignación, satisfacción, corte y devoluciones) · Cliente de muestra S.A. · corte 2025-12-31
A4: Línea | B4: Contrato | C4: Precio fijo | D4: Variable estimada | E4: Probabilidad | F4: Importe estimado por el método | G4: Importe que supera la restricción | H4: Variable incluida (restringida) | I4: Variable del cliente | J4: Exceso sobre la restricción | K4: Precio de la transacción del contrato
A5: C-01-1 | B5: C-01 | C5: ='03_Detalle'!J5 | D5: =IF('03_Detalle'!K5<>"",'03_Detalle'!K5,"") | E5: =IF('03_Detalle'!L5<>"",'03_Detalle'!L5/100,"") | F5: =IF(D5="","",IF('02_Parametros'!$B$11="Valor esperado",IF(E5="","",D5*E5),D5)) | G5: =IF('03_Detalle'!Z5<>"",'03_Detalle'!Z5,"") | H5: =IF(F5="",0,IF(G5<>"",MAX(F5-G5,0),IF(E5="",0,IF(E5>='02_Parametros'!$B$10/100,F5,0)))) | I5: =IF('03_Detalle'!M5<>"",'03_Detalle'!M5,"") | J5: =IF(I5="","",MAX(I5-H5,0)) | K5: =SUMIF($B$5:$B$18,B5,$C$5:$C$18)+SUMIF($B$5:$B$18,B5,$H$5:$H$18)
A6: C-01-2 | B6: C-01 | C6: ='03_Detalle'!J6 | D6: =IF('03_Detalle'!K6<>"",'03_Detalle'!K6,"") | E6: =IF('03_Detalle'!L6<>"",'03_Detalle'!L6/100,"") | F6: =IF(D6="","",IF('02_Parametros'!$B$11="Valor esperado",IF(E6="","",D6*E6),D6)) | G6: =IF('03_Detalle'!Z6<>"",'03_Detalle'!Z6,"") | H6: =IF(F6="",0,IF(G6<>"",MAX(F6-G6,0),IF(E6="",0,IF(E6>='02_Parametros'!$B$10/100,F6,0)))) | I6: =IF('03_Detalle'!M6<>"",'03_Detalle'!M6,"") | J6: =IF(I6="","",MAX(I6-H6,0)) | K6: =SUMIF($B$5:$B$18,B6,$C$5:$C$18)+SUMIF($B$5:$B$18,B6,$H$5:$H$18)
A7: C-02-1 | B7: C-02 | C7: ='03_Detalle'!J7 | D7: =IF('03_Detalle'!K7<>"",'03_Detalle'!K7,"") | E7: =IF('03_Detalle'!L7<>"",'03_Detalle'!L7/100,"") | F7: =IF(D7="","",IF('02_Parametros'!$B$11="Valor esperado",IF(E7="","",D7*E7),D7)) | G7: =IF('03_Detalle'!Z7<>"",'03_Detalle'!Z7,"") | H7: =IF(F7="",0,IF(G7<>"",MAX(F7-G7,0),IF(E7="",0,IF(E7>='02_Parametros'!$B$10/100,F7,0)))) | I7: =IF('03_Detalle'!M7<>"",'03_Detalle'!M7,"") | J7: =IF(I7="","",MAX(I7-H7,0)) | K7: =SUMIF($B$5:$B$18,B7,$C$5:$C$18)+SUMIF($B$5:$B$18,B7,$H$5:$H$18)
A8: C-03-1 | B8: C-03 | C8: ='03_Detalle'!J8 | D8: =IF('03_Detalle'!K8<>"",'03_Detalle'!K8,"") | E8: =IF('03_Detalle'!L8<>"",'03_Detalle'!L8/100,"") | F8: =IF(D8="","",IF('02_Parametros'!$B$11="Valor esperado",IF(E8="","",D8*E8),D8)) | G8: =IF('03_Detalle'!Z8<>"",'03_Detalle'!Z8,"") | H8: =IF(F8="",0,IF(G8<>"",MAX(F8-G8,0),IF(E8="",0,IF(E8>='02_Parametros'!$B$10/100,F8,0)))) | I8: =IF('03_Detalle'!M8<>"",'03_Detalle'!M8,"") | J8: =IF(I8="","",MAX(I8-H8,0)) | K8: =SUMIF($B$5:$B$18,B8,$C$5:$C$18)+SUMIF($B$5:$B$18,B8,$H$5:$H$18)
A9: C-04-1 | B9: C-04 | C9: ='03_Detalle'!J9 | D9: =IF('03_Detalle'!K9<>"",'03_Detalle'!K9,"") | E9: =IF('03_Detalle'!L9<>"",'03_Detalle'!L9/100,"") | F9: =IF(D9="","",IF('02_Parametros'!$B$11="Valor esperado",IF(E9="","",D9*E9),D9)) | G9: =IF('03_Detalle'!Z9<>"",'03_Detalle'!Z9,"") | H9: =IF(F9="",0,IF(G9<>"",MAX(F9-G9,0),IF(E9="",0,IF(E9>='02_Parametros'!$B$10/100,F9,0)))) | I9: =IF('03_Detalle'!M9<>"",'03_Detalle'!M9,"") | J9: =IF(I9="","",MAX(I9-H9,0)) | K9: =SUMIF($B$5:$B$18,B9,$C$5:$C$18)+SUMIF($B$5:$B$18,B9,$H$5:$H$18)
A10: C-05-1 | B10: C-05 | C10: ='03_Detalle'!J10 | D10: =IF('03_Detalle'!K10<>"",'03_Detalle'!K10,"") | E10: =IF('03_Detalle'!L10<>"",'03_Detalle'!L10/100,"") | F10: =IF(D10="","",IF('02_Parametros'!$B$11="Valor esperado",IF(E10="","",D10*E10),D10)) | G10: =IF('03_Detalle'!Z10<>"",'03_Detalle'!Z10,"") | H10: =IF(F10="",0,IF(G10<>"",MAX(F10-G10,0),IF(E10="",0,IF(E10>='02_Parametros'!$B$10/100,F10,0)))) | I10: =IF('03_Detalle'!M10<>"",'03_Detalle'!M10,"") | J10: =IF(I10="","",MAX(I10-H10,0)) | K10: =SUMIF($B$5:$B$18,B10,$C$5:$C$18)+SUMIF($B$5:$B$18,B10,$H$5:$H$18)
A11: C-06-1 | B11: C-06 | C11: ='03_Detalle'!J11 | D11: =IF('03_Detalle'!K11<>"",'03_Detalle'!K11,"") | E11: =IF('03_Detalle'!L11<>"",'03_Detalle'!L11/100,"") | F11: =IF(D11="","",IF('02_Parametros'!$B$11="Valor esperado",IF(E11="","",D11*E11),D11)) | G11: =IF('03_Detalle'!Z11<>"",'03_Detalle'!Z11,"") | H11: =IF(F11="",0,IF(G11<>"",MAX(F11-G11,0),IF(E11="",0,IF(E11>='02_Parametros'!$B$10/100,F11,0)))) | I11: =IF('03_Detalle'!M11<>"",'03_Detalle'!M11,"") | J11: =IF(I11="","",MAX(I11-H11,0)) | K11: =SUMIF($B$5:$B$18,B11,$C$5:$C$18)+SUMIF($B$5:$B$18,B11,$H$5:$H$18)
A12: C-07-1 | B12: C-07 | C12: ='03_Detalle'!J12 | D12: =IF('03_Detalle'!K12<>"",'03_Detalle'!K12,"") | E12: =IF('03_Detalle'!L12<>"",'03_Detalle'!L12/100,"") | F12: =IF(D12="","",IF('02_Parametros'!$B$11="Valor esperado",IF(E12="","",D12*E12),D12)) | G12: =IF('03_Detalle'!Z12<>"",'03_Detalle'!Z12,"") | H12: =IF(F12="",0,IF(G12<>"",MAX(F12-G12,0),IF(E12="",0,IF(E12>='02_Parametros'!$B$10/100,F12,0)))) | I12: =IF('03_Detalle'!M12<>"",'03_Detalle'!M12,"") | J12: =IF(I12="","",MAX(I12-H12,0)) | K12: =SUMIF($B$5:$B$18,B12,$C$5:$C$18)+SUMIF($B$5:$B$18,B12,$H$5:$H$18)
A13: C-08-1 | B13: C-08 | C13: ='03_Detalle'!J13 | D13: =IF('03_Detalle'!K13<>"",'03_Detalle'!K13,"") | E13: =IF('03_Detalle'!L13<>"",'03_Detalle'!L13/100,"") | F13: =IF(D13="","",IF('02_Parametros'!$B$11="Valor esperado",IF(E13="","",D13*E13),D13)) | G13: =IF('03_Detalle'!Z13<>"",'03_Detalle'!Z13,"") | H13: =IF(F13="",0,IF(G13<>"",MAX(F13-G13,0),IF(E13="",0,IF(E13>='02_Parametros'!$B$10/100,F13,0)))) | I13: =IF('03_Detalle'!M13<>"",'03_Detalle'!M13,"") | J13: =IF(I13="","",MAX(I13-H13,0)) | K13: =SUMIF($B$5:$B$18,B13,$C$5:$C$18)+SUMIF($B$5:$B$18,B13,$H$5:$H$18)
A14: C-09-1 | B14: C-09 | C14: ='03_Detalle'!J14 | D14: =IF('03_Detalle'!K14<>"",'03_Detalle'!K14,"") | E14: =IF('03_Detalle'!L14<>"",'03_Detalle'!L14/100,"") | F14: =IF(D14="","",IF('02_Parametros'!$B$11="Valor esperado",IF(E14="","",D14*E14),D14)) | G14: =IF('03_Detalle'!Z14<>"",'03_Detalle'!Z14,"") | H14: =IF(F14="",0,IF(G14<>"",MAX(F14-G14,0),IF(E14="",0,IF(E14>='02_Parametros'!$B$10/100,F14,0)))) | I14: =IF('03_Detalle'!M14<>"",'03_Detalle'!M14,"") | J14: =IF(I14="","",MAX(I14-H14,0)) | K14: =SUMIF($B$5:$B$18,B14,$C$5:$C$18)+SUMIF($B$5:$B$18,B14,$H$5:$H$18)
A15: C-09-2 | B15: C-09 | C15: ='03_Detalle'!J15 | D15: =IF('03_Detalle'!K15<>"",'03_Detalle'!K15,"") | E15: =IF('03_Detalle'!L15<>"",'03_Detalle'!L15/100,"") | F15: =IF(D15="","",IF('02_Parametros'!$B$11="Valor esperado",IF(E15="","",D15*E15),D15)) | G15: =IF('03_Detalle'!Z15<>"",'03_Detalle'!Z15,"") | H15: =IF(F15="",0,IF(G15<>"",MAX(F15-G15,0),IF(E15="",0,IF(E15>='02_Parametros'!$B$10/100,F15,0)))) | I15: =IF('03_Detalle'!M15<>"",'03_Detalle'!M15,"") | J15: =IF(I15="","",MAX(I15-H15,0)) | K15: =SUMIF($B$5:$B$18,B15,$C$5:$C$18)+SUMIF($B$5:$B$18,B15,$H$5:$H$18)
A16: C-10-1 | B16: C-10 | C16: ='03_Detalle'!J16 | D16: =IF('03_Detalle'!K16<>"",'03_Detalle'!K16,"") | E16: =IF('03_Detalle'!L16<>"",'03_Detalle'!L16/100,"") | F16: =IF(D16="","",IF('02_Parametros'!$B$11="Valor esperado",IF(E16="","",D16*E16),D16)) | G16: =IF('03_Detalle'!Z16<>"",'03_Detalle'!Z16,"") | H16: =IF(F16="",0,IF(G16<>"",MAX(F16-G16,0),IF(E16="",0,IF(E16>='02_Parametros'!$B$10/100,F16,0)))) | I16: =IF('03_Detalle'!M16<>"",'03_Detalle'!M16,"") | J16: =IF(I16="","",MAX(I16-H16,0)) | K16: =SUMIF($B$5:$B$18,B16,$C$5:$C$18)+SUMIF($B$5:$B$18,B16,$H$5:$H$18)
... A18: C-12-1 | B18: C-12 | C18: ='03_Detalle'!J18 | D18: =IF('03_Detalle'!K18<>"",'03_Detalle'!K18,"") | E18: =IF('03_Detalle'!L18<>"",'03_Detalle'!L18/100,"") | F18: =IF(D18="","",IF('02_Parametros'!$B$11="Valor esperado",IF(E18="","",D18*E18),D18)) | G18: =IF('03_Detalle'!Z18<>"",'03_Detalle'!Z18,"") | H18: =IF(F18="",0,IF(G18<>"",MAX(F18-G18,0),IF(E18="",0,IF(E18>='02_Parametros'!$B$10/100,F18,0)))) | I18: =IF('03_Detalle'!M18<>"",'03_Detalle'!M18,"") | J18: =IF(I18="","",MAX(I18-H18,0)) | K18: =SUMIF($B$5:$B$18,B18,$C$5:$C$18)+SUMIF($B$5:$B$18,B18,$H$5:$H$18)
A19: TOTAL | C19: =SUM(C5:C18) | H19: =SUM(H5:H18) | J19: =SUM(J5:J18)
A21: ⓘ Cómo se calcula esta hoja
A22: Columna | B22: Fórmula (Excel) | C22: Cómo se calcula (sencillo) | D22: Ejemplo con números reales | E22: De dónde viene | F22: Norma
A23: Precio fijo | B23: '='03_Detalle'!J5 | C23: Trae el precio del contrato asignado por el cliente a la línea, de la hoja 03 (Detalle por obligación). | D23: Fila 1: 90.000,00 → 90.000,00 | E23: hoja «Detalle por obligación» | F23: —
A24: Variable estimada | B24: '=IF('03_Detalle'!K5<>"",'03_Detalle'!K5,"") | C24: Trae la contraprestación variable estimada de la línea (hoja 03); queda en blanco si el contrato no tiene parte variable. | D24: Fila 1: IF((vacío)<>""; (vacío); "") → (en blanco) | E24: hoja «Detalle por obligación» | F24: —
A25: Probabilidad | B25: '=IF('03_Detalle'!L5<>"",'03_Detalle'!L5/100,"") | C25: Trae la probabilidad de la variable informada en la hoja 03 y la expresa como porcentaje; queda en blanco si no se informó. | D25: Fila 1: IF((vacío)<>""; (vacío)/100; "") → (en blanco) | E25: hoja «Detalle por obligación» | F25: —
A26: Importe estimado por el método | B26: '=IF(D5="","",IF('02_Parametros'!$B$11="Valor esperado",IF(E5="","",D5*E5),D5)) | C26: Si el método de la hoja 02 es «Valor esperado», multiplica la variable por su probabilidad; si es «Importe más probable», toma la variable completa. Queda en blanco si no hay variable (o, con valor esperado, si falta la probabilidad). | D26: Fila 1: IF((vacío)=""; ""; IF(«Importe más probable»="Valor esperado"; IF((vacío)=""; ""; (vacío)*(vacío)); (vacío))) → (en blanco) | E26: «Variable estimada» (esta hoja), «Probabilidad» (esta hoja), hoja «Parámetros» | F26: —
A27: Importe que supera la restricción | B27: '=IF('03_Detalle'!Z5<>"",'03_Detalle'!Z5,"") | C27: Trae de la hoja 03 la parte de la variable que el cliente no puede incluir por la restricción; queda en blanco si no se informó. | D27: Fila 1: IF((vacío)<>""; (vacío); "") → (en blanco) | E27: hoja «Detalle por obligación» | F27: —
A28: Variable incluida (restringida) | B28: '=IF(F5="",0,IF(G5<>"",MAX(F5-G5,0),IF(E5="",0,IF(E5>='02_Parametros'!$B$10/100,F5,0)))) | C28: Si se informó el importe que supera la restricción, incluye el importe estimado menos ese importe (nunca menos de cero); si no, incluye todo el importe estimado si su probabilidad alcanza el umbral de «altamente probable» de la hoja 02 (Parámetros) y nada en caso contrario o si falta la probabilidad. | D28: Fila 1: IF((vacío)=""; 0; IF((vacío)<>""; MAX((vacío)-(vacío); 0); IF((vacío)=""; 0; IF((vacío)>=75,00/100; (vacío); 0)))) → 0,00 | E28: «Importe estimado por el método» (esta hoja), «Importe que supera la restricción» (esta hoja), «Probabilidad» (esta hoja), hoja «Parámetros» | F28: —
A29: Variable del cliente | B29: '=IF('03_Detalle'!M5<>"",'03_Detalle'!M5,"") | C29: Trae la contraprestación variable que el cliente incluyó en el precio (hoja 03); queda en blanco si no la informó. | D29: Fila 1: IF((vacío)<>""; (vacío); "") → (en blanco) | E29: hoja «Detalle por obligación» | F29: —
A30: Exceso sobre la restricción | B30: '=IF(I5="","",MAX(I5-H5,0)) | C30: Resta la variable incluida por el auditor de la que incluyó el cliente; si el cliente incluyó menos, da cero. En blanco si el cliente no informó su variable. | D30: Fila 1: IF((vacío)=""; ""; MAX((vacío)-0,00; 0)) → (en blanco) | E30: «Variable del cliente» (esta hoja), «Variable incluida (restringida)» (esta hoja) | F30: —
A31: Precio de la transacción del contrato | B31: '=SUMIF($B$5:$B$18,B5,$C$5:$C$18)+SUMIF($B$5:$B$18,B5,$H$5:$H$18) | C31: Suma, para todas las líneas del mismo contrato de esta hoja, los precios fijos y las variables incluidas: es el precio total a repartir entre las obligaciones. | D31: Fila 1: SUMIF([«Contrato», 14 filas]; «C-01»; [«Precio fijo», 14 filas])+SUMIF([«Contrato», 14 filas]; «C-01»; [«Variable incluida (restringida)», 14 filas]) → 100.000,00 | E31: «Contrato» (esta hoja), «Precio fijo» (esta hoja), «Variable incluida (restringida)» (esta hoja) | F31: —

Sheet 05_Asignacion
A1: Asignación del precio | H1: ⟵ Inicio | I1: ◀ Anterior | J1: Siguiente ▶
A2: Ingresos · contratos con clientes (existencia, precio, asignación, satisfacción, corte y devoluciones) · Cliente de muestra S.A. · corte 2025-12-31
A4: Línea | B4: Contrato | C4: Precio independiente usado | D4: Suma del contrato | E4: Precio de la transacción | F4: Asignado (relativo) | G4: Asignación del cliente | H4: Diferencia | I4: Obligaciones del contrato | J4: Diferencia absoluta
A5: C-01-1 | B5: C-01 | C5: =IF('03_Detalle'!I5<>"",'03_Detalle'!I5,'03_Detalle'!J5) | D5: =SUMIF($B$5:$B$18,B5,$C$5:$C$18) | E5: ='04_Precio_variable'!K5 | F5: =IF(D5=0,"",E5*C5/D5) | G5: ='04_Precio_variable'!C5+IF('04_Precio_variable'!I5="",0,'04_Precio_variable'!I5) | H5: =IF(F5="","",F5-G5) | I5: =COUNTIF($B$5:$B$18,B5) | J5: =IF(OR(H5="",I5<2),0,ABS(H5))
A6: C-01-2 | B6: C-01 | C6: =IF('03_Detalle'!I6<>"",'03_Detalle'!I6,'03_Detalle'!J6) | D6: =SUMIF($B$5:$B$18,B6,$C$5:$C$18) | E6: ='04_Precio_variable'!K6 | F6: =IF(D6=0,"",E6*C6/D6) | G6: ='04_Precio_variable'!C6+IF('04_Precio_variable'!I6="",0,'04_Precio_variable'!I6) | H6: =IF(F6="","",F6-G6) | I6: =COUNTIF($B$5:$B$18,B6) | J6: =IF(OR(H6="",I6<2),0,ABS(H6))
A7: C-02-1 | B7: C-02 | C7: =IF('03_Detalle'!I7<>"",'03_Detalle'!I7,'03_Detalle'!J7) | D7: =SUMIF($B$5:$B$18,B7,$C$5:$C$18) | E7: ='04_Precio_variable'!K7 | F7: =IF(D7=0,"",E7*C7/D7) | G7: ='04_Precio_variable'!C7+IF('04_Precio_variable'!I7="",0,'04_Precio_variable'!I7) | H7: =IF(F7="","",F7-G7) | I7: =COUNTIF($B$5:$B$18,B7) | J7: =IF(OR(H7="",I7<2),0,ABS(H7))
A8: C-03-1 | B8: C-03 | C8: =IF('03_Detalle'!I8<>"",'03_Detalle'!I8,'03_Detalle'!J8) | D8: =SUMIF($B$5:$B$18,B8,$C$5:$C$18) | E8: ='04_Precio_variable'!K8 | F8: =IF(D8=0,"",E8*C8/D8) | G8: ='04_Precio_variable'!C8+IF('04_Precio_variable'!I8="",0,'04_Precio_variable'!I8) | H8: =IF(F8="","",F8-G8) | I8: =COUNTIF($B$5:$B$18,B8) | J8: =IF(OR(H8="",I8<2),0,ABS(H8))
A9: C-04-1 | B9: C-04 | C9: =IF('03_Detalle'!I9<>"",'03_Detalle'!I9,'03_Detalle'!J9) | D9: =SUMIF($B$5:$B$18,B9,$C$5:$C$18) | E9: ='04_Precio_variable'!K9 | F9: =IF(D9=0,"",E9*C9/D9) | G9: ='04_Precio_variable'!C9+IF('04_Precio_variable'!I9="",0,'04_Precio_variable'!I9) | H9: =IF(F9="","",F9-G9) | I9: =COUNTIF($B$5:$B$18,B9) | J9: =IF(OR(H9="",I9<2),0,ABS(H9))
A10: C-05-1 | B10: C-05 | C10: =IF('03_Detalle'!I10<>"",'03_Detalle'!I10,'03_Detalle'!J10) | D10: =SUMIF($B$5:$B$18,B10,$C$5:$C$18) | E10: ='04_Precio_variable'!K10 | F10: =IF(D10=0,"",E10*C10/D10) | G10: ='04_Precio_variable'!C10+IF('04_Precio_variable'!I10="",0,'04_Precio_variable'!I10) | H10: =IF(F10="","",F10-G10) | I10: =COUNTIF($B$5:$B$18,B10) | J10: =IF(OR(H10="",I10<2),0,ABS(H10))
A11: C-06-1 | B11: C-06 | C11: =IF('03_Detalle'!I11<>"",'03_Detalle'!I11,'03_Detalle'!J11) | D11: =SUMIF($B$5:$B$18,B11,$C$5:$C$18) | E11: ='04_Precio_variable'!K11 | F11: =IF(D11=0,"",E11*C11/D11) | G11: ='04_Precio_variable'!C11+IF('04_Precio_variable'!I11="",0,'04_Precio_variable'!I11) | H11: =IF(F11="","",F11-G11) | I11: =COUNTIF($B$5:$B$18,B11) | J11: =IF(OR(H11="",I11<2),0,ABS(H11))
A12: C-07-1 | B12: C-07 | C12: =IF('03_Detalle'!I12<>"",'03_Detalle'!I12,'03_Detalle'!J12) | D12: =SUMIF($B$5:$B$18,B12,$C$5:$C$18) | E12: ='04_Precio_variable'!K12 | F12: =IF(D12=0,"",E12*C12/D12) | G12: ='04_Precio_variable'!C12+IF('04_Precio_variable'!I12="",0,'04_Precio_variable'!I12) | H12: =IF(F12="","",F12-G12) | I12: =COUNTIF($B$5:$B$18,B12) | J12: =IF(OR(H12="",I12<2),0,ABS(H12))
A13: C-08-1 | B13: C-08 | C13: =IF('03_Detalle'!I13<>"",'03_Detalle'!I13,'03_Detalle'!J13) | D13: =SUMIF($B$5:$B$18,B13,$C$5:$C$18) | E13: ='04_Precio_variable'!K13 | F13: =IF(D13=0,"",E13*C13/D13) | G13: ='04_Precio_variable'!C13+IF('04_Precio_variable'!I13="",0,'04_Precio_variable'!I13) | H13: =IF(F13="","",F13-G13) | I13: =COUNTIF($B$5:$B$18,B13) | J13: =IF(OR(H13="",I13<2),0,ABS(H13))
A14: C-09-1 | B14: C-09 | C14: =IF('03_Detalle'!I14<>"",'03_Detalle'!I14,'03_Detalle'!J14) | D14: =SUMIF($B$5:$B$18,B14,$C$5:$C$18) | E14: ='04_Precio_variable'!K14 | F14: =IF(D14=0,"",E14*C14/D14) | G14: ='04_Precio_variable'!C14+IF('04_Precio_variable'!I14="",0,'04_Precio_variable'!I14) | H14: =IF(F14="","",F14-G14) | I14: =COUNTIF($B$5:$B$18,B14) | J14: =IF(OR(H14="",I14<2),0,ABS(H14))
A15: C-09-2 | B15: C-09 | C15: =IF('03_Detalle'!I15<>"",'03_Detalle'!I15,'03_Detalle'!J15) | D15: =SUMIF($B$5:$B$18,B15,$C$5:$C$18) | E15: ='04_Precio_variable'!K15 | F15: =IF(D15=0,"",E15*C15/D15) | G15: ='04_Precio_variable'!C15+IF('04_Precio_variable'!I15="",0,'04_Precio_variable'!I15) | H15: =IF(F15="","",F15-G15) | I15: =COUNTIF($B$5:$B$18,B15) | J15: =IF(OR(H15="",I15<2),0,ABS(H15))
A16: C-10-1 | B16: C-10 | C16: =IF('03_Detalle'!I16<>"",'03_Detalle'!I16,'03_Detalle'!J16) | D16: =SUMIF($B$5:$B$18,B16,$C$5:$C$18) | E16: ='04_Precio_variable'!K16 | F16: =IF(D16=0,"",E16*C16/D16) | G16: ='04_Precio_variable'!C16+IF('04_Precio_variable'!I16="",0,'04_Precio_variable'!I16) | H16: =IF(F16="","",F16-G16) | I16: =COUNTIF($B$5:$B$18,B16) | J16: =IF(OR(H16="",I16<2),0,ABS(H16))
... A18: C-12-1 | B18: C-12 | C18: =IF('03_Detalle'!I18<>"",'03_Detalle'!I18,'03_Detalle'!J18) | D18: =SUMIF($B$5:$B$18,B18,$C$5:$C$18) | E18: ='04_Precio_variable'!K18 | F18: =IF(D18=0,"",E18*C18/D18) | G18: ='04_Precio_variable'!C18+IF('04_Precio_variable'!I18="",0,'04_Precio_variable'!I18) | H18: =IF(F18="","",F18-G18) | I18: =COUNTIF($B$5:$B$18,B18) | J18: =IF(OR(H18="",I18<2),0,ABS(H18))
A19: TOTAL | F19: =SUM(F5:F18) | G19: =SUM(G5:G18) | J19: =SUM(J5:J18)
A21: ⓘ Cómo se calcula esta hoja
A22: Columna | B22: Fórmula (Excel) | C22: Cómo se calcula (sencillo) | D22: Ejemplo con números reales | E22: De dónde viene | F22: Norma
A23: Precio independiente usado | B23: '=IF('03_Detalle'!I5<>"",'03_Detalle'!I5,'03_Detalle'!J5) | C23: Toma el precio de venta independiente de la línea (hoja 03); si el cliente no lo informó, usa el precio del contrato de esa misma hoja. | D23: Fila 1: IF(100.000,00<>""; 100.000,00; 90.000,00) → 100.000,00 | E23: hoja «Detalle por obligación» | F23: —
A24: Suma del contrato | B24: '=SUMIF($B$5:$B$18,B5,$C$5:$C$18) | C24: Suma los precios independientes usados de todas las líneas del mismo contrato en esta hoja. | D24: Fila 1: SUMIF([«Contrato», 14 filas]; «C-01»; [«Precio independiente usado», 14 filas]) → 125.000,00 | E24: «Contrato» (esta hoja), «Precio independiente usado» (esta hoja) | F24: —
A25: Precio de la transacción | B25: '='04_Precio_variable'!K5 | C25: Trae el precio de la transacción del contrato calculado en la hoja 04 (Precio y contraprestación variable). | D25: Fila 1: 100.000,00 → 100.000,00 | E25: hoja «Precio y contraprestación variable» | F25: —
A26: Asignado (relativo) | B26: '=IF(D5=0,"",E5*C5/D5) | C26: Reparte el precio de la transacción en proporción al precio independiente de la línea sobre la suma del contrato; en blanco si esa suma es cero. | D26: Fila 1: IF(125.000,00=0; ""; 100.000,00*100.000,00/125.000,00) → 80.000,00 | E26: «Suma del contrato» (esta hoja), «Precio de la transacción» (esta hoja), «Precio independiente usado» (esta hoja) | F26: —
A27: Asignación del cliente | B27: '='04_Precio_variable'!C5+IF('04_Precio_variable'!I5="",0,'04_Precio_variable'!I5) | C27: Suma el precio fijo y la variable que incluyó el cliente (hoja 04; si no la informó se toma cero): es lo que el cliente asignó a la línea. | D27: Fila 1: 90.000,00+IF((vacío)=""; 0; (vacío)) → 90.000,00 | E27: hoja «Precio y contraprestación variable» | F27: —
A28: Diferencia | B28: '=IF(F5="","",F5-G5) | C28: Resta la asignación del cliente del importe asignado por el auditor; en blanco si no se pudo asignar. | D28: Fila 1: IF(80.000,00=""; ""; 80.000,00-90.000,00) → -10.000,00 | E28: «Asignado (relativo)» (esta hoja), «Asignación del cliente» (esta hoja) | F28: —
A29: Obligaciones del contrato | B29: '=COUNTIF($B$5:$B$18,B5) | C29: Cuenta cuántas líneas (obligaciones) de esta hoja pertenecen al mismo contrato. | D29: Fila 1: COUNTIF([«Contrato», 14 filas]; «C-01») → 2 | E29: «Contrato» (esta hoja) | F29: —
A30: Diferencia absoluta | B30: '=IF(OR(H5="",I5<2),0,ABS(H5)) | C30: Muestra la diferencia de asignación sin signo, solo cuando el contrato tiene dos o más obligaciones; en contratos de una sola obligación pone cero. | D30: Fila 1: IF(OR(-10.000,00=""; 2<2); 0; ABS(-10.000,00)) → 10.000,00 | E30: «Diferencia» (esta hoja), «Obligaciones del contrato» (esta hoja) | F30: —

Sheet 06_Satisfaccion
A1: Satisfacción y porcentaje de avance | H1: ⟵ Inicio | I1: ◀ Anterior | J1: Siguiente ▶
A2: Ingresos · contratos con clientes (existencia, precio, asignación, satisfacción, corte y devoluciones) · Cliente de muestra S.A. · corte 2025-12-31
A4: Línea | B4: Modo | C4: Avance recalculado (costos) | D4: Avance del cliente | E4: Diferencia de avance | F4: Control transferido al corte | G4: Factor de satisfacción | H4: Reconocible bruto acumulado | I4: Pérdida esperada del contrato
A5: C-01-1 | B5: ='03_Detalle'!F5 | C5: =IF(B5="A lo largo del tiempo",IF(AND('03_Detalle'!N5<>"",N('03_Detalle'!O5)>0),MIN('03_Detalle'!N5/'03_Detalle'!O5,1),""),"") | D5: =IF('03_Detalle'!P5<>"",'03_Detalle'!P5/100,"") | E5: =IF(OR(C5="",D5=""),"",D5-C5) | F5: =IF(B5="A lo largo del tiempo","",IF('03_Detalle'!G5="","",IF('03_Detalle'!G5<='02_Parametros'!$B$5,"Sí","No"))) | G5: =IF('03_Detalle'!AB5="No",0,IF(B5="A lo largo del tiempo",C5,IF(F5="","",IF(F5="Sí",1,0)))) | H5: =IF(OR(G5="",'05_Asignacion'!F5=""),"",'05_Asignacion'!F5*G5) | I5: =IF(AND(B5="A lo largo del tiempo",'03_Detalle'!O5<>"",'05_Asignacion'!F5<>""),MAX('03_Detalle'!O5-'05_Asignacion'!F5,0),0)
A6: C-01-2 | B6: ='03_Detalle'!F6 | C6: =IF(B6="A lo largo del tiempo",IF(AND('03_Detalle'!N6<>"",N('03_Detalle'!O6)>0),MIN('03_Detalle'!N6/'03_Detalle'!O6,1),""),"") | D6: =IF('03_Detalle'!P6<>"",'03_Detalle'!P6/100,"") | E6: =IF(OR(C6="",D6=""),"",D6-C6) | F6: =IF(B6="A lo largo del tiempo","",IF('03_Detalle'!G6="","",IF('03_Detalle'!G6<='02_Parametros'!$B$5,"Sí","No"))) | G6: =IF('03_Detalle'!AB6="No",0,IF(B6="A lo largo del tiempo",C6,IF(F6="","",IF(F6="Sí",1,0)))) | H6: =IF(OR(G6="",'05_Asignacion'!F6=""),"",'05_Asignacion'!F6*G6) | I6: =IF(AND(B6="A lo largo del tiempo",'03_Detalle'!O6<>"",'05_Asignacion'!F6<>""),MAX('03_Detalle'!O6-'05_Asignacion'!F6,0),0)
A7: C-02-1 | B7: ='03_Detalle'!F7 | C7: =IF(B7="A lo largo del tiempo",IF(AND('03_Detalle'!N7<>"",N('03_Detalle'!O7)>0),MIN('03_Detalle'!N7/'03_Detalle'!O7,1),""),"") | D7: =IF('03_Detalle'!P7<>"",'03_Detalle'!P7/100,"") | E7: =IF(OR(C7="",D7=""),"",D7-C7) | F7: =IF(B7="A lo largo del tiempo","",IF('03_Detalle'!G7="","",IF('03_Detalle'!G7<='02_Parametros'!$B$5,"Sí","No"))) | G7: =IF('03_Detalle'!AB7="No",0,IF(B7="A lo largo del tiempo",C7,IF(F7="","",IF(F7="Sí",1,0)))) | H7: =IF(OR(G7="",'05_Asignacion'!F7=""),"",'05_Asignacion'!F7*G7) | I7: =IF(AND(B7="A lo largo del tiempo",'03_Detalle'!O7<>"",'05_Asignacion'!F7<>""),MAX('03_Detalle'!O7-'05_Asignacion'!F7,0),0)
A8: C-03-1 | B8: ='03_Detalle'!F8 | C8: =IF(B8="A lo largo del tiempo",IF(AND('03_Detalle'!N8<>"",N('03_Detalle'!O8)>0),MIN('03_Detalle'!N8/'03_Detalle'!O8,1),""),"") | D8: =IF('03_Detalle'!P8<>"",'03_Detalle'!P8/100,"") | E8: =IF(OR(C8="",D8=""),"",D8-C8) | F8: =IF(B8="A lo largo del tiempo","",IF('03_Detalle'!G8="","",IF('03_Detalle'!G8<='02_Parametros'!$B$5,"Sí","No"))) | G8: =IF('03_Detalle'!AB8="No",0,IF(B8="A lo largo del tiempo",C8,IF(F8="","",IF(F8="Sí",1,0)))) | H8: =IF(OR(G8="",'05_Asignacion'!F8=""),"",'05_Asignacion'!F8*G8) | I8: =IF(AND(B8="A lo largo del tiempo",'03_Detalle'!O8<>"",'05_Asignacion'!F8<>""),MAX('03_Detalle'!O8-'05_Asignacion'!F8,0),0)
A9: C-04-1 | B9: ='03_Detalle'!F9 | C9: =IF(B9="A lo largo del tiempo",IF(AND('03_Detalle'!N9<>"",N('03_Detalle'!O9)>0),MIN('03_Detalle'!N9/'03_Detalle'!O9,1),""),"") | D9: =IF('03_Detalle'!P9<>"",'03_Detalle'!P9/100,"") | E9: =IF(OR(C9="",D9=""),"",D9-C9) | F9: =IF(B9="A lo largo del tiempo","",IF('03_Detalle'!G9="","",IF('03_Detalle'!G9<='02_Parametros'!$B$5,"Sí","No"))) | G9: =IF('03_Detalle'!AB9="No",0,IF(B9="A lo largo del tiempo",C9,IF(F9="","",IF(F9="Sí",1,0)))) | H9: =IF(OR(G9="",'05_Asignacion'!F9=""),"",'05_Asignacion'!F9*G9) | I9: =IF(AND(B9="A lo largo del tiempo",'03_Detalle'!O9<>"",'05_Asignacion'!F9<>""),MAX('03_Detalle'!O9-'05_Asignacion'!F9,0),0)
A10: C-05-1 | B10: ='03_Detalle'!F10 | C10: =IF(B10="A lo largo del tiempo",IF(AND('03_Detalle'!N10<>"",N('03_Detalle'!O10)>0),MIN('03_Detalle'!N10/'03_Detalle'!O10,1),""),"") | D10: =IF('03_Detalle'!P10<>"",'03_Detalle'!P10/100,"") | E10: =IF(OR(C10="",D10=""),"",D10-C10) | F10: =IF(B10="A lo largo del tiempo","",IF('03_Detalle'!G10="","",IF('03_Detalle'!G10<='02_Parametros'!$B$5,"Sí","No"))) | G10: =IF('03_Detalle'!AB10="No",0,IF(B10="A lo largo del tiempo",C10,IF(F10="","",IF(F10="Sí",1,0)))) | H10: =IF(OR(G10="",'05_Asignacion'!F10=""),"",'05_Asignacion'!F10*G10) | I10: =IF(AND(B10="A lo largo del tiempo",'03_Detalle'!O10<>"",'05_Asignacion'!F10<>""),MAX('03_Detalle'!O10-'05_Asignacion'!F10,0),0)
A11: C-06-1 | B11: ='03_Detalle'!F11 | C11: =IF(B11="A lo largo del tiempo",IF(AND('03_Detalle'!N11<>"",N('03_Detalle'!O11)>0),MIN('03_Detalle'!N11/'03_Detalle'!O11,1),""),"") | D11: =IF('03_Detalle'!P11<>"",'03_Detalle'!P11/100,"") | E11: =IF(OR(C11="",D11=""),"",D11-C11) | F11: =IF(B11="A lo largo del tiempo","",IF('03_Detalle'!G11="","",IF('03_Detalle'!G11<='02_Parametros'!$B$5,"Sí","No"))) | G11: =IF('03_Detalle'!AB11="No",0,IF(B11="A lo largo del tiempo",C11,IF(F11="","",IF(F11="Sí",1,0)))) | H11: =IF(OR(G11="",'05_Asignacion'!F11=""),"",'05_Asignacion'!F11*G11) | I11: =IF(AND(B11="A lo largo del tiempo",'03_Detalle'!O11<>"",'05_Asignacion'!F11<>""),MAX('03_Detalle'!O11-'05_Asignacion'!F11,0),0)
A12: C-07-1 | B12: ='03_Detalle'!F12 | C12: =IF(B12="A lo largo del tiempo",IF(AND('03_Detalle'!N12<>"",N('03_Detalle'!O12)>0),MIN('03_Detalle'!N12/'03_Detalle'!O12,1),""),"") | D12: =IF('03_Detalle'!P12<>"",'03_Detalle'!P12/100,"") | E12: =IF(OR(C12="",D12=""),"",D12-C12) | F12: =IF(B12="A lo largo del tiempo","",IF('03_Detalle'!G12="","",IF('03_Detalle'!G12<='02_Parametros'!$B$5,"Sí","No"))) | G12: =IF('03_Detalle'!AB12="No",0,IF(B12="A lo largo del tiempo",C12,IF(F12="","",IF(F12="Sí",1,0)))) | H12: =IF(OR(G12="",'05_Asignacion'!F12=""),"",'05_Asignacion'!F12*G12) | I12: =IF(AND(B12="A lo largo del tiempo",'03_Detalle'!O12<>"",'05_Asignacion'!F12<>""),MAX('03_Detalle'!O12-'05_Asignacion'!F12,0),0)
A13: C-08-1 | B13: ='03_Detalle'!F13 | C13: =IF(B13="A lo largo del tiempo",IF(AND('03_Detalle'!N13<>"",N('03_Detalle'!O13)>0),MIN('03_Detalle'!N13/'03_Detalle'!O13,1),""),"") | D13: =IF('03_Detalle'!P13<>"",'03_Detalle'!P13/100,"") | E13: =IF(OR(C13="",D13=""),"",D13-C13) | F13: =IF(B13="A lo largo del tiempo","",IF('03_Detalle'!G13="","",IF('03_Detalle'!G13<='02_Parametros'!$B$5,"Sí","No"))) | G13: =IF('03_Detalle'!AB13="No",0,IF(B13="A lo largo del tiempo",C13,IF(F13="","",IF(F13="Sí",1,0)))) | H13: =IF(OR(G13="",'05_Asignacion'!F13=""),"",'05_Asignacion'!F13*G13) | I13: =IF(AND(B13="A lo largo del tiempo",'03_Detalle'!O13<>"",'05_Asignacion'!F13<>""),MAX('03_Detalle'!O13-'05_Asignacion'!F13,0),0)
A14: C-09-1 | B14: ='03_Detalle'!F14 | C14: =IF(B14="A lo largo del tiempo",IF(AND('03_Detalle'!N14<>"",N('03_Detalle'!O14)>0),MIN('03_Detalle'!N14/'03_Detalle'!O14,1),""),"") | D14: =IF('03_Detalle'!P14<>"",'03_Detalle'!P14/100,"") | E14: =IF(OR(C14="",D14=""),"",D14-C14) | F14: =IF(B14="A lo largo del tiempo","",IF('03_Detalle'!G14="","",IF('03_Detalle'!G14<='02_Parametros'!$B$5,"Sí","No"))) | G14: =IF('03_Detalle'!AB14="No",0,IF(B14="A lo largo del tiempo",C14,IF(F14="","",IF(F14="Sí",1,0)))) | H14: =IF(OR(G14="",'05_Asignacion'!F14=""),"",'05_Asignacion'!F14*G14) | I14: =IF(AND(B14="A lo largo del tiempo",'03_Detalle'!O14<>"",'05_Asignacion'!F14<>""),MAX('03_Detalle'!O14-'05_Asignacion'!F14,0),0)
A15: C-09-2 | B15: ='03_Detalle'!F15 | C15: =IF(B15="A lo largo del tiempo",IF(AND('03_Detalle'!N15<>"",N('03_Detalle'!O15)>0),MIN('03_Detalle'!N15/'03_Detalle'!O15,1),""),"") | D15: =IF('03_Detalle'!P15<>"",'03_Detalle'!P15/100,"") | E15: =IF(OR(C15="",D15=""),"",D15-C15) | F15: =IF(B15="A lo largo del tiempo","",IF('03_Detalle'!G15="","",IF('03_Detalle'!G15<='02_Parametros'!$B$5,"Sí","No"))) | G15: =IF('03_Detalle'!AB15="No",0,IF(B15="A lo largo del tiempo",C15,IF(F15="","",IF(F15="Sí",1,0)))) | H15: =IF(OR(G15="",'05_Asignacion'!F15=""),"",'05_Asignacion'!F15*G15) | I15: =IF(AND(B15="A lo largo del tiempo",'03_Detalle'!O15<>"",'05_Asignacion'!F15<>""),MAX('03_Detalle'!O15-'05_Asignacion'!F15,0),0)
A16: C-10-1 | B16: ='03_Detalle'!F16 | C16: =IF(B16="A lo largo del tiempo",IF(AND('03_Detalle'!N16<>"",N('03_Detalle'!O16)>0),MIN('03_Detalle'!N16/'03_Detalle'!O16,1),""),"") | D16: =IF('03_Detalle'!P16<>"",'03_Detalle'!P16/100,"") | E16: =IF(OR(C16="",D16=""),"",D16-C16) | F16: =IF(B16="A lo largo del tiempo","",IF('03_Detalle'!G16="","",IF('03_Detalle'!G16<='02_Parametros'!$B$5,"Sí","No"))) | G16: =IF('03_Detalle'!AB16="No",0,IF(B16="A lo largo del tiempo",C16,IF(F16="","",IF(F16="Sí",1,0)))) | H16: =IF(OR(G16="",'05_Asignacion'!F16=""),"",'05_Asignacion'!F16*G16) | I16: =IF(AND(B16="A lo largo del tiempo",'03_Detalle'!O16<>"",'05_Asignacion'!F16<>""),MAX('03_Detalle'!O16-'05_Asignacion'!F16,0),0)
... A18: C-12-1 | B18: ='03_Detalle'!F18 | C18: =IF(B18="A lo largo del tiempo",IF(AND('03_Detalle'!N18<>"",N('03_Detalle'!O18)>0),MIN('03_Detalle'!N18/'03_Detalle'!O18,1),""),"") | D18: =IF('03_Detalle'!P18<>"",'03_Detalle'!P18/100,"") | E18: =IF(OR(C18="",D18=""),"",D18-C18) | F18: =IF(B18="A lo largo del tiempo","",IF('03_Detalle'!G18="","",IF('03_Detalle'!G18<='02_Parametros'!$B$5,"Sí","No"))) | G18: =IF('03_Detalle'!AB18="No",0,IF(B18="A lo largo del tiempo",C18,IF(F18="","",IF(F18="Sí",1,0)))) | H18: =IF(OR(G18="",'05_Asignacion'!F18=""),"",'05_Asignacion'!F18*G18) | I18: =IF(AND(B18="A lo largo del tiempo",'03_Detalle'!O18<>"",'05_Asignacion'!F18<>""),MAX('03_Detalle'!O18-'05_Asignacion'!F18,0),0)
A19: TOTAL | H19: =SUM(H5:H18) | I19: =SUM(I5:I18)
A21: ⓘ Cómo se calcula esta hoja
A22: Columna | B22: Fórmula (Excel) | C22: Cómo se calcula (sencillo) | D22: Ejemplo con números reales | E22: De dónde viene | F22: Norma
A23: Modo | B23: '='03_Detalle'!F5 | C23: Trae si la obligación se satisface en un momento o a lo largo del tiempo, según la hoja 03 (Detalle). | D23: Fila 1: «En un momento» → En un momento | E23: hoja «Detalle por obligación» | F23: —
A24: Avance recalculado (costos) | B24: '=IF(B5="A lo largo del tiempo",IF(AND('03_Detalle'!N5<>"",N('03_Detalle'!O5)>0),MIN('03_Detalle'!N5/'03_Detalle'!O5,1),""),"") | C24: Solo para obligaciones a lo largo del tiempo: divide los costos incurridos para los costos totales estimados de la hoja 03, con tope de 100 %; en blanco si faltan costos o si la obligación se satisface en un momento. | D24: Fila 1: IF(«En un momento»="A lo largo del tiempo"; IF(AND((vacío)<>""; N((vacío))>0); MIN((vacío)/(vacío); 1); ""); "") → (en blanco) | E24: «Modo» (esta hoja), hoja «Detalle por obligación» | F24: —
A25: Avance del cliente | B25: '=IF('03_Detalle'!P5<>"",'03_Detalle'!P5/100,"") | C25: Trae el porcentaje de avance que informó el cliente en la hoja 03; en blanco si no lo informó. | D25: Fila 1: IF((vacío)<>""; (vacío)/100; "") → (en blanco) | E25: hoja «Detalle por obligación» | F25: —
A26: Diferencia de avance | B26: '=IF(OR(C5="",D5=""),"",D5-C5) | C26: Resta el avance recalculado del avance del cliente; en blanco si falta cualquiera de los dos. | D26: Fila 1: IF(OR((vacío)=""; (vacío)=""); ""; (vacío)-(vacío)) → (en blanco) | E26: «Avance recalculado (costos)» (esta hoja), «Avance del cliente» (esta hoja) | F26: —
A27: Control transferido al corte | B27: '=IF(B5="A lo largo del tiempo","",IF('03_Detalle'!G5="","",IF('03_Detalle'!G5<='02_Parametros'!$B$5,"Sí","No"))) | C27: Solo para obligaciones en un momento: «Sí» si la fecha de transferencia del control (hoja 03) es igual o anterior al corte de la hoja 02 y «No» si es posterior; en blanco si falta la fecha. | D27: Fila 1: IF(«En un momento»="A lo largo del tiempo"; ""; IF(«2025-11-15»=""; ""; IF(«2025-11-15»<=«2025-12-31»; "Sí"; "No"))) → Sí | E27: «Modo» (esta hoja), hoja «Detalle por obligación», hoja «Parámetros» | F27: —
A28: Factor de satisfacción | B28: '=IF('03_Detalle'!AB5="No",0,IF(B5="A lo largo del tiempo",C5,IF(F5="","",IF(F5="Sí",1,0)))) | C28: Indica qué parte de la obligación está cumplida: cero si el contrato no es válido (hoja 03); el avance recalculado si es a lo largo del tiempo; 1 o 0 según se haya transferido el control si es en un momento. | D28: Fila 1: IF(«Sí»="No"; 0; IF(«En un momento»="A lo largo del tiempo"; (vacío); IF(«Sí»=""; ""; IF(«Sí»="Sí"; 1; 0)))) → 100,00 % | E28: «Modo» (esta hoja), «Avance recalculado (costos)» (esta hoja), «Control transferido al corte» (esta hoja), hoja «Detalle por obligación» | F28: —
A29: Reconocible bruto acumulado | B29: '=IF(OR(G5="",'05_Asignacion'!F5=""),"",'05_Asignacion'!F5*G5) | C29: Multiplica el importe asignado de la hoja 05 (Asignación) por el factor de satisfacción; en blanco si falta alguno de los dos. | D29: Fila 1: IF(OR(100,00 %=""; 80.000,00=""); ""; 80.000,00*100,00 %) → 80.000,00 | E29: «Factor de satisfacción» (esta hoja), hoja «Asignación del precio» | F29: —
A30: Pérdida esperada del contrato | B30: '=IF(AND(B5="A lo largo del tiempo",'03_Detalle'!O5<>"",'05_Asignacion'!F5<>""),MAX('03_Detalle'!O5-'05_Asignacion'!F5,0),0) | C30: Para obligaciones a lo largo del tiempo, resta el importe asignado (hoja 05) de los costos totales estimados (hoja 03); si los costos no lo superan, pone cero. | D30: Fila 1: IF(AND(«En un momento»="A lo largo del tiempo"; (vacío)<>""; 80.000,00<>""); MAX((vacío)-80.000,00; 0); 0) → 0,00 | E30: «Modo» (esta hoja), hoja «Detalle por obligación», hoja «Asignación del precio» | F30: —

Sheet 07_Devoluciones
A1: Devoluciones y notas de crédito | H1: ⟵ Inicio | I1: ◀ Anterior | J1: Siguiente ▶
A2: Ingresos · contratos con clientes (existencia, precio, asignación, satisfacción, corte y devoluciones) · Cliente de muestra S.A. · corte 2025-12-31
A4: Línea | B4: Reconocible bruto | C4: Devolución esperada | D4: Pasivo por reembolso | E4: Reconocible neto de devoluciones | F4: NC posteriores al cierre | G4: NC no provisionadas | H4: Costo de los bienes vendidos | I4: Activo por derecho a recuperar productos
A5: C-01-1 | B5: ='06_Satisfaccion'!H5 | C5: =IF('03_Detalle'!V5<>"",'03_Detalle'!V5/100,0) | D5: =IF(B5="","",B5*C5) | E5: =IF(B5="","",B5-D5) | F5: =IF('03_Detalle'!W5<>"",'03_Detalle'!W5,"") | G5: =IF(F5="",0,MAX(F5-N(D5),0)) | H5: =IF('03_Detalle'!AA5<>"",'03_Detalle'!AA5,"") | I5: =IF('02_Parametros'!$B$15="No",0,IF(C5=0,0,IF(OR(H5="",D5=""),"",H5*C5)))
A6: C-01-2 | B6: ='06_Satisfaccion'!H6 | C6: =IF('03_Detalle'!V6<>"",'03_Detalle'!V6/100,0) | D6: =IF(B6="","",B6*C6) | E6: =IF(B6="","",B6-D6) | F6: =IF('03_Detalle'!W6<>"",'03_Detalle'!W6,"") | G6: =IF(F6="",0,MAX(F6-N(D6),0)) | H6: =IF('03_Detalle'!AA6<>"",'03_Detalle'!AA6,"") | I6: =IF('02_Parametros'!$B$15="No",0,IF(C6=0,0,IF(OR(H6="",D6=""),"",H6*C6)))
A7: C-02-1 | B7: ='06_Satisfaccion'!H7 | C7: =IF('03_Detalle'!V7<>"",'03_Detalle'!V7/100,0) | D7: =IF(B7="","",B7*C7) | E7: =IF(B7="","",B7-D7) | F7: =IF('03_Detalle'!W7<>"",'03_Detalle'!W7,"") | G7: =IF(F7="",0,MAX(F7-N(D7),0)) | H7: =IF('03_Detalle'!AA7<>"",'03_Detalle'!AA7,"") | I7: =IF('02_Parametros'!$B$15="No",0,IF(C7=0,0,IF(OR(H7="",D7=""),"",H7*C7)))
A8: C-03-1 | B8: ='06_Satisfaccion'!H8 | C8: =IF('03_Detalle'!V8<>"",'03_Detalle'!V8/100,0) | D8: =IF(B8="","",B8*C8) | E8: =IF(B8="","",B8-D8) | F8: =IF('03_Detalle'!W8<>"",'03_Detalle'!W8,"") | G8: =IF(F8="",0,MAX(F8-N(D8),0)) | H8: =IF('03_Detalle'!AA8<>"",'03_Detalle'!AA8,"") | I8: =IF('02_Parametros'!$B$15="No",0,IF(C8=0,0,IF(OR(H8="",D8=""),"",H8*C8)))
A9: C-04-1 | B9: ='06_Satisfaccion'!H9 | C9: =IF('03_Detalle'!V9<>"",'03_Detalle'!V9/100,0) | D9: =IF(B9="","",B9*C9) | E9: =IF(B9="","",B9-D9) | F9: =IF('03_Detalle'!W9<>"",'03_Detalle'!W9,"") | G9: =IF(F9="",0,MAX(F9-N(D9),0)) | H9: =IF('03_Detalle'!AA9<>"",'03_Detalle'!AA9,"") | I9: =IF('02_Parametros'!$B$15="No",0,IF(C9=0,0,IF(OR(H9="",D9=""),"",H9*C9)))
A10: C-05-1 | B10: ='06_Satisfaccion'!H10 | C10: =IF('03_Detalle'!V10<>"",'03_Detalle'!V10/100,0) | D10: =IF(B10="","",B10*C10) | E10: =IF(B10="","",B10-D10) | F10: =IF('03_Detalle'!W10<>"",'03_Detalle'!W10,"") | G10: =IF(F10="",0,MAX(F10-N(D10),0)) | H10: =IF('03_Detalle'!AA10<>"",'03_Detalle'!AA10,"") | I10: =IF('02_Parametros'!$B$15="No",0,IF(C10=0,0,IF(OR(H10="",D10=""),"",H10*C10)))
A11: C-06-1 | B11: ='06_Satisfaccion'!H11 | C11: =IF('03_Detalle'!V11<>"",'03_Detalle'!V11/100,0) | D11: =IF(B11="","",B11*C11) | E11: =IF(B11="","",B11-D11) | F11: =IF('03_Detalle'!W11<>"",'03_Detalle'!W11,"") | G11: =IF(F11="",0,MAX(F11-N(D11),0)) | H11: =IF('03_Detalle'!AA11<>"",'03_Detalle'!AA11,"") | I11: =IF('02_Parametros'!$B$15="No",0,IF(C11=0,0,IF(OR(H11="",D11=""),"",H11*C11)))
A12: C-07-1 | B12: ='06_Satisfaccion'!H12 | C12: =IF('03_Detalle'!V12<>"",'03_Detalle'!V12/100,0) | D12: =IF(B12="","",B12*C12) | E12: =IF(B12="","",B12-D12) | F12: =IF('03_Detalle'!W12<>"",'03_Detalle'!W12,"") | G12: =IF(F12="",0,MAX(F12-N(D12),0)) | H12: =IF('03_Detalle'!AA12<>"",'03_Detalle'!AA12,"") | I12: =IF('02_Parametros'!$B$15="No",0,IF(C12=0,0,IF(OR(H12="",D12=""),"",H12*C12)))
A13: C-08-1 | B13: ='06_Satisfaccion'!H13 | C13: =IF('03_Detalle'!V13<>"",'03_Detalle'!V13/100,0) | D13: =IF(B13="","",B13*C13) | E13: =IF(B13="","",B13-D13) | F13: =IF('03_Detalle'!W13<>"",'03_Detalle'!W13,"") | G13: =IF(F13="",0,MAX(F13-N(D13),0)) | H13: =IF('03_Detalle'!AA13<>"",'03_Detalle'!AA13,"") | I13: =IF('02_Parametros'!$B$15="No",0,IF(C13=0,0,IF(OR(H13="",D13=""),"",H13*C13)))
A14: C-09-1 | B14: ='06_Satisfaccion'!H14 | C14: =IF('03_Detalle'!V14<>"",'03_Detalle'!V14/100,0) | D14: =IF(B14="","",B14*C14) | E14: =IF(B14="","",B14-D14) | F14: =IF('03_Detalle'!W14<>"",'03_Detalle'!W14,"") | G14: =IF(F14="",0,MAX(F14-N(D14),0)) | H14: =IF('03_Detalle'!AA14<>"",'03_Detalle'!AA14,"") | I14: =IF('02_Parametros'!$B$15="No",0,IF(C14=0,0,IF(OR(H14="",D14=""),"",H14*C14)))
A15: C-09-2 | B15: ='06_Satisfaccion'!H15 | C15: =IF('03_Detalle'!V15<>"",'03_Detalle'!V15/100,0) | D15: =IF(B15="","",B15*C15) | E15: =IF(B15="","",B15-D15) | F15: =IF('03_Detalle'!W15<>"",'03_Detalle'!W15,"") | G15: =IF(F15="",0,MAX(F15-N(D15),0)) | H15: =IF('03_Detalle'!AA15<>"",'03_Detalle'!AA15,"") | I15: =IF('02_Parametros'!$B$15="No",0,IF(C15=0,0,IF(OR(H15="",D15=""),"",H15*C15)))
A16: C-10-1 | B16: ='06_Satisfaccion'!H16 | C16: =IF('03_Detalle'!V16<>"",'03_Detalle'!V16/100,0) | D16: =IF(B16="","",B16*C16) | E16: =IF(B16="","",B16-D16) | F16: =IF('03_Detalle'!W16<>"",'03_Detalle'!W16,"") | G16: =IF(F16="",0,MAX(F16-N(D16),0)) | H16: =IF('03_Detalle'!AA16<>"",'03_Detalle'!AA16,"") | I16: =IF('02_Parametros'!$B$15="No",0,IF(C16=0,0,IF(OR(H16="",D16=""),"",H16*C16)))
... A18: C-12-1 | B18: ='06_Satisfaccion'!H18 | C18: =IF('03_Detalle'!V18<>"",'03_Detalle'!V18/100,0) | D18: =IF(B18="","",B18*C18) | E18: =IF(B18="","",B18-D18) | F18: =IF('03_Detalle'!W18<>"",'03_Detalle'!W18,"") | G18: =IF(F18="",0,MAX(F18-N(D18),0)) | H18: =IF('03_Detalle'!AA18<>"",'03_Detalle'!AA18,"") | I18: =IF('02_Parametros'!$B$15="No",0,IF(C18=0,0,IF(OR(H18="",D18=""),"",H18*C18)))
A19: TOTAL | B19: =SUM(B5:B18) | D19: =SUM(D5:D18) | E19: =SUM(E5:E18) | F19: =SUM(F5:F18) | G19: =SUM(G5:G18) | H19: =SUM(H5:H18) | I19: =SUM(I5:I18)
A21: ⓘ Cómo se calcula esta hoja
A22: Columna | B22: Fórmula (Excel) | C22: Cómo se calcula (sencillo) | D22: Ejemplo con números reales | E22: De dónde viene | F22: Norma
A23: Reconocible bruto | B23: '='06_Satisfaccion'!H5 | C23: Trae el reconocible bruto acumulado de la línea calculado en la hoja 06 (Satisfacción). | D23: Fila 1: 80.000,00 → 80.000,00 | E23: hoja «Satisfacción y porcentaje de avance» | F23: —
A24: Devolución esperada | B24: '=IF('03_Detalle'!V5<>"",'03_Detalle'!V5/100,0) | C24: Trae el porcentaje de devoluciones esperadas de la hoja 03; si no se informó, se toma cero. | D24: Fila 1: IF((vacío)<>""; (vacío)/100; 0) → 0,00 % | E24: hoja «Detalle por obligación» | F24: —
A25: Pasivo por reembolso | B25: '=IF(B5="","",B5*C5) | C25: Multiplica el reconocible bruto por el porcentaje de devolución esperada: es lo que se espera devolver al cliente. En blanco si el bruto no se pudo medir. | D25: Fila 1: IF(80.000,00=""; ""; 80.000,00*0,00 %) → 0,00 | E25: «Reconocible bruto» (esta hoja), «Devolución esperada» (esta hoja) | F25: —
A26: Reconocible neto de devoluciones | B26: '=IF(B5="","",B5-D5) | C26: Resta el pasivo por reembolso del reconocible bruto de la línea. | D26: Fila 1: IF(80.000,00=""; ""; 80.000,00-0,00) → 80.000,00 | E26: «Reconocible bruto» (esta hoja), «Pasivo por reembolso» (esta hoja) | F26: —
A27: NC posteriores al cierre | B27: '=IF('03_Detalle'!W5<>"",'03_Detalle'!W5,"") | C27: Trae las notas de crédito emitidas después del cierre para la línea (hoja 03); en blanco si no hay. | D27: Fila 1: IF((vacío)<>""; (vacío); "") → (en blanco) | E27: hoja «Detalle por obligación» | F27: —
A28: NC no provisionadas | B28: '=IF(F5="",0,MAX(F5-N(D5),0)) | C28: Resta el pasivo por reembolso de las notas de crédito posteriores; lo que exceda es devolución no provisionada (cero si no hay notas o si el pasivo las cubre). | D28: Fila 1: IF((vacío)=""; 0; MAX((vacío)-N(0,00); 0)) → 0,00 | E28: «NC posteriores al cierre» (esta hoja), «Pasivo por reembolso» (esta hoja) | F28: —
A29: Costo de los bienes vendidos | B29: '=IF('03_Detalle'!AA5<>"",'03_Detalle'!AA5,"") | C29: Trae el costo de los bienes vendidos de la línea informado en la hoja 03; en blanco si no se informó. | D29: Fila 1: IF((vacío)<>""; (vacío); "") → (en blanco) | E29: hoja «Detalle por obligación» | F29: —
A30: Activo por derecho a recuperar productos | B30: '=IF('02_Parametros'!$B$15="No",0,IF(C5=0,0,IF(OR(H5="",D5=""),"",H5*C5))) | C30: Multiplica el costo de los bienes vendidos por el porcentaje de devolución esperada. Es cero si la hoja 02 indica que el marco no lo reconoce o si no hay devoluciones; en blanco si falta el costo o el pasivo por reembolso. | D30: Fila 1: IF(«Sí»="No"; 0; IF(0,00 %=0; 0; IF(OR((vacío)=""; 0,00=""); ""; (vacío)*0,00 %))) → 0,00 | E30: «Devolución esperada» (esta hoja), «Costo de los bienes vendidos» (esta hoja), «Pasivo por reembolso» (esta hoja), hoja «Parámetros» | F30: —

Sheet 08_Financiacion
A1: Componente de financiación | H1: ⟵ Inicio | I1: ◀ Anterior | J1: Siguiente ▶
A2: Ingresos · contratos con clientes (existencia, precio, asignación, satisfacción, corte y devoluciones) · Cliente de muestra S.A. · corte 2025-12-31
A4: Línea | B4: Reconocible neto | C4: Plazo de cobro (meses) | D4: Financiación significativa | E4: Tasa anual | F4: Valor presente (ingreso ordinario) | G4: Componente de financiación | H4: Días devengados | I4: Interés devengado al corte
A5: C-01-1 | B5: ='07_Devoluciones'!E5 | C5: =IF('03_Detalle'!U5<>"",'03_Detalle'!U5,"") | D5: =IF(AND(C5<>"",N(C5)>'02_Parametros'!$B$9),"Sí","No") | E5: =IF('02_Parametros'!$B$8="","",'02_Parametros'!$B$8/100) | F5: =IF(B5="","",IF(D5="Sí",IF(E5="",B5,B5/(1+E5)^(C5/12)),B5)) | G5: =IF(B5="","",IF(D5="No",0,IF(E5="","",B5-F5))) | H5: =IF(AND(D5="Sí",'03_Detalle'!G5<>""),MAX(MIN('02_Parametros'!$B$5-'03_Detalle'!G5,C5*365/12),0),0) | I5: =IF(G5="","",IF(G5=0,0,F5*((1+E5)^(H5/365)-1)))
A6: C-01-2 | B6: ='07_Devoluciones'!E6 | C6: =IF('03_Detalle'!U6<>"",'03_Detalle'!U6,"") | D6: =IF(AND(C6<>"",N(C6)>'02_Parametros'!$B$9),"Sí","No") | E6: =IF('02_Parametros'!$B$8="","",'02_Parametros'!$B$8/100) | F6: =IF(B6="","",IF(D6="Sí",IF(E6="",B6,B6/(1+E6)^(C6/12)),B6)) | G6: =IF(B6="","",IF(D6="No",0,IF(E6="","",B6-F6))) | H6: =IF(AND(D6="Sí",'03_Detalle'!G6<>""),MAX(MIN('02_Parametros'!$B$5-'03_Detalle'!G6,C6*365/12),0),0) | I6: =IF(G6="","",IF(G6=0,0,F6*((1+E6)^(H6/365)-1)))
A7: C-02-1 | B7: ='07_Devoluciones'!E7 | C7: =IF('03_Detalle'!U7<>"",'03_Detalle'!U7,"") | D7: =IF(AND(C7<>"",N(C7)>'02_Parametros'!$B$9),"Sí","No") | E7: =IF('02_Parametros'!$B$8="","",'02_Parametros'!$B$8/100) | F7: =IF(B7="","",IF(D7="Sí",IF(E7="",B7,B7/(1+E7)^(C7/12)),B7)) | G7: =IF(B7="","",IF(D7="No",0,IF(E7="","",B7-F7))) | H7: =IF(AND(D7="Sí",'03_Detalle'!G7<>""),MAX(MIN('02_Parametros'!$B$5-'03_Detalle'!G7,C7*365/12),0),0) | I7: =IF(G7="","",IF(G7=0,0,F7*((1+E7)^(H7/365)-1)))
A8: C-03-1 | B8: ='07_Devoluciones'!E8 | C8: =IF('03_Detalle'!U8<>"",'03_Detalle'!U8,"") | D8: =IF(AND(C8<>"",N(C8)>'02_Parametros'!$B$9),"Sí","No") | E8: =IF('02_Parametros'!$B$8="","",'02_Parametros'!$B$8/100) | F8: =IF(B8="","",IF(D8="Sí",IF(E8="",B8,B8/(1+E8)^(C8/12)),B8)) | G8: =IF(B8="","",IF(D8="No",0,IF(E8="","",B8-F8))) | H8: =IF(AND(D8="Sí",'03_Detalle'!G8<>""),MAX(MIN('02_Parametros'!$B$5-'03_Detalle'!G8,C8*365/12),0),0) | I8: =IF(G8="","",IF(G8=0,0,F8*((1+E8)^(H8/365)-1)))
A9: C-04-1 | B9: ='07_Devoluciones'!E9 | C9: =IF('03_Detalle'!U9<>"",'03_Detalle'!U9,"") | D9: =IF(AND(C9<>"",N(C9)>'02_Parametros'!$B$9),"Sí","No") | E9: =IF('02_Parametros'!$B$8="","",'02_Parametros'!$B$8/100) | F9: =IF(B9="","",IF(D9="Sí",IF(E9="",B9,B9/(1+E9)^(C9/12)),B9)) | G9: =IF(B9="","",IF(D9="No",0,IF(E9="","",B9-F9))) | H9: =IF(AND(D9="Sí",'03_Detalle'!G9<>""),MAX(MIN('02_Parametros'!$B$5-'03_Detalle'!G9,C9*365/12),0),0) | I9: =IF(G9="","",IF(G9=0,0,F9*((1+E9)^(H9/365)-1)))
A10: C-05-1 | B10: ='07_Devoluciones'!E10 | C10: =IF('03_Detalle'!U10<>"",'03_Detalle'!U10,"") | D10: =IF(AND(C10<>"",N(C10)>'02_Parametros'!$B$9),"Sí","No") | E10: =IF('02_Parametros'!$B$8="","",'02_Parametros'!$B$8/100) | F10: =IF(B10="","",IF(D10="Sí",IF(E10="",B10,B10/(1+E10)^(C10/12)),B10)) | G10: =IF(B10="","",IF(D10="No",0,IF(E10="","",B10-F10))) | H10: =IF(AND(D10="Sí",'03_Detalle'!G10<>""),MAX(MIN('02_Parametros'!$B$5-'03_Detalle'!G10,C10*365/12),0),0) | I10: =IF(G10="","",IF(G10=0,0,F10*((1+E10)^(H10/365)-1)))
A11: C-06-1 | B11: ='07_Devoluciones'!E11 | C11: =IF('03_Detalle'!U11<>"",'03_Detalle'!U11,"") | D11: =IF(AND(C11<>"",N(C11)>'02_Parametros'!$B$9),"Sí","No") | E11: =IF('02_Parametros'!$B$8="","",'02_Parametros'!$B$8/100) | F11: =IF(B11="","",IF(D11="Sí",IF(E11="",B11,B11/(1+E11)^(C11/12)),B11)) | G11: =IF(B11="","",IF(D11="No",0,IF(E11="","",B11-F11))) | H11: =IF(AND(D11="Sí",'03_Detalle'!G11<>""),MAX(MIN('02_Parametros'!$B$5-'03_Detalle'!G11,C11*365/12),0),0) | I11: =IF(G11="","",IF(G11=0,0,F11*((1+E11)^(H11/365)-1)))
A12: C-07-1 | B12: ='07_Devoluciones'!E12 | C12: =IF('03_Detalle'!U12<>"",'03_Detalle'!U12,"") | D12: =IF(AND(C12<>"",N(C12)>'02_Parametros'!$B$9),"Sí","No") | E12: =IF('02_Parametros'!$B$8="","",'02_Parametros'!$B$8/100) | F12: =IF(B12="","",IF(D12="Sí",IF(E12="",B12,B12/(1+E12)^(C12/12)),B12)) | G12: =IF(B12="","",IF(D12="No",0,IF(E12="","",B12-F12))) | H12: =IF(AND(D12="Sí",'03_Detalle'!G12<>""),MAX(MIN('02_Parametros'!$B$5-'03_Detalle'!G12,C12*365/12),0),0) | I12: =IF(G12="","",IF(G12=0,0,F12*((1+E12)^(H12/365)-1)))
A13: C-08-1 | B13: ='07_Devoluciones'!E13 | C13: =IF('03_Detalle'!U13<>"",'03_Detalle'!U13,"") | D13: =IF(AND(C13<>"",N(C13)>'02_Parametros'!$B$9),"Sí","No") | E13: =IF('02_Parametros'!$B$8="","",'02_Parametros'!$B$8/100) | F13: =IF(B13="","",IF(D13="Sí",IF(E13="",B13,B13/(1+E13)^(C13/12)),B13)) | G13: =IF(B13="","",IF(D13="No",0,IF(E13="","",B13-F13))) | H13: =IF(AND(D13="Sí",'03_Detalle'!G13<>""),MAX(MIN('02_Parametros'!$B$5-'03_Detalle'!G13,C13*365/12),0),0) | I13: =IF(G13="","",IF(G13=0,0,F13*((1+E13)^(H13/365)-1)))
A14: C-09-1 | B14: ='07_Devoluciones'!E14 | C14: =IF('03_Detalle'!U14<>"",'03_Detalle'!U14,"") | D14: =IF(AND(C14<>"",N(C14)>'02_Parametros'!$B$9),"Sí","No") | E14: =IF('02_Parametros'!$B$8="","",'02_Parametros'!$B$8/100) | F14: =IF(B14="","",IF(D14="Sí",IF(E14="",B14,B14/(1+E14)^(C14/12)),B14)) | G14: =IF(B14="","",IF(D14="No",0,IF(E14="","",B14-F14))) | H14: =IF(AND(D14="Sí",'03_Detalle'!G14<>""),MAX(MIN('02_Parametros'!$B$5-'03_Detalle'!G14,C14*365/12),0),0) | I14: =IF(G14="","",IF(G14=0,0,F14*((1+E14)^(H14/365)-1)))
A15: C-09-2 | B15: ='07_Devoluciones'!E15 | C15: =IF('03_Detalle'!U15<>"",'03_Detalle'!U15,"") | D15: =IF(AND(C15<>"",N(C15)>'02_Parametros'!$B$9),"Sí","No") | E15: =IF('02_Parametros'!$B$8="","",'02_Parametros'!$B$8/100) | F15: =IF(B15="","",IF(D15="Sí",IF(E15="",B15,B15/(1+E15)^(C15/12)),B15)) | G15: =IF(B15="","",IF(D15="No",0,IF(E15="","",B15-F15))) | H15: =IF(AND(D15="Sí",'03_Detalle'!G15<>""),MAX(MIN('02_Parametros'!$B$5-'03_Detalle'!G15,C15*365/12),0),0) | I15: =IF(G15="","",IF(G15=0,0,F15*((1+E15)^(H15/365)-1)))
A16: C-10-1 | B16: ='07_Devoluciones'!E16 | C16: =IF('03_Detalle'!U16<>"",'03_Detalle'!U16,"") | D16: =IF(AND(C16<>"",N(C16)>'02_Parametros'!$B$9),"Sí","No") | E16: =IF('02_Parametros'!$B$8="","",'02_Parametros'!$B$8/100) | F16: =IF(B16="","",IF(D16="Sí",IF(E16="",B16,B16/(1+E16)^(C16/12)),B16)) | G16: =IF(B16="","",IF(D16="No",0,IF(E16="","",B16-F16))) | H16: =IF(AND(D16="Sí",'03_Detalle'!G16<>""),MAX(MIN('02_Parametros'!$B$5-'03_Detalle'!G16,C16*365/12),0),0) | I16: =IF(G16="","",IF(G16=0,0,F16*((1+E16)^(H16/365)-1)))
... A18: C-12-1 | B18: ='07_Devoluciones'!E18 | C18: =IF('03_Detalle'!U18<>"",'03_Detalle'!U18,"") | D18: =IF(AND(C18<>"",N(C18)>'02_Parametros'!$B$9),"Sí","No") | E18: =IF('02_Parametros'!$B$8="","",'02_Parametros'!$B$8/100) | F18: =IF(B18="","",IF(D18="Sí",IF(E18="",B18,B18/(1+E18)^(C18/12)),B18)) | G18: =IF(B18="","",IF(D18="No",0,IF(E18="","",B18-F18))) | H18: =IF(AND(D18="Sí",'03_Detalle'!G18<>""),MAX(MIN('02_Parametros'!$B$5-'03_Detalle'!G18,C18*365/12),0),0) | I18: =IF(G18="","",IF(G18=0,0,F18*((1+E18)^(H18/365)-1)))
A19: TOTAL | B19: =SUM(B5:B18) | F19: =SUM(F5:F18) | G19: =SUM(G5:G18) | I19: =SUM(I5:I18)
A21: ⓘ Cómo se calcula esta hoja
A22: Columna | B22: Fórmula (Excel) | C22: Cómo se calcula (sencillo) | D22: Ejemplo con números reales | E22: De dónde viene | F22: Norma
A23: Reconocible neto | B23: '='07_Devoluciones'!E5 | C23: Trae el reconocible neto de devoluciones de la línea, de la hoja 07 (Devoluciones). | D23: Fila 1: 80.000,00 → 80.000,00 | E23: hoja «Devoluciones y notas de crédito» | F23: —
A24: Plazo de cobro (meses) | B24: '=IF('03_Detalle'!U5<>"",'03_Detalle'!U5,"") | C24: Trae el plazo de cobro en meses informado en la hoja 03; en blanco si no se informó. | D24: Fila 1: IF((vacío)<>""; (vacío); "") → (en blanco) | E24: hoja «Detalle por obligación» | F24: —
A25: Financiación significativa | B25: '=IF(AND(C5<>"",N(C5)>'02_Parametros'!$B$9),"Sí","No") | C25: Marca «Sí» cuando el plazo de cobro supera el plazo que la hoja 02 (Parámetros) considera financiación significativa; en otro caso «No». | D25: Fila 1: IF(AND((vacío)<>""; N((vacío))>12,00); "Sí"; "No") → No | E25: «Plazo de cobro (meses)» (esta hoja), hoja «Parámetros» | F25: —
A26: Tasa anual | B26: '=IF('02_Parametros'!$B$8="","",'02_Parametros'!$B$8/100) | C26: Trae la tasa de descuento anual de la hoja 02 (Parámetros); en blanco si no se informó. | D26: Fila 1: IF(10,00=""; ""; 10,00/100) → 10,00 % | E26: hoja «Parámetros» | F26: —
A27: Valor presente (ingreso ordinario) | B27: '=IF(B5="","",IF(D5="Sí",IF(E5="",B5,B5/(1+E5)^(C5/12)),B5)) | C27: Si hay financiación significativa y tasa, descuenta el reconocible neto por el plazo de cobro a la tasa anual; si no hay financiación o falta la tasa, deja el reconocible neto tal cual. | D27: Fila 1: IF(80.000,00=""; ""; IF(«No»="Sí"; IF(10,00 %=""; 80.000,00; 80.000,00/(1+10,00 %)^((vacío)/12)); 80.000,00)) → 80.000,00 | E27: «Reconocible neto» (esta hoja), «Financiación significativa» (esta hoja), «Tasa anual» (esta hoja), «Plazo de cobro (meses)» (esta hoja) | F27: —
A28: Componente de financiación | B28: '=IF(B5="","",IF(D5="No",0,IF(E5="","",B5-F5))) | C28: Resta el valor presente del reconocible neto: es la parte que es interés y no ingreso ordinario. Cero sin financiación significativa; en blanco si falta la tasa. | D28: Fila 1: IF(80.000,00=""; ""; IF(«No»="No"; 0; IF(10,00 %=""; ""; 80.000,00-80.000,00))) → 0,00 | E28: «Reconocible neto» (esta hoja), «Financiación significativa» (esta hoja), «Tasa anual» (esta hoja), «Valor presente (ingreso ordinario)» (esta hoja) | F28: —
A29: Días devengados | B29: '=IF(AND(D5="Sí",'03_Detalle'!G5<>""),MAX(MIN('02_Parametros'!$B$5-'03_Detalle'!G5,C5*365/12),0),0) | C29: Con financiación significativa, cuenta los días desde la transferencia del control (hoja 03) hasta el corte (hoja 02), sin pasar del plazo de cobro; cero en los demás casos. | D29: Fila 1: IF(AND(«No»="Sí"; «2025-11-15»<>""); MAX(MIN(«2025-12-31»-«2025-11-15»; (vacío)*365/12); 0); 0) → 0,00 | E29: «Financiación significativa» (esta hoja), «Plazo de cobro (meses)» (esta hoja), hoja «Detalle por obligación», hoja «Parámetros» | F29: —
A30: Interés devengado al corte | B30: '=IF(G5="","",IF(G5=0,0,F5*((1+E5)^(H5/365)-1))) | C30: Capitaliza el valor presente a la tasa anual por los días devengados y toma solo el interés ganado hasta el corte; cero si no hay componente de financiación. | D30: Fila 1: IF(0,00=""; ""; IF(0,00=0; 0; 80.000,00*((1+10,00 %)^(0,00/365)-1))) → 0,00 | E30: «Componente de financiación» (esta hoja), «Valor presente (ingreso ordinario)» (esta hoja), «Tasa anual» (esta hoja), «Días devengados» (esta hoja) | F30: —

Sheet 09_Reconocimiento
A1: Ingreso reconocible vs registrado | H1: ⟵ Inicio | I1: ◀ Anterior | J1: Siguiente ▶
A2: Ingresos · contratos con clientes (existencia, precio, asignación, satisfacción, corte y devoluciones) · Cliente de muestra S.A. · corte 2025-12-31
A4: Línea | B4: Contrato | C4: Reconocible acumulado | D4: Reconocido años anteriores | E4: Reconocible del año | F4: Registrado en el año | G4: Ajuste
A5: C-01-1 | B5: C-01 | C5: ='08_Financiacion'!F5 | D5: =IF('03_Detalle'!R5<>"",'03_Detalle'!R5,0) | E5: =IF(C5="","",C5-D5) | F5: ='03_Detalle'!Q5 | G5: =IF(E5="","",E5-F5)
A6: C-01-2 | B6: C-01 | C6: ='08_Financiacion'!F6 | D6: =IF('03_Detalle'!R6<>"",'03_Detalle'!R6,0) | E6: =IF(C6="","",C6-D6) | F6: ='03_Detalle'!Q6 | G6: =IF(E6="","",E6-F6)
A7: C-02-1 | B7: C-02 | C7: ='08_Financiacion'!F7 | D7: =IF('03_Detalle'!R7<>"",'03_Detalle'!R7,0) | E7: =IF(C7="","",C7-D7) | F7: ='03_Detalle'!Q7 | G7: =IF(E7="","",E7-F7)
A8: C-03-1 | B8: C-03 | C8: ='08_Financiacion'!F8 | D8: =IF('03_Detalle'!R8<>"",'03_Detalle'!R8,0) | E8: =IF(C8="","",C8-D8) | F8: ='03_Detalle'!Q8 | G8: =IF(E8="","",E8-F8)
A9: C-04-1 | B9: C-04 | C9: ='08_Financiacion'!F9 | D9: =IF('03_Detalle'!R9<>"",'03_Detalle'!R9,0) | E9: =IF(C9="","",C9-D9) | F9: ='03_Detalle'!Q9 | G9: =IF(E9="","",E9-F9)
A10: C-05-1 | B10: C-05 | C10: ='08_Financiacion'!F10 | D10: =IF('03_Detalle'!R10<>"",'03_Detalle'!R10,0) | E10: =IF(C10="","",C10-D10) | F10: ='03_Detalle'!Q10 | G10: =IF(E10="","",E10-F10)
A11: C-06-1 | B11: C-06 | C11: ='08_Financiacion'!F11 | D11: =IF('03_Detalle'!R11<>"",'03_Detalle'!R11,0) | E11: =IF(C11="","",C11-D11) | F11: ='03_Detalle'!Q11 | G11: =IF(E11="","",E11-F11)
A12: C-07-1 | B12: C-07 | C12: ='08_Financiacion'!F12 | D12: =IF('03_Detalle'!R12<>"",'03_Detalle'!R12,0) | E12: =IF(C12="","",C12-D12) | F12: ='03_Detalle'!Q12 | G12: =IF(E12="","",E12-F12)
A13: C-08-1 | B13: C-08 | C13: ='08_Financiacion'!F13 | D13: =IF('03_Detalle'!R13<>"",'03_Detalle'!R13,0) | E13: =IF(C13="","",C13-D13) | F13: ='03_Detalle'!Q13 | G13: =IF(E13="","",E13-F13)
A14: C-09-1 | B14: C-09 | C14: ='08_Financiacion'!F14 | D14: =IF('03_Detalle'!R14<>"",'03_Detalle'!R14,0) | E14: =IF(C14="","",C14-D14) | F14: ='03_Detalle'!Q14 | G14: =IF(E14="","",E14-F14)
A15: C-09-2 | B15: C-09 | C15: ='08_Financiacion'!F15 | D15: =IF('03_Detalle'!R15<>"",'03_Detalle'!R15,0) | E15: =IF(C15="","",C15-D15) | F15: ='03_Detalle'!Q15 | G15: =IF(E15="","",E15-F15)
A16: C-10-1 | B16: C-10 | C16: ='08_Financiacion'!F16 | D16: =IF('03_Detalle'!R16<>"",'03_Detalle'!R16,0) | E16: =IF(C16="","",C16-D16) | F16: ='03_Detalle'!Q16 | G16: =IF(E16="","",E16-F16)
... A18: C-12-1 | B18: C-12 | C18: ='08_Financiacion'!F18 | D18: =IF('03_Detalle'!R18<>"",'03_Detalle'!R18,0) | E18: =IF(C18="","",C18-D18) | F18: ='03_Detalle'!Q18 | G18: =IF(E18="","",E18-F18)
A19: TOTAL | C19: =SUM(C5:C18) | D19: =SUM(D5:D18) | E19: =SUM(E5:E18) | F19: =SUM(F5:F18) | G19: =SUM(G5:G18)
A21: ⓘ Cómo se calcula esta hoja
A22: Columna | B22: Fórmula (Excel) | C22: Cómo se calcula (sencillo) | D22: Ejemplo con números reales | E22: De dónde viene | F22: Norma
A23: Reconocible acumulado | B23: '='08_Financiacion'!F5 | C23: Trae el valor presente (ingreso ordinario) acumulado de la línea, calculado en la hoja 08 (Componente de financiación). | D23: Fila 1: 80.000,00 → 80.000,00 | E23: hoja «Componente de financiación» | F23: —
A24: Reconocido años anteriores | B24: '=IF('03_Detalle'!R5<>"",'03_Detalle'!R5,0) | C24: Trae el ingreso de la línea reconocido en años anteriores (hoja 03); si no se informó, se toma cero. | D24: Fila 1: IF((vacío)<>""; (vacío); 0) → 0,00 | E24: hoja «Detalle por obligación» | F24: —
A25: Reconocible del año | B25: '=IF(C5="","",C5-D5) | C25: Resta lo reconocido en años anteriores del reconocible acumulado: es el ingreso que corresponde a este año. En blanco si la línea no se pudo medir. | D25: Fila 1: IF(80.000,00=""; ""; 80.000,00-0,00) → 80.000,00 | E25: «Reconocible acumulado» (esta hoja), «Reconocido años anteriores» (esta hoja) | F25: —
A26: Registrado en el año | B26: '='03_Detalle'!Q5 | C26: Trae el ingreso que el cliente registró en el año para la línea, de la hoja 03 (Detalle). | D26: Fila 1: 90.000,00 → 90.000,00 | E26: hoja «Detalle por obligación» | F26: —
A27: Ajuste | B27: '=IF(E5="","",E5-F5) | C27: Resta lo registrado del reconocible del año: negativo significa que el cliente registró ingreso de más. En blanco si la línea no se pudo medir. | D27: Fila 1: IF(80.000,00=""; ""; 80.000,00-90.000,00) → -10.000,00 | E27: «Reconocible del año» (esta hoja), «Registrado en el año» (esta hoja) | F27: —

Sheet 10_Activo_pasivo
A1: Activo y pasivo del contrato | H1: ⟵ Inicio | I1: ◀ Anterior | J1: Siguiente ▶
A2: Ingresos · contratos con clientes (existencia, precio, asignación, satisfacción, corte y devoluciones) · Cliente de muestra S.A. · corte 2025-12-31
A4: Contrato | B4: Cliente | C4: Reconocible bruto acumulado | D4: Facturado | E4: Cobrado | F4: Posición | G4: Activo del contrato | H4: Pasivo del contrato (ingreso diferido) | I4: Cuenta por cobrar | J4: Obligaciones sin medir
A5: C-01 | B5: Comercial Andina | C5: =SUMIF('03_Detalle'!$B$5:$B$18,A5,'06_Satisfaccion'!$H$5:$H$18) | D5: =SUMIF('03_Detalle'!$B$5:$B$18,A5,'03_Detalle'!$S$5:$S$18) | E5: =SUMIF('03_Detalle'!$B$5:$B$18,A5,'03_Detalle'!$T$5:$T$18) | F5: =IF(J5>0,"",C5-D5) | G5: =IF(F5="","",MAX(F5,0)) | H5: =IF(F5="","",MAX(-F5,0)) | I5: =D5-E5 | J5: =COUNTIFS('03_Detalle'!$B$5:$B$18,A5,'06_Satisfaccion'!$H$5:$H$18,"")
A6: C-02 | B6: Constructora Sur | C6: =SUMIF('03_Detalle'!$B$5:$B$18,A6,'06_Satisfaccion'!$H$5:$H$18) | D6: =SUMIF('03_Detalle'!$B$5:$B$18,A6,'03_Detalle'!$S$5:$S$18) | E6: =SUMIF('03_Detalle'!$B$5:$B$18,A6,'03_Detalle'!$T$5:$T$18) | F6: =IF(J6>0,"",C6-D6) | G6: =IF(F6="","",MAX(F6,0)) | H6: =IF(F6="","",MAX(-F6,0)) | I6: =D6-E6 | J6: =COUNTIFS('03_Detalle'!$B$5:$B$18,A6,'06_Satisfaccion'!$H$5:$H$18,"")
A7: C-03 | B7: Distribuidora Norte | C7: =SUMIF('03_Detalle'!$B$5:$B$18,A7,'06_Satisfaccion'!$H$5:$H$18) | D7: =SUMIF('03_Detalle'!$B$5:$B$18,A7,'03_Detalle'!$S$5:$S$18) | E7: =SUMIF('03_Detalle'!$B$5:$B$18,A7,'03_Detalle'!$T$5:$T$18) | F7: =IF(J7>0,"",C7-D7) | G7: =IF(F7="","",MAX(F7,0)) | H7: =IF(F7="","",MAX(-F7,0)) | I7: =D7-E7 | J7: =COUNTIFS('03_Detalle'!$B$5:$B$18,A7,'06_Satisfaccion'!$H$5:$H$18,"")
A8: C-04 | B8: Retail Express | C8: =SUMIF('03_Detalle'!$B$5:$B$18,A8,'06_Satisfaccion'!$H$5:$H$18) | D8: =SUMIF('03_Detalle'!$B$5:$B$18,A8,'03_Detalle'!$S$5:$S$18) | E8: =SUMIF('03_Detalle'!$B$5:$B$18,A8,'03_Detalle'!$T$5:$T$18) | F8: =IF(J8>0,"",C8-D8) | G8: =IF(F8="","",MAX(F8,0)) | H8: =IF(F8="","",MAX(-F8,0)) | I8: =D8-E8 | J8: =COUNTIFS('03_Detalle'!$B$5:$B$18,A8,'06_Satisfaccion'!$H$5:$H$18,"")
A9: C-05 | B9: Agro Plazo | C9: =SUMIF('03_Detalle'!$B$5:$B$18,A9,'06_Satisfaccion'!$H$5:$H$18) | D9: =SUMIF('03_Detalle'!$B$5:$B$18,A9,'03_Detalle'!$S$5:$S$18) | E9: =SUMIF('03_Detalle'!$B$5:$B$18,A9,'03_Detalle'!$T$5:$T$18) | F9: =IF(J9>0,"",C9-D9) | G9: =IF(F9="","",MAX(F9,0)) | H9: =IF(F9="","",MAX(-F9,0)) | I9: =D9-E9 | J9: =COUNTIFS('03_Detalle'!$B$5:$B$18,A9,'06_Satisfaccion'!$H$5:$H$18,"")
A10: C-06 | B10: Servicios Beta | C10: =SUMIF('03_Detalle'!$B$5:$B$18,A10,'06_Satisfaccion'!$H$5:$H$18) | D10: =SUMIF('03_Detalle'!$B$5:$B$18,A10,'03_Detalle'!$S$5:$S$18) | E10: =SUMIF('03_Detalle'!$B$5:$B$18,A10,'03_Detalle'!$T$5:$T$18) | F10: =IF(J10>0,"",C10-D10) | G10: =IF(F10="","",MAX(F10,0)) | H10: =IF(F10="","",MAX(-F10,0)) | I10: =D10-E10 | J10: =COUNTIFS('03_Detalle'!$B$5:$B$18,A10,'06_Satisfaccion'!$H$5:$H$18,"")
A11: C-07 | B11: Tecnología Gama | C11: =SUMIF('03_Detalle'!$B$5:$B$18,A11,'06_Satisfaccion'!$H$5:$H$18) | D11: =SUMIF('03_Detalle'!$B$5:$B$18,A11,'03_Detalle'!$S$5:$S$18) | E11: =SUMIF('03_Detalle'!$B$5:$B$18,A11,'03_Detalle'!$T$5:$T$18) | F11: =IF(J11>0,"",C11-D11) | G11: =IF(F11="","",MAX(F11,0)) | H11: =IF(F11="","",MAX(-F11,0)) | I11: =D11-E11 | J11: =COUNTIFS('03_Detalle'!$B$5:$B$18,A11,'06_Satisfaccion'!$H$5:$H$18,"")
A12: C-08 | B12: Software Delta | C12: =SUMIF('03_Detalle'!$B$5:$B$18,A12,'06_Satisfaccion'!$H$5:$H$18) | D12: =SUMIF('03_Detalle'!$B$5:$B$18,A12,'03_Detalle'!$S$5:$S$18) | E12: =SUMIF('03_Detalle'!$B$5:$B$18,A12,'03_Detalle'!$T$5:$T$18) | F12: =IF(J12>0,"",C12-D12) | G12: =IF(F12="","",MAX(F12,0)) | H12: =IF(F12="","",MAX(-F12,0)) | I12: =D12-E12 | J12: =COUNTIFS('03_Detalle'!$B$5:$B$18,A12,'06_Satisfaccion'!$H$5:$H$18,"")
A13: C-09 | B13: Mantenimientos Épsilon | C13: =SUMIF('03_Detalle'!$B$5:$B$18,A13,'06_Satisfaccion'!$H$5:$H$18) | D13: =SUMIF('03_Detalle'!$B$5:$B$18,A13,'03_Detalle'!$S$5:$S$18) | E13: =SUMIF('03_Detalle'!$B$5:$B$18,A13,'03_Detalle'!$T$5:$T$18) | F13: =IF(J13>0,"",C13-D13) | G13: =IF(F13="","",MAX(F13,0)) | H13: =IF(F13="","",MAX(-F13,0)) | I13: =D13-E13 | J13: =COUNTIFS('03_Detalle'!$B$5:$B$18,A13,'06_Satisfaccion'!$H$5:$H$18,"")
A14: C-10 | B14: Obra Zeta | C14: =SUMIF('03_Detalle'!$B$5:$B$18,A14,'06_Satisfaccion'!$H$5:$H$18) | D14: =SUMIF('03_Detalle'!$B$5:$B$18,A14,'03_Detalle'!$S$5:$S$18) | E14: =SUMIF('03_Detalle'!$B$5:$B$18,A14,'03_Detalle'!$T$5:$T$18) | F14: =IF(J14>0,"",C14-D14) | G14: =IF(F14="","",MAX(F14,0)) | H14: =IF(F14="","",MAX(-F14,0)) | I14: =D14-E14 | J14: =COUNTIFS('03_Detalle'!$B$5:$B$18,A14,'06_Satisfaccion'!$H$5:$H$18,"")
A15: C-11 | B15: Servicios Theta | C15: =SUMIF('03_Detalle'!$B$5:$B$18,A15,'06_Satisfaccion'!$H$5:$H$18) | D15: =SUMIF('03_Detalle'!$B$5:$B$18,A15,'03_Detalle'!$S$5:$S$18) | E15: =SUMIF('03_Detalle'!$B$5:$B$18,A15,'03_Detalle'!$T$5:$T$18) | F15: =IF(J15>0,"",C15-D15) | G15: =IF(F15="","",MAX(F15,0)) | H15: =IF(F15="","",MAX(-F15,0)) | I15: =D15-E15 | J15: =COUNTIFS('03_Detalle'!$B$5:$B$18,A15,'06_Satisfaccion'!$H$5:$H$18,"")
A16: C-12 | B16: Comercial Iota | C16: =SUMIF('03_Detalle'!$B$5:$B$18,A16,'06_Satisfaccion'!$H$5:$H$18) | D16: =SUMIF('03_Detalle'!$B$5:$B$18,A16,'03_Detalle'!$S$5:$S$18) | E16: =SUMIF('03_Detalle'!$B$5:$B$18,A16,'03_Detalle'!$T$5:$T$18) | F16: =IF(J16>0,"",C16-D16) | G16: =IF(F16="","",MAX(F16,0)) | H16: =IF(F16="","",MAX(-F16,0)) | I16: =D16-E16 | J16: =COUNTIFS('03_Detalle'!$B$5:$B$18,A16,'06_Satisfaccion'!$H$5:$H$18,"")
A17: TOTAL | C17: =SUM(C5:C16) | D17: =SUM(D5:D16) | E17: =SUM(E5:E16) | F17: =SUM(F5:F16) | G17: =SUM(G5:G16) | H17: =SUM(H5:H16) | I17: =SUM(I5:I16)
A19: ⓘ Cómo se calcula esta hoja
A20: Columna | B20: Fórmula (Excel) | C20: Cómo se calcula (sencillo) | D20: Ejemplo con números reales | E20: De dónde viene | F20: Norma
A21: Reconocible bruto acumulado | B21: '=SUMIF('03_Detalle'!$B$5:$B$18,A5,'06_Satisfaccion'!$H$5:$H$18) | C21: Suma el reconocible bruto acumulado de la hoja 06 (Satisfacción) de todas las líneas de este contrato (identificadas por el contrato en la hoja 03). | D21: Fila 1: SUMIF([«Contrato» de «Detalle por obligación», 14 filas]; «C-01»; [«Reconocible bruto acumulado» de «Satisfacción y porcentaje de avance», 14 filas]) → 85.000,00 | E21: «Contrato» (esta hoja), hoja «Detalle por obligación», hoja «Satisfacción y porcentaje de avance» | F21: —
A22: Facturado | B22: '=SUMIF('03_Detalle'!$B$5:$B$18,A5,'03_Detalle'!$S$5:$S$18) | C22: Suma el facturado acumulado de las líneas de este contrato informado en la hoja 03 (Detalle). | D22: Fila 1: SUMIF([«Contrato» de «Detalle por obligación», 14 filas]; «C-01»; [«Facturado acumulado» de «Detalle por obligación», 14 filas]) → 100.000,00 | E22: «Contrato» (esta hoja), hoja «Detalle por obligación» | F22: —
A23: Cobrado | B23: '=SUMIF('03_Detalle'!$B$5:$B$18,A5,'03_Detalle'!$T$5:$T$18) | C23: Suma el cobrado acumulado de las líneas de este contrato informado en la hoja 03 (Detalle). | D23: Fila 1: SUMIF([«Contrato» de «Detalle por obligación», 14 filas]; «C-01»; [«Cobrado acumulado» de «Detalle por obligación», 14 filas]) → 60.000,00 | E23: «Contrato» (esta hoja), hoja «Detalle por obligación» | F23: —
A24: Posición | B24: '=IF(J5>0,"",C5-D5) | C24: Resta lo facturado del reconocible bruto acumulado del contrato; queda en blanco si alguna obligación del contrato no se pudo medir. | D24: Fila 1: IF(0>0; ""; 85.000,00-100.000,00) → -15.000,00 | E24: «Obligaciones sin medir» (esta hoja), «Reconocible bruto acumulado» (esta hoja), «Facturado» (esta hoja) | F24: —
A25: Activo del contrato | B25: '=IF(F5="","",MAX(F5,0)) | C25: Si la posición es positiva (se ha cumplido más de lo facturado), ese importe se presenta como activo; si es negativa, cero. | D25: Fila 1: IF(-15.000,00=""; ""; MAX(-15.000,00; 0)) → 0,00 | E25: «Posición» (esta hoja) | F25: —
A26: Pasivo del contrato (ingreso diferido) | B26: '=IF(F5="","",MAX(-F5,0)) | C26: Si la posición es negativa (se ha facturado más de lo cumplido), su valor sin signo se presenta como pasivo; si es positiva, cero. | D26: Fila 1: IF(-15.000,00=""; ""; MAX(--15.000,00; 0)) → 15.000,00 | E26: «Posición» (esta hoja) | F26: —
A27: Cuenta por cobrar | B27: '=D5-E5 | C27: Resta lo cobrado de lo facturado del contrato: es el saldo que el cliente final aún debe. | D27: Fila 1: 100.000,00-60.000,00 → 40.000,00 | E27: «Facturado» (esta hoja), «Cobrado» (esta hoja) | F27: —
A28: Obligaciones sin medir | B28: '=COUNTIFS('03_Detalle'!$B$5:$B$18,A5,'06_Satisfaccion'!$H$5:$H$18,"") | C28: Cuenta cuántas líneas del contrato quedaron con el reconocible bruto en blanco en la hoja 06 (Satisfacción) por falta de datos. | D28: Fila 1: COUNTIFS([«Contrato» de «Detalle por obligación», 14 filas]; «C-01»; [«Reconocible bruto acumulado» de «Satisfacción y porcentaje de avance», 14 filas]; "") → 0 | E28: «Contrato» (esta hoja), hoja «Detalle por obligación», hoja «Satisfacción y porcentaje de avance» | F28: —

Sheet 11_Corte
A1: Corte de ingresos | H1: ⟵ Inicio | I1: ◀ Anterior | J1: Siguiente ▶
A2: Ingresos · contratos con clientes (existencia, precio, asignación, satisfacción, corte y devoluciones) · Cliente de muestra S.A. · corte 2025-12-31
A4: Línea | B4: Contrato | C4: Registro | D4: Transferencia | E4: Registrado en el año | F4: Registrado en el ejercicio | G4: Transferido en el ejercicio | H4: Registrado antes de transferir | I4: Transferido sin registrar
A5: C-01-1 | B5: C-01 | C5: 45976 | D5: 45976 | E5: ='03_Detalle'!Q5 | F5: =IF(C5<='02_Parametros'!$B$5,"Sí","No") | G5: =IF(D5<='02_Parametros'!$B$5,"Sí","No") | H5: =IF(AND(F5="Sí",G5="No"),E5,0) | I5: =IF(AND(F5="No",G5="Sí"),N('06_Satisfaccion'!H5),0)
A6: C-03-1 | B6: C-03 | C6: 46019 | D6: 46027 | E6: ='03_Detalle'!Q8 | F6: =IF(C6<='02_Parametros'!$B$5,"Sí","No") | G6: =IF(D6<='02_Parametros'!$B$5,"Sí","No") | H6: =IF(AND(F6="Sí",G6="No"),E6,0) | I6: =IF(AND(F6="No",G6="Sí"),N('06_Satisfaccion'!H8),0)
A7: C-04-1 | B7: C-04 | C7: 46001 | D7: 46001 | E7: ='03_Detalle'!Q9 | F7: =IF(C7<='02_Parametros'!$B$5,"Sí","No") | G7: =IF(D7<='02_Parametros'!$B$5,"Sí","No") | H7: =IF(AND(F7="Sí",G7="No"),E7,0) | I7: =IF(AND(F7="No",G7="Sí"),N('06_Satisfaccion'!H9),0)
A8: C-05-1 | B8: C-05 | C8: 45839 | D8: 45839 | E8: ='03_Detalle'!Q10 | F8: =IF(C8<='02_Parametros'!$B$5,"Sí","No") | G8: =IF(D8<='02_Parametros'!$B$5,"Sí","No") | H8: =IF(AND(F8="Sí",G8="No"),E8,0) | I8: =IF(AND(F8="No",G8="Sí"),N('06_Satisfaccion'!H10),0)
A9: C-07-1 | B9: C-07 | C9: 46025 | D9: 46011 | E9: ='03_Detalle'!Q12 | F9: =IF(C9<='02_Parametros'!$B$5,"Sí","No") | G9: =IF(D9<='02_Parametros'!$B$5,"Sí","No") | H9: =IF(AND(F9="Sí",G9="No"),E9,0) | I9: =IF(AND(F9="No",G9="Sí"),N('06_Satisfaccion'!H12),0)
A10: C-09-1 | B10: C-09 | C10: 45992 | D10: 45992 | E10: ='03_Detalle'!Q14 | F10: =IF(C10<='02_Parametros'!$B$5,"Sí","No") | G10: =IF(D10<='02_Parametros'!$B$5,"Sí","No") | H10: =IF(AND(F10="Sí",G10="No"),E10,0) | I10: =IF(AND(F10="No",G10="Sí"),N('06_Satisfaccion'!H14),0)
A11: C-11-1 | B11: C-11 | C11: 45931 | D11: 45931 | E11: ='03_Detalle'!Q17 | F11: =IF(C11<='02_Parametros'!$B$5,"Sí","No") | G11: =IF(D11<='02_Parametros'!$B$5,"Sí","No") | H11: =IF(AND(F11="Sí",G11="No"),E11,0) | I11: =IF(AND(F11="No",G11="Sí"),N('06_Satisfaccion'!H17),0)
A12: TOTAL | E12: =SUM(E5:E11) | H12: =SUM(H5:H11) | I12: =SUM(I5:I11)
A14: ⓘ Cómo se calcula esta hoja
A15: Columna | B15: Fórmula (Excel) | C15: Cómo se calcula (sencillo) | D15: Ejemplo con números reales | E15: De dónde viene | F15: Norma
A16: Registrado en el año | B16: '='03_Detalle'!Q5 | C16: Trae el ingreso registrado en el año para la línea, de la hoja 03 (Detalle por obligación). | D16: Fila 1: 90.000,00 → 90.000,00 | E16: hoja «Detalle por obligación» | F16: —
A17: Registrado en el ejercicio | B17: '=IF(C5<='02_Parametros'!$B$5,"Sí","No") | C17: Marca «Sí» si la fecha de registro del ingreso es igual o anterior al corte de la hoja 02; si es posterior, «No». | D17: Fila 1: IF(«2025-11-15»<=«2025-12-31»; "Sí"; "No") → Sí | E17: «Registro» (esta hoja), hoja «Parámetros» | F17: —
A18: Transferido en el ejercicio | B18: '=IF(D5<='02_Parametros'!$B$5,"Sí","No") | C18: Marca «Sí» si la fecha de transferencia del control es igual o anterior al corte de la hoja 02; si es posterior, «No». | D18: Fila 1: IF(«2025-11-15»<=«2025-12-31»; "Sí"; "No") → Sí | E18: «Transferencia» (esta hoja), hoja «Parámetros» | F18: —
A19: Registrado antes de transferir | B19: '=IF(AND(F5="Sí",G5="No"),E5,0) | C19: Si el ingreso se registró en el ejercicio pero el control se transfirió después del corte, trae el importe registrado (ingreso anticipado); si no, cero. | D19: Fila 1: IF(AND(«Sí»="Sí"; «Sí»="No"); 90.000,00; 0) → 0,00 | E19: «Registrado en el ejercicio» (esta hoja), «Transferido en el ejercicio» (esta hoja), «Registrado en el año» (esta hoja) | F19: —
A20: Transferido sin registrar | B20: '=IF(AND(F5="No",G5="Sí"),N('06_Satisfaccion'!H5),0) | C20: Si el control se transfirió en el ejercicio pero el ingreso se registró después del corte, trae el reconocible bruto de la hoja 06 (ingreso omitido); si no, cero. | D20: Fila 1: IF(AND(«Sí»="No"; «Sí»="Sí"); N(80.000,00); 0) → 0,00 | E20: «Registrado en el ejercicio» (esta hoja), «Transferido en el ejercicio» (esta hoja), hoja «Satisfacción y porcentaje de avance» | F20: —

Sheet 12_Modificaciones
A1: Modificaciones de contratos | H1: ⟵ Inicio | I1: ◀ Anterior | J1: Siguiente ▶
A2: Ingresos · contratos con clientes (existencia, precio, asignación, satisfacción, corte y devoluciones) · Cliente de muestra S.A. · corte 2025-12-31
A4: Línea | B4: Contrato | C4: Modificación informada | D4: Importe | E4: Tratamiento | F4: Estado
A5: C-08-1 | B5: C-08 | C5: Prospectivo | D5: =IF('03_Detalle'!Y13<>"",'03_Detalle'!Y13,"") | E5: Terminación del contrato original y nuevo contrato para lo pendiente (NIIF 15 21 a) | F5: Documentado
A6: C-09-1 | B6: C-09 | C6: Adenda de precio | D6: =IF('03_Detalle'!Y14<>"",'03_Detalle'!Y14,"") | E6: Falta documentar el tratamiento | F6: Pendiente
A8: ⓘ Cómo se calcula esta hoja
A9: Columna | B9: Fórmula (Excel) | C9: Cómo se calcula (sencillo) | D9: Ejemplo con números reales | E9: De dónde viene | F9: Norma
A10: Importe | B10: '=IF('03_Detalle'!Y13<>"",'03_Detalle'!Y13,"") | C10: Trae el importe de la modificación del contrato informado en la hoja 03; en blanco si no se informó. | D10: Fila 1: IF(8.000,00<>""; 8.000,00; "") → 8.000,00 | E10: hoja «Detalle por obligación» | F10: —

Sheet 13_Conciliacion
A1: Conciliación y ajustes | H1: ⟵ Inicio | I1: ◀ Anterior | J1: Siguiente ▶
A2: Ingresos · contratos con clientes (existencia, precio, asignación, satisfacción, corte y devoluciones) · Cliente de muestra S.A. · corte 2025-12-31
A4: Concepto | B4: Importe | C4: Referencia
A5: Ingreso registrado en el año (anexo) | B5: =SUM('03_Detalle'!$Q$5:$Q$18) | C5: Anexo de contratos
A6: Ingresos según el mayor | B6: =IF('02_Parametros'!$B$12="",B5,'02_Parametros'!$B$12) | C6: Parámetros (en blanco: el anexo)
A7: Diferencia anexo − mayor | B7: =B5-B6 | C7: Integridad del anexo (NIA 500)
A8: Ingreso reconocible del año (líneas medidas) | B8: ='09_Reconocimiento'!E19 | C8: 09_Reconocimiento
A9: Ajuste propuesto a ingresos | B9: ='09_Reconocimiento'!G19 | C9: Incluye corte, asignación, variable, avance, devoluciones y financiación
A10: Corte: registrado antes de la transferencia | B10: ='11_Corte'!H12 | C10: Ya incluido en el ajuste (NIIF 15 31, 38)
A11: Corte: transferido sin registrar en el ejercicio | B11: ='11_Corte'!I12 | C11: Ya incluido en el ajuste (NIIF 15 31, 38)
A12: Componente de financiación a separar | B12: ='08_Financiacion'!G19 | C12: NIIF 15 60-65
A13: Interés devengado al corte | B13: ='08_Financiacion'!I19 | C13: Ingreso financiero, separado del ingreso ordinario
A14: Pasivo por reembolso (devoluciones esperadas) | B14: ='07_Devoluciones'!D19 | C14: NIIF 15 B20-B27 (pasivo por reembolso B21 b; activo por el derecho a recuperar los productos B21 c y B25)
A15: Activo por el derecho a recuperar los productos (contra el costo de ventas) | B15: ='07_Devoluciones'!I19 | C15: NIIF 15 B20-B27 (pasivo por reembolso B21 b; activo por el derecho a recuperar los productos B21 c y B25) — contrapartida: costo de ventas
A16: Notas de crédito posteriores no provisionadas | B16: ='07_Devoluciones'!G19 | C16: Notas de crédito posteriores (NIA 560)
A17: Activo del contrato requerido | B17: ='10_Activo_pasivo'!G17 | C17: NIIF 15 105-109
A18: Activo del contrato registrado | B18: ='02_Parametros'!$B$13 | C18: Parámetros
A19: Activo del contrato: diferencia | B19: =B17-B18 | C19: Reclasificación de presentación
A20: Pasivo del contrato (ingreso diferido) requerido | B20: ='10_Activo_pasivo'!H17 | C20: NIIF 15 105-109
A21: Pasivo del contrato (ingreso diferido) registrado (no informado: se toma 0) | B21: ='02_Parametros'!$B$14 | C21: Parámetros
A22: Pasivo del contrato (ingreso diferido): diferencia | B22: =B20-B21 | C22: Reclasificación de presentación
A23: Diferencias de asignación (absolutas) | B23: ='05_Asignacion'!J19 | C23: NIIF 15 73-80
A24: Variable incluida sin cumplir la restricción | B24: ='04_Precio_variable'!J19 | C24: NIIF 15 53, 56-57
A26: ⓘ Cómo se calcula esta hoja
A27: Columna | B27: Fórmula (Excel) | C27: Cómo se calcula (sencillo) | D27: Ejemplo con números reales | E27: De dónde viene | F27: Norma
A28: Importe | B28: '=SUM('03_Detalle'!$Q$5:$Q$18) | C28: Cada concepto trae su importe de la hoja donde se calcula: el registrado suma la hoja 03, el mayor y los saldos registrados vienen de la hoja 02 (si falta el mayor se usa el anexo), los demás son totales de las hojas 04 a 11, y las diferencias restan dos renglones de esta misma hoja. | D28: Fila 1: SUM([«Registrado en el año» de «Detalle por obligación», 14 filas]) → 668.166,67 | E28: hoja «Detalle por obligación» | F28: —

Sheet 14_Asientos
A1: Asientos propuestos | H1: ⟵ Inicio | I1: ◀ Anterior | J1: Siguiente ▶
A2: Ingresos · contratos con clientes (existencia, precio, asignación, satisfacción, corte y devoluciones) · Cliente de muestra S.A. · corte 2025-12-31
A4: Asiento | B4: Cuenta | C4: Debe | D4: Haber
A5: 1 · Menor ingreso reconocible | B5: Ingresos de actividades ordinarias | C5: =ABS('13_Conciliacion'!B9)
B6: Activo del contrato / Pasivo del contrato (ingreso diferido) / pasivo por reembolso / cuentas por cobrar (ver 07 y 10) | D6: =ABS('13_Conciliacion'!B9)
A7: 2 · Interés devengado del componente de financiación | B7: Cuentas por cobrar (costo amortizado) | C7: ='13_Conciliacion'!B13
B8: Ingresos financieros por intereses | D8: ='13_Conciliacion'!B13
A9: 3 · Activo por el derecho a recuperar los productos (devoluciones esperadas) | B9: Activo por derecho a recuperar productos (inventario) | C9: ='13_Conciliacion'!B15
B10: Costo de ventas | D10: ='13_Conciliacion'!B15
A12: ⓘ Cómo se calcula esta hoja
A13: Columna | B13: Fórmula (Excel) | C13: Cómo se calcula (sencillo) | D13: Ejemplo con números reales | E13: De dónde viene | F13: Norma
A14: Debe | B14: '=ABS('13_Conciliacion'!B9) | C14: Toma, sin signo, el importe del concepto que origina el asiento en la hoja 13 (ajuste de ingresos, interés devengado o activo por devoluciones) y lo lleva a la cuenta que se debita. | D14: Fila 1: ABS(-114.620,00) → 114.620,00 | E14: hoja «Conciliación y ajustes» | F14: —
A15: Haber | B15: '=ABS('13_Conciliacion'!B9) | C15: Lleva a la cuenta que se acredita el mismo importe del débito, tomado sin signo de la hoja 13 (Conciliación y ajustes), para que el asiento cuadre. | D15: Fila 2: ABS(-114.620,00) → 114.620,00 | E15: hoja «Conciliación y ajustes» | F15: —

Sheet 15_Problemas
A1: Problemas encontrados | H1: ⟵ Inicio | I1: ◀ Anterior | J1: Siguiente ▶
A2: Ingresos · contratos con clientes (existencia, precio, asignación, satisfacción, corte y devoluciones) · Cliente de muestra S.A. · corte 2025-12-31
A4: Código | B4: Descripción | C4: Importe
A5: SIN_CONTRATO | B5: C-06-1 (C-06): ingreso registrado sin contrato válido; no procede reconocerlo (NIIF 15 9, 15-16). | C5: 15000
A6: CONTRATO_SIN_EVIDENCIA | B6: 1 línea(s) sin evidencia del contrato informada (C-08-1): obtenga el contrato o la orden aprobada (NIIF 15 9, 15-16). | C6: 0
A7: ASIGNACION_INCORRECTA | B7: C-01-1: asignado por precio independiente relativo 80.000,00 frente a 90.000,00 del cliente (NIIF 15 73-80). | C7: -10000
A8: ASIGNACION_INCORRECTA | B8: C-01-2: asignado por precio independiente relativo 20.000,00 frente a 10.000,00 del cliente (NIIF 15 73-80). | C8: 10000
A9: AVANCE_MAL_CALCULADO | B9: C-02-1: avance del cliente 50,00 % frente a 45,00 % recalculado con costos (NIIF 15 39-45, B18-B19). | C9: 25000
A10: VARIABLE_SIN_RESTRICCION | B10: C-02-1: contraprestación variable incluida por el cliente sin cumplir la restricción (NIIF 15 53, 56-57). | C10: 50000
A11: ERROR_CORTE | B11: C-03-1: ingreso registrado en el ejercicio y control transferido después del corte (NIIF 15 31, 38). | C11: 30000
A12: DEVOLUCIONES_NO_PROVISIONADAS | B12: C-04-1: notas de crédito posteriores al cierre superan el pasivo por reembolso estimado (NIIF 15 B20-B27 (pasivo por reembolso B21 b; activo por el derecho a recuperar los productos B21 c y B25); NIA 560). | C12: 1500
A13: ERROR_CORTE | B13: C-07-1: control transferido en el ejercicio e ingreso registrado después del corte (NIIF 15 31, 38). | C13: 12000
A14: PSI_FALTANTE | B14: C-09-1: sin precio de venta independiente en un contrato de 2 obligaciones; se usó el precio del contrato (NIIF 15 73-80). | C14: 0
A15: ACTIVO_DEVOLUCION_SIN_COSTO | B15: C-09-1: con devoluciones esperadas del 2,00 % falta el costo de los bienes vendidos: el activo por el derecho a recuperar los productos y su ajuste al costo de ventas quedan vacíos (NIIF 15 B20-B27 (pasivo por reembolso B21 b; activo por el derecho a recuperar los productos B21 c y B25)). | C15: 0
A16: MODIFICACION_SIN_TRATAMIENTO | B16: C-09-1: modificación sin tratamiento documentado (contrato separado, prospectivo o acumulativo; NIIF 15 18-21). | C16: 1000
... A25: AJUSTE_INGRESOS | B25: Ingreso reconocible del año 544.546,67 frente a 668.166,67 registrado en las líneas medidas: ajuste -114.620,00. | C25: -114620

Sheet 13_Conclusion
A1: Conclusión | H1: ⟵ Inicio | I1: ◀ Anterior | J1: Siguiente ▶
A2: Ingresos · contratos con clientes (existencia, precio, asignación, satisfacción, corte y devoluciones) · Cliente de muestra S.A. · corte 2025-12-31
A4: Concepto | B4: Detalle
A5: Conciliación con el mayor | B5: Población None · mayor None · diferencia None
A6: Evaluación de excepciones
A7: Análisis
A8: Conclusión

Sheet 14_Control_Revision
A1: Control de revisión | H1: ⟵ Inicio | I1: ◀ Anterior
A2: Ingresos · contratos con clientes (existencia, precio, asignación, satisfacción, corte y devoluciones) · Cliente de muestra S.A. · corte 2025-12-31
A4: Fecha | B4: Acción | C4: Estado anterior | D4: Estado nuevo | E4: Actor | F4: Comentario
