Workbook

Sheet 00_Inicio
B2: AuditConsulting Auditores Cía. Ltda. · AUDIT-IA
B4: Activos intangibles y goodwill
B6: Cliente | C6: Cliente de muestra S.A. | D6: RUC | E6: 1790000000001
B7: Marco contable | C7: NIIF completas | D7: Fecha de corte | E7: 2025-12-31
B8: Preparó | C8: Ejercicio modelo | D8: Revisó | E8: Pendiente
B10: INDICADORES CLAVE
B11: Ajuste propuesto (neto) | C11: Problemas encontrados
B12: -42000 | C12: 14
B15: IR A LA CÉDULA
B16: Carátula | C16: Programa | D16: Base técnica | E16: Resumen y ajuste propuesto
B17: Parámetros | C17: Auxiliar de intangibles y goodwill | D17: Reconocimiento e investigación / desarrollo | E17: Amortización y vida finita / indefinida
B18: Revisión de vida útil y valor residual | C18: Deterioro e importe recuperable | D18: Reversión del deterioro | E18: Valor neto y ajuste propuesto
B19: Problemas encontrados | C19: Conclusión | D19: Control de revisión
B21: PANORAMA | N21: Datos de los gráficos (fórmulas a las cédulas)
N22: Cifras del resumen | O22: Importe (USD)
N23: ='01_Resumen'!A5 | O23: ='01_Resumen'!B5
N24: ='01_Resumen'!A6 | O24: ='01_Resumen'!B6
N25: ='01_Resumen'!A7 | O25: ='01_Resumen'!B7
N26: ='01_Resumen'!A8 | O26: ='01_Resumen'!B8
N27: ='01_Resumen'!A9 | O27: ='01_Resumen'!B9
N28: ='01_Resumen'!A10 | O28: ='01_Resumen'!B10
N29: ='01_Resumen'!A11 | O29: ='01_Resumen'!B11
N30: ='01_Resumen'!A12 | O30: ='01_Resumen'!B12
N31: ='01_Resumen'!A13 | O31: ='01_Resumen'!B13
N32: ='01_Resumen'!A14 | O32: ='01_Resumen'!B14
N33: ='01_Resumen'!A15 | O33: ='01_Resumen'!B15
N34: ='01_Resumen'!A16 | O34: ='01_Resumen'!B16
... N36: ='01_Resumen'!A18 | O36: ='01_Resumen'!B18
N38: Hallazgos de mayor impacto | O38: Importe (USD)
N39: Ajuste | O39: =SUMIFS('10_Problemas'!$C$5:$C$18,'10_Problemas'!$A$5:$A$18,"AJUSTE",'10_Problemas'!$C$5:$C$18,">0")-SUMIFS('10_Problemas'!$C$5:$C$18,'10_Problemas'!$A$5:$A$18,"AJUSTE",'10_Problemas'!$C$5:$C$18,"<0")
N40: Sin prueba deterioro | O40: =SUMIFS('10_Problemas'!$C$5:$C$18,'10_Problemas'!$A$5:$A$18,"SIN_PRUEBA_DETERIORO",'10_Problemas'!$C$5:$C$18,">0")-SUMIFS('10_Problemas'!$C$5:$C$18,'10_Problemas'!$A$5:$A$18,"SIN_PRUEBA_DETERIORO",'10_Problemas'!$C$5:$C$18,"<0")
N41: Sin revision vida | O41: =SUMIFS('10_Problemas'!$C$5:$C$18,'10_Problemas'!$A$5:$A$18,"SIN_REVISION_VIDA",'10_Problemas'!$C$5:$C$18,">0")-SUMIFS('10_Problemas'!$C$5:$C$18,'10_Problemas'!$A$5:$A$18,"SIN_REVISION_VIDA",'10_Problemas'!$C$5:$C$18,"<0")
N42: Metodo ingresos excepcion | O42: =SUMIFS('10_Problemas'!$C$5:$C$18,'10_Problemas'!$A$5:$A$18,"METODO_INGRESOS_EXCEPCION",'10_Problemas'!$C$5:$C$18,">0")-SUMIFS('10_Problemas'!$C$5:$C$18,'10_Problemas'!$A$5:$A$18,"METODO_INGRESOS_EXCEPCION",'10_Problemas'!$C$5:$C$18,"<0")
N43: Investigacion capitalizada | O43: =SUMIFS('10_Problemas'!$C$5:$C$18,'10_Problemas'!$A$5:$A$18,"INVESTIGACION_CAPITALIZADA",'10_Problemas'!$C$5:$C$18,">0")-SUMIFS('10_Problemas'!$C$5:$C$18,'10_Problemas'!$A$5:$A$18,"INVESTIGACION_CAPITALIZADA",'10_Problemas'!$C$5:$C$18,"<0")
N44: Reversion goodwill | O44: =SUMIFS('10_Problemas'!$C$5:$C$18,'10_Problemas'!$A$5:$A$18,"REVERSION_GOODWILL",'10_Problemas'!$C$5:$C$18,">0")-SUMIFS('10_Problemas'!$C$5:$C$18,'10_Problemas'!$A$5:$A$18,"REVERSION_GOODWILL",'10_Problemas'!$C$5:$C$18,"<0")
N45: Desarrollo no cumple 57 | O45: =SUMIFS('10_Problemas'!$C$5:$C$18,'10_Problemas'!$A$5:$A$18,"DESARROLLO_NO_CUMPLE_57",'10_Problemas'!$C$5:$C$18,">0")-SUMIFS('10_Problemas'!$C$5:$C$18,'10_Problemas'!$A$5:$A$18,"DESARROLLO_NO_CUMPLE_57",'10_Problemas'!$C$5:$C$18,"<0")
N46: Otros (7 tipos) | O46: =SUMIF('10_Problemas'!$C$5:$C$18,">0")-SUMIF('10_Problemas'!$C$5:$C$18,"<0")-((SUMIFS('10_Problemas'!$C$5:$C$18,'10_Problemas'!$A$5:$A$18,"AJUSTE",'10_Problemas'!$C$5:$C$18,">0")-SUMIFS('10_Problemas'!$C$5:$C$18,'10_Problemas'!$A$5:$A$18,"AJUSTE",'10_Problemas'!$C$5:$C$18,"<0"))+(SUMIFS('10_Problemas'!$C$5:$C$18,'10_Problemas'!$A$5:$A$18,"SIN_PRUEBA_DETERIORO",'10_Problemas'!$C$5:$C$18,">0")-SUMIFS('10_Problemas'!$C$5:$C$18,'10_Problemas'!$A$5:$A$18,"SIN_PRUEBA_DETERIORO",'10_Problemas'!$C$5:$C$18,"<0"))+(SUMIFS('10_Problemas'!$C$5:$C$18,'10_Problemas'!$A$5:$A$18,"SIN_REVISION_VIDA",'10_Problemas'!$C$5:$C$18,">0")-SUMIFS('10_Problemas'!$C$5:$C$18,'10_Problemas'!$A$5:$A$18,"SIN_REVISION_VIDA",'10_Problemas'!$C$5:$C$18,"<0"))+(SUMIFS('10_Problemas'!$C$5:$C$18,'10_Problemas'!$A$5:$A$18,"METODO_INGRESOS_EXCEPCION",'10_Problemas'!$C$5:$C$18,">0")-SUMIFS('10_Problemas'!$C$5:$C$18,'10_Problemas'!$A$5:$A$18,"METODO_INGRESOS_EXCEPCION",'10_Problemas'!$C$5:$C$18,"<0"))+(SUMIFS('10_Problemas'!$C$5:$C$18,'10_Problemas'!$A$5:$A$18,"INVESTIGACION_CAPITALIZADA",'10_Problemas'!$C$5:$C$18,">0")-SUMIFS('10_Problemas'!$C$5:$C$18,'10_Problemas'!$A$5:$A$18,"INVESTIGACION_CAPITALIZADA",'10_Problemas'!$C$5:$C$18,"<0"))+(SUMIFS('10_Problemas'!$C$5:$C$18,'10_Problemas'!$A$5:$A$18,"REVERSION_GOODWILL",'10_Problemas'!$C$5:$C$18,">0")-SUMIFS('10_Problemas'!$C$5:$C$18,'10_Problemas'!$A$5:$A$18,"REVERSION_GOODWILL",'10_Problemas'!$C$5:$C$18,"<0"))+(SUMIFS('10_Problemas'!$C$5:$C$18,'10_Problemas'!$A$5:$A$18,"DESARROLLO_NO_CUMPLE_57",'10_Problemas'!$C$5:$C$18,">0")-SUMIFS('10_Problemas'!$C$5:$C$18,'10_Problemas'!$A$5:$A$18,"DESARROLLO_NO_CUMPLE_57",'10_Problemas'!$C$5:$C$18,"<0")))

Sheet 00_Caratula
A1: Carátula | H1: ⟵ Inicio | J1: Siguiente ▶
A2: Activos intangibles y goodwill · Cliente de muestra S.A. · corte 2025-12-31
A4: Concepto | B4: Detalle
A5: Firma | B5: AuditConsulting Auditores Cía. Ltda.
A6: Cliente | B6: Cliente de muestra S.A.
A7: RUC | B7: 1790000000001
A8: Ejercicio | B8: 2025
A9: Fecha de corte | B9: 2025-12-31
A10: Marco contable | B10: NIIF completas
A11: Herramienta | B11: Activos intangibles y goodwill
A12: Rubro | B12: Intangibles
A13: Motor | B13: intangibles_goodwill 1.0
A14: Versión del papel | B14: v1
A15: Estado | B15: MUESTRA
... A17: Revisó | B17: Pendiente
A18: Aprobó
A19: Fecha de aprobación
A20: Huella de la ejecución (SHA-256)

Sheet 00_Programa
A1: Programa | H1: ⟵ Inicio | I1: ◀ Anterior | J1: Siguiente ▶
A2: Activos intangibles y goodwill · Cliente de muestra S.A. · corte 2025-12-31
A4: Código | B4: Objetivo | C4: Afirmación | D4: Procedimiento | E4: Evidencia | F4: Criterio | G4: Referencia
A5: INT-01 | B5: Reconocimiento | C5: Existencia | D5: Cotejar costo y titularidad con contratos, facturas y registros; evaluar probabilidad de beneficios | E5: Contratos, facturas, registros de marcas y patentes | F5: Solo se reconoce lo que cumple NIC 38.21 / PYMES 18.4 | G5: NIC 38.21-23 · PYMES 18.4
A6: INT-02 | B6: Investigación y desarrollo | C6: Valoración | D6: Separar fases; en NIIF completas verificar los seis criterios de NIC 38.57; en PYMES llevar todo a gasto | E6: Memorias del proyecto, presupuestos, estudios de viabilidad | F6: Investigación y desarrollo sin criterios a gasto | G6: NIC 38.54, 38.57 · PYMES 18.14, INT-04
A7: INT-03 | B7: Amortización | C7: Valoración | D7: Recalcular la amortización desde la fecha disponible para su uso con la vida y el residual | E7: Auxiliar, actas de puesta en marcha | F7: Amortización recalculada = registrada | G7: NIC 38.97-100 · PYMES 18.21-18.23, INT-06
A8: INT-04 | B8: Vida útil finita e indefinida | C8: Valoración | D8: Evaluar la clasificación de la vida, su revisión anual y, en PYMES, que toda vida sea finita (máximo diez años sin estimación fiable) | E8: Análisis de factores de vida útil, contratos | F8: Clasificación sustentada y revisada | G8: NIC 38.88-96, 38.104, 38.107-110 · PYMES 18.19-18.20, 18.24, INT-08
A9: INT-05 | B9: Deterioro | C9: Valoración | D9: Revisar la prueba de deterioro: valor en uso y VR menos costos; prueba anual de goodwill, vida indefinida y no disponibles (NIIF completas) | E9: Modelos de flujos, tasas de descuento, tasaciones | F9: Pérdida reconocida | G9: NIC 36.10 a y b, 36.18, 36.59, 36.90 · PYMES 27.5-27.7
A10: INT-06 | B10: Goodwill | C10: Valoración | D10: Verificar la medición del goodwill según el marco y la prohibición de revertir su deterioro | E10: Asignación del precio de compra, pruebas de deterioro | F10: Tratamiento según el marco | G10: NIIF 3.32, B63 a · NIC 36.124 · PYMES 19.23 (2015) / 19.34 (2025), 27.28, INT-10
A11: INT-07 | B11: Reversión del deterioro | C11: Valoración | D11: Con indicio, recalcular la reversión limitada al importe en libros sin deterioro | E11: Nuevas estimaciones del recuperable | F11: Reversión dentro del límite | G11: NIC 36.114-119 · PYMES 27.29-27.30
A12: INT-09 | B12: Método de amortización | C12: Valoración | D12: Confirmar el método informado por el cliente; si se basa en los ingresos, exigir la excepción documentada («a» el intangible se expresa como una medida de los ingresos o «b» alta correlación entre ingresos y consumo de los beneficios) y, si no la hay, recalcular por el método lineal y cuantificar el efecto en resultados | E12: Contrato que fija el importe total de ingresos a generar, análisis de correlación, papel de cálculo de la amortización | F12: Método admitido por la norma y aplicado de forma coherente de ejercicio a ejercicio | G12: NIC 38.97-98, 98A-98C · PYMES 2025 18.22A (la edición 2015 solo exige 18.22: patrón esperado de consumo)
A13: INT-08 | B13: Conciliación con el mayor | C13: Integridad | D13: Conciliar el neto del auxiliar con el mayor y proponer el ajuste | E13: Auxiliar y mayor | F13: Diferencia explicada o ajustada | G13: NIA 330

Sheet 00_Fuentes
A1: Base técnica | H1: ⟵ Inicio | I1: ◀ Anterior | J1: Siguiente ▶
A2: Activos intangibles y goodwill · Cliente de muestra S.A. · corte 2025-12-31
A4: Categoría | B4: Documento | C4: Párrafos | D4: URL | E4: Verificada
A5: NIA · NIA 540 (Revisada) | B5: Vida útil, residual, valor en uso y VR menos costos son estimaciones: evaluar método, datos y supuestos. | C5: párr. 13, 16–17, 18–27 y 28–30
A6: NIA · NIA 500 | B6: Evidencia suficiente del costo, la fecha de disponibilidad y los criterios de NIC 38.57. | C6: párr. 6 y 9
A7: NIA · NIA 500 | B7: Evaluar el trabajo del experto en valoración usado para el importe recuperable y la asignación del precio de compra. | C7: párr. 8 (experto de la dirección; NIA 620 solo si lo contrata el auditor)
A8: NIA · NIA 330 | B8: Procedimientos sustantivos y conciliación del auxiliar con el mayor. | C8: párr. 18-20
A9: NIA · NIA 560 | B9: Hechos posteriores que evidencien deterioro al cierre. | C9: párr. 6

Sheet 01_Resumen
A1: Resumen y ajuste propuesto | H1: ⟵ Inicio | I1: ◀ Anterior | J1: Siguiente ▶
A2: Activos intangibles y goodwill · Cliente de muestra S.A. · corte 2025-12-31
A4: Concepto | B4: Importe
A5: Intangibles netos auditados | B5: =SUM('09_Ajuste'!$D$5:$D$17)
A6: Intangibles netos según el mayor | B6: =IF('02_Parametros'!$B$11="",SUM('09_Ajuste'!$C$5:$C$17),'02_Parametros'!$B$11)
A7: Ajuste propuesto (neto) | B7: =B5-B6
A8: Neto según el auxiliar del cliente | B8: =SUM('09_Ajuste'!$C$5:$C$17)
A9: Diferencia auxiliar − mayor | B9: =B8-B6
A10: Investigación / desarrollo no capitalizable (baja) | B10: =SUM('04_Reconocimiento'!$J$5:$J$17)
A11: Amortización del año recalculada (método lineal) | B11: =SUM('05_Amortizacion'!$K$5:$K$17)
A12: Amortización del año auditada (recalculada o aceptada) | B12: =SUM('05_Amortizacion'!$R$5:$R$17)
A13: Amortización del año registrada | B13: =SUM('05_Amortizacion'!$L$5:$L$17)
A14: Diferencia de amortización | B14: =SUM('05_Amortizacion'!$M$5:$M$17)
A15: Deterioro del año auditado | B15: =SUM('07_Deterioro'!$K$5:$K$17)
A16: Deterioro del año registrado | B16: =SUM('07_Deterioro'!$J$5:$J$17)
A17: Reversión de deterioro auditada | B17: =SUM('08_Reversion'!$I$5:$I$17)
A18: Reversión de deterioro registrada | B18: =SUM('08_Reversion'!$H$5:$H$17)
A20: ⓘ Cómo se calcula esta hoja
A21: Columna | B21: Fórmula (Excel) | C21: Cómo se calcula (sencillo) | D21: Ejemplo con números reales | E21: De dónde viene | F21: Norma
A22: Importe | B22: '=SUM('09_Ajuste'!$D$5:$D$17) | C22: Trae cada importe de la hoja de cálculo que le corresponde, concepto por concepto: los netos salen de la hoja 09 (Valor neto y ajuste propuesto), la baja a gasto de la hoja 04, la amortización de la hoja 05, el deterioro de la 07 y la reversión de la 08. El saldo del mayor es el del parámetro (si está en blanco, el neto del auxiliar) y el ajuste es el neto auditado menos ese saldo del mayor. | D22: Fila 1: SUM([«Neto auditado» de «Valor neto y ajuste propuesto», 13 filas]) → 549.050,00 | E22: hoja «Valor neto y ajuste propuesto» | F22: —

Sheet 02_Parametros
A1: Parámetros | H1: ⟵ Inicio | I1: ◀ Anterior | J1: Siguiente ▶
A2: Activos intangibles y goodwill · Cliente de muestra S.A. · corte 2025-12-31
A4: Parámetro | B4: Valor | C4: Sustento
A5: Corte del ejercicio | B5: 46022 | C5: Ficha del encargo; ejercicio de 12 meses que termina en el corte
A6: Marco contable | B6: NIIF completas · NIC 38, NIC 36 y NIIF 3 | C6: PYMES 2015 y 2025: investigación y desarrollo a gasto y goodwill amortizable en su vida útil; solo si no puede establecerse con fiabilidad, mejor estimación de la gerencia no mayor a diez años (19.23 en 2015; 19.34 en 2025). 2025: 18.22A presume que la amortización basada en ingresos no es apropiada; Sección 19 alineada con NIIF 3; la plusvalía sigue amortizándose; vigente desde el 1-1-2027; para cortes 2025–2026 solo con adopción anticipada
A7: Ruta PYMES (1 = sí, 0 = NIIF completas) | B7: 0 | C7: 1: todo intangible y el goodwill se amortizan y el desarrollo va a gasto; 0: vida indefinida y goodwill sin amortizar con prueba anual
A8: Edición PYMES | B8: 2015 | C8: Ficha del encargo
A9: Presunción contra la amortización basada en ingresos (1 = sí, 0 = no) | B9: 1 | C9: 1: NIC 38.98A (NIIF completas) y 18.22A (PYMES 2025) presumen inapropiado el método basado en los ingresos ordinarios y solo admiten dos circunstancias: que el intangible se exprese como una medida de los ingresos —importe total fijo de ingresos a generar fijado en el contrato (NIC 38.98C)— o que se demuestre que los ingresos y el consumo de los beneficios están estrechamente correlacionados. Sin esa justificación documentada la herramienta recalcula por el método lineal (NIC 38.97; PYMES 18.22). 0: la edición 2015 de la NIIF para las PYMES no contiene esa presunción (18.22 solo exige que el método refleje el patrón esperado de consumo): el método informado se acepta, no se recalcula y se pide el papel que lo sustenta
A10: PYMES: vida útil máxima si no es fiable (meses) | B10: 120 | C10: PYMES: TOPE de la mejor estimación de la gerencia cuando la vida no se puede establecer con fiabilidad (18.20 / 19.23 en 2015; 19.34 en 2025). No es una vida por defecto: sin vida en la ficha la partida no se amortiza y se pide la estimación; si la vida excede el tope, se limita al tope
A11: Intangibles netos según el mayor | B11: 591050 | C11: Mayor contable (en blanco: se toma el auxiliar)

Sheet 03_Intangibles
A1: Auxiliar de intangibles y goodwill | H1: ⟵ Inicio | I1: ◀ Anterior | J1: Siguiente ▶
A2: Activos intangibles y goodwill · Cliente de muestra S.A. · corte 2025-12-31
A4: Código | B4: Descripción | C4: Tipo | D4: Fase | E4: Cumple NIC 38.57 | F4: Disponible para uso | G4: Costo | H4: Valor residual | I4: Vida útil (meses) | J4: Amort. acum. inicial | K4: Amort. del año registrada | L4: Deterioro acum. previo | M4: Valor en uso | N4: VR menos costos de disposición | O4: Deterioro del año registrado | P4: Indicio de reversión | Q4: Reversión registrada | R4: Vida revisada al cierre | S4: Método de amortización informado | T4: Justificación del método por ingresos (a / b + papel)
A5: SW-01 | B5: Software ERP | C5: Software | F5: 44927 | G5: 60000 | I5: 60 | J5: 24000 | K5: 12000 | R5: Sí
A6: LIC-01 | B6: Licencia de distribución exclusiva | C6: Licencia | F6: 45748 | G6: 24000 | I6: 36 | J6: 0 | K6: 8000 | R6: Sí
A7: MAR-01 | B7: Marca comercial adquirida | C7: Marca | F7: 44743 | G7: 150000 | M7: 140000 | N7: 130000 | R7: Sí
A8: GW-01 | B8: Goodwill adquisición Distribuidora Andina | C8: Goodwill | F8: 44197 | G8: 200000 | L8: 30000 | M8: 185000 | P8: Sí | Q8: 15000 | R8: Sí
A9: INV-01 | B9: Estudio de mercado y prototipos nuevo producto | C9: Proyecto interno | D9: Investigación | G9: 18000 | R9: Sí
A10: DES-01 | B10: Aplicación móvil de pedidos | C10: Desarrollo | D10: Desarrollo | E10: Sí | F10: 45931 | G10: 45000 | I10: 36 | J10: 0 | K10: 3750 | R10: Sí
A11: DES-02 | B11: Módulo de comercio electrónico | C11: Desarrollo | D11: Desarrollo | E11: No | G11: 12000 | R11: Sí
A12: DES-03 | B12: Plataforma logística en desarrollo | C12: Desarrollo | D12: Desarrollo | E12: Sí | G12: 30000 | I12: 60 | R12: Sí
A13: PAT-01 | B13: Patente de proceso | C13: Patente | F13: 43831 | G13: 80000 | H13: 8000 | I13: 120 | J13: 36000 | K13: 7200 | L13: 10000 | M13: 40000 | N13: 38000 | P13: Sí | R13: No
A14: SW-02 | B14: Software CRM | C14: Software | F14: 43466 | G14: 9000 | I14: 48 | J14: 9000 | K14: 0 | R14: Sí
A15: SW-03 | B15: Software de nómina | C15: Software | F15: 45474 | G15: 12000 | I15: 36 | J15: 1000 | K15: 4000 | R15: Sí
A16: CON-01 | B16: Concesión de distribución regional | C16: Licencia | F16: 45658 | G16: 36000 | I16: 48 | J16: 0 | K16: 12000 | R16: Sí | S16: Ingresos del contrato
A17: CON-02 | B17: Concesión de peaje (importe total fijo de ingresos) | C17: Licencia | F17: 45292 | G17: 100000 | I17: 96 | J17: 20000 | K17: 25000 | R17: Sí | S17: Ingresos | T17: a) el contrato fija un importe total de peajes a recaudar; ver PT-INT-07
A18: TOTAL | G18: =SUM(G5:G17)

Sheet 04_Reconocimiento
A1: Reconocimiento e investigación / desarrollo | H1: ⟵ Inicio | I1: ◀ Anterior | J1: Siguiente ▶
A2: Activos intangibles y goodwill · Cliente de muestra S.A. · corte 2025-12-31
A4: Código | B4: Tipo | C4: Fase | D4: Cumple NIC 38.57 | E4: Categoría | F4: Capitalizable | G4: Criterio | H4: Costo registrado | I4: Costo auditado | J4: Neto a dar de baja (gasto)
A5: SW-01 | B5: ='03_Intangibles'!C5&"" | C5: ='03_Intangibles'!D5&"" | D5: ='03_Intangibles'!E5&"" | E5: =IF(OR(ISNUMBER(SEARCH("investig",B5)),ISNUMBER(SEARCH("investig",C5))),"Investigación",IF(OR(ISNUMBER(SEARCH("desarroll",B5)),ISNUMBER(SEARCH("desarroll",C5))),"Desarrollo",IF(OR(ISNUMBER(SEARCH("goodwill",B5)),ISNUMBER(SEARCH("plusval",B5))),"Goodwill","Otro"))) | F5: =IF(E5="Investigación","No",IF(E5="Desarrollo",IF('02_Parametros'!$B$7=1,"No",IF(D5="No","No","Sí")),"Sí")) | G5: =IF(E5="Investigación","Investigación a gasto (NIC 38.54; PYMES 18.14)",IF(AND(E5="Desarrollo",'02_Parametros'!$B$7=1),"PYMES: desarrollo a gasto (18.14)",IF(AND(E5="Desarrollo",D5="No"),"No cumple NIC 38.57",IF(AND(E5="Desarrollo",D5=""),"Criterios 57 sin evidencia","Reconocido (NIC 38.21; PYMES 18.4)")))) | H5: ='03_Intangibles'!G5 | I5: =IF(F5="Sí",H5,0) | J5: =IF(F5="No",'03_Intangibles'!G5-'03_Intangibles'!J5-'03_Intangibles'!K5-'03_Intangibles'!L5-'03_Intangibles'!O5+'03_Intangibles'!Q5,0)
A6: LIC-01 | B6: ='03_Intangibles'!C6&"" | C6: ='03_Intangibles'!D6&"" | D6: ='03_Intangibles'!E6&"" | E6: =IF(OR(ISNUMBER(SEARCH("investig",B6)),ISNUMBER(SEARCH("investig",C6))),"Investigación",IF(OR(ISNUMBER(SEARCH("desarroll",B6)),ISNUMBER(SEARCH("desarroll",C6))),"Desarrollo",IF(OR(ISNUMBER(SEARCH("goodwill",B6)),ISNUMBER(SEARCH("plusval",B6))),"Goodwill","Otro"))) | F6: =IF(E6="Investigación","No",IF(E6="Desarrollo",IF('02_Parametros'!$B$7=1,"No",IF(D6="No","No","Sí")),"Sí")) | G6: =IF(E6="Investigación","Investigación a gasto (NIC 38.54; PYMES 18.14)",IF(AND(E6="Desarrollo",'02_Parametros'!$B$7=1),"PYMES: desarrollo a gasto (18.14)",IF(AND(E6="Desarrollo",D6="No"),"No cumple NIC 38.57",IF(AND(E6="Desarrollo",D6=""),"Criterios 57 sin evidencia","Reconocido (NIC 38.21; PYMES 18.4)")))) | H6: ='03_Intangibles'!G6 | I6: =IF(F6="Sí",H6,0) | J6: =IF(F6="No",'03_Intangibles'!G6-'03_Intangibles'!J6-'03_Intangibles'!K6-'03_Intangibles'!L6-'03_Intangibles'!O6+'03_Intangibles'!Q6,0)
A7: MAR-01 | B7: ='03_Intangibles'!C7&"" | C7: ='03_Intangibles'!D7&"" | D7: ='03_Intangibles'!E7&"" | E7: =IF(OR(ISNUMBER(SEARCH("investig",B7)),ISNUMBER(SEARCH("investig",C7))),"Investigación",IF(OR(ISNUMBER(SEARCH("desarroll",B7)),ISNUMBER(SEARCH("desarroll",C7))),"Desarrollo",IF(OR(ISNUMBER(SEARCH("goodwill",B7)),ISNUMBER(SEARCH("plusval",B7))),"Goodwill","Otro"))) | F7: =IF(E7="Investigación","No",IF(E7="Desarrollo",IF('02_Parametros'!$B$7=1,"No",IF(D7="No","No","Sí")),"Sí")) | G7: =IF(E7="Investigación","Investigación a gasto (NIC 38.54; PYMES 18.14)",IF(AND(E7="Desarrollo",'02_Parametros'!$B$7=1),"PYMES: desarrollo a gasto (18.14)",IF(AND(E7="Desarrollo",D7="No"),"No cumple NIC 38.57",IF(AND(E7="Desarrollo",D7=""),"Criterios 57 sin evidencia","Reconocido (NIC 38.21; PYMES 18.4)")))) | H7: ='03_Intangibles'!G7 | I7: =IF(F7="Sí",H7,0) | J7: =IF(F7="No",'03_Intangibles'!G7-'03_Intangibles'!J7-'03_Intangibles'!K7-'03_Intangibles'!L7-'03_Intangibles'!O7+'03_Intangibles'!Q7,0)
A8: GW-01 | B8: ='03_Intangibles'!C8&"" | C8: ='03_Intangibles'!D8&"" | D8: ='03_Intangibles'!E8&"" | E8: =IF(OR(ISNUMBER(SEARCH("investig",B8)),ISNUMBER(SEARCH("investig",C8))),"Investigación",IF(OR(ISNUMBER(SEARCH("desarroll",B8)),ISNUMBER(SEARCH("desarroll",C8))),"Desarrollo",IF(OR(ISNUMBER(SEARCH("goodwill",B8)),ISNUMBER(SEARCH("plusval",B8))),"Goodwill","Otro"))) | F8: =IF(E8="Investigación","No",IF(E8="Desarrollo",IF('02_Parametros'!$B$7=1,"No",IF(D8="No","No","Sí")),"Sí")) | G8: =IF(E8="Investigación","Investigación a gasto (NIC 38.54; PYMES 18.14)",IF(AND(E8="Desarrollo",'02_Parametros'!$B$7=1),"PYMES: desarrollo a gasto (18.14)",IF(AND(E8="Desarrollo",D8="No"),"No cumple NIC 38.57",IF(AND(E8="Desarrollo",D8=""),"Criterios 57 sin evidencia","Reconocido (NIC 38.21; PYMES 18.4)")))) | H8: ='03_Intangibles'!G8 | I8: =IF(F8="Sí",H8,0) | J8: =IF(F8="No",'03_Intangibles'!G8-'03_Intangibles'!J8-'03_Intangibles'!K8-'03_Intangibles'!L8-'03_Intangibles'!O8+'03_Intangibles'!Q8,0)
A9: INV-01 | B9: ='03_Intangibles'!C9&"" | C9: ='03_Intangibles'!D9&"" | D9: ='03_Intangibles'!E9&"" | E9: =IF(OR(ISNUMBER(SEARCH("investig",B9)),ISNUMBER(SEARCH("investig",C9))),"Investigación",IF(OR(ISNUMBER(SEARCH("desarroll",B9)),ISNUMBER(SEARCH("desarroll",C9))),"Desarrollo",IF(OR(ISNUMBER(SEARCH("goodwill",B9)),ISNUMBER(SEARCH("plusval",B9))),"Goodwill","Otro"))) | F9: =IF(E9="Investigación","No",IF(E9="Desarrollo",IF('02_Parametros'!$B$7=1,"No",IF(D9="No","No","Sí")),"Sí")) | G9: =IF(E9="Investigación","Investigación a gasto (NIC 38.54; PYMES 18.14)",IF(AND(E9="Desarrollo",'02_Parametros'!$B$7=1),"PYMES: desarrollo a gasto (18.14)",IF(AND(E9="Desarrollo",D9="No"),"No cumple NIC 38.57",IF(AND(E9="Desarrollo",D9=""),"Criterios 57 sin evidencia","Reconocido (NIC 38.21; PYMES 18.4)")))) | H9: ='03_Intangibles'!G9 | I9: =IF(F9="Sí",H9,0) | J9: =IF(F9="No",'03_Intangibles'!G9-'03_Intangibles'!J9-'03_Intangibles'!K9-'03_Intangibles'!L9-'03_Intangibles'!O9+'03_Intangibles'!Q9,0)
A10: DES-01 | B10: ='03_Intangibles'!C10&"" | C10: ='03_Intangibles'!D10&"" | D10: ='03_Intangibles'!E10&"" | E10: =IF(OR(ISNUMBER(SEARCH("investig",B10)),ISNUMBER(SEARCH("investig",C10))),"Investigación",IF(OR(ISNUMBER(SEARCH("desarroll",B10)),ISNUMBER(SEARCH("desarroll",C10))),"Desarrollo",IF(OR(ISNUMBER(SEARCH("goodwill",B10)),ISNUMBER(SEARCH("plusval",B10))),"Goodwill","Otro"))) | F10: =IF(E10="Investigación","No",IF(E10="Desarrollo",IF('02_Parametros'!$B$7=1,"No",IF(D10="No","No","Sí")),"Sí")) | G10: =IF(E10="Investigación","Investigación a gasto (NIC 38.54; PYMES 18.14)",IF(AND(E10="Desarrollo",'02_Parametros'!$B$7=1),"PYMES: desarrollo a gasto (18.14)",IF(AND(E10="Desarrollo",D10="No"),"No cumple NIC 38.57",IF(AND(E10="Desarrollo",D10=""),"Criterios 57 sin evidencia","Reconocido (NIC 38.21; PYMES 18.4)")))) | H10: ='03_Intangibles'!G10 | I10: =IF(F10="Sí",H10,0) | J10: =IF(F10="No",'03_Intangibles'!G10-'03_Intangibles'!J10-'03_Intangibles'!K10-'03_Intangibles'!L10-'03_Intangibles'!O10+'03_Intangibles'!Q10,0)
A11: DES-02 | B11: ='03_Intangibles'!C11&"" | C11: ='03_Intangibles'!D11&"" | D11: ='03_Intangibles'!E11&"" | E11: =IF(OR(ISNUMBER(SEARCH("investig",B11)),ISNUMBER(SEARCH("investig",C11))),"Investigación",IF(OR(ISNUMBER(SEARCH("desarroll",B11)),ISNUMBER(SEARCH("desarroll",C11))),"Desarrollo",IF(OR(ISNUMBER(SEARCH("goodwill",B11)),ISNUMBER(SEARCH("plusval",B11))),"Goodwill","Otro"))) | F11: =IF(E11="Investigación","No",IF(E11="Desarrollo",IF('02_Parametros'!$B$7=1,"No",IF(D11="No","No","Sí")),"Sí")) | G11: =IF(E11="Investigación","Investigación a gasto (NIC 38.54; PYMES 18.14)",IF(AND(E11="Desarrollo",'02_Parametros'!$B$7=1),"PYMES: desarrollo a gasto (18.14)",IF(AND(E11="Desarrollo",D11="No"),"No cumple NIC 38.57",IF(AND(E11="Desarrollo",D11=""),"Criterios 57 sin evidencia","Reconocido (NIC 38.21; PYMES 18.4)")))) | H11: ='03_Intangibles'!G11 | I11: =IF(F11="Sí",H11,0) | J11: =IF(F11="No",'03_Intangibles'!G11-'03_Intangibles'!J11-'03_Intangibles'!K11-'03_Intangibles'!L11-'03_Intangibles'!O11+'03_Intangibles'!Q11,0)
A12: DES-03 | B12: ='03_Intangibles'!C12&"" | C12: ='03_Intangibles'!D12&"" | D12: ='03_Intangibles'!E12&"" | E12: =IF(OR(ISNUMBER(SEARCH("investig",B12)),ISNUMBER(SEARCH("investig",C12))),"Investigación",IF(OR(ISNUMBER(SEARCH("desarroll",B12)),ISNUMBER(SEARCH("desarroll",C12))),"Desarrollo",IF(OR(ISNUMBER(SEARCH("goodwill",B12)),ISNUMBER(SEARCH("plusval",B12))),"Goodwill","Otro"))) | F12: =IF(E12="Investigación","No",IF(E12="Desarrollo",IF('02_Parametros'!$B$7=1,"No",IF(D12="No","No","Sí")),"Sí")) | G12: =IF(E12="Investigación","Investigación a gasto (NIC 38.54; PYMES 18.14)",IF(AND(E12="Desarrollo",'02_Parametros'!$B$7=1),"PYMES: desarrollo a gasto (18.14)",IF(AND(E12="Desarrollo",D12="No"),"No cumple NIC 38.57",IF(AND(E12="Desarrollo",D12=""),"Criterios 57 sin evidencia","Reconocido (NIC 38.21; PYMES 18.4)")))) | H12: ='03_Intangibles'!G12 | I12: =IF(F12="Sí",H12,0) | J12: =IF(F12="No",'03_Intangibles'!G12-'03_Intangibles'!J12-'03_Intangibles'!K12-'03_Intangibles'!L12-'03_Intangibles'!O12+'03_Intangibles'!Q12,0)
A13: PAT-01 | B13: ='03_Intangibles'!C13&"" | C13: ='03_Intangibles'!D13&"" | D13: ='03_Intangibles'!E13&"" | E13: =IF(OR(ISNUMBER(SEARCH("investig",B13)),ISNUMBER(SEARCH("investig",C13))),"Investigación",IF(OR(ISNUMBER(SEARCH("desarroll",B13)),ISNUMBER(SEARCH("desarroll",C13))),"Desarrollo",IF(OR(ISNUMBER(SEARCH("goodwill",B13)),ISNUMBER(SEARCH("plusval",B13))),"Goodwill","Otro"))) | F13: =IF(E13="Investigación","No",IF(E13="Desarrollo",IF('02_Parametros'!$B$7=1,"No",IF(D13="No","No","Sí")),"Sí")) | G13: =IF(E13="Investigación","Investigación a gasto (NIC 38.54; PYMES 18.14)",IF(AND(E13="Desarrollo",'02_Parametros'!$B$7=1),"PYMES: desarrollo a gasto (18.14)",IF(AND(E13="Desarrollo",D13="No"),"No cumple NIC 38.57",IF(AND(E13="Desarrollo",D13=""),"Criterios 57 sin evidencia","Reconocido (NIC 38.21; PYMES 18.4)")))) | H13: ='03_Intangibles'!G13 | I13: =IF(F13="Sí",H13,0) | J13: =IF(F13="No",'03_Intangibles'!G13-'03_Intangibles'!J13-'03_Intangibles'!K13-'03_Intangibles'!L13-'03_Intangibles'!O13+'03_Intangibles'!Q13,0)
A14: SW-02 | B14: ='03_Intangibles'!C14&"" | C14: ='03_Intangibles'!D14&"" | D14: ='03_Intangibles'!E14&"" | E14: =IF(OR(ISNUMBER(SEARCH("investig",B14)),ISNUMBER(SEARCH("investig",C14))),"Investigación",IF(OR(ISNUMBER(SEARCH("desarroll",B14)),ISNUMBER(SEARCH("desarroll",C14))),"Desarrollo",IF(OR(ISNUMBER(SEARCH("goodwill",B14)),ISNUMBER(SEARCH("plusval",B14))),"Goodwill","Otro"))) | F14: =IF(E14="Investigación","No",IF(E14="Desarrollo",IF('02_Parametros'!$B$7=1,"No",IF(D14="No","No","Sí")),"Sí")) | G14: =IF(E14="Investigación","Investigación a gasto (NIC 38.54; PYMES 18.14)",IF(AND(E14="Desarrollo",'02_Parametros'!$B$7=1),"PYMES: desarrollo a gasto (18.14)",IF(AND(E14="Desarrollo",D14="No"),"No cumple NIC 38.57",IF(AND(E14="Desarrollo",D14=""),"Criterios 57 sin evidencia","Reconocido (NIC 38.21; PYMES 18.4)")))) | H14: ='03_Intangibles'!G14 | I14: =IF(F14="Sí",H14,0) | J14: =IF(F14="No",'03_Intangibles'!G14-'03_Intangibles'!J14-'03_Intangibles'!K14-'03_Intangibles'!L14-'03_Intangibles'!O14+'03_Intangibles'!Q14,0)
A15: SW-03 | B15: ='03_Intangibles'!C15&"" | C15: ='03_Intangibles'!D15&"" | D15: ='03_Intangibles'!E15&"" | E15: =IF(OR(ISNUMBER(SEARCH("investig",B15)),ISNUMBER(SEARCH("investig",C15))),"Investigación",IF(OR(ISNUMBER(SEARCH("desarroll",B15)),ISNUMBER(SEARCH("desarroll",C15))),"Desarrollo",IF(OR(ISNUMBER(SEARCH("goodwill",B15)),ISNUMBER(SEARCH("plusval",B15))),"Goodwill","Otro"))) | F15: =IF(E15="Investigación","No",IF(E15="Desarrollo",IF('02_Parametros'!$B$7=1,"No",IF(D15="No","No","Sí")),"Sí")) | G15: =IF(E15="Investigación","Investigación a gasto (NIC 38.54; PYMES 18.14)",IF(AND(E15="Desarrollo",'02_Parametros'!$B$7=1),"PYMES: desarrollo a gasto (18.14)",IF(AND(E15="Desarrollo",D15="No"),"No cumple NIC 38.57",IF(AND(E15="Desarrollo",D15=""),"Criterios 57 sin evidencia","Reconocido (NIC 38.21; PYMES 18.4)")))) | H15: ='03_Intangibles'!G15 | I15: =IF(F15="Sí",H15,0) | J15: =IF(F15="No",'03_Intangibles'!G15-'03_Intangibles'!J15-'03_Intangibles'!K15-'03_Intangibles'!L15-'03_Intangibles'!O15+'03_Intangibles'!Q15,0)
A16: CON-01 | B16: ='03_Intangibles'!C16&"" | C16: ='03_Intangibles'!D16&"" | D16: ='03_Intangibles'!E16&"" | E16: =IF(OR(ISNUMBER(SEARCH("investig",B16)),ISNUMBER(SEARCH("investig",C16))),"Investigación",IF(OR(ISNUMBER(SEARCH("desarroll",B16)),ISNUMBER(SEARCH("desarroll",C16))),"Desarrollo",IF(OR(ISNUMBER(SEARCH("goodwill",B16)),ISNUMBER(SEARCH("plusval",B16))),"Goodwill","Otro"))) | F16: =IF(E16="Investigación","No",IF(E16="Desarrollo",IF('02_Parametros'!$B$7=1,"No",IF(D16="No","No","Sí")),"Sí")) | G16: =IF(E16="Investigación","Investigación a gasto (NIC 38.54; PYMES 18.14)",IF(AND(E16="Desarrollo",'02_Parametros'!$B$7=1),"PYMES: desarrollo a gasto (18.14)",IF(AND(E16="Desarrollo",D16="No"),"No cumple NIC 38.57",IF(AND(E16="Desarrollo",D16=""),"Criterios 57 sin evidencia","Reconocido (NIC 38.21; PYMES 18.4)")))) | H16: ='03_Intangibles'!G16 | I16: =IF(F16="Sí",H16,0) | J16: =IF(F16="No",'03_Intangibles'!G16-'03_Intangibles'!J16-'03_Intangibles'!K16-'03_Intangibles'!L16-'03_Intangibles'!O16+'03_Intangibles'!Q16,0)
A17: CON-02 | B17: ='03_Intangibles'!C17&"" | C17: ='03_Intangibles'!D17&"" | D17: ='03_Intangibles'!E17&"" | E17: =IF(OR(ISNUMBER(SEARCH("investig",B17)),ISNUMBER(SEARCH("investig",C17))),"Investigación",IF(OR(ISNUMBER(SEARCH("desarroll",B17)),ISNUMBER(SEARCH("desarroll",C17))),"Desarrollo",IF(OR(ISNUMBER(SEARCH("goodwill",B17)),ISNUMBER(SEARCH("plusval",B17))),"Goodwill","Otro"))) | F17: =IF(E17="Investigación","No",IF(E17="Desarrollo",IF('02_Parametros'!$B$7=1,"No",IF(D17="No","No","Sí")),"Sí")) | G17: =IF(E17="Investigación","Investigación a gasto (NIC 38.54; PYMES 18.14)",IF(AND(E17="Desarrollo",'02_Parametros'!$B$7=1),"PYMES: desarrollo a gasto (18.14)",IF(AND(E17="Desarrollo",D17="No"),"No cumple NIC 38.57",IF(AND(E17="Desarrollo",D17=""),"Criterios 57 sin evidencia","Reconocido (NIC 38.21; PYMES 18.4)")))) | H17: ='03_Intangibles'!G17 | I17: =IF(F17="Sí",H17,0) | J17: =IF(F17="No",'03_Intangibles'!G17-'03_Intangibles'!J17-'03_Intangibles'!K17-'03_Intangibles'!L17-'03_Intangibles'!O17+'03_Intangibles'!Q17,0)
A18: TOTAL | H18: =SUM(H5:H17) | I18: =SUM(I5:I17) | J18: =SUM(J5:J17)
A20: ⓘ Cómo se calcula esta hoja
A21: Columna | B21: Fórmula (Excel) | C21: Cómo se calcula (sencillo) | D21: Ejemplo con números reales | E21: De dónde viene | F21: Norma
A22: Tipo | B22: '='03_Intangibles'!C5&"" | C22: Copia, como texto, el tipo de intangible (software, licencia, marca, goodwill…) que informó el cliente en la hoja 03 (Auxiliar de intangibles y goodwill). | D22: Fila 1: «Software»&"" → Software | E22: hoja «Auxiliar de intangibles y goodwill» | F22: —
A23: Fase | B23: '='03_Intangibles'!D5&"" | C23: Copia, como texto, la fase del proyecto interno (investigación o desarrollo) informada en la hoja 03 (Auxiliar de intangibles y goodwill); si no aplica, queda en blanco. | D23: Fila 1: (vacío)&"" → (en blanco) | E23: hoja «Auxiliar de intangibles y goodwill» | F23: —
A24: Cumple NIC 38.57 | B24: '='03_Intangibles'!E5&"" | C24: Copia la respuesta del cliente (Sí/No) sobre si el desarrollo cumple los criterios de la NIC 38.57, tomada de la hoja 03 (Auxiliar de intangibles y goodwill). | D24: Fila 1: (vacío)&"" → (en blanco) | E24: hoja «Auxiliar de intangibles y goodwill» | F24: —
A25: Categoría | B25: '=IF(OR(ISNUMBER(SEARCH("investig",B5)),ISNUMBER(SEARCH("investig",C5))),"Investigación",IF(OR(ISNUMBER(SEARCH("desarroll",B5)),ISNUMBER(SEARCH("desarroll",C5))),"Desarrollo",IF(OR(ISNUMBER(SEARCH("goodwill",B5)),ISNUMBER(SEARCH("plusval",B5))),"Goodwill","Otro"))) | C25: Clasifica la partida leyendo el tipo y la fase: si alguno menciona «investigación» es Investigación; si menciona «desarrollo» es Desarrollo; si el tipo dice «goodwill» o «plusvalía» es Goodwill; cualquier otro caso queda como Otro. | D25: Fila 1: IF(OR(ISNUMBER(SEARCH("investig"; «Software»)); ISNUMBER(SEARCH("investig"; (vacío)))); "Investigación"; IF(OR(ISNUMBER(SEARCH("desarroll"; «Software»)); ISNUMBER(SEARCH("desarroll"; (vacío)))); "Desarrollo"; IF(OR(ISNUMBER(SEARCH("goodwill"; «Software»)); ISNUMBER(SEARCH("plusval"; «Software»))); "Goodwill"; "Otro"))) → Otro | E25: «Tipo» (esta hoja), «Fase» (esta hoja) | F25: —
A26: Capitalizable | B26: '=IF(E5="Investigación","No",IF(E5="Desarrollo",IF('02_Parametros'!$B$7=1,"No",IF(D5="No","No","Sí")),"Sí")) | C26: Decide si la partida puede quedarse en el activo: la investigación nunca; el desarrollo no en la ruta PYMES (parámetro de la hoja 02) ni cuando el cliente respondió «No» a la NIC 38.57; todo lo demás sí. | D26: Fila 1: IF(«Otro»="Investigación"; "No"; IF(«Otro»="Desarrollo"; IF(0,00=1; "No"; IF((vacío)="No"; "No"; "Sí")); "Sí")) → Sí | E26: «Categoría» (esta hoja), «Cumple NIC 38.57» (esta hoja), hoja «Parámetros» | F26: —
A27: Criterio | B27: '=IF(E5="Investigación","Investigación a gasto (NIC 38.54; PYMES 18.14)",IF(AND(E5="Desarrollo",'02_Parametros'!$B$7=1),"PYMES: desarrollo a gasto (18.14)",IF(AND(E5="Desarrollo",D5="No"),"No cumple NIC 38.57",IF(AND(E5="Desarrollo",D5=""),"Criterios 57 sin evidencia","Reconocido (NIC 38.21; PYMES 18.4)")))) | C27: Escribe en palabras el motivo de la decisión anterior: investigación a gasto, desarrollo a gasto en PYMES, desarrollo que no cumple la NIC 38.57, desarrollo sin evidencia de esos criterios (respuesta en blanco) o intangible reconocido. | D27: Fila 1: IF(«Otro»="Investigación"; "Investigación a gasto (NIC 38.54; PYMES 18.14)"; IF(AND(«Otro»="Desarrollo"; 0,00=1); "PYMES: desarrollo a gasto (18.14)"; IF(AND(«Otro»="Desarrollo"; (vacío)="No"); "No cumple NIC 38.57"; IF(AND(«Otro»="Desarrollo"; (vacío)=""); "Criterios 57 sin evidencia"; "Reconocido (NIC 38.21; PYMES 18.4)")))) → Reconocido (NIC 38.21; PYMES 18.4) | E27: «Categoría» (esta hoja), «Cumple NIC 38.57» (esta hoja), hoja «Parámetros» | F27: —
A28: Costo registrado | B28: '='03_Intangibles'!G5 | C28: Trae el costo de la partida tal como lo registró el cliente en la hoja 03 (Auxiliar de intangibles y goodwill). | D28: Fila 1: 60.000,00 → 60.000,00 | E28: hoja «Auxiliar de intangibles y goodwill» | F28: —
A29: Costo auditado | B29: '=IF(F5="Sí",H5,0) | C29: Mantiene el costo registrado solo si la partida es capitalizable; si no lo es, el costo auditado es cero. | D29: Fila 1: IF(«Sí»="Sí"; 60.000,00; 0) → 60.000,00 | E29: «Capitalizable» (esta hoja), «Costo registrado» (esta hoja) | F29: —
A30: Neto a dar de baja (gasto) | B30: '=IF(F5="No",'03_Intangibles'!G5-'03_Intangibles'!J5-'03_Intangibles'!K5-'03_Intangibles'!L5-'03_Intangibles'!O5+'03_Intangibles'!Q5,0) | C30: Solo para partidas no capitalizables: parte del costo de la hoja 03 (Auxiliar de intangibles y goodwill), resta la amortización acumulada inicial, la del año, el deterioro previo y el del año, y suma la reversión registrada. Es el neto que debe pasar a gasto; en las capitalizables es cero. | D30: Fila 1: IF(«Sí»="No"; 60.000,00-24.000,00-12.000,00-(vacío)-(vacío)+(vacío); 0) → 0,00 | E30: «Capitalizable» (esta hoja), hoja «Auxiliar de intangibles y goodwill» | F30: —

Sheet 05_Amortizacion
A1: Amortización y vida finita / indefinida | H1: ⟵ Inicio | I1: ◀ Anterior | J1: Siguiente ▶
A2: Activos intangibles y goodwill · Cliente de muestra S.A. · corte 2025-12-31
A4: Código | B4: Categoría | C4: Capitalizable | D4: Costo auditado | E4: Valor residual | F4: Importe amortizable | G4: Vida aplicada (meses) | H4: Tipo de vida | I4: Meses en uso del ejercicio | J4: Importe pendiente | K4: Amortización recalculada (lineal) | L4: Amortización registrada (cliente) | M4: Diferencia | N4: Amort. acumulada recalculada | O4: Método informado por el cliente | P4: Circunstancia invocada (NIC 38.98A / 18.22A) | Q4: Método aplicado por la herramienta | R4: Amortización auditada
A5: SW-01 | B5: ='04_Reconocimiento'!E5 | C5: ='04_Reconocimiento'!F5 | D5: ='04_Reconocimiento'!I5 | E5: ='03_Intangibles'!H5+0 | F5: =MAX(D5-E5,0) | G5: =IF(C5="No","",IF('02_Parametros'!$B$7=1,IF('03_Intangibles'!I5="","",MIN('03_Intangibles'!I5,'02_Parametros'!$B$10)),IF(B5="Goodwill","",IF('03_Intangibles'!I5="","",'03_Intangibles'!I5)))) | H5: =IF(C5="No","No aplica",IF(G5<>"","Finita",IF('02_Parametros'!$B$7=1,"Sin estimación (18.20)",IF(B5="Goodwill","Goodwill: indefinida (no se amortiza)","Indefinida")))) | I5: =IF('03_Intangibles'!F5="",0,MAX(0,MIN(12,(YEAR('02_Parametros'!$B$5)-YEAR('03_Intangibles'!F5))*12+MONTH('02_Parametros'!$B$5)-MONTH('03_Intangibles'!F5)+1))) | J5: =MAX(F5-'03_Intangibles'!J5-'03_Intangibles'!L5,0) | K5: =IF(AND(C5="Sí",LEFT(Q5,6)<>"Lineal"),"",IF(AND('02_Parametros'!$B$7=1,C5="Sí",G5=""),"",IF(OR(G5="",I5=0),0,MIN(F5/G5*I5,J5)))) | L5: ='03_Intangibles'!K5+0 | M5: =IF(K5="","",K5-L5) | N5: ='03_Intangibles'!J5+IF(R5="",0,R5) | O5: ='03_Intangibles'!S5&"" | P5: =IF('03_Intangibles'!T5="","",IF(LEFT('03_Intangibles'!T5,1)="a","a) el intangible se expresa como una medida de los ingresos",IF(LEFT('03_Intangibles'!T5,1)="b","b) ingresos y consumo estrechamente correlacionados","No invoca ninguna de las dos circunstancias"))) | Q5: =IF(C5="No","No aplica",IF(ISNUMBER(SEARCH("ingres",O5)),IF('02_Parametros'!$B$9=0,"Ingresos (sin presunción: PYMES 2015)",IF(OR(LEFT(P5,1)="a",LEFT(P5,1)="b"),"Ingresos (excepción documentada)","Lineal (presunción no refutada)")),IF(OR(O5="",ISNUMBER(SEARCH("lineal",O5)),ISNUMBER(SEARCH("recta",O5))),"Lineal","Otro método informado (no recalculado)"))) | R5: =IF(AND(C5="Sí",LEFT(Q5,6)<>"Lineal"),L5,K5)
A6: LIC-01 | B6: ='04_Reconocimiento'!E6 | C6: ='04_Reconocimiento'!F6 | D6: ='04_Reconocimiento'!I6 | E6: ='03_Intangibles'!H6+0 | F6: =MAX(D6-E6,0) | G6: =IF(C6="No","",IF('02_Parametros'!$B$7=1,IF('03_Intangibles'!I6="","",MIN('03_Intangibles'!I6,'02_Parametros'!$B$10)),IF(B6="Goodwill","",IF('03_Intangibles'!I6="","",'03_Intangibles'!I6)))) | H6: =IF(C6="No","No aplica",IF(G6<>"","Finita",IF('02_Parametros'!$B$7=1,"Sin estimación (18.20)",IF(B6="Goodwill","Goodwill: indefinida (no se amortiza)","Indefinida")))) | I6: =IF('03_Intangibles'!F6="",0,MAX(0,MIN(12,(YEAR('02_Parametros'!$B$5)-YEAR('03_Intangibles'!F6))*12+MONTH('02_Parametros'!$B$5)-MONTH('03_Intangibles'!F6)+1))) | J6: =MAX(F6-'03_Intangibles'!J6-'03_Intangibles'!L6,0) | K6: =IF(AND(C6="Sí",LEFT(Q6,6)<>"Lineal"),"",IF(AND('02_Parametros'!$B$7=1,C6="Sí",G6=""),"",IF(OR(G6="",I6=0),0,MIN(F6/G6*I6,J6)))) | L6: ='03_Intangibles'!K6+0 | M6: =IF(K6="","",K6-L6) | N6: ='03_Intangibles'!J6+IF(R6="",0,R6) | O6: ='03_Intangibles'!S6&"" | P6: =IF('03_Intangibles'!T6="","",IF(LEFT('03_Intangibles'!T6,1)="a","a) el intangible se expresa como una medida de los ingresos",IF(LEFT('03_Intangibles'!T6,1)="b","b) ingresos y consumo estrechamente correlacionados","No invoca ninguna de las dos circunstancias"))) | Q6: =IF(C6="No","No aplica",IF(ISNUMBER(SEARCH("ingres",O6)),IF('02_Parametros'!$B$9=0,"Ingresos (sin presunción: PYMES 2015)",IF(OR(LEFT(P6,1)="a",LEFT(P6,1)="b"),"Ingresos (excepción documentada)","Lineal (presunción no refutada)")),IF(OR(O6="",ISNUMBER(SEARCH("lineal",O6)),ISNUMBER(SEARCH("recta",O6))),"Lineal","Otro método informado (no recalculado)"))) | R6: =IF(AND(C6="Sí",LEFT(Q6,6)<>"Lineal"),L6,K6)
A7: MAR-01 | B7: ='04_Reconocimiento'!E7 | C7: ='04_Reconocimiento'!F7 | D7: ='04_Reconocimiento'!I7 | E7: ='03_Intangibles'!H7+0 | F7: =MAX(D7-E7,0) | G7: =IF(C7="No","",IF('02_Parametros'!$B$7=1,IF('03_Intangibles'!I7="","",MIN('03_Intangibles'!I7,'02_Parametros'!$B$10)),IF(B7="Goodwill","",IF('03_Intangibles'!I7="","",'03_Intangibles'!I7)))) | H7: =IF(C7="No","No aplica",IF(G7<>"","Finita",IF('02_Parametros'!$B$7=1,"Sin estimación (18.20)",IF(B7="Goodwill","Goodwill: indefinida (no se amortiza)","Indefinida")))) | I7: =IF('03_Intangibles'!F7="",0,MAX(0,MIN(12,(YEAR('02_Parametros'!$B$5)-YEAR('03_Intangibles'!F7))*12+MONTH('02_Parametros'!$B$5)-MONTH('03_Intangibles'!F7)+1))) | J7: =MAX(F7-'03_Intangibles'!J7-'03_Intangibles'!L7,0) | K7: =IF(AND(C7="Sí",LEFT(Q7,6)<>"Lineal"),"",IF(AND('02_Parametros'!$B$7=1,C7="Sí",G7=""),"",IF(OR(G7="",I7=0),0,MIN(F7/G7*I7,J7)))) | L7: ='03_Intangibles'!K7+0 | M7: =IF(K7="","",K7-L7) | N7: ='03_Intangibles'!J7+IF(R7="",0,R7) | O7: ='03_Intangibles'!S7&"" | P7: =IF('03_Intangibles'!T7="","",IF(LEFT('03_Intangibles'!T7,1)="a","a) el intangible se expresa como una medida de los ingresos",IF(LEFT('03_Intangibles'!T7,1)="b","b) ingresos y consumo estrechamente correlacionados","No invoca ninguna de las dos circunstancias"))) | Q7: =IF(C7="No","No aplica",IF(ISNUMBER(SEARCH("ingres",O7)),IF('02_Parametros'!$B$9=0,"Ingresos (sin presunción: PYMES 2015)",IF(OR(LEFT(P7,1)="a",LEFT(P7,1)="b"),"Ingresos (excepción documentada)","Lineal (presunción no refutada)")),IF(OR(O7="",ISNUMBER(SEARCH("lineal",O7)),ISNUMBER(SEARCH("recta",O7))),"Lineal","Otro método informado (no recalculado)"))) | R7: =IF(AND(C7="Sí",LEFT(Q7,6)<>"Lineal"),L7,K7)
A8: GW-01 | B8: ='04_Reconocimiento'!E8 | C8: ='04_Reconocimiento'!F8 | D8: ='04_Reconocimiento'!I8 | E8: ='03_Intangibles'!H8+0 | F8: =MAX(D8-E8,0) | G8: =IF(C8="No","",IF('02_Parametros'!$B$7=1,IF('03_Intangibles'!I8="","",MIN('03_Intangibles'!I8,'02_Parametros'!$B$10)),IF(B8="Goodwill","",IF('03_Intangibles'!I8="","",'03_Intangibles'!I8)))) | H8: =IF(C8="No","No aplica",IF(G8<>"","Finita",IF('02_Parametros'!$B$7=1,"Sin estimación (18.20)",IF(B8="Goodwill","Goodwill: indefinida (no se amortiza)","Indefinida")))) | I8: =IF('03_Intangibles'!F8="",0,MAX(0,MIN(12,(YEAR('02_Parametros'!$B$5)-YEAR('03_Intangibles'!F8))*12+MONTH('02_Parametros'!$B$5)-MONTH('03_Intangibles'!F8)+1))) | J8: =MAX(F8-'03_Intangibles'!J8-'03_Intangibles'!L8,0) | K8: =IF(AND(C8="Sí",LEFT(Q8,6)<>"Lineal"),"",IF(AND('02_Parametros'!$B$7=1,C8="Sí",G8=""),"",IF(OR(G8="",I8=0),0,MIN(F8/G8*I8,J8)))) | L8: ='03_Intangibles'!K8+0 | M8: =IF(K8="","",K8-L8) | N8: ='03_Intangibles'!J8+IF(R8="",0,R8) | O8: ='03_Intangibles'!S8&"" | P8: =IF('03_Intangibles'!T8="","",IF(LEFT('03_Intangibles'!T8,1)="a","a) el intangible se expresa como una medida de los ingresos",IF(LEFT('03_Intangibles'!T8,1)="b","b) ingresos y consumo estrechamente correlacionados","No invoca ninguna de las dos circunstancias"))) | Q8: =IF(C8="No","No aplica",IF(ISNUMBER(SEARCH("ingres",O8)),IF('02_Parametros'!$B$9=0,"Ingresos (sin presunción: PYMES 2015)",IF(OR(LEFT(P8,1)="a",LEFT(P8,1)="b"),"Ingresos (excepción documentada)","Lineal (presunción no refutada)")),IF(OR(O8="",ISNUMBER(SEARCH("lineal",O8)),ISNUMBER(SEARCH("recta",O8))),"Lineal","Otro método informado (no recalculado)"))) | R8: =IF(AND(C8="Sí",LEFT(Q8,6)<>"Lineal"),L8,K8)
A9: INV-01 | B9: ='04_Reconocimiento'!E9 | C9: ='04_Reconocimiento'!F9 | D9: ='04_Reconocimiento'!I9 | E9: ='03_Intangibles'!H9+0 | F9: =MAX(D9-E9,0) | G9: =IF(C9="No","",IF('02_Parametros'!$B$7=1,IF('03_Intangibles'!I9="","",MIN('03_Intangibles'!I9,'02_Parametros'!$B$10)),IF(B9="Goodwill","",IF('03_Intangibles'!I9="","",'03_Intangibles'!I9)))) | H9: =IF(C9="No","No aplica",IF(G9<>"","Finita",IF('02_Parametros'!$B$7=1,"Sin estimación (18.20)",IF(B9="Goodwill","Goodwill: indefinida (no se amortiza)","Indefinida")))) | I9: =IF('03_Intangibles'!F9="",0,MAX(0,MIN(12,(YEAR('02_Parametros'!$B$5)-YEAR('03_Intangibles'!F9))*12+MONTH('02_Parametros'!$B$5)-MONTH('03_Intangibles'!F9)+1))) | J9: =MAX(F9-'03_Intangibles'!J9-'03_Intangibles'!L9,0) | K9: =IF(AND(C9="Sí",LEFT(Q9,6)<>"Lineal"),"",IF(AND('02_Parametros'!$B$7=1,C9="Sí",G9=""),"",IF(OR(G9="",I9=0),0,MIN(F9/G9*I9,J9)))) | L9: ='03_Intangibles'!K9+0 | M9: =IF(K9="","",K9-L9) | N9: ='03_Intangibles'!J9+IF(R9="",0,R9) | O9: ='03_Intangibles'!S9&"" | P9: =IF('03_Intangibles'!T9="","",IF(LEFT('03_Intangibles'!T9,1)="a","a) el intangible se expresa como una medida de los ingresos",IF(LEFT('03_Intangibles'!T9,1)="b","b) ingresos y consumo estrechamente correlacionados","No invoca ninguna de las dos circunstancias"))) | Q9: =IF(C9="No","No aplica",IF(ISNUMBER(SEARCH("ingres",O9)),IF('02_Parametros'!$B$9=0,"Ingresos (sin presunción: PYMES 2015)",IF(OR(LEFT(P9,1)="a",LEFT(P9,1)="b"),"Ingresos (excepción documentada)","Lineal (presunción no refutada)")),IF(OR(O9="",ISNUMBER(SEARCH("lineal",O9)),ISNUMBER(SEARCH("recta",O9))),"Lineal","Otro método informado (no recalculado)"))) | R9: =IF(AND(C9="Sí",LEFT(Q9,6)<>"Lineal"),L9,K9)
A10: DES-01 | B10: ='04_Reconocimiento'!E10 | C10: ='04_Reconocimiento'!F10 | D10: ='04_Reconocimiento'!I10 | E10: ='03_Intangibles'!H10+0 | F10: =MAX(D10-E10,0) | G10: =IF(C10="No","",IF('02_Parametros'!$B$7=1,IF('03_Intangibles'!I10="","",MIN('03_Intangibles'!I10,'02_Parametros'!$B$10)),IF(B10="Goodwill","",IF('03_Intangibles'!I10="","",'03_Intangibles'!I10)))) | H10: =IF(C10="No","No aplica",IF(G10<>"","Finita",IF('02_Parametros'!$B$7=1,"Sin estimación (18.20)",IF(B10="Goodwill","Goodwill: indefinida (no se amortiza)","Indefinida")))) | I10: =IF('03_Intangibles'!F10="",0,MAX(0,MIN(12,(YEAR('02_Parametros'!$B$5)-YEAR('03_Intangibles'!F10))*12+MONTH('02_Parametros'!$B$5)-MONTH('03_Intangibles'!F10)+1))) | J10: =MAX(F10-'03_Intangibles'!J10-'03_Intangibles'!L10,0) | K10: =IF(AND(C10="Sí",LEFT(Q10,6)<>"Lineal"),"",IF(AND('02_Parametros'!$B$7=1,C10="Sí",G10=""),"",IF(OR(G10="",I10=0),0,MIN(F10/G10*I10,J10)))) | L10: ='03_Intangibles'!K10+0 | M10: =IF(K10="","",K10-L10) | N10: ='03_Intangibles'!J10+IF(R10="",0,R10) | O10: ='03_Intangibles'!S10&"" | P10: =IF('03_Intangibles'!T10="","",IF(LEFT('03_Intangibles'!T10,1)="a","a) el intangible se expresa como una medida de los ingresos",IF(LEFT('03_Intangibles'!T10,1)="b","b) ingresos y consumo estrechamente correlacionados","No invoca ninguna de las dos circunstancias"))) | Q10: =IF(C10="No","No aplica",IF(ISNUMBER(SEARCH("ingres",O10)),IF('02_Parametros'!$B$9=0,"Ingresos (sin presunción: PYMES 2015)",IF(OR(LEFT(P10,1)="a",LEFT(P10,1)="b"),"Ingresos (excepción documentada)","Lineal (presunción no refutada)")),IF(OR(O10="",ISNUMBER(SEARCH("lineal",O10)),ISNUMBER(SEARCH("recta",O10))),"Lineal","Otro método informado (no recalculado)"))) | R10: =IF(AND(C10="Sí",LEFT(Q10,6)<>"Lineal"),L10,K10)
A11: DES-02 | B11: ='04_Reconocimiento'!E11 | C11: ='04_Reconocimiento'!F11 | D11: ='04_Reconocimiento'!I11 | E11: ='03_Intangibles'!H11+0 | F11: =MAX(D11-E11,0) | G11: =IF(C11="No","",IF('02_Parametros'!$B$7=1,IF('03_Intangibles'!I11="","",MIN('03_Intangibles'!I11,'02_Parametros'!$B$10)),IF(B11="Goodwill","",IF('03_Intangibles'!I11="","",'03_Intangibles'!I11)))) | H11: =IF(C11="No","No aplica",IF(G11<>"","Finita",IF('02_Parametros'!$B$7=1,"Sin estimación (18.20)",IF(B11="Goodwill","Goodwill: indefinida (no se amortiza)","Indefinida")))) | I11: =IF('03_Intangibles'!F11="",0,MAX(0,MIN(12,(YEAR('02_Parametros'!$B$5)-YEAR('03_Intangibles'!F11))*12+MONTH('02_Parametros'!$B$5)-MONTH('03_Intangibles'!F11)+1))) | J11: =MAX(F11-'03_Intangibles'!J11-'03_Intangibles'!L11,0) | K11: =IF(AND(C11="Sí",LEFT(Q11,6)<>"Lineal"),"",IF(AND('02_Parametros'!$B$7=1,C11="Sí",G11=""),"",IF(OR(G11="",I11=0),0,MIN(F11/G11*I11,J11)))) | L11: ='03_Intangibles'!K11+0 | M11: =IF(K11="","",K11-L11) | N11: ='03_Intangibles'!J11+IF(R11="",0,R11) | O11: ='03_Intangibles'!S11&"" | P11: =IF('03_Intangibles'!T11="","",IF(LEFT('03_Intangibles'!T11,1)="a","a) el intangible se expresa como una medida de los ingresos",IF(LEFT('03_Intangibles'!T11,1)="b","b) ingresos y consumo estrechamente correlacionados","No invoca ninguna de las dos circunstancias"))) | Q11: =IF(C11="No","No aplica",IF(ISNUMBER(SEARCH("ingres",O11)),IF('02_Parametros'!$B$9=0,"Ingresos (sin presunción: PYMES 2015)",IF(OR(LEFT(P11,1)="a",LEFT(P11,1)="b"),"Ingresos (excepción documentada)","Lineal (presunción no refutada)")),IF(OR(O11="",ISNUMBER(SEARCH("lineal",O11)),ISNUMBER(SEARCH("recta",O11))),"Lineal","Otro método informado (no recalculado)"))) | R11: =IF(AND(C11="Sí",LEFT(Q11,6)<>"Lineal"),L11,K11)
A12: DES-03 | B12: ='04_Reconocimiento'!E12 | C12: ='04_Reconocimiento'!F12 | D12: ='04_Reconocimiento'!I12 | E12: ='03_Intangibles'!H12+0 | F12: =MAX(D12-E12,0) | G12: =IF(C12="No","",IF('02_Parametros'!$B$7=1,IF('03_Intangibles'!I12="","",MIN('03_Intangibles'!I12,'02_Parametros'!$B$10)),IF(B12="Goodwill","",IF('03_Intangibles'!I12="","",'03_Intangibles'!I12)))) | H12: =IF(C12="No","No aplica",IF(G12<>"","Finita",IF('02_Parametros'!$B$7=1,"Sin estimación (18.20)",IF(B12="Goodwill","Goodwill: indefinida (no se amortiza)","Indefinida")))) | I12: =IF('03_Intangibles'!F12="",0,MAX(0,MIN(12,(YEAR('02_Parametros'!$B$5)-YEAR('03_Intangibles'!F12))*12+MONTH('02_Parametros'!$B$5)-MONTH('03_Intangibles'!F12)+1))) | J12: =MAX(F12-'03_Intangibles'!J12-'03_Intangibles'!L12,0) | K12: =IF(AND(C12="Sí",LEFT(Q12,6)<>"Lineal"),"",IF(AND('02_Parametros'!$B$7=1,C12="Sí",G12=""),"",IF(OR(G12="",I12=0),0,MIN(F12/G12*I12,J12)))) | L12: ='03_Intangibles'!K12+0 | M12: =IF(K12="","",K12-L12) | N12: ='03_Intangibles'!J12+IF(R12="",0,R12) | O12: ='03_Intangibles'!S12&"" | P12: =IF('03_Intangibles'!T12="","",IF(LEFT('03_Intangibles'!T12,1)="a","a) el intangible se expresa como una medida de los ingresos",IF(LEFT('03_Intangibles'!T12,1)="b","b) ingresos y consumo estrechamente correlacionados","No invoca ninguna de las dos circunstancias"))) | Q12: =IF(C12="No","No aplica",IF(ISNUMBER(SEARCH("ingres",O12)),IF('02_Parametros'!$B$9=0,"Ingresos (sin presunción: PYMES 2015)",IF(OR(LEFT(P12,1)="a",LEFT(P12,1)="b"),"Ingresos (excepción documentada)","Lineal (presunción no refutada)")),IF(OR(O12="",ISNUMBER(SEARCH("lineal",O12)),ISNUMBER(SEARCH("recta",O12))),"Lineal","Otro método informado (no recalculado)"))) | R12: =IF(AND(C12="Sí",LEFT(Q12,6)<>"Lineal"),L12,K12)
A13: PAT-01 | B13: ='04_Reconocimiento'!E13 | C13: ='04_Reconocimiento'!F13 | D13: ='04_Reconocimiento'!I13 | E13: ='03_Intangibles'!H13+0 | F13: =MAX(D13-E13,0) | G13: =IF(C13="No","",IF('02_Parametros'!$B$7=1,IF('03_Intangibles'!I13="","",MIN('03_Intangibles'!I13,'02_Parametros'!$B$10)),IF(B13="Goodwill","",IF('03_Intangibles'!I13="","",'03_Intangibles'!I13)))) | H13: =IF(C13="No","No aplica",IF(G13<>"","Finita",IF('02_Parametros'!$B$7=1,"Sin estimación (18.20)",IF(B13="Goodwill","Goodwill: indefinida (no se amortiza)","Indefinida")))) | I13: =IF('03_Intangibles'!F13="",0,MAX(0,MIN(12,(YEAR('02_Parametros'!$B$5)-YEAR('03_Intangibles'!F13))*12+MONTH('02_Parametros'!$B$5)-MONTH('03_Intangibles'!F13)+1))) | J13: =MAX(F13-'03_Intangibles'!J13-'03_Intangibles'!L13,0) | K13: =IF(AND(C13="Sí",LEFT(Q13,6)<>"Lineal"),"",IF(AND('02_Parametros'!$B$7=1,C13="Sí",G13=""),"",IF(OR(G13="",I13=0),0,MIN(F13/G13*I13,J13)))) | L13: ='03_Intangibles'!K13+0 | M13: =IF(K13="","",K13-L13) | N13: ='03_Intangibles'!J13+IF(R13="",0,R13) | O13: ='03_Intangibles'!S13&"" | P13: =IF('03_Intangibles'!T13="","",IF(LEFT('03_Intangibles'!T13,1)="a","a) el intangible se expresa como una medida de los ingresos",IF(LEFT('03_Intangibles'!T13,1)="b","b) ingresos y consumo estrechamente correlacionados","No invoca ninguna de las dos circunstancias"))) | Q13: =IF(C13="No","No aplica",IF(ISNUMBER(SEARCH("ingres",O13)),IF('02_Parametros'!$B$9=0,"Ingresos (sin presunción: PYMES 2015)",IF(OR(LEFT(P13,1)="a",LEFT(P13,1)="b"),"Ingresos (excepción documentada)","Lineal (presunción no refutada)")),IF(OR(O13="",ISNUMBER(SEARCH("lineal",O13)),ISNUMBER(SEARCH("recta",O13))),"Lineal","Otro método informado (no recalculado)"))) | R13: =IF(AND(C13="Sí",LEFT(Q13,6)<>"Lineal"),L13,K13)
A14: SW-02 | B14: ='04_Reconocimiento'!E14 | C14: ='04_Reconocimiento'!F14 | D14: ='04_Reconocimiento'!I14 | E14: ='03_Intangibles'!H14+0 | F14: =MAX(D14-E14,0) | G14: =IF(C14="No","",IF('02_Parametros'!$B$7=1,IF('03_Intangibles'!I14="","",MIN('03_Intangibles'!I14,'02_Parametros'!$B$10)),IF(B14="Goodwill","",IF('03_Intangibles'!I14="","",'03_Intangibles'!I14)))) | H14: =IF(C14="No","No aplica",IF(G14<>"","Finita",IF('02_Parametros'!$B$7=1,"Sin estimación (18.20)",IF(B14="Goodwill","Goodwill: indefinida (no se amortiza)","Indefinida")))) | I14: =IF('03_Intangibles'!F14="",0,MAX(0,MIN(12,(YEAR('02_Parametros'!$B$5)-YEAR('03_Intangibles'!F14))*12+MONTH('02_Parametros'!$B$5)-MONTH('03_Intangibles'!F14)+1))) | J14: =MAX(F14-'03_Intangibles'!J14-'03_Intangibles'!L14,0) | K14: =IF(AND(C14="Sí",LEFT(Q14,6)<>"Lineal"),"",IF(AND('02_Parametros'!$B$7=1,C14="Sí",G14=""),"",IF(OR(G14="",I14=0),0,MIN(F14/G14*I14,J14)))) | L14: ='03_Intangibles'!K14+0 | M14: =IF(K14="","",K14-L14) | N14: ='03_Intangibles'!J14+IF(R14="",0,R14) | O14: ='03_Intangibles'!S14&"" | P14: =IF('03_Intangibles'!T14="","",IF(LEFT('03_Intangibles'!T14,1)="a","a) el intangible se expresa como una medida de los ingresos",IF(LEFT('03_Intangibles'!T14,1)="b","b) ingresos y consumo estrechamente correlacionados","No invoca ninguna de las dos circunstancias"))) | Q14: =IF(C14="No","No aplica",IF(ISNUMBER(SEARCH("ingres",O14)),IF('02_Parametros'!$B$9=0,"Ingresos (sin presunción: PYMES 2015)",IF(OR(LEFT(P14,1)="a",LEFT(P14,1)="b"),"Ingresos (excepción documentada)","Lineal (presunción no refutada)")),IF(OR(O14="",ISNUMBER(SEARCH("lineal",O14)),ISNUMBER(SEARCH("recta",O14))),"Lineal","Otro método informado (no recalculado)"))) | R14: =IF(AND(C14="Sí",LEFT(Q14,6)<>"Lineal"),L14,K14)
A15: SW-03 | B15: ='04_Reconocimiento'!E15 | C15: ='04_Reconocimiento'!F15 | D15: ='04_Reconocimiento'!I15 | E15: ='03_Intangibles'!H15+0 | F15: =MAX(D15-E15,0) | G15: =IF(C15="No","",IF('02_Parametros'!$B$7=1,IF('03_Intangibles'!I15="","",MIN('03_Intangibles'!I15,'02_Parametros'!$B$10)),IF(B15="Goodwill","",IF('03_Intangibles'!I15="","",'03_Intangibles'!I15)))) | H15: =IF(C15="No","No aplica",IF(G15<>"","Finita",IF('02_Parametros'!$B$7=1,"Sin estimación (18.20)",IF(B15="Goodwill","Goodwill: indefinida (no se amortiza)","Indefinida")))) | I15: =IF('03_Intangibles'!F15="",0,MAX(0,MIN(12,(YEAR('02_Parametros'!$B$5)-YEAR('03_Intangibles'!F15))*12+MONTH('02_Parametros'!$B$5)-MONTH('03_Intangibles'!F15)+1))) | J15: =MAX(F15-'03_Intangibles'!J15-'03_Intangibles'!L15,0) | K15: =IF(AND(C15="Sí",LEFT(Q15,6)<>"Lineal"),"",IF(AND('02_Parametros'!$B$7=1,C15="Sí",G15=""),"",IF(OR(G15="",I15=0),0,MIN(F15/G15*I15,J15)))) | L15: ='03_Intangibles'!K15+0 | M15: =IF(K15="","",K15-L15) | N15: ='03_Intangibles'!J15+IF(R15="",0,R15) | O15: ='03_Intangibles'!S15&"" | P15: =IF('03_Intangibles'!T15="","",IF(LEFT('03_Intangibles'!T15,1)="a","a) el intangible se expresa como una medida de los ingresos",IF(LEFT('03_Intangibles'!T15,1)="b","b) ingresos y consumo estrechamente correlacionados","No invoca ninguna de las dos circunstancias"))) | Q15: =IF(C15="No","No aplica",IF(ISNUMBER(SEARCH("ingres",O15)),IF('02_Parametros'!$B$9=0,"Ingresos (sin presunción: PYMES 2015)",IF(OR(LEFT(P15,1)="a",LEFT(P15,1)="b"),"Ingresos (excepción documentada)","Lineal (presunción no refutada)")),IF(OR(O15="",ISNUMBER(SEARCH("lineal",O15)),ISNUMBER(SEARCH("recta",O15))),"Lineal","Otro método informado (no recalculado)"))) | R15: =IF(AND(C15="Sí",LEFT(Q15,6)<>"Lineal"),L15,K15)
A16: CON-01 | B16: ='04_Reconocimiento'!E16 | C16: ='04_Reconocimiento'!F16 | D16: ='04_Reconocimiento'!I16 | E16: ='03_Intangibles'!H16+0 | F16: =MAX(D16-E16,0) | G16: =IF(C16="No","",IF('02_Parametros'!$B$7=1,IF('03_Intangibles'!I16="","",MIN('03_Intangibles'!I16,'02_Parametros'!$B$10)),IF(B16="Goodwill","",IF('03_Intangibles'!I16="","",'03_Intangibles'!I16)))) | H16: =IF(C16="No","No aplica",IF(G16<>"","Finita",IF('02_Parametros'!$B$7=1,"Sin estimación (18.20)",IF(B16="Goodwill","Goodwill: indefinida (no se amortiza)","Indefinida")))) | I16: =IF('03_Intangibles'!F16="",0,MAX(0,MIN(12,(YEAR('02_Parametros'!$B$5)-YEAR('03_Intangibles'!F16))*12+MONTH('02_Parametros'!$B$5)-MONTH('03_Intangibles'!F16)+1))) | J16: =MAX(F16-'03_Intangibles'!J16-'03_Intangibles'!L16,0) | K16: =IF(AND(C16="Sí",LEFT(Q16,6)<>"Lineal"),"",IF(AND('02_Parametros'!$B$7=1,C16="Sí",G16=""),"",IF(OR(G16="",I16=0),0,MIN(F16/G16*I16,J16)))) | L16: ='03_Intangibles'!K16+0 | M16: =IF(K16="","",K16-L16) | N16: ='03_Intangibles'!J16+IF(R16="",0,R16) | O16: ='03_Intangibles'!S16&"" | P16: =IF('03_Intangibles'!T16="","",IF(LEFT('03_Intangibles'!T16,1)="a","a) el intangible se expresa como una medida de los ingresos",IF(LEFT('03_Intangibles'!T16,1)="b","b) ingresos y consumo estrechamente correlacionados","No invoca ninguna de las dos circunstancias"))) | Q16: =IF(C16="No","No aplica",IF(ISNUMBER(SEARCH("ingres",O16)),IF('02_Parametros'!$B$9=0,"Ingresos (sin presunción: PYMES 2015)",IF(OR(LEFT(P16,1)="a",LEFT(P16,1)="b"),"Ingresos (excepción documentada)","Lineal (presunción no refutada)")),IF(OR(O16="",ISNUMBER(SEARCH("lineal",O16)),ISNUMBER(SEARCH("recta",O16))),"Lineal","Otro método informado (no recalculado)"))) | R16: =IF(AND(C16="Sí",LEFT(Q16,6)<>"Lineal"),L16,K16)
A17: CON-02 | B17: ='04_Reconocimiento'!E17 | C17: ='04_Reconocimiento'!F17 | D17: ='04_Reconocimiento'!I17 | E17: ='03_Intangibles'!H17+0 | F17: =MAX(D17-E17,0) | G17: =IF(C17="No","",IF('02_Parametros'!$B$7=1,IF('03_Intangibles'!I17="","",MIN('03_Intangibles'!I17,'02_Parametros'!$B$10)),IF(B17="Goodwill","",IF('03_Intangibles'!I17="","",'03_Intangibles'!I17)))) | H17: =IF(C17="No","No aplica",IF(G17<>"","Finita",IF('02_Parametros'!$B$7=1,"Sin estimación (18.20)",IF(B17="Goodwill","Goodwill: indefinida (no se amortiza)","Indefinida")))) | I17: =IF('03_Intangibles'!F17="",0,MAX(0,MIN(12,(YEAR('02_Parametros'!$B$5)-YEAR('03_Intangibles'!F17))*12+MONTH('02_Parametros'!$B$5)-MONTH('03_Intangibles'!F17)+1))) | J17: =MAX(F17-'03_Intangibles'!J17-'03_Intangibles'!L17,0) | K17: =IF(AND(C17="Sí",LEFT(Q17,6)<>"Lineal"),"",IF(AND('02_Parametros'!$B$7=1,C17="Sí",G17=""),"",IF(OR(G17="",I17=0),0,MIN(F17/G17*I17,J17)))) | L17: ='03_Intangibles'!K17+0 | M17: =IF(K17="","",K17-L17) | N17: ='03_Intangibles'!J17+IF(R17="",0,R17) | O17: ='03_Intangibles'!S17&"" | P17: =IF('03_Intangibles'!T17="","",IF(LEFT('03_Intangibles'!T17,1)="a","a) el intangible se expresa como una medida de los ingresos",IF(LEFT('03_Intangibles'!T17,1)="b","b) ingresos y consumo estrechamente correlacionados","No invoca ninguna de las dos circunstancias"))) | Q17: =IF(C17="No","No aplica",IF(ISNUMBER(SEARCH("ingres",O17)),IF('02_Parametros'!$B$9=0,"Ingresos (sin presunción: PYMES 2015)",IF(OR(LEFT(P17,1)="a",LEFT(P17,1)="b"),"Ingresos (excepción documentada)","Lineal (presunción no refutada)")),IF(OR(O17="",ISNUMBER(SEARCH("lineal",O17)),ISNUMBER(SEARCH("recta",O17))),"Lineal","Otro método informado (no recalculado)"))) | R17: =IF(AND(C17="Sí",LEFT(Q17,6)<>"Lineal"),L17,K17)
A18: TOTAL | D18: =SUM(D5:D17) | F18: =SUM(F5:F17) | K18: =SUM(K5:K17) | L18: =SUM(L5:L17) | M18: =SUM(M5:M17) | N18: =SUM(N5:N17) | R18: =SUM(R5:R17)
A20: ⓘ Cómo se calcula esta hoja
A21: Columna | B21: Fórmula (Excel) | C21: Cómo se calcula (sencillo) | D21: Ejemplo con números reales | E21: De dónde viene | F21: Norma
A22: Categoría | B22: '='04_Reconocimiento'!E5 | C22: Trae la categoría (Investigación, Desarrollo, Goodwill u Otro) asignada en la hoja 04 (Reconocimiento). | D22: Fila 1: «Otro» → Otro | E22: hoja «Reconocimiento e investigación / desarrollo» | F22: —
A23: Capitalizable | B23: '='04_Reconocimiento'!F5 | C23: Trae de la hoja 04 (Reconocimiento) si la partida se mantiene en el activo (Sí) o va a gasto (No). | D23: Fila 1: «Sí» → Sí | E23: hoja «Reconocimiento e investigación / desarrollo» | F23: —
A24: Costo auditado | B24: '='04_Reconocimiento'!I5 | C24: Trae el costo auditado de la hoja 04 (Reconocimiento): el costo registrado si es capitalizable, o cero si no. | D24: Fila 1: 60.000,00 → 60.000,00 | E24: hoja «Reconocimiento e investigación / desarrollo» | F24: —
A25: Valor residual | B25: '='03_Intangibles'!H5+0 | C25: Trae el valor residual informado por el cliente en la hoja 03 (Auxiliar de intangibles y goodwill); si está en blanco, se toma como cero. | D25: Fila 1: (vacío)+0 → 0,00 | E25: hoja «Auxiliar de intangibles y goodwill» | F25: —
A26: Importe amortizable | B26: '=MAX(D5-E5,0) | C26: Resta el valor residual al costo auditado; si el resultado fuera negativo, queda en cero. | D26: Fila 1: MAX(60.000,00-0,00; 0) → 60.000,00 | E26: «Costo auditado» (esta hoja), «Valor residual» (esta hoja) | F26: —
A27: Vida aplicada (meses) | B27: '=IF(C5="No","",IF('02_Parametros'!$B$7=1,IF('03_Intangibles'!I5="","",MIN('03_Intangibles'!I5,'02_Parametros'!$B$10)),IF(B5="Goodwill","",IF('03_Intangibles'!I5="","",'03_Intangibles'!I5)))) | C27: Toma la vida útil en meses de la hoja 03 (Auxiliar de intangibles y goodwill). En la ruta PYMES la limita al tope de la hoja 02 (Parámetros); en NIIF completas el goodwill queda sin vida. Queda en blanco si la partida no es capitalizable o si no hay vida informada. | D27: Fila 1: IF(«Sí»="No"; ""; IF(0,00=1; IF(60=""; ""; MIN(60; 120,00)); IF(«Otro»="Goodwill"; ""; IF(60=""; ""; 60)))) → 60 | E27: «Capitalizable» (esta hoja), «Categoría» (esta hoja), hoja «Parámetros», hoja «Auxiliar de intangibles y goodwill» | F27: —
A28: Tipo de vida | B28: '=IF(C5="No","No aplica",IF(G5<>"","Finita",IF('02_Parametros'!$B$7=1,"Sin estimación (18.20)",IF(B5="Goodwill","Goodwill: indefinida (no se amortiza)","Indefinida")))) | C28: Indica «Finita» si hay vida aplicada. Sin vida: «No aplica» si no es capitalizable, «Sin estimación» en PYMES, y en NIIF completas «indefinida», con una leyenda propia para el goodwill, que no se amortiza. | D28: Fila 1: IF(«Sí»="No"; "No aplica"; IF(60<>""; "Finita"; IF(0,00=1; "Sin estimación (18.20)"; IF(«Otro»="Goodwill"; "Goodwill: indefinida (no se amortiza)"; "Indefinida")))) → Finita | E28: «Capitalizable» (esta hoja), «Vida aplicada (meses)» (esta hoja), «Categoría» (esta hoja), hoja «Parámetros» | F28: —
A29: Meses en uso del ejercicio | B29: '=IF('03_Intangibles'!F5="",0,MAX(0,MIN(12,(YEAR('02_Parametros'!$B$5)-YEAR('03_Intangibles'!F5))*12+MONTH('02_Parametros'!$B$5)-MONTH('03_Intangibles'!F5)+1))) | C29: Cuenta los meses desde la fecha en que el intangible quedó disponible para uso (la hoja 03 (Auxiliar de intangibles y goodwill)) hasta el corte de la hoja 02, incluido el mes de inicio, con un mínimo de 0 y un máximo de 12. Sin fecha, da cero. | D29: Fila 1: IF(«2023-01-01»=""; 0; MAX(0; MIN(12; (YEAR(«2025-12-31»)-YEAR(«2023-01-01»))*12+MONTH(«2025-12-31»)-MONTH(«2023-01-01»)+1))) → 12 | E29: hoja «Auxiliar de intangibles y goodwill», hoja «Parámetros» | F29: —
A30: Importe pendiente | B30: '=MAX(F5-'03_Intangibles'!J5-'03_Intangibles'!L5,0) | C30: Resta al importe amortizable la amortización acumulada inicial y el deterioro previo de la hoja 03 (Auxiliar de intangibles y goodwill): es lo que todavía queda por amortizar (nunca menos de cero). | D30: Fila 1: MAX(60.000,00-24.000,00-(vacío); 0) → 36.000,00 | E30: «Importe amortizable» (esta hoja), hoja «Auxiliar de intangibles y goodwill» | F30: —
A31: Amortización recalculada (lineal) | B31: '=IF(AND(C5="Sí",LEFT(Q5,6)<>"Lineal"),"",IF(AND('02_Parametros'!$B$7=1,C5="Sí",G5=""),"",IF(OR(G5="",I5=0),0,MIN(F5/G5*I5,J5)))) | C31: Divide el importe amortizable para la vida aplicada y lo multiplica por los meses en uso del ejercicio, sin pasar del importe pendiente. Da cero sin vida o sin meses de uso; en partidas capitalizables queda en blanco si el método aplicado no es el lineal o si en PYMES falta la vida. | D31: Fila 1: IF(AND(«Sí»="Sí"; LEFT(«Lineal»; 6)<>"Lineal"); ""; IF(AND(0,00=1; «Sí»="Sí"; 60=""); ""; IF(OR(60=""; 12=0); 0; MIN(60.000,00/60*12; 36.000,00)))) → 12.000,00 | E31: «Capitalizable» (esta hoja), «Método aplicado por la herramienta» (esta hoja), «Vida aplicada (meses)» (esta hoja), «Meses en uso del ejercicio» (esta hoja), «Importe amortizable» (esta hoja), «Importe pendiente» (esta hoja), hoja «Parámetros» | F31: —
A32: Amortización registrada (cliente) | B32: '='03_Intangibles'!K5+0 | C32: Trae la amortización del año que registró el cliente en la hoja 03 (Auxiliar de intangibles y goodwill) (cero si está en blanco). | D32: Fila 1: 12.000,00+0 → 12.000,00 | E32: hoja «Auxiliar de intangibles y goodwill» | F32: —
... A38: Amortización auditada | B38: '=IF(AND(C5="Sí",LEFT(Q5,6)<>"Lineal"),L5,K5) | C38: Usa la amortización recalculada cuando el método aplicado es el lineal; si la partida es capitalizable y se aceptó otro método (ingresos u otro), acepta la amortización registrada por el cliente. | D38: Fila 1: IF(AND(«Sí»="Sí"; LEFT(«Lineal»; 6)<>"Lineal"); 12.000,00; 12.000,00) → 12.000,00 | E38: «Capitalizable» (esta hoja), «Método aplicado por la herramienta» (esta hoja), «Amortización registrada (cliente)» (esta hoja), «Amortización recalculada (lineal)» (esta hoja) | F38: —

Sheet 06_Vida_util
A1: Revisión de vida útil y valor residual | H1: ⟵ Inicio | I1: ◀ Anterior | J1: Siguiente ▶
A2: Activos intangibles y goodwill · Cliente de muestra S.A. · corte 2025-12-31
A4: Código | B4: Categoría | C4: Vida registrada (meses) | D4: Vida aplicada (meses) | E4: Tipo de vida | F4: Meses transcurridos al cierre | G4: Vida remanente (meses) | H4: Amort. acumulada esperada | I4: Amort. acumulada recalculada | J4: Diferencia (esperada − recalculada) | K4: Valor residual | L4: Residual distinto de cero | M4: Vida revisada al cierre | N4: Revisión exigida | O4: Totalmente amortizado
A5: SW-01 | B5: ='05_Amortizacion'!B5 | C5: =IF('03_Intangibles'!I5="","",'03_Intangibles'!I5) | D5: =IF('05_Amortizacion'!G5="","",'05_Amortizacion'!G5) | E5: ='05_Amortizacion'!H5 | F5: =IF(OR('03_Intangibles'!F5="",'05_Amortizacion'!C5="No"),"",MAX(0,(YEAR('02_Parametros'!$B$5)-YEAR('03_Intangibles'!F5))*12+MONTH('02_Parametros'!$B$5)-MONTH('03_Intangibles'!F5)+1)) | G5: =IF(OR(D5="",F5=""),"",MAX(D5-F5,0)) | H5: =IF(OR(D5="",F5=""),"",MIN('05_Amortizacion'!F5,'05_Amortizacion'!F5/D5*F5)) | I5: ='05_Amortizacion'!N5 | J5: =IF(OR(H5="",'03_Intangibles'!L5>0,AND('05_Amortizacion'!C5="Sí",LEFT('05_Amortizacion'!Q5,6)<>"Lineal")),"",H5-I5) | K5: ='05_Amortizacion'!E5 | L5: =IF(AND('05_Amortizacion'!C5="Sí",K5>0),"Sí","No") | M5: ='03_Intangibles'!R5&"" | N5: =IF('05_Amortizacion'!C5="No","No aplica",IF('02_Parametros'!$B$7=1,"Con indicios (PYMES 18.24)",IF(B5="Goodwill","No aplica (prueba NIC 36.10 b y 36.90)",IF(E5="Finita","Anual (NIC 38.104)","Anual (NIC 38.109)")))) | O5: =IF(G5="","No",IF(G5=0,"Sí","No"))
A6: LIC-01 | B6: ='05_Amortizacion'!B6 | C6: =IF('03_Intangibles'!I6="","",'03_Intangibles'!I6) | D6: =IF('05_Amortizacion'!G6="","",'05_Amortizacion'!G6) | E6: ='05_Amortizacion'!H6 | F6: =IF(OR('03_Intangibles'!F6="",'05_Amortizacion'!C6="No"),"",MAX(0,(YEAR('02_Parametros'!$B$5)-YEAR('03_Intangibles'!F6))*12+MONTH('02_Parametros'!$B$5)-MONTH('03_Intangibles'!F6)+1)) | G6: =IF(OR(D6="",F6=""),"",MAX(D6-F6,0)) | H6: =IF(OR(D6="",F6=""),"",MIN('05_Amortizacion'!F6,'05_Amortizacion'!F6/D6*F6)) | I6: ='05_Amortizacion'!N6 | J6: =IF(OR(H6="",'03_Intangibles'!L6>0,AND('05_Amortizacion'!C6="Sí",LEFT('05_Amortizacion'!Q6,6)<>"Lineal")),"",H6-I6) | K6: ='05_Amortizacion'!E6 | L6: =IF(AND('05_Amortizacion'!C6="Sí",K6>0),"Sí","No") | M6: ='03_Intangibles'!R6&"" | N6: =IF('05_Amortizacion'!C6="No","No aplica",IF('02_Parametros'!$B$7=1,"Con indicios (PYMES 18.24)",IF(B6="Goodwill","No aplica (prueba NIC 36.10 b y 36.90)",IF(E6="Finita","Anual (NIC 38.104)","Anual (NIC 38.109)")))) | O6: =IF(G6="","No",IF(G6=0,"Sí","No"))
A7: MAR-01 | B7: ='05_Amortizacion'!B7 | C7: =IF('03_Intangibles'!I7="","",'03_Intangibles'!I7) | D7: =IF('05_Amortizacion'!G7="","",'05_Amortizacion'!G7) | E7: ='05_Amortizacion'!H7 | F7: =IF(OR('03_Intangibles'!F7="",'05_Amortizacion'!C7="No"),"",MAX(0,(YEAR('02_Parametros'!$B$5)-YEAR('03_Intangibles'!F7))*12+MONTH('02_Parametros'!$B$5)-MONTH('03_Intangibles'!F7)+1)) | G7: =IF(OR(D7="",F7=""),"",MAX(D7-F7,0)) | H7: =IF(OR(D7="",F7=""),"",MIN('05_Amortizacion'!F7,'05_Amortizacion'!F7/D7*F7)) | I7: ='05_Amortizacion'!N7 | J7: =IF(OR(H7="",'03_Intangibles'!L7>0,AND('05_Amortizacion'!C7="Sí",LEFT('05_Amortizacion'!Q7,6)<>"Lineal")),"",H7-I7) | K7: ='05_Amortizacion'!E7 | L7: =IF(AND('05_Amortizacion'!C7="Sí",K7>0),"Sí","No") | M7: ='03_Intangibles'!R7&"" | N7: =IF('05_Amortizacion'!C7="No","No aplica",IF('02_Parametros'!$B$7=1,"Con indicios (PYMES 18.24)",IF(B7="Goodwill","No aplica (prueba NIC 36.10 b y 36.90)",IF(E7="Finita","Anual (NIC 38.104)","Anual (NIC 38.109)")))) | O7: =IF(G7="","No",IF(G7=0,"Sí","No"))
A8: GW-01 | B8: ='05_Amortizacion'!B8 | C8: =IF('03_Intangibles'!I8="","",'03_Intangibles'!I8) | D8: =IF('05_Amortizacion'!G8="","",'05_Amortizacion'!G8) | E8: ='05_Amortizacion'!H8 | F8: =IF(OR('03_Intangibles'!F8="",'05_Amortizacion'!C8="No"),"",MAX(0,(YEAR('02_Parametros'!$B$5)-YEAR('03_Intangibles'!F8))*12+MONTH('02_Parametros'!$B$5)-MONTH('03_Intangibles'!F8)+1)) | G8: =IF(OR(D8="",F8=""),"",MAX(D8-F8,0)) | H8: =IF(OR(D8="",F8=""),"",MIN('05_Amortizacion'!F8,'05_Amortizacion'!F8/D8*F8)) | I8: ='05_Amortizacion'!N8 | J8: =IF(OR(H8="",'03_Intangibles'!L8>0,AND('05_Amortizacion'!C8="Sí",LEFT('05_Amortizacion'!Q8,6)<>"Lineal")),"",H8-I8) | K8: ='05_Amortizacion'!E8 | L8: =IF(AND('05_Amortizacion'!C8="Sí",K8>0),"Sí","No") | M8: ='03_Intangibles'!R8&"" | N8: =IF('05_Amortizacion'!C8="No","No aplica",IF('02_Parametros'!$B$7=1,"Con indicios (PYMES 18.24)",IF(B8="Goodwill","No aplica (prueba NIC 36.10 b y 36.90)",IF(E8="Finita","Anual (NIC 38.104)","Anual (NIC 38.109)")))) | O8: =IF(G8="","No",IF(G8=0,"Sí","No"))
A9: INV-01 | B9: ='05_Amortizacion'!B9 | C9: =IF('03_Intangibles'!I9="","",'03_Intangibles'!I9) | D9: =IF('05_Amortizacion'!G9="","",'05_Amortizacion'!G9) | E9: ='05_Amortizacion'!H9 | F9: =IF(OR('03_Intangibles'!F9="",'05_Amortizacion'!C9="No"),"",MAX(0,(YEAR('02_Parametros'!$B$5)-YEAR('03_Intangibles'!F9))*12+MONTH('02_Parametros'!$B$5)-MONTH('03_Intangibles'!F9)+1)) | G9: =IF(OR(D9="",F9=""),"",MAX(D9-F9,0)) | H9: =IF(OR(D9="",F9=""),"",MIN('05_Amortizacion'!F9,'05_Amortizacion'!F9/D9*F9)) | I9: ='05_Amortizacion'!N9 | J9: =IF(OR(H9="",'03_Intangibles'!L9>0,AND('05_Amortizacion'!C9="Sí",LEFT('05_Amortizacion'!Q9,6)<>"Lineal")),"",H9-I9) | K9: ='05_Amortizacion'!E9 | L9: =IF(AND('05_Amortizacion'!C9="Sí",K9>0),"Sí","No") | M9: ='03_Intangibles'!R9&"" | N9: =IF('05_Amortizacion'!C9="No","No aplica",IF('02_Parametros'!$B$7=1,"Con indicios (PYMES 18.24)",IF(B9="Goodwill","No aplica (prueba NIC 36.10 b y 36.90)",IF(E9="Finita","Anual (NIC 38.104)","Anual (NIC 38.109)")))) | O9: =IF(G9="","No",IF(G9=0,"Sí","No"))
A10: DES-01 | B10: ='05_Amortizacion'!B10 | C10: =IF('03_Intangibles'!I10="","",'03_Intangibles'!I10) | D10: =IF('05_Amortizacion'!G10="","",'05_Amortizacion'!G10) | E10: ='05_Amortizacion'!H10 | F10: =IF(OR('03_Intangibles'!F10="",'05_Amortizacion'!C10="No"),"",MAX(0,(YEAR('02_Parametros'!$B$5)-YEAR('03_Intangibles'!F10))*12+MONTH('02_Parametros'!$B$5)-MONTH('03_Intangibles'!F10)+1)) | G10: =IF(OR(D10="",F10=""),"",MAX(D10-F10,0)) | H10: =IF(OR(D10="",F10=""),"",MIN('05_Amortizacion'!F10,'05_Amortizacion'!F10/D10*F10)) | I10: ='05_Amortizacion'!N10 | J10: =IF(OR(H10="",'03_Intangibles'!L10>0,AND('05_Amortizacion'!C10="Sí",LEFT('05_Amortizacion'!Q10,6)<>"Lineal")),"",H10-I10) | K10: ='05_Amortizacion'!E10 | L10: =IF(AND('05_Amortizacion'!C10="Sí",K10>0),"Sí","No") | M10: ='03_Intangibles'!R10&"" | N10: =IF('05_Amortizacion'!C10="No","No aplica",IF('02_Parametros'!$B$7=1,"Con indicios (PYMES 18.24)",IF(B10="Goodwill","No aplica (prueba NIC 36.10 b y 36.90)",IF(E10="Finita","Anual (NIC 38.104)","Anual (NIC 38.109)")))) | O10: =IF(G10="","No",IF(G10=0,"Sí","No"))
A11: DES-02 | B11: ='05_Amortizacion'!B11 | C11: =IF('03_Intangibles'!I11="","",'03_Intangibles'!I11) | D11: =IF('05_Amortizacion'!G11="","",'05_Amortizacion'!G11) | E11: ='05_Amortizacion'!H11 | F11: =IF(OR('03_Intangibles'!F11="",'05_Amortizacion'!C11="No"),"",MAX(0,(YEAR('02_Parametros'!$B$5)-YEAR('03_Intangibles'!F11))*12+MONTH('02_Parametros'!$B$5)-MONTH('03_Intangibles'!F11)+1)) | G11: =IF(OR(D11="",F11=""),"",MAX(D11-F11,0)) | H11: =IF(OR(D11="",F11=""),"",MIN('05_Amortizacion'!F11,'05_Amortizacion'!F11/D11*F11)) | I11: ='05_Amortizacion'!N11 | J11: =IF(OR(H11="",'03_Intangibles'!L11>0,AND('05_Amortizacion'!C11="Sí",LEFT('05_Amortizacion'!Q11,6)<>"Lineal")),"",H11-I11) | K11: ='05_Amortizacion'!E11 | L11: =IF(AND('05_Amortizacion'!C11="Sí",K11>0),"Sí","No") | M11: ='03_Intangibles'!R11&"" | N11: =IF('05_Amortizacion'!C11="No","No aplica",IF('02_Parametros'!$B$7=1,"Con indicios (PYMES 18.24)",IF(B11="Goodwill","No aplica (prueba NIC 36.10 b y 36.90)",IF(E11="Finita","Anual (NIC 38.104)","Anual (NIC 38.109)")))) | O11: =IF(G11="","No",IF(G11=0,"Sí","No"))
A12: DES-03 | B12: ='05_Amortizacion'!B12 | C12: =IF('03_Intangibles'!I12="","",'03_Intangibles'!I12) | D12: =IF('05_Amortizacion'!G12="","",'05_Amortizacion'!G12) | E12: ='05_Amortizacion'!H12 | F12: =IF(OR('03_Intangibles'!F12="",'05_Amortizacion'!C12="No"),"",MAX(0,(YEAR('02_Parametros'!$B$5)-YEAR('03_Intangibles'!F12))*12+MONTH('02_Parametros'!$B$5)-MONTH('03_Intangibles'!F12)+1)) | G12: =IF(OR(D12="",F12=""),"",MAX(D12-F12,0)) | H12: =IF(OR(D12="",F12=""),"",MIN('05_Amortizacion'!F12,'05_Amortizacion'!F12/D12*F12)) | I12: ='05_Amortizacion'!N12 | J12: =IF(OR(H12="",'03_Intangibles'!L12>0,AND('05_Amortizacion'!C12="Sí",LEFT('05_Amortizacion'!Q12,6)<>"Lineal")),"",H12-I12) | K12: ='05_Amortizacion'!E12 | L12: =IF(AND('05_Amortizacion'!C12="Sí",K12>0),"Sí","No") | M12: ='03_Intangibles'!R12&"" | N12: =IF('05_Amortizacion'!C12="No","No aplica",IF('02_Parametros'!$B$7=1,"Con indicios (PYMES 18.24)",IF(B12="Goodwill","No aplica (prueba NIC 36.10 b y 36.90)",IF(E12="Finita","Anual (NIC 38.104)","Anual (NIC 38.109)")))) | O12: =IF(G12="","No",IF(G12=0,"Sí","No"))
A13: PAT-01 | B13: ='05_Amortizacion'!B13 | C13: =IF('03_Intangibles'!I13="","",'03_Intangibles'!I13) | D13: =IF('05_Amortizacion'!G13="","",'05_Amortizacion'!G13) | E13: ='05_Amortizacion'!H13 | F13: =IF(OR('03_Intangibles'!F13="",'05_Amortizacion'!C13="No"),"",MAX(0,(YEAR('02_Parametros'!$B$5)-YEAR('03_Intangibles'!F13))*12+MONTH('02_Parametros'!$B$5)-MONTH('03_Intangibles'!F13)+1)) | G13: =IF(OR(D13="",F13=""),"",MAX(D13-F13,0)) | H13: =IF(OR(D13="",F13=""),"",MIN('05_Amortizacion'!F13,'05_Amortizacion'!F13/D13*F13)) | I13: ='05_Amortizacion'!N13 | J13: =IF(OR(H13="",'03_Intangibles'!L13>0,AND('05_Amortizacion'!C13="Sí",LEFT('05_Amortizacion'!Q13,6)<>"Lineal")),"",H13-I13) | K13: ='05_Amortizacion'!E13 | L13: =IF(AND('05_Amortizacion'!C13="Sí",K13>0),"Sí","No") | M13: ='03_Intangibles'!R13&"" | N13: =IF('05_Amortizacion'!C13="No","No aplica",IF('02_Parametros'!$B$7=1,"Con indicios (PYMES 18.24)",IF(B13="Goodwill","No aplica (prueba NIC 36.10 b y 36.90)",IF(E13="Finita","Anual (NIC 38.104)","Anual (NIC 38.109)")))) | O13: =IF(G13="","No",IF(G13=0,"Sí","No"))
A14: SW-02 | B14: ='05_Amortizacion'!B14 | C14: =IF('03_Intangibles'!I14="","",'03_Intangibles'!I14) | D14: =IF('05_Amortizacion'!G14="","",'05_Amortizacion'!G14) | E14: ='05_Amortizacion'!H14 | F14: =IF(OR('03_Intangibles'!F14="",'05_Amortizacion'!C14="No"),"",MAX(0,(YEAR('02_Parametros'!$B$5)-YEAR('03_Intangibles'!F14))*12+MONTH('02_Parametros'!$B$5)-MONTH('03_Intangibles'!F14)+1)) | G14: =IF(OR(D14="",F14=""),"",MAX(D14-F14,0)) | H14: =IF(OR(D14="",F14=""),"",MIN('05_Amortizacion'!F14,'05_Amortizacion'!F14/D14*F14)) | I14: ='05_Amortizacion'!N14 | J14: =IF(OR(H14="",'03_Intangibles'!L14>0,AND('05_Amortizacion'!C14="Sí",LEFT('05_Amortizacion'!Q14,6)<>"Lineal")),"",H14-I14) | K14: ='05_Amortizacion'!E14 | L14: =IF(AND('05_Amortizacion'!C14="Sí",K14>0),"Sí","No") | M14: ='03_Intangibles'!R14&"" | N14: =IF('05_Amortizacion'!C14="No","No aplica",IF('02_Parametros'!$B$7=1,"Con indicios (PYMES 18.24)",IF(B14="Goodwill","No aplica (prueba NIC 36.10 b y 36.90)",IF(E14="Finita","Anual (NIC 38.104)","Anual (NIC 38.109)")))) | O14: =IF(G14="","No",IF(G14=0,"Sí","No"))
A15: SW-03 | B15: ='05_Amortizacion'!B15 | C15: =IF('03_Intangibles'!I15="","",'03_Intangibles'!I15) | D15: =IF('05_Amortizacion'!G15="","",'05_Amortizacion'!G15) | E15: ='05_Amortizacion'!H15 | F15: =IF(OR('03_Intangibles'!F15="",'05_Amortizacion'!C15="No"),"",MAX(0,(YEAR('02_Parametros'!$B$5)-YEAR('03_Intangibles'!F15))*12+MONTH('02_Parametros'!$B$5)-MONTH('03_Intangibles'!F15)+1)) | G15: =IF(OR(D15="",F15=""),"",MAX(D15-F15,0)) | H15: =IF(OR(D15="",F15=""),"",MIN('05_Amortizacion'!F15,'05_Amortizacion'!F15/D15*F15)) | I15: ='05_Amortizacion'!N15 | J15: =IF(OR(H15="",'03_Intangibles'!L15>0,AND('05_Amortizacion'!C15="Sí",LEFT('05_Amortizacion'!Q15,6)<>"Lineal")),"",H15-I15) | K15: ='05_Amortizacion'!E15 | L15: =IF(AND('05_Amortizacion'!C15="Sí",K15>0),"Sí","No") | M15: ='03_Intangibles'!R15&"" | N15: =IF('05_Amortizacion'!C15="No","No aplica",IF('02_Parametros'!$B$7=1,"Con indicios (PYMES 18.24)",IF(B15="Goodwill","No aplica (prueba NIC 36.10 b y 36.90)",IF(E15="Finita","Anual (NIC 38.104)","Anual (NIC 38.109)")))) | O15: =IF(G15="","No",IF(G15=0,"Sí","No"))
A16: CON-01 | B16: ='05_Amortizacion'!B16 | C16: =IF('03_Intangibles'!I16="","",'03_Intangibles'!I16) | D16: =IF('05_Amortizacion'!G16="","",'05_Amortizacion'!G16) | E16: ='05_Amortizacion'!H16 | F16: =IF(OR('03_Intangibles'!F16="",'05_Amortizacion'!C16="No"),"",MAX(0,(YEAR('02_Parametros'!$B$5)-YEAR('03_Intangibles'!F16))*12+MONTH('02_Parametros'!$B$5)-MONTH('03_Intangibles'!F16)+1)) | G16: =IF(OR(D16="",F16=""),"",MAX(D16-F16,0)) | H16: =IF(OR(D16="",F16=""),"",MIN('05_Amortizacion'!F16,'05_Amortizacion'!F16/D16*F16)) | I16: ='05_Amortizacion'!N16 | J16: =IF(OR(H16="",'03_Intangibles'!L16>0,AND('05_Amortizacion'!C16="Sí",LEFT('05_Amortizacion'!Q16,6)<>"Lineal")),"",H16-I16) | K16: ='05_Amortizacion'!E16 | L16: =IF(AND('05_Amortizacion'!C16="Sí",K16>0),"Sí","No") | M16: ='03_Intangibles'!R16&"" | N16: =IF('05_Amortizacion'!C16="No","No aplica",IF('02_Parametros'!$B$7=1,"Con indicios (PYMES 18.24)",IF(B16="Goodwill","No aplica (prueba NIC 36.10 b y 36.90)",IF(E16="Finita","Anual (NIC 38.104)","Anual (NIC 38.109)")))) | O16: =IF(G16="","No",IF(G16=0,"Sí","No"))
A17: CON-02 | B17: ='05_Amortizacion'!B17 | C17: =IF('03_Intangibles'!I17="","",'03_Intangibles'!I17) | D17: =IF('05_Amortizacion'!G17="","",'05_Amortizacion'!G17) | E17: ='05_Amortizacion'!H17 | F17: =IF(OR('03_Intangibles'!F17="",'05_Amortizacion'!C17="No"),"",MAX(0,(YEAR('02_Parametros'!$B$5)-YEAR('03_Intangibles'!F17))*12+MONTH('02_Parametros'!$B$5)-MONTH('03_Intangibles'!F17)+1)) | G17: =IF(OR(D17="",F17=""),"",MAX(D17-F17,0)) | H17: =IF(OR(D17="",F17=""),"",MIN('05_Amortizacion'!F17,'05_Amortizacion'!F17/D17*F17)) | I17: ='05_Amortizacion'!N17 | J17: =IF(OR(H17="",'03_Intangibles'!L17>0,AND('05_Amortizacion'!C17="Sí",LEFT('05_Amortizacion'!Q17,6)<>"Lineal")),"",H17-I17) | K17: ='05_Amortizacion'!E17 | L17: =IF(AND('05_Amortizacion'!C17="Sí",K17>0),"Sí","No") | M17: ='03_Intangibles'!R17&"" | N17: =IF('05_Amortizacion'!C17="No","No aplica",IF('02_Parametros'!$B$7=1,"Con indicios (PYMES 18.24)",IF(B17="Goodwill","No aplica (prueba NIC 36.10 b y 36.90)",IF(E17="Finita","Anual (NIC 38.104)","Anual (NIC 38.109)")))) | O17: =IF(G17="","No",IF(G17=0,"Sí","No"))
A19: ⓘ Cómo se calcula esta hoja
A20: Columna | B20: Fórmula (Excel) | C20: Cómo se calcula (sencillo) | D20: Ejemplo con números reales | E20: De dónde viene | F20: Norma
A21: Categoría | B21: '='05_Amortizacion'!B5 | C21: Trae la categoría de la partida desde la hoja 05 (Amortización y vida finita / indefinida). | D21: Fila 1: «Otro» → Otro | E21: hoja «Amortización y vida finita / indefinida» | F21: —
A22: Vida registrada (meses) | B22: '=IF('03_Intangibles'!I5="","",'03_Intangibles'!I5) | C22: Trae la vida útil en meses que registró el cliente en la hoja 03 (Auxiliar de intangibles y goodwill); si no la informó, queda en blanco. | D22: Fila 1: IF(60=""; ""; 60) → 60 | E22: hoja «Auxiliar de intangibles y goodwill» | F22: —
A23: Vida aplicada (meses) | B23: '=IF('05_Amortizacion'!G5="","",'05_Amortizacion'!G5) | C23: Trae la vida aplicada de la hoja 05 (Amortización), ya limitada al tope PYMES cuando corresponde; en blanco si no hay. | D23: Fila 1: IF(60=""; ""; 60) → 60 | E23: hoja «Amortización y vida finita / indefinida» | F23: —
A24: Tipo de vida | B24: '='05_Amortizacion'!H5 | C24: Trae de la hoja 05 (Amortización) si la vida es finita, indefinida, sin estimación o no aplica. | D24: Fila 1: «Finita» → Finita | E24: hoja «Amortización y vida finita / indefinida» | F24: —
A25: Meses transcurridos al cierre | B25: '=IF(OR('03_Intangibles'!F5="",'05_Amortizacion'!C5="No"),"",MAX(0,(YEAR('02_Parametros'!$B$5)-YEAR('03_Intangibles'!F5))*12+MONTH('02_Parametros'!$B$5)-MONTH('03_Intangibles'!F5)+1)) | C25: Cuenta los meses desde la fecha disponible para uso (la hoja 03 (Auxiliar de intangibles y goodwill)) hasta el corte, incluido el mes de inicio y sin tope de 12. Queda en blanco si falta la fecha o la partida no es capitalizable. | D25: Fila 1: IF(OR(«2023-01-01»=""; «Sí»="No"); ""; MAX(0; (YEAR(«2025-12-31»)-YEAR(«2023-01-01»))*12+MONTH(«2025-12-31»)-MONTH(«2023-01-01»)+1)) → 36 | E25: hoja «Auxiliar de intangibles y goodwill», hoja «Amortización y vida finita / indefinida», hoja «Parámetros» | F25: —
A26: Vida remanente (meses) | B26: '=IF(OR(D5="",F5=""),"",MAX(D5-F5,0)) | C26: Resta los meses transcurridos a la vida aplicada (mínimo cero); en blanco si falta alguno de los dos datos. | D26: Fila 1: IF(OR(60=""; 36=""); ""; MAX(60-36; 0)) → 24 | E26: «Vida aplicada (meses)» (esta hoja), «Meses transcurridos al cierre» (esta hoja) | F26: —
A27: Amort. acumulada esperada | B27: '=IF(OR(D5="",F5=""),"",MIN('05_Amortizacion'!F5,'05_Amortizacion'!F5/D5*F5)) | C27: Reparte el importe amortizable de la hoja 05 (Amortización) entre la vida aplicada y lo multiplica por los meses transcurridos, sin pasar del importe amortizable; en blanco si falta la vida o los meses. | D27: Fila 1: IF(OR(60=""; 36=""); ""; MIN(60.000,00; 60.000,00/60*36)) → 36.000,00 | E27: «Vida aplicada (meses)» (esta hoja), «Meses transcurridos al cierre» (esta hoja), hoja «Amortización y vida finita / indefinida» | F27: —
A28: Amort. acumulada recalculada | B28: '='05_Amortizacion'!N5 | C28: Trae la amortización acumulada al corte que recalculó el auditor en la hoja 05 (Amortización). | D28: Fila 1: 36.000,00 → 36.000,00 | E28: hoja «Amortización y vida finita / indefinida» | F28: —
A29: Diferencia (esperada − recalculada) | B29: '=IF(OR(H5="",'03_Intangibles'!L5>0,AND('05_Amortizacion'!C5="Sí",LEFT('05_Amortizacion'!Q5,6)<>"Lineal")),"",H5-I5) | C29: Resta la acumulada recalculada a la esperada. Queda en blanco si no hay esperada, si la partida tiene deterioro previo en la hoja 03 (Auxiliar de intangibles y goodwill) o si se aceptó un método distinto del lineal. | D29: Fila 1: IF(OR(36.000,00=""; (vacío)>0; AND(«Sí»="Sí"; LEFT(«Lineal»; 6)<>"Lineal")); ""; 36.000,00-36.000,00) → 0,00 | E29: «Amort. acumulada esperada» (esta hoja), «Amort. acumulada recalculada» (esta hoja), hoja «Auxiliar de intangibles y goodwill», hoja «Amortización y vida finita / indefinida» | F29: —
A30: Valor residual | B30: '='05_Amortizacion'!E5 | C30: Trae el valor residual usado en la hoja 05 (Amortización), cero si el cliente no lo informó. | D30: Fila 1: 0,00 → 0,00 | E30: hoja «Amortización y vida finita / indefinida» | F30: —
A31: Residual distinto de cero | B31: '=IF(AND('05_Amortizacion'!C5="Sí",K5>0),"Sí","No") | C31: Marca «Sí» cuando la partida es capitalizable y su valor residual es mayor que cero; si no, «No». | D31: Fila 1: IF(AND(«Sí»="Sí"; 0,00>0); "Sí"; "No") → No | E31: «Valor residual» (esta hoja), hoja «Amortización y vida finita / indefinida» | F31: —
... A34: Totalmente amortizado | B34: '=IF(G5="","No",IF(G5=0,"Sí","No")) | C34: Marca «Sí» cuando la vida remanente es cero; si es mayor o está en blanco, marca «No». | D34: Fila 1: IF(24=""; "No"; IF(24=0; "Sí"; "No")) → No | E34: «Vida remanente (meses)» (esta hoja) | F34: —

Sheet 07_Deterioro
A1: Deterioro e importe recuperable | H1: ⟵ Inicio | I1: ◀ Anterior | J1: Siguiente ▶
A2: Activos intangibles y goodwill · Cliente de muestra S.A. · corte 2025-12-31
A4: Código | B4: Categoría | C4: Capitalizable | D4: Prueba exigida | E4: Importe en libros antes del deterioro | F4: Valor en uso | G4: VR menos costos de disposición | H4: Importe recuperable | I4: Deterioro calculado | J4: Deterioro registrado | K4: Deterioro auditado | L4: Diferencia
A5: SW-01 | B5: ='05_Amortizacion'!B5 | C5: ='05_Amortizacion'!C5 | D5: =IF(C5="No","No aplica",IF('02_Parametros'!$B$7=1,"Solo si hay indicios (PYMES 27.7)",IF(B5="Goodwill","Anual (NIC 36.10 b y 36.90)",IF(OR('05_Amortizacion'!G5="",'03_Intangibles'!F5=""),"Anual (NIC 36.10 a)","Si hay indicios (NIC 36.9)")))) | E5: ='05_Amortizacion'!D5-'05_Amortizacion'!N5-'03_Intangibles'!L5 | F5: =IF('03_Intangibles'!M5="","",'03_Intangibles'!M5) | G5: =IF('03_Intangibles'!N5="","",'03_Intangibles'!N5) | H5: =IF(AND(F5="",G5=""),"",MAX(F5,G5)) | I5: =IF(OR(H5="",C5="No"),"",MAX(E5-H5,0)) | J5: ='03_Intangibles'!O5+0 | K5: =IF(C5="No",0,IF(I5="",J5,I5)) | L5: =K5-J5
A6: LIC-01 | B6: ='05_Amortizacion'!B6 | C6: ='05_Amortizacion'!C6 | D6: =IF(C6="No","No aplica",IF('02_Parametros'!$B$7=1,"Solo si hay indicios (PYMES 27.7)",IF(B6="Goodwill","Anual (NIC 36.10 b y 36.90)",IF(OR('05_Amortizacion'!G6="",'03_Intangibles'!F6=""),"Anual (NIC 36.10 a)","Si hay indicios (NIC 36.9)")))) | E6: ='05_Amortizacion'!D6-'05_Amortizacion'!N6-'03_Intangibles'!L6 | F6: =IF('03_Intangibles'!M6="","",'03_Intangibles'!M6) | G6: =IF('03_Intangibles'!N6="","",'03_Intangibles'!N6) | H6: =IF(AND(F6="",G6=""),"",MAX(F6,G6)) | I6: =IF(OR(H6="",C6="No"),"",MAX(E6-H6,0)) | J6: ='03_Intangibles'!O6+0 | K6: =IF(C6="No",0,IF(I6="",J6,I6)) | L6: =K6-J6
A7: MAR-01 | B7: ='05_Amortizacion'!B7 | C7: ='05_Amortizacion'!C7 | D7: =IF(C7="No","No aplica",IF('02_Parametros'!$B$7=1,"Solo si hay indicios (PYMES 27.7)",IF(B7="Goodwill","Anual (NIC 36.10 b y 36.90)",IF(OR('05_Amortizacion'!G7="",'03_Intangibles'!F7=""),"Anual (NIC 36.10 a)","Si hay indicios (NIC 36.9)")))) | E7: ='05_Amortizacion'!D7-'05_Amortizacion'!N7-'03_Intangibles'!L7 | F7: =IF('03_Intangibles'!M7="","",'03_Intangibles'!M7) | G7: =IF('03_Intangibles'!N7="","",'03_Intangibles'!N7) | H7: =IF(AND(F7="",G7=""),"",MAX(F7,G7)) | I7: =IF(OR(H7="",C7="No"),"",MAX(E7-H7,0)) | J7: ='03_Intangibles'!O7+0 | K7: =IF(C7="No",0,IF(I7="",J7,I7)) | L7: =K7-J7
A8: GW-01 | B8: ='05_Amortizacion'!B8 | C8: ='05_Amortizacion'!C8 | D8: =IF(C8="No","No aplica",IF('02_Parametros'!$B$7=1,"Solo si hay indicios (PYMES 27.7)",IF(B8="Goodwill","Anual (NIC 36.10 b y 36.90)",IF(OR('05_Amortizacion'!G8="",'03_Intangibles'!F8=""),"Anual (NIC 36.10 a)","Si hay indicios (NIC 36.9)")))) | E8: ='05_Amortizacion'!D8-'05_Amortizacion'!N8-'03_Intangibles'!L8 | F8: =IF('03_Intangibles'!M8="","",'03_Intangibles'!M8) | G8: =IF('03_Intangibles'!N8="","",'03_Intangibles'!N8) | H8: =IF(AND(F8="",G8=""),"",MAX(F8,G8)) | I8: =IF(OR(H8="",C8="No"),"",MAX(E8-H8,0)) | J8: ='03_Intangibles'!O8+0 | K8: =IF(C8="No",0,IF(I8="",J8,I8)) | L8: =K8-J8
A9: INV-01 | B9: ='05_Amortizacion'!B9 | C9: ='05_Amortizacion'!C9 | D9: =IF(C9="No","No aplica",IF('02_Parametros'!$B$7=1,"Solo si hay indicios (PYMES 27.7)",IF(B9="Goodwill","Anual (NIC 36.10 b y 36.90)",IF(OR('05_Amortizacion'!G9="",'03_Intangibles'!F9=""),"Anual (NIC 36.10 a)","Si hay indicios (NIC 36.9)")))) | E9: ='05_Amortizacion'!D9-'05_Amortizacion'!N9-'03_Intangibles'!L9 | F9: =IF('03_Intangibles'!M9="","",'03_Intangibles'!M9) | G9: =IF('03_Intangibles'!N9="","",'03_Intangibles'!N9) | H9: =IF(AND(F9="",G9=""),"",MAX(F9,G9)) | I9: =IF(OR(H9="",C9="No"),"",MAX(E9-H9,0)) | J9: ='03_Intangibles'!O9+0 | K9: =IF(C9="No",0,IF(I9="",J9,I9)) | L9: =K9-J9
A10: DES-01 | B10: ='05_Amortizacion'!B10 | C10: ='05_Amortizacion'!C10 | D10: =IF(C10="No","No aplica",IF('02_Parametros'!$B$7=1,"Solo si hay indicios (PYMES 27.7)",IF(B10="Goodwill","Anual (NIC 36.10 b y 36.90)",IF(OR('05_Amortizacion'!G10="",'03_Intangibles'!F10=""),"Anual (NIC 36.10 a)","Si hay indicios (NIC 36.9)")))) | E10: ='05_Amortizacion'!D10-'05_Amortizacion'!N10-'03_Intangibles'!L10 | F10: =IF('03_Intangibles'!M10="","",'03_Intangibles'!M10) | G10: =IF('03_Intangibles'!N10="","",'03_Intangibles'!N10) | H10: =IF(AND(F10="",G10=""),"",MAX(F10,G10)) | I10: =IF(OR(H10="",C10="No"),"",MAX(E10-H10,0)) | J10: ='03_Intangibles'!O10+0 | K10: =IF(C10="No",0,IF(I10="",J10,I10)) | L10: =K10-J10
A11: DES-02 | B11: ='05_Amortizacion'!B11 | C11: ='05_Amortizacion'!C11 | D11: =IF(C11="No","No aplica",IF('02_Parametros'!$B$7=1,"Solo si hay indicios (PYMES 27.7)",IF(B11="Goodwill","Anual (NIC 36.10 b y 36.90)",IF(OR('05_Amortizacion'!G11="",'03_Intangibles'!F11=""),"Anual (NIC 36.10 a)","Si hay indicios (NIC 36.9)")))) | E11: ='05_Amortizacion'!D11-'05_Amortizacion'!N11-'03_Intangibles'!L11 | F11: =IF('03_Intangibles'!M11="","",'03_Intangibles'!M11) | G11: =IF('03_Intangibles'!N11="","",'03_Intangibles'!N11) | H11: =IF(AND(F11="",G11=""),"",MAX(F11,G11)) | I11: =IF(OR(H11="",C11="No"),"",MAX(E11-H11,0)) | J11: ='03_Intangibles'!O11+0 | K11: =IF(C11="No",0,IF(I11="",J11,I11)) | L11: =K11-J11
A12: DES-03 | B12: ='05_Amortizacion'!B12 | C12: ='05_Amortizacion'!C12 | D12: =IF(C12="No","No aplica",IF('02_Parametros'!$B$7=1,"Solo si hay indicios (PYMES 27.7)",IF(B12="Goodwill","Anual (NIC 36.10 b y 36.90)",IF(OR('05_Amortizacion'!G12="",'03_Intangibles'!F12=""),"Anual (NIC 36.10 a)","Si hay indicios (NIC 36.9)")))) | E12: ='05_Amortizacion'!D12-'05_Amortizacion'!N12-'03_Intangibles'!L12 | F12: =IF('03_Intangibles'!M12="","",'03_Intangibles'!M12) | G12: =IF('03_Intangibles'!N12="","",'03_Intangibles'!N12) | H12: =IF(AND(F12="",G12=""),"",MAX(F12,G12)) | I12: =IF(OR(H12="",C12="No"),"",MAX(E12-H12,0)) | J12: ='03_Intangibles'!O12+0 | K12: =IF(C12="No",0,IF(I12="",J12,I12)) | L12: =K12-J12
A13: PAT-01 | B13: ='05_Amortizacion'!B13 | C13: ='05_Amortizacion'!C13 | D13: =IF(C13="No","No aplica",IF('02_Parametros'!$B$7=1,"Solo si hay indicios (PYMES 27.7)",IF(B13="Goodwill","Anual (NIC 36.10 b y 36.90)",IF(OR('05_Amortizacion'!G13="",'03_Intangibles'!F13=""),"Anual (NIC 36.10 a)","Si hay indicios (NIC 36.9)")))) | E13: ='05_Amortizacion'!D13-'05_Amortizacion'!N13-'03_Intangibles'!L13 | F13: =IF('03_Intangibles'!M13="","",'03_Intangibles'!M13) | G13: =IF('03_Intangibles'!N13="","",'03_Intangibles'!N13) | H13: =IF(AND(F13="",G13=""),"",MAX(F13,G13)) | I13: =IF(OR(H13="",C13="No"),"",MAX(E13-H13,0)) | J13: ='03_Intangibles'!O13+0 | K13: =IF(C13="No",0,IF(I13="",J13,I13)) | L13: =K13-J13
A14: SW-02 | B14: ='05_Amortizacion'!B14 | C14: ='05_Amortizacion'!C14 | D14: =IF(C14="No","No aplica",IF('02_Parametros'!$B$7=1,"Solo si hay indicios (PYMES 27.7)",IF(B14="Goodwill","Anual (NIC 36.10 b y 36.90)",IF(OR('05_Amortizacion'!G14="",'03_Intangibles'!F14=""),"Anual (NIC 36.10 a)","Si hay indicios (NIC 36.9)")))) | E14: ='05_Amortizacion'!D14-'05_Amortizacion'!N14-'03_Intangibles'!L14 | F14: =IF('03_Intangibles'!M14="","",'03_Intangibles'!M14) | G14: =IF('03_Intangibles'!N14="","",'03_Intangibles'!N14) | H14: =IF(AND(F14="",G14=""),"",MAX(F14,G14)) | I14: =IF(OR(H14="",C14="No"),"",MAX(E14-H14,0)) | J14: ='03_Intangibles'!O14+0 | K14: =IF(C14="No",0,IF(I14="",J14,I14)) | L14: =K14-J14
A15: SW-03 | B15: ='05_Amortizacion'!B15 | C15: ='05_Amortizacion'!C15 | D15: =IF(C15="No","No aplica",IF('02_Parametros'!$B$7=1,"Solo si hay indicios (PYMES 27.7)",IF(B15="Goodwill","Anual (NIC 36.10 b y 36.90)",IF(OR('05_Amortizacion'!G15="",'03_Intangibles'!F15=""),"Anual (NIC 36.10 a)","Si hay indicios (NIC 36.9)")))) | E15: ='05_Amortizacion'!D15-'05_Amortizacion'!N15-'03_Intangibles'!L15 | F15: =IF('03_Intangibles'!M15="","",'03_Intangibles'!M15) | G15: =IF('03_Intangibles'!N15="","",'03_Intangibles'!N15) | H15: =IF(AND(F15="",G15=""),"",MAX(F15,G15)) | I15: =IF(OR(H15="",C15="No"),"",MAX(E15-H15,0)) | J15: ='03_Intangibles'!O15+0 | K15: =IF(C15="No",0,IF(I15="",J15,I15)) | L15: =K15-J15
A16: CON-01 | B16: ='05_Amortizacion'!B16 | C16: ='05_Amortizacion'!C16 | D16: =IF(C16="No","No aplica",IF('02_Parametros'!$B$7=1,"Solo si hay indicios (PYMES 27.7)",IF(B16="Goodwill","Anual (NIC 36.10 b y 36.90)",IF(OR('05_Amortizacion'!G16="",'03_Intangibles'!F16=""),"Anual (NIC 36.10 a)","Si hay indicios (NIC 36.9)")))) | E16: ='05_Amortizacion'!D16-'05_Amortizacion'!N16-'03_Intangibles'!L16 | F16: =IF('03_Intangibles'!M16="","",'03_Intangibles'!M16) | G16: =IF('03_Intangibles'!N16="","",'03_Intangibles'!N16) | H16: =IF(AND(F16="",G16=""),"",MAX(F16,G16)) | I16: =IF(OR(H16="",C16="No"),"",MAX(E16-H16,0)) | J16: ='03_Intangibles'!O16+0 | K16: =IF(C16="No",0,IF(I16="",J16,I16)) | L16: =K16-J16
A17: CON-02 | B17: ='05_Amortizacion'!B17 | C17: ='05_Amortizacion'!C17 | D17: =IF(C17="No","No aplica",IF('02_Parametros'!$B$7=1,"Solo si hay indicios (PYMES 27.7)",IF(B17="Goodwill","Anual (NIC 36.10 b y 36.90)",IF(OR('05_Amortizacion'!G17="",'03_Intangibles'!F17=""),"Anual (NIC 36.10 a)","Si hay indicios (NIC 36.9)")))) | E17: ='05_Amortizacion'!D17-'05_Amortizacion'!N17-'03_Intangibles'!L17 | F17: =IF('03_Intangibles'!M17="","",'03_Intangibles'!M17) | G17: =IF('03_Intangibles'!N17="","",'03_Intangibles'!N17) | H17: =IF(AND(F17="",G17=""),"",MAX(F17,G17)) | I17: =IF(OR(H17="",C17="No"),"",MAX(E17-H17,0)) | J17: ='03_Intangibles'!O17+0 | K17: =IF(C17="No",0,IF(I17="",J17,I17)) | L17: =K17-J17
A18: TOTAL | J18: =SUM(J5:J17) | K18: =SUM(K5:K17) | L18: =SUM(L5:L17)
A20: ⓘ Cómo se calcula esta hoja
A21: Columna | B21: Fórmula (Excel) | C21: Cómo se calcula (sencillo) | D21: Ejemplo con números reales | E21: De dónde viene | F21: Norma
A22: Categoría | B22: '='05_Amortizacion'!B5 | C22: Trae la categoría de la partida desde la hoja 05 (Amortización y vida finita / indefinida) para esta prueba. | D22: Fila 1: «Otro» → Otro | E22: hoja «Amortización y vida finita / indefinida» | F22: —
A23: Capitalizable | B23: '='05_Amortizacion'!C5 | C23: Trae de la hoja 05 (Amortización) si la partida sigue en el activo; solo las capitalizables se prueban por deterioro. | D23: Fila 1: «Sí» → Sí | E23: hoja «Amortización y vida finita / indefinida» | F23: —
A24: Prueba exigida | B24: '=IF(C5="No","No aplica",IF('02_Parametros'!$B$7=1,"Solo si hay indicios (PYMES 27.7)",IF(B5="Goodwill","Anual (NIC 36.10 b y 36.90)",IF(OR('05_Amortizacion'!G5="",'03_Intangibles'!F5=""),"Anual (NIC 36.10 a)","Si hay indicios (NIC 36.9)")))) | C24: Indica cuándo se exige la prueba: no aplica si no es capitalizable; en PYMES solo con indicios; anual para el goodwill y para partidas sin vida aplicada o sin fecha de uso; en las demás, solo si hay indicios. | D24: Fila 1: IF(«Sí»="No"; "No aplica"; IF(0,00=1; "Solo si hay indicios (PYMES 27.7)"; IF(«Otro»="Goodwill"; "Anual (NIC 36.10 b y 36.90)"; IF(OR(60=""; «2023-01-01»=""); "Anual (NIC 36.10 a)"; "Si hay indicios (NIC 36.9)")))) → Si hay indicios (NIC 36.9) | E24: «Capitalizable» (esta hoja), «Categoría» (esta hoja), hoja «Parámetros», hoja «Amortización y vida finita / indefinida», hoja «Auxiliar de intangibles y goodwill» | F24: —
A25: Importe en libros antes del deterioro | B25: '='05_Amortizacion'!D5-'05_Amortizacion'!N5-'03_Intangibles'!L5 | C25: Parte del costo auditado de la hoja 05 (Amortización), resta la amortización acumulada recalculada y el deterioro previo de la hoja 03 (Auxiliar de intangibles y goodwill). | D25: Fila 1: 60.000,00-36.000,00-(vacío) → 24.000,00 | E25: hoja «Amortización y vida finita / indefinida», hoja «Auxiliar de intangibles y goodwill» | F25: —
A26: Valor en uso | B26: '=IF('03_Intangibles'!M5="","",'03_Intangibles'!M5) | C26: Trae el valor en uso que informó el cliente en la hoja 03 (Auxiliar de intangibles y goodwill); si no lo informó, queda en blanco. | D26: Fila 1: IF((vacío)=""; ""; (vacío)) → (en blanco) | E26: hoja «Auxiliar de intangibles y goodwill» | F26: —
A27: VR menos costos de disposición | B27: '=IF('03_Intangibles'!N5="","",'03_Intangibles'!N5) | C27: Trae el valor razonable menos costos de disposición informado en la hoja 03 (Auxiliar de intangibles y goodwill); en blanco si falta. | D27: Fila 1: IF((vacío)=""; ""; (vacío)) → (en blanco) | E27: hoja «Auxiliar de intangibles y goodwill» | F27: —
A28: Importe recuperable | B28: '=IF(AND(F5="",G5=""),"",MAX(F5,G5)) | C28: Toma el mayor entre el valor en uso y el valor razonable menos costos de disposición; si faltan ambos, queda en blanco. | D28: Fila 1: IF(AND((vacío)=""; (vacío)=""); ""; MAX((vacío); (vacío))) → (en blanco) | E28: «Valor en uso» (esta hoja), «VR menos costos de disposición» (esta hoja) | F28: —
A29: Deterioro calculado | B29: '=IF(OR(H5="",C5="No"),"",MAX(E5-H5,0)) | C29: Si el importe en libros supera al recuperable, la diferencia es el deterioro (si no, cero). Queda en blanco cuando no hay importe recuperable o la partida no es capitalizable. | D29: Fila 1: IF(OR((vacío)=""; «Sí»="No"); ""; MAX(24.000,00-(vacío); 0)) → (en blanco) | E29: «Importe recuperable» (esta hoja), «Capitalizable» (esta hoja), «Importe en libros antes del deterioro» (esta hoja) | F29: —
A30: Deterioro registrado | B30: '='03_Intangibles'!O5+0 | C30: Trae el deterioro del año que registró el cliente en la hoja 03 (Auxiliar de intangibles y goodwill) (cero si está en blanco). | D30: Fila 1: (vacío)+0 → 0,00 | E30: hoja «Auxiliar de intangibles y goodwill» | F30: —
A31: Deterioro auditado | B31: '=IF(C5="No",0,IF(I5="",J5,I5)) | C31: Usa el deterioro calculado; si no se pudo calcular (sin importe recuperable), acepta el registrado por el cliente. En partidas no capitalizables es cero. | D31: Fila 1: IF(«Sí»="No"; 0; IF((vacío)=""; 0,00; (vacío))) → 0,00 | E31: «Capitalizable» (esta hoja), «Deterioro calculado» (esta hoja), «Deterioro registrado» (esta hoja) | F31: —
A32: Diferencia | B32: '=K5-J5 | C32: Resta el deterioro registrado por el cliente al deterioro auditado: lo que falta (positivo) o sobra (negativo) registrar. | D32: Fila 1: 0,00-0,00 → 0,00 | E32: «Deterioro auditado» (esta hoja), «Deterioro registrado» (esta hoja) | F32: —

Sheet 08_Reversion
A1: Reversión del deterioro | H1: ⟵ Inicio | I1: ◀ Anterior | J1: Siguiente ▶
A2: Activos intangibles y goodwill · Cliente de muestra S.A. · corte 2025-12-31
A4: Código | B4: Categoría | C4: Deterioro acumulado previo | D4: Indicio de reversión | E4: Importe en libros | F4: Importe recuperable | G4: Reversión calculada | H4: Reversión registrada | I4: Reversión auditada | J4: Diferencia | K4: Límite: importe en libros sin deterioro (NIC 36.117)
A5: SW-01 | B5: ='05_Amortizacion'!B5 | C5: ='03_Intangibles'!L5+0 | D5: ='03_Intangibles'!P5&"" | E5: ='07_Deterioro'!E5 | F5: =IF('07_Deterioro'!H5="","",'07_Deterioro'!H5) | G5: =IF(OR(B5="Goodwill",'05_Amortizacion'!C5="No",C5=0,LEFT(D5,1)<>"S"),0,IF(F5="","",MAX(0,MIN(F5-E5,C5)))) | H5: ='03_Intangibles'!Q5+0 | I5: =IF(G5="",H5,G5) | J5: =I5-H5 | K5: =E5+C5
A6: LIC-01 | B6: ='05_Amortizacion'!B6 | C6: ='03_Intangibles'!L6+0 | D6: ='03_Intangibles'!P6&"" | E6: ='07_Deterioro'!E6 | F6: =IF('07_Deterioro'!H6="","",'07_Deterioro'!H6) | G6: =IF(OR(B6="Goodwill",'05_Amortizacion'!C6="No",C6=0,LEFT(D6,1)<>"S"),0,IF(F6="","",MAX(0,MIN(F6-E6,C6)))) | H6: ='03_Intangibles'!Q6+0 | I6: =IF(G6="",H6,G6) | J6: =I6-H6 | K6: =E6+C6
A7: MAR-01 | B7: ='05_Amortizacion'!B7 | C7: ='03_Intangibles'!L7+0 | D7: ='03_Intangibles'!P7&"" | E7: ='07_Deterioro'!E7 | F7: =IF('07_Deterioro'!H7="","",'07_Deterioro'!H7) | G7: =IF(OR(B7="Goodwill",'05_Amortizacion'!C7="No",C7=0,LEFT(D7,1)<>"S"),0,IF(F7="","",MAX(0,MIN(F7-E7,C7)))) | H7: ='03_Intangibles'!Q7+0 | I7: =IF(G7="",H7,G7) | J7: =I7-H7 | K7: =E7+C7
A8: GW-01 | B8: ='05_Amortizacion'!B8 | C8: ='03_Intangibles'!L8+0 | D8: ='03_Intangibles'!P8&"" | E8: ='07_Deterioro'!E8 | F8: =IF('07_Deterioro'!H8="","",'07_Deterioro'!H8) | G8: =IF(OR(B8="Goodwill",'05_Amortizacion'!C8="No",C8=0,LEFT(D8,1)<>"S"),0,IF(F8="","",MAX(0,MIN(F8-E8,C8)))) | H8: ='03_Intangibles'!Q8+0 | I8: =IF(G8="",H8,G8) | J8: =I8-H8 | K8: =E8+C8
A9: INV-01 | B9: ='05_Amortizacion'!B9 | C9: ='03_Intangibles'!L9+0 | D9: ='03_Intangibles'!P9&"" | E9: ='07_Deterioro'!E9 | F9: =IF('07_Deterioro'!H9="","",'07_Deterioro'!H9) | G9: =IF(OR(B9="Goodwill",'05_Amortizacion'!C9="No",C9=0,LEFT(D9,1)<>"S"),0,IF(F9="","",MAX(0,MIN(F9-E9,C9)))) | H9: ='03_Intangibles'!Q9+0 | I9: =IF(G9="",H9,G9) | J9: =I9-H9 | K9: =E9+C9
A10: DES-01 | B10: ='05_Amortizacion'!B10 | C10: ='03_Intangibles'!L10+0 | D10: ='03_Intangibles'!P10&"" | E10: ='07_Deterioro'!E10 | F10: =IF('07_Deterioro'!H10="","",'07_Deterioro'!H10) | G10: =IF(OR(B10="Goodwill",'05_Amortizacion'!C10="No",C10=0,LEFT(D10,1)<>"S"),0,IF(F10="","",MAX(0,MIN(F10-E10,C10)))) | H10: ='03_Intangibles'!Q10+0 | I10: =IF(G10="",H10,G10) | J10: =I10-H10 | K10: =E10+C10
A11: DES-02 | B11: ='05_Amortizacion'!B11 | C11: ='03_Intangibles'!L11+0 | D11: ='03_Intangibles'!P11&"" | E11: ='07_Deterioro'!E11 | F11: =IF('07_Deterioro'!H11="","",'07_Deterioro'!H11) | G11: =IF(OR(B11="Goodwill",'05_Amortizacion'!C11="No",C11=0,LEFT(D11,1)<>"S"),0,IF(F11="","",MAX(0,MIN(F11-E11,C11)))) | H11: ='03_Intangibles'!Q11+0 | I11: =IF(G11="",H11,G11) | J11: =I11-H11 | K11: =E11+C11
A12: DES-03 | B12: ='05_Amortizacion'!B12 | C12: ='03_Intangibles'!L12+0 | D12: ='03_Intangibles'!P12&"" | E12: ='07_Deterioro'!E12 | F12: =IF('07_Deterioro'!H12="","",'07_Deterioro'!H12) | G12: =IF(OR(B12="Goodwill",'05_Amortizacion'!C12="No",C12=0,LEFT(D12,1)<>"S"),0,IF(F12="","",MAX(0,MIN(F12-E12,C12)))) | H12: ='03_Intangibles'!Q12+0 | I12: =IF(G12="",H12,G12) | J12: =I12-H12 | K12: =E12+C12
A13: PAT-01 | B13: ='05_Amortizacion'!B13 | C13: ='03_Intangibles'!L13+0 | D13: ='03_Intangibles'!P13&"" | E13: ='07_Deterioro'!E13 | F13: =IF('07_Deterioro'!H13="","",'07_Deterioro'!H13) | G13: =IF(OR(B13="Goodwill",'05_Amortizacion'!C13="No",C13=0,LEFT(D13,1)<>"S"),0,IF(F13="","",MAX(0,MIN(F13-E13,C13)))) | H13: ='03_Intangibles'!Q13+0 | I13: =IF(G13="",H13,G13) | J13: =I13-H13 | K13: =E13+C13
A14: SW-02 | B14: ='05_Amortizacion'!B14 | C14: ='03_Intangibles'!L14+0 | D14: ='03_Intangibles'!P14&"" | E14: ='07_Deterioro'!E14 | F14: =IF('07_Deterioro'!H14="","",'07_Deterioro'!H14) | G14: =IF(OR(B14="Goodwill",'05_Amortizacion'!C14="No",C14=0,LEFT(D14,1)<>"S"),0,IF(F14="","",MAX(0,MIN(F14-E14,C14)))) | H14: ='03_Intangibles'!Q14+0 | I14: =IF(G14="",H14,G14) | J14: =I14-H14 | K14: =E14+C14
A15: SW-03 | B15: ='05_Amortizacion'!B15 | C15: ='03_Intangibles'!L15+0 | D15: ='03_Intangibles'!P15&"" | E15: ='07_Deterioro'!E15 | F15: =IF('07_Deterioro'!H15="","",'07_Deterioro'!H15) | G15: =IF(OR(B15="Goodwill",'05_Amortizacion'!C15="No",C15=0,LEFT(D15,1)<>"S"),0,IF(F15="","",MAX(0,MIN(F15-E15,C15)))) | H15: ='03_Intangibles'!Q15+0 | I15: =IF(G15="",H15,G15) | J15: =I15-H15 | K15: =E15+C15
A16: CON-01 | B16: ='05_Amortizacion'!B16 | C16: ='03_Intangibles'!L16+0 | D16: ='03_Intangibles'!P16&"" | E16: ='07_Deterioro'!E16 | F16: =IF('07_Deterioro'!H16="","",'07_Deterioro'!H16) | G16: =IF(OR(B16="Goodwill",'05_Amortizacion'!C16="No",C16=0,LEFT(D16,1)<>"S"),0,IF(F16="","",MAX(0,MIN(F16-E16,C16)))) | H16: ='03_Intangibles'!Q16+0 | I16: =IF(G16="",H16,G16) | J16: =I16-H16 | K16: =E16+C16
A17: CON-02 | B17: ='05_Amortizacion'!B17 | C17: ='03_Intangibles'!L17+0 | D17: ='03_Intangibles'!P17&"" | E17: ='07_Deterioro'!E17 | F17: =IF('07_Deterioro'!H17="","",'07_Deterioro'!H17) | G17: =IF(OR(B17="Goodwill",'05_Amortizacion'!C17="No",C17=0,LEFT(D17,1)<>"S"),0,IF(F17="","",MAX(0,MIN(F17-E17,C17)))) | H17: ='03_Intangibles'!Q17+0 | I17: =IF(G17="",H17,G17) | J17: =I17-H17 | K17: =E17+C17
A18: TOTAL | H18: =SUM(H5:H17) | I18: =SUM(I5:I17) | J18: =SUM(J5:J17)
A20: ⓘ Cómo se calcula esta hoja
A21: Columna | B21: Fórmula (Excel) | C21: Cómo se calcula (sencillo) | D21: Ejemplo con números reales | E21: De dónde viene | F21: Norma
A22: Categoría | B22: '='05_Amortizacion'!B5 | C22: Trae la categoría de la partida desde la hoja 05 (Amortización); el goodwill nunca revierte su deterioro. | D22: Fila 1: «Otro» → Otro | E22: hoja «Amortización y vida finita / indefinida» | F22: —
A23: Deterioro acumulado previo | B23: '='03_Intangibles'!L5+0 | C23: Trae el deterioro acumulado de ejercicios anteriores informado en la hoja 03 (Auxiliar de intangibles y goodwill) (cero si está en blanco). | D23: Fila 1: (vacío)+0 → 0,00 | E23: hoja «Auxiliar de intangibles y goodwill» | F23: —
A24: Indicio de reversión | B24: '='03_Intangibles'!P5&"" | C24: Copia la respuesta del cliente sobre si hay indicios de que el deterioro se revirtió, tomada de la hoja 03 (Auxiliar de intangibles y goodwill). | D24: Fila 1: (vacío)&"" → (en blanco) | E24: hoja «Auxiliar de intangibles y goodwill» | F24: —
A25: Importe en libros | B25: '='07_Deterioro'!E5 | C25: Trae el importe en libros antes del deterioro calculado en la hoja 07 (Deterioro e importe recuperable). | D25: Fila 1: 24.000,00 → 24.000,00 | E25: hoja «Deterioro e importe recuperable» | F25: —
A26: Importe recuperable | B26: '=IF('07_Deterioro'!H5="","",'07_Deterioro'!H5) | C26: Trae el importe recuperable de la hoja 07 (Deterioro e importe recuperable); en blanco si allí no se calculó. | D26: Fila 1: IF((vacío)=""; ""; (vacío)) → (en blanco) | E26: hoja «Deterioro e importe recuperable» | F26: —
A27: Reversión calculada | B27: '=IF(OR(B5="Goodwill",'05_Amortizacion'!C5="No",C5=0,LEFT(D5,1)<>"S"),0,IF(F5="","",MAX(0,MIN(F5-E5,C5)))) | C27: Revierte lo que el recuperable supera al importe en libros, sin pasar del deterioro previo. Es cero en el goodwill, en partidas no capitalizables, sin deterioro previo o sin indicio «Sí»; en blanco si falta el recuperable. | D27: Fila 1: IF(OR(«Otro»="Goodwill"; «Sí»="No"; 0,00=0; LEFT((vacío); 1)<>"S"); 0; IF((vacío)=""; ""; MAX(0; MIN((vacío)-24.000,00; 0,00)))) → 0,00 | E27: «Categoría» (esta hoja), «Deterioro acumulado previo» (esta hoja), «Indicio de reversión» (esta hoja), «Importe recuperable» (esta hoja), «Importe en libros» (esta hoja), hoja «Amortización y vida finita / indefinida» | F27: —
A28: Reversión registrada | B28: '='03_Intangibles'!Q5+0 | C28: Trae la reversión del deterioro que registró el cliente en la hoja 03 (Auxiliar de intangibles y goodwill) (cero si está en blanco). | D28: Fila 1: (vacío)+0 → 0,00 | E28: hoja «Auxiliar de intangibles y goodwill» | F28: —
A29: Reversión auditada | B29: '=IF(G5="",H5,G5) | C29: Usa la reversión calculada; si quedó en blanco por falta de importe recuperable, acepta la registrada por el cliente. | D29: Fila 1: IF(0,00=""; 0,00; 0,00) → 0,00 | E29: «Reversión calculada» (esta hoja), «Reversión registrada» (esta hoja) | F29: —
A30: Diferencia | B30: '=I5-H5 | C30: Resta la reversión registrada por el cliente a la reversión auditada: positivo falta revertir, negativo sobra. | D30: Fila 1: 0,00-0,00 → 0,00 | E30: «Reversión auditada» (esta hoja), «Reversión registrada» (esta hoja) | F30: —
A31: Límite: importe en libros sin deterioro (NIC 36.117) | B31: '=E5+C5 | C31: Suma el importe en libros y el deterioro acumulado previo: es el techo hasta donde puede subir el activo al revertir el deterioro. | D31: Fila 1: 24.000,00+0,00 → 24.000,00 | E31: «Importe en libros» (esta hoja), «Deterioro acumulado previo» (esta hoja) | F31: —

Sheet 09_Ajuste
A1: Valor neto y ajuste propuesto | H1: ⟵ Inicio | I1: ◀ Anterior | J1: Siguiente ▶
A2: Activos intangibles y goodwill · Cliente de muestra S.A. · corte 2025-12-31
A4: Código | B4: Descripción | C4: Neto en libros (cliente) | D4: Neto auditado | E4: Ajuste propuesto
A5: SW-01 | B5: Software ERP | C5: ='03_Intangibles'!G5-'03_Intangibles'!J5-'03_Intangibles'!K5-'03_Intangibles'!L5-'03_Intangibles'!O5+'03_Intangibles'!Q5 | D5: =IF('05_Amortizacion'!C5="No",0,'05_Amortizacion'!D5-'05_Amortizacion'!N5-'03_Intangibles'!L5-'07_Deterioro'!K5+'08_Reversion'!I5) | E5: =D5-C5
A6: LIC-01 | B6: Licencia de distribución exclusiva | C6: ='03_Intangibles'!G6-'03_Intangibles'!J6-'03_Intangibles'!K6-'03_Intangibles'!L6-'03_Intangibles'!O6+'03_Intangibles'!Q6 | D6: =IF('05_Amortizacion'!C6="No",0,'05_Amortizacion'!D6-'05_Amortizacion'!N6-'03_Intangibles'!L6-'07_Deterioro'!K6+'08_Reversion'!I6) | E6: =D6-C6
A7: MAR-01 | B7: Marca comercial adquirida | C7: ='03_Intangibles'!G7-'03_Intangibles'!J7-'03_Intangibles'!K7-'03_Intangibles'!L7-'03_Intangibles'!O7+'03_Intangibles'!Q7 | D7: =IF('05_Amortizacion'!C7="No",0,'05_Amortizacion'!D7-'05_Amortizacion'!N7-'03_Intangibles'!L7-'07_Deterioro'!K7+'08_Reversion'!I7) | E7: =D7-C7
A8: GW-01 | B8: Goodwill adquisición Distribuidora Andina | C8: ='03_Intangibles'!G8-'03_Intangibles'!J8-'03_Intangibles'!K8-'03_Intangibles'!L8-'03_Intangibles'!O8+'03_Intangibles'!Q8 | D8: =IF('05_Amortizacion'!C8="No",0,'05_Amortizacion'!D8-'05_Amortizacion'!N8-'03_Intangibles'!L8-'07_Deterioro'!K8+'08_Reversion'!I8) | E8: =D8-C8
A9: INV-01 | B9: Estudio de mercado y prototipos nuevo producto | C9: ='03_Intangibles'!G9-'03_Intangibles'!J9-'03_Intangibles'!K9-'03_Intangibles'!L9-'03_Intangibles'!O9+'03_Intangibles'!Q9 | D9: =IF('05_Amortizacion'!C9="No",0,'05_Amortizacion'!D9-'05_Amortizacion'!N9-'03_Intangibles'!L9-'07_Deterioro'!K9+'08_Reversion'!I9) | E9: =D9-C9
A10: DES-01 | B10: Aplicación móvil de pedidos | C10: ='03_Intangibles'!G10-'03_Intangibles'!J10-'03_Intangibles'!K10-'03_Intangibles'!L10-'03_Intangibles'!O10+'03_Intangibles'!Q10 | D10: =IF('05_Amortizacion'!C10="No",0,'05_Amortizacion'!D10-'05_Amortizacion'!N10-'03_Intangibles'!L10-'07_Deterioro'!K10+'08_Reversion'!I10) | E10: =D10-C10
A11: DES-02 | B11: Módulo de comercio electrónico | C11: ='03_Intangibles'!G11-'03_Intangibles'!J11-'03_Intangibles'!K11-'03_Intangibles'!L11-'03_Intangibles'!O11+'03_Intangibles'!Q11 | D11: =IF('05_Amortizacion'!C11="No",0,'05_Amortizacion'!D11-'05_Amortizacion'!N11-'03_Intangibles'!L11-'07_Deterioro'!K11+'08_Reversion'!I11) | E11: =D11-C11
A12: DES-03 | B12: Plataforma logística en desarrollo | C12: ='03_Intangibles'!G12-'03_Intangibles'!J12-'03_Intangibles'!K12-'03_Intangibles'!L12-'03_Intangibles'!O12+'03_Intangibles'!Q12 | D12: =IF('05_Amortizacion'!C12="No",0,'05_Amortizacion'!D12-'05_Amortizacion'!N12-'03_Intangibles'!L12-'07_Deterioro'!K12+'08_Reversion'!I12) | E12: =D12-C12
A13: PAT-01 | B13: Patente de proceso | C13: ='03_Intangibles'!G13-'03_Intangibles'!J13-'03_Intangibles'!K13-'03_Intangibles'!L13-'03_Intangibles'!O13+'03_Intangibles'!Q13 | D13: =IF('05_Amortizacion'!C13="No",0,'05_Amortizacion'!D13-'05_Amortizacion'!N13-'03_Intangibles'!L13-'07_Deterioro'!K13+'08_Reversion'!I13) | E13: =D13-C13
A14: SW-02 | B14: Software CRM | C14: ='03_Intangibles'!G14-'03_Intangibles'!J14-'03_Intangibles'!K14-'03_Intangibles'!L14-'03_Intangibles'!O14+'03_Intangibles'!Q14 | D14: =IF('05_Amortizacion'!C14="No",0,'05_Amortizacion'!D14-'05_Amortizacion'!N14-'03_Intangibles'!L14-'07_Deterioro'!K14+'08_Reversion'!I14) | E14: =D14-C14
A15: SW-03 | B15: Software de nómina | C15: ='03_Intangibles'!G15-'03_Intangibles'!J15-'03_Intangibles'!K15-'03_Intangibles'!L15-'03_Intangibles'!O15+'03_Intangibles'!Q15 | D15: =IF('05_Amortizacion'!C15="No",0,'05_Amortizacion'!D15-'05_Amortizacion'!N15-'03_Intangibles'!L15-'07_Deterioro'!K15+'08_Reversion'!I15) | E15: =D15-C15
A16: CON-01 | B16: Concesión de distribución regional | C16: ='03_Intangibles'!G16-'03_Intangibles'!J16-'03_Intangibles'!K16-'03_Intangibles'!L16-'03_Intangibles'!O16+'03_Intangibles'!Q16 | D16: =IF('05_Amortizacion'!C16="No",0,'05_Amortizacion'!D16-'05_Amortizacion'!N16-'03_Intangibles'!L16-'07_Deterioro'!K16+'08_Reversion'!I16) | E16: =D16-C16
A17: CON-02 | B17: Concesión de peaje (importe total fijo de ingresos) | C17: ='03_Intangibles'!G17-'03_Intangibles'!J17-'03_Intangibles'!K17-'03_Intangibles'!L17-'03_Intangibles'!O17+'03_Intangibles'!Q17 | D17: =IF('05_Amortizacion'!C17="No",0,'05_Amortizacion'!D17-'05_Amortizacion'!N17-'03_Intangibles'!L17-'07_Deterioro'!K17+'08_Reversion'!I17) | E17: =D17-C17
A18: TOTAL | C18: =SUM(C5:C17) | D18: =SUM(D5:D17) | E18: =SUM(E5:E17)
A20: ⓘ Cómo se calcula esta hoja
A21: Columna | B21: Fórmula (Excel) | C21: Cómo se calcula (sencillo) | D21: Ejemplo con números reales | E21: De dónde viene | F21: Norma
A22: Neto en libros (cliente) | B22: '='03_Intangibles'!G5-'03_Intangibles'!J5-'03_Intangibles'!K5-'03_Intangibles'!L5-'03_Intangibles'!O5+'03_Intangibles'!Q5 | C22: Parte del costo de la hoja 03 (Auxiliar de intangibles y goodwill), resta la amortización acumulada inicial, la del año, el deterioro previo y el del año, y suma la reversión registrada: es el neto según las cifras del cliente. | D22: Fila 1: 60.000,00-24.000,00-12.000,00-(vacío)-(vacío)+(vacío) → 24.000,00 | E22: hoja «Auxiliar de intangibles y goodwill» | F22: —
A23: Neto auditado | B23: '=IF('05_Amortizacion'!C5="No",0,'05_Amortizacion'!D5-'05_Amortizacion'!N5-'03_Intangibles'!L5-'07_Deterioro'!K5+'08_Reversion'!I5) | C23: Parte del costo auditado (hoja 05), resta la amortización acumulada recalculada, el deterioro previo y el deterioro auditado (hoja 07), y suma la reversión auditada (hoja 08). Si la partida no es capitalizable, es cero. | D23: Fila 1: IF(«Sí»="No"; 0; 60.000,00-36.000,00-(vacío)-0,00+0,00) → 24.000,00 | E23: hoja «Amortización y vida finita / indefinida», hoja «Auxiliar de intangibles y goodwill», hoja «Deterioro e importe recuperable», hoja «Reversión del deterioro» | F23: —
A24: Ajuste propuesto | B24: '=D5-C5 | C24: Resta el neto en libros del cliente al neto auditado: positivo aumenta el activo, negativo lo disminuye. | D24: Fila 1: 24.000,00-24.000,00 → 0,00 | E24: «Neto auditado» (esta hoja), «Neto en libros (cliente)» (esta hoja) | F24: —

Sheet 10_Problemas
A1: Problemas encontrados | H1: ⟵ Inicio | I1: ◀ Anterior | J1: Siguiente ▶
A2: Activos intangibles y goodwill · Cliente de muestra S.A. · corte 2025-12-31
A4: Código | B4: Descripción | C4: Importe
A5: INVESTIGACION_CAPITALIZADA | B5: Investigación capitalizada en INV-01: 18.000,00 deben ir a gasto del ejercicio en que se incurrieron (NIC 38.54; PYMES 18.14). | C5: 18000
A6: DESARROLLO_NO_CUMPLE_57 | B6: Desarrollo capitalizado sin cumplir los criterios de NIC 38.57 en DES-02: baja 12.000,00 (NIC 38.57, 38.68). | C6: 12000
A7: SIN_PRUEBA_DETERIORO | B7: Sin prueba de deterioro en DES-03 (goodwill, vida indefinida o aún no disponible para su uso): falta el valor en uso o el valor razonable menos costos de disposición; importe en libros sin probar 30.000,00 (NIC 36.10, 36.90; NIC 38.108). | C7: 30000
A8: SIN_REVISION_VIDA | B8: Sin revisión anual de la vida útil y el método en PAT-01 (NIC 38.104; para vida indefinida, 38.109). | C8: 26800
A9: METODO_INGRESOS_SIN_JUSTIFICAR | B9: Amortización basada en los ingresos ordinarios sin excepción documentada en CON-01: NIC 38.98A presume que ese método es inapropiado y solo admite dejar de aplicar la presunción en dos circunstancias: (a) que el intangible se exprese como una medida de los ingresos, es decir que el contrato especifique un importe total fijo de ingresos a generar sobre el cual se determina la amortización (NIC 38.98C), o (b) que pueda demostrarse que los ingresos y el consumo de los beneficios económicos del activo están estrechamente correlacionados. La herramienta recalculó por el método lineal (NIC 38.97): efecto en resultados -3.000,00 (amortización recalculada menos registrada). Documente la circunstancia («a» o «b») y el papel que la respalda en la columna de justificación del auxiliar, o corrija el método. | C9: -3000
A10: METODO_INGRESOS_EXCEPCION | B10: Amortización basada en los ingresos con excepción documentada en CON-02 (la circunstancia invocada consta por partida en la cédula 05_Amortizacion): se aceptó la amortización registrada 25.000,00 y la herramienta no la recalcula, porque el auxiliar no informa los ingresos del ejercicio ni el importe total fijo de ingresos del contrato. Revise el papel citado en la justificación y confirme que el contrato fija ese importe total de ingresos (NIC 38.98C) o que la correlación entre los ingresos y el consumo de los beneficios está demostrada (NIC 38.98A). | C10: 25000
A11: DIF_AMORTIZACION | B11: La amortización recalculada difiere de la registrada en LIC-01: -2.000,00 (NIC 38.97; PYMES 18.21). | C11: -2000
A12: ACUMULADA_INCONSISTENTE | B12: La amortización acumulada recalculada no es la esperada por la vida transcurrida en SW-03: 1.000,00; revise la vida útil o errores de años anteriores (NIC 8.42; PYMES 10.21). | C12: 1000
A13: RESIDUAL_NO_NULO | B13: Valor residual distinto de cero en PAT-01 (8.000,00): se supone nulo salvo compromiso de compra o mercado activo (NIC 38.100; PYMES 18.23). | C13: 8000
A14: DETERIORO_NO_RECONOCIDO | B14: Deterioro no reconocido en MAR-01: el importe recuperable es menor que el importe en libros; pérdida 10.000,00 (NIC 36.59; PYMES 27.5). | C14: 10000
A15: REVERSION_GOODWILL | B15: Reversión de deterioro de goodwill en GW-01 por 15.000,00: está prohibida (NIC 36.124; PYMES 27.28). | C15: 15000
A16: REVERSION_NO_RECONOCIDA | B16: Con indicio de reversión y recuperable mayor que el importe en libros en PAT-01: reversión pendiente 10.000,00, limitada al importe en libros sin deterioro (NIC 36.114, 36.117; PYMES 27.30). | C16: 10000
... A18: AJUSTE | B18: Los intangibles netos auditados (549.050,00) difieren del neto según el mayor (591.050,00). | C18: -42000

Sheet 13_Conclusion
A1: Conclusión | H1: ⟵ Inicio | I1: ◀ Anterior | J1: Siguiente ▶
A2: Activos intangibles y goodwill · Cliente de muestra S.A. · corte 2025-12-31
A4: Concepto | B4: Detalle
A5: Conciliación con el mayor | B5: Población None · mayor None · diferencia None
A6: Evaluación de excepciones
A7: Análisis
A8: Conclusión

Sheet 14_Control_Revision
A1: Control de revisión | H1: ⟵ Inicio | I1: ◀ Anterior
A2: Activos intangibles y goodwill · Cliente de muestra S.A. · corte 2025-12-31
A4: Fecha | B4: Acción | C4: Estado anterior | D4: Estado nuevo | E4: Actor | F4: Comentario
