Workbook

Sheet 00_Inicio
B2: AuditConsulting Auditores Cía. Ltda. · AUDIT-IA
B4: Patrimonio
B6: Cliente | C6: Cliente de muestra S.A. | D6: RUC | E6: 1790000000001
B7: Marco contable | C7: NIIF completas | D7: Fecha de corte | E7: 2025-12-31
B8: Preparó | C8: Ejercicio modelo | D8: Revisó | E8: Pendiente
B10: INDICADORES CLAVE
B11: Ajuste neto propuesto al patrimonio | C11: Problemas encontrados
B12: -25000 | C12: 13
B15: IR A LA CÉDULA
B16: Carátula | C16: Programa | D16: Base técnica | E16: Resumen
B17: Parámetros | C17: Movimiento patrimonial | D17: Actas y transacciones | E17: Reserva legal
B18: Dividendos | C18: Capital y aumentos | D18: Clasificación deuda / patrimonio | E18: Recompra de acciones propias
B19: Patrimonio auditado y ajustes | C19: Asientos propuestos | D19: Problemas encontrados | E19: Conclusión
B20: Control de revisión
B22: PANORAMA | N22: Datos de los gráficos (fórmulas a las cédulas)
N23: Cifras del resumen | O23: Importe (USD)
N24: ='01_Resumen'!A5 | O24: ='01_Resumen'!B5
N25: ='01_Resumen'!A6 | O25: ='01_Resumen'!B6
N26: ='01_Resumen'!A7 | O26: ='01_Resumen'!B7
N27: ='01_Resumen'!A8 | O27: ='01_Resumen'!B8
N28: ='01_Resumen'!A9 | O28: ='01_Resumen'!B9
N29: ='01_Resumen'!A10 | O29: ='01_Resumen'!B10
N30: ='01_Resumen'!A11 | O30: ='01_Resumen'!B11
N31: ='01_Resumen'!A12 | O31: ='01_Resumen'!B12
N32: ='01_Resumen'!A13 | O32: ='01_Resumen'!B13
N33: ='01_Resumen'!A14 | O33: ='01_Resumen'!B14
N34: ='01_Resumen'!A15 | O34: ='01_Resumen'!B15
N35: ='01_Resumen'!A16 | O35: ='01_Resumen'!B16
... N46: ='01_Resumen'!A27 | O46: ='01_Resumen'!B27
N48: Hallazgos de mayor impacto | O48: Importe (USD)
N49: Dividendo posterior como pasivo | O49: =SUMIFS('12_Problemas'!$C$5:$C$17,'12_Problemas'!$A$5:$A$17,"DIVIDENDO_POSTERIOR_COMO_PASIVO",'12_Problemas'!$C$5:$C$17,">0")-SUMIFS('12_Problemas'!$C$5:$C$17,'12_Problemas'!$A$5:$A$17,"DIVIDENDO_POSTERIOR_COMO_PASIVO",'12_Problemas'!$C$5:$C$17,"<0")
N50: Dividendo posterior revelar | O50: =SUMIFS('12_Problemas'!$C$5:$C$17,'12_Problemas'!$A$5:$A$17,"DIVIDENDO_POSTERIOR_REVELAR",'12_Problemas'!$C$5:$C$17,">0")-SUMIFS('12_Problemas'!$C$5:$C$17,'12_Problemas'!$A$5:$A$17,"DIVIDENDO_POSTERIOR_REVELAR",'12_Problemas'!$C$5:$C$17,"<0")
N51: Instrumento mal clasificado | O51: =SUMIFS('12_Problemas'!$C$5:$C$17,'12_Problemas'!$A$5:$A$17,"INSTRUMENTO_MAL_CLASIFICADO",'12_Problemas'!$C$5:$C$17,">0")-SUMIFS('12_Problemas'!$C$5:$C$17,'12_Problemas'!$A$5:$A$17,"INSTRUMENTO_MAL_CLASIFICADO",'12_Problemas'!$C$5:$C$17,"<0")
N52: Capital no coincide escritura | O52: =SUMIFS('12_Problemas'!$C$5:$C$17,'12_Problemas'!$A$5:$A$17,"CAPITAL_NO_COINCIDE_ESCRITURA",'12_Problemas'!$C$5:$C$17,">0")-SUMIFS('12_Problemas'!$C$5:$C$17,'12_Problemas'!$A$5:$A$17,"CAPITAL_NO_COINCIDE_ESCRITURA",'12_Problemas'!$C$5:$C$17,"<0")
N53: Aumento no inscrito | O53: =SUMIFS('12_Problemas'!$C$5:$C$17,'12_Problemas'!$A$5:$A$17,"AUMENTO_NO_INSCRITO",'12_Problemas'!$C$5:$C$17,">0")-SUMIFS('12_Problemas'!$C$5:$C$17,'12_Problemas'!$A$5:$A$17,"AUMENTO_NO_INSCRITO",'12_Problemas'!$C$5:$C$17,"<0")
N54: Sin acta | O54: =SUMIFS('12_Problemas'!$C$5:$C$17,'12_Problemas'!$A$5:$A$17,"SIN_ACTA",'12_Problemas'!$C$5:$C$17,">0")-SUMIFS('12_Problemas'!$C$5:$C$17,'12_Problemas'!$A$5:$A$17,"SIN_ACTA",'12_Problemas'!$C$5:$C$17,"<0")
N55: Aporte es pasivo | O55: =SUMIFS('12_Problemas'!$C$5:$C$17,'12_Problemas'!$A$5:$A$17,"APORTE_ES_PASIVO",'12_Problemas'!$C$5:$C$17,">0")-SUMIFS('12_Problemas'!$C$5:$C$17,'12_Problemas'!$A$5:$A$17,"APORTE_ES_PASIVO",'12_Problemas'!$C$5:$C$17,"<0")
N56: Otros (6 tipos) | O56: =SUMIF('12_Problemas'!$C$5:$C$17,">0")-SUMIF('12_Problemas'!$C$5:$C$17,"<0")-((SUMIFS('12_Problemas'!$C$5:$C$17,'12_Problemas'!$A$5:$A$17,"DIVIDENDO_POSTERIOR_COMO_PASIVO",'12_Problemas'!$C$5:$C$17,">0")-SUMIFS('12_Problemas'!$C$5:$C$17,'12_Problemas'!$A$5:$A$17,"DIVIDENDO_POSTERIOR_COMO_PASIVO",'12_Problemas'!$C$5:$C$17,"<0"))+(SUMIFS('12_Problemas'!$C$5:$C$17,'12_Problemas'!$A$5:$A$17,"DIVIDENDO_POSTERIOR_REVELAR",'12_Problemas'!$C$5:$C$17,">0")-SUMIFS('12_Problemas'!$C$5:$C$17,'12_Problemas'!$A$5:$A$17,"DIVIDENDO_POSTERIOR_REVELAR",'12_Problemas'!$C$5:$C$17,"<0"))+(SUMIFS('12_Problemas'!$C$5:$C$17,'12_Problemas'!$A$5:$A$17,"INSTRUMENTO_MAL_CLASIFICADO",'12_Problemas'!$C$5:$C$17,">0")-SUMIFS('12_Problemas'!$C$5:$C$17,'12_Problemas'!$A$5:$A$17,"INSTRUMENTO_MAL_CLASIFICADO",'12_Problemas'!$C$5:$C$17,"<0"))+(SUMIFS('12_Problemas'!$C$5:$C$17,'12_Problemas'!$A$5:$A$17,"CAPITAL_NO_COINCIDE_ESCRITURA",'12_Problemas'!$C$5:$C$17,">0")-SUMIFS('12_Problemas'!$C$5:$C$17,'12_Problemas'!$A$5:$A$17,"CAPITAL_NO_COINCIDE_ESCRITURA",'12_Problemas'!$C$5:$C$17,"<0"))+(SUMIFS('12_Problemas'!$C$5:$C$17,'12_Problemas'!$A$5:$A$17,"AUMENTO_NO_INSCRITO",'12_Problemas'!$C$5:$C$17,">0")-SUMIFS('12_Problemas'!$C$5:$C$17,'12_Problemas'!$A$5:$A$17,"AUMENTO_NO_INSCRITO",'12_Problemas'!$C$5:$C$17,"<0"))+(SUMIFS('12_Problemas'!$C$5:$C$17,'12_Problemas'!$A$5:$A$17,"SIN_ACTA",'12_Problemas'!$C$5:$C$17,">0")-SUMIFS('12_Problemas'!$C$5:$C$17,'12_Problemas'!$A$5:$A$17,"SIN_ACTA",'12_Problemas'!$C$5:$C$17,"<0"))+(SUMIFS('12_Problemas'!$C$5:$C$17,'12_Problemas'!$A$5:$A$17,"APORTE_ES_PASIVO",'12_Problemas'!$C$5:$C$17,">0")-SUMIFS('12_Problemas'!$C$5:$C$17,'12_Problemas'!$A$5:$A$17,"APORTE_ES_PASIVO",'12_Problemas'!$C$5:$C$17,"<0")))

Sheet 00_Caratula
A1: Carátula | H1: ⟵ Inicio | J1: Siguiente ▶
A2: Patrimonio · Cliente de muestra S.A. · corte 2025-12-31
A4: Concepto | B4: Detalle
A5: Firma | B5: AuditConsulting Auditores Cía. Ltda.
A6: Cliente | B6: Cliente de muestra S.A.
A7: RUC | B7: 1790000000001
A8: Ejercicio | B8: 2025
A9: Fecha de corte | B9: 2025-12-31
A10: Marco contable | B10: NIIF completas
A11: Herramienta | B11: Patrimonio
A12: Rubro | B12: Patrimonio
A13: Motor | B13: patrimonio 1.0
A14: Versión del papel | B14: v1
A15: Estado | B15: MUESTRA
... A17: Revisó | B17: Pendiente
A18: Aprobó
A19: Fecha de aprobación
A20: Huella de la ejecución (SHA-256)

Sheet 00_Programa
A1: Programa | H1: ⟵ Inicio | I1: ◀ Anterior | J1: Siguiente ▶
A2: Patrimonio · Cliente de muestra S.A. · corte 2025-12-31
A4: Código | B4: Objetivo | C4: Afirmación | D4: Procedimiento | E4: Evidencia | F4: Criterio | G4: Referencia
A5: PAT-01 | B5: Movimiento patrimonial | C5: Exactitud / Integridad | D5: Recalcular inicial + aumentos − disminuciones por cuenta y conciliar con el cliente y el mayor | E5: Mayor, estado de cambios en el patrimonio | F5: Diferencia cero o explicada | G5: NIC 1 106–110 · PYMES Sección 6 · NIA 500
A6: PAT-02 | B6: Capital y aportes | C6: Existencia / Clasificación | D6: Cotejar el capital con la escritura y Supercias, la inscripción de los aumentos y las condiciones de devolución de los aportes | E6: Escrituras, razón de inscripción, portal Supercias, actas | F6: Capital igual a lo inscrito; aportes sin obligación de devolución | G6: NIC 32 16 · PYMES 22.3–22.10 · Ley de Compañías
A7: PAT-03 | B7: Reserva legal y otras reservas | C7: Exactitud / Cumplimiento | D7: Confirmar la forma societaria en la escritura de constitución y en el certificado de existencia de la Superintendencia de Compañías y recalcular la reserva legal requerida con el % y el nivel mínimo de esa forma; en la sociedad por acciones simplificada no hay reserva legal obligatoria: revisar si el estatuto o la asamblea acordaron una reserva estatutaria o facultativa | E7: Escritura de constitución, certificado de existencia, estatuto social, actas de junta o asamblea, mayor | F7: Apropiado igual a lo requerido por la forma societaria; en la SAS, lo que acuerde el estatuto o la asamblea | G7: Ley de Compañías arts. 297 (anónima) y 109 (limitada); artículo innumerado «Constitución opcional de reservas» (SAS)
A8: PAT-08 | B8: Resultados acumulados por adopción por primera vez de las NIIF | C8: Presentación / Cumplimiento | D8: Identificar en el mayor la subcuenta de resultados acumulados por adopción por primera vez de las NIIF, cotejarla con la conciliación del patrimonio de la transición y analizar el origen de cada ajuste para concluir si es repartible según la regulación societaria aplicable | E8: Estado de situación financiera de apertura y su conciliación, mayor de la subcuenta, actas de junta o asamblea | F8: Presentados por separado y excluidos de la utilidad disponible mientras no se sustente su disponibilidad | G8: NIIF 1 11 y 24 a) · PYMES 35.8 y 35.13 b) · Ley de Compañías arts. 208 y 297
A9: PAT-04 | B9: Dividendos | C9: Ocurrencia / Corte | D9: Comparar dividendos declarados con las utilidades disponibles (incluidas las reservas de libre disposición) y con el mínimo legal del art. 297; revisar actas posteriores al cierre | E9: Actas, pagos, estados de cuenta | F9: Mínimo legal ≤ declarados ≤ disponibles; posteriores revelados, no registrados | G9: NIC 32 35 · NIC 10 12–13 · NIC 1 137 · CINIIF 17 · PYMES 22.17, 32.8 · Ley de Compañías arts. 297 y 298
A10: PAT-05 | B10: Resultados acumulados | C10: Exactitud | D10: Verificar el traspaso del resultado del ejercicio anterior, la apropiación de reservas y los dividendos contra resultados acumulados | E10: Mayor y actas | F10: Movimiento conciliado | G10: NIC 1 106 d) · PYMES 6.3
A11: PAT-06 | B11: Recompra de acciones | C11: Presentación | D11: Revisar que las recompras se deduzcan del patrimonio y que no afecten resultados | E11: Actas, contratos de compra, asientos | F11: Sin pérdida ni ganancia en resultados | G11: NIC 32 33 · PYMES 22.16
A12: PAT-07 | B12: Clasificación deuda / patrimonio | C12: Clasificación | D12: Analizar los términos de acciones preferentes, aportes e instrumentos con opción de venta | E12: Estatutos, contratos, actas | F12: Pasivo si hay obligación contractual de entregar efectivo | G12: NIC 32 11, 15–16D, 18 · PYMES 22.3–22.6

Sheet 00_Fuentes
A1: Base técnica | H1: ⟵ Inicio | I1: ◀ Anterior | J1: Siguiente ▶
A2: Patrimonio · Cliente de muestra S.A. · corte 2025-12-31
A4: Categoría | B4: Documento | C4: Párrafos | D4: URL | E4: Verificada
A5: NIA · NIA 500 | B5: Exactitud e integridad del movimiento patrimonial contra el mayor. | C5: párr. 9
A6: NIA · NIA 330 | B6: Conciliar el estado de cambios en el patrimonio con los registros. | C6: párr. 20
A7: NIA · NIA 250 (Revisada) | B7: Cumplimiento de la Ley de Compañías (reserva legal, dividendos, inscripción de aumentos). | C7: párr. 14
A8: NIA · NIA 560 | B8: Hechos posteriores: dividendos declarados después del cierre. | C8: párr. 6–9
A9: NIA · NIA 580 | B9: Manifestaciones escritas sobre actas de junta entregadas en su totalidad. | C9: párr. 11 y 13

Sheet 01_Resumen
A1: Resumen | H1: ⟵ Inicio | I1: ◀ Anterior | J1: Siguiente ▶
A2: Patrimonio · Cliente de muestra S.A. · corte 2025-12-31
A4: Concepto | B4: Importe
A5: Patrimonio según cliente | B5: ='10_Ajuste'!B5
A6: Patrimonio auditado | B6: ='10_Ajuste'!B9
A7: Ajuste neto propuesto al patrimonio | B7: ='10_Ajuste'!B10
A8: Aportes con obligación de devolución (a pasivo) | B8: ='10_Ajuste'!B6
A9: Instrumentos con obligación contractual (a pasivo) | B9: ='10_Ajuste'!B7
A10: Dividendos posteriores registrados como pasivo (revertir) | B10: ='10_Ajuste'!B8
A11: Diferencias del movimiento recalculado (absolutas) | B11: ='10_Ajuste'!B11
A12: Patrimonio según el mayor | B12: ='10_Ajuste'!B12
A13: Diferencia cliente − mayor | B13: ='10_Ajuste'!B13
A14: Reserva legal requerida | B14: ='10_Ajuste'!B14
A15: Reserva legal apropiada | B15: ='10_Ajuste'!B15
A16: Reserva legal por apropiar (− exceso) | B16: ='10_Ajuste'!B16
A17: Resultados acumulados por adopción por primera vez de NIIF (no distribuibles) | B17: ='10_Ajuste'!B17
A18: Dividendos declarados en el período | B18: ='10_Ajuste'!B19
A19: Utilidades disponibles para dividendos | B19: ='10_Ajuste'!B20
A20: Dividendos en exceso de utilidades disponibles | B20: ='10_Ajuste'!B21
A21: Aumentos de capital no inscritos al corte | B21: ='10_Ajuste'!B24
A22: Capital según cliente | B22: ='10_Ajuste'!B25
A23: Dividendo mínimo legal (Ley de Compañías art. 297) | B23: ='10_Ajuste'!B22
A24: Dividendos por debajo del mínimo legal | B24: ='10_Ajuste'!B23
A25: Capital según escritura / Supercias | B25: ='10_Ajuste'!B26
A26: Diferencia capital cliente − escritura | B26: ='10_Ajuste'!B27
A27: Resultado reconocido por recompras (a reclasificar al patrimonio) | B27: ='10_Ajuste'!B28
A29: ⓘ Cómo se calcula esta hoja
A30: Columna | B30: Fórmula (Excel) | C30: Cómo se calcula (sencillo) | D30: Ejemplo con números reales | E30: De dónde viene | F30: Norma
A31: Importe | B31: '='10_Ajuste'!B5 | C31: Trae cada importe, concepto por concepto, de la hoja 10 (Patrimonio auditado y ajustes), donde se calcula el patrimonio auditado y se reúnen las pruebas de reserva, dividendos y capital. | D31: Fila 1: 935.000,00 → 935.000,00 | E31: hoja «Patrimonio auditado y ajustes» | F31: —

Sheet 02_Parametros
A1: Parámetros | H1: ⟵ Inicio | I1: ◀ Anterior | J1: Siguiente ▶
A2: Patrimonio · Cliente de muestra S.A. · corte 2025-12-31
A4: Parámetro | B4: Valor | C4: Sustento
A5: Corte del ejercicio | B5: 46022 | C5: Ficha del encargo
A6: Marco contable | B6: NIIF completas | C6: Mismo cálculo en ambos marcos; cambian las citas
A7: Tipo de compañía | B7: Anónima | C7: Escritura de constitución / Superintendencia de Compañías · Reserva legal obligatoria: 10 % de las utilidades líquidas hasta por lo menos el 50 % del capital (Ley de Compañías art. 297)
A8: Utilidad líquida base de la reserva legal | B8: =SUMIF('03_Movimiento'!$C$5:$C$13,"Resultado del ejercicio",'03_Movimiento'!$D$5:$D$13) | C8: Saldo inicial del resultado del ejercicio (utilidad que la junta apropia en el período)
A9: % de la utilidad para reserva legal | B9: 10 | C9: por defecto según el tipo de compañía; 10 % de las utilidades líquidas hasta por lo menos el 50 % del capital (Ley de Compañías art. 297, anónimas); 5 % de las utilidades líquidas y realizadas hasta por lo menos el 20 % (art. 109, limitadas); en la SAS la reserva legal no es obligatoria (artículo innumerado «Constitución opcional de reservas»); vigente al corte
A10: Nivel mínimo de la reserva legal a partir del cual cesa la apropiación obligatoria (% del capital) | B10: 50 | C10: por defecto según el tipo de compañía; 10 % de las utilidades líquidas hasta por lo menos el 50 % del capital (Ley de Compañías art. 297, anónimas); 5 % de las utilidades líquidas y realizadas hasta por lo menos el 20 % (art. 109, limitadas); en la SAS la reserva legal no es obligatoria (artículo innumerado «Constitución opcional de reservas»); vigente al corte
A11: Capital suscrito según escritura / Supercias | B11: 460000 | C11: Escritura inscrita / portal Supercias
A12: Utilidades disponibles según el auditor | B12: 80000 | C12: Vacío: se calculan en 06_Dividendos (Ley de Compañías arts. 208 y 298: solo beneficios realmente obtenidos y percibidos o reservas de libre disposición)
A13: Reservas expresas efectivas de libre disposición | B13: 25000 | C13: Ley de Compañías art. 298: también sirven para pagar dividendos
A14: % mínimo de dividendos sobre los beneficios líquidos | B14: 50 | C14: Ley de Compañías art. 297: al menos el 50 %, salvo resolución unánime; 30 % en emisores inscritos en el Catastro Público del Mercado de Valores; en las demás formas societarias, el % que fije la norma o el estatuto; vigente al corte
A15: Resolución unánime de la junta sobre las utilidades | B15: No | C15: Ley de Compañías art. 297: con resolución unánime no aplica el mínimo
A17: ⓘ Cómo se calcula esta hoja
A18: Columna | B18: Fórmula (Excel) | C18: Cómo se calcula (sencillo) | D18: Ejemplo con números reales | E18: De dónde viene | F18: Norma
A19: Valor | B19: '=SUMIF('03_Movimiento'!$C$5:$C$13,"Resultado del ejercicio",'03_Movimiento'!$D$5:$D$13) | C19: Los valores son datos del encargo o del auditor; solo la utilidad líquida base, cuando el auditor no la indica, se toma del saldo inicial del resultado del ejercicio en la hoja 03 (Movimiento patrimonial). | D19: Fila 4: SUMIF([«Clase» de «Movimiento patrimonial», 9 filas]; "Resultado del ejercicio"; [«Saldo inicial» de «Movimiento patrimonial», 9 filas]) → 128.000,00 | E19: hoja «Movimiento patrimonial» | F19: —

Sheet 03_Movimiento
A1: Movimiento patrimonial | H1: ⟵ Inicio | I1: ◀ Anterior | J1: Siguiente ▶
A2: Patrimonio · Cliente de muestra S.A. · corte 2025-12-31
A4: Código | B4: Cuenta | C4: Clase | D4: Saldo inicial | E4: Aumentos | F4: Disminuciones | G4: Final recalculado | H4: Final según cliente | I4: Diferencia | J4: Final según mayor | K4: Cliente − mayor | L4: Del saldo inicial: adopción por primera vez de NIIF
A5: 301 | B5: Capital suscrito y pagado | C5: Capital | D5: 400000 | E5: 100000 | F5: 0 | G5: =D5+E5-F5 | H5: 500000 | I5: =H5-G5 | J5: 500000 | K5: =IF(J5<>"",H5-J5,"")
A6: 302 | B6: Aportes para futuras capitalizaciones | C6: Aportes futuras capitalizaciones | D6: 100000 | E6: 30000 | F6: 100000 | G6: =D6+E6-F6 | H6: 30000 | I6: =H6-G6 | J6: 30000 | K6: =IF(J6<>"",H6-J6,"")
A7: 304 | B7: Reserva legal | C7: Reserva legal | D7: 60000 | E7: 8000 | F7: 0 | G7: =D7+E7-F7 | H7: 68000 | I7: =H7-G7 | J7: 68000 | K7: =IF(J7<>"",H7-J7,"")
A8: 305 | B8: Reserva facultativa | C8: Otras reservas | D8: 25000 | E8: 0 | F8: 0 | G8: =D8+E8-F8 | H8: 25000 | I8: =H8-G8 | J8: 25000 | K8: =IF(J8<>"",H8-J8,"")
A9: 306 | B9: Otros resultados integrales | C9: Otros resultados integrales | D9: 12000 | E9: 3500 | F9: 0 | G9: =D9+E9-F9 | H9: 15000 | I9: =H9-G9 | J9: 15000 | K9: =IF(J9<>"",H9-J9,"")
A10: 307 | B10: Resultados acumulados | C10: Resultados acumulados | D10: 150000 | E10: 120000 | F10: 140000 | G10: =D10+E10-F10 | H10: 130000 | I10: =H10-G10 | J10: 130000 | K10: =IF(J10<>"",H10-J10,"") | L10: 18000
A11: 308 | B11: Resultado del ejercicio | C11: Resultado del ejercicio | D11: 128000 | E11: 142000 | F11: 128000 | G11: =D11+E11-F11 | H11: 142000 | I11: =H11-G11 | J11: 143200 | K11: =IF(J11<>"",H11-J11,"")
A12: 309 | B12: Acciones propias en cartera | C12: Acciones propias | D12: 0 | E12: 0 | F12: 20000 | G12: =D12+E12-F12 | H12: -20000 | I12: =H12-G12 | J12: -20000 | K12: =IF(J12<>"",H12-J12,"")
A13: 310 | B13: Acciones preferentes rescatables | C13: Otra | D13: 0 | E13: 45000 | F13: 0 | G13: =D13+E13-F13 | H13: 45000 | I13: =H13-G13 | J13: 45000 | K13: =IF(J13<>"",H13-J13,"")
A14: TOTAL | D14: =SUM(D5:D13) | E14: =SUM(E5:E13) | F14: =SUM(F5:F13) | G14: =SUM(G5:G13) | H14: =SUM(H5:H13) | I14: =SUM(I5:I13) | J14: =IF(COUNT(J5:J13)=0,"",SUM(J5:J13)) | K14: =IF(COUNT(J5:J13)=0,"",SUM(K5:K13)) | L14: =IF(COUNT(L5:L13)=0,"",SUM(L5:L13))
A16: ⓘ Cómo se calcula esta hoja
A17: Columna | B17: Fórmula (Excel) | C17: Cómo se calcula (sencillo) | D17: Ejemplo con números reales | E17: De dónde viene | F17: Norma
A18: Final recalculado | B18: '=D5+E5-F5 | C18: Parte del saldo inicial de la cuenta, suma los aumentos y resta las disminuciones del período. | D18: Fila 1: 400.000,00+100.000,00-0,00 → 500.000,00 | E18: «Saldo inicial» (esta hoja), «Aumentos» (esta hoja), «Disminuciones» (esta hoja) | F18: —
A19: Diferencia | B19: '=H5-G5 | C19: Resta al saldo final que informa el cliente el final recalculado: si no es cero, el movimiento de la cuenta no cuadra. | D19: Fila 1: 500.000,00-500.000,00 → 0,00 | E19: «Final según cliente» (esta hoja), «Final recalculado» (esta hoja) | F19: —
A20: Cliente − mayor | B20: '=IF(J5<>"",H5-J5,"") | C20: Resta al saldo final según el cliente el saldo final según el mayor; si no se informó el saldo del mayor, queda en blanco. | D20: Fila 1: IF(500.000,00<>""; 500.000,00-500.000,00; "") → 0,00 | E20: «Final según mayor» (esta hoja), «Final según cliente» (esta hoja) | F20: —

Sheet 04_Transacciones
A1: Actas y transacciones | H1: ⟵ Inicio | I1: ◀ Anterior | J1: Siguiente ▶
A2: Patrimonio · Cliente de muestra S.A. · corte 2025-12-31
A4: Referencia | B4: Fecha | C4: Tipo | D4: Importe | E4: Acta | F4: Fecha del acta | G4: Inscripción | H4: Devolución | I4: Obligación contractual | J4: Cuenta afectada | K4: Pasivo al corte | L4: Resultado reconocido | M4: Fecha efectiva (acta o registro) | N4: Posterior al corte | O4: Dividendo del período | P4: Dividendo posterior como pasivo | Q4: Aumento no inscrito | R4: Aporte a pasivo | S4: Instrumento a pasivo | T4: Resultado de recompra | U4: Sin acta
A5: JGA-2025-01 | B5: 45744 | C5: Aumento de capital | D5: 60000 | E5: Sí | F5: 45736 | G5: 45792 | J5: Capital | M5: 45736 | N5: =IF(IF(F5<>"",F5,B5)>'02_Parametros'!$B$5,"Sí","No") | O5: =IF(AND(C5="Dividendo declarado",N5="No"),D5,0) | P5: =IF(AND(C5="Dividendo declarado",N5="Sí",K5="Sí"),D5,0) | Q5: =IF(AND(C5="Aumento de capital",B5<='02_Parametros'!$B$5,OR(G5="",G5>'02_Parametros'!$B$5)),D5,0) | R5: =IF(AND(C5="Aporte",H5="Sí"),D5,0) | S5: =IF(AND(I5="Sí",NOT(AND(C5="Aporte",H5="Sí"))),D5,0) | T5: =IF(AND(C5="Recompra",L5<>""),L5,0) | U5: =IF(AND(E5<>"Sí",OR(C5="Aumento de capital",C5="Aporte",C5="Dividendo declarado",C5="Apropiación de reserva",C5="Recompra")),"Sí","No")
A6: JGA-2025-02 | B6: 45762 | C6: Apropiación de reserva | D6: 8000 | E6: Sí | F6: 45736 | J6: Reserva legal | M6: 45736 | N6: =IF(IF(F6<>"",F6,B6)>'02_Parametros'!$B$5,"Sí","No") | O6: =IF(AND(C6="Dividendo declarado",N6="No"),D6,0) | P6: =IF(AND(C6="Dividendo declarado",N6="Sí",K6="Sí"),D6,0) | Q6: =IF(AND(C6="Aumento de capital",B6<='02_Parametros'!$B$5,OR(G6="",G6>'02_Parametros'!$B$5)),D6,0) | R6: =IF(AND(C6="Aporte",H6="Sí"),D6,0) | S6: =IF(AND(I6="Sí",NOT(AND(C6="Aporte",H6="Sí"))),D6,0) | T6: =IF(AND(C6="Recompra",L6<>""),L6,0) | U6: =IF(AND(E6<>"Sí",OR(C6="Aumento de capital",C6="Aporte",C6="Dividendo declarado",C6="Apropiación de reserva",C6="Recompra")),"Sí","No")
A7: JGA-2025-03 | B7: 45762 | C7: Dividendo declarado | D7: 90000 | E7: Sí | F7: 45736 | J7: Resultados acumulados | K7: No | M7: 45736 | N7: =IF(IF(F7<>"",F7,B7)>'02_Parametros'!$B$5,"Sí","No") | O7: =IF(AND(C7="Dividendo declarado",N7="No"),D7,0) | P7: =IF(AND(C7="Dividendo declarado",N7="Sí",K7="Sí"),D7,0) | Q7: =IF(AND(C7="Aumento de capital",B7<='02_Parametros'!$B$5,OR(G7="",G7>'02_Parametros'!$B$5)),D7,0) | R7: =IF(AND(C7="Aporte",H7="Sí"),D7,0) | S7: =IF(AND(I7="Sí",NOT(AND(C7="Aporte",H7="Sí"))),D7,0) | T7: =IF(AND(C7="Recompra",L7<>""),L7,0) | U7: =IF(AND(E7<>"Sí",OR(C7="Aumento de capital",C7="Aporte",C7="Dividendo declarado",C7="Apropiación de reserva",C7="Recompra")),"Sí","No")
A8: EG-2025-118 | B8: 45807 | C8: Dividendo pagado | D8: 90000 | E8: Sí | F8: 45736 | J8: Resultados acumulados | M8: 45736 | N8: =IF(IF(F8<>"",F8,B8)>'02_Parametros'!$B$5,"Sí","No") | O8: =IF(AND(C8="Dividendo declarado",N8="No"),D8,0) | P8: =IF(AND(C8="Dividendo declarado",N8="Sí",K8="Sí"),D8,0) | Q8: =IF(AND(C8="Aumento de capital",B8<='02_Parametros'!$B$5,OR(G8="",G8>'02_Parametros'!$B$5)),D8,0) | R8: =IF(AND(C8="Aporte",H8="Sí"),D8,0) | S8: =IF(AND(I8="Sí",NOT(AND(C8="Aporte",H8="Sí"))),D8,0) | T8: =IF(AND(C8="Recompra",L8<>""),L8,0) | U8: =IF(AND(E8<>"Sí",OR(C8="Aumento de capital",C8="Aporte",C8="Dividendo declarado",C8="Apropiación de reserva",C8="Recompra")),"Sí","No")
A9: AP-2025-01 | B9: 45818 | C9: Aporte | D9: 30000 | E9: Sí | F9: 45813 | H9: Sí | J9: Aportes futuras capitalizaciones | M9: 45813 | N9: =IF(IF(F9<>"",F9,B9)>'02_Parametros'!$B$5,"Sí","No") | O9: =IF(AND(C9="Dividendo declarado",N9="No"),D9,0) | P9: =IF(AND(C9="Dividendo declarado",N9="Sí",K9="Sí"),D9,0) | Q9: =IF(AND(C9="Aumento de capital",B9<='02_Parametros'!$B$5,OR(G9="",G9>'02_Parametros'!$B$5)),D9,0) | R9: =IF(AND(C9="Aporte",H9="Sí"),D9,0) | S9: =IF(AND(I9="Sí",NOT(AND(C9="Aporte",H9="Sí"))),D9,0) | T9: =IF(AND(C9="Recompra",L9<>""),L9,0) | U9: =IF(AND(E9<>"Sí",OR(C9="Aumento de capital",C9="Aporte",C9="Dividendo declarado",C9="Apropiación de reserva",C9="Recompra")),"Sí","No")
A10: JGA-2025-05 | B10: 45881 | C10: Recompra | D10: 20000 | E10: Sí | F10: 45870 | J10: Acciones propias | L10: -1500 | M10: 45870 | N10: =IF(IF(F10<>"",F10,B10)>'02_Parametros'!$B$5,"Sí","No") | O10: =IF(AND(C10="Dividendo declarado",N10="No"),D10,0) | P10: =IF(AND(C10="Dividendo declarado",N10="Sí",K10="Sí"),D10,0) | Q10: =IF(AND(C10="Aumento de capital",B10<='02_Parametros'!$B$5,OR(G10="",G10>'02_Parametros'!$B$5)),D10,0) | R10: =IF(AND(C10="Aporte",H10="Sí"),D10,0) | S10: =IF(AND(I10="Sí",NOT(AND(C10="Aporte",H10="Sí"))),D10,0) | T10: =IF(AND(C10="Recompra",L10<>""),L10,0) | U10: =IF(AND(E10<>"Sí",OR(C10="Aumento de capital",C10="Aporte",C10="Dividendo declarado",C10="Apropiación de reserva",C10="Recompra")),"Sí","No")
A11: JGA-2025-06 | B11: 45930 | C11: Otro | D11: 45000 | E11: Sí | F11: 45915 | I11: Sí | J11: Otra | M11: 45915 | N11: =IF(IF(F11<>"",F11,B11)>'02_Parametros'!$B$5,"Sí","No") | O11: =IF(AND(C11="Dividendo declarado",N11="No"),D11,0) | P11: =IF(AND(C11="Dividendo declarado",N11="Sí",K11="Sí"),D11,0) | Q11: =IF(AND(C11="Aumento de capital",B11<='02_Parametros'!$B$5,OR(G11="",G11>'02_Parametros'!$B$5)),D11,0) | R11: =IF(AND(C11="Aporte",H11="Sí"),D11,0) | S11: =IF(AND(I11="Sí",NOT(AND(C11="Aporte",H11="Sí"))),D11,0) | T11: =IF(AND(C11="Recompra",L11<>""),L11,0) | U11: =IF(AND(E11<>"Sí",OR(C11="Aumento de capital",C11="Aporte",C11="Dividendo declarado",C11="Apropiación de reserva",C11="Recompra")),"Sí","No")
A12: JGA-2025-04 | B12: 45991 | C12: Aumento de capital | D12: 40000 | E12: No | J12: Capital | M12: 45991 | N12: =IF(IF(F12<>"",F12,B12)>'02_Parametros'!$B$5,"Sí","No") | O12: =IF(AND(C12="Dividendo declarado",N12="No"),D12,0) | P12: =IF(AND(C12="Dividendo declarado",N12="Sí",K12="Sí"),D12,0) | Q12: =IF(AND(C12="Aumento de capital",B12<='02_Parametros'!$B$5,OR(G12="",G12>'02_Parametros'!$B$5)),D12,0) | R12: =IF(AND(C12="Aporte",H12="Sí"),D12,0) | S12: =IF(AND(I12="Sí",NOT(AND(C12="Aporte",H12="Sí"))),D12,0) | T12: =IF(AND(C12="Recompra",L12<>""),L12,0) | U12: =IF(AND(E12<>"Sí",OR(C12="Aumento de capital",C12="Aporte",C12="Dividendo declarado",C12="Apropiación de reserva",C12="Recompra")),"Sí","No")
A13: AS-2025-ORI | B13: 46022 | C13: Otro | D13: 3500 | J13: Otros resultados integrales | M13: 46022 | N13: =IF(IF(F13<>"",F13,B13)>'02_Parametros'!$B$5,"Sí","No") | O13: =IF(AND(C13="Dividendo declarado",N13="No"),D13,0) | P13: =IF(AND(C13="Dividendo declarado",N13="Sí",K13="Sí"),D13,0) | Q13: =IF(AND(C13="Aumento de capital",B13<='02_Parametros'!$B$5,OR(G13="",G13>'02_Parametros'!$B$5)),D13,0) | R13: =IF(AND(C13="Aporte",H13="Sí"),D13,0) | S13: =IF(AND(I13="Sí",NOT(AND(C13="Aporte",H13="Sí"))),D13,0) | T13: =IF(AND(C13="Recompra",L13<>""),L13,0) | U13: =IF(AND(E13<>"Sí",OR(C13="Aumento de capital",C13="Aporte",C13="Dividendo declarado",C13="Apropiación de reserva",C13="Recompra")),"Sí","No")
A14: JGA-2026-01 | B14: 46022 | C14: Dividendo declarado | D14: 50000 | E14: Sí | F14: 46073 | J14: Resultados acumulados | K14: Sí | M14: 46073 | N14: =IF(IF(F14<>"",F14,B14)>'02_Parametros'!$B$5,"Sí","No") | O14: =IF(AND(C14="Dividendo declarado",N14="No"),D14,0) | P14: =IF(AND(C14="Dividendo declarado",N14="Sí",K14="Sí"),D14,0) | Q14: =IF(AND(C14="Aumento de capital",B14<='02_Parametros'!$B$5,OR(G14="",G14>'02_Parametros'!$B$5)),D14,0) | R14: =IF(AND(C14="Aporte",H14="Sí"),D14,0) | S14: =IF(AND(I14="Sí",NOT(AND(C14="Aporte",H14="Sí"))),D14,0) | T14: =IF(AND(C14="Recompra",L14<>""),L14,0) | U14: =IF(AND(E14<>"Sí",OR(C14="Aumento de capital",C14="Aporte",C14="Dividendo declarado",C14="Apropiación de reserva",C14="Recompra")),"Sí","No")
A15: TOTAL | D15: =SUM(D5:D14) | O15: =SUM(O5:O14) | P15: =SUM(P5:P14) | Q15: =SUM(Q5:Q14) | R15: =SUM(R5:R14) | S15: =SUM(S5:S14) | T15: =SUM(T5:T14)
A17: ⓘ Cómo se calcula esta hoja
A18: Columna | B18: Fórmula (Excel) | C18: Cómo se calcula (sencillo) | D18: Ejemplo con números reales | E18: De dónde viene | F18: Norma
A19: Posterior al corte | B19: '=IF(IF(F5<>"",F5,B5)>'02_Parametros'!$B$5,"Sí","No") | C19: Marca «Sí» si la fecha del acta (o, sin ella, la fecha de la transacción) es posterior al corte de la hoja 02 (Parámetros); si no, «No». | D19: Fila 1: IF(IF(«2025-03-20»<>""; «2025-03-20»; «2025-03-28»)>«2025-12-31»; "Sí"; "No") → No | E19: «Fecha del acta» (esta hoja), «Fecha» (esta hoja), hoja «Parámetros» | F19: —
A20: Dividendo del período | B20: '=IF(AND(C5="Dividendo declarado",N5="No"),D5,0) | C20: Si es un dividendo declarado y no es posterior al corte, toma su importe; si no, pone cero. | D20: Fila 1: IF(AND(«Aumento de capital»="Dividendo declarado"; «No»="No"); 60.000,00; 0) → 0,00 | E20: «Tipo» (esta hoja), «Posterior al corte» (esta hoja), «Importe» (esta hoja) | F20: —
A21: Dividendo posterior como pasivo | B21: '=IF(AND(C5="Dividendo declarado",N5="Sí",K5="Sí"),D5,0) | C21: Si es un dividendo declarado después del corte y el cliente igual lo registró como pasivo al corte, toma su importe (es un error); si no, cero. | D21: Fila 1: IF(AND(«Aumento de capital»="Dividendo declarado"; «No»="Sí"; (vacío)="Sí"); 60.000,00; 0) → 0,00 | E21: «Tipo» (esta hoja), «Posterior al corte» (esta hoja), «Pasivo al corte» (esta hoja), «Importe» (esta hoja) | F21: —
A22: Aumento no inscrito | B22: '=IF(AND(C5="Aumento de capital",B5<='02_Parametros'!$B$5,OR(G5="",G5>'02_Parametros'!$B$5)),D5,0) | C22: Si es un aumento de capital con fecha hasta el corte de la hoja 02 y no tiene inscripción, o se inscribió después del corte, toma su importe; si no, cero. | D22: Fila 1: IF(AND(«Aumento de capital»="Aumento de capital"; «2025-03-28»<=«2025-12-31»; OR(«2025-05-15»=""; «2025-05-15»>«2025-12-31»)); 60.000,00; 0) → 0,00 | E22: «Tipo» (esta hoja), «Fecha» (esta hoja), «Inscripción» (esta hoja), «Importe» (esta hoja), hoja «Parámetros» | F22: —
A23: Aporte a pasivo | B23: '=IF(AND(C5="Aporte",H5="Sí"),D5,0) | C23: Si es un aporte que tiene obligación de devolución, toma su importe para pasarlo a pasivo; si no, cero. | D23: Fila 1: IF(AND(«Aumento de capital»="Aporte"; (vacío)="Sí"); 60.000,00; 0) → 0,00 | E23: «Tipo» (esta hoja), «Devolución» (esta hoja), «Importe» (esta hoja) | F23: —
A24: Instrumento a pasivo | B24: '=IF(AND(I5="Sí",NOT(AND(C5="Aporte",H5="Sí"))),D5,0) | C24: Si la transacción tiene obligación contractual de entregar efectivo, toma su importe para pasarlo a pasivo, salvo los aportes con devolución, que ya se cuentan en la columna anterior. | D24: Fila 1: IF(AND((vacío)="Sí"; NOT(AND(«Aumento de capital»="Aporte"; (vacío)="Sí"))); 60.000,00; 0) → 0,00 | E24: «Obligación contractual» (esta hoja), «Tipo» (esta hoja), «Devolución» (esta hoja), «Importe» (esta hoja) | F24: —
A25: Resultado de recompra | B25: '=IF(AND(C5="Recompra",L5<>""),L5,0) | C25: Si es una recompra de acciones y el cliente reconoció un resultado, toma ese resultado; si no, pone cero. | D25: Fila 1: IF(AND(«Aumento de capital»="Recompra"; (vacío)<>""); (vacío); 0) → 0,00 | E25: «Tipo» (esta hoja), «Resultado reconocido» (esta hoja) | F25: —
A26: Sin acta | B26: '=IF(AND(E5<>"Sí",OR(C5="Aumento de capital",C5="Aporte",C5="Dividendo declarado",C5="Apropiación de reserva",C5="Recompra")),"Sí","No") | C26: Marca «Sí» si la transacción no tiene acta y es de un tipo que la exige: aumento de capital, aporte, dividendo declarado, apropiación de reserva o recompra. | D26: Fila 1: IF(AND(«Sí»<>"Sí"; OR(«Aumento de capital»="Aumento de capital"; «Aumento de capital»="Aporte"; «Aumento de capital»="Dividendo declarado"; «Aumento de capital»="Apropiación de reserva"; «Aumento de capital»="Recompra")); "Sí"; "No") → No | E26: «Acta» (esta hoja), «Tipo» (esta hoja) | F26: —

Sheet 05_Reserva_legal
A1: Reserva legal | H1: ⟵ Inicio | I1: ◀ Anterior | J1: Siguiente ▶
A2: Patrimonio · Cliente de muestra S.A. · corte 2025-12-31
A4: Concepto | B4: Importe | C4: Porcentaje | D4: Referencia
A5: Tipo de compañía aplicado | D5: Anónima (informado: «Anónima») · 02_Parametros
A6: Régimen de reserva legal enrutado | D6: Reserva legal obligatoria: 10 % de las utilidades líquidas hasta por lo menos el 50 % del capital (Ley de Compañías art. 297)
A7: Utilidad líquida base | B7: =IF('02_Parametros'!$B$8="","",'02_Parametros'!$B$8) | D7: 02_Parametros
A8: % de la utilidad para reserva legal | C8: =IF('02_Parametros'!$B$9="","",'02_Parametros'!$B$9/100) | D8: 02_Parametros · Reserva legal obligatoria: 10 % de las utilidades líquidas hasta por lo menos el 50 % del capital (Ley de Compañías art. 297)
A9: Reserva calculada sobre la utilidad | B9: =IF(OR(B7="",C8=""),"",MAX(B7,0)*C8) | D9: Utilidad positiva × %
A10: Capital según cliente | B10: =SUMIF('03_Movimiento'!$C$5:$C$13,"Capital",'03_Movimiento'!$H$5:$H$13) | D10: 03_Movimiento
A11: Nivel mínimo de la reserva (% del capital) | C11: =IF('02_Parametros'!$B$10="","",'02_Parametros'!$B$10/100) | D11: 02_Parametros · Ley de Compañías arts. 297 y 109 (la SAS no tiene nivel mínimo legal)
A12: Nivel mínimo de la reserva legal (cesa la apropiación obligatoria) | B12: =IF(C11="","",B10*C11) | D12: Capital × % del nivel mínimo
A13: Reserva legal inicial | B13: =SUMIF('03_Movimiento'!$C$5:$C$13,"Reserva legal",'03_Movimiento'!$D$5:$D$13) | D13: 03_Movimiento
A14: Margen hasta el nivel mínimo | B14: =IF(B12="","",MAX(B12-B13,0)) | D14: Nivel mínimo − reserva inicial
A15: Reserva legal requerida | B15: =IF(B9="","",IF(B14="",B9,MIN(B9,B14))) | D15: mín(calculada, margen); vacío: el régimen no exige reserva legal o no se enrutó
A16: Reserva legal apropiada en el período | B16: =SUMIF('03_Movimiento'!$C$5:$C$13,"Reserva legal",'03_Movimiento'!$E$5:$E$13) | D16: Aumentos de la cuenta (03_Movimiento)
A17: Por apropiar (+) / exceso (−) | B17: =IF(B15="","",B15-B16) | D17: Requerida − apropiada
A18: Reserva legal final según cliente | B18: =SUMIF('03_Movimiento'!$C$5:$C$13,"Reserva legal",'03_Movimiento'!$H$5:$H$13) | D18: 03_Movimiento
A19: Reserva final sobre el nivel mínimo | B19: =IF(B12="","",MAX(B18-B12,0)) | D19: Informativo
A21: ⓘ Cómo se calcula esta hoja
A22: Columna | B22: Fórmula (Excel) | C22: Cómo se calcula (sencillo) | D22: Ejemplo con números reales | E22: De dónde viene | F22: Norma
A23: Importe | B23: '=IF('02_Parametros'!$B$8="","",'02_Parametros'!$B$8) | C23: Cada concepto tiene su cálculo: la utilidad base viene de la hoja 02 (Parámetros); la reserva calculada es la utilidad positiva por el %; capital y reserva inicial, apropiada y final se suman por clase de la hoja 03; el nivel mínimo es capital por %; la requerida es la menor entre la calculada y el margen hasta el nivel mínimo; por apropiar = requerida − apropiada. | D23: Fila 3: IF(128.000,00=""; ""; 128.000,00) → 128.000,00 | E23: hoja «Parámetros» | F23: —
A24: Porcentaje | B24: '=IF('02_Parametros'!$B$9="","",'02_Parametros'!$B$9/100) | C24: Toma de la hoja 02 (Parámetros) el % de la utilidad para la reserva legal y el % del capital que fija su nivel mínimo, divididos para 100; si no se fijaron, quedan en blanco. | D24: Fila 4: IF(10,00=""; ""; 10,00/100) → 10,00 % | E24: hoja «Parámetros» | F24: —

Sheet 06_Dividendos
A1: Dividendos | H1: ⟵ Inicio | I1: ◀ Anterior | J1: Siguiente ▶
A2: Patrimonio · Cliente de muestra S.A. · corte 2025-12-31
A4: Concepto | B4: Importe | C4: Referencia
A5: Resultados acumulados (saldo inicial) | B5: =SUMIF('03_Movimiento'!$C$5:$C$13,"Resultados acumulados",'03_Movimiento'!$D$5:$D$13) | C5: 03_Movimiento
A6: Resultado del ejercicio anterior (saldo inicial) | B6: =SUMIF('03_Movimiento'!$C$5:$C$13,"Resultado del ejercicio",'03_Movimiento'!$D$5:$D$13) | C6: 03_Movimiento
A7: Utilidades antes de la reserva legal | B7: =MAX(B5+B6,0)
A8: Resultados acumulados por adopción por primera vez de NIIF informados | B8: =IF(COUNT('03_Movimiento'!$L$5:$L$13)=0,"",SUM('03_Movimiento'!$L$5:$L$13)) | C8: 03_Movimiento · NIIF 1 párr. 11 (los ajustes de transición se reconocen en las reservas por ganancias acumuladas) y 24 a) (conciliación del patrimonio)
A9: (−) De ellos en resultados acumulados y del ejercicio (no distribuibles) | B9: =IF(B8="","",SUMIF('03_Movimiento'!$C$5:$C$13,"Resultados acumulados",'03_Movimiento'!$L$5:$L$13)+SUMIF('03_Movimiento'!$C$5:$C$13,"Resultado del ejercicio",'03_Movimiento'!$L$5:$L$13)) | C9: Se presentan aparte; su disponibilidad depende de la regulación societaria y del origen del ajuste
A10: Utilidades antes de la reserva legal, netas de los ajustes de transición | B10: =MAX(B7-IF(B9="",0,B9),0)
A11: (−) Reserva legal requerida | B11: =IF('05_Reserva_legal'!B15="",0,'05_Reserva_legal'!B15) | C11: 05_Reserva_legal
A12: (+) Reservas expresas de libre disposición | B12: =IF('02_Parametros'!$B$13="",0,'02_Parametros'!$B$13) | C12: Ley de Compañías art. 298
A13: Utilidades disponibles calculadas | B13: =MAX(B10-B11,0)+B12
A14: Utilidades disponibles según el auditor | B14: =IF('02_Parametros'!$B$12="","",'02_Parametros'!$B$12) | C14: 02_Parametros (líquidas y realizadas)
A15: Utilidades disponibles usadas | B15: =IF(B14<>"",B14,B13)
A16: Dividendos declarados en el período | B16: =SUM('04_Transacciones'!$O$5:$O$14) | C16: 04_Transacciones · NIC 32 35
A17: Dividendos en exceso de utilidades disponibles | B17: =MAX(B16-B15,0) | C17: Ley de Compañías arts. 208 y 298
A18: Dividendos declarados después del cierre | B18: =SUMIFS('04_Transacciones'!$D$5:$D$14,'04_Transacciones'!$C$5:$C$14,"Dividendo declarado",'04_Transacciones'!$N$5:$N$14,"Sí") | C18: Revelar · NIC 1 137 a)
A19: De ellos registrados como pasivo al corte | B19: =SUM('04_Transacciones'!$P$5:$P$14) | C19: Error · NIC 10 12–13
A20: Dividendos pagados en el período | B20: =SUMIFS('04_Transacciones'!$D$5:$D$14,'04_Transacciones'!$C$5:$C$14,"Dividendo pagado",'04_Transacciones'!$N$5:$N$14,"No") | C20: 04_Transacciones
A21: Beneficios líquidos base del mínimo legal (utilidad − reserva legal requerida) | B21: =IF('05_Reserva_legal'!B7="","",MAX('05_Reserva_legal'!B7-B11,0)) | C21: 05_Reserva_legal · Ley de Compañías art. 297
A22: Dividendo mínimo legal | B22: =IF(OR(B21="",'02_Parametros'!$B$15="Sí",'02_Parametros'!$B$14=""),"",B21*'02_Parametros'!$B$14/100) | C22: Art. 297 (compañía anónima): 50 % salvo resolución unánime (30 % en emisores inscritos en el Catastro Público del Mercado de Valores); en otras formas societarias, el % que informe el auditor; vigente al corte
A23: Dividendos por debajo del mínimo legal | B23: =IF(B22="","",MAX(B22-B16,0)) | C23: Faltante por asignar
A25: ⓘ Cómo se calcula esta hoja
A26: Columna | B26: Fórmula (Excel) | C26: Cómo se calcula (sencillo) | D26: Ejemplo con números reales | E26: De dónde viene | F26: Norma
A27: Importe | B27: '=SUMIF('03_Movimiento'!$C$5:$C$13,"Resultados acumulados",'03_Movimiento'!$D$5:$D$13) | C27: Los saldos iniciales de resultados y los ajustes por adopción de NIIF se suman por clase de la hoja 03; la reserva requerida viene de la hoja 05; las reservas libres y el dato del auditor, de la hoja 02; los dividendos declarados, posteriores y pagados se suman de la hoja 04; el resto combina las filas de esta hoja (utilidad disponible, exceso, mínimo legal y faltante). | D27: Fila 1: SUMIF([«Clase» de «Movimiento patrimonial», 9 filas]; "Resultados acumulados"; [«Saldo inicial» de «Movimiento patrimonial», 9 filas]) → 150.000,00 | E27: hoja «Movimiento patrimonial» | F27: —

Sheet 07_Capital
A1: Capital y aumentos | H1: ⟵ Inicio | I1: ◀ Anterior | J1: Siguiente ▶
A2: Patrimonio · Cliente de muestra S.A. · corte 2025-12-31
A4: Concepto | B4: Importe | C4: Referencia
A5: Capital según cliente | B5: =SUMIF('03_Movimiento'!$C$5:$C$13,"Capital",'03_Movimiento'!$H$5:$H$13) | C5: 03_Movimiento
A6: Capital según escritura / Supercias | B6: =IF('02_Parametros'!$B$11="","",'02_Parametros'!$B$11) | C6: 02_Parametros
A7: Diferencia cliente − escritura | B7: =IF(B6="","",B5-B6)
A8: Aumentos de capital del período | B8: =SUMIF('04_Transacciones'!$C$5:$C$14,"Aumento de capital",'04_Transacciones'!$D$5:$D$14) | C8: 04_Transacciones
A9: Aumentos no inscritos al corte | B9: =SUM('04_Transacciones'!$Q$5:$Q$14) | C9: Registro Mercantil
A10: Aportes para futuras capitalizaciones según cliente | B10: =SUMIF('03_Movimiento'!$C$5:$C$13,"Aportes futuras capitalizaciones",'03_Movimiento'!$H$5:$H$13) | C10: 03_Movimiento
A11: Capital menos aumentos no inscritos | B11: =B5-B9
A12: Diferencia no explicada por aumentos no inscritos | B12: =IF(B6="","",B11-B6)
A14: ⓘ Cómo se calcula esta hoja
A15: Columna | B15: Fórmula (Excel) | C15: Cómo se calcula (sencillo) | D15: Ejemplo con números reales | E15: De dónde viene | F15: Norma
A16: Importe | B16: '=SUMIF('03_Movimiento'!$C$5:$C$13,"Capital",'03_Movimiento'!$H$5:$H$13) | C16: El capital y los aportes según el cliente se suman de la hoja 03 (Movimiento patrimonial); el capital según escritura viene de la hoja 02 (Parámetros); los aumentos y los no inscritos se suman de la hoja 04 (Actas y transacciones); las diferencias restan esas filas entre sí. | D16: Fila 1: SUMIF([«Clase» de «Movimiento patrimonial», 9 filas]; "Capital"; [«Final según cliente» de «Movimiento patrimonial», 9 filas]) → 500.000,00 | E16: hoja «Movimiento patrimonial» | F16: —

Sheet 08_Clasificacion
A1: Clasificación deuda / patrimonio | H1: ⟵ Inicio | I1: ◀ Anterior | J1: Siguiente ▶
A2: Patrimonio · Cliente de muestra S.A. · corte 2025-12-31
A4: Referencia | B4: Tipo | C4: Cuenta | D4: Importe | E4: Devolución | F4: Obligación contractual | G4: A reclasificar a pasivo | H4: Fundamento
A5: AP-2025-01 | B5: Aporte | C5: Aportes futuras capitalizaciones | D5: ='04_Transacciones'!D9 | E5: Sí | G5: ='04_Transacciones'!R9+'04_Transacciones'!S9 | H5: Aporte con obligación de devolución (NIC 32 11, 15–16, 18 a))
A6: JGA-2025-06 | B6: Otro | C6: Otra | D6: ='04_Transacciones'!D11 | F6: Sí | G6: ='04_Transacciones'!R11+'04_Transacciones'!S11 | H6: Obligación contractual de entregar efectivo (NIC 32 11, 15–16, 18 a))
A7: TOTAL | D7: =SUM(D5:D6) | G7: =SUM(G5:G6)
A9: ⓘ Cómo se calcula esta hoja
A10: Columna | B10: Fórmula (Excel) | C10: Cómo se calcula (sencillo) | D10: Ejemplo con números reales | E10: De dónde viene | F10: Norma
A11: Importe | B11: '='04_Transacciones'!D9 | C11: Trae el importe de la misma transacción desde la hoja 04 (Actas y transacciones). | D11: Fila 1: 30.000,00 → 30.000,00 | E11: hoja «Actas y transacciones» | F11: —
A12: A reclasificar a pasivo | B12: '='04_Transacciones'!R9+'04_Transacciones'!S9 | C12: Suma lo que la hoja 04 (Actas y transacciones) marcó como aporte a pasivo y como instrumento a pasivo para esta transacción. | D12: Fila 1: 30.000,00+0,00 → 30.000,00 | E12: hoja «Actas y transacciones» | F12: —

Sheet 09_Recompra
A1: Recompra de acciones propias | H1: ⟵ Inicio | I1: ◀ Anterior | J1: Siguiente ▶
A2: Patrimonio · Cliente de muestra S.A. · corte 2025-12-31
A4: Referencia | B4: Fecha | C4: Costo | D4: Cuenta | E4: Deducida como acciones propias | F4: Resultado reconocido | G4: A reclasificar al patrimonio
A5: JGA-2025-05 | B5: 45881 | C5: ='04_Transacciones'!D10 | D5: Acciones propias | E5: =IF('04_Transacciones'!J10="","",IF('04_Transacciones'!J10="Acciones propias","Sí","No")) | F5: ='04_Transacciones'!T10 | G5: =ABS(F5)
A6: TOTAL | C6: =SUM(C5:C5) | F6: =SUM(F5:F5) | G6: =SUM(G5:G5)
A8: ⓘ Cómo se calcula esta hoja
A9: Columna | B9: Fórmula (Excel) | C9: Cómo se calcula (sencillo) | D9: Ejemplo con números reales | E9: De dónde viene | F9: Norma
A10: Costo | B10: '='04_Transacciones'!D10 | C10: Trae el importe pagado en la recompra desde la hoja 04 (Actas y transacciones). | D10: Fila 1: 20.000,00 → 20.000,00 | E10: hoja «Actas y transacciones» | F10: —
A11: Deducida como acciones propias | B11: '=IF('04_Transacciones'!J10="","",IF('04_Transacciones'!J10="Acciones propias","Sí","No")) | C11: Marca «Sí» si en la hoja 04 la cuenta afectada es «Acciones propias» y «No» si se registró en otra cuenta; si no se indicó la cuenta, queda en blanco. | D11: Fila 1: IF(«Acciones propias»=""; ""; IF(«Acciones propias»="Acciones propias"; "Sí"; "No")) → Sí | E11: hoja «Actas y transacciones» | F11: —
A12: Resultado reconocido | B12: '='04_Transacciones'!T10 | C12: Trae el resultado que el cliente reconoció por la recompra desde la hoja 04 (Actas y transacciones). | D12: Fila 1: -1.500,00 → -1.500,00 | E12: hoja «Actas y transacciones» | F12: —
A13: A reclasificar al patrimonio | B13: '=ABS(F5) | C13: Toma el resultado reconocido sin signo: es el importe que debe pasar de resultados al patrimonio. | D13: Fila 1: ABS(-1.500,00) → 1.500,00 | E13: «Resultado reconocido» (esta hoja) | F13: —

Sheet 10_Ajuste
A1: Patrimonio auditado y ajustes | H1: ⟵ Inicio | I1: ◀ Anterior | J1: Siguiente ▶
A2: Patrimonio · Cliente de muestra S.A. · corte 2025-12-31
A4: Concepto | B4: Importe | C4: Referencia
A5: Patrimonio según cliente | B5: =SUM('03_Movimiento'!$H$5:$H$13) | C5: 03_Movimiento
A6: (−) Aportes con obligación de devolución (a pasivo) | B6: =SUM('04_Transacciones'!$R$5:$R$14) | C6: 08_Clasificacion · NIC 32 11, 15–16, 18 a)
A7: (−) Instrumentos con obligación contractual (a pasivo) | B7: =SUM('04_Transacciones'!$S$5:$S$14) | C7: 08_Clasificacion · NIC 32 11, 15–16, 18 a)
A8: (+) Dividendos posteriores registrados como pasivo (revertir) | B8: =SUM('04_Transacciones'!$P$5:$P$14) | C8: NIC 10 12–13
A9: Patrimonio auditado | B9: =B5-B6-B7+B8
A10: Ajuste neto propuesto al patrimonio | B10: =B9-B5 | C10: Negativo: disminuye el patrimonio
A11: Diferencias del movimiento recalculado (absolutas) | B11: =SUMPRODUCT(ABS('03_Movimiento'!$I$5:$I$13)) | C11: NIC 1 106–110
A12: Patrimonio según el mayor | B12: =IF(COUNT('03_Movimiento'!$J$5:$J$13)=0,"",SUM('03_Movimiento'!$J$5:$J$13)) | C12: 03_Movimiento
A13: Diferencia cliente − mayor | B13: =IF(B12="","",B5-B12) | C13: NIA 500
A14: Reserva legal requerida | B14: ='05_Reserva_legal'!B15 | C14: 05_Reserva_legal
A15: Reserva legal apropiada | B15: ='05_Reserva_legal'!B16 | C15: 05_Reserva_legal
A16: Reserva legal por apropiar (− exceso) | B16: ='05_Reserva_legal'!B17 | C16: Reclasificación dentro del patrimonio
A17: Resultados acumulados por adopción por primera vez de NIIF (no distribuibles) | B17: ='06_Dividendos'!B8 | C17: 06_Dividendos · NIIF 1 párr. 11 (los ajustes de transición se reconocen en las reservas por ganancias acumuladas) y 24 a) (conciliación del patrimonio)
A18: De ellos excluidos de la utilidad disponible para dividendos | B18: ='06_Dividendos'!B9 | C18: Sujetos a la regulación societaria aplicable y al origen del ajuste
A19: Dividendos declarados en el período | B19: ='06_Dividendos'!B16 | C19: 06_Dividendos
A20: Utilidades disponibles para dividendos | B20: ='06_Dividendos'!B15 | C20: 06_Dividendos
A21: Dividendos en exceso de utilidades disponibles | B21: ='06_Dividendos'!B17 | C21: 06_Dividendos
A22: Dividendo mínimo legal (art. 297) | B22: ='06_Dividendos'!B22 | C22: 06_Dividendos
A23: Dividendos por debajo del mínimo legal | B23: ='06_Dividendos'!B23 | C23: 06_Dividendos
A24: Aumentos de capital no inscritos al corte | B24: ='07_Capital'!B9 | C24: 07_Capital
A25: Capital según cliente | B25: ='07_Capital'!B5 | C25: 07_Capital
A26: Capital según escritura / Supercias | B26: ='07_Capital'!B6 | C26: 07_Capital
A27: Diferencia capital cliente − escritura | B27: ='07_Capital'!B7 | C27: 07_Capital
A28: Resultado reconocido por recompras | B28: =SUM('04_Transacciones'!$T$5:$T$14) | C28: 09_Recompra · NIC 32 33
A30: ⓘ Cómo se calcula esta hoja
A31: Columna | B31: Fórmula (Excel) | C31: Cómo se calcula (sencillo) | D31: Ejemplo con números reales | E31: De dónde viene | F31: Norma
A32: Importe | B32: '=SUM('03_Movimiento'!$H$5:$H$13) | C32: El patrimonio según cliente y según mayor y las diferencias del movimiento salen de la hoja 03; las reclasificaciones a pasivo, los dividendos posteriores y las recompras, de la hoja 04; el auditado es cliente − aportes e instrumentos a pasivo + dividendos posteriores; el ajuste, auditado − cliente; reserva, dividendos y capital se traen de las hojas 05, 06 y 07. | D32: Fila 1: SUM([«Final según cliente» de «Movimiento patrimonial», 9 filas]) → 935.000,00 | E32: hoja «Movimiento patrimonial» | F32: —

Sheet 11_Asientos
A1: Asientos propuestos | H1: ⟵ Inicio | I1: ◀ Anterior | J1: Siguiente ▶
A2: Patrimonio · Cliente de muestra S.A. · corte 2025-12-31
A4: Asiento | B4: Cuenta | C4: Debe | D4: Haber
A5: 1 · Aportes con obligación de devolución | B5: Aportes para futuras capitalizaciones (patrimonio) | C5: ='10_Ajuste'!B6
B6: Cuentas por pagar a accionistas / socios (pasivo) | D6: ='10_Ajuste'!B6
A7: 2 · Instrumentos con obligación contractual | B7: Capital / acciones preferentes (patrimonio) | C7: ='10_Ajuste'!B7
B8: Pasivo financiero (acciones rescatables) | D8: ='10_Ajuste'!B7
A9: 3 · Reversión de dividendos posteriores | B9: Dividendos por pagar | C9: ='10_Ajuste'!B8
B10: Resultados acumulados | D10: ='10_Ajuste'!B8
A11: 4 · Reserva legal | B11: Resultados acumulados | C11: =ABS('10_Ajuste'!B16)
B12: Reserva legal | D12: =ABS('10_Ajuste'!B16)
A13: 5 · Resultado de recompras al patrimonio | B13: Otras reservas / acciones propias (patrimonio) | C13: =ABS('10_Ajuste'!B28)
B14: Resultados del ejercicio (pérdida por recompra) | D14: =ABS('10_Ajuste'!B28)
A15: 6 · Aumentos de capital no inscritos (pendientes de inscripción) | B15: Capital social | C15: ='10_Ajuste'!B24
B16: Aportes para futuras capitalizaciones | D16: ='10_Ajuste'!B24
A18: ⓘ Cómo se calcula esta hoja
A19: Columna | B19: Fórmula (Excel) | C19: Cómo se calcula (sencillo) | D19: Ejemplo con números reales | E19: De dónde viene | F19: Norma
A20: Debe | B20: '='10_Ajuste'!B6 | C20: Toma cada importe de la hoja 10 (Patrimonio auditado y ajustes): aportes e instrumentos a pasivo, dividendos posteriores, reserva legal, recompras y aumentos no inscritos. | D20: Fila 1: 30.000,00 → 30.000,00 | E20: hoja «Patrimonio auditado y ajustes» | F20: —
A21: Haber | B21: '='10_Ajuste'!B6 | C21: Lleva a la contrapartida el mismo importe del asiento, tomado de la hoja 10 (Patrimonio auditado y ajustes), para que debe y haber cuadren. | D21: Fila 2: 30.000,00 → 30.000,00 | E21: hoja «Patrimonio auditado y ajustes» | F21: —

Sheet 12_Problemas
A1: Problemas encontrados | H1: ⟵ Inicio | I1: ◀ Anterior | J1: Siguiente ▶
A2: Patrimonio · Cliente de muestra S.A. · corte 2025-12-31
A4: Código | B4: Descripción | C4: Importe
A5: MOVIMIENTO_NO_CUADRA | B5: 306 Otros resultados integrales: inicial 12.000,00 + aumentos 3.500,00 − disminuciones 0,00 = 15.500,00, pero el saldo final informado es 15.000,00 (diferencia -500,00); el estado de cambios en el patrimonio debe conciliar cada componente (NIC 1 106–110). | C5: -500
A6: DIF_MAYOR | B6: 308 Resultado del ejercicio: saldo del cliente 142.000,00 vs mayor 143.200,00 (diferencia -1.200,00) (NIA 500). | C6: -1200
A7: RESERVA_LEGAL_NO_APROPIADA | B7: Reserva legal requerida 12.800,00 (10,00 % de la utilidad 128.000,00, hasta el 50,00 % del capital) frente a 8.000,00 apropiada: falta apropiar 4.800,00 (Reserva legal obligatoria: 10 % de las utilidades líquidas hasta por lo menos el 50 % del capital (Ley de Compañías art. 297); compañía Anónima; confirmar que sigue vigente al corte). | C7: 4800
A8: TRANSICION_NIIF_NO_DISTRIBUIBLE | B8: Resultados acumulados por adopción por primera vez de NIIF por 18.000,00 separados del resultado disponible para dividendos: no se mezclan automáticamente con la utilidad distribuible. Su disponibilidad queda sujeta a la regulación societaria ecuatoriana aplicable y a la naturaleza y el origen de cada ajuste (revalorizaciones y ajustes que no corresponden a beneficios realmente obtenidos y percibidos no son repartibles: Ley de Compañías arts. 208 y 297; confirmar que sigue vigente al corte y revisar la resolución de la Superintendencia de Compañías sobre el destino de los resultados acumulados por adopción por primera vez de NIIF). | C8: 18000
A9: DIVIDENDOS_SOBRE_UTILIDADES_NO_DISPONIBLES | B9: Dividendos declarados en el período 90.000,00 superan las utilidades disponibles 80.000,00 en 10.000,00: Ley de Compañías arts. 208 y 298: solo beneficios realmente obtenidos y percibidos o reservas de libre disposición — evalúe la legalidad y la revelación (NIC 32 35). | C9: 10000
A10: DIVIDENDO_POSTERIOR_COMO_PASIVO | B10: JGA-2026-01: dividendo declarado el 2026-02-20 (después del cierre) registrado como pasivo al corte por 50.000,00: no existía obligación al cierre; revertir contra el patrimonio y revelar en notas (NIC 10 12–13; NIC 1 137 a)). | C10: 50000
A11: DIVIDENDO_POSTERIOR_REVELAR | B11: Dividendos declarados después del cierre por 50.000,00: revelar el importe y el importe por acción en las notas (NIC 1 137 a)). | C11: 50000
A12: CAPITAL_NO_COINCIDE_ESCRITURA | B12: Capital según cliente 500.000,00 vs escritura / Supercias 460.000,00: diferencia 40.000,00 (de ella 40.000,00 por aumentos no inscritos). | C12: 40000
A13: APORTE_ES_PASIVO | B13: AP-2025-01: aporte de 30.000,00 con obligación de devolución: es un pasivo financiero, no patrimonio (NIC 32 11, 15–16, 18 a); confirme la resolución vigente de la Superintendencia de Compañías). | C13: 30000
A14: RECOMPRA_CON_RESULTADO | B14: JGA-2025-05: la recompra reconoció -1.500,00 en resultados: la contraprestación de acciones propias se reconoce directamente en el patrimonio, sin pérdida ni ganancia (NIC 32 33). | C14: 1500
A15: INSTRUMENTO_MAL_CLASIFICADO | B15: JGA-2025-06: instrumento de 45.000,00 con obligación contractual de entregar efectivo (p. ej. acciones preferentes rescatables) presentado en patrimonio: reclasificar a pasivo (NIC 32 11, 15–16, 18 a)). | C15: 45000
A16: AUMENTO_NO_INSCRITO | B16: JGA-2025-04: aumento de capital de 40.000,00 sin inscripción en el Registro Mercantil al corte: presentarlo como aporte para futura capitalización hasta la inscripción (Ley de Compañías art. 33: el aumento sigue las solemnidades de la constitución; confirme la inscripción en el Registro Mercantil). | C16: 40000
A17: SIN_ACTA | B17: JGA-2025-04: aumento de capital de 40.000,00 sin acta de junta informada: obtenga la resolución que la autoriza (Ley de Compañías; NIA 500). | C17: 40000

Sheet 13_Conclusion
A1: Conclusión | H1: ⟵ Inicio | I1: ◀ Anterior | J1: Siguiente ▶
A2: Patrimonio · Cliente de muestra S.A. · corte 2025-12-31
A4: Concepto | B4: Detalle
A5: Conciliación con el mayor | B5: Población None · mayor None · diferencia None
A6: Evaluación de excepciones
A7: Análisis
A8: Conclusión

Sheet 14_Control_Revision
A1: Control de revisión | H1: ⟵ Inicio | I1: ◀ Anterior
A2: Patrimonio · Cliente de muestra S.A. · corte 2025-12-31
A4: Fecha | B4: Acción | C4: Estado anterior | D4: Estado nuevo | E4: Actor | F4: Comentario
