Workbook

Sheet 00_Inicio
B2: AuditConsulting Auditores Cía. Ltda. · AUDIT-IA
B4: Pérdida crediticia esperada · enfoque simplificado (NIIF 9)
B6: Cliente | C6: Cliente de muestra S.A. | D6: RUC | E6: 1790000000001
B7: Marco contable | C7: NIIF completas | D7: Fecha de corte | E7: 2025-12-31
B8: Preparó | C8: Ejercicio modelo | D8: Revisó | E8: Pendiente
B10: INDICADORES CLAVE
B11: Ajuste propuesto | C11: Problemas encontrados
B12: 18377.39 | C12: 5
B15: IR A LA CÉDULA
B16: Carátula | C16: Programa | D16: Base técnica | E16: Resumen
B17: Parámetros | C17: Tasas históricas | D17: Matriz de provisiones | E17: Revelación NIIF 7 (35M/35N)
B18: Movimiento de la provisión (NIIF 7 35H) | C18: Fiscal e impuesto diferido | D18: Asientos propuestos | E18: Detalle por factura
B19: Cartera del corte anterior | C19: Castigos del ejercicio | D19: Problemas encontrados | E19: Conclusión
B20: Control de revisión
B22: PANORAMA | N22: Datos de los gráficos (fórmulas a las cédulas)
N23: Cifras del resumen | O23: Importe (USD)
N24: ='01_Resumen'!A5 | O24: ='01_Resumen'!B5
N25: ='01_Resumen'!A6 | O25: ='01_Resumen'!B6
N26: ='01_Resumen'!A7 | O26: ='01_Resumen'!B7
N27: ='01_Resumen'!A8 | O27: ='01_Resumen'!B8
N28: ='01_Resumen'!A9 | O28: ='01_Resumen'!B9
N29: ='01_Resumen'!A10 | O29: ='01_Resumen'!B10
N30: ='01_Resumen'!A11 | O30: ='01_Resumen'!B11
N31: ='01_Resumen'!A12 | O31: ='01_Resumen'!B12
N32: ='01_Resumen'!A13 | O32: ='01_Resumen'!B13
N33: ='01_Resumen'!A14 | O33: ='01_Resumen'!B14
N35: Hallazgos de mayor impacto | O35: Importe (USD)
N36: Tasa cero (×2) | O36: =SUMIFS('12_Problemas'!$C$5:$C$9,'12_Problemas'!$A$5:$A$9,"TASA_CERO",'12_Problemas'!$C$5:$C$9,">0")-SUMIFS('12_Problemas'!$C$5:$C$9,'12_Problemas'!$A$5:$A$9,"TASA_CERO",'12_Problemas'!$C$5:$C$9,"<0")
N37: En impago | O37: =SUMIFS('12_Problemas'!$C$5:$C$9,'12_Problemas'!$A$5:$A$9,"EN_IMPAGO",'12_Problemas'!$C$5:$C$9,">0")-SUMIFS('12_Problemas'!$C$5:$C$9,'12_Problemas'!$A$5:$A$9,"EN_IMPAGO",'12_Problemas'!$C$5:$C$9,"<0")
N38: No deducible | O38: =SUMIFS('12_Problemas'!$C$5:$C$9,'12_Problemas'!$A$5:$A$9,"NO_DEDUCIBLE",'12_Problemas'!$C$5:$C$9,">0")-SUMIFS('12_Problemas'!$C$5:$C$9,'12_Problemas'!$A$5:$A$9,"NO_DEDUCIBLE",'12_Problemas'!$C$5:$C$9,"<0")
N39: Ajuste | O39: =SUMIFS('12_Problemas'!$C$5:$C$9,'12_Problemas'!$A$5:$A$9,"AJUSTE",'12_Problemas'!$C$5:$C$9,">0")-SUMIFS('12_Problemas'!$C$5:$C$9,'12_Problemas'!$A$5:$A$9,"AJUSTE",'12_Problemas'!$C$5:$C$9,"<0")

Sheet 00_Caratula
A1: Carátula | H1: ⟵ Inicio | J1: Siguiente ▶
A2: Pérdida crediticia esperada · enfoque simplificado (NIIF 9) · Cliente de muestra S.A. · corte 2025-12-31
A4: Concepto | B4: Detalle
A5: Firma | B5: AuditConsulting Auditores Cía. Ltda.
A6: Cliente | B6: Cliente de muestra S.A.
A7: RUC | B7: 1790000000001
A8: Ejercicio | B8: 2025
A9: Fecha de corte | B9: 2025-12-31
A10: Marco contable | B10: NIIF completas
A11: Herramienta | B11: Pérdida crediticia esperada · enfoque simplificado (NIIF 9)
A12: Rubro | B12: Cuentas por cobrar
A13: Motor | B13: pce-simplificada 1.0
A14: Versión del papel | B14: v1
A15: Estado | B15: MUESTRA
... A17: Revisó | B17: Pendiente
A18: Aprobó
A19: Fecha de aprobación
A20: Huella de la ejecución (SHA-256)

Sheet 00_Programa
A1: Programa | H1: ⟵ Inicio | I1: ◀ Anterior | J1: Siguiente ▶
A2: Pérdida crediticia esperada · enfoque simplificado (NIIF 9) · Cliente de muestra S.A. · corte 2025-12-31
A4: Código | B4: Objetivo | C4: Afirmación | D4: Procedimiento | E4: Evidencia | F4: Criterio | G4: Referencia
A5: CXCPCE-01 | B5: Integridad de la cartera | C5: Integridad | D5: Conciliar la cartera por factura con el mayor al corte | E5: Cartera por factura y mayor | F5: Diferencia dentro de tolerancia o explicada | G5: NIA 500 párr. 9
A6: CXCPCE-02 | B6: Tasas históricas | C6: Valoración | D6: Medir por tramo la pérdida observada un año después (impago o castigo) sobre la cartera del corte anterior | E6: Cartera del corte anterior y castigos del año | F6: Tasa por tramo medida o fijada con sustento | G6: NIIF 9 B5.5.35, B5.5.37 · NIA 540
A7: CXCPCE-03 | B7: Información prospectiva | C7: Valoración | D7: Evaluar los escenarios, sus pesos y ajustes, y su sustento | E7: Proyecciones, indicadores del sector y de la economía | F7: Factor prospectivo documentado | G7: NIIF 9 5.5.17, B5.5.52
A8: CXCPCE-04 | B8: Medición de la pérdida esperada | C8: Valoración | D8: Recalcular la pérdida esperada por factura con la matriz y compararla con la provisión registrada | E8: Detalle por factura | F8: Ajuste cuantificado | G8: NIIF 9 5.5.15, B5.5.35
A9: CXCPCE-05 | B9: Movimiento, castigos y revelación | C9: Presentación | D9: Conciliar el movimiento de la provisión y preparar la matriz de revelación | E9: Castigos, mayor, notas | F9: Movimiento conciliado; nota NIIF 7 completa | G9: NIIF 9 5.4.4 · NIIF 7 35H, 35M, 35N
A10: CXCPCE-06 | B10: Tratamiento fiscal | C10: Presentación | D10: Aplicar los límites de deducibilidad y medir el impuesto diferido | E10: Parámetros fiscales | F10: Deducible y diferido recalculados | G10: LRTI Art. 10 num. 11 · NIC 12
A11: CXCPCE-07 | B11: Cobros posteriores | C11: Valoración | D11: Cotejar cobros posteriores al cierre con la cartera en impago y con tasa alta | E11: Estados de cuenta, depósitos posteriores | F11: Diferencias evaluadas | G11: NIA 560 párr. 6

Sheet 00_Fuentes
A1: Base técnica | H1: ⟵ Inicio | I1: ◀ Anterior | J1: Siguiente ▶
A2: Pérdida crediticia esperada · enfoque simplificado (NIIF 9) · Cliente de muestra S.A. · corte 2025-12-31
A4: Categoría | B4: Documento | C4: Párrafos | D4: URL | E4: Verificada
A5: NIA · NIA 540 (Revisada) | B5: Estimación contable: evaluar el método (matriz), los datos (cartera y castigos) y los supuestos (escenarios, tasas fijadas) y el posible sesgo. | C5: párr. 13 y 17–30
A6: NIA · NIA 500 | B6: Evaluar exactitud e integridad de los anexos de cartera contra el mayor. | C6: párr. 9
A7: NIA · NIA 505 | B7: Considerar confirmaciones de saldos significativos. | C7: párr. 7
A8: NIA · NIA 560 | B8: Cobros posteriores al cierre como evidencia sobre la estimación. | C8: párr. 6

Sheet 01_Resumen
A1: Resumen | H1: ⟵ Inicio | I1: ◀ Anterior | J1: Siguiente ▶
A2: Pérdida crediticia esperada · enfoque simplificado (NIIF 9) · Cliente de muestra S.A. · corte 2025-12-31
A4: Concepto | B4: Importe
A5: Cartera al corte | B5: ='07_Fiscal'!$B$5
A6: Pérdida crediticia esperada | B6: ='07_Fiscal'!$B$7
A7: Provisión registrada (mayor) | B7: ='02_Parametros'!B16
A8: Ajuste propuesto | B8: =B6-B7
A9: Dotación neta del ejercicio | B9: ='07_Fiscal'!$B$10
A10: Castigos del ejercicio | B10: ='07_Fiscal'!$B$9
A11: Gasto deducible | B11: ='07_Fiscal'!$B$15
A12: Gasto no deducible | B12: ='07_Fiscal'!$B$16
A13: Activo por impuesto diferido | B13: ='07_Fiscal'!$B$19
A14: Movimiento del diferido | B14: ='07_Fiscal'!$B$21
A16: ⓘ Cómo se calcula esta hoja
A17: Columna | B17: Fórmula (Excel) | C17: Cómo se calcula (sencillo) | D17: Ejemplo con números reales | E17: De dónde viene | F17: Norma
A18: Importe | B18: '='07_Fiscal'!$B$5 | C18: Trae cada importe de la hoja donde se calculó: cartera, pérdida esperada, dotación, castigos, gasto deducible y no deducible y diferido de la hoja 07 (Fiscal e impuesto diferido); la provisión registrada de la hoja 02 (Parámetros). El ajuste propuesto es la pérdida esperada menos la provisión registrada. | D18: Fila 1: 167.059,86 → 167.059,86 | E18: hoja «Fiscal e impuesto diferido» | F18: —

Sheet 02_Parametros
A1: Parámetros | H1: ⟵ Inicio | I1: ◀ Anterior | J1: Siguiente ▶
A2: Pérdida crediticia esperada · enfoque simplificado (NIIF 9) · Cliente de muestra S.A. · corte 2025-12-31
A4: Parámetro | B4: Valor | C4: Sustento
A5: Corte del ejercicio | B5: 46022 | C5: Ficha del encargo
A6: Corte anterior (un año antes) | B6: 45657 | C6: Base de la tasa histórica
A7: Tasa efectiva para descontar (%) | B7: 0 | C7: 5.5.17 b; 0 % en cartera de corto plazo sin componente financiero
A8: Plazo esperado de cobro (meses) | B8: 12 | C8: Juicio del auditor
A9: Escenario base: peso (%) | B9: 60 | C9: 5.5.17 a — importe ponderado por probabilidad
A10: Escenario base: ajuste a la historia (%) | B10: 0 | C10: 5.5.17 c, B5.5.52
A11: Escenario optimista: peso (%) | B11: 20 | C11: 5.5.17 a
A12: Escenario optimista: ajuste (%) | B12: -10 | C12: B5.5.52
A13: Escenario pesimista: peso (%) | B13: 20 | C13: 5.5.17 a
A14: Escenario pesimista: ajuste (%) | B14: 25 | C14: B5.5.52
A15: Factor prospectivo ponderado | B15: =(B9*(1+B10/100)+B11*(1+B12/100)+B13*(1+B14/100))/(B9+B11+B13) | C15: Σ peso × (1 + ajuste) ÷ Σ peso
A16: Provisión registrada al cierre (mayor) | B16: 5816.04 | C16: Mayor contable
A17: Provisión al inicio del ejercicio | B17: 0 | C17: Mayor contable
A18: Límite anual deducible (%) | B18: 1 | C18: LRTI Art. 10 num. 11
A19: Límite acumulado (%) | B19: 10 | C19: LRTI Art. 10 num. 11
A20: Tasa del impuesto (%) | B20: 25 | C20: Tarifa del contribuyente
A21: Provisión fiscal acumulada anterior | C21: En blanco: mínimo entre la provisión inicial y el límite acumulado
A23: ⓘ Cómo se calcula esta hoja
A24: Columna | B24: Fórmula (Excel) | C24: Cómo se calcula (sencillo) | D24: Ejemplo con números reales | E24: De dónde viene | F24: Norma
A25: Valor | B25: '=(B9*(1+B10/100)+B11*(1+B12/100)+B13*(1+B14/100))/(B9+B11+B13) | C25: Los parámetros son datos del encargo o juicio del auditor; solo el factor prospectivo ponderado se calcula: suma peso × (1 + ajuste) de los tres escenarios y lo divide para la suma de los pesos. | D25: Fila 11: (60,00*(1+0,00/100)+20,00*(1+-10,00/100)+20,00*(1+25,00/100))/(60,00+20,00+20,00) → 1,03 | E25: «Valor» (esta hoja) | F25: —

Sheet 03_Tasas_historicas
A1: Tasas históricas | H1: ⟵ Inicio | I1: ◀ Anterior | J1: Siguiente ▶
A2: Pérdida crediticia esperada · enfoque simplificado (NIIF 9) · Cliente de muestra S.A. · corte 2025-12-31
A4: Segmento | B4: Tramo | C4: Clave | D4: Facturas | E4: Saldo al corte anterior | F4: Impago o castigado un año después | G4: Tasa histórica
A5: General | B5: Corriente / por vencer | C5: General|Corriente / por vencer | D5: =COUNTIF('10_Cartera_anterior'!$G$5:$G$21,C5) | E5: =SUMIF('10_Cartera_anterior'!$G$5:$G$21,C5,'10_Cartera_anterior'!$H$5:$H$21) | F5: =SUMIF('10_Cartera_anterior'!$G$5:$G$21,C5,'10_Cartera_anterior'!$K$5:$K$21) | G5: =IF(E5=0,"",F5/E5)
A6: General | B6: 1 a 30 días | C6: General|1 a 30 días | D6: =COUNTIF('10_Cartera_anterior'!$G$5:$G$21,C6) | E6: =SUMIF('10_Cartera_anterior'!$G$5:$G$21,C6,'10_Cartera_anterior'!$H$5:$H$21) | F6: =SUMIF('10_Cartera_anterior'!$G$5:$G$21,C6,'10_Cartera_anterior'!$K$5:$K$21) | G6: =IF(E6=0,"",F6/E6)
A7: General | B7: 31 a 60 días | C7: General|31 a 60 días | D7: =COUNTIF('10_Cartera_anterior'!$G$5:$G$21,C7) | E7: =SUMIF('10_Cartera_anterior'!$G$5:$G$21,C7,'10_Cartera_anterior'!$H$5:$H$21) | F7: =SUMIF('10_Cartera_anterior'!$G$5:$G$21,C7,'10_Cartera_anterior'!$K$5:$K$21) | G7: =IF(E7=0,"",F7/E7)
A8: General | B8: 61 a 90 días | C8: General|61 a 90 días | D8: =COUNTIF('10_Cartera_anterior'!$G$5:$G$21,C8) | E8: =SUMIF('10_Cartera_anterior'!$G$5:$G$21,C8,'10_Cartera_anterior'!$H$5:$H$21) | F8: =SUMIF('10_Cartera_anterior'!$G$5:$G$21,C8,'10_Cartera_anterior'!$K$5:$K$21) | G8: =IF(E8=0,"",F8/E8)
A9: General | B9: 91 a 180 días | C9: General|91 a 180 días | D9: =COUNTIF('10_Cartera_anterior'!$G$5:$G$21,C9) | E9: =SUMIF('10_Cartera_anterior'!$G$5:$G$21,C9,'10_Cartera_anterior'!$H$5:$H$21) | F9: =SUMIF('10_Cartera_anterior'!$G$5:$G$21,C9,'10_Cartera_anterior'!$K$5:$K$21) | G9: =IF(E9=0,"",F9/E9)
A10: General | B10: 181 a 360 días | C10: General|181 a 360 días | D10: =COUNTIF('10_Cartera_anterior'!$G$5:$G$21,C10) | E10: =SUMIF('10_Cartera_anterior'!$G$5:$G$21,C10,'10_Cartera_anterior'!$H$5:$H$21) | F10: =SUMIF('10_Cartera_anterior'!$G$5:$G$21,C10,'10_Cartera_anterior'!$K$5:$K$21) | G10: =IF(E10=0,"",F10/E10)
A11: General | B11: Más de 360 días | C11: General|Más de 360 días | D11: =COUNTIF('10_Cartera_anterior'!$G$5:$G$21,C11) | E11: =SUMIF('10_Cartera_anterior'!$G$5:$G$21,C11,'10_Cartera_anterior'!$H$5:$H$21) | F11: =SUMIF('10_Cartera_anterior'!$G$5:$G$21,C11,'10_Cartera_anterior'!$K$5:$K$21) | G11: =IF(E11=0,"",F11/E11)
A13: ⓘ Cómo se calcula esta hoja
A14: Columna | B14: Fórmula (Excel) | C14: Cómo se calcula (sencillo) | D14: Ejemplo con números reales | E14: De dónde viene | F14: Norma
A15: Facturas | B15: '=COUNTIF('10_Cartera_anterior'!$G$5:$G$21,C5) | C15: Cuenta cuántas facturas de la cartera del corte anterior (hoja 10) tienen este mismo segmento y tramo de mora. | D15: Fila 1: COUNTIF([«Clave» de «Cartera del corte anterior», 17 filas]; «General|Corriente / por vencer») → 3 | E15: «Clave» (esta hoja), hoja «Cartera del corte anterior» | F15: —
A16: Saldo al corte anterior | B16: '=SUMIF('10_Cartera_anterior'!$G$5:$G$21,C5,'10_Cartera_anterior'!$H$5:$H$21) | C16: Suma el saldo que tenían, al corte anterior, las facturas de este segmento y tramo en la hoja 10 (Cartera del corte anterior). | D16: Fila 1: SUMIF([«Clave» de «Cartera del corte anterior», 17 filas]; «General|Corriente / por vencer»; [«Saldo» de «Cartera del corte anterior», 17 filas]) → 46.175,33 | E16: «Clave» (esta hoja), hoja «Cartera del corte anterior» | F16: —
A17: Impago o castigado un año después | B17: '=SUMIF('10_Cartera_anterior'!$G$5:$G$21,C5,'10_Cartera_anterior'!$K$5:$K$21) | C17: Suma la pérdida observada de esas mismas facturas en la hoja 10: lo que un año después seguía impago más lo que se castigó. | D17: Fila 1: SUMIF([«Clave» de «Cartera del corte anterior», 17 filas]; «General|Corriente / por vencer»; [«Pérdida observada» de «Cartera del corte anterior», 17 filas]) → 0,00 | E17: «Clave» (esta hoja), hoja «Cartera del corte anterior» | F17: —
A18: Tasa histórica | B18: '=IF(E5=0,"",F5/E5) | C18: Divide lo impago o castigado un año después para el saldo al corte anterior: es la tasa de pérdida que mostró la historia. Si no hubo saldo anterior, queda en blanco. | D18: Fila 1: IF(46.175,33=0; ""; 0,00/46.175,33) → 0,00 % | E18: «Saldo al corte anterior» (esta hoja), «Impago o castigado un año después» (esta hoja) | F18: —

Sheet 04_Matriz_provisiones
A1: Matriz de provisiones | H1: ⟵ Inicio | I1: ◀ Anterior | J1: Siguiente ▶
A2: Pérdida crediticia esperada · enfoque simplificado (NIIF 9) · Cliente de muestra S.A. · corte 2025-12-31
A4: Segmento | B4: Tramo | C4: Clave | D4: Tasa histórica | E4: Tasa fijada | F4: Tasa base | G4: Factor prospectivo | H4: Tasa aplicada | I4: Saldo al corte | J4: Pérdida esperada
A5: General | B5: Corriente / por vencer | C5: General|Corriente / por vencer | D5: ='03_Tasas_historicas'!G5 | F5: =IF(D5<>"",D5,IF(E5<>"",E5,"")) | G5: ='02_Parametros'!$B$15 | H5: =IF(F5="","",MIN(F5*G5,1)) | I5: =SUMIF('09_Detalle'!$G$5:$G$24,C5,'09_Detalle'!$H$5:$H$24) | J5: =SUMIF('09_Detalle'!$G$5:$G$24,C5,'09_Detalle'!$K$5:$K$24)
A6: General | B6: 1 a 30 días | C6: General|1 a 30 días | D6: ='03_Tasas_historicas'!G6 | F6: =IF(D6<>"",D6,IF(E6<>"",E6,"")) | G6: ='02_Parametros'!$B$15 | H6: =IF(F6="","",MIN(F6*G6,1)) | I6: =SUMIF('09_Detalle'!$G$5:$G$24,C6,'09_Detalle'!$H$5:$H$24) | J6: =SUMIF('09_Detalle'!$G$5:$G$24,C6,'09_Detalle'!$K$5:$K$24)
A7: General | B7: 31 a 60 días | C7: General|31 a 60 días | D7: ='03_Tasas_historicas'!G7 | F7: =IF(D7<>"",D7,IF(E7<>"",E7,"")) | G7: ='02_Parametros'!$B$15 | H7: =IF(F7="","",MIN(F7*G7,1)) | I7: =SUMIF('09_Detalle'!$G$5:$G$24,C7,'09_Detalle'!$H$5:$H$24) | J7: =SUMIF('09_Detalle'!$G$5:$G$24,C7,'09_Detalle'!$K$5:$K$24)
A8: General | B8: 61 a 90 días | C8: General|61 a 90 días | D8: ='03_Tasas_historicas'!G8 | F8: =IF(D8<>"",D8,IF(E8<>"",E8,"")) | G8: ='02_Parametros'!$B$15 | H8: =IF(F8="","",MIN(F8*G8,1)) | I8: =SUMIF('09_Detalle'!$G$5:$G$24,C8,'09_Detalle'!$H$5:$H$24) | J8: =SUMIF('09_Detalle'!$G$5:$G$24,C8,'09_Detalle'!$K$5:$K$24)
A9: General | B9: 91 a 180 días | C9: General|91 a 180 días | D9: ='03_Tasas_historicas'!G9 | F9: =IF(D9<>"",D9,IF(E9<>"",E9,"")) | G9: ='02_Parametros'!$B$15 | H9: =IF(F9="","",MIN(F9*G9,1)) | I9: =SUMIF('09_Detalle'!$G$5:$G$24,C9,'09_Detalle'!$H$5:$H$24) | J9: =SUMIF('09_Detalle'!$G$5:$G$24,C9,'09_Detalle'!$K$5:$K$24)
A10: General | B10: 181 a 360 días | C10: General|181 a 360 días | D10: ='03_Tasas_historicas'!G10 | F10: =IF(D10<>"",D10,IF(E10<>"",E10,"")) | G10: ='02_Parametros'!$B$15 | H10: =IF(F10="","",MIN(F10*G10,1)) | I10: =SUMIF('09_Detalle'!$G$5:$G$24,C10,'09_Detalle'!$H$5:$H$24) | J10: =SUMIF('09_Detalle'!$G$5:$G$24,C10,'09_Detalle'!$K$5:$K$24)
A11: General | B11: Más de 360 días | C11: General|Más de 360 días | D11: ='03_Tasas_historicas'!G11 | F11: =IF(D11<>"",D11,IF(E11<>"",E11,"")) | G11: ='02_Parametros'!$B$15 | H11: =IF(F11="","",MIN(F11*G11,1)) | I11: =SUMIF('09_Detalle'!$G$5:$G$24,C11,'09_Detalle'!$H$5:$H$24) | J11: =SUMIF('09_Detalle'!$G$5:$G$24,C11,'09_Detalle'!$K$5:$K$24)
A12: TOTAL | I12: =SUM(I5:I11) | J12: =SUM(J5:J11)
A14: ⓘ Cómo se calcula esta hoja
A15: Columna | B15: Fórmula (Excel) | C15: Cómo se calcula (sencillo) | D15: Ejemplo con números reales | E15: De dónde viene | F15: Norma
A16: Tasa histórica | B16: '='03_Tasas_historicas'!G5 | C16: Trae la tasa histórica del mismo segmento y tramo desde la hoja 03 (Tasas históricas). | D16: Fila 1: 0,00 % → 0,00 % | E16: hoja «Tasas históricas» | F16: —
A17: Tasa base | B17: '=IF(D5<>"",D5,IF(E5<>"",E5,"")) | C17: Usa la tasa histórica si existe; si no hay historia, usa la tasa fijada por el auditor; si no hay ninguna de las dos, queda en blanco. | D17: Fila 1: IF(0,00 %<>""; 0,00 %; IF((vacío)<>""; (vacío); "")) → 0,00 % | E17: «Tasa histórica» (esta hoja), «Tasa fijada» (esta hoja) | F17: —
A18: Factor prospectivo | B18: '='02_Parametros'!$B$15 | C18: Trae el factor prospectivo ponderado de la hoja 02 (Parámetros), que ajusta la historia con los escenarios base, optimista y pesimista. | D18: Fila 1: 1,03 → 1,03 | E18: hoja «Parámetros» | F18: —
A19: Tasa aplicada | B19: '=IF(F5="","",MIN(F5*G5,1)) | C19: Multiplica la tasa base por el factor prospectivo, con un tope de 100 %. Si el tramo no tiene tasa base, queda en blanco. | D19: Fila 1: IF(0,00 %=""; ""; MIN(0,00 %*1,03; 1)) → 0,00 % | E19: «Tasa base» (esta hoja), «Factor prospectivo» (esta hoja) | F19: —
A20: Saldo al corte | B20: '=SUMIF('09_Detalle'!$G$5:$G$24,C5,'09_Detalle'!$H$5:$H$24) | C20: Suma el saldo de las facturas del detalle (hoja 09) que tienen este mismo segmento y tramo de mora. | D20: Fila 1: SUMIF([«Clave» de «Detalle por factura», 20 filas]; «General|Corriente / por vencer»; [«Saldo» de «Detalle por factura», 20 filas]) → 90.377,19 | E20: «Clave» (esta hoja), hoja «Detalle por factura» | F20: —
A21: Pérdida esperada | B21: '=SUMIF('09_Detalle'!$G$5:$G$24,C5,'09_Detalle'!$K$5:$K$24) | C21: Suma la pérdida esperada calculada factura por factura en la hoja 09 (Detalle por factura) para este segmento y tramo. | D21: Fila 1: SUMIF([«Clave» de «Detalle por factura», 20 filas]; «General|Corriente / por vencer»; [«Pérdida esperada» de «Detalle por factura», 20 filas]) → 0,00 | E21: «Clave» (esta hoja), hoja «Detalle por factura» | F21: —

Sheet 05_Revelacion_NIIF7
A1: Revelación NIIF 7 (35M/35N) | H1: ⟵ Inicio | I1: ◀ Anterior | J1: Siguiente ▶
A2: Pérdida crediticia esperada · enfoque simplificado (NIIF 9) · Cliente de muestra S.A. · corte 2025-12-31
A4: Tramo de mora | B4: Importe en libros bruto | C4: Tasa esperada promedio | D4: Pérdida esperada | E4: En impago (B5.5.37)
A5: Corriente / por vencer | B5: =SUMIF('09_Detalle'!$F$5:$F$24,A5,'09_Detalle'!$H$5:$H$24) | C5: =IF(B5=0,"",D5/B5) | D5: =SUMIF('09_Detalle'!$F$5:$F$24,A5,'09_Detalle'!$K$5:$K$24) | E5: No
A6: 1 a 30 días | B6: =SUMIF('09_Detalle'!$F$5:$F$24,A6,'09_Detalle'!$H$5:$H$24) | C6: =IF(B6=0,"",D6/B6) | D6: =SUMIF('09_Detalle'!$F$5:$F$24,A6,'09_Detalle'!$K$5:$K$24) | E6: No
A7: 31 a 60 días | B7: =SUMIF('09_Detalle'!$F$5:$F$24,A7,'09_Detalle'!$H$5:$H$24) | C7: =IF(B7=0,"",D7/B7) | D7: =SUMIF('09_Detalle'!$F$5:$F$24,A7,'09_Detalle'!$K$5:$K$24) | E7: No
A8: 61 a 90 días | B8: =SUMIF('09_Detalle'!$F$5:$F$24,A8,'09_Detalle'!$H$5:$H$24) | C8: =IF(B8=0,"",D8/B8) | D8: =SUMIF('09_Detalle'!$F$5:$F$24,A8,'09_Detalle'!$K$5:$K$24) | E8: No
A9: 91 a 180 días | B9: =SUMIF('09_Detalle'!$F$5:$F$24,A9,'09_Detalle'!$H$5:$H$24) | C9: =IF(B9=0,"",D9/B9) | D9: =SUMIF('09_Detalle'!$F$5:$F$24,A9,'09_Detalle'!$K$5:$K$24) | E9: Sí
A10: 181 a 360 días | B10: =SUMIF('09_Detalle'!$F$5:$F$24,A10,'09_Detalle'!$H$5:$H$24) | C10: =IF(B10=0,"",D10/B10) | D10: =SUMIF('09_Detalle'!$F$5:$F$24,A10,'09_Detalle'!$K$5:$K$24) | E10: Sí
A11: Más de 360 días | B11: =SUMIF('09_Detalle'!$F$5:$F$24,A11,'09_Detalle'!$H$5:$H$24) | C11: =IF(B11=0,"",D11/B11) | D11: =SUMIF('09_Detalle'!$F$5:$F$24,A11,'09_Detalle'!$K$5:$K$24) | E11: Sí
A12: TOTAL | B12: =SUM(B5:B11) | D12: =SUM(D5:D11)
A14: ⓘ Cómo se calcula esta hoja
A15: Columna | B15: Fórmula (Excel) | C15: Cómo se calcula (sencillo) | D15: Ejemplo con números reales | E15: De dónde viene | F15: Norma
A16: Importe en libros bruto | B16: '=SUMIF('09_Detalle'!$F$5:$F$24,A5,'09_Detalle'!$H$5:$H$24) | C16: Suma el saldo de todas las facturas del detalle (hoja 09) que caen en este tramo de mora, sin importar el segmento. | D16: Fila 1: SUMIF([«Tramo» de «Detalle por factura», 20 filas]; «Corriente / por vencer»; [«Saldo» de «Detalle por factura», 20 filas]) → 90.377,19 | E16: «Tramo de mora» (esta hoja), hoja «Detalle por factura» | F16: —
A17: Tasa esperada promedio | B17: '=IF(B5=0,"",D5/B5) | C17: Divide la pérdida esperada del tramo para su importe en libros bruto: es la tasa promedio del tramo. Si el tramo no tiene saldo, queda en blanco. | D17: Fila 1: IF(90.377,19=0; ""; 0,00/90.377,19) → 0,00 % | E17: «Importe en libros bruto» (esta hoja), «Pérdida esperada» (esta hoja) | F17: —
A18: Pérdida esperada | B18: '=SUMIF('09_Detalle'!$F$5:$F$24,A5,'09_Detalle'!$K$5:$K$24) | C18: Suma la pérdida esperada de todas las facturas del detalle (hoja 09) que caen en este tramo de mora, de todos los segmentos. | D18: Fila 1: SUMIF([«Tramo» de «Detalle por factura», 20 filas]; «Corriente / por vencer»; [«Pérdida esperada» de «Detalle por factura», 20 filas]) → 0,00 | E18: «Tramo de mora» (esta hoja), hoja «Detalle por factura» | F18: —

Sheet 06_Movimiento
A1: Movimiento de la provisión (NIIF 7 35H) | H1: ⟵ Inicio | I1: ◀ Anterior | J1: Siguiente ▶
A2: Pérdida crediticia esperada · enfoque simplificado (NIIF 9) · Cliente de muestra S.A. · corte 2025-12-31
A4: Concepto | B4: Importe
A5: Provisión al inicio del ejercicio | B5: ='07_Fiscal'!$B$8
A6: (−) Castigos del ejercicio (5.4.4) | B6: ='07_Fiscal'!$B$9
A7: (+) Dotación neta / (−) reversión del ejercicio | B7: ='07_Fiscal'!$B$10
A8: Provisión al cierre = pérdida crediticia esperada | B8: =B5-B6+B7
A10: ⓘ Cómo se calcula esta hoja
A11: Columna | B11: Fórmula (Excel) | C11: Cómo se calcula (sencillo) | D11: Ejemplo con números reales | E11: De dónde viene | F11: Norma
A12: Importe | B12: '='07_Fiscal'!$B$8 | C12: Trae la provisión inicial, los castigos y la dotación neta de la hoja 07 (Fiscal e impuesto diferido); la última fila parte de la provisión inicial, resta los castigos y suma la dotación, y debe igualar la pérdida esperada al cierre. | D12: Fila 1: 0,00 → 0,00 | E12: hoja «Fiscal e impuesto diferido» | F12: —

Sheet 07_Fiscal
A1: Fiscal e impuesto diferido | H1: ⟵ Inicio | I1: ◀ Anterior | J1: Siguiente ▶
A2: Pérdida crediticia esperada · enfoque simplificado (NIIF 9) · Cliente de muestra S.A. · corte 2025-12-31
A4: Concepto | B4: Importe
A5: Cartera total al corte | B5: =SUM('09_Detalle'!$H$5:$H$24)
A6: Cartera corriente (créditos del ejercicio) | B6: =SUMIF('09_Detalle'!$E$5:$E$24,"<=0",'09_Detalle'!$H$5:$H$24)
A7: Pérdida crediticia esperada al cierre | B7: =SUM('09_Detalle'!$K$5:$K$24)
A8: Provisión al inicio del ejercicio | B8: ='02_Parametros'!B17
A9: Castigos del ejercicio | B9: =SUM('11_Castigos'!$C$5:$C$7)
A10: Dotación neta del ejercicio | B10: ='07_Fiscal'!$B$7-'07_Fiscal'!$B$8+'07_Fiscal'!$B$9
A11: Límite anual (% sobre la cartera corriente) | B11: ='07_Fiscal'!$B$6*'02_Parametros'!$B$18/100
A12: Límite acumulado (% sobre la cartera total) | B12: ='07_Fiscal'!$B$5*'02_Parametros'!$B$19/100
A13: Provisión fiscal acumulada anterior (estimada) | B13: =MIN('07_Fiscal'!$B$8,'07_Fiscal'!$B$12)
A14: Margen acumulado disponible | B14: =MAX('07_Fiscal'!$B$12-'07_Fiscal'!$B$13,0)
A15: Gasto deducible | B15: =MAX(MIN(MAX('07_Fiscal'!$B$10,0),'07_Fiscal'!$B$11,'07_Fiscal'!$B$14),0)
A16: Gasto no deducible | B16: =MAX(MAX('07_Fiscal'!$B$10,0)-'07_Fiscal'!$B$15,0)
A17: Provisión fiscal acumulada al cierre | B17: ='07_Fiscal'!$B$13+'07_Fiscal'!$B$15
A18: Diferencia temporaria al cierre | B18: =MAX('07_Fiscal'!$B$7-'07_Fiscal'!$B$17,0)
A19: Activo por impuesto diferido al cierre | B19: ='07_Fiscal'!$B$18*'02_Parametros'!$B$20/100
A20: Activo por impuesto diferido inicial | B20: =MAX('07_Fiscal'!$B$8-'07_Fiscal'!$B$13,0)*'02_Parametros'!$B$20/100
A21: Movimiento del diferido | B21: ='07_Fiscal'!$B$19-'07_Fiscal'!$B$20
A23: ⓘ Cómo se calcula esta hoja
A24: Columna | B24: Fórmula (Excel) | C24: Cómo se calcula (sencillo) | D24: Ejemplo con números reales | E24: De dónde viene | F24: Norma
A25: Importe | B25: '=SUM('09_Detalle'!$H$5:$H$24) | C25: Cada concepto tiene su propio cálculo: cartera, parte corriente y pérdida esperada se suman del detalle (hoja 09); la provisión inicial viene de la hoja 02 (Parámetros) y los castigos de la hoja 11; la dotación es pérdida esperada − provisión inicial + castigos; los límites y el diferido aplican los porcentajes de la hoja 02; el resto combina las filas anteriores de esta hoja. | D25: Fila 1: SUM([«Saldo» de «Detalle por factura», 20 filas]) → 167.059,86 | E25: hoja «Detalle por factura» | F25: —

Sheet 08_Asientos
A1: Asientos propuestos | H1: ⟵ Inicio | I1: ◀ Anterior | J1: Siguiente ▶
A2: Pérdida crediticia esperada · enfoque simplificado (NIIF 9) · Cliente de muestra S.A. · corte 2025-12-31
A4: Asiento | B4: Cuenta | C4: Debe | D4: Haber
A5: 1 · Pérdida crediticia esperada del ejercicio | B5: Gasto por pérdidas crediticias esperadas | C5: =ABS('07_Fiscal'!$B$10)
B6: (-) Provisión por pérdidas crediticias esperadas | D6: =ABS('07_Fiscal'!$B$10)
A7: 2 · Castigos del ejercicio (5.4.4) | B7: (-) Provisión por pérdidas crediticias esperadas | C7: ='07_Fiscal'!$B$9
B8: Cuentas por cobrar comerciales | D8: ='07_Fiscal'!$B$9
A9: 3 · Activo por impuesto diferido | B9: Activo por impuesto diferido | C9: =ABS('07_Fiscal'!$B$21)
B10: Ingreso por impuesto a la renta diferido | D10: =ABS('07_Fiscal'!$B$21)
A12: ⓘ Cómo se calcula esta hoja
A13: Columna | B13: Fórmula (Excel) | C13: Cómo se calcula (sencillo) | D13: Ejemplo con números reales | E13: De dónde viene | F13: Norma
A14: Debe | B14: '=ABS('07_Fiscal'!$B$10) | C14: Toma el importe del asiento de la hoja 07 (Fiscal e impuesto diferido): la dotación neta y el movimiento del diferido en valor absoluto, y los castigos del ejercicio. | D14: Fila 1: ABS(30.225,13) → 30.225,13 | E14: hoja «Fiscal e impuesto diferido» | F14: —
A15: Haber | B15: '=ABS('07_Fiscal'!$B$10) | C15: Lleva a la contrapartida el mismo importe del asiento, tomado de la hoja 07 (Fiscal e impuesto diferido), para que debe y haber cuadren. | D15: Fila 2: ABS(30.225,13) → 30.225,13 | E15: hoja «Fiscal e impuesto diferido» | F15: —

Sheet 09_Detalle
A1: Detalle por factura | H1: ⟵ Inicio | I1: ◀ Anterior | J1: Siguiente ▶
A2: Pérdida crediticia esperada · enfoque simplificado (NIIF 9) · Cliente de muestra S.A. · corte 2025-12-31
A4: Factura | B4: Cliente | C4: Segmento | D4: Vencimiento | E4: Días de mora | F4: Tramo | G4: Clave | H4: Saldo | I4: Tasa individual (%) | J4: Tasa aplicada | K4: Pérdida esperada | L4: En impago
A5: 001-001-000001009 | B5: Vialidad Norte S.A. | C5: General | D5: 45203 | E5: =IF(D5="","",'02_Parametros'!$B$5-D5) | F5: =IF(E5="","",IF(E5<=0,"Corriente / por vencer",IF(E5<=30,"1 a 30 días",IF(E5<=60,"31 a 60 días",IF(E5<=90,"61 a 90 días",IF(E5<=180,"91 a 180 días",IF(E5<=360,"181 a 360 días","Más de 360 días"))))))) | G5: =C5&"|"&F5 | H5: 2266.21 | J5: =IF(I5<>"",I5/100,IF(ISNA(MATCH(G5,'04_Matriz_provisiones'!$C$5:$C$11,0)),"",IF(INDEX('04_Matriz_provisiones'!$H$5:$H$11,MATCH(G5,'04_Matriz_provisiones'!$C$5:$C$11,0))="","",INDEX('04_Matriz_provisiones'!$H$5:$H$11,MATCH(G5,'04_Matriz_provisiones'!$C$5:$C$11,0))))) | K5: =IF(J5="","",MAX(H5*J5/(1+'02_Parametros'!$B$7/100)^('02_Parametros'!$B$8/12),0)) | L5: =IF(E5="","",IF(E5>90,"Sí","No"))
A6: 001-001-000001011 | B6: Obras Civiles Pacífico S.A. | C6: General | D6: 45051 | E6: =IF(D6="","",'02_Parametros'!$B$5-D6) | F6: =IF(E6="","",IF(E6<=0,"Corriente / por vencer",IF(E6<=30,"1 a 30 días",IF(E6<=60,"31 a 60 días",IF(E6<=90,"61 a 90 días",IF(E6<=180,"91 a 180 días",IF(E6<=360,"181 a 360 días","Más de 360 días"))))))) | G6: =C6&"|"&F6 | H6: 4342.93 | J6: =IF(I6<>"",I6/100,IF(ISNA(MATCH(G6,'04_Matriz_provisiones'!$C$5:$C$11,0)),"",IF(INDEX('04_Matriz_provisiones'!$H$5:$H$11,MATCH(G6,'04_Matriz_provisiones'!$C$5:$C$11,0))="","",INDEX('04_Matriz_provisiones'!$H$5:$H$11,MATCH(G6,'04_Matriz_provisiones'!$C$5:$C$11,0))))) | K6: =IF(J6="","",MAX(H6*J6/(1+'02_Parametros'!$B$7/100)^('02_Parametros'!$B$8/12),0)) | L6: =IF(E6="","",IF(E6>90,"Sí","No"))
A7: 001-001-000001021 | B7: Minera Austral S.A. | C7: General | D7: 45387 | E7: =IF(D7="","",'02_Parametros'!$B$5-D7) | F7: =IF(E7="","",IF(E7<=0,"Corriente / por vencer",IF(E7<=30,"1 a 30 días",IF(E7<=60,"31 a 60 días",IF(E7<=90,"61 a 90 días",IF(E7<=180,"91 a 180 días",IF(E7<=360,"181 a 360 días","Más de 360 días"))))))) | G7: =C7&"|"&F7 | H7: 1375.09 | J7: =IF(I7<>"",I7/100,IF(ISNA(MATCH(G7,'04_Matriz_provisiones'!$C$5:$C$11,0)),"",IF(INDEX('04_Matriz_provisiones'!$H$5:$H$11,MATCH(G7,'04_Matriz_provisiones'!$C$5:$C$11,0))="","",INDEX('04_Matriz_provisiones'!$H$5:$H$11,MATCH(G7,'04_Matriz_provisiones'!$C$5:$C$11,0))))) | K7: =IF(J7="","",MAX(H7*J7/(1+'02_Parametros'!$B$7/100)^('02_Parametros'!$B$8/12),0)) | L7: =IF(E7="","",IF(E7>90,"Sí","No"))
A8: 001-001-000001022 | B8: Vialidad Norte S.A. | C8: General | D8: 45394 | E8: =IF(D8="","",'02_Parametros'!$B$5-D8) | F8: =IF(E8="","",IF(E8<=0,"Corriente / por vencer",IF(E8<=30,"1 a 30 días",IF(E8<=60,"31 a 60 días",IF(E8<=90,"61 a 90 días",IF(E8<=180,"91 a 180 días",IF(E8<=360,"181 a 360 días","Más de 360 días"))))))) | G8: =C8&"|"&F8 | H8: 7172.35 | J8: =IF(I8<>"",I8/100,IF(ISNA(MATCH(G8,'04_Matriz_provisiones'!$C$5:$C$11,0)),"",IF(INDEX('04_Matriz_provisiones'!$H$5:$H$11,MATCH(G8,'04_Matriz_provisiones'!$C$5:$C$11,0))="","",INDEX('04_Matriz_provisiones'!$H$5:$H$11,MATCH(G8,'04_Matriz_provisiones'!$C$5:$C$11,0))))) | K8: =IF(J8="","",MAX(H8*J8/(1+'02_Parametros'!$B$7/100)^('02_Parametros'!$B$8/12),0)) | L8: =IF(E8="","",IF(E8>90,"Sí","No"))
A9: 001-001-000001023 | B9: Hidrosur Cía. Ltda. | C9: General | D9: 45571 | E9: =IF(D9="","",'02_Parametros'!$B$5-D9) | F9: =IF(E9="","",IF(E9<=0,"Corriente / por vencer",IF(E9<=30,"1 a 30 días",IF(E9<=60,"31 a 60 días",IF(E9<=90,"61 a 90 días",IF(E9<=180,"91 a 180 días",IF(E9<=360,"181 a 360 días","Más de 360 días"))))))) | G9: =C9&"|"&F9 | H9: 1787.01 | J9: =IF(I9<>"",I9/100,IF(ISNA(MATCH(G9,'04_Matriz_provisiones'!$C$5:$C$11,0)),"",IF(INDEX('04_Matriz_provisiones'!$H$5:$H$11,MATCH(G9,'04_Matriz_provisiones'!$C$5:$C$11,0))="","",INDEX('04_Matriz_provisiones'!$H$5:$H$11,MATCH(G9,'04_Matriz_provisiones'!$C$5:$C$11,0))))) | K9: =IF(J9="","",MAX(H9*J9/(1+'02_Parametros'!$B$7/100)^('02_Parametros'!$B$8/12),0)) | L9: =IF(E9="","",IF(E9>90,"Sí","No"))
A10: 001-001-000001024 | B10: Obras Civiles Pacífico S.A. | C10: General | D10: 45621 | E10: =IF(D10="","",'02_Parametros'!$B$5-D10) | F10: =IF(E10="","",IF(E10<=0,"Corriente / por vencer",IF(E10<=30,"1 a 30 días",IF(E10<=60,"31 a 60 días",IF(E10<=90,"61 a 90 días",IF(E10<=180,"91 a 180 días",IF(E10<=360,"181 a 360 días","Más de 360 días"))))))) | G10: =C10&"|"&F10 | H10: 5514.61 | J10: =IF(I10<>"",I10/100,IF(ISNA(MATCH(G10,'04_Matriz_provisiones'!$C$5:$C$11,0)),"",IF(INDEX('04_Matriz_provisiones'!$H$5:$H$11,MATCH(G10,'04_Matriz_provisiones'!$C$5:$C$11,0))="","",INDEX('04_Matriz_provisiones'!$H$5:$H$11,MATCH(G10,'04_Matriz_provisiones'!$C$5:$C$11,0))))) | K10: =IF(J10="","",MAX(H10*J10/(1+'02_Parametros'!$B$7/100)^('02_Parametros'!$B$8/12),0)) | L10: =IF(E10="","",IF(E10>90,"Sí","No"))
A11: 001-001-000001027 | B11: Minera Austral S.A. | C11: General | D11: 45611 | E11: =IF(D11="","",'02_Parametros'!$B$5-D11) | F11: =IF(E11="","",IF(E11<=0,"Corriente / por vencer",IF(E11<=30,"1 a 30 días",IF(E11<=60,"31 a 60 días",IF(E11<=90,"61 a 90 días",IF(E11<=180,"91 a 180 días",IF(E11<=360,"181 a 360 días","Más de 360 días"))))))) | G11: =C11&"|"&F11 | H11: 442.06 | J11: =IF(I11<>"",I11/100,IF(ISNA(MATCH(G11,'04_Matriz_provisiones'!$C$5:$C$11,0)),"",IF(INDEX('04_Matriz_provisiones'!$H$5:$H$11,MATCH(G11,'04_Matriz_provisiones'!$C$5:$C$11,0))="","",INDEX('04_Matriz_provisiones'!$H$5:$H$11,MATCH(G11,'04_Matriz_provisiones'!$C$5:$C$11,0))))) | K11: =IF(J11="","",MAX(H11*J11/(1+'02_Parametros'!$B$7/100)^('02_Parametros'!$B$8/12),0)) | L11: =IF(E11="","",IF(E11>90,"Sí","No"))
A12: 001-001-000001028 | B12: Vialidad Norte S.A. | C12: General | D12: 45435 | E12: =IF(D12="","",'02_Parametros'!$B$5-D12) | F12: =IF(E12="","",IF(E12<=0,"Corriente / por vencer",IF(E12<=30,"1 a 30 días",IF(E12<=60,"31 a 60 días",IF(E12<=90,"61 a 90 días",IF(E12<=180,"91 a 180 días",IF(E12<=360,"181 a 360 días","Más de 360 días"))))))) | G12: =C12&"|"&F12 | H12: 8659.56 | J12: =IF(I12<>"",I12/100,IF(ISNA(MATCH(G12,'04_Matriz_provisiones'!$C$5:$C$11,0)),"",IF(INDEX('04_Matriz_provisiones'!$H$5:$H$11,MATCH(G12,'04_Matriz_provisiones'!$C$5:$C$11,0))="","",INDEX('04_Matriz_provisiones'!$H$5:$H$11,MATCH(G12,'04_Matriz_provisiones'!$C$5:$C$11,0))))) | K12: =IF(J12="","",MAX(H12*J12/(1+'02_Parametros'!$B$7/100)^('02_Parametros'!$B$8/12),0)) | L12: =IF(E12="","",IF(E12>90,"Sí","No"))
A13: 001-001-000001029 | B13: Vialidad Norte S.A. | C13: General | D13: 46023 | E13: =IF(D13="","",'02_Parametros'!$B$5-D13) | F13: =IF(E13="","",IF(E13<=0,"Corriente / por vencer",IF(E13<=30,"1 a 30 días",IF(E13<=60,"31 a 60 días",IF(E13<=90,"61 a 90 días",IF(E13<=180,"91 a 180 días",IF(E13<=360,"181 a 360 días","Más de 360 días"))))))) | G13: =C13&"|"&F13 | H13: 7754.65 | J13: =IF(I13<>"",I13/100,IF(ISNA(MATCH(G13,'04_Matriz_provisiones'!$C$5:$C$11,0)),"",IF(INDEX('04_Matriz_provisiones'!$H$5:$H$11,MATCH(G13,'04_Matriz_provisiones'!$C$5:$C$11,0))="","",INDEX('04_Matriz_provisiones'!$H$5:$H$11,MATCH(G13,'04_Matriz_provisiones'!$C$5:$C$11,0))))) | K13: =IF(J13="","",MAX(H13*J13/(1+'02_Parametros'!$B$7/100)^('02_Parametros'!$B$8/12),0)) | L13: =IF(E13="","",IF(E13>90,"Sí","No"))
A14: 001-001-000001030 | B14: Hidrosur Cía. Ltda. | C14: General | D14: 46034 | E14: =IF(D14="","",'02_Parametros'!$B$5-D14) | F14: =IF(E14="","",IF(E14<=0,"Corriente / por vencer",IF(E14<=30,"1 a 30 días",IF(E14<=60,"31 a 60 días",IF(E14<=90,"61 a 90 días",IF(E14<=180,"91 a 180 días",IF(E14<=360,"181 a 360 días","Más de 360 días"))))))) | G14: =C14&"|"&F14 | H14: 29394.77 | J14: =IF(I14<>"",I14/100,IF(ISNA(MATCH(G14,'04_Matriz_provisiones'!$C$5:$C$11,0)),"",IF(INDEX('04_Matriz_provisiones'!$H$5:$H$11,MATCH(G14,'04_Matriz_provisiones'!$C$5:$C$11,0))="","",INDEX('04_Matriz_provisiones'!$H$5:$H$11,MATCH(G14,'04_Matriz_provisiones'!$C$5:$C$11,0))))) | K14: =IF(J14="","",MAX(H14*J14/(1+'02_Parametros'!$B$7/100)^('02_Parametros'!$B$8/12),0)) | L14: =IF(E14="","",IF(E14>90,"Sí","No"))
A15: 001-001-000001031 | B15: Obras Civiles Pacífico S.A. | C15: General | D15: 46026 | E15: =IF(D15="","",'02_Parametros'!$B$5-D15) | F15: =IF(E15="","",IF(E15<=0,"Corriente / por vencer",IF(E15<=30,"1 a 30 días",IF(E15<=60,"31 a 60 días",IF(E15<=90,"61 a 90 días",IF(E15<=180,"91 a 180 días",IF(E15<=360,"181 a 360 días","Más de 360 días"))))))) | G15: =C15&"|"&F15 | H15: 7119.93 | J15: =IF(I15<>"",I15/100,IF(ISNA(MATCH(G15,'04_Matriz_provisiones'!$C$5:$C$11,0)),"",IF(INDEX('04_Matriz_provisiones'!$H$5:$H$11,MATCH(G15,'04_Matriz_provisiones'!$C$5:$C$11,0))="","",INDEX('04_Matriz_provisiones'!$H$5:$H$11,MATCH(G15,'04_Matriz_provisiones'!$C$5:$C$11,0))))) | K15: =IF(J15="","",MAX(H15*J15/(1+'02_Parametros'!$B$7/100)^('02_Parametros'!$B$8/12),0)) | L15: =IF(E15="","",IF(E15>90,"Sí","No"))
A16: 001-001-000001032 | B16: Constructora Andina S.A. | C16: General | D16: 46049 | E16: =IF(D16="","",'02_Parametros'!$B$5-D16) | F16: =IF(E16="","",IF(E16<=0,"Corriente / por vencer",IF(E16<=30,"1 a 30 días",IF(E16<=60,"31 a 60 días",IF(E16<=90,"61 a 90 días",IF(E16<=180,"91 a 180 días",IF(E16<=360,"181 a 360 días","Más de 360 días"))))))) | G16: =C16&"|"&F16 | H16: 28854.13 | J16: =IF(I16<>"",I16/100,IF(ISNA(MATCH(G16,'04_Matriz_provisiones'!$C$5:$C$11,0)),"",IF(INDEX('04_Matriz_provisiones'!$H$5:$H$11,MATCH(G16,'04_Matriz_provisiones'!$C$5:$C$11,0))="","",INDEX('04_Matriz_provisiones'!$H$5:$H$11,MATCH(G16,'04_Matriz_provisiones'!$C$5:$C$11,0))))) | K16: =IF(J16="","",MAX(H16*J16/(1+'02_Parametros'!$B$7/100)^('02_Parametros'!$B$8/12),0)) | L16: =IF(E16="","",IF(E16>90,"Sí","No"))
... A24: 001-001-000001042 | B24: Hidrosur Cía. Ltda. | C24: General | D24: 45987 | E24: =IF(D24="","",'02_Parametros'!$B$5-D24) | F24: =IF(E24="","",IF(E24<=0,"Corriente / por vencer",IF(E24<=30,"1 a 30 días",IF(E24<=60,"31 a 60 días",IF(E24<=90,"61 a 90 días",IF(E24<=180,"91 a 180 días",IF(E24<=360,"181 a 360 días","Más de 360 días"))))))) | G24: =C24&"|"&F24 | H24: 691.42 | J24: =IF(I24<>"",I24/100,IF(ISNA(MATCH(G24,'04_Matriz_provisiones'!$C$5:$C$11,0)),"",IF(INDEX('04_Matriz_provisiones'!$H$5:$H$11,MATCH(G24,'04_Matriz_provisiones'!$C$5:$C$11,0))="","",INDEX('04_Matriz_provisiones'!$H$5:$H$11,MATCH(G24,'04_Matriz_provisiones'!$C$5:$C$11,0))))) | K24: =IF(J24="","",MAX(H24*J24/(1+'02_Parametros'!$B$7/100)^('02_Parametros'!$B$8/12),0)) | L24: =IF(E24="","",IF(E24>90,"Sí","No"))
A25: TOTAL | H25: =SUM(H5:H24) | K25: =SUM(K5:K24)
A27: ⓘ Cómo se calcula esta hoja
A28: Columna | B28: Fórmula (Excel) | C28: Cómo se calcula (sencillo) | D28: Ejemplo con números reales | E28: De dónde viene | F28: Norma
A29: Días de mora | B29: '=IF(D5="","",'02_Parametros'!$B$5-D5) | C29: Resta la fecha de vencimiento de la fecha de corte de la hoja 02 (Parámetros); si la factura no tiene vencimiento, queda en blanco. Cero o negativo significa que aún no vence. | D29: Fila 1: IF(«2023-10-04»=""; ""; «2025-12-31»-«2023-10-04») → 819 | E29: «Vencimiento» (esta hoja), hoja «Parámetros» | F29: —
A30: Tramo | B30: '=IF(E5="","",IF(E5<=0,"Corriente / por vencer",IF(E5<=30,"1 a 30 días",IF(E5<=60,"31 a 60 días",IF(E5<=90,"61 a 90 días",IF(E5<=180,"91 a 180 días",IF(E5<=360,"181 a 360 días","Más de 360 días"))))))) | C30: Clasifica la factura por sus días de mora: corriente/por vencer si no tiene mora, luego 1 a 30, 31 a 60, 61 a 90, 91 a 180, 181 a 360 y más de 360 días. Sin días de mora queda en blanco. | D30: Fila 1: IF(819=""; ""; IF(819<=0; "Corriente / por vencer"; IF(819<=30; "1 a 30 días"; IF(819<=60; "31 a 60 días"; IF(819<=90; "61 a 90 días"; IF(819<=180; "91 a 180 días"; IF(819<=360; "181 a 360 días"; "Más de 360 días"))))))) → Más de 360 días | E30: «Días de mora» (esta hoja) | F30: —
A31: Clave | B31: '=C5&"|"&F5 | C31: Une el segmento y el tramo de la factura (segmento|tramo) para buscar su tasa en la hoja 04 (Matriz de provisiones). | D31: Fila 1: «General»&"|"&«Más de 360 días» → General|Más de 360 días | E31: «Segmento» (esta hoja), «Tramo» (esta hoja) | F31: —
A32: Tasa aplicada | B32: '=IF(I5<>"",I5/100,IF(ISNA(MATCH(G5,'04_Matriz_provisiones'!$C$5:$C$11,0)),"",IF(INDEX('04_Matriz_provisiones'!$H$5:$H$11,MATCH(G5,'04_Matriz_provisiones'!$C$5:$C$11,0))="","",INDEX('04_Matriz_provisiones'!$H$5:$H$11,MATCH(G5,'04_Matriz_provisiones'!$C$5:$C$11,0))))) | C32: Si la factura tiene tasa individual, usa esa tasa dividida para 100; si no, busca la tasa aplicada de su segmento y tramo en la hoja 04 (Matriz de provisiones). Si no la encuentra o está vacía, queda en blanco. | D32: Fila 1: IF((vacío)<>""; (vacío)/100; IF(ISNA(MATCH(«General|Más de 360 días»; [«Clave» de «Matriz de provisiones», 7 filas]; 0)); ""; IF(INDEX([«Tasa aplicada» de «Matriz de provisiones», 7 filas]; MATCH(«General|Más de 360 días»; [«Clave» de «Matriz de provisiones», 7 filas]; 0))=""; ""; INDEX([«Tasa aplicada» de «Matriz de provisiones», 7 filas]; MATCH(«General|Más de 360 días»; [«Clave» de «Matriz de provisiones», 7 filas]; 0))))) → 63,29 % | E32: «Tasa individual (%)» (esta hoja), «Clave» (esta hoja), hoja «Matriz de provisiones» | F32: —
A33: Pérdida esperada | B33: '=IF(J5="","",MAX(H5*J5/(1+'02_Parametros'!$B$7/100)^('02_Parametros'!$B$8/12),0)) | C33: Multiplica el saldo por la tasa aplicada y lo descuenta con la tasa y el plazo de cobro de la hoja 02 (Parámetros); nunca es negativa. Sin tasa, queda en blanco. | D33: Fila 1: IF(63,29 %=""; ""; MAX(2.266,21*63,29 %/(1+0,00/100)^(12,00/12); 0)) → 1.434,30 | E33: «Tasa aplicada» (esta hoja), «Saldo» (esta hoja), hoja «Parámetros» | F33: —
A34: En impago | B34: '=IF(E5="","",IF(E5>90,"Sí","No")) | C34: Marca «Sí» si la factura tiene más de 90 días de mora y «No» en caso contrario; sin días de mora queda en blanco. | D34: Fila 1: IF(819=""; ""; IF(819>90; "Sí"; "No")) → Sí | E34: «Días de mora» (esta hoja) | F34: —

Sheet 10_Cartera_anterior
A1: Cartera del corte anterior | H1: ⟵ Inicio | I1: ◀ Anterior | J1: Siguiente ▶
A2: Pérdida crediticia esperada · enfoque simplificado (NIIF 9) · Cliente de muestra S.A. · corte 2025-12-31
A4: Factura | B4: Cliente | C4: Segmento | D4: Vencimiento | E4: Días de mora | F4: Tramo | G4: Clave | H4: Saldo | I4: Sigue impago al corte | J4: Castigado | K4: Pérdida observada
A5: 001-001-000001008 | B5: Minera Austral S.A. | C5: General | D5: 45112 | E5: =IF(D5="","",'02_Parametros'!$B$6-D5) | F5: =IF(E5="","",IF(E5<=0,"Corriente / por vencer",IF(E5<=30,"1 a 30 días",IF(E5<=60,"31 a 60 días",IF(E5<=90,"61 a 90 días",IF(E5<=180,"91 a 180 días",IF(E5<=360,"181 a 360 días","Más de 360 días"))))))) | G5: =C5&"|"&F5 | H5: 2401.38 | I5: =MAX(0,MIN(SUMIF('09_Detalle'!$A$5:$A$24,A5,'09_Detalle'!$H$5:$H$24),H5)) | J5: =MAX(0,MIN(SUMIF('11_Castigos'!$A$5:$A$7,A5,'11_Castigos'!$C$5:$C$7),H5-I5)) | K5: =I5+J5
A6: 001-001-000001009 | B6: Vialidad Norte S.A. | C6: General | D6: 45203 | E6: =IF(D6="","",'02_Parametros'!$B$6-D6) | F6: =IF(E6="","",IF(E6<=0,"Corriente / por vencer",IF(E6<=30,"1 a 30 días",IF(E6<=60,"31 a 60 días",IF(E6<=90,"61 a 90 días",IF(E6<=180,"91 a 180 días",IF(E6<=360,"181 a 360 días","Más de 360 días"))))))) | G6: =C6&"|"&F6 | H6: 4985.66 | I6: =MAX(0,MIN(SUMIF('09_Detalle'!$A$5:$A$24,A6,'09_Detalle'!$H$5:$H$24),H6)) | J6: =MAX(0,MIN(SUMIF('11_Castigos'!$A$5:$A$7,A6,'11_Castigos'!$C$5:$C$7),H6-I6)) | K6: =I6+J6
A7: 001-001-000001010 | B7: Hidrosur Cía. Ltda. | C7: General | D7: 45119 | E7: =IF(D7="","",'02_Parametros'!$B$6-D7) | F7: =IF(E7="","",IF(E7<=0,"Corriente / por vencer",IF(E7<=30,"1 a 30 días",IF(E7<=60,"31 a 60 días",IF(E7<=90,"61 a 90 días",IF(E7<=180,"91 a 180 días",IF(E7<=360,"181 a 360 días","Más de 360 días"))))))) | G7: =C7&"|"&F7 | H7: 1243.47 | I7: =MAX(0,MIN(SUMIF('09_Detalle'!$A$5:$A$24,A7,'09_Detalle'!$H$5:$H$24),H7)) | J7: =MAX(0,MIN(SUMIF('11_Castigos'!$A$5:$A$7,A7,'11_Castigos'!$C$5:$C$7),H7-I7)) | K7: =I7+J7
A8: 001-001-000001011 | B8: Obras Civiles Pacífico S.A. | C8: General | D8: 45051 | E8: =IF(D8="","",'02_Parametros'!$B$6-D8) | F8: =IF(E8="","",IF(E8<=0,"Corriente / por vencer",IF(E8<=30,"1 a 30 días",IF(E8<=60,"31 a 60 días",IF(E8<=90,"61 a 90 días",IF(E8<=180,"91 a 180 días",IF(E8<=360,"181 a 360 días","Más de 360 días"))))))) | G8: =C8&"|"&F8 | H8: 9554.44 | I8: =MAX(0,MIN(SUMIF('09_Detalle'!$A$5:$A$24,A8,'09_Detalle'!$H$5:$H$24),H8)) | J8: =MAX(0,MIN(SUMIF('11_Castigos'!$A$5:$A$7,A8,'11_Castigos'!$C$5:$C$7),H8-I8)) | K8: =I8+J8
A9: 001-001-000001014 | B9: Minera Austral S.A. | C9: General | D9: 45086 | E9: =IF(D9="","",'02_Parametros'!$B$6-D9) | F9: =IF(E9="","",IF(E9<=0,"Corriente / por vencer",IF(E9<=30,"1 a 30 días",IF(E9<=60,"31 a 60 días",IF(E9<=90,"61 a 90 días",IF(E9<=180,"91 a 180 días",IF(E9<=360,"181 a 360 días","Más de 360 días"))))))) | G9: =C9&"|"&F9 | H9: 2386.85 | I9: =MAX(0,MIN(SUMIF('09_Detalle'!$A$5:$A$24,A9,'09_Detalle'!$H$5:$H$24),H9)) | J9: =MAX(0,MIN(SUMIF('11_Castigos'!$A$5:$A$7,A9,'11_Castigos'!$C$5:$C$7),H9-I9)) | K9: =I9+J9
A10: 001-001-000001015 | B10: Minera Austral S.A. | C10: General | D10: 45679 | E10: =IF(D10="","",'02_Parametros'!$B$6-D10) | F10: =IF(E10="","",IF(E10<=0,"Corriente / por vencer",IF(E10<=30,"1 a 30 días",IF(E10<=60,"31 a 60 días",IF(E10<=90,"61 a 90 días",IF(E10<=180,"91 a 180 días",IF(E10<=360,"181 a 360 días","Más de 360 días"))))))) | G10: =C10&"|"&F10 | H10: 15515.21 | I10: =MAX(0,MIN(SUMIF('09_Detalle'!$A$5:$A$24,A10,'09_Detalle'!$H$5:$H$24),H10)) | J10: =MAX(0,MIN(SUMIF('11_Castigos'!$A$5:$A$7,A10,'11_Castigos'!$C$5:$C$7),H10-I10)) | K10: =I10+J10
A11: 001-001-000001016 | B11: Vialidad Norte S.A. | C11: General | D11: 45689 | E11: =IF(D11="","",'02_Parametros'!$B$6-D11) | F11: =IF(E11="","",IF(E11<=0,"Corriente / por vencer",IF(E11<=30,"1 a 30 días",IF(E11<=60,"31 a 60 días",IF(E11<=90,"61 a 90 días",IF(E11<=180,"91 a 180 días",IF(E11<=360,"181 a 360 días","Más de 360 días"))))))) | G11: =C11&"|"&F11 | H11: 10351.94 | I11: =MAX(0,MIN(SUMIF('09_Detalle'!$A$5:$A$24,A11,'09_Detalle'!$H$5:$H$24),H11)) | J11: =MAX(0,MIN(SUMIF('11_Castigos'!$A$5:$A$7,A11,'11_Castigos'!$C$5:$C$7),H11-I11)) | K11: =I11+J11
A12: 001-001-000001017 | B12: Hidrosur Cía. Ltda. | C12: General | D12: 45627 | E12: =IF(D12="","",'02_Parametros'!$B$6-D12) | F12: =IF(E12="","",IF(E12<=0,"Corriente / por vencer",IF(E12<=30,"1 a 30 días",IF(E12<=60,"31 a 60 días",IF(E12<=90,"61 a 90 días",IF(E12<=180,"91 a 180 días",IF(E12<=360,"181 a 360 días","Más de 360 días"))))))) | G12: =C12&"|"&F12 | H12: 10702.09 | I12: =MAX(0,MIN(SUMIF('09_Detalle'!$A$5:$A$24,A12,'09_Detalle'!$H$5:$H$24),H12)) | J12: =MAX(0,MIN(SUMIF('11_Castigos'!$A$5:$A$7,A12,'11_Castigos'!$C$5:$C$7),H12-I12)) | K12: =I12+J12
A13: 001-001-000001018 | B13: Obras Civiles Pacífico S.A. | C13: General | D13: 45706 | E13: =IF(D13="","",'02_Parametros'!$B$6-D13) | F13: =IF(E13="","",IF(E13<=0,"Corriente / por vencer",IF(E13<=30,"1 a 30 días",IF(E13<=60,"31 a 60 días",IF(E13<=90,"61 a 90 días",IF(E13<=180,"91 a 180 días",IF(E13<=360,"181 a 360 días","Más de 360 días"))))))) | G13: =C13&"|"&F13 | H13: 20308.18 | I13: =MAX(0,MIN(SUMIF('09_Detalle'!$A$5:$A$24,A13,'09_Detalle'!$H$5:$H$24),H13)) | J13: =MAX(0,MIN(SUMIF('11_Castigos'!$A$5:$A$7,A13,'11_Castigos'!$C$5:$C$7),H13-I13)) | K13: =I13+J13
A14: 001-001-000001019 | B14: Constructora Andina S.A. | C14: General | D14: 45612 | E14: =IF(D14="","",'02_Parametros'!$B$6-D14) | F14: =IF(E14="","",IF(E14<=0,"Corriente / por vencer",IF(E14<=30,"1 a 30 días",IF(E14<=60,"31 a 60 días",IF(E14<=90,"61 a 90 días",IF(E14<=180,"91 a 180 días",IF(E14<=360,"181 a 360 días","Más de 360 días"))))))) | G14: =C14&"|"&F14 | H14: 11294.43 | I14: =MAX(0,MIN(SUMIF('09_Detalle'!$A$5:$A$24,A14,'09_Detalle'!$H$5:$H$24),H14)) | J14: =MAX(0,MIN(SUMIF('11_Castigos'!$A$5:$A$7,A14,'11_Castigos'!$C$5:$C$7),H14-I14)) | K14: =I14+J14
A15: 001-001-000001020 | B15: Agroexport del Litoral Cía. Ltda. | C15: General | D15: 45609 | E15: =IF(D15="","",'02_Parametros'!$B$6-D15) | F15: =IF(E15="","",IF(E15<=0,"Corriente / por vencer",IF(E15<=30,"1 a 30 días",IF(E15<=60,"31 a 60 días",IF(E15<=90,"61 a 90 días",IF(E15<=180,"91 a 180 días",IF(E15<=360,"181 a 360 días","Más de 360 días"))))))) | G15: =C15&"|"&F15 | H15: 9267.41 | I15: =MAX(0,MIN(SUMIF('09_Detalle'!$A$5:$A$24,A15,'09_Detalle'!$H$5:$H$24),H15)) | J15: =MAX(0,MIN(SUMIF('11_Castigos'!$A$5:$A$7,A15,'11_Castigos'!$C$5:$C$7),H15-I15)) | K15: =I15+J15
A16: 001-001-000001021 | B16: Minera Austral S.A. | C16: General | D16: 45387 | E16: =IF(D16="","",'02_Parametros'!$B$6-D16) | F16: =IF(E16="","",IF(E16<=0,"Corriente / por vencer",IF(E16<=30,"1 a 30 días",IF(E16<=60,"31 a 60 días",IF(E16<=90,"61 a 90 días",IF(E16<=180,"91 a 180 días",IF(E16<=360,"181 a 360 días","Más de 360 días"))))))) | G16: =C16&"|"&F16 | H16: 6875.45 | I16: =MAX(0,MIN(SUMIF('09_Detalle'!$A$5:$A$24,A16,'09_Detalle'!$H$5:$H$24),H16)) | J16: =MAX(0,MIN(SUMIF('11_Castigos'!$A$5:$A$7,A16,'11_Castigos'!$C$5:$C$7),H16-I16)) | K16: =I16+J16
... A21: 001-001-000001028 | B21: Vialidad Norte S.A. | C21: General | D21: 45435 | E21: =IF(D21="","",'02_Parametros'!$B$6-D21) | F21: =IF(E21="","",IF(E21<=0,"Corriente / por vencer",IF(E21<=30,"1 a 30 días",IF(E21<=60,"31 a 60 días",IF(E21<=90,"61 a 90 días",IF(E21<=180,"91 a 180 días",IF(E21<=360,"181 a 360 días","Más de 360 días"))))))) | G21: =C21&"|"&F21 | H21: 17712.73 | I21: =MAX(0,MIN(SUMIF('09_Detalle'!$A$5:$A$24,A21,'09_Detalle'!$H$5:$H$24),H21)) | J21: =MAX(0,MIN(SUMIF('11_Castigos'!$A$5:$A$7,A21,'11_Castigos'!$C$5:$C$7),H21-I21)) | K21: =I21+J21
A22: TOTAL | H22: =SUM(H5:H21) | I22: =SUM(I5:I21) | J22: =SUM(J5:J21) | K22: =SUM(K5:K21)
A24: ⓘ Cómo se calcula esta hoja
A25: Columna | B25: Fórmula (Excel) | C25: Cómo se calcula (sencillo) | D25: Ejemplo con números reales | E25: De dónde viene | F25: Norma
A26: Días de mora | B26: '=IF(D5="","",'02_Parametros'!$B$6-D5) | C26: Resta la fecha de vencimiento de la fecha del corte anterior de la hoja 02 (Parámetros); sin vencimiento, queda en blanco. | D26: Fila 1: IF(«2023-07-05»=""; ""; «2024-12-31»-«2023-07-05») → 545 | E26: «Vencimiento» (esta hoja), hoja «Parámetros» | F26: —
A27: Tramo | B27: '=IF(E5="","",IF(E5<=0,"Corriente / por vencer",IF(E5<=30,"1 a 30 días",IF(E5<=60,"31 a 60 días",IF(E5<=90,"61 a 90 días",IF(E5<=180,"91 a 180 días",IF(E5<=360,"181 a 360 días","Más de 360 días"))))))) | C27: Clasifica la factura en su tramo de mora al corte anterior (corriente, 1 a 30, 31 a 60, 61 a 90, 91 a 180, 181 a 360 o más de 360 días). Sin días de mora queda en blanco. | D27: Fila 1: IF(545=""; ""; IF(545<=0; "Corriente / por vencer"; IF(545<=30; "1 a 30 días"; IF(545<=60; "31 a 60 días"; IF(545<=90; "61 a 90 días"; IF(545<=180; "91 a 180 días"; IF(545<=360; "181 a 360 días"; "Más de 360 días"))))))) → Más de 360 días | E27: «Días de mora» (esta hoja) | F27: —
A28: Clave | B28: '=C5&"|"&F5 | C28: Une el segmento y el tramo al corte anterior (segmento|tramo) para agruparla en la hoja 03 (Tasas históricas). | D28: Fila 1: «General»&"|"&«Más de 360 días» → General|Más de 360 días | E28: «Segmento» (esta hoja), «Tramo» (esta hoja) | F28: —
A29: Sigue impago al corte | B29: '=MAX(0,MIN(SUMIF('09_Detalle'!$A$5:$A$24,A5,'09_Detalle'!$H$5:$H$24),H5)) | C29: Busca la misma factura en el detalle actual (hoja 09) y toma su saldo, sin pasar del saldo que tenía al corte anterior ni bajar de cero: es lo que sigue sin cobrarse. | D29: Fila 1: MAX(0; MIN(SUMIF([«Factura» de «Detalle por factura», 20 filas]; «001-001-000001008»; [«Saldo» de «Detalle por factura», 20 filas]); 2.401,38)) → 0,00 | E29: «Factura» (esta hoja), «Saldo» (esta hoja), hoja «Detalle por factura» | F29: —
A30: Castigado | B30: '=MAX(0,MIN(SUMIF('11_Castigos'!$A$5:$A$7,A5,'11_Castigos'!$C$5:$C$7),H5-I5)) | C30: Suma lo castigado de la misma factura en la hoja 11 (Castigos del ejercicio), limitado al saldo anterior que no sigue impago y nunca negativo. | D30: Fila 1: MAX(0; MIN(SUMIF([«Factura» de «Castigos del ejercicio», 3 filas]; «001-001-000001008»; [«Importe castigado» de «Castigos del ejercicio», 3 filas]); 2.401,38-0,00)) → 2.401,38 | E30: «Factura» (esta hoja), «Saldo» (esta hoja), «Sigue impago al corte» (esta hoja), hoja «Castigos del ejercicio» | F30: —
A31: Pérdida observada | B31: '=I5+J5 | C31: Suma lo que sigue impago al corte y lo castigado: es lo que no se recuperó de esa factura en el año. | D31: Fila 1: 0,00+2.401,38 → 2.401,38 | E31: «Sigue impago al corte» (esta hoja), «Castigado» (esta hoja) | F31: —

Sheet 11_Castigos
A1: Castigos del ejercicio | H1: ⟵ Inicio | I1: ◀ Anterior | J1: Siguiente ▶
A2: Pérdida crediticia esperada · enfoque simplificado (NIIF 9) · Cliente de muestra S.A. · corte 2025-12-31
A4: Factura | B4: Cliente | C4: Importe castigado
A5: 001-001-000001008 | B5: Minera Austral S.A. | C5: 2401.38
A6: 001-001-000001010 | B6: Hidrosur Cía. Ltda. | C6: 1243.47
A7: 001-001-000001014 | B7: Minera Austral S.A. | C7: 2386.85
A8: TOTAL | C8: =SUM(C5:C7)

Sheet 12_Problemas
A1: Problemas encontrados | H1: ⟵ Inicio | I1: ◀ Anterior | J1: Siguiente ▶
A2: Pérdida crediticia esperada · enfoque simplificado (NIIF 9) · Cliente de muestra S.A. · corte 2025-12-31
A4: Código | B4: Descripción | C4: Importe
A5: TASA_CERO | B5: General · Corriente / por vencer: tasa 0 % sobre 90.377,19. La pérdida esperada se estima aunque la posibilidad sea muy baja (5.5.18): documente por qué es cero o fije una tasa. | C5: 90377.19
A6: TASA_CERO | B6: General · 1 a 30 días: tasa 0 % sobre 27.938,78. La pérdida esperada se estima aunque la posibilidad sea muy baja (5.5.18): documente por qué es cero o fije una tasa. | C6: 27938.78
A7: AJUSTE | B7: La pérdida esperada (24.193,43) difiere de la provisión registrada (5.816,04). | C7: 18377.39
A8: EN_IMPAGO | B8: Cartera en impago (más de 90 días, B5.5.37): 34.399,16. Evalúe castigo (5.4.4) o tasa individual. | C8: 34399.16
A9: NO_DEDUCIBLE | B9: Gasto no deducible del ejercicio: 29.321,36 (límites LRTI). | C9: 29321.36

Sheet 13_Conclusion
A1: Conclusión | H1: ⟵ Inicio | I1: ◀ Anterior | J1: Siguiente ▶
A2: Pérdida crediticia esperada · enfoque simplificado (NIIF 9) · Cliente de muestra S.A. · corte 2025-12-31
A4: Concepto | B4: Detalle
A5: Conciliación con el mayor | B5: Población None · mayor None · diferencia None
A6: Evaluación de excepciones
A7: Análisis
A8: Conclusión

Sheet 14_Control_Revision
A1: Control de revisión | H1: ⟵ Inicio | I1: ◀ Anterior
A2: Pérdida crediticia esperada · enfoque simplificado (NIIF 9) · Cliente de muestra S.A. · corte 2025-12-31
A4: Fecha | B4: Acción | C4: Estado anterior | D4: Estado nuevo | E4: Actor | F4: Comentario
