Workbook

Sheet 00_Inicio
B2: AuditConsulting Auditores Cía. Ltda. · AUDIT-IA
B4: Deterioro de cuentas por cobrar · pérdidas incurridas (PYMES)
B6: Cliente | C6: Cliente de muestra S.A. | D6: RUC | E6: 1790000000001
B7: Marco contable | C7: NIIF para las PYMES | D7: Fecha de corte | E7: 2025-12-31
B8: Preparó | C8: Ejercicio modelo | D8: Revisó | E8: Pendiente
B10: INDICADORES CLAVE
B11: Ajuste propuesto | C11: Pérdida incurrida recalculada | D11: Problemas encontrados
B12: 14932.98 | C12: 20749.02 | D12: 7
B15: IR A LA CÉDULA
B16: Carátula | C16: Programa | D16: Base técnica | E16: Resumen
B17: Parámetros | C17: Evidencia histórica | D17: Matriz de deterioro | E17: Por cliente
B18: Movimiento de la provisión | C18: Provisión según el mayor | D18: Fiscal | E18: Impuesto diferido por factura
B19: Asientos propuestos | C19: Detalle por factura | D19: Problemas encontrados | E19: Conclusión
B20: Control de revisión
B22: PANORAMA | N22: Datos de los gráficos (fórmulas a las cédulas)
N23: Cifras del resumen | O23: Importe (USD)
N24: ='01_Resumen'!A5 | O24: ='01_Resumen'!B5
N25: ='01_Resumen'!A6 | O25: ='01_Resumen'!B6
N26: ='01_Resumen'!A7 | O26: ='01_Resumen'!B7
N27: ='01_Resumen'!A8 | O27: ='01_Resumen'!B8
N28: ='01_Resumen'!A9 | O28: ='01_Resumen'!B9
N29: ='01_Resumen'!A10 | O29: ='01_Resumen'!B10
N30: ='01_Resumen'!A11 | O30: ='01_Resumen'!B11
N31: ='01_Resumen'!A12 | O31: ='01_Resumen'!B12
N32: ='01_Resumen'!A13 | O32: ='01_Resumen'!B13
N33: ='01_Resumen'!A14 | O33: ='01_Resumen'!B14
N35: Hallazgos de mayor impacto | O35: Importe (USD)
N36: Tramo no medible | O36: =SUMIFS('12_Problemas'!$C$5:$C$11,'12_Problemas'!$A$5:$A$11,"TRAMO_NO_MEDIBLE",'12_Problemas'!$C$5:$C$11,">0")-SUMIFS('12_Problemas'!$C$5:$C$11,'12_Problemas'!$A$5:$A$11,"TRAMO_NO_MEDIBLE",'12_Problemas'!$C$5:$C$11,"<0")
N37: Evaluacion individual (×4) | O37: =SUMIFS('12_Problemas'!$C$5:$C$11,'12_Problemas'!$A$5:$A$11,"EVALUACION_INDIVIDUAL",'12_Problemas'!$C$5:$C$11,">0")-SUMIFS('12_Problemas'!$C$5:$C$11,'12_Problemas'!$A$5:$A$11,"EVALUACION_INDIVIDUAL",'12_Problemas'!$C$5:$C$11,"<0")
N38: Ajuste | O38: =SUMIFS('12_Problemas'!$C$5:$C$11,'12_Problemas'!$A$5:$A$11,"AJUSTE",'12_Problemas'!$C$5:$C$11,">0")-SUMIFS('12_Problemas'!$C$5:$C$11,'12_Problemas'!$A$5:$A$11,"AJUSTE",'12_Problemas'!$C$5:$C$11,"<0")
N39: No deducible | O39: =SUMIFS('12_Problemas'!$C$5:$C$11,'12_Problemas'!$A$5:$A$11,"NO_DEDUCIBLE",'12_Problemas'!$C$5:$C$11,">0")-SUMIFS('12_Problemas'!$C$5:$C$11,'12_Problemas'!$A$5:$A$11,"NO_DEDUCIBLE",'12_Problemas'!$C$5:$C$11,"<0")

Sheet 00_Caratula
A1: Carátula | H1: ⟵ Inicio | J1: Siguiente ▶
A2: Deterioro de cuentas por cobrar · pérdidas incurridas (PYMES) · Cliente de muestra S.A. · corte 2025-12-31
A4: Concepto | B4: Detalle
A5: Firma | B5: AuditConsulting Auditores Cía. Ltda.
A6: Cliente | B6: Cliente de muestra S.A.
A7: RUC | B7: 1790000000001
A8: Ejercicio | B8: 2025
A9: Fecha de corte | B9: 2025-12-31
A10: Marco contable | B10: NIIF para las PYMES
A11: Herramienta | B11: Deterioro de cuentas por cobrar · pérdidas incurridas (PYMES)
A12: Rubro | B12: Cuentas por cobrar
A13: Motor | B13: pi-s11 1.0
A14: Versión del papel | B14: v1
A15: Estado | B15: MUESTRA
... A17: Revisó | B17: Pendiente
A18: Aprobó
A19: Fecha de aprobación
A20: Huella de la ejecución (SHA-256)

Sheet 00_Programa
A1: Programa | H1: ⟵ Inicio | I1: ◀ Anterior | J1: Siguiente ▶
A2: Deterioro de cuentas por cobrar · pérdidas incurridas (PYMES) · Cliente de muestra S.A. · corte 2025-12-31
A4: Código | B4: Objetivo | C4: Afirmación | D4: Procedimiento | E4: Evidencia | F4: Criterio | G4: Referencia
A5: CXCPI-01 | B5: Integridad de la cartera | C5: Integridad | D5: Conciliar el anexo de cartera del ejercicio con el mayor al corte | E5: Anexo de cartera y mayor | F5: Diferencia dentro de tolerancia o explicada | G5: NIA 500 párr. 9
A6: CXCPI-02 | B6: Evidencia histórica de recuperación | C6: Valoración | D6: Emparejar las facturas de cada año con las del año siguiente y medir la no recuperación por tramo | E6: Anexos de cartera de 3 ejercicios | F6: Tasa por tramo medida, o declarada no medible con su causa | G6: Secc. 11 párr. 11.22(e) · NIA 540
A7: CXCPI-03 | B7: Evaluación individual | C7: Valoración | D7: Evaluar individualmente los clientes sobre el umbral de saldo o con mora de 361 días o más | E7: Antigüedad por cliente, gestión de cobro | F7: Tasa y plazo por cliente documentados | G7: Secc. 11 párr. 11.24
A8: CXCPI-04 | B8: Medición de la pérdida | C8: Valoración | D8: Recalcular por factura y por cliente: importe en libros − valor presente de los flujos estimados | E8: Detalle por factura | F8: Pérdida recalculada | G8: Secc. 11 párr. 11.25
A9: CXCPI-05 | B9: Movimiento de la provisión | C9: Exactitud | D9: Conciliar provisión inicial − reversiones − bajas + provisión del año con el mayor | E9: Anexo de provisión inicial, mayor | F9: Movimiento conciliado; reversiones dentro del límite | G9: Secc. 11 párr. 11.26
A10: CXCPI-06 | B10: Tratamiento fiscal e impuesto diferido | C10: Presentación | D10: Aplicar los límites de deducibilidad y medir el activo por impuesto diferido | E10: Parámetros fiscales, provisión fiscal anterior | F10: Deducible y diferido recalculados | G10: LRTI Art. 10 num. 11 · Secc. 29
A11: CXCPI-07 | B11: Cobros posteriores | C11: Valoración | D11: Cotejar cobros posteriores al cierre con las facturas deterioradas | E11: Estados de cuenta, depósitos posteriores | F11: Excepciones evaluadas | G11: NIA 560 párr. 6 · Secc. 32

Sheet 00_Fuentes
A1: Base técnica | H1: ⟵ Inicio | I1: ◀ Anterior | J1: Siguiente ▶
A2: Deterioro de cuentas por cobrar · pérdidas incurridas (PYMES) · Cliente de muestra S.A. · corte 2025-12-31
A4: Categoría | B4: Documento | C4: Párrafos | D4: URL | E4: Verificada
A5: NIA · NIA 540 (Revisada) | B5: La provisión es una estimación: evaluar el método (migración por tramos), los datos (anexos de 3 años), los supuestos (plazo, tasa, umbrales) y el posible sesgo. | C5: párr. 13 y 17–30
A6: NIA · NIA 500 | B6: Los anexos de cartera los produce la entidad: evaluar su exactitud e integridad contra el mayor antes de usarlos. | C6: párr. 9
A7: NIA · NIA 505 | B7: Considerar confirmaciones de saldos de clientes significativos. | C7: párr. 7
A8: NIA · NIA 560 | B8: Revisar cobros posteriores al cierre como evidencia de recuperabilidad. | C8: párr. 6
A9: NIA · NIA 330 | B9: Procedimientos sustantivos sobre la valoración de la cartera, saldo material. | C9: párr. 18

Sheet 01_Resumen
A1: Resumen | H1: ⟵ Inicio | I1: ◀ Anterior | J1: Siguiente ▶
A2: Deterioro de cuentas por cobrar · pérdidas incurridas (PYMES) · Cliente de muestra S.A. · corte 2025-12-31
A4: Concepto | B4: Importe
A5: Cartera al corte | B5: ='08_Fiscal'!$B$5
A6: Pérdida incurrida recalculada | B6: ='08_Fiscal'!$B$7
A7: Provisión registrada (mayor) | B7: ='07_Mayor'!F7
A8: Ajuste propuesto | B8: =B6-B7
A9: Reversión de la provisión anterior | B9: ='06_Movimiento_provision'!D19
A10: Bajas y castigos | B10: ='06_Movimiento_provision'!E19
A11: Gasto deducible | B11: ='08_Fiscal'!$B$14
A12: Gasto no deducible | B12: ='08_Fiscal'!$B$15
A13: Activo por impuesto diferido | B13: ='08_Fiscal'!$B$18
A14: Movimiento del diferido | B14: ='08_Fiscal'!$B$20
A16: ⓘ Cómo se calcula esta hoja
A17: Columna | B17: Fórmula (Excel) | C17: Cómo se calcula (sencillo) | D17: Ejemplo con números reales | E17: De dónde viene | F17: Norma
A18: Importe | B18: '='08_Fiscal'!$B$5 | C18: Trae cada importe de la hoja donde se calculó: cartera, pérdida, gasto deducible y no deducible y diferido de la hoja 08 (Fiscal); provisión registrada del último año de la hoja 07 (Provisión según el mayor); reversión y bajas de los totales de la hoja 06 (Movimiento de la provisión). El ajuste propuesto es la pérdida recalculada menos la provisión registrada. | D18: Fila 1: 167.059,86 → 167.059,86 | E18: hoja «Fiscal» | F18: —

Sheet 02_Parametros
A1: Parámetros | H1: ⟵ Inicio | I1: ◀ Anterior | J1: Siguiente ▶
A2: Deterioro de cuentas por cobrar · pérdidas incurridas (PYMES) · Cliente de muestra S.A. · corte 2025-12-31
A4: Parámetro | B4: Valor | C4: Sustento
A5: Corte del ejercicio corriente | B5: 46022 | C5: Ficha del encargo
A6: Corte del ejercicio anterior | B6: 45657 | C6: Fin del mes de la última emisión del anexo
A7: Corte de dos ejercicios antes | B7: 45291 | C7: Fin del mes de la última emisión del anexo
A8: Tasa efectiva para descontar (%) | B8: 0 | C8: Secc. 11 párr. 11.13 y 11.25
A9: Plazo esperado de cobro (meses) | B9: 12 | C9: Juicio del auditor
A10: Umbral de mora grave (días) | B10: 361 | C10: Secc. 11 párr. 11.24
A11: Umbral de saldo significativo | B11: 0 | C11: Secc. 11 párr. 11.24 (0 = desactivado)
A12: Límite anual deducible (%) | B12: 1 | C12: LRTI Art. 10 num. 11
A13: Límite acumulado (%) | B13: 10 | C13: LRTI Art. 10 num. 11
A14: Tasa del impuesto (%) | B14: 25 | C14: Tarifa del contribuyente
A15: Provisión fiscal acumulada anterior | C15: En blanco: mínimo entre la provisión anterior y el límite acumulado
A16: Activo por impuesto diferido inicial | C16: En blanco: el del anexo de provisión inicial

Sheet 03_Evidencia_historica
A1: Evidencia histórica | H1: ⟵ Inicio | I1: ◀ Anterior | J1: Siguiente ▶
A2: Deterioro de cuentas por cobrar · pérdidas incurridas (PYMES) · Cliente de muestra S.A. · corte 2025-12-31
A4: Ventana | B4: Tramo | C4: Documentos | D4: Emparejados | E4: Saldo inicial | F4: Sigue vivo al año siguiente | G4: No recuperación | H4: Usable
A5: a1 → a2 | B5: Corriente / por vencer | C5: 5 | D5: 0 | E5: 125487.31 | F5: 0 | G5: =IF(E5=0,"",F5/E5) | H5: Sí
A6: a1 → a2 | B6: 1 a 30 días | C6: 1 | D6: 0 | E6: 27240.87 | F6: 0 | G6: =IF(E6=0,"",F6/E6) | H6: Sí
A7: a1 → a2 | B7: 91 a 180 días | C7: 2 | D7: 2 | E7: 18224.27 | F7: 3644.85 | G7: =IF(E7=0,"",F7/E7) | H7: Sí
A8: a1 → a2 | B8: 61 a 90 días | C8: 1 | D8: 1 | E8: 10197.94 | F8: 4985.66 | G8: =IF(E8=0,"",F8/E8) | H8: Sí
A9: a1 → a2 | B9: 181 a 360 días | C9: 2 | D9: 2 | E9: 31477.43 | F9: 11941.29 | G9: =IF(E9=0,"",F9/E9) | H9: Sí
A10: a2 → a3 | B10: 361 a 730 días | C10: 5 | D10: 2 | E10: 20571.8 | F10: 6609.14 | G10: =IF(E10=0,"",F10/E10) | H10: Sí
A11: a2 → a3 | B11: Corriente / por vencer | C11: 3 | D11: 0 | E11: 46175.33 | F11: 0 | G11: =IF(E11=0,"",F11/E11) | H11: Sí
A12: a2 → a3 | B12: 1 a 30 días | C12: 1 | D12: 0 | E12: 10702.09 | F12: 0 | G12: =IF(E12=0,"",F12/E12) | H12: Sí
A13: a2 → a3 | B13: 31 a 60 días | C13: 4 | D13: 2 | E13: 34052.04 | F13: 5956.67 | G13: =IF(E13=0,"",F13/E13) | H13: Sí
A14: a2 → a3 | B14: 181 a 360 días | C14: 3 | D14: 3 | E14: 39258.89 | F14: 17207 | G14: =IF(E14=0,"",F14/E14) | H14: Sí
A15: a2 → a3 | B15: 61 a 90 días | C15: 1 | D15: 1 | E15: 8935.07 | F15: 1787.01 | G15: =IF(E15=0,"",F15/E15) | H15: Sí
A17: ⓘ Cómo se calcula esta hoja
A18: Columna | B18: Fórmula (Excel) | C18: Cómo se calcula (sencillo) | D18: Ejemplo con números reales | E18: De dónde viene | F18: Norma
A19: No recuperación | B19: '=IF(E5=0,"",F5/E5) | C19: Divide el saldo del tramo que seguía sin cobrarse al año siguiente para su saldo inicial en esa ventana: es la parte que no se recuperó. Si el saldo inicial es cero, queda en blanco. | D19: Fila 1: IF(125.487,31=0; ""; 0,00/125.487,31) → 0,00 % | E19: «Saldo inicial» (esta hoja), «Sigue vivo al año siguiente» (esta hoja) | F19: —

Sheet 04_Matriz_deterioro
A1: Matriz de deterioro | H1: ⟵ Inicio | I1: ◀ Anterior | J1: Siguiente ▶
A2: Deterioro de cuentas por cobrar · pérdidas incurridas (PYMES) · Cliente de muestra S.A. · corte 2025-12-31
A4: Tramo | B4: Documentos | C4: Saldo | D4: Tasa aplicada | E4: Origen | F4: Pérdida | G4: Base de la tasa
A5: Corriente / por vencer | B5: =COUNTIF('11_Detalle'!$F$5:$F$24,A5) | C5: =SUMIF('11_Detalle'!$F$5:$F$24,A5,'11_Detalle'!$G$5:$G$24) | D5: 0 | E5: Sección 11 — sin evidencia objetiva | F5: =SUMIF('11_Detalle'!$F$5:$F$24,A5,'11_Detalle'!$J$5:$J$24) | G5: Cartera al día sin evento de pérdida: la Sección 11 no admite provisión general.
A6: 1 a 30 días | B6: =COUNTIF('11_Detalle'!$F$5:$F$24,A6) | C6: =SUMIF('11_Detalle'!$F$5:$F$24,A6,'11_Detalle'!$G$5:$G$24) | E6: No medible | F6: =SUMIF('11_Detalle'!$F$5:$F$24,A6,'11_Detalle'!$J$5:$J$24) | G6: Ningún documento del tramo se localizó en el ejercicio siguiente: falta la medición, no el cobro.
A7: 31 a 60 días | B7: =COUNTIF('11_Detalle'!$F$5:$F$24,A7) | C7: =SUMIF('11_Detalle'!$F$5:$F$24,A7,'11_Detalle'!$G$5:$G$24) | D7: =SUMIFS('03_Evidencia_historica'!$F:$F,'03_Evidencia_historica'!$B:$B,A7,'03_Evidencia_historica'!$H:$H,"Sí")/SUMIFS('03_Evidencia_historica'!$E:$E,'03_Evidencia_historica'!$B:$B,A7,'03_Evidencia_historica'!$H:$H,"Sí") | E7: Migración observada | F7: =SUMIF('11_Detalle'!$F$5:$F$24,A7,'11_Detalle'!$J$5:$J$24) | G7: De 34.052,04 en este tramo, 5.956,67 seguían vivos un año después (2 de 4 documentos; 2 ventana(s) anual(es)).
A8: 61 a 90 días | B8: =COUNTIF('11_Detalle'!$F$5:$F$24,A8) | C8: =SUMIF('11_Detalle'!$F$5:$F$24,A8,'11_Detalle'!$G$5:$G$24) | D8: =SUMIFS('03_Evidencia_historica'!$F:$F,'03_Evidencia_historica'!$B:$B,A8,'03_Evidencia_historica'!$H:$H,"Sí")/SUMIFS('03_Evidencia_historica'!$E:$E,'03_Evidencia_historica'!$B:$B,A8,'03_Evidencia_historica'!$H:$H,"Sí") | E8: Migración observada | F8: =SUMIF('11_Detalle'!$F$5:$F$24,A8,'11_Detalle'!$J$5:$J$24) | G8: De 19.133,01 en este tramo, 6.772,67 seguían vivos un año después (2 de 2 documentos; 2 ventana(s) anual(es)).
A9: 91 a 180 días | B9: =COUNTIF('11_Detalle'!$F$5:$F$24,A9) | C9: =SUMIF('11_Detalle'!$F$5:$F$24,A9,'11_Detalle'!$G$5:$G$24) | D9: =SUMIFS('03_Evidencia_historica'!$F:$F,'03_Evidencia_historica'!$B:$B,A9,'03_Evidencia_historica'!$H:$H,"Sí")/SUMIFS('03_Evidencia_historica'!$E:$E,'03_Evidencia_historica'!$B:$B,A9,'03_Evidencia_historica'!$H:$H,"Sí") | E9: Migración observada | F9: =SUMIF('11_Detalle'!$F$5:$F$24,A9,'11_Detalle'!$J$5:$J$24) | G9: De 18.224,27 en este tramo, 3.644,85 seguían vivos un año después (2 de 2 documentos; 2 ventana(s) anual(es)).
A10: 181 a 360 días | B10: =COUNTIF('11_Detalle'!$F$5:$F$24,A10) | C10: =SUMIF('11_Detalle'!$F$5:$F$24,A10,'11_Detalle'!$G$5:$G$24) | D10: =SUMIFS('03_Evidencia_historica'!$F:$F,'03_Evidencia_historica'!$B:$B,A10,'03_Evidencia_historica'!$H:$H,"Sí")/SUMIFS('03_Evidencia_historica'!$E:$E,'03_Evidencia_historica'!$B:$B,A10,'03_Evidencia_historica'!$H:$H,"Sí") | E10: Migración observada | F10: =SUMIF('11_Detalle'!$F$5:$F$24,A10,'11_Detalle'!$J$5:$J$24) | G10: De 70.736,32 en este tramo, 29.148,29 seguían vivos un año después (5 de 5 documentos; 2 ventana(s) anual(es)).
A11: 361 a 730 días | B11: =COUNTIF('11_Detalle'!$F$5:$F$24,A11) | C11: =SUMIF('11_Detalle'!$F$5:$F$24,A11,'11_Detalle'!$G$5:$G$24) | D11: =SUMIFS('03_Evidencia_historica'!$F:$F,'03_Evidencia_historica'!$B:$B,A11,'03_Evidencia_historica'!$H:$H,"Sí")/SUMIFS('03_Evidencia_historica'!$E:$E,'03_Evidencia_historica'!$B:$B,A11,'03_Evidencia_historica'!$H:$H,"Sí") | E11: Migración observada | F11: =SUMIF('11_Detalle'!$F$5:$F$24,A11,'11_Detalle'!$J$5:$J$24) | G11: De 20.571,80 en este tramo, 6.609,14 seguían vivos un año después (2 de 5 documentos; 2 ventana(s) anual(es)).
A12: Más de 730 días | B12: =COUNTIF('11_Detalle'!$F$5:$F$24,A12) | C12: =SUMIF('11_Detalle'!$F$5:$F$24,A12,'11_Detalle'!$G$5:$G$24) | D12: 1 | E12: Evidencia objetiva del tramo | F12: =SUMIF('11_Detalle'!$F$5:$F$24,A12,'11_Detalle'!$J$5:$J$24) | G12: Pérdida total del remanente: 2 documentos de más de 730 días sin evidencia de recuperación (Sección 11: incumplimiento sostenido).
A13: TOTAL | B13: =SUM(B5:B12) | C13: =SUM(C5:C12) | F13: =SUM(F5:F12)
A15: ⓘ Cómo se calcula esta hoja
A16: Columna | B16: Fórmula (Excel) | C16: Cómo se calcula (sencillo) | D16: Ejemplo con números reales | E16: De dónde viene | F16: Norma
A17: Documentos | B17: '=COUNTIF('11_Detalle'!$F$5:$F$24,A5) | C17: Cuenta cuántas facturas del detalle (hoja 11, Detalle por factura) caen en este tramo de mora. | D17: Fila 1: COUNTIF([«Tramo» de «Detalle por factura», 20 filas]; «Corriente / por vencer») → 5 | E17: «Tramo» (esta hoja), hoja «Detalle por factura» | F17: —
A18: Saldo | B18: '=SUMIF('11_Detalle'!$F$5:$F$24,A5,'11_Detalle'!$G$5:$G$24) | C18: Suma el saldo de todas las facturas del detalle (hoja 11, Detalle por factura) que caen en este tramo. | D18: Fila 1: SUMIF([«Tramo» de «Detalle por factura», 20 filas]; «Corriente / por vencer»; [«Saldo» de «Detalle por factura», 20 filas]) → 90.377,19 | E18: «Tramo» (esta hoja), hoja «Detalle por factura» | F18: —
A19: Tasa aplicada | B19: '=SUMIFS('03_Evidencia_historica'!$F:$F,'03_Evidencia_historica'!$B:$B,A7,'03_Evidencia_historica'!$H:$H,"Sí")/SUMIFS('03_Evidencia_historica'!$E:$E,'03_Evidencia_historica'!$B:$B,A7,'03_Evidencia_historica'!$H:$H,"Sí") | C19: Si el auditor fijó la tasa del tramo, la toma de la hoja 02 (Parámetros) y la divide para 100; si viene de la migración observada, divide el saldo que siguió vivo para el saldo inicial del tramo, sumando solo las ventanas marcadas «Sí» como usables en la hoja 03 (Evidencia histórica). | D19: Fila 3: SUMIFS([«Sigue vivo al año siguiente» de «Evidencia histórica», columna completa]; [«Tramo» de «Evidencia histórica», columna completa]; «31 a 60 días»; [«Usable» de «Evidencia histórica», columna completa]; "Sí")/SUMIFS([«Saldo inicial» de «Evidencia histórica», columna completa]; [«Tramo» de «Evidencia histórica», columna completa]; «31 a 60 días»; [«Usable» de «Evidencia histórica», columna completa]; "Sí") → 17,49 % | E19: «Tramo» (esta hoja) | F19: —
A20: Pérdida | B20: '=SUMIF('11_Detalle'!$F$5:$F$24,A5,'11_Detalle'!$J$5:$J$24) | C20: Suma la pérdida calculada factura por factura en la hoja 11 (Detalle por factura) para las facturas de este tramo. | D20: Fila 1: SUMIF([«Tramo» de «Detalle por factura», 20 filas]; «Corriente / por vencer»; [«Pérdida» de «Detalle por factura», 20 filas]) → 0,00 | E20: «Tramo» (esta hoja), hoja «Detalle por factura» | F20: —

Sheet 05_Por_cliente
A1: Por cliente | H1: ⟵ Inicio | I1: ◀ Anterior | J1: Siguiente ▶
A2: Deterioro de cuentas por cobrar · pérdidas incurridas (PYMES) · Cliente de muestra S.A. · corte 2025-12-31
A4: Cliente | B4: RUC | C4: Documentos | D4: Saldo | E4: Corriente | F4: Vencido | G4: Mora máxima (días) | H4: Tasa ponderada | I4: Pérdida | J4: Evaluación
A5: Vialidad Norte S.A. | B5: 1090044556001 | C5: =COUNTIF('11_Detalle'!$B$5:$B$24,A5) | D5: =SUMIF('11_Detalle'!$B$5:$B$24,A5,'11_Detalle'!$G$5:$G$24) | E5: =SUMIFS('11_Detalle'!$G$5:$G$24,'11_Detalle'!$B$5:$B$24,A5,'11_Detalle'!$E$5:$E$24,"<=0") | F5: =D5-E5 | G5: 819 | H5: 0.30092179 | I5: =IF(H5="","",D5*(1-(1-H5)/(1+'02_Parametros'!$B$8/100)^('02_Parametros'!$B$9/12))) | J5: Antigüedad
A6: Obras Civiles Pacífico S.A. | B6: 1390066778001 | C6: =COUNTIF('11_Detalle'!$B$5:$B$24,A6) | D6: =SUMIF('11_Detalle'!$B$5:$B$24,A6,'11_Detalle'!$G$5:$G$24) | E6: =SUMIFS('11_Detalle'!$G$5:$G$24,'11_Detalle'!$B$5:$B$24,A6,'11_Detalle'!$E$5:$E$24,"<=0") | F6: =D6-E6 | G6: 971 | H6: 0.3597282 | I6: =IF(H6="","",D6*(1-(1-H6)/(1+'02_Parametros'!$B$8/100)^('02_Parametros'!$B$9/12))) | J6: Antigüedad
A7: Hidrosur Cía. Ltda. | B7: 0190055667001 | C7: =COUNTIF('11_Detalle'!$B$5:$B$24,A7) | D7: =SUMIF('11_Detalle'!$B$5:$B$24,A7,'11_Detalle'!$G$5:$G$24) | E7: =SUMIFS('11_Detalle'!$G$5:$G$24,'11_Detalle'!$B$5:$B$24,A7,'11_Detalle'!$E$5:$E$24,"<=0") | F7: =D7-E7 | G7: 451 | H7: 0.073474394 | I7: =IF(H7="","",D7*(1-(1-H7)/(1+'02_Parametros'!$B$8/100)^('02_Parametros'!$B$9/12))) | J7: Antigüedad
A8: Minera Austral S.A. | B8: 1790033445001 | C8: =COUNTIF('11_Detalle'!$B$5:$B$24,A8) | D8: =SUMIF('11_Detalle'!$B$5:$B$24,A8,'11_Detalle'!$G$5:$G$24) | E8: =SUMIFS('11_Detalle'!$G$5:$G$24,'11_Detalle'!$B$5:$B$24,A8,'11_Detalle'!$E$5:$E$24,"<=0") | F8: =D8-E8 | G8: 635 | H8: 0.091269365 | I8: =IF(H8="","",D8*(1-(1-H8)/(1+'02_Parametros'!$B$8/100)^('02_Parametros'!$B$9/12))) | J8: Antigüedad
A9: Constructora Andina S.A. | B9: 1790011223001 | C9: =COUNTIF('11_Detalle'!$B$5:$B$24,A9) | D9: =SUMIF('11_Detalle'!$B$5:$B$24,A9,'11_Detalle'!$G$5:$G$24) | E9: =SUMIFS('11_Detalle'!$G$5:$G$24,'11_Detalle'!$B$5:$B$24,A9,'11_Detalle'!$E$5:$E$24,"<=0") | F9: =D9-E9 | G9: 0 | H9: 0 | I9: =IF(H9="","",D9*(1-(1-H9)/(1+'02_Parametros'!$B$8/100)^('02_Parametros'!$B$9/12))) | J9: Colectiva
A10: Agroexport del Litoral Cía. Ltda. | B10: 0990022334001 | C10: =COUNTIF('11_Detalle'!$B$5:$B$24,A10) | D10: =SUMIF('11_Detalle'!$B$5:$B$24,A10,'11_Detalle'!$G$5:$G$24) | E10: =SUMIFS('11_Detalle'!$G$5:$G$24,'11_Detalle'!$B$5:$B$24,A10,'11_Detalle'!$E$5:$E$24,"<=0") | F10: =D10-E10 | G10: 24 | I10: =IF(H10="","",D10*(1-(1-H10)/(1+'02_Parametros'!$B$8/100)^('02_Parametros'!$B$9/12))) | J10: Colectiva
A11: TOTAL | C11: =SUM(C5:C10) | D11: =SUM(D5:D10) | E11: =SUM(E5:E10) | F11: =SUM(F5:F10) | I11: =SUM(I5:I10)
A13: ⓘ Cómo se calcula esta hoja
A14: Columna | B14: Fórmula (Excel) | C14: Cómo se calcula (sencillo) | D14: Ejemplo con números reales | E14: De dónde viene | F14: Norma
A15: Documentos | B15: '=COUNTIF('11_Detalle'!$B$5:$B$24,A5) | C15: Cuenta cuántas facturas del cliente hay en el detalle de la hoja 11 (Detalle por factura). | D15: Fila 1: COUNTIF([«Cliente» de «Detalle por factura», 20 filas]; «Vialidad Norte S.A.») → 6 | E15: «Cliente» (esta hoja), hoja «Detalle por factura» | F15: —
A16: Saldo | B16: '=SUMIF('11_Detalle'!$B$5:$B$24,A5,'11_Detalle'!$G$5:$G$24) | C16: Suma el saldo de todas las facturas del cliente que figuran en la hoja 11 (Detalle por factura). | D16: Fila 1: SUMIF([«Cliente» de «Detalle por factura», 20 filas]; «Vialidad Norte S.A.»; [«Saldo» de «Detalle por factura», 20 filas]) → 30.793,99 | E16: «Cliente» (esta hoja), hoja «Detalle por factura» | F16: —
A17: Corriente | B17: '=SUMIFS('11_Detalle'!$G$5:$G$24,'11_Detalle'!$B$5:$B$24,A5,'11_Detalle'!$E$5:$E$24,"<=0") | C17: Suma el saldo de las facturas del cliente que al corte no están vencidas (días de mora cero o negativos) según la hoja 11 (Detalle por factura). | D17: Fila 1: SUMIFS([«Saldo» de «Detalle por factura», 20 filas]; [«Cliente» de «Detalle por factura», 20 filas]; «Vialidad Norte S.A.»; [«Días de mora» de «Detalle por factura», 20 filas]; "<=0") → 7.754,65 | E17: «Cliente» (esta hoja), hoja «Detalle por factura» | F17: —
A18: Vencido | B18: '=D5-E5 | C18: Resta al saldo total del cliente la parte corriente: lo que queda es la cartera ya vencida del cliente. | D18: Fila 1: 30.793,99-7.754,65 → 23.039,34 | E18: «Saldo» (esta hoja), «Corriente» (esta hoja) | F18: —
A19: Pérdida | B19: '=IF(H5="","",D5*(1-(1-H5)/(1+'02_Parametros'!$B$8/100)^('02_Parametros'!$B$9/12))) | C19: Aplica la tasa ponderada del cliente: al saldo le resta el valor presente de la parte que se espera cobrar, descontada con la tasa y el plazo de la hoja 02 (Parámetros). Sin tasa ponderada, queda en blanco. | D19: Fila 1: IF(30,09 %=""; ""; 30.793,99*(1-(1-30,09 %)/(1+0,00/100)^(12,00/12))) → 9.266,58 | E19: «Tasa ponderada» (esta hoja), «Saldo» (esta hoja), hoja «Parámetros» | F19: —

Sheet 06_Movimiento_provision
A1: Movimiento de la provisión | H1: ⟵ Inicio | I1: ◀ Anterior | J1: Siguiente ▶
A2: Deterioro de cuentas por cobrar · pérdidas incurridas (PYMES) · Cliente de muestra S.A. · corte 2025-12-31
A4: Cliente | B4: Factura | C4: Provisión inicial | D4: Reversión | E4: Bajas | F4: Provisión del año | G4: Saldo final | H4: Tipo
A5: Obras Civiles Pacífico S.A. | B5: 001-001-000001011 | C5: 3821.78 | D5: 3821.78 | E5: 0 | F5: =SUMIF('11_Detalle'!$A$5:$A$24,B5,'11_Detalle'!$J$5:$J$24) | G5: =C5-D5-E5+F5 | H5: Con deterioro
A6: Vialidad Norte S.A. | B6: 001-001-000001009 | C6: 1994.26 | D6: 1994.26 | E6: 0 | F6: =SUMIF('11_Detalle'!$A$5:$A$24,B6,'11_Detalle'!$J$5:$J$24) | G6: =C6-D6-E6+F6 | H6: Con deterioro
A7: Minera Austral S.A. | B7: 001-001-000001021 | C7: 0 | D7: 0 | E7: 0 | F7: =SUMIF('11_Detalle'!$A$5:$A$24,B7,'11_Detalle'!$J$5:$J$24) | G7: =C7-D7-E7+F7 | H7: Con deterioro
A8: Vialidad Norte S.A. | B8: 001-001-000001022 | C8: 0 | D8: 0 | E8: 0 | F8: =SUMIF('11_Detalle'!$A$5:$A$24,B8,'11_Detalle'!$J$5:$J$24) | G8: =C8-D8-E8+F8 | H8: Con deterioro
A9: Vialidad Norte S.A. | B9: 001-001-000001028 | C9: 0 | D9: 0 | E9: 0 | F9: =SUMIF('11_Detalle'!$A$5:$A$24,B9,'11_Detalle'!$J$5:$J$24) | G9: =C9-D9-E9+F9 | H9: Con deterioro
A10: Hidrosur Cía. Ltda. | B10: 001-001-000001023 | C10: 0 | D10: 0 | E10: 0 | F10: =SUMIF('11_Detalle'!$A$5:$A$24,B10,'11_Detalle'!$J$5:$J$24) | G10: =C10-D10-E10+F10 | H10: Con deterioro
A11: Minera Austral S.A. | B11: 001-001-000001027 | C11: 0 | D11: 0 | E11: 0 | F11: =SUMIF('11_Detalle'!$A$5:$A$24,B11,'11_Detalle'!$J$5:$J$24) | G11: =C11-D11-E11+F11 | H11: Con deterioro
A12: Obras Civiles Pacífico S.A. | B12: 001-001-000001024 | C12: 0 | D12: 0 | E12: 0 | F12: =SUMIF('11_Detalle'!$A$5:$A$24,B12,'11_Detalle'!$J$5:$J$24) | G12: =C12-D12-E12+F12 | H12: Con deterioro
A13: Vialidad Norte S.A. | B13: 001-001-000001041 | C13: 0 | D13: 0 | E13: 0 | F13: =SUMIF('11_Detalle'!$A$5:$A$24,B13,'11_Detalle'!$J$5:$J$24) | G13: =C13-D13-E13+F13 | H13: Con deterioro
A14: Vialidad Norte S.A. | B14: 001-001-000001035 | C14: 0 | D14: 0 | E14: 0 | F14: =SUMIF('11_Detalle'!$A$5:$A$24,B14,'11_Detalle'!$J$5:$J$24) | G14: =C14-D14-E14+F14 | H14: Con deterioro
A15: Hidrosur Cía. Ltda. | B15: 001-001-000001036 | C15: 0 | D15: 0 | E15: 0 | F15: =SUMIF('11_Detalle'!$A$5:$A$24,B15,'11_Detalle'!$J$5:$J$24) | G15: =C15-D15-E15+F15 | H15: Con deterioro
A16: Obras Civiles Pacífico S.A. | B16: 001-001-000001037 | C16: 0 | D16: 0 | E16: 0 | F16: =SUMIF('11_Detalle'!$A$5:$A$24,B16,'11_Detalle'!$J$5:$J$24) | G16: =C16-D16-E16+F16 | H16: Con deterioro
... A18: Hidrosur Cía. Ltda. | B18: 001-001-000001042 | C18: 0 | D18: 0 | E18: 0 | F18: =SUMIF('11_Detalle'!$A$5:$A$24,B18,'11_Detalle'!$J$5:$J$24) | G18: =C18-D18-E18+F18 | H18: Con deterioro
A19: TOTAL | C19: =SUM(C5:C18) | D19: =SUM(D5:D18) | E19: =SUM(E5:E18) | F19: =SUM(F5:F18) | G19: =SUM(G5:G18)
A21: ⓘ Cómo se calcula esta hoja
A22: Columna | B22: Fórmula (Excel) | C22: Cómo se calcula (sencillo) | D22: Ejemplo con números reales | E22: De dónde viene | F22: Norma
A23: Provisión del año | B23: '=SUMIF('11_Detalle'!$A$5:$A$24,B5,'11_Detalle'!$J$5:$J$24) | C23: Trae la pérdida recalculada de esta misma factura desde la hoja 11 (Detalle por factura); es la provisión que debería constituirse en el año. | D23: Fila 1: SUMIF([«Factura» de «Detalle por factura», 20 filas]; «001-001-000001011»; [«Pérdida» de «Detalle por factura», 20 filas]) → 4.342,93 | E23: «Factura» (esta hoja), hoja «Detalle por factura» | F23: —
A24: Saldo final | B24: '=C5-D5-E5+F5 | C24: Parte de la provisión inicial, resta la reversión y las bajas del año y suma la provisión del año: es el saldo que debería quedar en la provisión de la factura. | D24: Fila 1: 3.821,78-3.821,78-0,00+4.342,93 → 4.342,93 | E24: «Provisión inicial» (esta hoja), «Reversión» (esta hoja), «Bajas» (esta hoja), «Provisión del año» (esta hoja) | F24: —

Sheet 07_Mayor
A1: Provisión según el mayor | H1: ⟵ Inicio | I1: ◀ Anterior | J1: Siguiente ▶
A2: Deterioro de cuentas por cobrar · pérdidas incurridas (PYMES) · Cliente de muestra S.A. · corte 2025-12-31
A4: Año | B4: Inicial | C4: Gasto | D4: Castigos | E4: Recuperaciones | F4: Final
A5: 2023 | B5: 2442.74 | C5: 1628.49 | D5: 0 | E5: 0 | F5: =B5+C5-D5+E5
A6: 2024 | B6: 4071.23 | C6: 1744.81 | D6: 0 | E6: 0 | F6: =B6+C6-D6+E6
A7: 2025 | B7: 5816.04 | C7: 0 | D7: 0 | E7: 0 | F7: =B7+C7-D7+E7
A9: ⓘ Cómo se calcula esta hoja
A10: Columna | B10: Fórmula (Excel) | C10: Cómo se calcula (sencillo) | D10: Ejemplo con números reales | E10: De dónde viene | F10: Norma
A11: Final | B11: '=B5+C5-D5+E5 | C11: Parte del saldo inicial del mayor, suma el gasto del año, resta los castigos y suma las recuperaciones: es el saldo de la provisión al cierre de ese año. | D11: Fila 1: 2.442,74+1.628,49-0,00+0,00 → 4.071,23 | E11: «Inicial» (esta hoja), «Gasto» (esta hoja), «Castigos» (esta hoja), «Recuperaciones» (esta hoja) | F11: —

Sheet 08_Fiscal
A1: Fiscal | H1: ⟵ Inicio | I1: ◀ Anterior | J1: Siguiente ▶
A2: Deterioro de cuentas por cobrar · pérdidas incurridas (PYMES) · Cliente de muestra S.A. · corte 2025-12-31
A4: Concepto | B4: Importe
A5: Cartera total al corte | B5: =SUM('11_Detalle'!$G$5:$G$24)
A6: Cartera corriente (créditos del ejercicio) | B6: =SUMIF('11_Detalle'!$E$5:$E$24,"<=0",'11_Detalle'!$G$5:$G$24)
A7: Pérdida incurrida recalculada | B7: =SUM('11_Detalle'!$J$5:$J$24)
A8: Provisión del ejercicio anterior (mayor) | B8: ='07_Mayor'!F6
A9: Gasto del ejercicio | B9: ='08_Fiscal'!$B$7-'08_Fiscal'!$B$8
A10: Límite anual (% sobre la cartera corriente) | B10: ='08_Fiscal'!$B$6*'02_Parametros'!$B$12/100
A11: Límite acumulado (% sobre la cartera total) | B11: ='08_Fiscal'!$B$5*'02_Parametros'!$B$13/100
A12: Provisión fiscal acumulada anterior (estimada) | B12: =MIN('08_Fiscal'!$B$8,'08_Fiscal'!$B$11)
A13: Margen acumulado disponible | B13: =MAX('08_Fiscal'!$B$11-'08_Fiscal'!$B$12,0)
A14: Gasto deducible | B14: =MAX(MIN(MAX('08_Fiscal'!$B$9,0),'08_Fiscal'!$B$10,'08_Fiscal'!$B$13),0)
A15: Gasto no deducible | B15: =MAX(MAX('08_Fiscal'!$B$9,0)-'08_Fiscal'!$B$14,0)
A16: Provisión fiscal acumulada al cierre | B16: ='08_Fiscal'!$B$12+'08_Fiscal'!$B$14
A17: Diferencia temporaria acumulada al cierre | B17: =MAX('08_Fiscal'!$B$7-'08_Fiscal'!$B$16,0)
A18: Activo por impuesto diferido al cierre | B18: ='08_Fiscal'!$B$17*'02_Parametros'!$B$14/100
A19: Activo por impuesto diferido inicial (anexo de provisión) | B19: 1454.02
A20: Movimiento del diferido | B20: ='08_Fiscal'!$B$18-'08_Fiscal'!$B$19
A22: ⓘ Cómo se calcula esta hoja
A23: Columna | B23: Fórmula (Excel) | C23: Cómo se calcula (sencillo) | D23: Ejemplo con números reales | E23: De dónde viene | F23: Norma
A24: Importe | B24: '=SUM('11_Detalle'!$G$5:$G$24) | C24: Cada concepto tiene su propio cálculo: la cartera, la parte corriente y la pérdida se suman del detalle de la hoja 11; la provisión anterior viene de la hoja 07 (Provisión según el mayor); los límites y el diferido aplican los porcentajes de la hoja 02 (Parámetros); el resto combina las filas anteriores de esta hoja (gasto, margen, parte deducible y no deducible). | D24: Fila 1: SUM([«Saldo» de «Detalle por factura», 20 filas]) → 167.059,86 | E24: hoja «Detalle por factura» | F24: —

Sheet 09_Impuesto_diferido
A1: Impuesto diferido por factura | H1: ⟵ Inicio | I1: ◀ Anterior | J1: Siguiente ▶
A2: Deterioro de cuentas por cobrar · pérdidas incurridas (PYMES) · Cliente de muestra S.A. · corte 2025-12-31
A4: Cliente | B4: Factura | C4: Deterioro | D4: Deducible | E4: No deducible | F4: Diferido inicial | G4: Reversión | H4: Diferido nuevo | I4: Diferido final
A5: Obras Civiles Pacífico S.A. | B5: 001-001-000001011 | C5: =SUMIF('11_Detalle'!$A$5:$A$24,B5,'11_Detalle'!$J$5:$J$24) | D5: =IF($C$19=0,0,C5*MIN('08_Fiscal'!$B$16,$C$19)/$C$19) | E5: =C5-D5 | F5: 955.45 | G5: 955.45 | H5: =E5*'02_Parametros'!$B$14/100 | I5: =F5-G5+H5
A6: Vialidad Norte S.A. | B6: 001-001-000001009 | C6: =SUMIF('11_Detalle'!$A$5:$A$24,B6,'11_Detalle'!$J$5:$J$24) | D6: =IF($C$19=0,0,C6*MIN('08_Fiscal'!$B$16,$C$19)/$C$19) | E6: =C6-D6 | F6: 498.57 | G6: 498.57 | H6: =E6*'02_Parametros'!$B$14/100 | I6: =F6-G6+H6
A7: Minera Austral S.A. | B7: 001-001-000001021 | C7: =SUMIF('11_Detalle'!$A$5:$A$24,B7,'11_Detalle'!$J$5:$J$24) | D7: =IF($C$19=0,0,C7*MIN('08_Fiscal'!$B$16,$C$19)/$C$19) | E7: =C7-D7 | F7: 0 | G7: 0 | H7: =E7*'02_Parametros'!$B$14/100 | I7: =F7-G7+H7
A8: Vialidad Norte S.A. | B8: 001-001-000001022 | C8: =SUMIF('11_Detalle'!$A$5:$A$24,B8,'11_Detalle'!$J$5:$J$24) | D8: =IF($C$19=0,0,C8*MIN('08_Fiscal'!$B$16,$C$19)/$C$19) | E8: =C8-D8 | F8: 0 | G8: 0 | H8: =E8*'02_Parametros'!$B$14/100 | I8: =F8-G8+H8
A9: Vialidad Norte S.A. | B9: 001-001-000001028 | C9: =SUMIF('11_Detalle'!$A$5:$A$24,B9,'11_Detalle'!$J$5:$J$24) | D9: =IF($C$19=0,0,C9*MIN('08_Fiscal'!$B$16,$C$19)/$C$19) | E9: =C9-D9 | F9: 0 | G9: 0 | H9: =E9*'02_Parametros'!$B$14/100 | I9: =F9-G9+H9
A10: Hidrosur Cía. Ltda. | B10: 001-001-000001023 | C10: =SUMIF('11_Detalle'!$A$5:$A$24,B10,'11_Detalle'!$J$5:$J$24) | D10: =IF($C$19=0,0,C10*MIN('08_Fiscal'!$B$16,$C$19)/$C$19) | E10: =C10-D10 | F10: 0 | G10: 0 | H10: =E10*'02_Parametros'!$B$14/100 | I10: =F10-G10+H10
A11: Minera Austral S.A. | B11: 001-001-000001027 | C11: =SUMIF('11_Detalle'!$A$5:$A$24,B11,'11_Detalle'!$J$5:$J$24) | D11: =IF($C$19=0,0,C11*MIN('08_Fiscal'!$B$16,$C$19)/$C$19) | E11: =C11-D11 | F11: 0 | G11: 0 | H11: =E11*'02_Parametros'!$B$14/100 | I11: =F11-G11+H11
A12: Obras Civiles Pacífico S.A. | B12: 001-001-000001024 | C12: =SUMIF('11_Detalle'!$A$5:$A$24,B12,'11_Detalle'!$J$5:$J$24) | D12: =IF($C$19=0,0,C12*MIN('08_Fiscal'!$B$16,$C$19)/$C$19) | E12: =C12-D12 | F12: 0 | G12: 0 | H12: =E12*'02_Parametros'!$B$14/100 | I12: =F12-G12+H12
A13: Vialidad Norte S.A. | B13: 001-001-000001041 | C13: =SUMIF('11_Detalle'!$A$5:$A$24,B13,'11_Detalle'!$J$5:$J$24) | D13: =IF($C$19=0,0,C13*MIN('08_Fiscal'!$B$16,$C$19)/$C$19) | E13: =C13-D13 | F13: 0 | G13: 0 | H13: =E13*'02_Parametros'!$B$14/100 | I13: =F13-G13+H13
A14: Vialidad Norte S.A. | B14: 001-001-000001035 | C14: =SUMIF('11_Detalle'!$A$5:$A$24,B14,'11_Detalle'!$J$5:$J$24) | D14: =IF($C$19=0,0,C14*MIN('08_Fiscal'!$B$16,$C$19)/$C$19) | E14: =C14-D14 | F14: 0 | G14: 0 | H14: =E14*'02_Parametros'!$B$14/100 | I14: =F14-G14+H14
A15: Hidrosur Cía. Ltda. | B15: 001-001-000001036 | C15: =SUMIF('11_Detalle'!$A$5:$A$24,B15,'11_Detalle'!$J$5:$J$24) | D15: =IF($C$19=0,0,C15*MIN('08_Fiscal'!$B$16,$C$19)/$C$19) | E15: =C15-D15 | F15: 0 | G15: 0 | H15: =E15*'02_Parametros'!$B$14/100 | I15: =F15-G15+H15
A16: Obras Civiles Pacífico S.A. | B16: 001-001-000001037 | C16: =SUMIF('11_Detalle'!$A$5:$A$24,B16,'11_Detalle'!$J$5:$J$24) | D16: =IF($C$19=0,0,C16*MIN('08_Fiscal'!$B$16,$C$19)/$C$19) | E16: =C16-D16 | F16: 0 | G16: 0 | H16: =E16*'02_Parametros'!$B$14/100 | I16: =F16-G16+H16
... A18: Hidrosur Cía. Ltda. | B18: 001-001-000001042 | C18: =SUMIF('11_Detalle'!$A$5:$A$24,B18,'11_Detalle'!$J$5:$J$24) | D18: =IF($C$19=0,0,C18*MIN('08_Fiscal'!$B$16,$C$19)/$C$19) | E18: =C18-D18 | F18: 0 | G18: 0 | H18: =E18*'02_Parametros'!$B$14/100 | I18: =F18-G18+H18
A19: TOTAL | C19: =SUM(C5:C18) | D19: =SUM(D5:D18) | E19: =SUM(E5:E18) | F19: =SUM(F5:F18) | G19: =SUM(G5:G18) | H19: =SUM(H5:H18) | I19: =SUM(I5:I18)
A21: ⓘ Cómo se calcula esta hoja
A22: Columna | B22: Fórmula (Excel) | C22: Cómo se calcula (sencillo) | D22: Ejemplo con números reales | E22: De dónde viene | F22: Norma
A23: Deterioro | B23: '=SUMIF('11_Detalle'!$A$5:$A$24,B5,'11_Detalle'!$J$5:$J$24) | C23: Trae la pérdida recalculada de esta factura desde la hoja 11 (Detalle por factura). | D23: Fila 1: SUMIF([«Factura» de «Detalle por factura», 20 filas]; «001-001-000001011»; [«Pérdida» de «Detalle por factura», 20 filas]) → 4.342,93 | E23: «Factura» (esta hoja), hoja «Detalle por factura» | F23: —
A24: Deducible | B24: '=IF($C$19=0,0,C5*MIN('08_Fiscal'!$B$16,$C$19)/$C$19) | C24: Reparte la provisión fiscal acumulada al cierre (hoja 08, Fiscal) entre las facturas en proporción a su deterioro, sin pasar del deterioro total; si no hay deterioro, es cero. | D24: Fila 1: IF(20.749,02=0; 0; 4.342,93*MIN(6.719,81; 20.749,02)/20.749,02) → 1.406,51 | E24: «Deterioro» (esta hoja), hoja «Fiscal» | F24: —
A25: No deducible | B25: '=C5-D5 | C25: Resta al deterioro de la factura su parte deducible: lo que queda no se acepta como gasto fiscal. | D25: Fila 1: 4.342,93-1.406,51 → 2.936,42 | E25: «Deterioro» (esta hoja), «Deducible» (esta hoja) | F25: —
A26: Diferido nuevo | B26: '=E5*'02_Parametros'!$B$14/100 | C26: Multiplica la parte no deducible por la tasa del impuesto de la hoja 02 (Parámetros): es el activo por impuesto diferido que genera la factura. | D26: Fila 1: 2.936,42*25,00/100 → 734,11 | E26: «No deducible» (esta hoja), hoja «Parámetros» | F26: —
A27: Diferido final | B27: '=F5-G5+H5 | C27: Parte del diferido inicial, resta su reversión y suma el diferido nuevo: es el activo por impuesto diferido que queda al cierre para la factura. | D27: Fila 1: 955,45-955,45+734,11 → 734,11 | E27: «Diferido inicial» (esta hoja), «Reversión» (esta hoja), «Diferido nuevo» (esta hoja) | F27: —

Sheet 10_Asientos
A1: Asientos propuestos | H1: ⟵ Inicio | I1: ◀ Anterior | J1: Siguiente ▶
A2: Deterioro de cuentas por cobrar · pérdidas incurridas (PYMES) · Cliente de muestra S.A. · corte 2025-12-31
A4: Asiento | B4: Cuenta | C4: Debe | D4: Haber
A5: 1 · Gasto por deterioro de cuentas por cobrar | B5: Gasto por deterioro de cuentas incobrables | C5: ='06_Movimiento_provision'!F19
B6: (-) Provisión de deterioro de cuentas por cobrar | D6: ='06_Movimiento_provision'!F19
A7: 1b · Reversión de la provisión del ejercicio anterior | B7: (-) Provisión de deterioro de cuentas por cobrar | C7: ='06_Movimiento_provision'!D19
B8: Ingreso por reversión de deterioro de cuentas incobrables | D8: ='06_Movimiento_provision'!D19
A9: 2 · Activo por impuesto diferido: reconocimiento | B9: Activo por impuesto diferido | C9: ='09_Impuesto_diferido'!H19
B10: Ingreso por impuesto a la renta diferido | D10: ='09_Impuesto_diferido'!H19
A11: 3 · Activo por impuesto diferido: reversión | B11: Gasto por impuesto a la renta diferido | C11: ='09_Impuesto_diferido'!G19
B12: Activo por impuesto diferido | D12: ='09_Impuesto_diferido'!G19
A14: ⓘ Cómo se calcula esta hoja
A15: Columna | B15: Fórmula (Excel) | C15: Cómo se calcula (sencillo) | D15: Ejemplo con números reales | E15: De dónde viene | F15: Norma
A16: Debe | B16: '='06_Movimiento_provision'!F19 | C16: Toma el importe del asiento del total de su cédula: provisión del año, reversión o bajas de la hoja 06 (Movimiento de la provisión); diferido nuevo o su reversión de la hoja 09 (Impuesto diferido por factura). | D16: Fila 1: 20.749,02 → 20.749,02 | E16: hoja «Movimiento de la provisión» | F16: —
A17: Haber | B17: '='06_Movimiento_provision'!F19 | C17: Lleva a la contrapartida el mismo importe del asiento, tomado del total de la hoja 06 (Movimiento de la provisión) o de la hoja 09 (Impuesto diferido por factura), para que debe y haber cuadren. | D17: Fila 2: 20.749,02 → 20.749,02 | E17: hoja «Movimiento de la provisión» | F17: —

Sheet 11_Detalle
A1: Detalle por factura | H1: ⟵ Inicio | I1: ◀ Anterior | J1: Siguiente ▶
A2: Deterioro de cuentas por cobrar · pérdidas incurridas (PYMES) · Cliente de muestra S.A. · corte 2025-12-31
A4: Factura | B4: Cliente | C4: Emisión | D4: Vencimiento | E4: Días de mora | F4: Tramo | G4: Saldo | H4: Tasa | I4: Valor presente | J4: Pérdida | K4: Provisión inicial
A5: 001-001-000001011 | B5: Obras Civiles Pacífico S.A. | C5: 44991 | D5: 45051 | E5: =IF(D5="","",'02_Parametros'!$B$5-D5) | F5: =IF(E5="","",IF(E5<=0,"Corriente / por vencer",IF(E5<=30,"1 a 30 días",IF(E5<=60,"31 a 60 días",IF(E5<=90,"61 a 90 días",IF(E5<=180,"91 a 180 días",IF(E5<=360,"181 a 360 días",IF(E5<=730,"361 a 730 días","Más de 730 días")))))))) | G5: 4342.93 | H5: =IF(F5="","",IF(INDEX('04_Matriz_deterioro'!$D$5:$D$12,MATCH(F5,'04_Matriz_deterioro'!$A$5:$A$12,0))="","",INDEX('04_Matriz_deterioro'!$D$5:$D$12,MATCH(F5,'04_Matriz_deterioro'!$A$5:$A$12,0)))) | I5: =IF(H5="","",G5*(1-H5)/(1+'02_Parametros'!$B$8/100)^('02_Parametros'!$B$9/12)) | J5: =IF(I5="","",MAX(G5-I5,0)) | K5: 3821.78
A6: 001-001-000001009 | B6: Vialidad Norte S.A. | C6: 45173 | D6: 45203 | E6: =IF(D6="","",'02_Parametros'!$B$5-D6) | F6: =IF(E6="","",IF(E6<=0,"Corriente / por vencer",IF(E6<=30,"1 a 30 días",IF(E6<=60,"31 a 60 días",IF(E6<=90,"61 a 90 días",IF(E6<=180,"91 a 180 días",IF(E6<=360,"181 a 360 días",IF(E6<=730,"361 a 730 días","Más de 730 días")))))))) | G6: 2266.21 | H6: =IF(F6="","",IF(INDEX('04_Matriz_deterioro'!$D$5:$D$12,MATCH(F6,'04_Matriz_deterioro'!$A$5:$A$12,0))="","",INDEX('04_Matriz_deterioro'!$D$5:$D$12,MATCH(F6,'04_Matriz_deterioro'!$A$5:$A$12,0)))) | I6: =IF(H6="","",G6*(1-H6)/(1+'02_Parametros'!$B$8/100)^('02_Parametros'!$B$9/12)) | J6: =IF(I6="","",MAX(G6-I6,0)) | K6: 1994.26
A7: 001-001-000001021 | B7: Minera Austral S.A. | C7: 45327 | D7: 45387 | E7: =IF(D7="","",'02_Parametros'!$B$5-D7) | F7: =IF(E7="","",IF(E7<=0,"Corriente / por vencer",IF(E7<=30,"1 a 30 días",IF(E7<=60,"31 a 60 días",IF(E7<=90,"61 a 90 días",IF(E7<=180,"91 a 180 días",IF(E7<=360,"181 a 360 días",IF(E7<=730,"361 a 730 días","Más de 730 días")))))))) | G7: 1375.09 | H7: =IF(F7="","",IF(INDEX('04_Matriz_deterioro'!$D$5:$D$12,MATCH(F7,'04_Matriz_deterioro'!$A$5:$A$12,0))="","",INDEX('04_Matriz_deterioro'!$D$5:$D$12,MATCH(F7,'04_Matriz_deterioro'!$A$5:$A$12,0)))) | I7: =IF(H7="","",G7*(1-H7)/(1+'02_Parametros'!$B$8/100)^('02_Parametros'!$B$9/12)) | J7: =IF(I7="","",MAX(G7-I7,0)) | K7: 0
A8: 001-001-000001022 | B8: Vialidad Norte S.A. | C8: 45334 | D8: 45394 | E8: =IF(D8="","",'02_Parametros'!$B$5-D8) | F8: =IF(E8="","",IF(E8<=0,"Corriente / por vencer",IF(E8<=30,"1 a 30 días",IF(E8<=60,"31 a 60 días",IF(E8<=90,"61 a 90 días",IF(E8<=180,"91 a 180 días",IF(E8<=360,"181 a 360 días",IF(E8<=730,"361 a 730 días","Más de 730 días")))))))) | G8: 7172.35 | H8: =IF(F8="","",IF(INDEX('04_Matriz_deterioro'!$D$5:$D$12,MATCH(F8,'04_Matriz_deterioro'!$A$5:$A$12,0))="","",INDEX('04_Matriz_deterioro'!$D$5:$D$12,MATCH(F8,'04_Matriz_deterioro'!$A$5:$A$12,0)))) | I8: =IF(H8="","",G8*(1-H8)/(1+'02_Parametros'!$B$8/100)^('02_Parametros'!$B$9/12)) | J8: =IF(I8="","",MAX(G8-I8,0)) | K8: 0
A9: 001-001-000001028 | B9: Vialidad Norte S.A. | C9: 45375 | D9: 45435 | E9: =IF(D9="","",'02_Parametros'!$B$5-D9) | F9: =IF(E9="","",IF(E9<=0,"Corriente / por vencer",IF(E9<=30,"1 a 30 días",IF(E9<=60,"31 a 60 días",IF(E9<=90,"61 a 90 días",IF(E9<=180,"91 a 180 días",IF(E9<=360,"181 a 360 días",IF(E9<=730,"361 a 730 días","Más de 730 días")))))))) | G9: 8659.56 | H9: =IF(F9="","",IF(INDEX('04_Matriz_deterioro'!$D$5:$D$12,MATCH(F9,'04_Matriz_deterioro'!$A$5:$A$12,0))="","",INDEX('04_Matriz_deterioro'!$D$5:$D$12,MATCH(F9,'04_Matriz_deterioro'!$A$5:$A$12,0)))) | I9: =IF(H9="","",G9*(1-H9)/(1+'02_Parametros'!$B$8/100)^('02_Parametros'!$B$9/12)) | J9: =IF(I9="","",MAX(G9-I9,0)) | K9: 0
A10: 001-001-000001023 | B10: Hidrosur Cía. Ltda. | C10: 45526 | D10: 45571 | E10: =IF(D10="","",'02_Parametros'!$B$5-D10) | F10: =IF(E10="","",IF(E10<=0,"Corriente / por vencer",IF(E10<=30,"1 a 30 días",IF(E10<=60,"31 a 60 días",IF(E10<=90,"61 a 90 días",IF(E10<=180,"91 a 180 días",IF(E10<=360,"181 a 360 días",IF(E10<=730,"361 a 730 días","Más de 730 días")))))))) | G10: 1787.01 | H10: =IF(F10="","",IF(INDEX('04_Matriz_deterioro'!$D$5:$D$12,MATCH(F10,'04_Matriz_deterioro'!$A$5:$A$12,0))="","",INDEX('04_Matriz_deterioro'!$D$5:$D$12,MATCH(F10,'04_Matriz_deterioro'!$A$5:$A$12,0)))) | I10: =IF(H10="","",G10*(1-H10)/(1+'02_Parametros'!$B$8/100)^('02_Parametros'!$B$9/12)) | J10: =IF(I10="","",MAX(G10-I10,0)) | K10: 0
A11: 001-001-000001027 | B11: Minera Austral S.A. | C11: 45551 | D11: 45611 | E11: =IF(D11="","",'02_Parametros'!$B$5-D11) | F11: =IF(E11="","",IF(E11<=0,"Corriente / por vencer",IF(E11<=30,"1 a 30 días",IF(E11<=60,"31 a 60 días",IF(E11<=90,"61 a 90 días",IF(E11<=180,"91 a 180 días",IF(E11<=360,"181 a 360 días",IF(E11<=730,"361 a 730 días","Más de 730 días")))))))) | G11: 442.06 | H11: =IF(F11="","",IF(INDEX('04_Matriz_deterioro'!$D$5:$D$12,MATCH(F11,'04_Matriz_deterioro'!$A$5:$A$12,0))="","",INDEX('04_Matriz_deterioro'!$D$5:$D$12,MATCH(F11,'04_Matriz_deterioro'!$A$5:$A$12,0)))) | I11: =IF(H11="","",G11*(1-H11)/(1+'02_Parametros'!$B$8/100)^('02_Parametros'!$B$9/12)) | J11: =IF(I11="","",MAX(G11-I11,0)) | K11: 0
A12: 001-001-000001024 | B12: Obras Civiles Pacífico S.A. | C12: 45561 | D12: 45621 | E12: =IF(D12="","",'02_Parametros'!$B$5-D12) | F12: =IF(E12="","",IF(E12<=0,"Corriente / por vencer",IF(E12<=30,"1 a 30 días",IF(E12<=60,"31 a 60 días",IF(E12<=90,"61 a 90 días",IF(E12<=180,"91 a 180 días",IF(E12<=360,"181 a 360 días",IF(E12<=730,"361 a 730 días","Más de 730 días")))))))) | G12: 5514.61 | H12: =IF(F12="","",IF(INDEX('04_Matriz_deterioro'!$D$5:$D$12,MATCH(F12,'04_Matriz_deterioro'!$A$5:$A$12,0))="","",INDEX('04_Matriz_deterioro'!$D$5:$D$12,MATCH(F12,'04_Matriz_deterioro'!$A$5:$A$12,0)))) | I12: =IF(H12="","",G12*(1-H12)/(1+'02_Parametros'!$B$8/100)^('02_Parametros'!$B$9/12)) | J12: =IF(I12="","",MAX(G12-I12,0)) | K12: 0
A13: 001-001-000001041 | B13: Vialidad Norte S.A. | C13: 45691 | D13: 45781 | E13: =IF(D13="","",'02_Parametros'!$B$5-D13) | F13: =IF(E13="","",IF(E13<=0,"Corriente / por vencer",IF(E13<=30,"1 a 30 días",IF(E13<=60,"31 a 60 días",IF(E13<=90,"61 a 90 días",IF(E13<=180,"91 a 180 días",IF(E13<=360,"181 a 360 días",IF(E13<=730,"361 a 730 días","Más de 730 días")))))))) | G13: 2839.34 | H13: =IF(F13="","",IF(INDEX('04_Matriz_deterioro'!$D$5:$D$12,MATCH(F13,'04_Matriz_deterioro'!$A$5:$A$12,0))="","",INDEX('04_Matriz_deterioro'!$D$5:$D$12,MATCH(F13,'04_Matriz_deterioro'!$A$5:$A$12,0)))) | I13: =IF(H13="","",G13*(1-H13)/(1+'02_Parametros'!$B$8/100)^('02_Parametros'!$B$9/12)) | J13: =IF(I13="","",MAX(G13-I13,0)) | K13: 0
A14: 001-001-000001035 | B14: Vialidad Norte S.A. | C14: 45905 | D14: 45935 | E14: =IF(D14="","",'02_Parametros'!$B$5-D14) | F14: =IF(E14="","",IF(E14<=0,"Corriente / por vencer",IF(E14<=30,"1 a 30 días",IF(E14<=60,"31 a 60 días",IF(E14<=90,"61 a 90 días",IF(E14<=180,"91 a 180 días",IF(E14<=360,"181 a 360 días",IF(E14<=730,"361 a 730 días","Más de 730 días")))))))) | G14: 2101.88 | H14: =IF(F14="","",IF(INDEX('04_Matriz_deterioro'!$D$5:$D$12,MATCH(F14,'04_Matriz_deterioro'!$A$5:$A$12,0))="","",INDEX('04_Matriz_deterioro'!$D$5:$D$12,MATCH(F14,'04_Matriz_deterioro'!$A$5:$A$12,0)))) | I14: =IF(H14="","",G14*(1-H14)/(1+'02_Parametros'!$B$8/100)^('02_Parametros'!$B$9/12)) | J14: =IF(I14="","",MAX(G14-I14,0)) | K14: 0
A15: 001-001-000001036 | B15: Hidrosur Cía. Ltda. | C15: 45851 | D15: 45941 | E15: =IF(D15="","",'02_Parametros'!$B$5-D15) | F15: =IF(E15="","",IF(E15<=0,"Corriente / por vencer",IF(E15<=30,"1 a 30 días",IF(E15<=60,"31 a 60 días",IF(E15<=90,"61 a 90 días",IF(E15<=180,"91 a 180 días",IF(E15<=360,"181 a 360 días",IF(E15<=730,"361 a 730 días","Más de 730 días")))))))) | G15: 5870.86 | H15: =IF(F15="","",IF(INDEX('04_Matriz_deterioro'!$D$5:$D$12,MATCH(F15,'04_Matriz_deterioro'!$A$5:$A$12,0))="","",INDEX('04_Matriz_deterioro'!$D$5:$D$12,MATCH(F15,'04_Matriz_deterioro'!$A$5:$A$12,0)))) | I15: =IF(H15="","",G15*(1-H15)/(1+'02_Parametros'!$B$8/100)^('02_Parametros'!$B$9/12)) | J15: =IF(I15="","",MAX(G15-I15,0)) | K15: 0
A16: 001-001-000001037 | B16: Obras Civiles Pacífico S.A. | C16: 45856 | D16: 45946 | E16: =IF(D16="","",'02_Parametros'!$B$5-D16) | F16: =IF(E16="","",IF(E16<=0,"Corriente / por vencer",IF(E16<=30,"1 a 30 días",IF(E16<=60,"31 a 60 días",IF(E16<=90,"61 a 90 días",IF(E16<=180,"91 a 180 días",IF(E16<=360,"181 a 360 días",IF(E16<=730,"361 a 730 días","Más de 730 días")))))))) | G16: 1277.27 | H16: =IF(F16="","",IF(INDEX('04_Matriz_deterioro'!$D$5:$D$12,MATCH(F16,'04_Matriz_deterioro'!$A$5:$A$12,0))="","",INDEX('04_Matriz_deterioro'!$D$5:$D$12,MATCH(F16,'04_Matriz_deterioro'!$A$5:$A$12,0)))) | I16: =IF(H16="","",G16*(1-H16)/(1+'02_Parametros'!$B$8/100)^('02_Parametros'!$B$9/12)) | J16: =IF(I16="","",MAX(G16-I16,0)) | K16: 0
... A24: 001-001-000001034 | B24: Minera Austral S.A. | C24: 45996 | D24: 46056 | E24: =IF(D24="","",'02_Parametros'!$B$5-D24) | F24: =IF(E24="","",IF(E24<=0,"Corriente / por vencer",IF(E24<=30,"1 a 30 días",IF(E24<=60,"31 a 60 días",IF(E24<=90,"61 a 90 días",IF(E24<=180,"91 a 180 días",IF(E24<=360,"181 a 360 días",IF(E24<=730,"361 a 730 días","Más de 730 días")))))))) | G24: 17253.71 | H24: =IF(F24="","",IF(INDEX('04_Matriz_deterioro'!$D$5:$D$12,MATCH(F24,'04_Matriz_deterioro'!$A$5:$A$12,0))="","",INDEX('04_Matriz_deterioro'!$D$5:$D$12,MATCH(F24,'04_Matriz_deterioro'!$A$5:$A$12,0)))) | I24: =IF(H24="","",G24*(1-H24)/(1+'02_Parametros'!$B$8/100)^('02_Parametros'!$B$9/12)) | J24: =IF(I24="","",MAX(G24-I24,0)) | K24: 0
A25: TOTAL | G25: =SUM(G5:G24) | I25: =SUM(I5:I24) | J25: =SUM(J5:J24) | K25: =SUM(K5:K24)
A27: ⓘ Cómo se calcula esta hoja
A28: Columna | B28: Fórmula (Excel) | C28: Cómo se calcula (sencillo) | D28: Ejemplo con números reales | E28: De dónde viene | F28: Norma
A29: Días de mora | B29: '=IF(D5="","",'02_Parametros'!$B$5-D5) | C29: Resta la fecha de vencimiento de la fecha de corte de la hoja 02 (Parámetros); si la factura no tiene vencimiento, queda en blanco. Cero o negativo significa que aún no vence. | D29: Fila 1: IF(«2023-05-05»=""; ""; «2025-12-31»-«2023-05-05») → 971 | E29: «Vencimiento» (esta hoja), hoja «Parámetros» | F29: —
A30: Tramo | B30: '=IF(E5="","",IF(E5<=0,"Corriente / por vencer",IF(E5<=30,"1 a 30 días",IF(E5<=60,"31 a 60 días",IF(E5<=90,"61 a 90 días",IF(E5<=180,"91 a 180 días",IF(E5<=360,"181 a 360 días",IF(E5<=730,"361 a 730 días","Más de 730 días")))))))) | C30: Clasifica la factura por sus días de mora: corriente/por vencer si no tiene mora, luego 1 a 30, 31 a 60, 61 a 90, 91 a 180, 181 a 360, 361 a 730 y más de 730 días. Sin días de mora queda en blanco. | D30: Fila 1: IF(971=""; ""; IF(971<=0; "Corriente / por vencer"; IF(971<=30; "1 a 30 días"; IF(971<=60; "31 a 60 días"; IF(971<=90; "61 a 90 días"; IF(971<=180; "91 a 180 días"; IF(971<=360; "181 a 360 días"; IF(971<=730; "361 a 730 días"; "Más de 730 días")))))))) → Más de 730 días | E30: «Días de mora» (esta hoja) | F30: —
A31: Tasa | B31: '=IF(F5="","",IF(INDEX('04_Matriz_deterioro'!$D$5:$D$12,MATCH(F5,'04_Matriz_deterioro'!$A$5:$A$12,0))="","",INDEX('04_Matriz_deterioro'!$D$5:$D$12,MATCH(F5,'04_Matriz_deterioro'!$A$5:$A$12,0)))) | C31: Busca la tasa aplicada al tramo de esta factura en la hoja 04 (Matriz de deterioro). Si la factura no tiene tramo o el tramo no tiene tasa medible, queda en blanco. | D31: Fila 1: IF(«Más de 730 días»=""; ""; IF(INDEX([«Tasa aplicada» de «Matriz de deterioro», 8 filas]; MATCH(«Más de 730 días»; [«Tramo» de «Matriz de deterioro», 8 filas]; 0))=""; ""; INDEX([«Tasa aplicada» de «Matriz de deterioro», 8 filas]; MATCH(«Más de 730 días»; [«Tramo» de «Matriz de deterioro», 8 filas]; 0)))) → 100,00 % | E31: «Tramo» (esta hoja), hoja «Matriz de deterioro» | F31: —
A32: Valor presente | B32: '=IF(H5="","",G5*(1-H5)/(1+'02_Parametros'!$B$8/100)^('02_Parametros'!$B$9/12)) | C32: Toma la parte del saldo que se espera cobrar (saldo por uno menos la tasa) y la descuenta con la tasa y el plazo de cobro de la hoja 02 (Parámetros). Sin tasa, queda en blanco. | D32: Fila 1: IF(100,00 %=""; ""; 4.342,93*(1-100,00 %)/(1+0,00/100)^(12,00/12)) → 0,00 | E32: «Tasa» (esta hoja), «Saldo» (esta hoja), hoja «Parámetros» | F32: —
A33: Pérdida | B33: '=IF(I5="","",MAX(G5-I5,0)) | C33: Resta al saldo el valor presente de lo que se espera cobrar; nunca es negativa. Si no hay valor presente, queda en blanco. | D33: Fila 1: IF(0,00=""; ""; MAX(4.342,93-0,00; 0)) → 4.342,93 | E33: «Valor presente» (esta hoja), «Saldo» (esta hoja) | F33: —

Sheet 12_Problemas
A1: Problemas encontrados | H1: ⟵ Inicio | I1: ◀ Anterior | J1: Siguiente ▶
A2: Deterioro de cuentas por cobrar · pérdidas incurridas (PYMES) · Cliente de muestra S.A. · corte 2025-12-31
A4: Código | B4: Descripción | C4: Importe
A5: TRAMO_NO_MEDIBLE | B5: Tramo «1 a 30 días» sin tasa medible (27.938,78): fije la tasa con evidencia. | C5: 27938.78
A6: EVALUACION_INDIVIDUAL | B6: Vialidad Norte S.A.: antigüedad (mora máxima 819 días); evalúe individualmente (11.24). | C6: 9266.58
A7: EVALUACION_INDIVIDUAL | B7: Obras Civiles Pacífico S.A.: antigüedad (mora máxima 971 días); evalúe individualmente (11.24). | C7: 6566.74
A8: EVALUACION_INDIVIDUAL | B8: Hidrosur Cía. Ltda.: antigüedad (mora máxima 451 días); evalúe individualmente (11.24). | C8: 2773.22
A9: EVALUACION_INDIVIDUAL | B9: Minera Austral S.A.: antigüedad (mora máxima 635 días); evalúe individualmente (11.24). | C9: 2142.47
A10: AJUSTE | B10: La pérdida recalculada (20.749,02) difiere de la provisión registrada según el mayor (5.816,04). | C10: 14932.98
A11: NO_DEDUCIBLE | B11: Gasto no deducible del ejercicio: 14.029,21 (límites LRTI). | C11: 14029.21

Sheet 13_Conclusion
A1: Conclusión | H1: ⟵ Inicio | I1: ◀ Anterior | J1: Siguiente ▶
A2: Deterioro de cuentas por cobrar · pérdidas incurridas (PYMES) · Cliente de muestra S.A. · corte 2025-12-31
A4: Concepto | B4: Detalle
A5: Conciliación con el mayor | B5: Población None · mayor None · diferencia None
A6: Evaluación de excepciones
A7: Análisis
A8: Conclusión

Sheet 14_Control_Revision
A1: Control de revisión | H1: ⟵ Inicio | I1: ◀ Anterior
A2: Deterioro de cuentas por cobrar · pérdidas incurridas (PYMES) · Cliente de muestra S.A. · corte 2025-12-31
A4: Fecha | B4: Acción | C4: Estado anterior | D4: Estado nuevo | E4: Actor | F4: Comentario
