Workbook

Sheet 00_Inicio
B2: AuditConsulting Auditores Cía. Ltda. · AUDIT-IA
B4: Préstamos y obligaciones financieras
B6: Cliente | C6: Cliente de muestra S.A. | D6: RUC | E6: 1790000000001
B7: Marco contable | C7: NIIF completas | D7: Fecha de corte | E7: 2025-12-31
B8: Preparó | C8: Ejercicio modelo | D8: Revisó | E8: Pendiente
B10: INDICADORES CLAVE
B11: Ajuste propuesto al pasivo | C11: Problemas encontrados
B12: 5075.37 | C12: 24
B15: IR A LA CÉDULA
B16: Carátula | C16: Programa | D16: Base técnica | E16: Resumen
B17: Parámetros | C17: Universo de préstamos | D17: Condiciones y tasa de interés efectiva | E17: Tabla de amortización
B18: Costo amortizado al corte y del ejercicio | C18: Comisiones y costos de transacción | D18: Recálculo de intereses | E18: Confirmación bancaria y pagos
B19: Covenants y dispensas | C19: Clasificación corriente / no corriente | D19: Endeudamiento y ratios de covenants (analítica, no requisito NIIF) | E19: Conciliación y ajuste
B20: Flujos de la modificación (adenda) descontados a la TIE original | C20: Prueba del 10 % (NIIF 9 3.3.2 y B3.3.6) | D20: Problemas encontrados | E20: Conclusión
B21: Control de revisión
B23: PANORAMA | N23: Datos de los gráficos (fórmulas a las cédulas)
N24: Cifras del resumen | O24: Importe (USD)
N25: ='01_Resumen'!A5 | O25: ='01_Resumen'!B5
N26: ='01_Resumen'!A6 | O26: ='01_Resumen'!B6
N27: ='01_Resumen'!A7 | O27: ='01_Resumen'!B7
N28: ='01_Resumen'!A8 | O28: ='01_Resumen'!B8
N29: ='01_Resumen'!A9 | O29: ='01_Resumen'!B9
N30: ='01_Resumen'!A10 | O30: ='01_Resumen'!B10
N31: ='01_Resumen'!A11 | O31: ='01_Resumen'!B11
N32: ='01_Resumen'!A12 | O32: ='01_Resumen'!B12
N33: ='01_Resumen'!A13 | O33: ='01_Resumen'!B13
N34: ='01_Resumen'!A14 | O34: ='01_Resumen'!B14
N35: ='01_Resumen'!A15 | O35: ='01_Resumen'!B15
N36: ='01_Resumen'!A16 | O36: ='01_Resumen'!B16
N38: Hallazgos de mayor impacto | O38: Importe (USD)
N39: Revelacion incumplimiento (×3) | O39: =SUMIFS('16_Problemas'!$C$5:$C$28,'16_Problemas'!$A$5:$A$28,"REVELACION_INCUMPLIMIENTO",'16_Problemas'!$C$5:$C$28,">0")-SUMIFS('16_Problemas'!$C$5:$C$28,'16_Problemas'!$A$5:$A$28,"REVELACION_INCUMPLIMIENTO",'16_Problemas'!$C$5:$C$28,"<0")
N40: Clasificacion cp lp (×2) | O40: =SUMIFS('16_Problemas'!$C$5:$C$28,'16_Problemas'!$A$5:$A$28,"CLASIFICACION_CP_LP",'16_Problemas'!$C$5:$C$28,">0")-SUMIFS('16_Problemas'!$C$5:$C$28,'16_Problemas'!$A$5:$A$28,"CLASIFICACION_CP_LP",'16_Problemas'!$C$5:$C$28,"<0")
N41: Covenant sin dispensa | O41: =SUMIFS('16_Problemas'!$C$5:$C$28,'16_Problemas'!$A$5:$A$28,"COVENANT_SIN_DISPENSA",'16_Problemas'!$C$5:$C$28,">0")-SUMIFS('16_Problemas'!$C$5:$C$28,'16_Problemas'!$A$5:$A$28,"COVENANT_SIN_DISPENSA",'16_Problemas'!$C$5:$C$28,"<0")
N42: Covenant posterior al corte | O42: =SUMIFS('16_Problemas'!$C$5:$C$28,'16_Problemas'!$A$5:$A$28,"COVENANT_POSTERIOR_AL_CORTE",'16_Problemas'!$C$5:$C$28,">0")-SUMIFS('16_Problemas'!$C$5:$C$28,'16_Problemas'!$A$5:$A$28,"COVENANT_POSTERIOR_AL_CORTE",'16_Problemas'!$C$5:$C$28,"<0")
N43: Modificacion sustancial | O43: =SUMIFS('16_Problemas'!$C$5:$C$28,'16_Problemas'!$A$5:$A$28,"MODIFICACION_SUSTANCIAL",'16_Problemas'!$C$5:$C$28,">0")-SUMIFS('16_Problemas'!$C$5:$C$28,'16_Problemas'!$A$5:$A$28,"MODIFICACION_SUSTANCIAL",'16_Problemas'!$C$5:$C$28,"<0")
N44: Pasivo diferencia (×4) | O44: =SUMIFS('16_Problemas'!$C$5:$C$28,'16_Problemas'!$A$5:$A$28,"PASIVO_DIFERENCIA",'16_Problemas'!$C$5:$C$28,">0")-SUMIFS('16_Problemas'!$C$5:$C$28,'16_Problemas'!$A$5:$A$28,"PASIVO_DIFERENCIA",'16_Problemas'!$C$5:$C$28,"<0")
N45: Confirmacion diferencia | O45: =SUMIFS('16_Problemas'!$C$5:$C$28,'16_Problemas'!$A$5:$A$28,"CONFIRMACION_DIFERENCIA",'16_Problemas'!$C$5:$C$28,">0")-SUMIFS('16_Problemas'!$C$5:$C$28,'16_Problemas'!$A$5:$A$28,"CONFIRMACION_DIFERENCIA",'16_Problemas'!$C$5:$C$28,"<0")
N46: Otros (4 tipos) | O46: =SUMIF('16_Problemas'!$C$5:$C$28,">0")-SUMIF('16_Problemas'!$C$5:$C$28,"<0")-((SUMIFS('16_Problemas'!$C$5:$C$28,'16_Problemas'!$A$5:$A$28,"REVELACION_INCUMPLIMIENTO",'16_Problemas'!$C$5:$C$28,">0")-SUMIFS('16_Problemas'!$C$5:$C$28,'16_Problemas'!$A$5:$A$28,"REVELACION_INCUMPLIMIENTO",'16_Problemas'!$C$5:$C$28,"<0"))+(SUMIFS('16_Problemas'!$C$5:$C$28,'16_Problemas'!$A$5:$A$28,"CLASIFICACION_CP_LP",'16_Problemas'!$C$5:$C$28,">0")-SUMIFS('16_Problemas'!$C$5:$C$28,'16_Problemas'!$A$5:$A$28,"CLASIFICACION_CP_LP",'16_Problemas'!$C$5:$C$28,"<0"))+(SUMIFS('16_Problemas'!$C$5:$C$28,'16_Problemas'!$A$5:$A$28,"COVENANT_SIN_DISPENSA",'16_Problemas'!$C$5:$C$28,">0")-SUMIFS('16_Problemas'!$C$5:$C$28,'16_Problemas'!$A$5:$A$28,"COVENANT_SIN_DISPENSA",'16_Problemas'!$C$5:$C$28,"<0"))+(SUMIFS('16_Problemas'!$C$5:$C$28,'16_Problemas'!$A$5:$A$28,"COVENANT_POSTERIOR_AL_CORTE",'16_Problemas'!$C$5:$C$28,">0")-SUMIFS('16_Problemas'!$C$5:$C$28,'16_Problemas'!$A$5:$A$28,"COVENANT_POSTERIOR_AL_CORTE",'16_Problemas'!$C$5:$C$28,"<0"))+(SUMIFS('16_Problemas'!$C$5:$C$28,'16_Problemas'!$A$5:$A$28,"MODIFICACION_SUSTANCIAL",'16_Problemas'!$C$5:$C$28,">0")-SUMIFS('16_Problemas'!$C$5:$C$28,'16_Problemas'!$A$5:$A$28,"MODIFICACION_SUSTANCIAL",'16_Problemas'!$C$5:$C$28,"<0"))+(SUMIFS('16_Problemas'!$C$5:$C$28,'16_Problemas'!$A$5:$A$28,"PASIVO_DIFERENCIA",'16_Problemas'!$C$5:$C$28,">0")-SUMIFS('16_Problemas'!$C$5:$C$28,'16_Problemas'!$A$5:$A$28,"PASIVO_DIFERENCIA",'16_Problemas'!$C$5:$C$28,"<0"))+(SUMIFS('16_Problemas'!$C$5:$C$28,'16_Problemas'!$A$5:$A$28,"CONFIRMACION_DIFERENCIA",'16_Problemas'!$C$5:$C$28,">0")-SUMIFS('16_Problemas'!$C$5:$C$28,'16_Problemas'!$A$5:$A$28,"CONFIRMACION_DIFERENCIA",'16_Problemas'!$C$5:$C$28,"<0")))

Sheet 00_Caratula
A1: Carátula | H1: ⟵ Inicio | J1: Siguiente ▶
A2: Préstamos y obligaciones financieras · Cliente de muestra S.A. · corte 2025-12-31
A4: Concepto | B4: Detalle
A5: Firma | B5: AuditConsulting Auditores Cía. Ltda.
A6: Cliente | B6: Cliente de muestra S.A.
A7: RUC | B7: 1790000000001
A8: Ejercicio | B8: 2025
A9: Fecha de corte | B9: 2025-12-31
A10: Marco contable | B10: NIIF completas
A11: Herramienta | B11: Préstamos y obligaciones financieras
A12: Rubro | B12: Préstamos y obligaciones financieras
A13: Motor | B13: prestamos_obligaciones 1.0
A14: Versión del papel | B14: v1
A15: Estado | B15: MUESTRA
... A17: Revisó | B17: Pendiente
A18: Aprobó
A19: Fecha de aprobación
A20: Huella de la ejecución (SHA-256)

Sheet 00_Programa
A1: Programa | H1: ⟵ Inicio | I1: ◀ Anterior | J1: Siguiente ▶
A2: Préstamos y obligaciones financieras · Cliente de muestra S.A. · corte 2025-12-31
A4: Código | B4: Objetivo | C4: Afirmación | D4: Procedimiento | E4: Evidencia | F4: Criterio | G4: Referencia
A5: DEU-01 | B5: Existencia e integridad de la deuda | C5: Existencia / Integridad | D5: Confirmar con cada banco saldo, tasa, garantías y covenants; conciliar confirmado vs registrado y vs tabla | E5: Confirmaciones bancarias, cédula 09 | F5: Diferencias explicadas | G5: NIA 505 · NIIF 9 3.1.1
A6: DEU-02 | B6: Tabla de amortización e intereses | C6: Valoración / Corte | D6: Rehacer la tabla contractual, recalcular el interés del ejercicio y el devengado al corte | E6: Contratos, tablas del banco, cédulas 05, 06 y 08 | F6: Diferencias cuantificadas | G6: NIIF 9 4.2.1, 5.3.1 y Apéndice A (método del interés efectivo) · PYMES 11.15–11.20
A7: DEU-03 | B7: Tasa de interés efectiva y comisiones | C7: Valoración | D7: Calcular la TIE con los costos de transacción y comparar el costo amortizado con lo registrado | E7: Liquidaciones de desembolso, cédulas 04 y 07 | F7: Costo amortizado a la TIE | G7: NIIF 9 5.1.1 y Apéndice A · PYMES 11.13
A8: DEU-04 | B8: Covenants y dispensas | C8: Presentación | D8: Recalcular los ratios pactados, verificar la fecha de medición de cada condición, los incumplimientos y la fecha y alcance de las dispensas | E8: Contratos, cartas de dispensa, cédulas 10 y 12 | F8: NIC 1 72B (solo inciden las condiciones a cumplir al cierre o antes), 74–75 y 76ZA (revelación de las condiciones futuras) | G8: NIC 1 69–76 y 76ZA · PYMES 4.7 (NIC 1 72B por analogía, 10.6)
A9: DEU-08 | B9: Revelación de impagos e incumplimientos | C9: Presentación / Revelación | D9: Identificar impagos e infracciones no subsanados al cierre y verificar su revelación en las notas | E9: Contratos, estados de cuenta, cartas del banco, notas a los estados financieros | F9: Detalle del incumplimiento, importe en libros y si se subsanó o renegoció antes de la autorización | G9: NIIF 7 párr. 18–19 · PYMES 11.47 · NIA 560
A10: DEU-05 | B10: Clasificación corriente / no corriente | C10: Presentación | D10: Recalcular lo que vence en 12 meses y aplicar el efecto de los covenants | E10: Cédula 11 | F10: NIC 1 69 c), 72B y 74 | G10: NIC 1 69–76 · PYMES 4.7
A11: DEU-06 | B11: Endeudamiento y capacidad de pago | C11: Presentación / Revelación | D11: Analizar deuda/activos, deuda/patrimonio, deuda/EBITDA y cobertura (analítica, no requisito NIIF). Para el DSCR, obtener del contrato su definición (numerador y denominador) y usarla; sin definición contractual el DSCR se presenta como «DSCR analítico de la firma», como indicador | E11: Estados financieros, contratos de préstamo, cédula 12 | F11: El contrato manda: el «DSCR analítico de la firma» no concluye incumplimiento del covenant | G11: NIA 520 párr. 5–6 · NIA 570 · NIIF 7 18–19
A12: DEU-07 | B12: Modificaciones y refinanciaciones | C12: Valoración | D12: Obtener la adenda con sus flujos, cargar en el anexo de flujos los contractuales originales restantes y los modificados y resolver la prueba del 10 % descontando a la tasa de interés efectiva original | E12: Adendas con su tabla de flujos, liquidaciones de comisiones, confirmaciones, cédulas 14 y 15 | F12: Sin flujos comparables la prueba no concluye: «dato insuficiente: conclusión bloqueada»; nunca se presume «no sustancial» | G12: NIIF 9 3.3.2 y B3.3.6 · PYMES 11.37 (sin umbral; el 10 % por analogía, 10.6) · NIA 560

Sheet 00_Fuentes
A1: Base técnica | H1: ⟵ Inicio | I1: ◀ Anterior | J1: Siguiente ▶
A2: Préstamos y obligaciones financieras · Cliente de muestra S.A. · corte 2025-12-31
A4: Categoría | B4: Documento | C4: Párrafos | D4: URL | E4: Verificada
A5: NIA · NIA 505 | B5: Confirmación externa de saldos, tasas, garantías y covenants con los bancos. | C5: párr. 7 y 14
A6: NIA · NIA 500 | B6: Exactitud e integridad del anexo de préstamos contra el mayor y los contratos. | C6: párr. 9
A7: NIA · NIA 540 (Revisada) | B7: Método (TIE), datos (contratos) y supuestos del costo amortizado. | C7: párr. 13, 18–30 (22–25: métodos, supuestos significativos y datos)
A8: NIA · NIA 560 | B8: Dispensas, refinanciaciones y pagos posteriores al cierre. | C8: párr. 6
A9: NIA · NIA 570 (Revisada) | B9: Incumplimientos de covenants y capacidad de pago como indicios de empresa en marcha. La NIA 570 (Revisada 2024) rige para períodos desde el 15-12-2026. | C9: párr. 10–16

Sheet 01_Resumen
A1: Resumen | H1: ⟵ Inicio | I1: ◀ Anterior | J1: Siguiente ▶
A2: Préstamos y obligaciones financieras · Cliente de muestra S.A. · corte 2025-12-31
A4: Concepto | B4: Importe
A5: Obligaciones financieras registradas (capital + intereses) | B5: ='13_Conciliacion'!E12
A6: Costo amortizado recalculado (con interés devengado) | B6: ='13_Conciliacion'!B12
A7: Ajuste propuesto al pasivo | B7: =B6-B5
A8: Capital contractual según tablas | B8: =SUM('06_Costo_amortizado'!E5:E11)
A9: Interés contractual devengado al corte | B9: =SUM('06_Costo_amortizado'!F5:F11)
A10: Intereses por pagar registrados | B10: ='13_Conciliacion'!D12
A11: Pasivo corriente auditado | B11: ='13_Conciliacion'!G12
A12: Pasivo no corriente auditado | B12: ='13_Conciliacion'!H12
A13: Reclasificación a corriente por covenants | B13: =SUM('11_Clasificacion'!G5:G11)-SUM('11_Clasificacion'!E5:E11)
A14: Gasto financiero del ejercicio (TIE) | B14: ='13_Conciliacion'!I12
A15: Diferencia de gasto financiero (préstamos con gasto registrado) | B15: =SUM('08_Intereses'!G5:G11)
A16: Costos de transacción por amortizar al corte | B16: =SUM('07_Comisiones'!G5:G11)
A18: ⓘ Cómo se calcula esta hoja
A19: Columna | B19: Fórmula (Excel) | C19: Cómo se calcula (sencillo) | D19: Ejemplo con números reales | E19: De dónde viene | F19: Norma
A20: Importe | B20: '='13_Conciliacion'!E12 | C20: Trae cada importe de la cédula donde se calcula, concepto por concepto: los saldos auditados, registrados, el ajuste, la clasificación y el gasto salen de los totales de la hoja 13 (Conciliación y ajuste); el capital y el interés devengado, de la hoja 06 (Costo amortizado); la diferencia de gasto, de la hoja 08; los costos por amortizar, de la hoja 07; la reclasificación por covenants, de la hoja 11. El ajuste es el pasivo recalculado menos el registrado de este mismo resumen. | D20: Fila 1: 654.889,82 → 654.889,82 | E20: hoja «Conciliación y ajuste» | F20: —

Sheet 02_Parametros
A1: Parámetros | H1: ⟵ Inicio | I1: ◀ Anterior | J1: Siguiente ▶
A2: Préstamos y obligaciones financieras · Cliente de muestra S.A. · corte 2025-12-31
A4: Parámetro | B4: Valor | C4: Sustento
A5: Fecha de corte | B5: 46022 | C5: Ficha del encargo
A6: Inicio del ejercicio (corte − 12 meses) | B6: 45657 | C6: Base del gasto financiero del ejercicio
A7: Marco y ruta de cálculo | B7: NIIF completas · NIIF 9 (5.1.1, 4.2.1, 5.3.1 y Apéndice A) y NIC 1 69–76 (modificaciones 2020/2022, vigentes desde 2024) | C7: El modelo de costo amortizado es el mismo en ambos marcos; cambian las citas
A8: Total de activos de la entidad al corte | B8: 2500000 | C8: Estados financieros al corte
A9: Patrimonio de la entidad al corte | B9: 800000 | C9: Estados financieros al corte (admite negativo)
A10: EBITDA del ejercicio | B10: 300000 | C10: Estado de resultados; use la definición del contrato, que manda sobre cualquier otra
A11: EBIT (utilidad operativa) del ejercicio | B11: 220000 | C11: Estado de resultados
A12: Efectivo disponible para el servicio de la deuda | B12: 200000 | C12: Use la definición del contrato de préstamo, que manda sobre cualquier otra
A13: Base de la cobertura de intereses (EBITDA / EBIT) | B13: EBITDA | C13: EBITDA o EBIT, según el contrato
A14: Límite máximo deuda / activos (veces) | B14: 0.6 | C14: Contrato de préstamo
A15: Límite máximo deuda / patrimonio (veces) | B15: 1.2 | C15: Contrato de préstamo
A16: Límite máximo deuda / EBITDA (veces) | B16: 1.8 | C16: Contrato de préstamo
A17: Límite mínimo de cobertura de intereses (veces) | B17: 3 | C17: Contrato de préstamo
A18: Límite mínimo DSCR (veces) | B18: 1.25 | C18: Contrato de préstamo
A19: Definición contractual del DSCR (numerador ÷ denominador, según el contrato) | B19: Flujo de caja operativo antes de intereses ÷ servicio de la deuda del ejercicio (cláusula 8.2 del contrato) | C19: Transcriba la definición del contrato (numerador ÷ denominador). El contrato manda: sin esta definición el DSCR se muestra como «DSCR analítico de la firma» y no concluye incumplimiento del covenant
A20: Servicio de la deuda del DSCR según el contrato | C20: Contrato de préstamo; vacío = servicio de la deuda del ejercicio según las tablas (cédula 12)

Sheet 03_Prestamos
A1: Universo de préstamos | H1: ⟵ Inicio | I1: ◀ Anterior | J1: Siguiente ▶
A2: Préstamos y obligaciones financieras · Cliente de muestra S.A. · corte 2025-12-31
A4: Operación | B4: Banco / acreedor | C4: Fecha de desembolso | D4: Monto desembolsado | E4: Plazo (meses) | F4: Tasa nominal anual (%) | G4: Periodicidad de pago (mensual/trimestral/semestral/anual) | H4: Sistema de amortización (francés/alemán/bullet) | I4: Comisiones y costos de transacción | J4: Tratamiento de las comisiones por el cliente (TIE/gasto) | K4: Pagos realizados en el año (capital + interés) | L4: Saldo de capital confirmado por el banco | M4: Saldo de capital registrado | N4: Intereses por pagar registrados | O4: Gasto financiero registrado del año | P4: Porción corriente registrada | Q4: Covenant (deuda/activos, deuda/patrimonio, deuda/EBITDA, cobertura de intereses, DSCR) | R4: Incumplimiento de covenant declarado (sí/no) | S4: Fecha de la dispensa del banco | T4: Fin del período de gracia de la dispensa | U4: Fecha de medición del covenant | V4: Modificación de condiciones en el ejercicio (sí/no) | W4: Fecha de la modificación (adenda) | X4: Comisiones pagadas al prestamista netas de las recibidas por la modificación
A5: OP-101 | B5: Banco Pichincha | C5: 45306 | D5: 120000 | E5: 36 | F5: 11 | G5: Mensual | H5: Francés | I5: 2400 | J5: Gasto | K5: 47143.75 | L5: 47940.12 | M5: 47940.12 | N5: 226.81 | O5: 7478.25 | V5: No
A6: OP-102 | B6: Produbanco | C6: 45717 | D6: 200000 | E6: 60 | F6: 10 | G6: Trimestral | H6: Alemán | I6: 3000 | J6: TIE | K6: 44250 | L6: 170000 | M6: 167760.65 | O6: 15010.65 | P6: 41494.17 | Q6: Deuda / EBITDA | R6: Sí | S6: 46042 | T6: 46568 | U6: 46022 | V6: No
A7: OP-103 | B7: Banco Guayaquil | C7: 45108 | D7: 300000 | E7: 48 | F7: 9.5 | G7: Semestral | H7: Francés | K7: 91897.18 | L7: 163882.07 | M7: 163882.07 | N7: 7742.09 | O7: 17317.78 | P7: 70000 | Q7: Cobertura de intereses | R7: No | V7: Sí | W7: 45992 | X7: 1500
A8: OP-104 | B8: Banco del Pacífico | C8: 45838 | D8: 150000 | E8: 24 | F8: 12 | G8: Semestral | H8: Bullet | I8: 1500 | J8: TIE | K8: 9000 | L8: 150000 | M8: 145000 | N8: 49.45 | O8: 9392.86 | V8: No
A9: OP-105 | B9: Corporación Financiera Nacional | C9: 44562 | D9: 80000 | E9: 60 | F9: 8 | G9: Mensual | H9: Francés | K9: 19465.34 | L9: 20135.32 | M9: 20135.32 | N9: 129.91 | O9: 2250.69 | P9: 18653.85 | Q9: Deuda / patrimonio | R9: Sí | S9: 46006 | T9: 46477 | U9: 46022 | V9: Sí
A10: OP-106 | B10: Banco Internacional | C10: 45931 | D10: 50000 | E10: 12 | F10: 13 | G10: Mensual | H10: Francés | K10: 8931.73 | L10: 42109.09 | M10: 42109.09 | N10: 441.47 | O10: 1482.29 | P10: 42550.56 | V10: No
A11: OP-107 | B11: Banco Bolivariano | C11: 45474 | D11: 100000 | E11: 36 | F11: 10.5 | G11: Trimestral | H11: Alemán | I11: 1000 | J11: TIE | K11: 40000 | L11: 58333.33 | M11: 57958.23 | N11: 1514.61 | O11: 7881.2 | P11: 34938.2 | Q11: DSCR | U11: 46203 | V11: No

Sheet 04_Condiciones_TIE
A1: Condiciones y tasa de interés efectiva | H1: ⟵ Inicio | I1: ◀ Anterior | J1: Siguiente ▶
A2: Préstamos y obligaciones financieras · Cliente de muestra S.A. · corte 2025-12-31
A4: Operación | B4: Sistema | C4: Monto | D4: Comisiones y costos | E4: Importe neto recibido (5.1.1 / 11.13) | F4: Plazo (meses) | G4: Meses por período | H4: Períodos | I4: Tasa nominal anual (%) | J4: Tasa periódica nominal | K4: Cuota fija (francés) | L4: TIE periódica (TIR de los flujos) | M4: TIE anual efectiva | N4: Tasa efectiva anual contractual | O4: Efecto de las comisiones en la tasa
A5: OP-101 | B5: ='03_Prestamos'!H5 | C5: ='03_Prestamos'!D5 | D5: =N('03_Prestamos'!I5) | E5: =C5-D5 | F5: ='03_Prestamos'!E5 | G5: =IF('03_Prestamos'!G5="Mensual",1,IF('03_Prestamos'!G5="Trimestral",3,IF('03_Prestamos'!G5="Semestral",6,12))) | H5: =F5/G5 | I5: ='03_Prestamos'!F5 | J5: =I5/100*G5/12 | K5: =IF(B5="Francés",PMT(J5,H5,-C5),"") | L5: =IRR('05_Tabla_amortizacion'!I5:I41,J5) | M5: =(1+L5)^(12/G5)-1 | N5: =(1+J5)^(12/G5)-1 | O5: =M5-N5
A6: OP-102 | B6: ='03_Prestamos'!H6 | C6: ='03_Prestamos'!D6 | D6: =N('03_Prestamos'!I6) | E6: =C6-D6 | F6: ='03_Prestamos'!E6 | G6: =IF('03_Prestamos'!G6="Mensual",1,IF('03_Prestamos'!G6="Trimestral",3,IF('03_Prestamos'!G6="Semestral",6,12))) | H6: =F6/G6 | I6: ='03_Prestamos'!F6 | J6: =I6/100*G6/12 | K6: =IF(B6="Francés",PMT(J6,H6,-C6),"") | L6: =IRR('05_Tabla_amortizacion'!I42:I62,J6) | M6: =(1+L6)^(12/G6)-1 | N6: =(1+J6)^(12/G6)-1 | O6: =M6-N6
A7: OP-103 | B7: ='03_Prestamos'!H7 | C7: ='03_Prestamos'!D7 | D7: =N('03_Prestamos'!I7) | E7: =C7-D7 | F7: ='03_Prestamos'!E7 | G7: =IF('03_Prestamos'!G7="Mensual",1,IF('03_Prestamos'!G7="Trimestral",3,IF('03_Prestamos'!G7="Semestral",6,12))) | H7: =F7/G7 | I7: ='03_Prestamos'!F7 | J7: =I7/100*G7/12 | K7: =IF(B7="Francés",PMT(J7,H7,-C7),"") | L7: =IRR('05_Tabla_amortizacion'!I63:I71,J7) | M7: =(1+L7)^(12/G7)-1 | N7: =(1+J7)^(12/G7)-1 | O7: =M7-N7
A8: OP-104 | B8: ='03_Prestamos'!H8 | C8: ='03_Prestamos'!D8 | D8: =N('03_Prestamos'!I8) | E8: =C8-D8 | F8: ='03_Prestamos'!E8 | G8: =IF('03_Prestamos'!G8="Mensual",1,IF('03_Prestamos'!G8="Trimestral",3,IF('03_Prestamos'!G8="Semestral",6,12))) | H8: =F8/G8 | I8: ='03_Prestamos'!F8 | J8: =I8/100*G8/12 | K8: =IF(B8="Francés",PMT(J8,H8,-C8),"") | L8: =IRR('05_Tabla_amortizacion'!I72:I76,J8) | M8: =(1+L8)^(12/G8)-1 | N8: =(1+J8)^(12/G8)-1 | O8: =M8-N8
A9: OP-105 | B9: ='03_Prestamos'!H9 | C9: ='03_Prestamos'!D9 | D9: =N('03_Prestamos'!I9) | E9: =C9-D9 | F9: ='03_Prestamos'!E9 | G9: =IF('03_Prestamos'!G9="Mensual",1,IF('03_Prestamos'!G9="Trimestral",3,IF('03_Prestamos'!G9="Semestral",6,12))) | H9: =F9/G9 | I9: ='03_Prestamos'!F9 | J9: =I9/100*G9/12 | K9: =IF(B9="Francés",PMT(J9,H9,-C9),"") | L9: =IRR('05_Tabla_amortizacion'!I77:I137,J9) | M9: =(1+L9)^(12/G9)-1 | N9: =(1+J9)^(12/G9)-1 | O9: =M9-N9
A10: OP-106 | B10: ='03_Prestamos'!H10 | C10: ='03_Prestamos'!D10 | D10: =N('03_Prestamos'!I10) | E10: =C10-D10 | F10: ='03_Prestamos'!E10 | G10: =IF('03_Prestamos'!G10="Mensual",1,IF('03_Prestamos'!G10="Trimestral",3,IF('03_Prestamos'!G10="Semestral",6,12))) | H10: =F10/G10 | I10: ='03_Prestamos'!F10 | J10: =I10/100*G10/12 | K10: =IF(B10="Francés",PMT(J10,H10,-C10),"") | L10: =IRR('05_Tabla_amortizacion'!I138:I150,J10) | M10: =(1+L10)^(12/G10)-1 | N10: =(1+J10)^(12/G10)-1 | O10: =M10-N10
A11: OP-107 | B11: ='03_Prestamos'!H11 | C11: ='03_Prestamos'!D11 | D11: =N('03_Prestamos'!I11) | E11: =C11-D11 | F11: ='03_Prestamos'!E11 | G11: =IF('03_Prestamos'!G11="Mensual",1,IF('03_Prestamos'!G11="Trimestral",3,IF('03_Prestamos'!G11="Semestral",6,12))) | H11: =F11/G11 | I11: ='03_Prestamos'!F11 | J11: =I11/100*G11/12 | K11: =IF(B11="Francés",PMT(J11,H11,-C11),"") | L11: =IRR('05_Tabla_amortizacion'!I151:I163,J11) | M11: =(1+L11)^(12/G11)-1 | N11: =(1+J11)^(12/G11)-1 | O11: =M11-N11
A12: TOTAL | C12: =SUM(C5:C11) | D12: =SUM(D5:D11) | E12: =SUM(E5:E11)
A14: ⓘ Cómo se calcula esta hoja
A15: Columna | B15: Fórmula (Excel) | C15: Cómo se calcula (sencillo) | D15: Ejemplo con números reales | E15: De dónde viene | F15: Norma
A16: Sistema | B16: '='03_Prestamos'!H5 | C16: Copia el sistema de amortización del préstamo (francés, alemán o bullet) tal como quedó en la hoja 03 (Universo de préstamos). | D16: Fila 1: «Francés» → Francés | E16: hoja «Universo de préstamos» | F16: —
A17: Monto | B17: '='03_Prestamos'!D5 | C17: Copia el monto desembolsado por el banco para esta operación desde la hoja 03 (Universo de préstamos). | D17: Fila 1: 120.000,00 → 120.000,00 | E17: hoja «Universo de préstamos» | F17: —
A18: Comisiones y costos | B18: '=N('03_Prestamos'!I5) | C18: Trae las comisiones y costos de transacción pagados al obtener el préstamo desde la hoja 03 (Universo de préstamos); si el cliente no los informó, se toman como cero. | D18: Fila 1: N(2.400,00) → 2.400,00 | E18: hoja «Universo de préstamos» | F18: —
A19: Importe neto recibido (5.1.1 / 11.13) | B19: '=C5-D5 | C19: Resta al monto desembolsado las comisiones y costos de transacción: es el dinero que realmente recibió la entidad y el punto de partida del costo amortizado. | D19: Fila 1: 120.000,00-2.400,00 → 117.600,00 | E19: «Monto» (esta hoja), «Comisiones y costos» (esta hoja) | F19: —
A20: Plazo (meses) | B20: '='03_Prestamos'!E5 | C20: Copia el plazo total del préstamo, en meses, informado en la hoja 03 (Universo de préstamos). | D20: Fila 1: 36,00 → 36 | E20: hoja «Universo de préstamos» | F20: —
A21: Meses por período | B21: '=IF('03_Prestamos'!G5="Mensual",1,IF('03_Prestamos'!G5="Trimestral",3,IF('03_Prestamos'!G5="Semestral",6,12))) | C21: Convierte la periodicidad de pago de la hoja 03 en meses: mensual = 1, trimestral = 3, semestral = 6 y cualquier otra (anual) = 12. | D21: Fila 1: IF(«Mensual»="Mensual"; 1; IF(«Mensual»="Trimestral"; 3; IF(«Mensual»="Semestral"; 6; 12))) → 1 | E21: hoja «Universo de préstamos» | F21: —
A22: Períodos | B22: '=F5/G5 | C22: Divide el plazo en meses para los meses de cada período: es el número de cuotas que tiene el préstamo. | D22: Fila 1: 36/1 → 36 | E22: «Plazo (meses)» (esta hoja), «Meses por período» (esta hoja) | F22: —
A23: Tasa nominal anual (%) | B23: '='03_Prestamos'!F5 | C23: Copia la tasa de interés nominal anual pactada en el contrato, tal como figura en la hoja 03 (Universo de préstamos). | D23: Fila 1: 11,00 → 11,00 | E23: hoja «Universo de préstamos» | F23: —
A24: Tasa periódica nominal | B24: '=I5/100*G5/12 | C24: Pasa la tasa nominal anual a la tasa de cada período: la divide para 100 y la multiplica por los meses del período sobre 12. | D24: Fila 1: 11,00/100*1/12 → 0,92 % | E24: «Tasa nominal anual (%)» (esta hoja), «Meses por período» (esta hoja) | F24: —
A25: Cuota fija (francés) | B25: '=IF(B5="Francés",PMT(J5,H5,-C5),"") | C25: Solo para el sistema francés: calcula con la función PAGO la cuota constante que amortiza el monto en el número de períodos a la tasa periódica nominal. En alemán o bullet queda en blanco. | D25: Fila 1: IF(«Francés»="Francés"; PMT(0,92 %; 36; -120.000,00); "") → 3.928,65 | E25: «Sistema» (esta hoja), «Tasa periódica nominal» (esta hoja), «Períodos» (esta hoja), «Monto» (esta hoja) | F25: —
A26: TIE periódica (TIR de los flujos) | B26: '=IRR('05_Tabla_amortizacion'!I5:I41,J5) | C26: Calcula la TIR de los flujos de esta operación en la hoja 05 (Tabla de amortización): el importe neto recibido en negativo y luego cada pago. Es la tasa que iguala los pagos con lo recibido, e incluye el efecto de las comisiones. | D26: Fila 1: IRR([«Flujo para la TIE» de «Tabla de amortización», 37 filas]; 0,92 %) → 1,03 % | E26: «Tasa periódica nominal» (esta hoja), hoja «Tabla de amortización» | F26: —
... A29: Efecto de las comisiones en la tasa | B29: '=M5-N5 | C29: Resta la tasa efectiva anual contractual de la TIE anual efectiva: muestra cuántos puntos de tasa suman las comisiones y costos de transacción. | D29: Fila 1: 13,13 %-11,57 % → 1,56 % | E29: «TIE anual efectiva» (esta hoja), «Tasa efectiva anual contractual» (esta hoja) | F29: —

Sheet 05_Tabla_amortizacion
A1: Tabla de amortización | H1: ⟵ Inicio | I1: ◀ Anterior | J1: Siguiente ▶
A2: Préstamos y obligaciones financieras · Cliente de muestra S.A. · corte 2025-12-31
A4: Operación | B4: Período | C4: Vencimiento | D4: Pago contractual | E4: Capital inicial | F4: Interés nominal | G4: Capital amortizado | H4: Capital final | I4: Flujo para la TIE | J4: Costo amortizado inicial | K4: Interés a la TIE (Apéndice A) | L4: Amortización (pago − interés) | M4: Costo amortizado final
A5: OP-101 | B5: 0 | C5: 45306 | H5: ='04_Condiciones_TIE'!C5 | I5: =-'04_Condiciones_TIE'!E5 | M5: ='04_Condiciones_TIE'!E5
A6: OP-101 | B6: 1 | C6: 45337 | D6: =IF('04_Condiciones_TIE'!B5="Francés",'04_Condiciones_TIE'!K5,IF('04_Condiciones_TIE'!B5="Alemán",'04_Condiciones_TIE'!C5/'04_Condiciones_TIE'!H5+F6,IF(B6<'04_Condiciones_TIE'!H5,F6,F6+E6))) | E6: =H5 | F6: =E6*'04_Condiciones_TIE'!J5 | G6: =D6-F6 | H6: =E6-G6 | I6: =D6 | J6: =M5 | K6: =J6*'04_Condiciones_TIE'!L5 | L6: =D6-K6 | M6: =J6-L6
A7: OP-101 | B7: 2 | C7: 45366 | D7: =IF('04_Condiciones_TIE'!B5="Francés",'04_Condiciones_TIE'!K5,IF('04_Condiciones_TIE'!B5="Alemán",'04_Condiciones_TIE'!C5/'04_Condiciones_TIE'!H5+F7,IF(B7<'04_Condiciones_TIE'!H5,F7,F7+E7))) | E7: =H6 | F7: =E7*'04_Condiciones_TIE'!J5 | G7: =D7-F7 | H7: =E7-G7 | I7: =D7 | J7: =M6 | K7: =J7*'04_Condiciones_TIE'!L5 | L7: =D7-K7 | M7: =J7-L7
A8: OP-101 | B8: 3 | C8: 45397 | D8: =IF('04_Condiciones_TIE'!B5="Francés",'04_Condiciones_TIE'!K5,IF('04_Condiciones_TIE'!B5="Alemán",'04_Condiciones_TIE'!C5/'04_Condiciones_TIE'!H5+F8,IF(B8<'04_Condiciones_TIE'!H5,F8,F8+E8))) | E8: =H7 | F8: =E8*'04_Condiciones_TIE'!J5 | G8: =D8-F8 | H8: =E8-G8 | I8: =D8 | J8: =M7 | K8: =J8*'04_Condiciones_TIE'!L5 | L8: =D8-K8 | M8: =J8-L8
A9: OP-101 | B9: 4 | C9: 45427 | D9: =IF('04_Condiciones_TIE'!B5="Francés",'04_Condiciones_TIE'!K5,IF('04_Condiciones_TIE'!B5="Alemán",'04_Condiciones_TIE'!C5/'04_Condiciones_TIE'!H5+F9,IF(B9<'04_Condiciones_TIE'!H5,F9,F9+E9))) | E9: =H8 | F9: =E9*'04_Condiciones_TIE'!J5 | G9: =D9-F9 | H9: =E9-G9 | I9: =D9 | J9: =M8 | K9: =J9*'04_Condiciones_TIE'!L5 | L9: =D9-K9 | M9: =J9-L9
A10: OP-101 | B10: 5 | C10: 45458 | D10: =IF('04_Condiciones_TIE'!B5="Francés",'04_Condiciones_TIE'!K5,IF('04_Condiciones_TIE'!B5="Alemán",'04_Condiciones_TIE'!C5/'04_Condiciones_TIE'!H5+F10,IF(B10<'04_Condiciones_TIE'!H5,F10,F10+E10))) | E10: =H9 | F10: =E10*'04_Condiciones_TIE'!J5 | G10: =D10-F10 | H10: =E10-G10 | I10: =D10 | J10: =M9 | K10: =J10*'04_Condiciones_TIE'!L5 | L10: =D10-K10 | M10: =J10-L10
A11: OP-101 | B11: 6 | C11: 45488 | D11: =IF('04_Condiciones_TIE'!B5="Francés",'04_Condiciones_TIE'!K5,IF('04_Condiciones_TIE'!B5="Alemán",'04_Condiciones_TIE'!C5/'04_Condiciones_TIE'!H5+F11,IF(B11<'04_Condiciones_TIE'!H5,F11,F11+E11))) | E11: =H10 | F11: =E11*'04_Condiciones_TIE'!J5 | G11: =D11-F11 | H11: =E11-G11 | I11: =D11 | J11: =M10 | K11: =J11*'04_Condiciones_TIE'!L5 | L11: =D11-K11 | M11: =J11-L11
A12: OP-101 | B12: 7 | C12: 45519 | D12: =IF('04_Condiciones_TIE'!B5="Francés",'04_Condiciones_TIE'!K5,IF('04_Condiciones_TIE'!B5="Alemán",'04_Condiciones_TIE'!C5/'04_Condiciones_TIE'!H5+F12,IF(B12<'04_Condiciones_TIE'!H5,F12,F12+E12))) | E12: =H11 | F12: =E12*'04_Condiciones_TIE'!J5 | G12: =D12-F12 | H12: =E12-G12 | I12: =D12 | J12: =M11 | K12: =J12*'04_Condiciones_TIE'!L5 | L12: =D12-K12 | M12: =J12-L12
A13: OP-101 | B13: 8 | C13: 45550 | D13: =IF('04_Condiciones_TIE'!B5="Francés",'04_Condiciones_TIE'!K5,IF('04_Condiciones_TIE'!B5="Alemán",'04_Condiciones_TIE'!C5/'04_Condiciones_TIE'!H5+F13,IF(B13<'04_Condiciones_TIE'!H5,F13,F13+E13))) | E13: =H12 | F13: =E13*'04_Condiciones_TIE'!J5 | G13: =D13-F13 | H13: =E13-G13 | I13: =D13 | J13: =M12 | K13: =J13*'04_Condiciones_TIE'!L5 | L13: =D13-K13 | M13: =J13-L13
A14: OP-101 | B14: 9 | C14: 45580 | D14: =IF('04_Condiciones_TIE'!B5="Francés",'04_Condiciones_TIE'!K5,IF('04_Condiciones_TIE'!B5="Alemán",'04_Condiciones_TIE'!C5/'04_Condiciones_TIE'!H5+F14,IF(B14<'04_Condiciones_TIE'!H5,F14,F14+E14))) | E14: =H13 | F14: =E14*'04_Condiciones_TIE'!J5 | G14: =D14-F14 | H14: =E14-G14 | I14: =D14 | J14: =M13 | K14: =J14*'04_Condiciones_TIE'!L5 | L14: =D14-K14 | M14: =J14-L14
A15: OP-101 | B15: 10 | C15: 45611 | D15: =IF('04_Condiciones_TIE'!B5="Francés",'04_Condiciones_TIE'!K5,IF('04_Condiciones_TIE'!B5="Alemán",'04_Condiciones_TIE'!C5/'04_Condiciones_TIE'!H5+F15,IF(B15<'04_Condiciones_TIE'!H5,F15,F15+E15))) | E15: =H14 | F15: =E15*'04_Condiciones_TIE'!J5 | G15: =D15-F15 | H15: =E15-G15 | I15: =D15 | J15: =M14 | K15: =J15*'04_Condiciones_TIE'!L5 | L15: =D15-K15 | M15: =J15-L15
A16: OP-101 | B16: 11 | C16: 45641 | D16: =IF('04_Condiciones_TIE'!B5="Francés",'04_Condiciones_TIE'!K5,IF('04_Condiciones_TIE'!B5="Alemán",'04_Condiciones_TIE'!C5/'04_Condiciones_TIE'!H5+F16,IF(B16<'04_Condiciones_TIE'!H5,F16,F16+E16))) | E16: =H15 | F16: =E16*'04_Condiciones_TIE'!J5 | G16: =D16-F16 | H16: =E16-G16 | I16: =D16 | J16: =M15 | K16: =J16*'04_Condiciones_TIE'!L5 | L16: =D16-K16 | M16: =J16-L16
A17: OP-101 | B17: 12 | C17: 45672 | D17: =IF('04_Condiciones_TIE'!B5="Francés",'04_Condiciones_TIE'!K5,IF('04_Condiciones_TIE'!B5="Alemán",'04_Condiciones_TIE'!C5/'04_Condiciones_TIE'!H5+F17,IF(B17<'04_Condiciones_TIE'!H5,F17,F17+E17))) | E17: =H16 | F17: =E17*'04_Condiciones_TIE'!J5 | G17: =D17-F17 | H17: =E17-G17 | I17: =D17 | J17: =M16 | K17: =J17*'04_Condiciones_TIE'!L5 | L17: =D17-K17 | M17: =J17-L17
A18: OP-101 | B18: 13 | C18: 45703 | D18: =IF('04_Condiciones_TIE'!B5="Francés",'04_Condiciones_TIE'!K5,IF('04_Condiciones_TIE'!B5="Alemán",'04_Condiciones_TIE'!C5/'04_Condiciones_TIE'!H5+F18,IF(B18<'04_Condiciones_TIE'!H5,F18,F18+E18))) | E18: =H17 | F18: =E18*'04_Condiciones_TIE'!J5 | G18: =D18-F18 | H18: =E18-G18 | I18: =D18 | J18: =M17 | K18: =J18*'04_Condiciones_TIE'!L5 | L18: =D18-K18 | M18: =J18-L18
A19: OP-101 | B19: 14 | C19: 45731 | D19: =IF('04_Condiciones_TIE'!B5="Francés",'04_Condiciones_TIE'!K5,IF('04_Condiciones_TIE'!B5="Alemán",'04_Condiciones_TIE'!C5/'04_Condiciones_TIE'!H5+F19,IF(B19<'04_Condiciones_TIE'!H5,F19,F19+E19))) | E19: =H18 | F19: =E19*'04_Condiciones_TIE'!J5 | G19: =D19-F19 | H19: =E19-G19 | I19: =D19 | J19: =M18 | K19: =J19*'04_Condiciones_TIE'!L5 | L19: =D19-K19 | M19: =J19-L19
A20: OP-101 | B20: 15 | C20: 45762 | D20: =IF('04_Condiciones_TIE'!B5="Francés",'04_Condiciones_TIE'!K5,IF('04_Condiciones_TIE'!B5="Alemán",'04_Condiciones_TIE'!C5/'04_Condiciones_TIE'!H5+F20,IF(B20<'04_Condiciones_TIE'!H5,F20,F20+E20))) | E20: =H19 | F20: =E20*'04_Condiciones_TIE'!J5 | G20: =D20-F20 | H20: =E20-G20 | I20: =D20 | J20: =M19 | K20: =J20*'04_Condiciones_TIE'!L5 | L20: =D20-K20 | M20: =J20-L20
A21: OP-101 | B21: 16 | C21: 45792 | D21: =IF('04_Condiciones_TIE'!B5="Francés",'04_Condiciones_TIE'!K5,IF('04_Condiciones_TIE'!B5="Alemán",'04_Condiciones_TIE'!C5/'04_Condiciones_TIE'!H5+F21,IF(B21<'04_Condiciones_TIE'!H5,F21,F21+E21))) | E21: =H20 | F21: =E21*'04_Condiciones_TIE'!J5 | G21: =D21-F21 | H21: =E21-G21 | I21: =D21 | J21: =M20 | K21: =J21*'04_Condiciones_TIE'!L5 | L21: =D21-K21 | M21: =J21-L21
A22: OP-101 | B22: 17 | C22: 45823 | D22: =IF('04_Condiciones_TIE'!B5="Francés",'04_Condiciones_TIE'!K5,IF('04_Condiciones_TIE'!B5="Alemán",'04_Condiciones_TIE'!C5/'04_Condiciones_TIE'!H5+F22,IF(B22<'04_Condiciones_TIE'!H5,F22,F22+E22))) | E22: =H21 | F22: =E22*'04_Condiciones_TIE'!J5 | G22: =D22-F22 | H22: =E22-G22 | I22: =D22 | J22: =M21 | K22: =J22*'04_Condiciones_TIE'!L5 | L22: =D22-K22 | M22: =J22-L22
A23: OP-101 | B23: 18 | C23: 45853 | D23: =IF('04_Condiciones_TIE'!B5="Francés",'04_Condiciones_TIE'!K5,IF('04_Condiciones_TIE'!B5="Alemán",'04_Condiciones_TIE'!C5/'04_Condiciones_TIE'!H5+F23,IF(B23<'04_Condiciones_TIE'!H5,F23,F23+E23))) | E23: =H22 | F23: =E23*'04_Condiciones_TIE'!J5 | G23: =D23-F23 | H23: =E23-G23 | I23: =D23 | J23: =M22 | K23: =J23*'04_Condiciones_TIE'!L5 | L23: =D23-K23 | M23: =J23-L23
A24: OP-101 | B24: 19 | C24: 45884 | D24: =IF('04_Condiciones_TIE'!B5="Francés",'04_Condiciones_TIE'!K5,IF('04_Condiciones_TIE'!B5="Alemán",'04_Condiciones_TIE'!C5/'04_Condiciones_TIE'!H5+F24,IF(B24<'04_Condiciones_TIE'!H5,F24,F24+E24))) | E24: =H23 | F24: =E24*'04_Condiciones_TIE'!J5 | G24: =D24-F24 | H24: =E24-G24 | I24: =D24 | J24: =M23 | K24: =J24*'04_Condiciones_TIE'!L5 | L24: =D24-K24 | M24: =J24-L24
A25: OP-101 | B25: 20 | C25: 45915 | D25: =IF('04_Condiciones_TIE'!B5="Francés",'04_Condiciones_TIE'!K5,IF('04_Condiciones_TIE'!B5="Alemán",'04_Condiciones_TIE'!C5/'04_Condiciones_TIE'!H5+F25,IF(B25<'04_Condiciones_TIE'!H5,F25,F25+E25))) | E25: =H24 | F25: =E25*'04_Condiciones_TIE'!J5 | G25: =D25-F25 | H25: =E25-G25 | I25: =D25 | J25: =M24 | K25: =J25*'04_Condiciones_TIE'!L5 | L25: =D25-K25 | M25: =J25-L25
A26: OP-101 | B26: 21 | C26: 45945 | D26: =IF('04_Condiciones_TIE'!B5="Francés",'04_Condiciones_TIE'!K5,IF('04_Condiciones_TIE'!B5="Alemán",'04_Condiciones_TIE'!C5/'04_Condiciones_TIE'!H5+F26,IF(B26<'04_Condiciones_TIE'!H5,F26,F26+E26))) | E26: =H25 | F26: =E26*'04_Condiciones_TIE'!J5 | G26: =D26-F26 | H26: =E26-G26 | I26: =D26 | J26: =M25 | K26: =J26*'04_Condiciones_TIE'!L5 | L26: =D26-K26 | M26: =J26-L26
A27: OP-101 | B27: 22 | C27: 45976 | D27: =IF('04_Condiciones_TIE'!B5="Francés",'04_Condiciones_TIE'!K5,IF('04_Condiciones_TIE'!B5="Alemán",'04_Condiciones_TIE'!C5/'04_Condiciones_TIE'!H5+F27,IF(B27<'04_Condiciones_TIE'!H5,F27,F27+E27))) | E27: =H26 | F27: =E27*'04_Condiciones_TIE'!J5 | G27: =D27-F27 | H27: =E27-G27 | I27: =D27 | J27: =M26 | K27: =J27*'04_Condiciones_TIE'!L5 | L27: =D27-K27 | M27: =J27-L27
A28: OP-101 | B28: 23 | C28: 46006 | D28: =IF('04_Condiciones_TIE'!B5="Francés",'04_Condiciones_TIE'!K5,IF('04_Condiciones_TIE'!B5="Alemán",'04_Condiciones_TIE'!C5/'04_Condiciones_TIE'!H5+F28,IF(B28<'04_Condiciones_TIE'!H5,F28,F28+E28))) | E28: =H27 | F28: =E28*'04_Condiciones_TIE'!J5 | G28: =D28-F28 | H28: =E28-G28 | I28: =D28 | J28: =M27 | K28: =J28*'04_Condiciones_TIE'!L5 | L28: =D28-K28 | M28: =J28-L28
A29: OP-101 | B29: 24 | C29: 46037 | D29: =IF('04_Condiciones_TIE'!B5="Francés",'04_Condiciones_TIE'!K5,IF('04_Condiciones_TIE'!B5="Alemán",'04_Condiciones_TIE'!C5/'04_Condiciones_TIE'!H5+F29,IF(B29<'04_Condiciones_TIE'!H5,F29,F29+E29))) | E29: =H28 | F29: =E29*'04_Condiciones_TIE'!J5 | G29: =D29-F29 | H29: =E29-G29 | I29: =D29 | J29: =M28 | K29: =J29*'04_Condiciones_TIE'!L5 | L29: =D29-K29 | M29: =J29-L29
A30: OP-101 | B30: 25 | C30: 46068 | D30: =IF('04_Condiciones_TIE'!B5="Francés",'04_Condiciones_TIE'!K5,IF('04_Condiciones_TIE'!B5="Alemán",'04_Condiciones_TIE'!C5/'04_Condiciones_TIE'!H5+F30,IF(B30<'04_Condiciones_TIE'!H5,F30,F30+E30))) | E30: =H29 | F30: =E30*'04_Condiciones_TIE'!J5 | G30: =D30-F30 | H30: =E30-G30 | I30: =D30 | J30: =M29 | K30: =J30*'04_Condiciones_TIE'!L5 | L30: =D30-K30 | M30: =J30-L30
A31: OP-101 | B31: 26 | C31: 46096 | D31: =IF('04_Condiciones_TIE'!B5="Francés",'04_Condiciones_TIE'!K5,IF('04_Condiciones_TIE'!B5="Alemán",'04_Condiciones_TIE'!C5/'04_Condiciones_TIE'!H5+F31,IF(B31<'04_Condiciones_TIE'!H5,F31,F31+E31))) | E31: =H30 | F31: =E31*'04_Condiciones_TIE'!J5 | G31: =D31-F31 | H31: =E31-G31 | I31: =D31 | J31: =M30 | K31: =J31*'04_Condiciones_TIE'!L5 | L31: =D31-K31 | M31: =J31-L31
A32: OP-101 | B32: 27 | C32: 46127 | D32: =IF('04_Condiciones_TIE'!B5="Francés",'04_Condiciones_TIE'!K5,IF('04_Condiciones_TIE'!B5="Alemán",'04_Condiciones_TIE'!C5/'04_Condiciones_TIE'!H5+F32,IF(B32<'04_Condiciones_TIE'!H5,F32,F32+E32))) | E32: =H31 | F32: =E32*'04_Condiciones_TIE'!J5 | G32: =D32-F32 | H32: =E32-G32 | I32: =D32 | J32: =M31 | K32: =J32*'04_Condiciones_TIE'!L5 | L32: =D32-K32 | M32: =J32-L32
A33: OP-101 | B33: 28 | C33: 46157 | D33: =IF('04_Condiciones_TIE'!B5="Francés",'04_Condiciones_TIE'!K5,IF('04_Condiciones_TIE'!B5="Alemán",'04_Condiciones_TIE'!C5/'04_Condiciones_TIE'!H5+F33,IF(B33<'04_Condiciones_TIE'!H5,F33,F33+E33))) | E33: =H32 | F33: =E33*'04_Condiciones_TIE'!J5 | G33: =D33-F33 | H33: =E33-G33 | I33: =D33 | J33: =M32 | K33: =J33*'04_Condiciones_TIE'!L5 | L33: =D33-K33 | M33: =J33-L33
A34: OP-101 | B34: 29 | C34: 46188 | D34: =IF('04_Condiciones_TIE'!B5="Francés",'04_Condiciones_TIE'!K5,IF('04_Condiciones_TIE'!B5="Alemán",'04_Condiciones_TIE'!C5/'04_Condiciones_TIE'!H5+F34,IF(B34<'04_Condiciones_TIE'!H5,F34,F34+E34))) | E34: =H33 | F34: =E34*'04_Condiciones_TIE'!J5 | G34: =D34-F34 | H34: =E34-G34 | I34: =D34 | J34: =M33 | K34: =J34*'04_Condiciones_TIE'!L5 | L34: =D34-K34 | M34: =J34-L34
A35: OP-101 | B35: 30 | C35: 46218 | D35: =IF('04_Condiciones_TIE'!B5="Francés",'04_Condiciones_TIE'!K5,IF('04_Condiciones_TIE'!B5="Alemán",'04_Condiciones_TIE'!C5/'04_Condiciones_TIE'!H5+F35,IF(B35<'04_Condiciones_TIE'!H5,F35,F35+E35))) | E35: =H34 | F35: =E35*'04_Condiciones_TIE'!J5 | G35: =D35-F35 | H35: =E35-G35 | I35: =D35 | J35: =M34 | K35: =J35*'04_Condiciones_TIE'!L5 | L35: =D35-K35 | M35: =J35-L35
A36: OP-101 | B36: 31 | C36: 46249 | D36: =IF('04_Condiciones_TIE'!B5="Francés",'04_Condiciones_TIE'!K5,IF('04_Condiciones_TIE'!B5="Alemán",'04_Condiciones_TIE'!C5/'04_Condiciones_TIE'!H5+F36,IF(B36<'04_Condiciones_TIE'!H5,F36,F36+E36))) | E36: =H35 | F36: =E36*'04_Condiciones_TIE'!J5 | G36: =D36-F36 | H36: =E36-G36 | I36: =D36 | J36: =M35 | K36: =J36*'04_Condiciones_TIE'!L5 | L36: =D36-K36 | M36: =J36-L36
A37: OP-101 | B37: 32 | C37: 46280 | D37: =IF('04_Condiciones_TIE'!B5="Francés",'04_Condiciones_TIE'!K5,IF('04_Condiciones_TIE'!B5="Alemán",'04_Condiciones_TIE'!C5/'04_Condiciones_TIE'!H5+F37,IF(B37<'04_Condiciones_TIE'!H5,F37,F37+E37))) | E37: =H36 | F37: =E37*'04_Condiciones_TIE'!J5 | G37: =D37-F37 | H37: =E37-G37 | I37: =D37 | J37: =M36 | K37: =J37*'04_Condiciones_TIE'!L5 | L37: =D37-K37 | M37: =J37-L37
A38: OP-101 | B38: 33 | C38: 46310 | D38: =IF('04_Condiciones_TIE'!B5="Francés",'04_Condiciones_TIE'!K5,IF('04_Condiciones_TIE'!B5="Alemán",'04_Condiciones_TIE'!C5/'04_Condiciones_TIE'!H5+F38,IF(B38<'04_Condiciones_TIE'!H5,F38,F38+E38))) | E38: =H37 | F38: =E38*'04_Condiciones_TIE'!J5 | G38: =D38-F38 | H38: =E38-G38 | I38: =D38 | J38: =M37 | K38: =J38*'04_Condiciones_TIE'!L5 | L38: =D38-K38 | M38: =J38-L38
A39: OP-101 | B39: 34 | C39: 46341 | D39: =IF('04_Condiciones_TIE'!B5="Francés",'04_Condiciones_TIE'!K5,IF('04_Condiciones_TIE'!B5="Alemán",'04_Condiciones_TIE'!C5/'04_Condiciones_TIE'!H5+F39,IF(B39<'04_Condiciones_TIE'!H5,F39,F39+E39))) | E39: =H38 | F39: =E39*'04_Condiciones_TIE'!J5 | G39: =D39-F39 | H39: =E39-G39 | I39: =D39 | J39: =M38 | K39: =J39*'04_Condiciones_TIE'!L5 | L39: =D39-K39 | M39: =J39-L39
A40: OP-101 | B40: 35 | C40: 46371 | D40: =IF('04_Condiciones_TIE'!B5="Francés",'04_Condiciones_TIE'!K5,IF('04_Condiciones_TIE'!B5="Alemán",'04_Condiciones_TIE'!C5/'04_Condiciones_TIE'!H5+F40,IF(B40<'04_Condiciones_TIE'!H5,F40,F40+E40))) | E40: =H39 | F40: =E40*'04_Condiciones_TIE'!J5 | G40: =D40-F40 | H40: =E40-G40 | I40: =D40 | J40: =M39 | K40: =J40*'04_Condiciones_TIE'!L5 | L40: =D40-K40 | M40: =J40-L40
A41: OP-101 | B41: 36 | C41: 46402 | D41: =IF('04_Condiciones_TIE'!B5="Francés",'04_Condiciones_TIE'!K5,IF('04_Condiciones_TIE'!B5="Alemán",'04_Condiciones_TIE'!C5/'04_Condiciones_TIE'!H5+F41,IF(B41<'04_Condiciones_TIE'!H5,F41,F41+E41))) | E41: =H40 | F41: =E41*'04_Condiciones_TIE'!J5 | G41: =D41-F41 | H41: =E41-G41 | I41: =D41 | J41: =M40 | K41: =J41*'04_Condiciones_TIE'!L5 | L41: =D41-K41 | M41: =J41-L41
A42: OP-102 | B42: 0 | C42: 45717 | H42: ='04_Condiciones_TIE'!C6 | I42: =-'04_Condiciones_TIE'!E6 | M42: ='04_Condiciones_TIE'!E6
A43: OP-102 | B43: 1 | C43: 45809 | D43: =IF('04_Condiciones_TIE'!B6="Francés",'04_Condiciones_TIE'!K6,IF('04_Condiciones_TIE'!B6="Alemán",'04_Condiciones_TIE'!C6/'04_Condiciones_TIE'!H6+F43,IF(B43<'04_Condiciones_TIE'!H6,F43,F43+E43))) | E43: =H42 | F43: =E43*'04_Condiciones_TIE'!J6 | G43: =D43-F43 | H43: =E43-G43 | I43: =D43 | J43: =M42 | K43: =J43*'04_Condiciones_TIE'!L6 | L43: =D43-K43 | M43: =J43-L43
A44: OP-102 | B44: 2 | C44: 45901 | D44: =IF('04_Condiciones_TIE'!B6="Francés",'04_Condiciones_TIE'!K6,IF('04_Condiciones_TIE'!B6="Alemán",'04_Condiciones_TIE'!C6/'04_Condiciones_TIE'!H6+F44,IF(B44<'04_Condiciones_TIE'!H6,F44,F44+E44))) | E44: =H43 | F44: =E44*'04_Condiciones_TIE'!J6 | G44: =D44-F44 | H44: =E44-G44 | I44: =D44 | J44: =M43 | K44: =J44*'04_Condiciones_TIE'!L6 | L44: =D44-K44 | M44: =J44-L44
A45: OP-102 | B45: 3 | C45: 45992 | D45: =IF('04_Condiciones_TIE'!B6="Francés",'04_Condiciones_TIE'!K6,IF('04_Condiciones_TIE'!B6="Alemán",'04_Condiciones_TIE'!C6/'04_Condiciones_TIE'!H6+F45,IF(B45<'04_Condiciones_TIE'!H6,F45,F45+E45))) | E45: =H44 | F45: =E45*'04_Condiciones_TIE'!J6 | G45: =D45-F45 | H45: =E45-G45 | I45: =D45 | J45: =M44 | K45: =J45*'04_Condiciones_TIE'!L6 | L45: =D45-K45 | M45: =J45-L45
A46: OP-102 | B46: 4 | C46: 46082 | D46: =IF('04_Condiciones_TIE'!B6="Francés",'04_Condiciones_TIE'!K6,IF('04_Condiciones_TIE'!B6="Alemán",'04_Condiciones_TIE'!C6/'04_Condiciones_TIE'!H6+F46,IF(B46<'04_Condiciones_TIE'!H6,F46,F46+E46))) | E46: =H45 | F46: =E46*'04_Condiciones_TIE'!J6 | G46: =D46-F46 | H46: =E46-G46 | I46: =D46 | J46: =M45 | K46: =J46*'04_Condiciones_TIE'!L6 | L46: =D46-K46 | M46: =J46-L46
A47: OP-102 | B47: 5 | C47: 46174 | D47: =IF('04_Condiciones_TIE'!B6="Francés",'04_Condiciones_TIE'!K6,IF('04_Condiciones_TIE'!B6="Alemán",'04_Condiciones_TIE'!C6/'04_Condiciones_TIE'!H6+F47,IF(B47<'04_Condiciones_TIE'!H6,F47,F47+E47))) | E47: =H46 | F47: =E47*'04_Condiciones_TIE'!J6 | G47: =D47-F47 | H47: =E47-G47 | I47: =D47 | J47: =M46 | K47: =J47*'04_Condiciones_TIE'!L6 | L47: =D47-K47 | M47: =J47-L47
A48: OP-102 | B48: 6 | C48: 46266 | D48: =IF('04_Condiciones_TIE'!B6="Francés",'04_Condiciones_TIE'!K6,IF('04_Condiciones_TIE'!B6="Alemán",'04_Condiciones_TIE'!C6/'04_Condiciones_TIE'!H6+F48,IF(B48<'04_Condiciones_TIE'!H6,F48,F48+E48))) | E48: =H47 | F48: =E48*'04_Condiciones_TIE'!J6 | G48: =D48-F48 | H48: =E48-G48 | I48: =D48 | J48: =M47 | K48: =J48*'04_Condiciones_TIE'!L6 | L48: =D48-K48 | M48: =J48-L48
A49: OP-102 | B49: 7 | C49: 46357 | D49: =IF('04_Condiciones_TIE'!B6="Francés",'04_Condiciones_TIE'!K6,IF('04_Condiciones_TIE'!B6="Alemán",'04_Condiciones_TIE'!C6/'04_Condiciones_TIE'!H6+F49,IF(B49<'04_Condiciones_TIE'!H6,F49,F49+E49))) | E49: =H48 | F49: =E49*'04_Condiciones_TIE'!J6 | G49: =D49-F49 | H49: =E49-G49 | I49: =D49 | J49: =M48 | K49: =J49*'04_Condiciones_TIE'!L6 | L49: =D49-K49 | M49: =J49-L49
A50: OP-102 | B50: 8 | C50: 46447 | D50: =IF('04_Condiciones_TIE'!B6="Francés",'04_Condiciones_TIE'!K6,IF('04_Condiciones_TIE'!B6="Alemán",'04_Condiciones_TIE'!C6/'04_Condiciones_TIE'!H6+F50,IF(B50<'04_Condiciones_TIE'!H6,F50,F50+E50))) | E50: =H49 | F50: =E50*'04_Condiciones_TIE'!J6 | G50: =D50-F50 | H50: =E50-G50 | I50: =D50 | J50: =M49 | K50: =J50*'04_Condiciones_TIE'!L6 | L50: =D50-K50 | M50: =J50-L50
A51: OP-102 | B51: 9 | C51: 46539 | D51: =IF('04_Condiciones_TIE'!B6="Francés",'04_Condiciones_TIE'!K6,IF('04_Condiciones_TIE'!B6="Alemán",'04_Condiciones_TIE'!C6/'04_Condiciones_TIE'!H6+F51,IF(B51<'04_Condiciones_TIE'!H6,F51,F51+E51))) | E51: =H50 | F51: =E51*'04_Condiciones_TIE'!J6 | G51: =D51-F51 | H51: =E51-G51 | I51: =D51 | J51: =M50 | K51: =J51*'04_Condiciones_TIE'!L6 | L51: =D51-K51 | M51: =J51-L51
A52: OP-102 | B52: 10 | C52: 46631 | D52: =IF('04_Condiciones_TIE'!B6="Francés",'04_Condiciones_TIE'!K6,IF('04_Condiciones_TIE'!B6="Alemán",'04_Condiciones_TIE'!C6/'04_Condiciones_TIE'!H6+F52,IF(B52<'04_Condiciones_TIE'!H6,F52,F52+E52))) | E52: =H51 | F52: =E52*'04_Condiciones_TIE'!J6 | G52: =D52-F52 | H52: =E52-G52 | I52: =D52 | J52: =M51 | K52: =J52*'04_Condiciones_TIE'!L6 | L52: =D52-K52 | M52: =J52-L52
A53: OP-102 | B53: 11 | C53: 46722 | D53: =IF('04_Condiciones_TIE'!B6="Francés",'04_Condiciones_TIE'!K6,IF('04_Condiciones_TIE'!B6="Alemán",'04_Condiciones_TIE'!C6/'04_Condiciones_TIE'!H6+F53,IF(B53<'04_Condiciones_TIE'!H6,F53,F53+E53))) | E53: =H52 | F53: =E53*'04_Condiciones_TIE'!J6 | G53: =D53-F53 | H53: =E53-G53 | I53: =D53 | J53: =M52 | K53: =J53*'04_Condiciones_TIE'!L6 | L53: =D53-K53 | M53: =J53-L53
A54: OP-102 | B54: 12 | C54: 46813 | D54: =IF('04_Condiciones_TIE'!B6="Francés",'04_Condiciones_TIE'!K6,IF('04_Condiciones_TIE'!B6="Alemán",'04_Condiciones_TIE'!C6/'04_Condiciones_TIE'!H6+F54,IF(B54<'04_Condiciones_TIE'!H6,F54,F54+E54))) | E54: =H53 | F54: =E54*'04_Condiciones_TIE'!J6 | G54: =D54-F54 | H54: =E54-G54 | I54: =D54 | J54: =M53 | K54: =J54*'04_Condiciones_TIE'!L6 | L54: =D54-K54 | M54: =J54-L54
A55: OP-102 | B55: 13 | C55: 46905 | D55: =IF('04_Condiciones_TIE'!B6="Francés",'04_Condiciones_TIE'!K6,IF('04_Condiciones_TIE'!B6="Alemán",'04_Condiciones_TIE'!C6/'04_Condiciones_TIE'!H6+F55,IF(B55<'04_Condiciones_TIE'!H6,F55,F55+E55))) | E55: =H54 | F55: =E55*'04_Condiciones_TIE'!J6 | G55: =D55-F55 | H55: =E55-G55 | I55: =D55 | J55: =M54 | K55: =J55*'04_Condiciones_TIE'!L6 | L55: =D55-K55 | M55: =J55-L55
A56: OP-102 | B56: 14 | C56: 46997 | D56: =IF('04_Condiciones_TIE'!B6="Francés",'04_Condiciones_TIE'!K6,IF('04_Condiciones_TIE'!B6="Alemán",'04_Condiciones_TIE'!C6/'04_Condiciones_TIE'!H6+F56,IF(B56<'04_Condiciones_TIE'!H6,F56,F56+E56))) | E56: =H55 | F56: =E56*'04_Condiciones_TIE'!J6 | G56: =D56-F56 | H56: =E56-G56 | I56: =D56 | J56: =M55 | K56: =J56*'04_Condiciones_TIE'!L6 | L56: =D56-K56 | M56: =J56-L56
A57: OP-102 | B57: 15 | C57: 47088 | D57: =IF('04_Condiciones_TIE'!B6="Francés",'04_Condiciones_TIE'!K6,IF('04_Condiciones_TIE'!B6="Alemán",'04_Condiciones_TIE'!C6/'04_Condiciones_TIE'!H6+F57,IF(B57<'04_Condiciones_TIE'!H6,F57,F57+E57))) | E57: =H56 | F57: =E57*'04_Condiciones_TIE'!J6 | G57: =D57-F57 | H57: =E57-G57 | I57: =D57 | J57: =M56 | K57: =J57*'04_Condiciones_TIE'!L6 | L57: =D57-K57 | M57: =J57-L57
A58: OP-102 | B58: 16 | C58: 47178 | D58: =IF('04_Condiciones_TIE'!B6="Francés",'04_Condiciones_TIE'!K6,IF('04_Condiciones_TIE'!B6="Alemán",'04_Condiciones_TIE'!C6/'04_Condiciones_TIE'!H6+F58,IF(B58<'04_Condiciones_TIE'!H6,F58,F58+E58))) | E58: =H57 | F58: =E58*'04_Condiciones_TIE'!J6 | G58: =D58-F58 | H58: =E58-G58 | I58: =D58 | J58: =M57 | K58: =J58*'04_Condiciones_TIE'!L6 | L58: =D58-K58 | M58: =J58-L58
A59: OP-102 | B59: 17 | C59: 47270 | D59: =IF('04_Condiciones_TIE'!B6="Francés",'04_Condiciones_TIE'!K6,IF('04_Condiciones_TIE'!B6="Alemán",'04_Condiciones_TIE'!C6/'04_Condiciones_TIE'!H6+F59,IF(B59<'04_Condiciones_TIE'!H6,F59,F59+E59))) | E59: =H58 | F59: =E59*'04_Condiciones_TIE'!J6 | G59: =D59-F59 | H59: =E59-G59 | I59: =D59 | J59: =M58 | K59: =J59*'04_Condiciones_TIE'!L6 | L59: =D59-K59 | M59: =J59-L59
A60: OP-102 | B60: 18 | C60: 47362 | D60: =IF('04_Condiciones_TIE'!B6="Francés",'04_Condiciones_TIE'!K6,IF('04_Condiciones_TIE'!B6="Alemán",'04_Condiciones_TIE'!C6/'04_Condiciones_TIE'!H6+F60,IF(B60<'04_Condiciones_TIE'!H6,F60,F60+E60))) | E60: =H59 | F60: =E60*'04_Condiciones_TIE'!J6 | G60: =D60-F60 | H60: =E60-G60 | I60: =D60 | J60: =M59 | K60: =J60*'04_Condiciones_TIE'!L6 | L60: =D60-K60 | M60: =J60-L60
A61: OP-102 | B61: 19 | C61: 47453 | D61: =IF('04_Condiciones_TIE'!B6="Francés",'04_Condiciones_TIE'!K6,IF('04_Condiciones_TIE'!B6="Alemán",'04_Condiciones_TIE'!C6/'04_Condiciones_TIE'!H6+F61,IF(B61<'04_Condiciones_TIE'!H6,F61,F61+E61))) | E61: =H60 | F61: =E61*'04_Condiciones_TIE'!J6 | G61: =D61-F61 | H61: =E61-G61 | I61: =D61 | J61: =M60 | K61: =J61*'04_Condiciones_TIE'!L6 | L61: =D61-K61 | M61: =J61-L61
A62: OP-102 | B62: 20 | C62: 47543 | D62: =IF('04_Condiciones_TIE'!B6="Francés",'04_Condiciones_TIE'!K6,IF('04_Condiciones_TIE'!B6="Alemán",'04_Condiciones_TIE'!C6/'04_Condiciones_TIE'!H6+F62,IF(B62<'04_Condiciones_TIE'!H6,F62,F62+E62))) | E62: =H61 | F62: =E62*'04_Condiciones_TIE'!J6 | G62: =D62-F62 | H62: =E62-G62 | I62: =D62 | J62: =M61 | K62: =J62*'04_Condiciones_TIE'!L6 | L62: =D62-K62 | M62: =J62-L62
A63: OP-103 | B63: 0 | C63: 45108 | H63: ='04_Condiciones_TIE'!C7 | I63: =-'04_Condiciones_TIE'!E7 | M63: ='04_Condiciones_TIE'!E7
A64: OP-103 | B64: 1 | C64: 45292 | D64: =IF('04_Condiciones_TIE'!B7="Francés",'04_Condiciones_TIE'!K7,IF('04_Condiciones_TIE'!B7="Alemán",'04_Condiciones_TIE'!C7/'04_Condiciones_TIE'!H7+F64,IF(B64<'04_Condiciones_TIE'!H7,F64,F64+E64))) | E64: =H63 | F64: =E64*'04_Condiciones_TIE'!J7 | G64: =D64-F64 | H64: =E64-G64 | I64: =D64 | J64: =M63 | K64: =J64*'04_Condiciones_TIE'!L7 | L64: =D64-K64 | M64: =J64-L64
A65: OP-103 | B65: 2 | C65: 45474 | D65: =IF('04_Condiciones_TIE'!B7="Francés",'04_Condiciones_TIE'!K7,IF('04_Condiciones_TIE'!B7="Alemán",'04_Condiciones_TIE'!C7/'04_Condiciones_TIE'!H7+F65,IF(B65<'04_Condiciones_TIE'!H7,F65,F65+E65))) | E65: =H64 | F65: =E65*'04_Condiciones_TIE'!J7 | G65: =D65-F65 | H65: =E65-G65 | I65: =D65 | J65: =M64 | K65: =J65*'04_Condiciones_TIE'!L7 | L65: =D65-K65 | M65: =J65-L65
A66: OP-103 | B66: 3 | C66: 45658 | D66: =IF('04_Condiciones_TIE'!B7="Francés",'04_Condiciones_TIE'!K7,IF('04_Condiciones_TIE'!B7="Alemán",'04_Condiciones_TIE'!C7/'04_Condiciones_TIE'!H7+F66,IF(B66<'04_Condiciones_TIE'!H7,F66,F66+E66))) | E66: =H65 | F66: =E66*'04_Condiciones_TIE'!J7 | G66: =D66-F66 | H66: =E66-G66 | I66: =D66 | J66: =M65 | K66: =J66*'04_Condiciones_TIE'!L7 | L66: =D66-K66 | M66: =J66-L66
A67: OP-103 | B67: 4 | C67: 45839 | D67: =IF('04_Condiciones_TIE'!B7="Francés",'04_Condiciones_TIE'!K7,IF('04_Condiciones_TIE'!B7="Alemán",'04_Condiciones_TIE'!C7/'04_Condiciones_TIE'!H7+F67,IF(B67<'04_Condiciones_TIE'!H7,F67,F67+E67))) | E67: =H66 | F67: =E67*'04_Condiciones_TIE'!J7 | G67: =D67-F67 | H67: =E67-G67 | I67: =D67 | J67: =M66 | K67: =J67*'04_Condiciones_TIE'!L7 | L67: =D67-K67 | M67: =J67-L67
A68: OP-103 | B68: 5 | C68: 46023 | D68: =IF('04_Condiciones_TIE'!B7="Francés",'04_Condiciones_TIE'!K7,IF('04_Condiciones_TIE'!B7="Alemán",'04_Condiciones_TIE'!C7/'04_Condiciones_TIE'!H7+F68,IF(B68<'04_Condiciones_TIE'!H7,F68,F68+E68))) | E68: =H67 | F68: =E68*'04_Condiciones_TIE'!J7 | G68: =D68-F68 | H68: =E68-G68 | I68: =D68 | J68: =M67 | K68: =J68*'04_Condiciones_TIE'!L7 | L68: =D68-K68 | M68: =J68-L68
A69: OP-103 | B69: 6 | C69: 46204 | D69: =IF('04_Condiciones_TIE'!B7="Francés",'04_Condiciones_TIE'!K7,IF('04_Condiciones_TIE'!B7="Alemán",'04_Condiciones_TIE'!C7/'04_Condiciones_TIE'!H7+F69,IF(B69<'04_Condiciones_TIE'!H7,F69,F69+E69))) | E69: =H68 | F69: =E69*'04_Condiciones_TIE'!J7 | G69: =D69-F69 | H69: =E69-G69 | I69: =D69 | J69: =M68 | K69: =J69*'04_Condiciones_TIE'!L7 | L69: =D69-K69 | M69: =J69-L69
A70: OP-103 | B70: 7 | C70: 46388 | D70: =IF('04_Condiciones_TIE'!B7="Francés",'04_Condiciones_TIE'!K7,IF('04_Condiciones_TIE'!B7="Alemán",'04_Condiciones_TIE'!C7/'04_Condiciones_TIE'!H7+F70,IF(B70<'04_Condiciones_TIE'!H7,F70,F70+E70))) | E70: =H69 | F70: =E70*'04_Condiciones_TIE'!J7 | G70: =D70-F70 | H70: =E70-G70 | I70: =D70 | J70: =M69 | K70: =J70*'04_Condiciones_TIE'!L7 | L70: =D70-K70 | M70: =J70-L70
A71: OP-103 | B71: 8 | C71: 46569 | D71: =IF('04_Condiciones_TIE'!B7="Francés",'04_Condiciones_TIE'!K7,IF('04_Condiciones_TIE'!B7="Alemán",'04_Condiciones_TIE'!C7/'04_Condiciones_TIE'!H7+F71,IF(B71<'04_Condiciones_TIE'!H7,F71,F71+E71))) | E71: =H70 | F71: =E71*'04_Condiciones_TIE'!J7 | G71: =D71-F71 | H71: =E71-G71 | I71: =D71 | J71: =M70 | K71: =J71*'04_Condiciones_TIE'!L7 | L71: =D71-K71 | M71: =J71-L71
A72: OP-104 | B72: 0 | C72: 45838 | H72: ='04_Condiciones_TIE'!C8 | I72: =-'04_Condiciones_TIE'!E8 | M72: ='04_Condiciones_TIE'!E8
A73: OP-104 | B73: 1 | C73: 46021 | D73: =IF('04_Condiciones_TIE'!B8="Francés",'04_Condiciones_TIE'!K8,IF('04_Condiciones_TIE'!B8="Alemán",'04_Condiciones_TIE'!C8/'04_Condiciones_TIE'!H8+F73,IF(B73<'04_Condiciones_TIE'!H8,F73,F73+E73))) | E73: =H72 | F73: =E73*'04_Condiciones_TIE'!J8 | G73: =D73-F73 | H73: =E73-G73 | I73: =D73 | J73: =M72 | K73: =J73*'04_Condiciones_TIE'!L8 | L73: =D73-K73 | M73: =J73-L73
A74: OP-104 | B74: 2 | C74: 46203 | D74: =IF('04_Condiciones_TIE'!B8="Francés",'04_Condiciones_TIE'!K8,IF('04_Condiciones_TIE'!B8="Alemán",'04_Condiciones_TIE'!C8/'04_Condiciones_TIE'!H8+F74,IF(B74<'04_Condiciones_TIE'!H8,F74,F74+E74))) | E74: =H73 | F74: =E74*'04_Condiciones_TIE'!J8 | G74: =D74-F74 | H74: =E74-G74 | I74: =D74 | J74: =M73 | K74: =J74*'04_Condiciones_TIE'!L8 | L74: =D74-K74 | M74: =J74-L74
A75: OP-104 | B75: 3 | C75: 46386 | D75: =IF('04_Condiciones_TIE'!B8="Francés",'04_Condiciones_TIE'!K8,IF('04_Condiciones_TIE'!B8="Alemán",'04_Condiciones_TIE'!C8/'04_Condiciones_TIE'!H8+F75,IF(B75<'04_Condiciones_TIE'!H8,F75,F75+E75))) | E75: =H74 | F75: =E75*'04_Condiciones_TIE'!J8 | G75: =D75-F75 | H75: =E75-G75 | I75: =D75 | J75: =M74 | K75: =J75*'04_Condiciones_TIE'!L8 | L75: =D75-K75 | M75: =J75-L75
A76: OP-104 | B76: 4 | C76: 46568 | D76: =IF('04_Condiciones_TIE'!B8="Francés",'04_Condiciones_TIE'!K8,IF('04_Condiciones_TIE'!B8="Alemán",'04_Condiciones_TIE'!C8/'04_Condiciones_TIE'!H8+F76,IF(B76<'04_Condiciones_TIE'!H8,F76,F76+E76))) | E76: =H75 | F76: =E76*'04_Condiciones_TIE'!J8 | G76: =D76-F76 | H76: =E76-G76 | I76: =D76 | J76: =M75 | K76: =J76*'04_Condiciones_TIE'!L8 | L76: =D76-K76 | M76: =J76-L76
A77: OP-105 | B77: 0 | C77: 44562 | H77: ='04_Condiciones_TIE'!C9 | I77: =-'04_Condiciones_TIE'!E9 | M77: ='04_Condiciones_TIE'!E9
A78: OP-105 | B78: 1 | C78: 44593 | D78: =IF('04_Condiciones_TIE'!B9="Francés",'04_Condiciones_TIE'!K9,IF('04_Condiciones_TIE'!B9="Alemán",'04_Condiciones_TIE'!C9/'04_Condiciones_TIE'!H9+F78,IF(B78<'04_Condiciones_TIE'!H9,F78,F78+E78))) | E78: =H77 | F78: =E78*'04_Condiciones_TIE'!J9 | G78: =D78-F78 | H78: =E78-G78 | I78: =D78 | J78: =M77 | K78: =J78*'04_Condiciones_TIE'!L9 | L78: =D78-K78 | M78: =J78-L78
A79: OP-105 | B79: 2 | C79: 44621 | D79: =IF('04_Condiciones_TIE'!B9="Francés",'04_Condiciones_TIE'!K9,IF('04_Condiciones_TIE'!B9="Alemán",'04_Condiciones_TIE'!C9/'04_Condiciones_TIE'!H9+F79,IF(B79<'04_Condiciones_TIE'!H9,F79,F79+E79))) | E79: =H78 | F79: =E79*'04_Condiciones_TIE'!J9 | G79: =D79-F79 | H79: =E79-G79 | I79: =D79 | J79: =M78 | K79: =J79*'04_Condiciones_TIE'!L9 | L79: =D79-K79 | M79: =J79-L79
A80: OP-105 | B80: 3 | C80: 44652 | D80: =IF('04_Condiciones_TIE'!B9="Francés",'04_Condiciones_TIE'!K9,IF('04_Condiciones_TIE'!B9="Alemán",'04_Condiciones_TIE'!C9/'04_Condiciones_TIE'!H9+F80,IF(B80<'04_Condiciones_TIE'!H9,F80,F80+E80))) | E80: =H79 | F80: =E80*'04_Condiciones_TIE'!J9 | G80: =D80-F80 | H80: =E80-G80 | I80: =D80 | J80: =M79 | K80: =J80*'04_Condiciones_TIE'!L9 | L80: =D80-K80 | M80: =J80-L80
A81: OP-105 | B81: 4 | C81: 44682 | D81: =IF('04_Condiciones_TIE'!B9="Francés",'04_Condiciones_TIE'!K9,IF('04_Condiciones_TIE'!B9="Alemán",'04_Condiciones_TIE'!C9/'04_Condiciones_TIE'!H9+F81,IF(B81<'04_Condiciones_TIE'!H9,F81,F81+E81))) | E81: =H80 | F81: =E81*'04_Condiciones_TIE'!J9 | G81: =D81-F81 | H81: =E81-G81 | I81: =D81 | J81: =M80 | K81: =J81*'04_Condiciones_TIE'!L9 | L81: =D81-K81 | M81: =J81-L81
A82: OP-105 | B82: 5 | C82: 44713 | D82: =IF('04_Condiciones_TIE'!B9="Francés",'04_Condiciones_TIE'!K9,IF('04_Condiciones_TIE'!B9="Alemán",'04_Condiciones_TIE'!C9/'04_Condiciones_TIE'!H9+F82,IF(B82<'04_Condiciones_TIE'!H9,F82,F82+E82))) | E82: =H81 | F82: =E82*'04_Condiciones_TIE'!J9 | G82: =D82-F82 | H82: =E82-G82 | I82: =D82 | J82: =M81 | K82: =J82*'04_Condiciones_TIE'!L9 | L82: =D82-K82 | M82: =J82-L82
A83: OP-105 | B83: 6 | C83: 44743 | D83: =IF('04_Condiciones_TIE'!B9="Francés",'04_Condiciones_TIE'!K9,IF('04_Condiciones_TIE'!B9="Alemán",'04_Condiciones_TIE'!C9/'04_Condiciones_TIE'!H9+F83,IF(B83<'04_Condiciones_TIE'!H9,F83,F83+E83))) | E83: =H82 | F83: =E83*'04_Condiciones_TIE'!J9 | G83: =D83-F83 | H83: =E83-G83 | I83: =D83 | J83: =M82 | K83: =J83*'04_Condiciones_TIE'!L9 | L83: =D83-K83 | M83: =J83-L83
A84: OP-105 | B84: 7 | C84: 44774 | D84: =IF('04_Condiciones_TIE'!B9="Francés",'04_Condiciones_TIE'!K9,IF('04_Condiciones_TIE'!B9="Alemán",'04_Condiciones_TIE'!C9/'04_Condiciones_TIE'!H9+F84,IF(B84<'04_Condiciones_TIE'!H9,F84,F84+E84))) | E84: =H83 | F84: =E84*'04_Condiciones_TIE'!J9 | G84: =D84-F84 | H84: =E84-G84 | I84: =D84 | J84: =M83 | K84: =J84*'04_Condiciones_TIE'!L9 | L84: =D84-K84 | M84: =J84-L84
A85: OP-105 | B85: 8 | C85: 44805 | D85: =IF('04_Condiciones_TIE'!B9="Francés",'04_Condiciones_TIE'!K9,IF('04_Condiciones_TIE'!B9="Alemán",'04_Condiciones_TIE'!C9/'04_Condiciones_TIE'!H9+F85,IF(B85<'04_Condiciones_TIE'!H9,F85,F85+E85))) | E85: =H84 | F85: =E85*'04_Condiciones_TIE'!J9 | G85: =D85-F85 | H85: =E85-G85 | I85: =D85 | J85: =M84 | K85: =J85*'04_Condiciones_TIE'!L9 | L85: =D85-K85 | M85: =J85-L85
A86: OP-105 | B86: 9 | C86: 44835 | D86: =IF('04_Condiciones_TIE'!B9="Francés",'04_Condiciones_TIE'!K9,IF('04_Condiciones_TIE'!B9="Alemán",'04_Condiciones_TIE'!C9/'04_Condiciones_TIE'!H9+F86,IF(B86<'04_Condiciones_TIE'!H9,F86,F86+E86))) | E86: =H85 | F86: =E86*'04_Condiciones_TIE'!J9 | G86: =D86-F86 | H86: =E86-G86 | I86: =D86 | J86: =M85 | K86: =J86*'04_Condiciones_TIE'!L9 | L86: =D86-K86 | M86: =J86-L86
A87: OP-105 | B87: 10 | C87: 44866 | D87: =IF('04_Condiciones_TIE'!B9="Francés",'04_Condiciones_TIE'!K9,IF('04_Condiciones_TIE'!B9="Alemán",'04_Condiciones_TIE'!C9/'04_Condiciones_TIE'!H9+F87,IF(B87<'04_Condiciones_TIE'!H9,F87,F87+E87))) | E87: =H86 | F87: =E87*'04_Condiciones_TIE'!J9 | G87: =D87-F87 | H87: =E87-G87 | I87: =D87 | J87: =M86 | K87: =J87*'04_Condiciones_TIE'!L9 | L87: =D87-K87 | M87: =J87-L87
A88: OP-105 | B88: 11 | C88: 44896 | D88: =IF('04_Condiciones_TIE'!B9="Francés",'04_Condiciones_TIE'!K9,IF('04_Condiciones_TIE'!B9="Alemán",'04_Condiciones_TIE'!C9/'04_Condiciones_TIE'!H9+F88,IF(B88<'04_Condiciones_TIE'!H9,F88,F88+E88))) | E88: =H87 | F88: =E88*'04_Condiciones_TIE'!J9 | G88: =D88-F88 | H88: =E88-G88 | I88: =D88 | J88: =M87 | K88: =J88*'04_Condiciones_TIE'!L9 | L88: =D88-K88 | M88: =J88-L88
A89: OP-105 | B89: 12 | C89: 44927 | D89: =IF('04_Condiciones_TIE'!B9="Francés",'04_Condiciones_TIE'!K9,IF('04_Condiciones_TIE'!B9="Alemán",'04_Condiciones_TIE'!C9/'04_Condiciones_TIE'!H9+F89,IF(B89<'04_Condiciones_TIE'!H9,F89,F89+E89))) | E89: =H88 | F89: =E89*'04_Condiciones_TIE'!J9 | G89: =D89-F89 | H89: =E89-G89 | I89: =D89 | J89: =M88 | K89: =J89*'04_Condiciones_TIE'!L9 | L89: =D89-K89 | M89: =J89-L89
A90: OP-105 | B90: 13 | C90: 44958 | D90: =IF('04_Condiciones_TIE'!B9="Francés",'04_Condiciones_TIE'!K9,IF('04_Condiciones_TIE'!B9="Alemán",'04_Condiciones_TIE'!C9/'04_Condiciones_TIE'!H9+F90,IF(B90<'04_Condiciones_TIE'!H9,F90,F90+E90))) | E90: =H89 | F90: =E90*'04_Condiciones_TIE'!J9 | G90: =D90-F90 | H90: =E90-G90 | I90: =D90 | J90: =M89 | K90: =J90*'04_Condiciones_TIE'!L9 | L90: =D90-K90 | M90: =J90-L90
A91: OP-105 | B91: 14 | C91: 44986 | D91: =IF('04_Condiciones_TIE'!B9="Francés",'04_Condiciones_TIE'!K9,IF('04_Condiciones_TIE'!B9="Alemán",'04_Condiciones_TIE'!C9/'04_Condiciones_TIE'!H9+F91,IF(B91<'04_Condiciones_TIE'!H9,F91,F91+E91))) | E91: =H90 | F91: =E91*'04_Condiciones_TIE'!J9 | G91: =D91-F91 | H91: =E91-G91 | I91: =D91 | J91: =M90 | K91: =J91*'04_Condiciones_TIE'!L9 | L91: =D91-K91 | M91: =J91-L91
A92: OP-105 | B92: 15 | C92: 45017 | D92: =IF('04_Condiciones_TIE'!B9="Francés",'04_Condiciones_TIE'!K9,IF('04_Condiciones_TIE'!B9="Alemán",'04_Condiciones_TIE'!C9/'04_Condiciones_TIE'!H9+F92,IF(B92<'04_Condiciones_TIE'!H9,F92,F92+E92))) | E92: =H91 | F92: =E92*'04_Condiciones_TIE'!J9 | G92: =D92-F92 | H92: =E92-G92 | I92: =D92 | J92: =M91 | K92: =J92*'04_Condiciones_TIE'!L9 | L92: =D92-K92 | M92: =J92-L92
A93: OP-105 | B93: 16 | C93: 45047 | D93: =IF('04_Condiciones_TIE'!B9="Francés",'04_Condiciones_TIE'!K9,IF('04_Condiciones_TIE'!B9="Alemán",'04_Condiciones_TIE'!C9/'04_Condiciones_TIE'!H9+F93,IF(B93<'04_Condiciones_TIE'!H9,F93,F93+E93))) | E93: =H92 | F93: =E93*'04_Condiciones_TIE'!J9 | G93: =D93-F93 | H93: =E93-G93 | I93: =D93 | J93: =M92 | K93: =J93*'04_Condiciones_TIE'!L9 | L93: =D93-K93 | M93: =J93-L93
A94: OP-105 | B94: 17 | C94: 45078 | D94: =IF('04_Condiciones_TIE'!B9="Francés",'04_Condiciones_TIE'!K9,IF('04_Condiciones_TIE'!B9="Alemán",'04_Condiciones_TIE'!C9/'04_Condiciones_TIE'!H9+F94,IF(B94<'04_Condiciones_TIE'!H9,F94,F94+E94))) | E94: =H93 | F94: =E94*'04_Condiciones_TIE'!J9 | G94: =D94-F94 | H94: =E94-G94 | I94: =D94 | J94: =M93 | K94: =J94*'04_Condiciones_TIE'!L9 | L94: =D94-K94 | M94: =J94-L94
A95: OP-105 | B95: 18 | C95: 45108 | D95: =IF('04_Condiciones_TIE'!B9="Francés",'04_Condiciones_TIE'!K9,IF('04_Condiciones_TIE'!B9="Alemán",'04_Condiciones_TIE'!C9/'04_Condiciones_TIE'!H9+F95,IF(B95<'04_Condiciones_TIE'!H9,F95,F95+E95))) | E95: =H94 | F95: =E95*'04_Condiciones_TIE'!J9 | G95: =D95-F95 | H95: =E95-G95 | I95: =D95 | J95: =M94 | K95: =J95*'04_Condiciones_TIE'!L9 | L95: =D95-K95 | M95: =J95-L95
A96: OP-105 | B96: 19 | C96: 45139 | D96: =IF('04_Condiciones_TIE'!B9="Francés",'04_Condiciones_TIE'!K9,IF('04_Condiciones_TIE'!B9="Alemán",'04_Condiciones_TIE'!C9/'04_Condiciones_TIE'!H9+F96,IF(B96<'04_Condiciones_TIE'!H9,F96,F96+E96))) | E96: =H95 | F96: =E96*'04_Condiciones_TIE'!J9 | G96: =D96-F96 | H96: =E96-G96 | I96: =D96 | J96: =M95 | K96: =J96*'04_Condiciones_TIE'!L9 | L96: =D96-K96 | M96: =J96-L96
A97: OP-105 | B97: 20 | C97: 45170 | D97: =IF('04_Condiciones_TIE'!B9="Francés",'04_Condiciones_TIE'!K9,IF('04_Condiciones_TIE'!B9="Alemán",'04_Condiciones_TIE'!C9/'04_Condiciones_TIE'!H9+F97,IF(B97<'04_Condiciones_TIE'!H9,F97,F97+E97))) | E97: =H96 | F97: =E97*'04_Condiciones_TIE'!J9 | G97: =D97-F97 | H97: =E97-G97 | I97: =D97 | J97: =M96 | K97: =J97*'04_Condiciones_TIE'!L9 | L97: =D97-K97 | M97: =J97-L97
A98: OP-105 | B98: 21 | C98: 45200 | D98: =IF('04_Condiciones_TIE'!B9="Francés",'04_Condiciones_TIE'!K9,IF('04_Condiciones_TIE'!B9="Alemán",'04_Condiciones_TIE'!C9/'04_Condiciones_TIE'!H9+F98,IF(B98<'04_Condiciones_TIE'!H9,F98,F98+E98))) | E98: =H97 | F98: =E98*'04_Condiciones_TIE'!J9 | G98: =D98-F98 | H98: =E98-G98 | I98: =D98 | J98: =M97 | K98: =J98*'04_Condiciones_TIE'!L9 | L98: =D98-K98 | M98: =J98-L98
A99: OP-105 | B99: 22 | C99: 45231 | D99: =IF('04_Condiciones_TIE'!B9="Francés",'04_Condiciones_TIE'!K9,IF('04_Condiciones_TIE'!B9="Alemán",'04_Condiciones_TIE'!C9/'04_Condiciones_TIE'!H9+F99,IF(B99<'04_Condiciones_TIE'!H9,F99,F99+E99))) | E99: =H98 | F99: =E99*'04_Condiciones_TIE'!J9 | G99: =D99-F99 | H99: =E99-G99 | I99: =D99 | J99: =M98 | K99: =J99*'04_Condiciones_TIE'!L9 | L99: =D99-K99 | M99: =J99-L99
A100: OP-105 | B100: 23 | C100: 45261 | D100: =IF('04_Condiciones_TIE'!B9="Francés",'04_Condiciones_TIE'!K9,IF('04_Condiciones_TIE'!B9="Alemán",'04_Condiciones_TIE'!C9/'04_Condiciones_TIE'!H9+F100,IF(B100<'04_Condiciones_TIE'!H9,F100,F100+E100))) | E100: =H99 | F100: =E100*'04_Condiciones_TIE'!J9 | G100: =D100-F100 | H100: =E100-G100 | I100: =D100 | J100: =M99 | K100: =J100*'04_Condiciones_TIE'!L9 | L100: =D100-K100 | M100: =J100-L100
A101: OP-105 | B101: 24 | C101: 45292 | D101: =IF('04_Condiciones_TIE'!B9="Francés",'04_Condiciones_TIE'!K9,IF('04_Condiciones_TIE'!B9="Alemán",'04_Condiciones_TIE'!C9/'04_Condiciones_TIE'!H9+F101,IF(B101<'04_Condiciones_TIE'!H9,F101,F101+E101))) | E101: =H100 | F101: =E101*'04_Condiciones_TIE'!J9 | G101: =D101-F101 | H101: =E101-G101 | I101: =D101 | J101: =M100 | K101: =J101*'04_Condiciones_TIE'!L9 | L101: =D101-K101 | M101: =J101-L101
...

Sheet 06_Costo_amortizado
A1: Costo amortizado al corte y del ejercicio | H1: ⟵ Inicio | I1: ◀ Anterior | J1: Siguiente ▶
A2: Préstamos y obligaciones financieras · Cliente de muestra S.A. · corte 2025-12-31
A4: Operación | B4: Meses al corte | C4: Períodos vencidos al corte | D4: Fracción del período en curso | E4: Capital contractual al corte | F4: Interés nominal devengado | G4: Costo amortizado al último vencimiento | H4: Interés a la TIE devengado | I4: Costo amortizado al corte | J4: Meses al inicio del ejercicio | K4: Períodos vencidos al inicio | L4: Fracción al inicio | M4: Capital contractual al inicio | N4: Interés nominal devengado al inicio | O4: Costo amortizado al vencimiento previo al inicio | P4: Interés a la TIE devengado al inicio | Q4: Costo amortizado al inicio | R4: Desembolso neto del ejercicio | S4: Pagos del ejercicio | T4: Interés nominal del ejercicio | U4: Gasto financiero a la TIE del ejercicio | V4: Comprobación del movimiento (0)
A5: OP-101 | B5: =DATEDIF('03_Prestamos'!C5,'02_Parametros'!$B$5,"m") | C5: =MIN('04_Condiciones_TIE'!H5,INT(B5/'04_Condiciones_TIE'!G5)) | D5: =IF(C5>='04_Condiciones_TIE'!H5,0,('02_Parametros'!$B$5-EDATE('03_Prestamos'!C5,C5*'04_Condiciones_TIE'!G5))/(EDATE('03_Prestamos'!C5,(C5+1)*'04_Condiciones_TIE'!G5)-EDATE('03_Prestamos'!C5,C5*'04_Condiciones_TIE'!G5))) | E5: =SUMIFS('05_Tabla_amortizacion'!$H$5:$H$163,'05_Tabla_amortizacion'!$A$5:$A$163,A5,'05_Tabla_amortizacion'!$B$5:$B$163,C5) | F5: =E5*'04_Condiciones_TIE'!J5*D5 | G5: =SUMIFS('05_Tabla_amortizacion'!$M$5:$M$163,'05_Tabla_amortizacion'!$A$5:$A$163,A5,'05_Tabla_amortizacion'!$B$5:$B$163,C5) | H5: =G5*'04_Condiciones_TIE'!L5*D5 | I5: =G5+H5 | J5: =IF('03_Prestamos'!C5>'02_Parametros'!$B$6,-1,DATEDIF('03_Prestamos'!C5,'02_Parametros'!$B$6,"m")) | K5: =IF(J5<0,0,MIN('04_Condiciones_TIE'!H5,INT(J5/'04_Condiciones_TIE'!G5))) | L5: =IF(OR(J5<0,K5>='04_Condiciones_TIE'!H5),0,('02_Parametros'!$B$6-EDATE('03_Prestamos'!C5,K5*'04_Condiciones_TIE'!G5))/(EDATE('03_Prestamos'!C5,(K5+1)*'04_Condiciones_TIE'!G5)-EDATE('03_Prestamos'!C5,K5*'04_Condiciones_TIE'!G5))) | M5: =IF(J5<0,0,SUMIFS('05_Tabla_amortizacion'!$H$5:$H$163,'05_Tabla_amortizacion'!$A$5:$A$163,A5,'05_Tabla_amortizacion'!$B$5:$B$163,K5)) | N5: =M5*'04_Condiciones_TIE'!J5*L5 | O5: =IF(J5<0,0,SUMIFS('05_Tabla_amortizacion'!$M$5:$M$163,'05_Tabla_amortizacion'!$A$5:$A$163,A5,'05_Tabla_amortizacion'!$B$5:$B$163,K5)) | P5: =O5*'04_Condiciones_TIE'!L5*L5 | Q5: =O5+P5 | R5: =IF(J5<0,'04_Condiciones_TIE'!E5,0) | S5: =SUMIFS('05_Tabla_amortizacion'!$D$5:$D$163,'05_Tabla_amortizacion'!$A$5:$A$163,A5,'05_Tabla_amortizacion'!$B$5:$B$163,">"&K5,'05_Tabla_amortizacion'!$B$5:$B$163,"<="&C5) | T5: =SUMIFS('05_Tabla_amortizacion'!$F$5:$F$163,'05_Tabla_amortizacion'!$A$5:$A$163,A5,'05_Tabla_amortizacion'!$B$5:$B$163,">"&K5,'05_Tabla_amortizacion'!$B$5:$B$163,"<="&C5)+F5-N5 | U5: =SUMIFS('05_Tabla_amortizacion'!$K$5:$K$163,'05_Tabla_amortizacion'!$A$5:$A$163,A5,'05_Tabla_amortizacion'!$B$5:$B$163,">"&K5,'05_Tabla_amortizacion'!$B$5:$B$163,"<="&C5)+H5-P5 | V5: =Q5+R5+U5-S5-I5
A6: OP-102 | B6: =DATEDIF('03_Prestamos'!C6,'02_Parametros'!$B$5,"m") | C6: =MIN('04_Condiciones_TIE'!H6,INT(B6/'04_Condiciones_TIE'!G6)) | D6: =IF(C6>='04_Condiciones_TIE'!H6,0,('02_Parametros'!$B$5-EDATE('03_Prestamos'!C6,C6*'04_Condiciones_TIE'!G6))/(EDATE('03_Prestamos'!C6,(C6+1)*'04_Condiciones_TIE'!G6)-EDATE('03_Prestamos'!C6,C6*'04_Condiciones_TIE'!G6))) | E6: =SUMIFS('05_Tabla_amortizacion'!$H$5:$H$163,'05_Tabla_amortizacion'!$A$5:$A$163,A6,'05_Tabla_amortizacion'!$B$5:$B$163,C6) | F6: =E6*'04_Condiciones_TIE'!J6*D6 | G6: =SUMIFS('05_Tabla_amortizacion'!$M$5:$M$163,'05_Tabla_amortizacion'!$A$5:$A$163,A6,'05_Tabla_amortizacion'!$B$5:$B$163,C6) | H6: =G6*'04_Condiciones_TIE'!L6*D6 | I6: =G6+H6 | J6: =IF('03_Prestamos'!C6>'02_Parametros'!$B$6,-1,DATEDIF('03_Prestamos'!C6,'02_Parametros'!$B$6,"m")) | K6: =IF(J6<0,0,MIN('04_Condiciones_TIE'!H6,INT(J6/'04_Condiciones_TIE'!G6))) | L6: =IF(OR(J6<0,K6>='04_Condiciones_TIE'!H6),0,('02_Parametros'!$B$6-EDATE('03_Prestamos'!C6,K6*'04_Condiciones_TIE'!G6))/(EDATE('03_Prestamos'!C6,(K6+1)*'04_Condiciones_TIE'!G6)-EDATE('03_Prestamos'!C6,K6*'04_Condiciones_TIE'!G6))) | M6: =IF(J6<0,0,SUMIFS('05_Tabla_amortizacion'!$H$5:$H$163,'05_Tabla_amortizacion'!$A$5:$A$163,A6,'05_Tabla_amortizacion'!$B$5:$B$163,K6)) | N6: =M6*'04_Condiciones_TIE'!J6*L6 | O6: =IF(J6<0,0,SUMIFS('05_Tabla_amortizacion'!$M$5:$M$163,'05_Tabla_amortizacion'!$A$5:$A$163,A6,'05_Tabla_amortizacion'!$B$5:$B$163,K6)) | P6: =O6*'04_Condiciones_TIE'!L6*L6 | Q6: =O6+P6 | R6: =IF(J6<0,'04_Condiciones_TIE'!E6,0) | S6: =SUMIFS('05_Tabla_amortizacion'!$D$5:$D$163,'05_Tabla_amortizacion'!$A$5:$A$163,A6,'05_Tabla_amortizacion'!$B$5:$B$163,">"&K6,'05_Tabla_amortizacion'!$B$5:$B$163,"<="&C6) | T6: =SUMIFS('05_Tabla_amortizacion'!$F$5:$F$163,'05_Tabla_amortizacion'!$A$5:$A$163,A6,'05_Tabla_amortizacion'!$B$5:$B$163,">"&K6,'05_Tabla_amortizacion'!$B$5:$B$163,"<="&C6)+F6-N6 | U6: =SUMIFS('05_Tabla_amortizacion'!$K$5:$K$163,'05_Tabla_amortizacion'!$A$5:$A$163,A6,'05_Tabla_amortizacion'!$B$5:$B$163,">"&K6,'05_Tabla_amortizacion'!$B$5:$B$163,"<="&C6)+H6-P6 | V6: =Q6+R6+U6-S6-I6
A7: OP-103 | B7: =DATEDIF('03_Prestamos'!C7,'02_Parametros'!$B$5,"m") | C7: =MIN('04_Condiciones_TIE'!H7,INT(B7/'04_Condiciones_TIE'!G7)) | D7: =IF(C7>='04_Condiciones_TIE'!H7,0,('02_Parametros'!$B$5-EDATE('03_Prestamos'!C7,C7*'04_Condiciones_TIE'!G7))/(EDATE('03_Prestamos'!C7,(C7+1)*'04_Condiciones_TIE'!G7)-EDATE('03_Prestamos'!C7,C7*'04_Condiciones_TIE'!G7))) | E7: =SUMIFS('05_Tabla_amortizacion'!$H$5:$H$163,'05_Tabla_amortizacion'!$A$5:$A$163,A7,'05_Tabla_amortizacion'!$B$5:$B$163,C7) | F7: =E7*'04_Condiciones_TIE'!J7*D7 | G7: =SUMIFS('05_Tabla_amortizacion'!$M$5:$M$163,'05_Tabla_amortizacion'!$A$5:$A$163,A7,'05_Tabla_amortizacion'!$B$5:$B$163,C7) | H7: =G7*'04_Condiciones_TIE'!L7*D7 | I7: =G7+H7 | J7: =IF('03_Prestamos'!C7>'02_Parametros'!$B$6,-1,DATEDIF('03_Prestamos'!C7,'02_Parametros'!$B$6,"m")) | K7: =IF(J7<0,0,MIN('04_Condiciones_TIE'!H7,INT(J7/'04_Condiciones_TIE'!G7))) | L7: =IF(OR(J7<0,K7>='04_Condiciones_TIE'!H7),0,('02_Parametros'!$B$6-EDATE('03_Prestamos'!C7,K7*'04_Condiciones_TIE'!G7))/(EDATE('03_Prestamos'!C7,(K7+1)*'04_Condiciones_TIE'!G7)-EDATE('03_Prestamos'!C7,K7*'04_Condiciones_TIE'!G7))) | M7: =IF(J7<0,0,SUMIFS('05_Tabla_amortizacion'!$H$5:$H$163,'05_Tabla_amortizacion'!$A$5:$A$163,A7,'05_Tabla_amortizacion'!$B$5:$B$163,K7)) | N7: =M7*'04_Condiciones_TIE'!J7*L7 | O7: =IF(J7<0,0,SUMIFS('05_Tabla_amortizacion'!$M$5:$M$163,'05_Tabla_amortizacion'!$A$5:$A$163,A7,'05_Tabla_amortizacion'!$B$5:$B$163,K7)) | P7: =O7*'04_Condiciones_TIE'!L7*L7 | Q7: =O7+P7 | R7: =IF(J7<0,'04_Condiciones_TIE'!E7,0) | S7: =SUMIFS('05_Tabla_amortizacion'!$D$5:$D$163,'05_Tabla_amortizacion'!$A$5:$A$163,A7,'05_Tabla_amortizacion'!$B$5:$B$163,">"&K7,'05_Tabla_amortizacion'!$B$5:$B$163,"<="&C7) | T7: =SUMIFS('05_Tabla_amortizacion'!$F$5:$F$163,'05_Tabla_amortizacion'!$A$5:$A$163,A7,'05_Tabla_amortizacion'!$B$5:$B$163,">"&K7,'05_Tabla_amortizacion'!$B$5:$B$163,"<="&C7)+F7-N7 | U7: =SUMIFS('05_Tabla_amortizacion'!$K$5:$K$163,'05_Tabla_amortizacion'!$A$5:$A$163,A7,'05_Tabla_amortizacion'!$B$5:$B$163,">"&K7,'05_Tabla_amortizacion'!$B$5:$B$163,"<="&C7)+H7-P7 | V7: =Q7+R7+U7-S7-I7
A8: OP-104 | B8: =DATEDIF('03_Prestamos'!C8,'02_Parametros'!$B$5,"m") | C8: =MIN('04_Condiciones_TIE'!H8,INT(B8/'04_Condiciones_TIE'!G8)) | D8: =IF(C8>='04_Condiciones_TIE'!H8,0,('02_Parametros'!$B$5-EDATE('03_Prestamos'!C8,C8*'04_Condiciones_TIE'!G8))/(EDATE('03_Prestamos'!C8,(C8+1)*'04_Condiciones_TIE'!G8)-EDATE('03_Prestamos'!C8,C8*'04_Condiciones_TIE'!G8))) | E8: =SUMIFS('05_Tabla_amortizacion'!$H$5:$H$163,'05_Tabla_amortizacion'!$A$5:$A$163,A8,'05_Tabla_amortizacion'!$B$5:$B$163,C8) | F8: =E8*'04_Condiciones_TIE'!J8*D8 | G8: =SUMIFS('05_Tabla_amortizacion'!$M$5:$M$163,'05_Tabla_amortizacion'!$A$5:$A$163,A8,'05_Tabla_amortizacion'!$B$5:$B$163,C8) | H8: =G8*'04_Condiciones_TIE'!L8*D8 | I8: =G8+H8 | J8: =IF('03_Prestamos'!C8>'02_Parametros'!$B$6,-1,DATEDIF('03_Prestamos'!C8,'02_Parametros'!$B$6,"m")) | K8: =IF(J8<0,0,MIN('04_Condiciones_TIE'!H8,INT(J8/'04_Condiciones_TIE'!G8))) | L8: =IF(OR(J8<0,K8>='04_Condiciones_TIE'!H8),0,('02_Parametros'!$B$6-EDATE('03_Prestamos'!C8,K8*'04_Condiciones_TIE'!G8))/(EDATE('03_Prestamos'!C8,(K8+1)*'04_Condiciones_TIE'!G8)-EDATE('03_Prestamos'!C8,K8*'04_Condiciones_TIE'!G8))) | M8: =IF(J8<0,0,SUMIFS('05_Tabla_amortizacion'!$H$5:$H$163,'05_Tabla_amortizacion'!$A$5:$A$163,A8,'05_Tabla_amortizacion'!$B$5:$B$163,K8)) | N8: =M8*'04_Condiciones_TIE'!J8*L8 | O8: =IF(J8<0,0,SUMIFS('05_Tabla_amortizacion'!$M$5:$M$163,'05_Tabla_amortizacion'!$A$5:$A$163,A8,'05_Tabla_amortizacion'!$B$5:$B$163,K8)) | P8: =O8*'04_Condiciones_TIE'!L8*L8 | Q8: =O8+P8 | R8: =IF(J8<0,'04_Condiciones_TIE'!E8,0) | S8: =SUMIFS('05_Tabla_amortizacion'!$D$5:$D$163,'05_Tabla_amortizacion'!$A$5:$A$163,A8,'05_Tabla_amortizacion'!$B$5:$B$163,">"&K8,'05_Tabla_amortizacion'!$B$5:$B$163,"<="&C8) | T8: =SUMIFS('05_Tabla_amortizacion'!$F$5:$F$163,'05_Tabla_amortizacion'!$A$5:$A$163,A8,'05_Tabla_amortizacion'!$B$5:$B$163,">"&K8,'05_Tabla_amortizacion'!$B$5:$B$163,"<="&C8)+F8-N8 | U8: =SUMIFS('05_Tabla_amortizacion'!$K$5:$K$163,'05_Tabla_amortizacion'!$A$5:$A$163,A8,'05_Tabla_amortizacion'!$B$5:$B$163,">"&K8,'05_Tabla_amortizacion'!$B$5:$B$163,"<="&C8)+H8-P8 | V8: =Q8+R8+U8-S8-I8
A9: OP-105 | B9: =DATEDIF('03_Prestamos'!C9,'02_Parametros'!$B$5,"m") | C9: =MIN('04_Condiciones_TIE'!H9,INT(B9/'04_Condiciones_TIE'!G9)) | D9: =IF(C9>='04_Condiciones_TIE'!H9,0,('02_Parametros'!$B$5-EDATE('03_Prestamos'!C9,C9*'04_Condiciones_TIE'!G9))/(EDATE('03_Prestamos'!C9,(C9+1)*'04_Condiciones_TIE'!G9)-EDATE('03_Prestamos'!C9,C9*'04_Condiciones_TIE'!G9))) | E9: =SUMIFS('05_Tabla_amortizacion'!$H$5:$H$163,'05_Tabla_amortizacion'!$A$5:$A$163,A9,'05_Tabla_amortizacion'!$B$5:$B$163,C9) | F9: =E9*'04_Condiciones_TIE'!J9*D9 | G9: =SUMIFS('05_Tabla_amortizacion'!$M$5:$M$163,'05_Tabla_amortizacion'!$A$5:$A$163,A9,'05_Tabla_amortizacion'!$B$5:$B$163,C9) | H9: =G9*'04_Condiciones_TIE'!L9*D9 | I9: =G9+H9 | J9: =IF('03_Prestamos'!C9>'02_Parametros'!$B$6,-1,DATEDIF('03_Prestamos'!C9,'02_Parametros'!$B$6,"m")) | K9: =IF(J9<0,0,MIN('04_Condiciones_TIE'!H9,INT(J9/'04_Condiciones_TIE'!G9))) | L9: =IF(OR(J9<0,K9>='04_Condiciones_TIE'!H9),0,('02_Parametros'!$B$6-EDATE('03_Prestamos'!C9,K9*'04_Condiciones_TIE'!G9))/(EDATE('03_Prestamos'!C9,(K9+1)*'04_Condiciones_TIE'!G9)-EDATE('03_Prestamos'!C9,K9*'04_Condiciones_TIE'!G9))) | M9: =IF(J9<0,0,SUMIFS('05_Tabla_amortizacion'!$H$5:$H$163,'05_Tabla_amortizacion'!$A$5:$A$163,A9,'05_Tabla_amortizacion'!$B$5:$B$163,K9)) | N9: =M9*'04_Condiciones_TIE'!J9*L9 | O9: =IF(J9<0,0,SUMIFS('05_Tabla_amortizacion'!$M$5:$M$163,'05_Tabla_amortizacion'!$A$5:$A$163,A9,'05_Tabla_amortizacion'!$B$5:$B$163,K9)) | P9: =O9*'04_Condiciones_TIE'!L9*L9 | Q9: =O9+P9 | R9: =IF(J9<0,'04_Condiciones_TIE'!E9,0) | S9: =SUMIFS('05_Tabla_amortizacion'!$D$5:$D$163,'05_Tabla_amortizacion'!$A$5:$A$163,A9,'05_Tabla_amortizacion'!$B$5:$B$163,">"&K9,'05_Tabla_amortizacion'!$B$5:$B$163,"<="&C9) | T9: =SUMIFS('05_Tabla_amortizacion'!$F$5:$F$163,'05_Tabla_amortizacion'!$A$5:$A$163,A9,'05_Tabla_amortizacion'!$B$5:$B$163,">"&K9,'05_Tabla_amortizacion'!$B$5:$B$163,"<="&C9)+F9-N9 | U9: =SUMIFS('05_Tabla_amortizacion'!$K$5:$K$163,'05_Tabla_amortizacion'!$A$5:$A$163,A9,'05_Tabla_amortizacion'!$B$5:$B$163,">"&K9,'05_Tabla_amortizacion'!$B$5:$B$163,"<="&C9)+H9-P9 | V9: =Q9+R9+U9-S9-I9
A10: OP-106 | B10: =DATEDIF('03_Prestamos'!C10,'02_Parametros'!$B$5,"m") | C10: =MIN('04_Condiciones_TIE'!H10,INT(B10/'04_Condiciones_TIE'!G10)) | D10: =IF(C10>='04_Condiciones_TIE'!H10,0,('02_Parametros'!$B$5-EDATE('03_Prestamos'!C10,C10*'04_Condiciones_TIE'!G10))/(EDATE('03_Prestamos'!C10,(C10+1)*'04_Condiciones_TIE'!G10)-EDATE('03_Prestamos'!C10,C10*'04_Condiciones_TIE'!G10))) | E10: =SUMIFS('05_Tabla_amortizacion'!$H$5:$H$163,'05_Tabla_amortizacion'!$A$5:$A$163,A10,'05_Tabla_amortizacion'!$B$5:$B$163,C10) | F10: =E10*'04_Condiciones_TIE'!J10*D10 | G10: =SUMIFS('05_Tabla_amortizacion'!$M$5:$M$163,'05_Tabla_amortizacion'!$A$5:$A$163,A10,'05_Tabla_amortizacion'!$B$5:$B$163,C10) | H10: =G10*'04_Condiciones_TIE'!L10*D10 | I10: =G10+H10 | J10: =IF('03_Prestamos'!C10>'02_Parametros'!$B$6,-1,DATEDIF('03_Prestamos'!C10,'02_Parametros'!$B$6,"m")) | K10: =IF(J10<0,0,MIN('04_Condiciones_TIE'!H10,INT(J10/'04_Condiciones_TIE'!G10))) | L10: =IF(OR(J10<0,K10>='04_Condiciones_TIE'!H10),0,('02_Parametros'!$B$6-EDATE('03_Prestamos'!C10,K10*'04_Condiciones_TIE'!G10))/(EDATE('03_Prestamos'!C10,(K10+1)*'04_Condiciones_TIE'!G10)-EDATE('03_Prestamos'!C10,K10*'04_Condiciones_TIE'!G10))) | M10: =IF(J10<0,0,SUMIFS('05_Tabla_amortizacion'!$H$5:$H$163,'05_Tabla_amortizacion'!$A$5:$A$163,A10,'05_Tabla_amortizacion'!$B$5:$B$163,K10)) | N10: =M10*'04_Condiciones_TIE'!J10*L10 | O10: =IF(J10<0,0,SUMIFS('05_Tabla_amortizacion'!$M$5:$M$163,'05_Tabla_amortizacion'!$A$5:$A$163,A10,'05_Tabla_amortizacion'!$B$5:$B$163,K10)) | P10: =O10*'04_Condiciones_TIE'!L10*L10 | Q10: =O10+P10 | R10: =IF(J10<0,'04_Condiciones_TIE'!E10,0) | S10: =SUMIFS('05_Tabla_amortizacion'!$D$5:$D$163,'05_Tabla_amortizacion'!$A$5:$A$163,A10,'05_Tabla_amortizacion'!$B$5:$B$163,">"&K10,'05_Tabla_amortizacion'!$B$5:$B$163,"<="&C10) | T10: =SUMIFS('05_Tabla_amortizacion'!$F$5:$F$163,'05_Tabla_amortizacion'!$A$5:$A$163,A10,'05_Tabla_amortizacion'!$B$5:$B$163,">"&K10,'05_Tabla_amortizacion'!$B$5:$B$163,"<="&C10)+F10-N10 | U10: =SUMIFS('05_Tabla_amortizacion'!$K$5:$K$163,'05_Tabla_amortizacion'!$A$5:$A$163,A10,'05_Tabla_amortizacion'!$B$5:$B$163,">"&K10,'05_Tabla_amortizacion'!$B$5:$B$163,"<="&C10)+H10-P10 | V10: =Q10+R10+U10-S10-I10
A11: OP-107 | B11: =DATEDIF('03_Prestamos'!C11,'02_Parametros'!$B$5,"m") | C11: =MIN('04_Condiciones_TIE'!H11,INT(B11/'04_Condiciones_TIE'!G11)) | D11: =IF(C11>='04_Condiciones_TIE'!H11,0,('02_Parametros'!$B$5-EDATE('03_Prestamos'!C11,C11*'04_Condiciones_TIE'!G11))/(EDATE('03_Prestamos'!C11,(C11+1)*'04_Condiciones_TIE'!G11)-EDATE('03_Prestamos'!C11,C11*'04_Condiciones_TIE'!G11))) | E11: =SUMIFS('05_Tabla_amortizacion'!$H$5:$H$163,'05_Tabla_amortizacion'!$A$5:$A$163,A11,'05_Tabla_amortizacion'!$B$5:$B$163,C11) | F11: =E11*'04_Condiciones_TIE'!J11*D11 | G11: =SUMIFS('05_Tabla_amortizacion'!$M$5:$M$163,'05_Tabla_amortizacion'!$A$5:$A$163,A11,'05_Tabla_amortizacion'!$B$5:$B$163,C11) | H11: =G11*'04_Condiciones_TIE'!L11*D11 | I11: =G11+H11 | J11: =IF('03_Prestamos'!C11>'02_Parametros'!$B$6,-1,DATEDIF('03_Prestamos'!C11,'02_Parametros'!$B$6,"m")) | K11: =IF(J11<0,0,MIN('04_Condiciones_TIE'!H11,INT(J11/'04_Condiciones_TIE'!G11))) | L11: =IF(OR(J11<0,K11>='04_Condiciones_TIE'!H11),0,('02_Parametros'!$B$6-EDATE('03_Prestamos'!C11,K11*'04_Condiciones_TIE'!G11))/(EDATE('03_Prestamos'!C11,(K11+1)*'04_Condiciones_TIE'!G11)-EDATE('03_Prestamos'!C11,K11*'04_Condiciones_TIE'!G11))) | M11: =IF(J11<0,0,SUMIFS('05_Tabla_amortizacion'!$H$5:$H$163,'05_Tabla_amortizacion'!$A$5:$A$163,A11,'05_Tabla_amortizacion'!$B$5:$B$163,K11)) | N11: =M11*'04_Condiciones_TIE'!J11*L11 | O11: =IF(J11<0,0,SUMIFS('05_Tabla_amortizacion'!$M$5:$M$163,'05_Tabla_amortizacion'!$A$5:$A$163,A11,'05_Tabla_amortizacion'!$B$5:$B$163,K11)) | P11: =O11*'04_Condiciones_TIE'!L11*L11 | Q11: =O11+P11 | R11: =IF(J11<0,'04_Condiciones_TIE'!E11,0) | S11: =SUMIFS('05_Tabla_amortizacion'!$D$5:$D$163,'05_Tabla_amortizacion'!$A$5:$A$163,A11,'05_Tabla_amortizacion'!$B$5:$B$163,">"&K11,'05_Tabla_amortizacion'!$B$5:$B$163,"<="&C11) | T11: =SUMIFS('05_Tabla_amortizacion'!$F$5:$F$163,'05_Tabla_amortizacion'!$A$5:$A$163,A11,'05_Tabla_amortizacion'!$B$5:$B$163,">"&K11,'05_Tabla_amortizacion'!$B$5:$B$163,"<="&C11)+F11-N11 | U11: =SUMIFS('05_Tabla_amortizacion'!$K$5:$K$163,'05_Tabla_amortizacion'!$A$5:$A$163,A11,'05_Tabla_amortizacion'!$B$5:$B$163,">"&K11,'05_Tabla_amortizacion'!$B$5:$B$163,"<="&C11)+H11-P11 | V11: =Q11+R11+U11-S11-I11
A12: TOTAL | E12: =SUM(E5:E11) | F12: =SUM(F5:F11) | I12: =SUM(I5:I11) | Q12: =SUM(Q5:Q11) | R12: =SUM(R5:R11) | S12: =SUM(S5:S11) | T12: =SUM(T5:T11) | U12: =SUM(U5:U11)
A14: ⓘ Cómo se calcula esta hoja
A15: Columna | B15: Fórmula (Excel) | C15: Cómo se calcula (sencillo) | D15: Ejemplo con números reales | E15: De dónde viene | F15: Norma
A16: Meses al corte | B16: '=DATEDIF('03_Prestamos'!C5,'02_Parametros'!$B$5,"m") | C16: Cuenta los meses completos transcurridos entre la fecha de desembolso (hoja 03) y la fecha de corte (hoja 02). | D16: Fila 1: DATEDIF(«2024-01-15»; «2025-12-31»; "m") → 23 | E16: hoja «Universo de préstamos», hoja «Parámetros» | F16: —
A17: Períodos vencidos al corte | B17: '=MIN('04_Condiciones_TIE'!H5,INT(B5/'04_Condiciones_TIE'!G5)) | C17: Divide los meses al corte para los meses de cada período (hoja 04) y toma la parte entera, sin pasar del número total de períodos: son las cuotas ya vencidas al corte. | D17: Fila 1: MIN(36; INT(23/1)) → 23 | E17: «Meses al corte» (esta hoja), hoja «Condiciones y tasa de interés efectiva» | F17: —
A18: Fracción del período en curso | B18: '=IF(C5>='04_Condiciones_TIE'!H5,0,('02_Parametros'!$B$5-EDATE('03_Prestamos'!C5,C5*'04_Condiciones_TIE'!G5))/(EDATE('03_Prestamos'!C5,(C5+1)*'04_Condiciones_TIE'!G5)-EDATE('03_Prestamos'!C5,C5*'04_Condiciones_TIE'!G5))) | C18: Mide qué parte del período en curso ya pasó al corte: días desde el último vencimiento hasta el corte divididos para los días del período. Si el préstamo ya venció por completo, es cero. | D18: Fila 1: IF(23>=36; 0; («2025-12-31»-EDATE(«2024-01-15»; 23*1))/(EDATE(«2024-01-15»; (23+1)*1)-EDATE(«2024-01-15»; 23*1))) → 51,61 % | E18: «Períodos vencidos al corte» (esta hoja), hoja «Condiciones y tasa de interés efectiva», hoja «Parámetros», hoja «Universo de préstamos» | F18: —
A19: Capital contractual al corte | B19: '=SUMIFS('05_Tabla_amortizacion'!$H$5:$H$163,'05_Tabla_amortizacion'!$A$5:$A$163,A5,'05_Tabla_amortizacion'!$B$5:$B$163,C5) | C19: Busca en la hoja 05 (Tabla de amortización) el capital final de esta operación en el último período vencido al corte. | D19: Fila 1: SUMIFS([«Capital final» de «Tabla de amortización», 159 filas]; [«Operación» de «Tabla de amortización», 159 filas]; «OP-101»; [«Período» de «Tabla de amortización», 159 filas]; 23) → 47.940,12 | E19: «Operación» (esta hoja), «Períodos vencidos al corte» (esta hoja), hoja «Tabla de amortización» | F19: —
A20: Interés nominal devengado | B20: '=E5*'04_Condiciones_TIE'!J5*D5 | C20: Multiplica el capital contractual al corte por la tasa periódica nominal (hoja 04) y por la fracción del período en curso: es el interés del contrato devengado y aún no vencido. | D20: Fila 1: 47.940,12*0,92 %*51,61 % → 226,81 | E20: «Capital contractual al corte» (esta hoja), «Fracción del período en curso» (esta hoja), hoja «Condiciones y tasa de interés efectiva» | F20: —
A21: Costo amortizado al último vencimiento | B21: '=SUMIFS('05_Tabla_amortizacion'!$M$5:$M$163,'05_Tabla_amortizacion'!$A$5:$A$163,A5,'05_Tabla_amortizacion'!$B$5:$B$163,C5) | C21: Busca en la hoja 05 (Tabla de amortización) el costo amortizado final de esta operación en el último período vencido al corte. | D21: Fila 1: SUMIFS([«Costo amortizado final» de «Tabla de amortización», 159 filas]; [«Operación» de «Tabla de amortización», 159 filas]; «OP-101»; [«Período» de «Tabla de amortización», 159 filas]; 23) → 47.560,75 | E21: «Operación» (esta hoja), «Períodos vencidos al corte» (esta hoja), hoja «Tabla de amortización» | F21: —
A22: Interés a la TIE devengado | B22: '=G5*'04_Condiciones_TIE'!L5*D5 | C22: Multiplica el costo amortizado al último vencimiento por la TIE periódica (hoja 04) y por la fracción del período en curso ya transcurrida. | D22: Fila 1: 47.560,75*1,03 %*51,61 % → 253,71 | E22: «Costo amortizado al último vencimiento» (esta hoja), «Fracción del período en curso» (esta hoja), hoja «Condiciones y tasa de interés efectiva» | F22: —
A23: Costo amortizado al corte | B23: '=G5+H5 | C23: Suma el costo amortizado al último vencimiento y el interés a la TIE devengado hasta el corte: es el pasivo auditado. | D23: Fila 1: 47.560,75+253,71 → 47.814,46 | E23: «Costo amortizado al último vencimiento» (esta hoja), «Interés a la TIE devengado» (esta hoja) | F23: —
A24: Meses al inicio del ejercicio | B24: '=IF('03_Prestamos'!C5>'02_Parametros'!$B$6,-1,DATEDIF('03_Prestamos'!C5,'02_Parametros'!$B$6,"m")) | C24: Cuenta los meses completos entre el desembolso y el inicio del ejercicio (hoja 02); si el préstamo se desembolsó después del inicio, marca −1 (préstamo nuevo del año). | D24: Fila 1: IF(«2024-01-15»>«2024-12-31»; -1; DATEDIF(«2024-01-15»; «2024-12-31»; "m")) → 11 | E24: hoja «Universo de préstamos», hoja «Parámetros» | F24: —
A25: Períodos vencidos al inicio | B25: '=IF(J5<0,0,MIN('04_Condiciones_TIE'!H5,INT(J5/'04_Condiciones_TIE'!G5))) | C25: Cuotas ya vencidas al inicio del ejercicio: meses al inicio divididos para los meses del período, parte entera y sin pasar del total. En un préstamo nuevo del año es cero. | D25: Fila 1: IF(11<0; 0; MIN(36; INT(11/1))) → 11 | E25: «Meses al inicio del ejercicio» (esta hoja), hoja «Condiciones y tasa de interés efectiva» | F25: —
A26: Fracción al inicio | B26: '=IF(OR(J5<0,K5>='04_Condiciones_TIE'!H5),0,('02_Parametros'!$B$6-EDATE('03_Prestamos'!C5,K5*'04_Condiciones_TIE'!G5))/(EDATE('03_Prestamos'!C5,(K5+1)*'04_Condiciones_TIE'!G5)-EDATE('03_Prestamos'!C5,K5*'04_Condiciones_TIE'!G5))) | C26: Parte del período que estaba en curso al inicio del ejercicio y que ya había transcurrido; es cero si el préstamo es nuevo del año o ya había vencido por completo. | D26: Fila 1: IF(OR(11<0; 11>=36); 0; («2024-12-31»-EDATE(«2024-01-15»; 11*1))/(EDATE(«2024-01-15»; (11+1)*1)-EDATE(«2024-01-15»; 11*1))) → 51,61 % | E26: «Meses al inicio del ejercicio» (esta hoja), «Períodos vencidos al inicio» (esta hoja), hoja «Condiciones y tasa de interés efectiva», hoja «Parámetros», hoja «Universo de préstamos» | F26: —
... A36: Comprobación del movimiento (0) | B36: '=Q5+R5+U5-S5-I5 | C36: Cuadra el movimiento del año: costo amortizado al inicio + desembolso + gasto a la TIE − pagos − costo amortizado al corte. Debe dar cero; otro valor indica un error en la tabla. | D36: Fila 1: 86.623,23+0,00+8.334,99-47.143,75-47.814,46 → 0,00 | E36: «Costo amortizado al inicio» (esta hoja), «Desembolso neto del ejercicio» (esta hoja), «Gasto financiero a la TIE del ejercicio» (esta hoja), «Pagos del ejercicio» (esta hoja), «Costo amortizado al corte» (esta hoja) | F36: —

Sheet 07_Comisiones
A1: Comisiones y costos de transacción | H1: ⟵ Inicio | I1: ◀ Anterior | J1: Siguiente ▶
A2: Préstamos y obligaciones financieras · Cliente de muestra S.A. · corte 2025-12-31
A4: Operación | B4: Comisiones y costos | C4: Tratamiento del cliente | D4: Interés nominal del ejercicio | E4: Gasto a la TIE del ejercicio | F4: Amortización de costos del ejercicio | G4: Costo por amortizar al corte | H4: Llevado a gasto indebidamente (por amortizar)
A5: OP-101 | B5: ='04_Condiciones_TIE'!D5 | C5: =IF('03_Prestamos'!J5<>"",'03_Prestamos'!J5,IF(B5=0,"Sin comisiones",IF(ABS(N('03_Prestamos'!M5)-'06_Costo_amortizado'!E5)<=0.01,"Gasto (inferido)","TIE"))) | D5: ='06_Costo_amortizado'!T5 | E5: ='06_Costo_amortizado'!U5 | F5: =E5-D5 | G5: ='06_Costo_amortizado'!E5-'06_Costo_amortizado'!G5 | H5: =IF(LEFT(C5,5)="Gasto",G5,0)
A6: OP-102 | B6: ='04_Condiciones_TIE'!D6 | C6: =IF('03_Prestamos'!J6<>"",'03_Prestamos'!J6,IF(B6=0,"Sin comisiones",IF(ABS(N('03_Prestamos'!M6)-'06_Costo_amortizado'!E6)<=0.01,"Gasto (inferido)","TIE"))) | D6: ='06_Costo_amortizado'!T6 | E6: ='06_Costo_amortizado'!U6 | F6: =E6-D6 | G6: ='06_Costo_amortizado'!E6-'06_Costo_amortizado'!G6 | H6: =IF(LEFT(C6,5)="Gasto",G6,0)
A7: OP-103 | B7: ='04_Condiciones_TIE'!D7 | C7: =IF('03_Prestamos'!J7<>"",'03_Prestamos'!J7,IF(B7=0,"Sin comisiones",IF(ABS(N('03_Prestamos'!M7)-'06_Costo_amortizado'!E7)<=0.01,"Gasto (inferido)","TIE"))) | D7: ='06_Costo_amortizado'!T7 | E7: ='06_Costo_amortizado'!U7 | F7: =E7-D7 | G7: ='06_Costo_amortizado'!E7-'06_Costo_amortizado'!G7 | H7: =IF(LEFT(C7,5)="Gasto",G7,0)
A8: OP-104 | B8: ='04_Condiciones_TIE'!D8 | C8: =IF('03_Prestamos'!J8<>"",'03_Prestamos'!J8,IF(B8=0,"Sin comisiones",IF(ABS(N('03_Prestamos'!M8)-'06_Costo_amortizado'!E8)<=0.01,"Gasto (inferido)","TIE"))) | D8: ='06_Costo_amortizado'!T8 | E8: ='06_Costo_amortizado'!U8 | F8: =E8-D8 | G8: ='06_Costo_amortizado'!E8-'06_Costo_amortizado'!G8 | H8: =IF(LEFT(C8,5)="Gasto",G8,0)
A9: OP-105 | B9: ='04_Condiciones_TIE'!D9 | C9: =IF('03_Prestamos'!J9<>"",'03_Prestamos'!J9,IF(B9=0,"Sin comisiones",IF(ABS(N('03_Prestamos'!M9)-'06_Costo_amortizado'!E9)<=0.01,"Gasto (inferido)","TIE"))) | D9: ='06_Costo_amortizado'!T9 | E9: ='06_Costo_amortizado'!U9 | F9: =E9-D9 | G9: ='06_Costo_amortizado'!E9-'06_Costo_amortizado'!G9 | H9: =IF(LEFT(C9,5)="Gasto",G9,0)
A10: OP-106 | B10: ='04_Condiciones_TIE'!D10 | C10: =IF('03_Prestamos'!J10<>"",'03_Prestamos'!J10,IF(B10=0,"Sin comisiones",IF(ABS(N('03_Prestamos'!M10)-'06_Costo_amortizado'!E10)<=0.01,"Gasto (inferido)","TIE"))) | D10: ='06_Costo_amortizado'!T10 | E10: ='06_Costo_amortizado'!U10 | F10: =E10-D10 | G10: ='06_Costo_amortizado'!E10-'06_Costo_amortizado'!G10 | H10: =IF(LEFT(C10,5)="Gasto",G10,0)
A11: OP-107 | B11: ='04_Condiciones_TIE'!D11 | C11: =IF('03_Prestamos'!J11<>"",'03_Prestamos'!J11,IF(B11=0,"Sin comisiones",IF(ABS(N('03_Prestamos'!M11)-'06_Costo_amortizado'!E11)<=0.01,"Gasto (inferido)","TIE"))) | D11: ='06_Costo_amortizado'!T11 | E11: ='06_Costo_amortizado'!U11 | F11: =E11-D11 | G11: ='06_Costo_amortizado'!E11-'06_Costo_amortizado'!G11 | H11: =IF(LEFT(C11,5)="Gasto",G11,0)
A12: TOTAL | B12: =SUM(B5:B11) | F12: =SUM(F5:F11) | G12: =SUM(G5:G11) | H12: =SUM(H5:H11)
A14: ⓘ Cómo se calcula esta hoja
A15: Columna | B15: Fórmula (Excel) | C15: Cómo se calcula (sencillo) | D15: Ejemplo con números reales | E15: De dónde viene | F15: Norma
A16: Comisiones y costos | B16: '='04_Condiciones_TIE'!D5 | C16: Trae las comisiones y costos de transacción de la operación desde la hoja 04 (Condiciones y TIE). | D16: Fila 1: 2.400,00 → 2.400,00 | E16: hoja «Condiciones y tasa de interés efectiva» | F16: —
A17: Tratamiento del cliente | B17: '=IF('03_Prestamos'!J5<>"",'03_Prestamos'!J5,IF(B5=0,"Sin comisiones",IF(ABS(N('03_Prestamos'!M5)-'06_Costo_amortizado'!E5)<=0.01,"Gasto (inferido)","TIE"))) | C17: Usa el tratamiento que informó el cliente en la hoja 03; si no lo informó: sin comisiones, «Sin comisiones»; si el capital registrado es igual al capital contractual al corte (hoja 06), «Gasto (inferido)»; en otro caso, «TIE». | D17: Fila 1: IF(«Gasto»<>""; «Gasto»; IF(2.400,00=0; "Sin comisiones"; IF(ABS(N(47.940,12)-47.940,12)<=0.01; "Gasto (inferido)"; "TIE"))) → Gasto | E17: «Comisiones y costos» (esta hoja), hoja «Universo de préstamos», hoja «Costo amortizado al corte y del ejercicio» | F17: —
A18: Interés nominal del ejercicio | B18: '='06_Costo_amortizado'!T5 | C18: Trae el interés nominal del ejercicio de esta operación desde la hoja 06 (Costo amortizado). | D18: Fila 1: 7.478,25 → 7.478,25 | E18: hoja «Costo amortizado al corte y del ejercicio» | F18: —
A19: Gasto a la TIE del ejercicio | B19: '='06_Costo_amortizado'!U5 | C19: Trae el gasto financiero a la TIE del ejercicio de esta operación desde la hoja 06 (Costo amortizado). | D19: Fila 1: 8.334,99 → 8.334,99 | E19: hoja «Costo amortizado al corte y del ejercicio» | F19: —
A20: Amortización de costos del ejercicio | B20: '=E5-D5 | C20: Resta el interés nominal del gasto a la TIE: es la parte de las comisiones que se lleva a resultados en este ejercicio. | D20: Fila 1: 8.334,99-7.478,25 → 856,74 | E20: «Gasto a la TIE del ejercicio» (esta hoja), «Interés nominal del ejercicio» (esta hoja) | F20: —
A21: Costo por amortizar al corte | B21: '='06_Costo_amortizado'!E5-'06_Costo_amortizado'!G5 | C21: Resta al capital contractual al corte el costo amortizado al último vencimiento (ambos de la hoja 06): son las comisiones que aún quedan por llevar a gasto. | D21: Fila 1: 47.940,12-47.560,75 → 379,36 | E21: hoja «Costo amortizado al corte y del ejercicio» | F21: —
A22: Llevado a gasto indebidamente (por amortizar) | B22: '=IF(LEFT(C5,5)="Gasto",G5,0) | C22: Si el tratamiento del cliente empieza por «Gasto», toma el costo por amortizar al corte: es lo que el cliente ya llevó a resultados antes de tiempo. En otro caso, cero. | D22: Fila 1: IF(LEFT(«Gasto»; 5)="Gasto"; 379,36; 0) → 379,36 | E22: «Tratamiento del cliente» (esta hoja), «Costo por amortizar al corte» (esta hoja) | F22: —

Sheet 08_Intereses
A1: Recálculo de intereses | H1: ⟵ Inicio | I1: ◀ Anterior | J1: Siguiente ▶
A2: Préstamos y obligaciones financieras · Cliente de muestra S.A. · corte 2025-12-31
A4: Operación | B4: Tasa nominal anual (%) | C4: TIE anual efectiva | D4: Interés nominal del ejercicio | E4: Gasto financiero a la TIE | F4: Gasto financiero registrado | G4: Diferencia de gasto | H4: Interés contractual devengado al corte | I4: Intereses por pagar registrados | J4: Interés devengado no registrado
A5: OP-101 | B5: ='04_Condiciones_TIE'!I5 | C5: ='04_Condiciones_TIE'!M5 | D5: ='06_Costo_amortizado'!T5 | E5: ='06_Costo_amortizado'!U5 | F5: =IF('03_Prestamos'!O5="","",'03_Prestamos'!O5) | G5: =IF(F5="","",E5-F5) | H5: ='06_Costo_amortizado'!F5 | I5: =N('03_Prestamos'!N5) | J5: =H5-I5
A6: OP-102 | B6: ='04_Condiciones_TIE'!I6 | C6: ='04_Condiciones_TIE'!M6 | D6: ='06_Costo_amortizado'!T6 | E6: ='06_Costo_amortizado'!U6 | F6: =IF('03_Prestamos'!O6="","",'03_Prestamos'!O6) | G6: =IF(F6="","",E6-F6) | H6: ='06_Costo_amortizado'!F6 | I6: =N('03_Prestamos'!N6) | J6: =H6-I6
A7: OP-103 | B7: ='04_Condiciones_TIE'!I7 | C7: ='04_Condiciones_TIE'!M7 | D7: ='06_Costo_amortizado'!T7 | E7: ='06_Costo_amortizado'!U7 | F7: =IF('03_Prestamos'!O7="","",'03_Prestamos'!O7) | G7: =IF(F7="","",E7-F7) | H7: ='06_Costo_amortizado'!F7 | I7: =N('03_Prestamos'!N7) | J7: =H7-I7
A8: OP-104 | B8: ='04_Condiciones_TIE'!I8 | C8: ='04_Condiciones_TIE'!M8 | D8: ='06_Costo_amortizado'!T8 | E8: ='06_Costo_amortizado'!U8 | F8: =IF('03_Prestamos'!O8="","",'03_Prestamos'!O8) | G8: =IF(F8="","",E8-F8) | H8: ='06_Costo_amortizado'!F8 | I8: =N('03_Prestamos'!N8) | J8: =H8-I8
A9: OP-105 | B9: ='04_Condiciones_TIE'!I9 | C9: ='04_Condiciones_TIE'!M9 | D9: ='06_Costo_amortizado'!T9 | E9: ='06_Costo_amortizado'!U9 | F9: =IF('03_Prestamos'!O9="","",'03_Prestamos'!O9) | G9: =IF(F9="","",E9-F9) | H9: ='06_Costo_amortizado'!F9 | I9: =N('03_Prestamos'!N9) | J9: =H9-I9
A10: OP-106 | B10: ='04_Condiciones_TIE'!I10 | C10: ='04_Condiciones_TIE'!M10 | D10: ='06_Costo_amortizado'!T10 | E10: ='06_Costo_amortizado'!U10 | F10: =IF('03_Prestamos'!O10="","",'03_Prestamos'!O10) | G10: =IF(F10="","",E10-F10) | H10: ='06_Costo_amortizado'!F10 | I10: =N('03_Prestamos'!N10) | J10: =H10-I10
A11: OP-107 | B11: ='04_Condiciones_TIE'!I11 | C11: ='04_Condiciones_TIE'!M11 | D11: ='06_Costo_amortizado'!T11 | E11: ='06_Costo_amortizado'!U11 | F11: =IF('03_Prestamos'!O11="","",'03_Prestamos'!O11) | G11: =IF(F11="","",E11-F11) | H11: ='06_Costo_amortizado'!F11 | I11: =N('03_Prestamos'!N11) | J11: =H11-I11
A12: TOTAL | D12: =SUM(D5:D11) | E12: =SUM(E5:E11) | G12: =SUM(G5:G11) | H12: =SUM(H5:H11) | I12: =SUM(I5:I11) | J12: =SUM(J5:J11)
A14: ⓘ Cómo se calcula esta hoja
A15: Columna | B15: Fórmula (Excel) | C15: Cómo se calcula (sencillo) | D15: Ejemplo con números reales | E15: De dónde viene | F15: Norma
A16: Tasa nominal anual (%) | B16: '='04_Condiciones_TIE'!I5 | C16: Trae la tasa nominal anual del contrato desde la hoja 04 (Condiciones y tasa de interés efectiva). | D16: Fila 1: 11,00 → 11,00 | E16: hoja «Condiciones y tasa de interés efectiva» | F16: —
A17: TIE anual efectiva | B17: '='04_Condiciones_TIE'!M5 | C17: Trae la TIE anual efectiva de la operación, calculada en la hoja 04 (Condiciones y tasa de interés efectiva). | D17: Fila 1: 13,13 % → 13,13 % | E17: hoja «Condiciones y tasa de interés efectiva» | F17: —
A18: Interés nominal del ejercicio | B18: '='06_Costo_amortizado'!T5 | C18: Trae de la hoja 06 (Costo amortizado) el interés del ejercicio calculado a la tasa del contrato. | D18: Fila 1: 7.478,25 → 7.478,25 | E18: hoja «Costo amortizado al corte y del ejercicio» | F18: —
A19: Gasto financiero a la TIE | B19: '='06_Costo_amortizado'!U5 | C19: Trae de la hoja 06 (Costo amortizado) el gasto financiero del ejercicio calculado a la TIE. | D19: Fila 1: 8.334,99 → 8.334,99 | E19: hoja «Costo amortizado al corte y del ejercicio» | F19: —
A20: Gasto financiero registrado | B20: '=IF('03_Prestamos'!O5="","",'03_Prestamos'!O5) | C20: Copia el gasto financiero del año que registró el cliente (hoja 03); si no lo informó, queda en blanco. | D20: Fila 1: IF(7.478,25=""; ""; 7.478,25) → 7.478,25 | E20: hoja «Universo de préstamos» | F20: —
A21: Diferencia de gasto | B21: '=IF(F5="","",E5-F5) | C21: Resta el gasto registrado del gasto a la TIE recalculado; solo se calcula si el cliente informó su gasto. Positivo: el cliente registró menos gasto. | D21: Fila 1: IF(7.478,25=""; ""; 8.334,99-7.478,25) → 856,74 | E21: «Gasto financiero registrado» (esta hoja), «Gasto financiero a la TIE» (esta hoja) | F21: —
A22: Interés contractual devengado al corte | B22: '='06_Costo_amortizado'!F5 | C22: Trae de la hoja 06 el interés nominal devengado desde el último vencimiento hasta el corte. | D22: Fila 1: 226,81 → 226,81 | E22: hoja «Costo amortizado al corte y del ejercicio» | F22: —
A23: Intereses por pagar registrados | B23: '=N('03_Prestamos'!N5) | C23: Copia los intereses por pagar que registró el cliente (hoja 03); si no los informó, cuenta cero. | D23: Fila 1: N(226,81) → 226,81 | E23: hoja «Universo de préstamos» | F23: —
A24: Interés devengado no registrado | B24: '=H5-I5 | C24: Resta los intereses por pagar registrados del interés contractual devengado al corte: es el interés que falta provisionar. | D24: Fila 1: 226,81-226,81 → 0,00 | E24: «Interés contractual devengado al corte» (esta hoja), «Intereses por pagar registrados» (esta hoja) | F24: —

Sheet 09_Confirmacion
A1: Confirmación bancaria y pagos | H1: ⟵ Inicio | I1: ◀ Anterior | J1: Siguiente ▶
A2: Préstamos y obligaciones financieras · Cliente de muestra S.A. · corte 2025-12-31
A4: Operación | B4: Banco | C4: Capital según tabla | D4: Saldo confirmado por el banco | E4: Capital registrado | F4: Costos por amortizar (cliente a la TIE) | G4: Diferencia no explicada | H4: Confirmado − tabla | I4: Pagos del ejercicio (tabla) | J4: Pagos informados | K4: Diferencia de pagos
A5: OP-101 | B5: Banco Pichincha | C5: ='06_Costo_amortizado'!E5 | D5: =IF('03_Prestamos'!L5="","",'03_Prestamos'!L5) | E5: =N('03_Prestamos'!M5) | F5: =IF('07_Comisiones'!C5="TIE",'07_Comisiones'!G5,0) | G5: =IF(D5="","",D5-E5-F5) | H5: =IF(D5="","",D5-C5) | I5: ='06_Costo_amortizado'!S5 | J5: =IF('03_Prestamos'!K5="","",'03_Prestamos'!K5) | K5: =IF(J5="","",I5-J5)
A6: OP-102 | B6: Produbanco | C6: ='06_Costo_amortizado'!E6 | D6: =IF('03_Prestamos'!L6="","",'03_Prestamos'!L6) | E6: =N('03_Prestamos'!M6) | F6: =IF('07_Comisiones'!C6="TIE",'07_Comisiones'!G6,0) | G6: =IF(D6="","",D6-E6-F6) | H6: =IF(D6="","",D6-C6) | I6: ='06_Costo_amortizado'!S6 | J6: =IF('03_Prestamos'!K6="","",'03_Prestamos'!K6) | K6: =IF(J6="","",I6-J6)
A7: OP-103 | B7: Banco Guayaquil | C7: ='06_Costo_amortizado'!E7 | D7: =IF('03_Prestamos'!L7="","",'03_Prestamos'!L7) | E7: =N('03_Prestamos'!M7) | F7: =IF('07_Comisiones'!C7="TIE",'07_Comisiones'!G7,0) | G7: =IF(D7="","",D7-E7-F7) | H7: =IF(D7="","",D7-C7) | I7: ='06_Costo_amortizado'!S7 | J7: =IF('03_Prestamos'!K7="","",'03_Prestamos'!K7) | K7: =IF(J7="","",I7-J7)
A8: OP-104 | B8: Banco del Pacífico | C8: ='06_Costo_amortizado'!E8 | D8: =IF('03_Prestamos'!L8="","",'03_Prestamos'!L8) | E8: =N('03_Prestamos'!M8) | F8: =IF('07_Comisiones'!C8="TIE",'07_Comisiones'!G8,0) | G8: =IF(D8="","",D8-E8-F8) | H8: =IF(D8="","",D8-C8) | I8: ='06_Costo_amortizado'!S8 | J8: =IF('03_Prestamos'!K8="","",'03_Prestamos'!K8) | K8: =IF(J8="","",I8-J8)
A9: OP-105 | B9: Corporación Financiera Nacional | C9: ='06_Costo_amortizado'!E9 | D9: =IF('03_Prestamos'!L9="","",'03_Prestamos'!L9) | E9: =N('03_Prestamos'!M9) | F9: =IF('07_Comisiones'!C9="TIE",'07_Comisiones'!G9,0) | G9: =IF(D9="","",D9-E9-F9) | H9: =IF(D9="","",D9-C9) | I9: ='06_Costo_amortizado'!S9 | J9: =IF('03_Prestamos'!K9="","",'03_Prestamos'!K9) | K9: =IF(J9="","",I9-J9)
A10: OP-106 | B10: Banco Internacional | C10: ='06_Costo_amortizado'!E10 | D10: =IF('03_Prestamos'!L10="","",'03_Prestamos'!L10) | E10: =N('03_Prestamos'!M10) | F10: =IF('07_Comisiones'!C10="TIE",'07_Comisiones'!G10,0) | G10: =IF(D10="","",D10-E10-F10) | H10: =IF(D10="","",D10-C10) | I10: ='06_Costo_amortizado'!S10 | J10: =IF('03_Prestamos'!K10="","",'03_Prestamos'!K10) | K10: =IF(J10="","",I10-J10)
A11: OP-107 | B11: Banco Bolivariano | C11: ='06_Costo_amortizado'!E11 | D11: =IF('03_Prestamos'!L11="","",'03_Prestamos'!L11) | E11: =N('03_Prestamos'!M11) | F11: =IF('07_Comisiones'!C11="TIE",'07_Comisiones'!G11,0) | G11: =IF(D11="","",D11-E11-F11) | H11: =IF(D11="","",D11-C11) | I11: ='06_Costo_amortizado'!S11 | J11: =IF('03_Prestamos'!K11="","",'03_Prestamos'!K11) | K11: =IF(J11="","",I11-J11)
A12: TOTAL | C12: =SUM(C5:C11) | E12: =SUM(E5:E11) | F12: =SUM(F5:F11) | I12: =SUM(I5:I11)
A14: ⓘ Cómo se calcula esta hoja
A15: Columna | B15: Fórmula (Excel) | C15: Cómo se calcula (sencillo) | D15: Ejemplo con números reales | E15: De dónde viene | F15: Norma
A16: Capital según tabla | B16: '='06_Costo_amortizado'!E5 | C16: Trae el capital contractual al corte de esta operación calculado en la hoja 06 (Costo amortizado). | D16: Fila 1: 47.940,12 → 47.940,12 | E16: hoja «Costo amortizado al corte y del ejercicio» | F16: —
A17: Saldo confirmado por el banco | B17: '=IF('03_Prestamos'!L5="","",'03_Prestamos'!L5) | C17: Copia el saldo de capital que confirmó el banco (hoja 03); si no hay confirmación, queda en blanco. | D17: Fila 1: IF(47.940,12=""; ""; 47.940,12) → 47.940,12 | E17: hoja «Universo de préstamos» | F17: —
A18: Capital registrado | B18: '=N('03_Prestamos'!M5) | C18: Copia el saldo de capital registrado por el cliente (hoja 03); si no lo informó, cuenta cero. | D18: Fila 1: N(47.940,12) → 47.940,12 | E18: hoja «Universo de préstamos» | F18: —
A19: Costos por amortizar (cliente a la TIE) | B19: '=IF('07_Comisiones'!C5="TIE",'07_Comisiones'!G5,0) | C19: Si el cliente aplica la TIE a las comisiones (hoja 07), trae el costo por amortizar al corte, porque su saldo contable está neto de esas comisiones; si no, cero. | D19: Fila 1: IF(«Gasto»="TIE"; 379,36; 0) → 0,00 | E19: hoja «Comisiones y costos de transacción» | F19: —
A20: Diferencia no explicada | B20: '=IF(D5="","",D5-E5-F5) | C20: Resta al saldo confirmado el capital registrado y los costos por amortizar: lo que queda no tiene explicación. Solo se calcula si hay saldo confirmado. | D20: Fila 1: IF(47.940,12=""; ""; 47.940,12-47.940,12-0,00) → 0,00 | E20: «Saldo confirmado por el banco» (esta hoja), «Capital registrado» (esta hoja), «Costos por amortizar (cliente a la TIE)» (esta hoja) | F20: —
A21: Confirmado − tabla | B21: '=IF(D5="","",D5-C5) | C21: Resta al saldo confirmado por el banco el capital según la tabla recalculada; en blanco si no hay confirmación. | D21: Fila 1: IF(47.940,12=""; ""; 47.940,12-47.940,12) → 0,00 | E21: «Saldo confirmado por el banco» (esta hoja), «Capital según tabla» (esta hoja) | F21: —
A22: Pagos del ejercicio (tabla) | B22: '='06_Costo_amortizado'!S5 | C22: Trae de la hoja 06 los pagos contractuales que vencieron en el ejercicio según la tabla de amortización. | D22: Fila 1: 47.143,75 → 47.143,75 | E22: hoja «Costo amortizado al corte y del ejercicio» | F22: —
A23: Pagos informados | B23: '=IF('03_Prestamos'!K5="","",'03_Prestamos'!K5) | C23: Copia los pagos del año (capital más interés) que informó el cliente en la hoja 03; en blanco si no los informó. | D23: Fila 1: IF(47.143,75=""; ""; 47.143,75) → 47.143,75 | E23: hoja «Universo de préstamos» | F23: —
A24: Diferencia de pagos | B24: '=IF(J5="","",I5-J5) | C24: Resta los pagos informados de los pagos según la tabla; solo se calcula si el cliente informó sus pagos. | D24: Fila 1: IF(47.143,75=""; ""; 47.143,75-47.143,75) → 0,00 | E24: «Pagos informados» (esta hoja), «Pagos del ejercicio (tabla)» (esta hoja) | F24: —

Sheet 10_Covenants
A1: Covenants y dispensas | H1: ⟵ Inicio | I1: ◀ Anterior | J1: Siguiente ▶
A2: Préstamos y obligaciones financieras · Cliente de muestra S.A. · corte 2025-12-31
A4: Operación | B4: Covenant | C4: Ratio de la entidad | D4: Límite | E4: Tipo de límite | F4: Cumple el límite | G4: Incumplimiento declarado | H4: Incumplimiento al corte | I4: Fecha de la dispensa | J4: Gracia hasta | K4: Dispensa válida al corte (NIC 1 75) | L4: Deuda exigible: toda corriente (74) | M4: Fecha de medición del covenant | N4: Se mide después del corte (72B) | O4: Definición aplicada del covenant
A5: OP-101 | B5: =IF('03_Prestamos'!Q5="","",'03_Prestamos'!Q5) | C5: =IF(B5="","",INDEX('12_Endeudamiento'!$D$8:$D$12,MATCH(B5,'12_Endeudamiento'!$A$8:$A$12,0))) | D5: =IF(B5="","",INDEX('12_Endeudamiento'!$E$8:$E$12,MATCH(B5,'12_Endeudamiento'!$A$8:$A$12,0))) | E5: =IF(B5="","",INDEX('12_Endeudamiento'!$F$8:$F$12,MATCH(B5,'12_Endeudamiento'!$A$8:$A$12,0))) | F5: =IF(B5="","",INDEX('12_Endeudamiento'!$G$8:$G$12,MATCH(B5,'12_Endeudamiento'!$A$8:$A$12,0))) | G5: =IF('03_Prestamos'!R5="","No",'03_Prestamos'!R5) | H5: =IF(OR(G5="Sí",F5="No"),"Sí","No") | K5: =IF(AND('03_Prestamos'!S5<>"",'03_Prestamos'!S5<='02_Parametros'!$B$5,OR('03_Prestamos'!T5="",'03_Prestamos'!T5>=EDATE('02_Parametros'!$B$5,12))),"Sí","No") | L5: =IF(AND(H5="Sí",K5="No",N5="No"),"Sí","No") | N5: =IF(AND('03_Prestamos'!U5<>"",'03_Prestamos'!U5>'02_Parametros'!$B$5),"Sí","No") | O5: =IF(B5="","",INDEX('12_Endeudamiento'!$H$8:$H$12,MATCH(B5,'12_Endeudamiento'!$A$8:$A$12,0)))
A6: OP-102 | B6: =IF('03_Prestamos'!Q6="","",'03_Prestamos'!Q6) | C6: =IF(B6="","",INDEX('12_Endeudamiento'!$D$8:$D$12,MATCH(B6,'12_Endeudamiento'!$A$8:$A$12,0))) | D6: =IF(B6="","",INDEX('12_Endeudamiento'!$E$8:$E$12,MATCH(B6,'12_Endeudamiento'!$A$8:$A$12,0))) | E6: =IF(B6="","",INDEX('12_Endeudamiento'!$F$8:$F$12,MATCH(B6,'12_Endeudamiento'!$A$8:$A$12,0))) | F6: =IF(B6="","",INDEX('12_Endeudamiento'!$G$8:$G$12,MATCH(B6,'12_Endeudamiento'!$A$8:$A$12,0))) | G6: =IF('03_Prestamos'!R6="","No",'03_Prestamos'!R6) | H6: =IF(OR(G6="Sí",F6="No"),"Sí","No") | I6: 46042 | J6: 46568 | K6: =IF(AND('03_Prestamos'!S6<>"",'03_Prestamos'!S6<='02_Parametros'!$B$5,OR('03_Prestamos'!T6="",'03_Prestamos'!T6>=EDATE('02_Parametros'!$B$5,12))),"Sí","No") | L6: =IF(AND(H6="Sí",K6="No",N6="No"),"Sí","No") | M6: 46022 | N6: =IF(AND('03_Prestamos'!U6<>"",'03_Prestamos'!U6>'02_Parametros'!$B$5),"Sí","No") | O6: =IF(B6="","",INDEX('12_Endeudamiento'!$H$8:$H$12,MATCH(B6,'12_Endeudamiento'!$A$8:$A$12,0)))
A7: OP-103 | B7: =IF('03_Prestamos'!Q7="","",'03_Prestamos'!Q7) | C7: =IF(B7="","",INDEX('12_Endeudamiento'!$D$8:$D$12,MATCH(B7,'12_Endeudamiento'!$A$8:$A$12,0))) | D7: =IF(B7="","",INDEX('12_Endeudamiento'!$E$8:$E$12,MATCH(B7,'12_Endeudamiento'!$A$8:$A$12,0))) | E7: =IF(B7="","",INDEX('12_Endeudamiento'!$F$8:$F$12,MATCH(B7,'12_Endeudamiento'!$A$8:$A$12,0))) | F7: =IF(B7="","",INDEX('12_Endeudamiento'!$G$8:$G$12,MATCH(B7,'12_Endeudamiento'!$A$8:$A$12,0))) | G7: =IF('03_Prestamos'!R7="","No",'03_Prestamos'!R7) | H7: =IF(OR(G7="Sí",F7="No"),"Sí","No") | K7: =IF(AND('03_Prestamos'!S7<>"",'03_Prestamos'!S7<='02_Parametros'!$B$5,OR('03_Prestamos'!T7="",'03_Prestamos'!T7>=EDATE('02_Parametros'!$B$5,12))),"Sí","No") | L7: =IF(AND(H7="Sí",K7="No",N7="No"),"Sí","No") | N7: =IF(AND('03_Prestamos'!U7<>"",'03_Prestamos'!U7>'02_Parametros'!$B$5),"Sí","No") | O7: =IF(B7="","",INDEX('12_Endeudamiento'!$H$8:$H$12,MATCH(B7,'12_Endeudamiento'!$A$8:$A$12,0)))
A8: OP-104 | B8: =IF('03_Prestamos'!Q8="","",'03_Prestamos'!Q8) | C8: =IF(B8="","",INDEX('12_Endeudamiento'!$D$8:$D$12,MATCH(B8,'12_Endeudamiento'!$A$8:$A$12,0))) | D8: =IF(B8="","",INDEX('12_Endeudamiento'!$E$8:$E$12,MATCH(B8,'12_Endeudamiento'!$A$8:$A$12,0))) | E8: =IF(B8="","",INDEX('12_Endeudamiento'!$F$8:$F$12,MATCH(B8,'12_Endeudamiento'!$A$8:$A$12,0))) | F8: =IF(B8="","",INDEX('12_Endeudamiento'!$G$8:$G$12,MATCH(B8,'12_Endeudamiento'!$A$8:$A$12,0))) | G8: =IF('03_Prestamos'!R8="","No",'03_Prestamos'!R8) | H8: =IF(OR(G8="Sí",F8="No"),"Sí","No") | K8: =IF(AND('03_Prestamos'!S8<>"",'03_Prestamos'!S8<='02_Parametros'!$B$5,OR('03_Prestamos'!T8="",'03_Prestamos'!T8>=EDATE('02_Parametros'!$B$5,12))),"Sí","No") | L8: =IF(AND(H8="Sí",K8="No",N8="No"),"Sí","No") | N8: =IF(AND('03_Prestamos'!U8<>"",'03_Prestamos'!U8>'02_Parametros'!$B$5),"Sí","No") | O8: =IF(B8="","",INDEX('12_Endeudamiento'!$H$8:$H$12,MATCH(B8,'12_Endeudamiento'!$A$8:$A$12,0)))
A9: OP-105 | B9: =IF('03_Prestamos'!Q9="","",'03_Prestamos'!Q9) | C9: =IF(B9="","",INDEX('12_Endeudamiento'!$D$8:$D$12,MATCH(B9,'12_Endeudamiento'!$A$8:$A$12,0))) | D9: =IF(B9="","",INDEX('12_Endeudamiento'!$E$8:$E$12,MATCH(B9,'12_Endeudamiento'!$A$8:$A$12,0))) | E9: =IF(B9="","",INDEX('12_Endeudamiento'!$F$8:$F$12,MATCH(B9,'12_Endeudamiento'!$A$8:$A$12,0))) | F9: =IF(B9="","",INDEX('12_Endeudamiento'!$G$8:$G$12,MATCH(B9,'12_Endeudamiento'!$A$8:$A$12,0))) | G9: =IF('03_Prestamos'!R9="","No",'03_Prestamos'!R9) | H9: =IF(OR(G9="Sí",F9="No"),"Sí","No") | I9: 46006 | J9: 46477 | K9: =IF(AND('03_Prestamos'!S9<>"",'03_Prestamos'!S9<='02_Parametros'!$B$5,OR('03_Prestamos'!T9="",'03_Prestamos'!T9>=EDATE('02_Parametros'!$B$5,12))),"Sí","No") | L9: =IF(AND(H9="Sí",K9="No",N9="No"),"Sí","No") | M9: 46022 | N9: =IF(AND('03_Prestamos'!U9<>"",'03_Prestamos'!U9>'02_Parametros'!$B$5),"Sí","No") | O9: =IF(B9="","",INDEX('12_Endeudamiento'!$H$8:$H$12,MATCH(B9,'12_Endeudamiento'!$A$8:$A$12,0)))
A10: OP-106 | B10: =IF('03_Prestamos'!Q10="","",'03_Prestamos'!Q10) | C10: =IF(B10="","",INDEX('12_Endeudamiento'!$D$8:$D$12,MATCH(B10,'12_Endeudamiento'!$A$8:$A$12,0))) | D10: =IF(B10="","",INDEX('12_Endeudamiento'!$E$8:$E$12,MATCH(B10,'12_Endeudamiento'!$A$8:$A$12,0))) | E10: =IF(B10="","",INDEX('12_Endeudamiento'!$F$8:$F$12,MATCH(B10,'12_Endeudamiento'!$A$8:$A$12,0))) | F10: =IF(B10="","",INDEX('12_Endeudamiento'!$G$8:$G$12,MATCH(B10,'12_Endeudamiento'!$A$8:$A$12,0))) | G10: =IF('03_Prestamos'!R10="","No",'03_Prestamos'!R10) | H10: =IF(OR(G10="Sí",F10="No"),"Sí","No") | K10: =IF(AND('03_Prestamos'!S10<>"",'03_Prestamos'!S10<='02_Parametros'!$B$5,OR('03_Prestamos'!T10="",'03_Prestamos'!T10>=EDATE('02_Parametros'!$B$5,12))),"Sí","No") | L10: =IF(AND(H10="Sí",K10="No",N10="No"),"Sí","No") | N10: =IF(AND('03_Prestamos'!U10<>"",'03_Prestamos'!U10>'02_Parametros'!$B$5),"Sí","No") | O10: =IF(B10="","",INDEX('12_Endeudamiento'!$H$8:$H$12,MATCH(B10,'12_Endeudamiento'!$A$8:$A$12,0)))
A11: OP-107 | B11: =IF('03_Prestamos'!Q11="","",'03_Prestamos'!Q11) | C11: =IF(B11="","",INDEX('12_Endeudamiento'!$D$8:$D$12,MATCH(B11,'12_Endeudamiento'!$A$8:$A$12,0))) | D11: =IF(B11="","",INDEX('12_Endeudamiento'!$E$8:$E$12,MATCH(B11,'12_Endeudamiento'!$A$8:$A$12,0))) | E11: =IF(B11="","",INDEX('12_Endeudamiento'!$F$8:$F$12,MATCH(B11,'12_Endeudamiento'!$A$8:$A$12,0))) | F11: =IF(B11="","",INDEX('12_Endeudamiento'!$G$8:$G$12,MATCH(B11,'12_Endeudamiento'!$A$8:$A$12,0))) | G11: =IF('03_Prestamos'!R11="","No",'03_Prestamos'!R11) | H11: =IF(OR(G11="Sí",F11="No"),"Sí","No") | K11: =IF(AND('03_Prestamos'!S11<>"",'03_Prestamos'!S11<='02_Parametros'!$B$5,OR('03_Prestamos'!T11="",'03_Prestamos'!T11>=EDATE('02_Parametros'!$B$5,12))),"Sí","No") | L11: =IF(AND(H11="Sí",K11="No",N11="No"),"Sí","No") | M11: 46203 | N11: =IF(AND('03_Prestamos'!U11<>"",'03_Prestamos'!U11>'02_Parametros'!$B$5),"Sí","No") | O11: =IF(B11="","",INDEX('12_Endeudamiento'!$H$8:$H$12,MATCH(B11,'12_Endeudamiento'!$A$8:$A$12,0)))
A13: ⓘ Cómo se calcula esta hoja
A14: Columna | B14: Fórmula (Excel) | C14: Cómo se calcula (sencillo) | D14: Ejemplo con números reales | E14: De dónde viene | F14: Norma
A15: Covenant | B15: '=IF('03_Prestamos'!Q5="","",'03_Prestamos'!Q5) | C15: Copia el ratio pactado como covenant (deuda/activos, deuda/EBITDA, DSCR…) de la hoja 03; en blanco si no hay covenant. | D15: Fila 1: IF((vacío)=""; ""; (vacío)) → (en blanco) | E15: hoja «Universo de préstamos» | F15: —
A16: Ratio de la entidad | B16: '=IF(B5="","",INDEX('12_Endeudamiento'!$D$8:$D$12,MATCH(B5,'12_Endeudamiento'!$A$8:$A$12,0))) | C16: Busca el covenant de esta operación en la hoja 12 (Endeudamiento) y trae el ratio calculado para la entidad; en blanco si no hay covenant. | D16: Fila 1: IF((vacío)=""; ""; INDEX([«Ratio (veces)» de «Endeudamiento y ratios de covenants (analítica, no requisito NIIF)», 5 filas]; MATCH((vacío); [«Concepto» de «Endeudamiento y ratios de covenants (analítica, no requisito NIIF)», 5 filas]; 0))) → (en blanco) | E16: «Covenant» (esta hoja), hoja «Endeudamiento y ratios de covenants (analítica, no requisito NIIF)» | F16: —
A17: Límite | B17: '=IF(B5="","",INDEX('12_Endeudamiento'!$E$8:$E$12,MATCH(B5,'12_Endeudamiento'!$A$8:$A$12,0))) | C17: Busca el covenant en la hoja 12 (Endeudamiento) y trae el límite pactado en el contrato, tomado de los parámetros. | D17: Fila 1: IF((vacío)=""; ""; INDEX([«Límite (veces)» de «Endeudamiento y ratios de covenants (analítica, no requisito NIIF)», 5 filas]; MATCH((vacío); [«Concepto» de «Endeudamiento y ratios de covenants (analítica, no requisito NIIF)», 5 filas]; 0))) → (en blanco) | E17: «Covenant» (esta hoja), hoja «Endeudamiento y ratios de covenants (analítica, no requisito NIIF)» | F17: —
A18: Tipo de límite | B18: '=IF(B5="","",INDEX('12_Endeudamiento'!$F$8:$F$12,MATCH(B5,'12_Endeudamiento'!$A$8:$A$12,0))) | C18: Busca el covenant en la hoja 12 (Endeudamiento) y trae si el límite es un máximo o un mínimo. | D18: Fila 1: IF((vacío)=""; ""; INDEX([«Tipo» de «Endeudamiento y ratios de covenants (analítica, no requisito NIIF)», 5 filas]; MATCH((vacío); [«Concepto» de «Endeudamiento y ratios de covenants (analítica, no requisito NIIF)», 5 filas]; 0))) → (en blanco) | E18: «Covenant» (esta hoja), hoja «Endeudamiento y ratios de covenants (analítica, no requisito NIIF)» | F18: —
A19: Cumple el límite | B19: '=IF(B5="","",INDEX('12_Endeudamiento'!$G$8:$G$12,MATCH(B5,'12_Endeudamiento'!$A$8:$A$12,0))) | C19: Busca el covenant en la hoja 12 (Endeudamiento) y trae si la entidad cumple el límite; queda en blanco si falta el ratio, el límite o, en el DSCR, la definición contractual. | D19: Fila 1: IF((vacío)=""; ""; INDEX([«Cumple (solo con definición contractual)» de «Endeudamiento y ratios de covenants (analítica, no requisito NIIF)», 5 filas]; MATCH((vacío); [«Concepto» de «Endeudamiento y ratios de covenants (analítica, no requisito NIIF)», 5 filas]; 0))) → (en blanco) | E19: «Covenant» (esta hoja), hoja «Endeudamiento y ratios de covenants (analítica, no requisito NIIF)» | F19: —
A20: Incumplimiento declarado | B20: '=IF('03_Prestamos'!R5="","No",'03_Prestamos'!R5) | C20: Copia si el cliente declaró incumplimiento del covenant (hoja 03); si no dijo nada, se toma como «No». | D20: Fila 1: IF((vacío)=""; "No"; (vacío)) → No | E20: hoja «Universo de préstamos» | F20: —
A21: Incumplimiento al corte | B21: '=IF(OR(G5="Sí",F5="No"),"Sí","No") | C21: Marca «Sí» si el cliente declaró el incumplimiento o si el recálculo muestra que no cumple el límite. | D21: Fila 1: IF(OR(«No»="Sí"; (vacío)="No"); "Sí"; "No") → No | E21: «Incumplimiento declarado» (esta hoja), «Cumple el límite» (esta hoja) | F21: —
A22: Dispensa válida al corte (NIC 1 75) | B22: '=IF(AND('03_Prestamos'!S5<>"",'03_Prestamos'!S5<='02_Parametros'!$B$5,OR('03_Prestamos'!T5="",'03_Prestamos'!T5>=EDATE('02_Parametros'!$B$5,12))),"Sí","No") | C22: «Sí» cuando hay fecha de dispensa, es anterior o igual al corte y la gracia no tiene fecha o llega al menos 12 meses después del corte (hojas 02 y 03). | D22: Fila 1: IF(AND((vacío)<>""; (vacío)<=«2025-12-31»; OR((vacío)=""; (vacío)>=EDATE(«2025-12-31»; 12))); "Sí"; "No") → No | E22: hoja «Universo de préstamos», hoja «Parámetros» | F22: —
A23: Deuda exigible: toda corriente (74) | B23: '=IF(AND(H5="Sí",K5="No",N5="No"),"Sí","No") | C23: «Sí» cuando hay incumplimiento al corte, no hay dispensa válida y el covenant no se mide después del corte: entonces toda la deuda pasa a corriente. | D23: Fila 1: IF(AND(«No»="Sí"; «No»="No"; «No»="No"); "Sí"; "No") → No | E23: «Incumplimiento al corte» (esta hoja), «Dispensa válida al corte (NIC 1 75)» (esta hoja), «Se mide después del corte (72B)» (esta hoja) | F23: —
A24: Se mide después del corte (72B) | B24: '=IF(AND('03_Prestamos'!U5<>"",'03_Prestamos'!U5>'02_Parametros'!$B$5),"Sí","No") | C24: «Sí» si la fecha de medición del covenant informada en la hoja 03 es posterior al corte: ese covenant no reclasifica la deuda, solo se revela. | D24: Fila 1: IF(AND((vacío)<>""; (vacío)>«2025-12-31»); "Sí"; "No") → No | E24: hoja «Universo de préstamos», hoja «Parámetros» | F24: —
A25: Definición aplicada del covenant | B25: '=IF(B5="","",INDEX('12_Endeudamiento'!$H$8:$H$12,MATCH(B5,'12_Endeudamiento'!$A$8:$A$12,0))) | C25: Busca el covenant en la hoja 12 (Endeudamiento) y trae la definición con la que se midió (la del contrato o, en el DSCR sin definición, la analítica de la firma). | D25: Fila 1: IF((vacío)=""; ""; INDEX([«Definición aplicada» de «Endeudamiento y ratios de covenants (analítica, no requisito NIIF)», 5 filas]; MATCH((vacío); [«Concepto» de «Endeudamiento y ratios de covenants (analítica, no requisito NIIF)», 5 filas]; 0))) → (en blanco) | E25: «Covenant» (esta hoja), hoja «Endeudamiento y ratios de covenants (analítica, no requisito NIIF)» | F25: —

Sheet 11_Clasificacion
A1: Clasificación corriente / no corriente | H1: ⟵ Inicio | I1: ◀ Anterior | J1: Siguiente ▶
A2: Préstamos y obligaciones financieras · Cliente de muestra S.A. · corte 2025-12-31
A4: Operación | B4: Costo amortizado al corte | C4: Período a 12 meses | D4: Capital contractual después de 12 meses | E4: Corriente: capital de 12 meses + interés devengado (69 c) | F4: Exigible por covenant | G4: Corriente auditado | H4: No corriente auditado | I4: Corriente registrado | J4: Diferencia corriente
A5: OP-101 | B5: ='06_Costo_amortizado'!I5 | C5: =MIN('06_Costo_amortizado'!C5+12/'04_Condiciones_TIE'!G5,'04_Condiciones_TIE'!H5) | D5: =SUMIFS('05_Tabla_amortizacion'!$H$5:$H$163,'05_Tabla_amortizacion'!$A$5:$A$163,A5,'05_Tabla_amortizacion'!$B$5:$B$163,C5) | E5: =MIN('06_Costo_amortizado'!E5-D5+'06_Costo_amortizado'!H5,B5) | F5: ='10_Covenants'!L5 | G5: =IF(F5="Sí",B5,E5) | H5: =B5-G5 | I5: =IF('03_Prestamos'!P5="","",'03_Prestamos'!P5) | J5: =IF(I5="","",G5-I5)
A6: OP-102 | B6: ='06_Costo_amortizado'!I6 | C6: =MIN('06_Costo_amortizado'!C6+12/'04_Condiciones_TIE'!G6,'04_Condiciones_TIE'!H6) | D6: =SUMIFS('05_Tabla_amortizacion'!$H$5:$H$163,'05_Tabla_amortizacion'!$A$5:$A$163,A6,'05_Tabla_amortizacion'!$B$5:$B$163,C6) | E6: =MIN('06_Costo_amortizado'!E6-D6+'06_Costo_amortizado'!H6,B6) | F6: ='10_Covenants'!L6 | G6: =IF(F6="Sí",B6,E6) | H6: =B6-G6 | I6: =IF('03_Prestamos'!P6="","",'03_Prestamos'!P6) | J6: =IF(I6="","",G6-I6)
A7: OP-103 | B7: ='06_Costo_amortizado'!I7 | C7: =MIN('06_Costo_amortizado'!C7+12/'04_Condiciones_TIE'!G7,'04_Condiciones_TIE'!H7) | D7: =SUMIFS('05_Tabla_amortizacion'!$H$5:$H$163,'05_Tabla_amortizacion'!$A$5:$A$163,A7,'05_Tabla_amortizacion'!$B$5:$B$163,C7) | E7: =MIN('06_Costo_amortizado'!E7-D7+'06_Costo_amortizado'!H7,B7) | F7: ='10_Covenants'!L7 | G7: =IF(F7="Sí",B7,E7) | H7: =B7-G7 | I7: =IF('03_Prestamos'!P7="","",'03_Prestamos'!P7) | J7: =IF(I7="","",G7-I7)
A8: OP-104 | B8: ='06_Costo_amortizado'!I8 | C8: =MIN('06_Costo_amortizado'!C8+12/'04_Condiciones_TIE'!G8,'04_Condiciones_TIE'!H8) | D8: =SUMIFS('05_Tabla_amortizacion'!$H$5:$H$163,'05_Tabla_amortizacion'!$A$5:$A$163,A8,'05_Tabla_amortizacion'!$B$5:$B$163,C8) | E8: =MIN('06_Costo_amortizado'!E8-D8+'06_Costo_amortizado'!H8,B8) | F8: ='10_Covenants'!L8 | G8: =IF(F8="Sí",B8,E8) | H8: =B8-G8 | I8: =IF('03_Prestamos'!P8="","",'03_Prestamos'!P8) | J8: =IF(I8="","",G8-I8)
A9: OP-105 | B9: ='06_Costo_amortizado'!I9 | C9: =MIN('06_Costo_amortizado'!C9+12/'04_Condiciones_TIE'!G9,'04_Condiciones_TIE'!H9) | D9: =SUMIFS('05_Tabla_amortizacion'!$H$5:$H$163,'05_Tabla_amortizacion'!$A$5:$A$163,A9,'05_Tabla_amortizacion'!$B$5:$B$163,C9) | E9: =MIN('06_Costo_amortizado'!E9-D9+'06_Costo_amortizado'!H9,B9) | F9: ='10_Covenants'!L9 | G9: =IF(F9="Sí",B9,E9) | H9: =B9-G9 | I9: =IF('03_Prestamos'!P9="","",'03_Prestamos'!P9) | J9: =IF(I9="","",G9-I9)
A10: OP-106 | B10: ='06_Costo_amortizado'!I10 | C10: =MIN('06_Costo_amortizado'!C10+12/'04_Condiciones_TIE'!G10,'04_Condiciones_TIE'!H10) | D10: =SUMIFS('05_Tabla_amortizacion'!$H$5:$H$163,'05_Tabla_amortizacion'!$A$5:$A$163,A10,'05_Tabla_amortizacion'!$B$5:$B$163,C10) | E10: =MIN('06_Costo_amortizado'!E10-D10+'06_Costo_amortizado'!H10,B10) | F10: ='10_Covenants'!L10 | G10: =IF(F10="Sí",B10,E10) | H10: =B10-G10 | I10: =IF('03_Prestamos'!P10="","",'03_Prestamos'!P10) | J10: =IF(I10="","",G10-I10)
A11: OP-107 | B11: ='06_Costo_amortizado'!I11 | C11: =MIN('06_Costo_amortizado'!C11+12/'04_Condiciones_TIE'!G11,'04_Condiciones_TIE'!H11) | D11: =SUMIFS('05_Tabla_amortizacion'!$H$5:$H$163,'05_Tabla_amortizacion'!$A$5:$A$163,A11,'05_Tabla_amortizacion'!$B$5:$B$163,C11) | E11: =MIN('06_Costo_amortizado'!E11-D11+'06_Costo_amortizado'!H11,B11) | F11: ='10_Covenants'!L11 | G11: =IF(F11="Sí",B11,E11) | H11: =B11-G11 | I11: =IF('03_Prestamos'!P11="","",'03_Prestamos'!P11) | J11: =IF(I11="","",G11-I11)
A12: TOTAL | B12: =SUM(B5:B11) | E12: =SUM(E5:E11) | G12: =SUM(G5:G11) | H12: =SUM(H5:H11)
A14: ⓘ Cómo se calcula esta hoja
A15: Columna | B15: Fórmula (Excel) | C15: Cómo se calcula (sencillo) | D15: Ejemplo con números reales | E15: De dónde viene | F15: Norma
A16: Costo amortizado al corte | B16: '='06_Costo_amortizado'!I5 | C16: Trae el costo amortizado al corte de esta operación calculado en la hoja 06 (Costo amortizado). | D16: Fila 1: 47.814,46 → 47.814,46 | E16: hoja «Costo amortizado al corte y del ejercicio» | F16: —
A17: Período a 12 meses | B17: '=MIN('06_Costo_amortizado'!C5+12/'04_Condiciones_TIE'!G5,'04_Condiciones_TIE'!H5) | C17: Suma a los períodos vencidos al corte (hoja 06) los períodos que caben en 12 meses, sin pasar del total de períodos: es la cuota que vence un año después del corte. | D17: Fila 1: MIN(23+12/1; 36) → 35 | E17: hoja «Costo amortizado al corte y del ejercicio», hoja «Condiciones y tasa de interés efectiva» | F17: —
A18: Capital contractual después de 12 meses | B18: '=SUMIFS('05_Tabla_amortizacion'!$H$5:$H$163,'05_Tabla_amortizacion'!$A$5:$A$163,A5,'05_Tabla_amortizacion'!$B$5:$B$163,C5) | C18: Busca en la hoja 05 (Tabla de amortización) el capital final de esta operación en el período a 12 meses: es lo que se seguirá debiendo dentro de un año. | D18: Fila 1: SUMIFS([«Capital final» de «Tabla de amortización», 159 filas]; [«Operación» de «Tabla de amortización», 159 filas]; «OP-101»; [«Período» de «Tabla de amortización», 159 filas]; 35) → 3.892,96 | E18: «Operación» (esta hoja), «Período a 12 meses» (esta hoja), hoja «Tabla de amortización» | F18: —
A19: Corriente: capital de 12 meses + interés devengado (69 c) | B19: '=MIN('06_Costo_amortizado'!E5-D5+'06_Costo_amortizado'!H5,B5) | C19: Capital contractual al corte (hoja 06) menos el que queda después de 12 meses, más el interés a la TIE devengado; sin superar el costo amortizado al corte. | D19: Fila 1: MIN(47.940,12-3.892,96+253,71; 47.814,46) → 44.300,86 | E19: «Capital contractual después de 12 meses» (esta hoja), «Costo amortizado al corte» (esta hoja), hoja «Costo amortizado al corte y del ejercicio» | F19: —
A20: Exigible por covenant | B20: '='10_Covenants'!L5 | C20: Trae de la hoja 10 (Covenants) si la deuda es exigible por un covenant incumplido sin dispensa válida. | D20: Fila 1: «No» → No | E20: hoja «Covenants y dispensas» | F20: —
A21: Corriente auditado | B21: '=IF(F5="Sí",B5,E5) | C21: Si la deuda es exigible por covenant, todo el costo amortizado es corriente; si no, la porción que vence en 12 meses más el interés devengado. | D21: Fila 1: IF(«No»="Sí"; 47.814,46; 44.300,86) → 44.300,86 | E21: «Exigible por covenant» (esta hoja), «Costo amortizado al corte» (esta hoja), «Corriente: capital de 12 meses + interés devengado (69 c)» (esta hoja) | F21: —
A22: No corriente auditado | B22: '=B5-G5 | C22: Resta el corriente auditado del costo amortizado al corte: es la parte que vence después de 12 meses. | D22: Fila 1: 47.814,46-44.300,86 → 3.513,60 | E22: «Costo amortizado al corte» (esta hoja), «Corriente auditado» (esta hoja) | F22: —
A23: Corriente registrado | B23: '=IF('03_Prestamos'!P5="","",'03_Prestamos'!P5) | C23: Copia la porción corriente que presentó el cliente (hoja 03); en blanco si no la informó. | D23: Fila 1: IF((vacío)=""; ""; (vacío)) → (en blanco) | E23: hoja «Universo de préstamos» | F23: —
A24: Diferencia corriente | B24: '=IF(I5="","",G5-I5) | C24: Resta el corriente registrado del corriente auditado; solo se calcula si el cliente informó su porción corriente. Positivo: falta reclasificar a corriente. | D24: Fila 1: IF((vacío)=""; ""; 44.300,86-(vacío)) → (en blanco) | E24: «Corriente registrado» (esta hoja), «Corriente auditado» (esta hoja) | F24: —

Sheet 12_Endeudamiento
A1: Endeudamiento y ratios de covenants (analítica, no requisito NIIF) | H1: ⟵ Inicio | I1: ◀ Anterior | J1: Siguiente ▶
A2: Préstamos y obligaciones financieras · Cliente de muestra S.A. · corte 2025-12-31
A4: Concepto | B4: Numerador | C4: Denominador | D4: Ratio (veces) | E4: Límite (veces) | F4: Tipo | G4: Cumple (solo con definición contractual) | H4: Definición aplicada
A5: Deuda financiera auditada (costo amortizado) | B5: =SUM('06_Costo_amortizado'!I5:I11)
A6: Gasto financiero del ejercicio (TIE) | B6: =SUM('06_Costo_amortizado'!U5:U11)
A7: Servicio de la deuda del ejercicio (pagos) | B7: =SUM('06_Costo_amortizado'!S5:S11)
A8: Deuda / activos | B8: =B5 | C8: =IF('02_Parametros'!$B$8="","",'02_Parametros'!$B$8) | D8: =IF(OR(B8="",C8="",C8<=0),"",B8/C8) | E8: =IF('02_Parametros'!$B$14="","",'02_Parametros'!$B$14) | F8: Máximo | G8: =IF(OR(D8="",E8=""),"",IF(F8="Máximo",IF(D8<=E8,"Sí","No"),IF(D8>=E8,"Sí","No"))) | H8: Analítica de auditoría (no es un requisito NIIF)
A9: Deuda / patrimonio | B9: =B5 | C9: =IF('02_Parametros'!$B$9="","",'02_Parametros'!$B$9) | D9: =IF(OR(B9="",C9="",C9<=0),"",B9/C9) | E9: =IF('02_Parametros'!$B$15="","",'02_Parametros'!$B$15) | F9: Máximo | G9: =IF(OR(D9="",E9=""),"",IF(F9="Máximo",IF(D9<=E9,"Sí","No"),IF(D9>=E9,"Sí","No"))) | H9: Analítica de auditoría (no es un requisito NIIF)
A10: Deuda / EBITDA | B10: =B5 | C10: =IF('02_Parametros'!$B$10="","",'02_Parametros'!$B$10) | D10: =IF(OR(B10="",C10="",C10<=0),"",B10/C10) | E10: =IF('02_Parametros'!$B$16="","",'02_Parametros'!$B$16) | F10: Máximo | G10: =IF(OR(D10="",E10=""),"",IF(F10="Máximo",IF(D10<=E10,"Sí","No"),IF(D10>=E10,"Sí","No"))) | H10: Analítica de auditoría (no es un requisito NIIF)
A11: Cobertura de intereses | B11: =IF('02_Parametros'!$B$13="EBIT",IF('02_Parametros'!$B$11="","",'02_Parametros'!$B$11),IF('02_Parametros'!$B$10="","",'02_Parametros'!$B$10)) | C11: =B6 | D11: =IF(OR(B11="",C11="",C11<=0),"",B11/C11) | E11: =IF('02_Parametros'!$B$17="","",'02_Parametros'!$B$17) | F11: Mínimo | G11: =IF(OR(D11="",E11=""),"",IF(F11="Máximo",IF(D11<=E11,"Sí","No"),IF(D11>=E11,"Sí","No"))) | H11: Analítica de auditoría (no es un requisito NIIF)
A12: DSCR | B12: =IF('02_Parametros'!$B$12="","",'02_Parametros'!$B$12) | C12: =IF('02_Parametros'!$B$20="",B7,'02_Parametros'!$B$20) | D12: =IF(OR(B12="",C12="",C12<=0),"",B12/C12) | E12: =IF('02_Parametros'!$B$18="","",'02_Parametros'!$B$18) | F12: Mínimo | G12: =IF(OR(D12="",E12="",'02_Parametros'!$B$19=""),"",IF(F12="Máximo",IF(D12<=E12,"Sí","No"),IF(D12>=E12,"Sí","No"))) | H12: =IF('02_Parametros'!$B$19="","DSCR analítico de la firma",'02_Parametros'!$B$19)
A14: ⓘ Cómo se calcula esta hoja
A15: Columna | B15: Fórmula (Excel) | C15: Cómo se calcula (sencillo) | D15: Ejemplo con números reales | E15: De dónde viene | F15: Norma
A16: Numerador | B16: '=SUM('06_Costo_amortizado'!I5:I11) | C16: Cambia por fila: la deuda auditada es la suma del costo amortizado al corte (hoja 06), el gasto financiero la suma del gasto a la TIE y el servicio de la deuda la suma de los pagos del ejercicio; en los ratios, la deuda auditada, el EBITDA o EBIT según la base elegida, o el efectivo para el servicio de la deuda (hoja 02). | D16: Fila 1: SUM([«Costo amortizado al corte» de «Costo amortizado al corte y del ejercicio», 7 filas]) → 659.965,19 | E16: hoja «Costo amortizado al corte y del ejercicio» | F16: —
A17: Denominador | B17: '=IF('02_Parametros'!$B$8="","",'02_Parametros'!$B$8) | C17: En cada ratio trae la base de la hoja 02 (Parámetros): total de activos, patrimonio o EBITDA; en la cobertura, el gasto financiero del ejercicio; en el DSCR, el servicio de la deuda del contrato o, si falta, el del ejercicio. | D17: Fila 4: IF(2.500.000,00=""; ""; 2.500.000,00) → 2.500.000,00 | E17: hoja «Parámetros» | F17: —
A18: Ratio (veces) | B18: '=IF(OR(B8="",C8="",C8<=0),"",B8/C8) | C18: Divide el numerador para el denominador; queda en blanco si falta alguno o si el denominador es cero o negativo. | D18: Fila 4: IF(OR(659.965,19=""; 2.500.000,00=""; 2.500.000,00<=0); ""; 659.965,19/2.500.000,00) → 0,26 | E18: «Numerador» (esta hoja), «Denominador» (esta hoja) | F18: —
A19: Límite (veces) | B19: '=IF('02_Parametros'!$B$14="","",'02_Parametros'!$B$14) | C19: Trae el límite pactado para este ratio desde la hoja 02 (Parámetros); en blanco si el contrato no lo fija. | D19: Fila 4: IF(0,60=""; ""; 0,60) → 0,60 | E19: hoja «Parámetros» | F19: —
A20: Cumple (solo con definición contractual) | B20: '=IF(OR(D8="",E8=""),"",IF(F8="Máximo",IF(D8<=E8,"Sí","No"),IF(D8>=E8,"Sí","No"))) | C20: Compara el ratio con el límite: si es un máximo, cumple cuando no lo supera; si es un mínimo, cuando lo alcanza. En el DSCR solo concluye si hay definición contractual. | D20: Fila 4: IF(OR(0,26=""; 0,60=""); ""; IF(«Máximo»="Máximo"; IF(0,26<=0,60; "Sí"; "No"); IF(0,26>=0,60; "Sí"; "No"))) → Sí | E20: «Ratio (veces)» (esta hoja), «Límite (veces)» (esta hoja), «Tipo» (esta hoja) | F20: —
A21: Definición aplicada | B21: '=IF('02_Parametros'!$B$19="","DSCR analítico de la firma",'02_Parametros'!$B$19) | C21: En el DSCR muestra la definición contractual de la hoja 02 o, si falta, «DSCR analítico de la firma», que no concluye incumplimiento. | D21: Fila 8: IF(«Flujo de caja operativo antes de intereses ÷ servicio de la deuda del ejercicio (cláusula 8.2 del contrato)»=""; "DSCR analítico de la firma"; «Flujo de caja operativo antes de intereses ÷ servicio de la deuda del ejercicio (cláusula 8.2 del contrato)») → Flujo de caja operativo antes de intereses ÷ servicio de la deuda del ejercicio (cláusula 8.2 del contrato) | E21: hoja «Parámetros» | F21: —

Sheet 13_Conciliacion
A1: Conciliación y ajuste | H1: ⟵ Inicio | I1: ◀ Anterior | J1: Siguiente ▶
A2: Préstamos y obligaciones financieras · Cliente de muestra S.A. · corte 2025-12-31
A4: Operación | B4: Costo amortizado auditado | C4: Capital registrado | D4: Intereses registrados | E4: Total registrado | F4: Ajuste propuesto | G4: Corriente auditado | H4: No corriente auditado | I4: Gasto financiero (TIE)
A5: OP-101 | B5: ='06_Costo_amortizado'!I5 | C5: =N('03_Prestamos'!M5) | D5: =N('03_Prestamos'!N5) | E5: =C5+D5 | F5: =B5-E5 | G5: ='11_Clasificacion'!G5 | H5: ='11_Clasificacion'!H5 | I5: ='06_Costo_amortizado'!U5
A6: OP-102 | B6: ='06_Costo_amortizado'!I6 | C6: =N('03_Prestamos'!M6) | D6: =N('03_Prestamos'!N6) | E6: =C6+D6 | F6: =B6-E6 | G6: ='11_Clasificacion'!G6 | H6: ='11_Clasificacion'!H6 | I6: ='06_Costo_amortizado'!U6
A7: OP-103 | B7: ='06_Costo_amortizado'!I7 | C7: =N('03_Prestamos'!M7) | D7: =N('03_Prestamos'!N7) | E7: =C7+D7 | F7: =B7-E7 | G7: ='11_Clasificacion'!G7 | H7: ='11_Clasificacion'!H7 | I7: ='06_Costo_amortizado'!U7
A8: OP-104 | B8: ='06_Costo_amortizado'!I8 | C8: =N('03_Prestamos'!M8) | D8: =N('03_Prestamos'!N8) | E8: =C8+D8 | F8: =B8-E8 | G8: ='11_Clasificacion'!G8 | H8: ='11_Clasificacion'!H8 | I8: ='06_Costo_amortizado'!U8
A9: OP-105 | B9: ='06_Costo_amortizado'!I9 | C9: =N('03_Prestamos'!M9) | D9: =N('03_Prestamos'!N9) | E9: =C9+D9 | F9: =B9-E9 | G9: ='11_Clasificacion'!G9 | H9: ='11_Clasificacion'!H9 | I9: ='06_Costo_amortizado'!U9
A10: OP-106 | B10: ='06_Costo_amortizado'!I10 | C10: =N('03_Prestamos'!M10) | D10: =N('03_Prestamos'!N10) | E10: =C10+D10 | F10: =B10-E10 | G10: ='11_Clasificacion'!G10 | H10: ='11_Clasificacion'!H10 | I10: ='06_Costo_amortizado'!U10
A11: OP-107 | B11: ='06_Costo_amortizado'!I11 | C11: =N('03_Prestamos'!M11) | D11: =N('03_Prestamos'!N11) | E11: =C11+D11 | F11: =B11-E11 | G11: ='11_Clasificacion'!G11 | H11: ='11_Clasificacion'!H11 | I11: ='06_Costo_amortizado'!U11
A12: TOTAL | B12: =SUM(B5:B11) | C12: =SUM(C5:C11) | D12: =SUM(D5:D11) | E12: =SUM(E5:E11) | F12: =SUM(F5:F11) | G12: =SUM(G5:G11) | H12: =SUM(H5:H11) | I12: =SUM(I5:I11)
A14: ⓘ Cómo se calcula esta hoja
A15: Columna | B15: Fórmula (Excel) | C15: Cómo se calcula (sencillo) | D15: Ejemplo con números reales | E15: De dónde viene | F15: Norma
A16: Costo amortizado auditado | B16: '='06_Costo_amortizado'!I5 | C16: Trae el costo amortizado al corte de esta operación, calculado en la hoja 06 (Costo amortizado). | D16: Fila 1: 47.814,46 → 47.814,46 | E16: hoja «Costo amortizado al corte y del ejercicio» | F16: —
A17: Capital registrado | B17: '=N('03_Prestamos'!M5) | C17: Copia el saldo de capital que registró el cliente en la hoja 03 (Universo de préstamos); vacío cuenta cero. | D17: Fila 1: N(47.940,12) → 47.940,12 | E17: hoja «Universo de préstamos» | F17: —
A18: Intereses registrados | B18: '=N('03_Prestamos'!N5) | C18: Copia los intereses por pagar que registró el cliente en la hoja 03 (Universo de préstamos); vacío cuenta cero. | D18: Fila 1: N(226,81) → 226,81 | E18: hoja «Universo de préstamos» | F18: —
A19: Total registrado | B19: '=C5+D5 | C19: Suma el capital registrado y los intereses registrados: es el pasivo según los libros del cliente. | D19: Fila 1: 47.940,12+226,81 → 48.166,93 | E19: «Capital registrado» (esta hoja), «Intereses registrados» (esta hoja) | F19: —
A20: Ajuste propuesto | B20: '=B5-E5 | C20: Resta el total registrado del costo amortizado auditado. Positivo: el pasivo del cliente está subestimado. | D20: Fila 1: 47.814,46-48.166,93 → -352,47 | E20: «Costo amortizado auditado» (esta hoja), «Total registrado» (esta hoja) | F20: —
A21: Corriente auditado | B21: '='11_Clasificacion'!G5 | C21: Trae la porción corriente auditada de la operación desde la hoja 11 (Clasificación corriente / no corriente). | D21: Fila 1: 44.300,86 → 44.300,86 | E21: hoja «Clasificación corriente / no corriente» | F21: —
A22: No corriente auditado | B22: '='11_Clasificacion'!H5 | C22: Trae la porción no corriente auditada de la operación desde la hoja 11 (Clasificación corriente / no corriente). | D22: Fila 1: 3.513,60 → 3.513,60 | E22: hoja «Clasificación corriente / no corriente» | F22: —
A23: Gasto financiero (TIE) | B23: '='06_Costo_amortizado'!U5 | C23: Trae el gasto financiero del ejercicio a la TIE de esta operación desde la hoja 06 (Costo amortizado). | D23: Fila 1: 8.334,99 → 8.334,99 | E23: hoja «Costo amortizado al corte y del ejercicio» | F23: —

Sheet 14_Flujos_modificacion
A1: Flujos de la modificación (adenda) descontados a la TIE original | H1: ⟵ Inicio | I1: ◀ Anterior | J1: Siguiente ▶
A2: Préstamos y obligaciones financieras · Cliente de muestra S.A. · corte 2025-12-31
A4: Operación | B4: Escenario | C4: Fecha del flujo | D4: Importe del flujo | E4: Años al descuento (días ÷ 365) | F4: TIE anual original | G4: Valor presente a la TIE original
A5: OP-103 | B5: Modificado | C5: 46388 | D5: 30000 | E5: =IF('03_Prestamos'!W7="","",(C5-'03_Prestamos'!W7)/365) | F5: ='04_Condiciones_TIE'!M7 | G5: =IF(E5="","",D5/(1+F5)^E5)
A6: OP-103 | B6: Modificado | C6: 46569 | D6: 30000 | E6: =IF('03_Prestamos'!W7="","",(C6-'03_Prestamos'!W7)/365) | F6: ='04_Condiciones_TIE'!M7 | G6: =IF(E6="","",D6/(1+F6)^E6)
A7: OP-103 | B7: Modificado | C7: 46753 | D7: 30000 | E7: =IF('03_Prestamos'!W7="","",(C7-'03_Prestamos'!W7)/365) | F7: ='04_Condiciones_TIE'!M7 | G7: =IF(E7="","",D7/(1+F7)^E7)
A8: OP-103 | B8: Modificado | C8: 46935 | D8: 30000 | E8: =IF('03_Prestamos'!W7="","",(C8-'03_Prestamos'!W7)/365) | F8: ='04_Condiciones_TIE'!M7 | G8: =IF(E8="","",D8/(1+F8)^E8)
A9: OP-103 | B9: Modificado | C9: 47119 | D9: 30000 | E9: =IF('03_Prestamos'!W7="","",(C9-'03_Prestamos'!W7)/365) | F9: ='04_Condiciones_TIE'!M7 | G9: =IF(E9="","",D9/(1+F9)^E9)
A10: OP-103 | B10: Modificado | C10: 47300 | D10: 30000 | E10: =IF('03_Prestamos'!W7="","",(C10-'03_Prestamos'!W7)/365) | F10: ='04_Condiciones_TIE'!M7 | G10: =IF(E10="","",D10/(1+F10)^E10)
A11: OP-103 | B11: Original | C11: 46023 | D11: 45948.59 | E11: =IF('03_Prestamos'!W7="","",(C11-'03_Prestamos'!W7)/365) | F11: ='04_Condiciones_TIE'!M7 | G11: =IF(E11="","",D11/(1+F11)^E11)
A12: OP-103 | B12: Original | C12: 46204 | D12: 45948.59 | E12: =IF('03_Prestamos'!W7="","",(C12-'03_Prestamos'!W7)/365) | F12: ='04_Condiciones_TIE'!M7 | G12: =IF(E12="","",D12/(1+F12)^E12)
A13: OP-103 | B13: Original | C13: 46388 | D13: 45948.59 | E13: =IF('03_Prestamos'!W7="","",(C13-'03_Prestamos'!W7)/365) | F13: ='04_Condiciones_TIE'!M7 | G13: =IF(E13="","",D13/(1+F13)^E13)
A14: OP-103 | B14: Original | C14: 46569 | D14: 45948.59 | E14: =IF('03_Prestamos'!W7="","",(C14-'03_Prestamos'!W7)/365) | F14: ='04_Condiciones_TIE'!M7 | G14: =IF(E14="","",D14/(1+F14)^E14)
A16: ⓘ Cómo se calcula esta hoja
A17: Columna | B17: Fórmula (Excel) | C17: Cómo se calcula (sencillo) | D17: Ejemplo con números reales | E17: De dónde viene | F17: Norma
A18: Años al descuento (días ÷ 365) | B18: '=IF('03_Prestamos'!W7="","",(C5-'03_Prestamos'!W7)/365) | C18: Cuenta los días entre la fecha de la modificación (hoja 03) y la fecha del flujo y los divide para 365; en blanco si no hay fecha de modificación. | D18: Fila 1: IF(«2025-12-01»=""; ""; («2027-01-01»-«2025-12-01»)/365) → 1,08 | E18: «Fecha del flujo» (esta hoja), hoja «Universo de préstamos» | F18: —
A19: TIE anual original | B19: '='04_Condiciones_TIE'!M7 | C19: Trae la TIE anual efectiva original del préstamo desde la hoja 04 (Condiciones y tasa de interés efectiva). | D19: Fila 1: 9,73 % → 9,73 % | E19: hoja «Condiciones y tasa de interés efectiva» | F19: —
A20: Valor presente a la TIE original | B20: '=IF(E5="","",D5/(1+F5)^E5) | C20: Descuenta el importe del flujo a la TIE anual original por los años al descuento: importe ÷ (1 + TIE) elevado a los años. En blanco si no hay años. | D20: Fila 1: IF(1,08=""; ""; 30.000,00/(1+9,73 %)^1,08) → 27.126,25 | E20: «Años al descuento (días ÷ 365)» (esta hoja), «Importe del flujo» (esta hoja), «TIE anual original» (esta hoja) | F20: —

Sheet 15_Prueba_10pct
A1: Prueba del 10 % (NIIF 9 3.3.2 y B3.3.6) | H1: ⟵ Inicio | I1: ◀ Anterior | J1: Siguiente ▶
A2: Préstamos y obligaciones financieras · Cliente de muestra S.A. · corte 2025-12-31
A4: Operación | B4: Modificación declarada | C4: Fecha de la modificación | D4: TIE anual original | E4: Flujos originales restantes informados | F4: Flujos modificados informados | G4: Valor presente de los flujos originales restantes | H4: Valor presente de los flujos modificados | I4: Comisiones netas pagadas por la modificación | J4: Valor presente de las nuevas condiciones | K4: Diferencia | L4: Diferencia / valor presente original | M4: ¿Condiciones sustancialmente diferentes (≥ 10 %)? | N4: Conclusión | O4: Marco aplicado
A5: OP-103 | B5: =IF('03_Prestamos'!V7="","No",'03_Prestamos'!V7) | C5: 45992 | D5: ='04_Condiciones_TIE'!M7 | E5: =COUNTIFS('14_Flujos_modificacion'!$A$5:$A$14,A5,'14_Flujos_modificacion'!$B$5:$B$14,"Original") | F5: =COUNTIFS('14_Flujos_modificacion'!$A$5:$A$14,A5,'14_Flujos_modificacion'!$B$5:$B$14,"Modificado") | G5: =SUMIFS('14_Flujos_modificacion'!$G$5:$G$14,'14_Flujos_modificacion'!$A$5:$A$14,A5,'14_Flujos_modificacion'!$B$5:$B$14,"Original") | H5: =SUMIFS('14_Flujos_modificacion'!$G$5:$G$14,'14_Flujos_modificacion'!$A$5:$A$14,A5,'14_Flujos_modificacion'!$B$5:$B$14,"Modificado") | I5: =N('03_Prestamos'!X7) | J5: =IF(OR(E5=0,F5=0,'03_Prestamos'!W7="",G5<=0),"",H5+I5) | K5: =IF(J5="","",J5-G5) | L5: =IF(J5="","",K5/G5) | M5: =IF(L5="","",IF(ABS(L5)>=0.1,"Sí","No")) | N5: =IF(M5="","Dato insuficiente: conclusión bloqueada",IF(M5="Sí","Sustancial: baja del pasivo original y reconocimiento de uno nuevo (3.3.2)","No sustancial: el pasivo continúa; costos y comisiones se amortizan (B3.3.6A)")) | O5: NIIF 9 3.3.2 y B3.3.6: prueba del 10 % sobre el valor presente descontado a la tasa de interés efectiva original.
A6: OP-105 | B6: =IF('03_Prestamos'!V9="","No",'03_Prestamos'!V9) | D6: ='04_Condiciones_TIE'!M9 | E6: =COUNTIFS('14_Flujos_modificacion'!$A$5:$A$14,A6,'14_Flujos_modificacion'!$B$5:$B$14,"Original") | F6: =COUNTIFS('14_Flujos_modificacion'!$A$5:$A$14,A6,'14_Flujos_modificacion'!$B$5:$B$14,"Modificado") | G6: =SUMIFS('14_Flujos_modificacion'!$G$5:$G$14,'14_Flujos_modificacion'!$A$5:$A$14,A6,'14_Flujos_modificacion'!$B$5:$B$14,"Original") | H6: =SUMIFS('14_Flujos_modificacion'!$G$5:$G$14,'14_Flujos_modificacion'!$A$5:$A$14,A6,'14_Flujos_modificacion'!$B$5:$B$14,"Modificado") | I6: =N('03_Prestamos'!X9) | J6: =IF(OR(E6=0,F6=0,'03_Prestamos'!W9="",G6<=0),"",H6+I6) | K6: =IF(J6="","",J6-G6) | L6: =IF(J6="","",K6/G6) | M6: =IF(L6="","",IF(ABS(L6)>=0.1,"Sí","No")) | N6: =IF(M6="","Dato insuficiente: conclusión bloqueada",IF(M6="Sí","Sustancial: baja del pasivo original y reconocimiento de uno nuevo (3.3.2)","No sustancial: el pasivo continúa; costos y comisiones se amortizan (B3.3.6A)")) | O6: NIIF 9 3.3.2 y B3.3.6: prueba del 10 % sobre el valor presente descontado a la tasa de interés efectiva original.
A8: ⓘ Cómo se calcula esta hoja
A9: Columna | B9: Fórmula (Excel) | C9: Cómo se calcula (sencillo) | D9: Ejemplo con números reales | E9: De dónde viene | F9: Norma
A10: Modificación declarada | B10: '=IF('03_Prestamos'!V7="","No",'03_Prestamos'!V7) | C10: Copia si el cliente declaró una modificación de condiciones en el año (hoja 03); si no dijo nada, «No». | D10: Fila 1: IF(«Sí»=""; "No"; «Sí») → Sí | E10: hoja «Universo de préstamos» | F10: —
A11: TIE anual original | B11: '='04_Condiciones_TIE'!M7 | C11: Trae la TIE anual efectiva original de la operación desde la hoja 04 (Condiciones y TIE). | D11: Fila 1: 9,73 % → 9,73 % | E11: hoja «Condiciones y tasa de interés efectiva» | F11: —
A12: Flujos originales restantes informados | B12: '=COUNTIFS('14_Flujos_modificacion'!$A$5:$A$14,A5,'14_Flujos_modificacion'!$B$5:$B$14,"Original") | C12: Cuenta cuántos flujos «Original» de esta operación hay en la hoja 14 (Flujos de la modificación). | D12: Fila 1: COUNTIFS([«Operación» de «Flujos de la modificación (adenda) descontados a la TIE original», 10 filas]; «OP-103»; [«Escenario» de «Flujos de la modificación (adenda) descontados a la TIE original», 10 filas]; "Original") → 4 | E12: «Operación» (esta hoja), hoja «Flujos de la modificación (adenda) descontados a la TIE original» | F12: —
A13: Flujos modificados informados | B13: '=COUNTIFS('14_Flujos_modificacion'!$A$5:$A$14,A5,'14_Flujos_modificacion'!$B$5:$B$14,"Modificado") | C13: Cuenta cuántos flujos «Modificado» de esta operación hay en la hoja 14 (Flujos de la modificación). | D13: Fila 1: COUNTIFS([«Operación» de «Flujos de la modificación (adenda) descontados a la TIE original», 10 filas]; «OP-103»; [«Escenario» de «Flujos de la modificación (adenda) descontados a la TIE original», 10 filas]; "Modificado") → 6 | E13: «Operación» (esta hoja), hoja «Flujos de la modificación (adenda) descontados a la TIE original» | F13: —
A14: Valor presente de los flujos originales restantes | B14: '=SUMIFS('14_Flujos_modificacion'!$G$5:$G$14,'14_Flujos_modificacion'!$A$5:$A$14,A5,'14_Flujos_modificacion'!$B$5:$B$14,"Original") | C14: Suma en la hoja 14 el valor presente a la TIE original de los flujos «Original» de esta operación. | D14: Fila 1: SUMIFS([«Valor presente a la TIE original» de «Flujos de la modificación (adenda) descontados a la TIE original», 10 filas]; [«Operación» de «Flujos de la modificación (adenda) descontados a la TIE original», 10 filas]; «OP-103»; [«Escenario» de «Flujos de la modificación (adenda) descontados a la TIE original», 10 filas]; "Original") → 170.350,33 | E14: «Operación» (esta hoja), hoja «Flujos de la modificación (adenda) descontados a la TIE original» | F14: —
A15: Valor presente de los flujos modificados | B15: '=SUMIFS('14_Flujos_modificacion'!$G$5:$G$14,'14_Flujos_modificacion'!$A$5:$A$14,A5,'14_Flujos_modificacion'!$B$5:$B$14,"Modificado") | C15: Suma en la hoja 14 el valor presente a la TIE original de los flujos «Modificado» de esta operación. | D15: Fila 1: SUMIFS([«Valor presente a la TIE original» de «Flujos de la modificación (adenda) descontados a la TIE original», 10 filas]; [«Operación» de «Flujos de la modificación (adenda) descontados a la TIE original», 10 filas]; «OP-103»; [«Escenario» de «Flujos de la modificación (adenda) descontados a la TIE original», 10 filas]; "Modificado") → 145.394,68 | E15: «Operación» (esta hoja), hoja «Flujos de la modificación (adenda) descontados a la TIE original» | F15: —
A16: Comisiones netas pagadas por la modificación | B16: '=N('03_Prestamos'!X7) | C16: Copia las comisiones pagadas al prestamista netas de las recibidas por la adenda (hoja 03); vacío cuenta cero. | D16: Fila 1: N(1.500,00) → 1.500,00 | E16: hoja «Universo de préstamos» | F16: —
A17: Valor presente de las nuevas condiciones | B17: '=IF(OR(E5=0,F5=0,'03_Prestamos'!W7="",G5<=0),"",H5+I5) | C17: Suma el valor presente de los flujos modificados y las comisiones netas. Queda en blanco si faltan flujos originales o modificados, la fecha de modificación o el valor presente original. | D17: Fila 1: IF(OR(4=0; 6=0; «2025-12-01»=""; 170.350,33<=0); ""; 145.394,68+1.500,00) → 146.894,68 | E17: «Flujos originales restantes informados» (esta hoja), «Flujos modificados informados» (esta hoja), «Valor presente de los flujos originales restantes» (esta hoja), «Valor presente de los flujos modificados» (esta hoja), «Comisiones netas pagadas por la modificación» (esta hoja), hoja «Universo de préstamos» | F17: —
A18: Diferencia | B18: '=IF(J5="","",J5-G5) | C18: Resta el valor presente de los flujos originales restantes del valor presente de las nuevas condiciones. | D18: Fila 1: IF(146.894,68=""; ""; 146.894,68-170.350,33) → -23.455,66 | E18: «Valor presente de las nuevas condiciones» (esta hoja), «Valor presente de los flujos originales restantes» (esta hoja) | F18: —
A19: Diferencia / valor presente original | B19: '=IF(J5="","",K5/G5) | C19: Divide la diferencia para el valor presente de los flujos originales restantes: es el porcentaje de cambio. | D19: Fila 1: IF(146.894,68=""; ""; -23.455,66/170.350,33) → -13,77 % | E19: «Valor presente de las nuevas condiciones» (esta hoja), «Diferencia» (esta hoja), «Valor presente de los flujos originales restantes» (esta hoja) | F19: —
A20: ¿Condiciones sustancialmente diferentes (≥ 10 %)? | B20: '=IF(L5="","",IF(ABS(L5)>=0.1,"Sí","No")) | C20: «Sí» si la diferencia, en valor absoluto, llega al 10 % del valor presente original; en blanco si la prueba no se pudo calcular. | D20: Fila 1: IF(-13,77 %=""; ""; IF(ABS(-13,77 %)>=0.1; "Sí"; "No")) → Sí | E20: «Diferencia / valor presente original» (esta hoja) | F20: —
A21: Conclusión | B21: '=IF(M5="","Dato insuficiente: conclusión bloqueada",IF(M5="Sí","Sustancial: baja del pasivo original y reconocimiento de uno nuevo (3.3.2)","No sustancial: el pasivo continúa; costos y comisiones se amortizan (B3.3.6A)")) | C21: Redacta la conclusión: sin resultado, «Dato insuficiente: conclusión bloqueada»; si es sustancial, baja del pasivo original y alta de uno nuevo; si no, el pasivo continúa y los costos se amortizan. | D21: Fila 1: IF(«Sí»=""; "Dato insuficiente: conclusión bloqueada"; IF(«Sí»="Sí"; "Sustancial: baja del pasivo original y reconocimiento de uno nuevo (3.3.2)"; "No sustancial: el pasivo continúa; costos y comisiones se amortizan (B3.3.6A)")) → Sustancial: baja del pasivo original y reconocimiento de uno nuevo (3.3.2) | E21: «¿Condiciones sustancialmente diferentes (≥ 10 %)?» (esta hoja) | F21: —

Sheet 16_Problemas
A1: Problemas encontrados | H1: ⟵ Inicio | I1: ◀ Anterior | J1: Siguiente ▶
A2: Préstamos y obligaciones financieras · Cliente de muestra S.A. · corte 2025-12-31
A4: Código | B4: Descripción | C4: Importe
A5: NO_DESEMBOLSADO | B5: OP-108: desembolso del 2026-01-10, posterior al corte; no es un pasivo al corte (NIIF 9 3.1.1). Revele si es un hecho posterior significativo. | C5: 0
A6: ENDEUDAMIENTO_SOBRE_LIMITE | B6: Deuda / EBITDA: 2,20 veces frente al límite máximo de 1,8 veces. Analítica de auditoría (no es un requisito NIIF): revise el efecto en covenants, empresa en marcha (NIA 570) y revelaciones (NIIF 7 18–19). | C6: 0
A7: ENDEUDAMIENTO_SOBRE_LIMITE | B7: DSCR: 0,76 veces frente al límite mínimo de 1,25 veces. Analítica de auditoría (no es un requisito NIIF): revise el efecto en covenants, empresa en marcha (NIA 570) y revelaciones (NIIF 7 18–19). | C7: 0
A8: COMISIONES_A_GASTO | B8: OP-101: las comisiones de 2.400,00 se llevaron a gasto; forman parte de la TIE (NIIF 9 5.1.1 y Apéndice A). Costo pendiente de amortizar al corte 379,36. | C8: -379.36
A9: GASTO_FINANCIERO_DIFERENCIA | B9: OP-101: gasto financiero a la TIE 8.334,99 vs registrado 7.478,25. | C9: 856.74
A10: PASIVO_DIFERENCIA | B10: OP-101: costo amortizado con intereses devengados 47.814,46 vs registrado (capital + intereses) 48.166,93. | C10: -352.47
A11: INTERES_DEVENGADO_NO_REGISTRADO | B11: OP-102: interés devengado desde el último vencimiento 1.416,67 y registrado 0,00 (devengo, NIIF 9 4.2.1 y Apéndice A). | C11: 1416.67
A12: GASTO_FINANCIERO_DIFERENCIA | B12: OP-102: gasto financiero a la TIE 16.504,82 vs registrado 15.010,65. | C12: 1494.17
A13: COVENANT_SIN_DISPENSA | B13: OP-102: covenant «Deuda / EBITDA» incumplido al corte sin dispensa obtenida hasta el corte con gracia ≥ 12 meses: toda la deuda es corriente (NIC 1 74–75). | C13: 127760.65
A14: DISPENSA_POSTERIOR | B14: OP-102: la dispensa del 2026-01-20 es posterior al corte: no cambia la clasificación (NIC 1 74); revele como hecho posterior no ajustante (NIC 1 76 b)–c), NIC 10). | C14: 0
A15: CLASIFICACION_CP_LP | B15: OP-102: porción corriente auditada 169.254,82 vs registrada 41.494,17 (NIC 1 69–76). | C15: 127760.65
A16: PASIVO_DIFERENCIA | B16: OP-102: costo amortizado con intereses devengados 169.254,82 vs registrado (capital + intereses) 167.760,65. | C16: 1494.17
... A28: REVELACION_INCUMPLIMIENTO | B28: OP-107: incumplimiento de la condición pactada «DSCR» y impago de principal o intereses por 1.645,83 (pagos de la tabla 41.645,83 vs informados 40.000,00) sin subsanar al cierre. Revele el detalle del incumplimiento, el importe en libros del préstamo (59.563,11) y si se subsanó o se renegociaron las condiciones antes de la autorización de los estados financieros (NIIF 7 18–19). | C28: 59563.11

Sheet 13_Conclusion
A1: Conclusión | H1: ⟵ Inicio | I1: ◀ Anterior | J1: Siguiente ▶
A2: Préstamos y obligaciones financieras · Cliente de muestra S.A. · corte 2025-12-31
A4: Concepto | B4: Detalle
A5: Conciliación con el mayor | B5: Población None · mayor None · diferencia None
A6: Evaluación de excepciones
A7: Análisis
A8: Conclusión

Sheet 14_Control_Revision
A1: Control de revisión | H1: ⟵ Inicio | I1: ◀ Anterior
A2: Préstamos y obligaciones financieras · Cliente de muestra S.A. · corte 2025-12-31
A4: Fecha | B4: Acción | C4: Estado anterior | D4: Estado nuevo | E4: Actor | F4: Comentario
