Workbook

Sheet 00_Inicio
B2: AuditConsulting Auditores Cía. Ltda. · AUDIT-IA
B4: Propiedades de inversión
B6: Cliente | C6: Cliente de muestra S.A. | D6: RUC | E6: 1790000000001
B7: Marco contable | C7: NIIF completas | D7: Fecha de corte | E7: 2025-12-31
B8: Preparó | C8: Ejercicio modelo | D8: Revisó | E8: Pendiente
B10: INDICADORES CLAVE
B11: Ajuste propuesto (neto) | C11: Problemas encontrados
B12: -198500 | C12: 18
B15: IR A LA CÉDULA
B16: Carátula | C16: Programa | D16: Base técnica | E16: Resumen y ajuste propuesto
B17: Parámetros y ruta por marco | C17: Registro de inmuebles | D17: Clasificación | E17: Costo inicial
B18: Valor razonable | C18: Modelo del costo: depreciación y deterioro | D18: Medición auditada por inmueble | E18: Transferencias
B19: Historial del superávit de revaluación | C19: Ingresos por alquiler | D19: Bajas | E19: Sumaria y conciliación
B20: Problemas encontrados | C20: Conclusión | D20: Control de revisión
B22: PANORAMA | N22: Datos de los gráficos (fórmulas a las cédulas)
N23: Cifras del resumen | O23: Importe (USD)
N24: ='01_Resumen'!A5 | O24: ='01_Resumen'!B5
N25: ='01_Resumen'!A6 | O25: ='01_Resumen'!B6
N26: ='01_Resumen'!A7 | O26: ='01_Resumen'!B7
N27: ='01_Resumen'!A8 | O27: ='01_Resumen'!B8
N28: ='01_Resumen'!A9 | O28: ='01_Resumen'!B9
N29: ='01_Resumen'!A10 | O29: ='01_Resumen'!B10
N30: ='01_Resumen'!A11 | O30: ='01_Resumen'!B11
N31: ='01_Resumen'!A12 | O31: ='01_Resumen'!B12
N32: ='01_Resumen'!A13 | O32: ='01_Resumen'!B13
N33: ='01_Resumen'!A14 | O33: ='01_Resumen'!B14
N34: ='01_Resumen'!A15 | O34: ='01_Resumen'!B15
N35: ='01_Resumen'!A16 | O35: ='01_Resumen'!B16
... N43: ='01_Resumen'!A24 | O43: ='01_Resumen'!B24
N45: Hallazgos de mayor impacto | O45: Importe (USD)
N46: Mal clasificado | O46: =SUMIFS('14_Problemas'!$C$5:$C$22,'14_Problemas'!$A$5:$A$22,"MAL_CLASIFICADO",'14_Problemas'!$C$5:$C$22,">0")-SUMIFS('14_Problemas'!$C$5:$C$22,'14_Problemas'!$A$5:$A$22,"MAL_CLASIFICADO",'14_Problemas'!$C$5:$C$22,"<0")
N47: Ajuste | O47: =SUMIFS('14_Problemas'!$C$5:$C$22,'14_Problemas'!$A$5:$A$22,"AJUSTE",'14_Problemas'!$C$5:$C$22,">0")-SUMIFS('14_Problemas'!$C$5:$C$22,'14_Problemas'!$A$5:$A$22,"AJUSTE",'14_Problemas'!$C$5:$C$22,"<0")
N48: Superavit en patrimonio | O48: =SUMIFS('14_Problemas'!$C$5:$C$22,'14_Problemas'!$A$5:$A$22,"SUPERAVIT_EN_PATRIMONIO",'14_Problemas'!$C$5:$C$22,">0")-SUMIFS('14_Problemas'!$C$5:$C$22,'14_Problemas'!$A$5:$A$22,"SUPERAVIT_EN_PATRIMONIO",'14_Problemas'!$C$5:$C$22,"<0")
N49: Transferencia | O49: =SUMIFS('14_Problemas'!$C$5:$C$22,'14_Problemas'!$A$5:$A$22,"TRANSFERENCIA",'14_Problemas'!$C$5:$C$22,">0")-SUMIFS('14_Problemas'!$C$5:$C$22,'14_Problemas'!$A$5:$A$22,"TRANSFERENCIA",'14_Problemas'!$C$5:$C$22,"<0")
N50: Superavit aumento | O50: =SUMIFS('14_Problemas'!$C$5:$C$22,'14_Problemas'!$A$5:$A$22,"SUPERAVIT_AUMENTO",'14_Problemas'!$C$5:$C$22,">0")-SUMIFS('14_Problemas'!$C$5:$C$22,'14_Problemas'!$A$5:$A$22,"SUPERAVIT_AUMENTO",'14_Problemas'!$C$5:$C$22,"<0")
N51: Uso mixto separado | O51: =SUMIFS('14_Problemas'!$C$5:$C$22,'14_Problemas'!$A$5:$A$22,"USO_MIXTO_SEPARADO",'14_Problemas'!$C$5:$C$22,">0")-SUMIFS('14_Problemas'!$C$5:$C$22,'14_Problemas'!$A$5:$A$22,"USO_MIXTO_SEPARADO",'14_Problemas'!$C$5:$C$22,"<0")
N52: Vr no reconocido | O52: =SUMIFS('14_Problemas'!$C$5:$C$22,'14_Problemas'!$A$5:$A$22,"VR_NO_RECONOCIDO",'14_Problemas'!$C$5:$C$22,">0")-SUMIFS('14_Problemas'!$C$5:$C$22,'14_Problemas'!$A$5:$A$22,"VR_NO_RECONOCIDO",'14_Problemas'!$C$5:$C$22,"<0")
N53: Otros (6 tipos) | O53: =SUMIF('14_Problemas'!$C$5:$C$22,">0")-SUMIF('14_Problemas'!$C$5:$C$22,"<0")-((SUMIFS('14_Problemas'!$C$5:$C$22,'14_Problemas'!$A$5:$A$22,"MAL_CLASIFICADO",'14_Problemas'!$C$5:$C$22,">0")-SUMIFS('14_Problemas'!$C$5:$C$22,'14_Problemas'!$A$5:$A$22,"MAL_CLASIFICADO",'14_Problemas'!$C$5:$C$22,"<0"))+(SUMIFS('14_Problemas'!$C$5:$C$22,'14_Problemas'!$A$5:$A$22,"AJUSTE",'14_Problemas'!$C$5:$C$22,">0")-SUMIFS('14_Problemas'!$C$5:$C$22,'14_Problemas'!$A$5:$A$22,"AJUSTE",'14_Problemas'!$C$5:$C$22,"<0"))+(SUMIFS('14_Problemas'!$C$5:$C$22,'14_Problemas'!$A$5:$A$22,"SUPERAVIT_EN_PATRIMONIO",'14_Problemas'!$C$5:$C$22,">0")-SUMIFS('14_Problemas'!$C$5:$C$22,'14_Problemas'!$A$5:$A$22,"SUPERAVIT_EN_PATRIMONIO",'14_Problemas'!$C$5:$C$22,"<0"))+(SUMIFS('14_Problemas'!$C$5:$C$22,'14_Problemas'!$A$5:$A$22,"TRANSFERENCIA",'14_Problemas'!$C$5:$C$22,">0")-SUMIFS('14_Problemas'!$C$5:$C$22,'14_Problemas'!$A$5:$A$22,"TRANSFERENCIA",'14_Problemas'!$C$5:$C$22,"<0"))+(SUMIFS('14_Problemas'!$C$5:$C$22,'14_Problemas'!$A$5:$A$22,"SUPERAVIT_AUMENTO",'14_Problemas'!$C$5:$C$22,">0")-SUMIFS('14_Problemas'!$C$5:$C$22,'14_Problemas'!$A$5:$A$22,"SUPERAVIT_AUMENTO",'14_Problemas'!$C$5:$C$22,"<0"))+(SUMIFS('14_Problemas'!$C$5:$C$22,'14_Problemas'!$A$5:$A$22,"USO_MIXTO_SEPARADO",'14_Problemas'!$C$5:$C$22,">0")-SUMIFS('14_Problemas'!$C$5:$C$22,'14_Problemas'!$A$5:$A$22,"USO_MIXTO_SEPARADO",'14_Problemas'!$C$5:$C$22,"<0"))+(SUMIFS('14_Problemas'!$C$5:$C$22,'14_Problemas'!$A$5:$A$22,"VR_NO_RECONOCIDO",'14_Problemas'!$C$5:$C$22,">0")-SUMIFS('14_Problemas'!$C$5:$C$22,'14_Problemas'!$A$5:$A$22,"VR_NO_RECONOCIDO",'14_Problemas'!$C$5:$C$22,"<0")))

Sheet 00_Caratula
A1: Carátula | H1: ⟵ Inicio | J1: Siguiente ▶
A2: Propiedades de inversión · Cliente de muestra S.A. · corte 2025-12-31
A4: Concepto | B4: Detalle
A5: Firma | B5: AuditConsulting Auditores Cía. Ltda.
A6: Cliente | B6: Cliente de muestra S.A.
A7: RUC | B7: 1790000000001
A8: Ejercicio | B8: 2025
A9: Fecha de corte | B9: 2025-12-31
A10: Marco contable | B10: NIIF completas
A11: Herramienta | B11: Propiedades de inversión
A12: Rubro | B12: Propiedades de inversión
A13: Motor | B13: propiedades_inversion 1.1
A14: Versión del papel | B14: v1
A15: Estado | B15: MUESTRA
... A17: Revisó | B17: Pendiente
A18: Aprobó
A19: Fecha de aprobación
A20: Huella de la ejecución (SHA-256)

Sheet 00_Programa
A1: Programa | H1: ⟵ Inicio | I1: ◀ Anterior | J1: Siguiente ▶
A2: Propiedades de inversión · Cliente de muestra S.A. · corte 2025-12-31
A4: Código | B4: Objetivo | C4: Afirmación | D4: Procedimiento | E4: Evidencia | F4: Criterio | G4: Referencia
A5: IP-01 | B5: Clasificación | C5: Clasificación | D5: Revisar uso real, contratos y ocupación de cada inmueble y aplicar el umbral de uso propio | E5: Contratos, inspección, certificado de uso | F5: Solo inmuebles para rentas o plusvalías | G5: NIC 40.5-14 · PYMES 16.2-16.4
A6: IP-02 | B6: Sumaria y conciliación | C6: Integridad | D6: Conciliar el registro de inmuebles con el mayor | E6: Registro de propiedades, mayor | F6: Diferencia explicada o ajustada | G6: NIA 500
A7: IP-03 | B7: Costo inicial | C7: Valoración | D7: Cotejar precio de escritura y desembolsos directamente atribuibles | E7: Escrituras, facturas de honorarios, impuestos de transferencia | F7: Costo = precio + atribuibles | G7: NIC 40.20-24 · PYMES 16.5
A8: IP-04 | B8: Valor razonable | C8: Valoración | D8: Comparar el VR de la tasación con el importe en libros y evaluar al tasador | E8: Informes de tasación, NIA 620 | F8: Ajuste de VR en resultados | G8: NIC 40.33-55 · NIIF 13 · PYMES 16.7 (2025: secc. 12)
A9: IP-05 | B9: Modelo del costo | C9: Valoración | D9: Recalcular depreciación y comparar el valor neto con el importe recuperable | E9: Vidas útiles, tasaciones, flujos | F9: Depreciación y deterioro correctos; VR revelado | G9: NIC 40.56, 79 e · NIC 16 · NIC 36 · PYMES 16.8, secc. 17 y 27
A10: IP-06 | B10: Ingresos por alquiler | C10: Ocurrencia / Integridad | D10: Recalcular las rentas del año con los contratos y compararlas con lo registrado | E10: Contratos de arrendamiento, facturas | F10: Ingresos conciliados | G10: NIC 40.75 f · NIIF 16
A11: IP-07 | B11: Transferencias | C11: Clasificación / Valoración | D11: Verificar evidencia del cambio de uso y la medición a la fecha | E11: Actas, contratos, tasación a la fecha del cambio | F11: Tratamiento según NIC 40.57-65 | G11: NIC 40.57-65 · PYMES 16.8-16.9
A12: IP-09 | B12: Superávit de revaluación | C12: Presentación / Valoración | D12: Cotejar el superávit acumulado de cada inmueble transferido con el auxiliar de la cuenta y el estado de cambios en el patrimonio; recalcular el aumento a otro resultado integral, el uso contra la disminución y el saldo final | E12: Auxiliar del superávit de revaluación por inmueble, estado de cambios en el patrimonio, auxiliar de deterioros | F12: Aumento a otro resultado integral; disminución contra el superávit de ese inmueble y el exceso a resultados; el superávit permanece en patrimonio y solo se transfiere a resultados acumulados | G12: NIC 40.61-62 · NIC 16.39-41 · PYMES 17.15C-17.15D
A13: IP-08 | B13: Bajas | C13: Exactitud | D13: Recalcular producto neto − importe en libros | E13: Escrituras de venta, cobros | F13: Resultado correcto | G13: NIC 40.66-73

Sheet 00_Fuentes
A1: Base técnica | H1: ⟵ Inicio | I1: ◀ Anterior | J1: Siguiente ▶
A2: Propiedades de inversión · Cliente de muestra S.A. · corte 2025-12-31
A4: Categoría | B4: Documento | C4: Párrafos | D4: URL | E4: Verificada
A5: NIA · NIA 540 (Revisada) | B5: El VR, la vida útil y el importe recuperable son estimaciones: evaluar método, datos y supuestos. | C5: párr. 13, 18, 22-27 y 28-29
A6: NIA · NIA 500 / NIA 620 | B6: Evaluar competencia, objetividad y trabajo del tasador cuando el VR se basa en un experto. | C6: NIA 500.8 (tasador de la entidad = experto de la dirección); NIA 620.9-12 solo si el auditor contrata su propio tasador
A7: NIA · NIA 500 | B7: Fiabilidad del registro de inmuebles, escrituras y contratos. | C7: párr. 7 y 9
A8: NIA · NIA 500 / NIA 330 | B8: Existencia y titularidad: inspección y certificados del Registro de la Propiedad. | C8: NIA 500 párr. A18-A20 (inspección; titularidad con certificados) · NIA 330 párr. 18
A9: NIA · NIA 520 | B9: Analítica de ingresos por alquiler frente a contratos y ocupación. | C9: párr. 5

Sheet 01_Resumen
A1: Resumen y ajuste propuesto | H1: ⟵ Inicio | I1: ◀ Anterior | J1: Siguiente ▶
A2: Propiedades de inversión · Cliente de muestra S.A. · corte 2025-12-31
A4: Concepto | B4: Importe
A5: Propiedades de inversión auditadas | B5: =SUM('08_Medicion'!$E$5:$E$14)
A6: Saldo según el mayor | B6: =IF('02_Parametros'!$B$13="",SUM('03_Inmuebles'!$Q$5:$Q$14),'02_Parametros'!$B$13)
A7: Ajuste propuesto (neto) | B7: =B5-B6
A8: Importe en libros según el detalle | B8: =SUM('03_Inmuebles'!$Q$5:$Q$14)
A9: Diferencia detalle − mayor | B9: =B8-B6
A10: Ajuste de valor razonable no reconocido (resultados) | B10: =SUM('06_Valor_razonable'!$H$5:$H$14)
A11: Efecto de la medición al costo (depreciación y deterioro) | B11: =SUM('08_Medicion'!$H$5:$H$14)
A12: Reclasificación fuera de propiedades de inversión | B12: =SUM('04_Clasificacion'!$J$5:$J$14)
A13: Depreciación del año (modelo del costo) | B13: =SUM('07_Modelo_costo'!$K$5:$K$14)
A14: Diferencia de depreciación acumulada | B14: =SUM('07_Modelo_costo'!$M$5:$M$14)
A15: Deterioro (modelo del costo) | B15: =SUM('07_Modelo_costo'!$P$5:$P$14)
A16: Variación del valor razonable del año | B16: =SUM('06_Valor_razonable'!$F$5:$F$14)
A17: Diferencia en el costo inicial | B17: =SUM('05_Costo_inicial'!$G$5:$G$14)
A18: Transferencias: diferencia a resultados | B18: =SUM('09_Transferencias'!$K$5:$K$6)
A19: Transferencias: diferencia a otro resultado integral | B19: =SUM('09_Transferencias'!$L$5:$L$6)
A20: Superávit de revaluación usado contra disminuciones | B20: =SUM('09_Transferencias'!$J$5:$J$6)
A21: Superávit de revaluación en patrimonio al cierre | B21: =SUM('10_Superavit'!$G$5:$G$5)
A22: Diferencia en ingresos por alquiler | B22: =SUM('11_Alquileres'!$E$5:$E$14)
A23: Resultado recalculado en bajas | B23: =SUM('12_Bajas'!$F$5:$F$6)
A24: Diferencia en el resultado de bajas | B24: =SUM('12_Bajas'!$H$5:$H$6)
A26: ⓘ Cómo se calcula esta hoja
A27: Columna | B27: Fórmula (Excel) | C27: Cómo se calcula (sencillo) | D27: Ejemplo con números reales | E27: De dónde viene | F27: Norma
A28: Importe | B28: '=SUM('08_Medicion'!$E$5:$E$14) | C28: Trae cada importe de su hoja de origen, concepto por concepto, sumando la columna que corresponde de las hojas 03 a 12 (por ejemplo, la medición auditada de la hoja 08 o la depreciación de la hoja 07). El saldo del mayor sale de la hoja 02 (Parámetros) o, si no se informó, de la suma del detalle; el ajuste propuesto es auditado menos mayor. | D28: Fila 1: SUM([«Auditado en la cuenta» de «Medición auditada por inmueble», 10 filas]) → 2.586.500,00 | E28: hoja «Medición auditada por inmueble» | F28: —

Sheet 02_Parametros
A1: Parámetros y ruta por marco | H1: ⟵ Inicio | I1: ◀ Anterior | J1: Siguiente ▶
A2: Propiedades de inversión · Cliente de muestra S.A. · corte 2025-12-31
A4: Parámetro | B4: Valor | C4: Sustento
A5: Corte del ejercicio | B5: 46022 | C5: Ficha del encargo
A6: Inicio del ejercicio | B6: 45658 | C6: Corte − 12 meses + 1 día
A7: Marco | B7: NIIF completas | C7: NIIF completas · NIC 40 y NIIF 13
A8: ¿Es PYMES? | B8: =IF(ISNUMBER(SEARCH("PYMES",'02_Parametros'!$B$7)),"Sí","No") | C8: Deriva del marco
A9: Modelo aplicado por la entidad | B9: valor_razonable | C9: NIC 40.30 (elección); PYMES 16.7 (no es elección: depende de la medición fiable sin costo o esfuerzo desproporcionado)
A10: PYMES: VR fiable sin costo o esfuerzo desproporcionado | B10: sí | C10: Juicio documentado (PYMES 16.7-16.8); sin efecto en NIIF completas
A11: Modelo con que se mide (ruta) | B11: =IF('02_Parametros'!$B$8="Sí",IF('02_Parametros'!$B$10="sí","valor_razonable","costo"),'02_Parametros'!$B$9) | C11: Completas: el elegido por la entidad; PYMES: VR solo si es fiable sin esfuerzo desproporcionado
A12: Uso propio significativo desde (%) | B12: 10 | C12: NIC 40.10 exige que la parte de uso propio sea «insignificante»; el umbral es juicio del auditor (NIC 40.10 no fija porcentaje); solo NIIF completas — en PYMES 16.4 se separan las partes
A13: Saldo según el mayor | B13: 2785000 | C13: Mayor contable (en blanco: se toma la suma del detalle)
A15: ⓘ Cómo se calcula esta hoja
A16: Columna | B16: Fórmula (Excel) | C16: Cómo se calcula (sencillo) | D16: Ejemplo con números reales | E16: De dónde viene | F16: Norma
A17: Valor | B17: '=IF(ISNUMBER(SEARCH("PYMES",'02_Parametros'!$B$7)),"Sí","No") | C17: Muestra cada parámetro del encargo tal como se fijó; solo dos se calculan: «¿Es PYMES?» sale del marco, y el modelo con que se mide es el elegido por la entidad en NIIF completas y, en PYMES, valor razonable solo si es fiable sin costo o esfuerzo desproporcionado (si no, costo). | D17: Fila 4: IF(ISNUMBER(SEARCH("PYMES"; «NIIF completas»)); "Sí"; "No") → No | E17: hoja «Parámetros y ruta por marco» | F17: —

Sheet 03_Inmuebles
A1: Registro de inmuebles | H1: ⟵ Inicio | I1: ◀ Anterior | J1: Siguiente ▶
A2: Propiedades de inversión · Cliente de muestra S.A. · corte 2025-12-31
A4: Código | B4: Descripción | C4: Uso actual | D4: % uso propio | E4: Separable | F4: Costo registrado | G4: Fecha de adquisición | H4: Precio de compra | I4: Desembolsos atribuibles | J4: Terreno | K4: Vida útil (años) | L4: Dep. acumulada registrada | M4: VR año anterior | N4: VR al corte | O4: Fuente del VR | P4: Nivel VR | Q4: Importe en libros | R4: Alquiler según contratos | S4: Alquiler registrado | T4: Cambio de uso | U4: Fecha del cambio | V4: Libros al cambio | W4: VR al cambio | X4: Superávit de revaluación a esa fecha | Y4: Importe recuperable
A5: IP-01 | B5: Edificio de oficinas Norte | C5: Alquiler | D5: 0 | F5: 500000 | G5: 43160 | J5: 100000 | K5: 40 | M5: 700000 | N5: 720000 | O5: Perito independiente (tasación dic-2025) | P5: Nivel 2 | Q5: 700000 | R5: 48000 | S5: 48000
A6: IP-02 | B6: Terreno Samborondón | C6: Plusvalía | F6: 300000 | J6: 300000 | M6: 350000 | N6: 380000 | O6: Perito independiente | P6: Nivel 2 | Q6: 380000
A7: IP-03 | B7: Local comercial Sur | C7: Alquiler | F7: 250000 | G7: 44012 | J7: 50000 | K7: 30 | M7: 260000 | N7: 240000 | O7: Perito independiente | P7: Nivel 3 | Q7: 260000 | R7: 24000 | S7: 22000
A8: IP-04 | B8: Bodega Durán (35 % uso propio) | C8: Alquiler | D8: 35 | E8: Sí | F8: 180000 | G8: 43830 | J8: 30000 | K8: 30 | N8: 210000 | O8: Perito independiente | P8: Nivel 3 | Q8: 190000 | R8: 9000 | S8: 9000
A9: IP-05 | B9: Departamentos para la venta | C9: Venta | F9: 150000 | Q9: 150000
A10: IP-06 | B10: Edificio Centro (compra 2025) | C10: Alquiler | F10: 400000 | G10: 45839 | H10: 400000 | I10: 12000 | J10: 80000 | K10: 40 | N10: 425000 | O10: Tasación interna | P10: Nivel 3 | Q10: 400000 | R10: 18000 | S10: 12000
A11: IP-07 | B11: Edificio zona sin mercado activo | C11: Uso futuro no determinado | F11: 300000 | G11: 42369 | J11: 60000 | K11: 50 | L11: 45000 | Q11: 255000 | Y11: 230000
A12: IP-08 | B12: Oficina ex uso propio | C12: Alquiler | F12: 160000 | G12: 42005 | J12: 40000 | K12: 40 | L12: 33000 | N12: 210000 | O12: Perito independiente | P12: Nivel 2 | Q12: 205000 | R12: 6000 | S12: 6000 | T12: PPE→PI | U12: 45930 | V12: 125000 | W12: 205000 | X12: 30000
A13: IP-09 | B13: Casa arrendada (ex inventario) | C13: Alquiler | F13: 70000 | G13: 43830 | J13: 10000 | K13: 30 | M13: 90000 | N13: 95000 | Q13: 90000 | S13: 7000 | T13: Inventario→PI | U13: 45792
A14: IP-10 | B14: Galpón industrial arrendado | C14: Alquiler | D14: 5 | F14: 120000 | G14: 43100 | J14: 20000 | K14: 25 | M14: 150000 | N14: 150000 | O14: Perito independiente | P14: Nivel 2 | Q14: 150000 | R14: 12000 | S14: 12000
A15: TOTAL | F15: =SUM(F5:F14) | Q15: =SUM(Q5:Q14)

Sheet 04_Clasificacion
A1: Clasificación | H1: ⟵ Inicio | I1: ◀ Anterior | J1: Siguiente ▶
A2: Propiedades de inversión · Cliente de muestra S.A. · corte 2025-12-31
A4: Código | B4: Descripción | C4: Uso actual | D4: % uso propio | E4: Separable | F4: Umbral (%) | G4: Clasificación auditada | H4: ¿Propiedad de inversión? | I4: Importe en libros | J4: Reclasificación | K4: Parte que es propiedad de inversión
A5: IP-01 | B5: Edificio de oficinas Norte | C5: ='03_Inmuebles'!C5 | D5: =IF('03_Inmuebles'!D5="","",'03_Inmuebles'!D5) | E5: =IF('03_Inmuebles'!E5="","",'03_Inmuebles'!E5) | F5: ='02_Parametros'!$B$12 | G5: =IF(C5="Venta",IF('02_Parametros'!$B$8="Sí","Inventario (sección 13)","Inventario (NIC 2)"),IF(C5="Uso propio","PPE (uso propio)",IF(AND('02_Parametros'!$B$8="Sí",AND(D5<>"",D5>0,D5<100)),IF('02_Parametros'!$B$10="no","PPE (uso mixto sin VR fiable: sección 17)","Propiedad de inversión (parte)"),IF(AND('02_Parametros'!$B$8="No",AND(D5<>"",D5>0,D5<100),E5="Sí"),"Propiedad de inversión (parte)",IF(AND(D5<>"",D5>F5),"PPE (uso propio significativo)","Propiedad de inversión"))))) | H5: =IF(K5>0,"Sí","No") | I5: ='03_Inmuebles'!Q5 | J5: =IF(K5=1,"",-I5*(1-K5)) | K5: =IF(G5="Propiedad de inversión",1,IF(G5="Propiedad de inversión (parte)",1-D5/100,0))
A6: IP-02 | B6: Terreno Samborondón | C6: ='03_Inmuebles'!C6 | D6: =IF('03_Inmuebles'!D6="","",'03_Inmuebles'!D6) | E6: =IF('03_Inmuebles'!E6="","",'03_Inmuebles'!E6) | F6: ='02_Parametros'!$B$12 | G6: =IF(C6="Venta",IF('02_Parametros'!$B$8="Sí","Inventario (sección 13)","Inventario (NIC 2)"),IF(C6="Uso propio","PPE (uso propio)",IF(AND('02_Parametros'!$B$8="Sí",AND(D6<>"",D6>0,D6<100)),IF('02_Parametros'!$B$10="no","PPE (uso mixto sin VR fiable: sección 17)","Propiedad de inversión (parte)"),IF(AND('02_Parametros'!$B$8="No",AND(D6<>"",D6>0,D6<100),E6="Sí"),"Propiedad de inversión (parte)",IF(AND(D6<>"",D6>F6),"PPE (uso propio significativo)","Propiedad de inversión"))))) | H6: =IF(K6>0,"Sí","No") | I6: ='03_Inmuebles'!Q6 | J6: =IF(K6=1,"",-I6*(1-K6)) | K6: =IF(G6="Propiedad de inversión",1,IF(G6="Propiedad de inversión (parte)",1-D6/100,0))
A7: IP-03 | B7: Local comercial Sur | C7: ='03_Inmuebles'!C7 | D7: =IF('03_Inmuebles'!D7="","",'03_Inmuebles'!D7) | E7: =IF('03_Inmuebles'!E7="","",'03_Inmuebles'!E7) | F7: ='02_Parametros'!$B$12 | G7: =IF(C7="Venta",IF('02_Parametros'!$B$8="Sí","Inventario (sección 13)","Inventario (NIC 2)"),IF(C7="Uso propio","PPE (uso propio)",IF(AND('02_Parametros'!$B$8="Sí",AND(D7<>"",D7>0,D7<100)),IF('02_Parametros'!$B$10="no","PPE (uso mixto sin VR fiable: sección 17)","Propiedad de inversión (parte)"),IF(AND('02_Parametros'!$B$8="No",AND(D7<>"",D7>0,D7<100),E7="Sí"),"Propiedad de inversión (parte)",IF(AND(D7<>"",D7>F7),"PPE (uso propio significativo)","Propiedad de inversión"))))) | H7: =IF(K7>0,"Sí","No") | I7: ='03_Inmuebles'!Q7 | J7: =IF(K7=1,"",-I7*(1-K7)) | K7: =IF(G7="Propiedad de inversión",1,IF(G7="Propiedad de inversión (parte)",1-D7/100,0))
A8: IP-04 | B8: Bodega Durán (35 % uso propio) | C8: ='03_Inmuebles'!C8 | D8: =IF('03_Inmuebles'!D8="","",'03_Inmuebles'!D8) | E8: =IF('03_Inmuebles'!E8="","",'03_Inmuebles'!E8) | F8: ='02_Parametros'!$B$12 | G8: =IF(C8="Venta",IF('02_Parametros'!$B$8="Sí","Inventario (sección 13)","Inventario (NIC 2)"),IF(C8="Uso propio","PPE (uso propio)",IF(AND('02_Parametros'!$B$8="Sí",AND(D8<>"",D8>0,D8<100)),IF('02_Parametros'!$B$10="no","PPE (uso mixto sin VR fiable: sección 17)","Propiedad de inversión (parte)"),IF(AND('02_Parametros'!$B$8="No",AND(D8<>"",D8>0,D8<100),E8="Sí"),"Propiedad de inversión (parte)",IF(AND(D8<>"",D8>F8),"PPE (uso propio significativo)","Propiedad de inversión"))))) | H8: =IF(K8>0,"Sí","No") | I8: ='03_Inmuebles'!Q8 | J8: =IF(K8=1,"",-I8*(1-K8)) | K8: =IF(G8="Propiedad de inversión",1,IF(G8="Propiedad de inversión (parte)",1-D8/100,0))
A9: IP-05 | B9: Departamentos para la venta | C9: ='03_Inmuebles'!C9 | D9: =IF('03_Inmuebles'!D9="","",'03_Inmuebles'!D9) | E9: =IF('03_Inmuebles'!E9="","",'03_Inmuebles'!E9) | F9: ='02_Parametros'!$B$12 | G9: =IF(C9="Venta",IF('02_Parametros'!$B$8="Sí","Inventario (sección 13)","Inventario (NIC 2)"),IF(C9="Uso propio","PPE (uso propio)",IF(AND('02_Parametros'!$B$8="Sí",AND(D9<>"",D9>0,D9<100)),IF('02_Parametros'!$B$10="no","PPE (uso mixto sin VR fiable: sección 17)","Propiedad de inversión (parte)"),IF(AND('02_Parametros'!$B$8="No",AND(D9<>"",D9>0,D9<100),E9="Sí"),"Propiedad de inversión (parte)",IF(AND(D9<>"",D9>F9),"PPE (uso propio significativo)","Propiedad de inversión"))))) | H9: =IF(K9>0,"Sí","No") | I9: ='03_Inmuebles'!Q9 | J9: =IF(K9=1,"",-I9*(1-K9)) | K9: =IF(G9="Propiedad de inversión",1,IF(G9="Propiedad de inversión (parte)",1-D9/100,0))
A10: IP-06 | B10: Edificio Centro (compra 2025) | C10: ='03_Inmuebles'!C10 | D10: =IF('03_Inmuebles'!D10="","",'03_Inmuebles'!D10) | E10: =IF('03_Inmuebles'!E10="","",'03_Inmuebles'!E10) | F10: ='02_Parametros'!$B$12 | G10: =IF(C10="Venta",IF('02_Parametros'!$B$8="Sí","Inventario (sección 13)","Inventario (NIC 2)"),IF(C10="Uso propio","PPE (uso propio)",IF(AND('02_Parametros'!$B$8="Sí",AND(D10<>"",D10>0,D10<100)),IF('02_Parametros'!$B$10="no","PPE (uso mixto sin VR fiable: sección 17)","Propiedad de inversión (parte)"),IF(AND('02_Parametros'!$B$8="No",AND(D10<>"",D10>0,D10<100),E10="Sí"),"Propiedad de inversión (parte)",IF(AND(D10<>"",D10>F10),"PPE (uso propio significativo)","Propiedad de inversión"))))) | H10: =IF(K10>0,"Sí","No") | I10: ='03_Inmuebles'!Q10 | J10: =IF(K10=1,"",-I10*(1-K10)) | K10: =IF(G10="Propiedad de inversión",1,IF(G10="Propiedad de inversión (parte)",1-D10/100,0))
A11: IP-07 | B11: Edificio zona sin mercado activo | C11: ='03_Inmuebles'!C11 | D11: =IF('03_Inmuebles'!D11="","",'03_Inmuebles'!D11) | E11: =IF('03_Inmuebles'!E11="","",'03_Inmuebles'!E11) | F11: ='02_Parametros'!$B$12 | G11: =IF(C11="Venta",IF('02_Parametros'!$B$8="Sí","Inventario (sección 13)","Inventario (NIC 2)"),IF(C11="Uso propio","PPE (uso propio)",IF(AND('02_Parametros'!$B$8="Sí",AND(D11<>"",D11>0,D11<100)),IF('02_Parametros'!$B$10="no","PPE (uso mixto sin VR fiable: sección 17)","Propiedad de inversión (parte)"),IF(AND('02_Parametros'!$B$8="No",AND(D11<>"",D11>0,D11<100),E11="Sí"),"Propiedad de inversión (parte)",IF(AND(D11<>"",D11>F11),"PPE (uso propio significativo)","Propiedad de inversión"))))) | H11: =IF(K11>0,"Sí","No") | I11: ='03_Inmuebles'!Q11 | J11: =IF(K11=1,"",-I11*(1-K11)) | K11: =IF(G11="Propiedad de inversión",1,IF(G11="Propiedad de inversión (parte)",1-D11/100,0))
A12: IP-08 | B12: Oficina ex uso propio | C12: ='03_Inmuebles'!C12 | D12: =IF('03_Inmuebles'!D12="","",'03_Inmuebles'!D12) | E12: =IF('03_Inmuebles'!E12="","",'03_Inmuebles'!E12) | F12: ='02_Parametros'!$B$12 | G12: =IF(C12="Venta",IF('02_Parametros'!$B$8="Sí","Inventario (sección 13)","Inventario (NIC 2)"),IF(C12="Uso propio","PPE (uso propio)",IF(AND('02_Parametros'!$B$8="Sí",AND(D12<>"",D12>0,D12<100)),IF('02_Parametros'!$B$10="no","PPE (uso mixto sin VR fiable: sección 17)","Propiedad de inversión (parte)"),IF(AND('02_Parametros'!$B$8="No",AND(D12<>"",D12>0,D12<100),E12="Sí"),"Propiedad de inversión (parte)",IF(AND(D12<>"",D12>F12),"PPE (uso propio significativo)","Propiedad de inversión"))))) | H12: =IF(K12>0,"Sí","No") | I12: ='03_Inmuebles'!Q12 | J12: =IF(K12=1,"",-I12*(1-K12)) | K12: =IF(G12="Propiedad de inversión",1,IF(G12="Propiedad de inversión (parte)",1-D12/100,0))
A13: IP-09 | B13: Casa arrendada (ex inventario) | C13: ='03_Inmuebles'!C13 | D13: =IF('03_Inmuebles'!D13="","",'03_Inmuebles'!D13) | E13: =IF('03_Inmuebles'!E13="","",'03_Inmuebles'!E13) | F13: ='02_Parametros'!$B$12 | G13: =IF(C13="Venta",IF('02_Parametros'!$B$8="Sí","Inventario (sección 13)","Inventario (NIC 2)"),IF(C13="Uso propio","PPE (uso propio)",IF(AND('02_Parametros'!$B$8="Sí",AND(D13<>"",D13>0,D13<100)),IF('02_Parametros'!$B$10="no","PPE (uso mixto sin VR fiable: sección 17)","Propiedad de inversión (parte)"),IF(AND('02_Parametros'!$B$8="No",AND(D13<>"",D13>0,D13<100),E13="Sí"),"Propiedad de inversión (parte)",IF(AND(D13<>"",D13>F13),"PPE (uso propio significativo)","Propiedad de inversión"))))) | H13: =IF(K13>0,"Sí","No") | I13: ='03_Inmuebles'!Q13 | J13: =IF(K13=1,"",-I13*(1-K13)) | K13: =IF(G13="Propiedad de inversión",1,IF(G13="Propiedad de inversión (parte)",1-D13/100,0))
A14: IP-10 | B14: Galpón industrial arrendado | C14: ='03_Inmuebles'!C14 | D14: =IF('03_Inmuebles'!D14="","",'03_Inmuebles'!D14) | E14: =IF('03_Inmuebles'!E14="","",'03_Inmuebles'!E14) | F14: ='02_Parametros'!$B$12 | G14: =IF(C14="Venta",IF('02_Parametros'!$B$8="Sí","Inventario (sección 13)","Inventario (NIC 2)"),IF(C14="Uso propio","PPE (uso propio)",IF(AND('02_Parametros'!$B$8="Sí",AND(D14<>"",D14>0,D14<100)),IF('02_Parametros'!$B$10="no","PPE (uso mixto sin VR fiable: sección 17)","Propiedad de inversión (parte)"),IF(AND('02_Parametros'!$B$8="No",AND(D14<>"",D14>0,D14<100),E14="Sí"),"Propiedad de inversión (parte)",IF(AND(D14<>"",D14>F14),"PPE (uso propio significativo)","Propiedad de inversión"))))) | H14: =IF(K14>0,"Sí","No") | I14: ='03_Inmuebles'!Q14 | J14: =IF(K14=1,"",-I14*(1-K14)) | K14: =IF(G14="Propiedad de inversión",1,IF(G14="Propiedad de inversión (parte)",1-D14/100,0))
A15: TOTAL | I15: =SUM(I5:I14) | J15: =SUM(J5:J14)
A17: ⓘ Cómo se calcula esta hoja
A18: Columna | B18: Fórmula (Excel) | C18: Cómo se calcula (sencillo) | D18: Ejemplo con números reales | E18: De dónde viene | F18: Norma
A19: Uso actual | B19: '='03_Inmuebles'!C5 | C19: Trae el uso actual del inmueble declarado por el cliente en la hoja 03 (Registro de inmuebles): alquiler, plusvalía, uso propio, venta, uso futuro no determinado o en construcción. | D19: Fila 1: «Alquiler» → Alquiler | E19: hoja «Registro de inmuebles» | F19: —
A20: % uso propio | B20: '=IF('03_Inmuebles'!D5="","",'03_Inmuebles'!D5) | C20: Trae de la hoja 03 (Registro de inmuebles) el porcentaje del inmueble que la entidad ocupa para sí misma; si el cliente no lo informó, queda en blanco. | D20: Fila 1: IF(0,00=""; ""; 0,00) → 0,00 | E20: hoja «Registro de inmuebles» | F20: —
A21: Separable | B21: '=IF('03_Inmuebles'!E5="","",'03_Inmuebles'!E5) | C21: Trae de la hoja 03 (Registro de inmuebles) si las partes del inmueble pueden venderse por separado (Sí/No); queda en blanco si no se informó. | D21: Fila 1: IF((vacío)=""; ""; (vacío)) → (en blanco) | E21: hoja «Registro de inmuebles» | F21: —
A22: Umbral (%) | B22: '='02_Parametros'!$B$12 | C22: Repite en cada fila el porcentaje de uso propio desde el cual el auditor lo considera significativo, fijado en la hoja 02 (Parámetros). | D22: Fila 1: 10,00 → 10,00 | E22: hoja «Parámetros y ruta por marco» | F22: —
A23: Clasificación auditada | B23: '=IF(C5="Venta",IF('02_Parametros'!$B$8="Sí","Inventario (sección 13)","Inventario (NIC 2)"),IF(C5="Uso propio","PPE (uso propio)",IF(AND('02_Parametros'!$B$8="Sí",AND(D5<>"",D5>0,D5<100)),IF('02_Parametros'!$B$10="no","PPE (uso mixto sin VR fiable: sección 17)","Propiedad de inversión (parte)"),IF(AND('02_Parametros'!$B$8="No",AND(D5<>"",D5>0,D5<100),E5="Sí"),"Propiedad de inversión (parte)",IF(AND(D5<>"",D5>F5),"PPE (uso propio significativo)","Propiedad de inversión"))))) | C23: Si el inmueble es para la venta va a inventario y si es de uso propio a PPE. Con uso mixto (uso propio entre 0 % y 100 %) en PYMES se separa la parte de inversión, salvo que el VR no sea fiable según la hoja 02 (entonces todo va a PPE), y en NIIF completas solo se separa si las partes son vendibles por separado; si el uso propio supera el umbral va a PPE y, en los demás casos, es propiedad de inversión. | D23: Fila 1: IF(«Alquiler»="Venta"; IF(«No»="Sí"; "Inventario (sección 13)"; "Inventario (NIC 2)"); IF(«Alquiler»="Uso propio"; "PPE (uso propio)"; IF(AND(«No»="Sí"; AND(0,00<>""; 0,00>0; 0,00<100)); IF(«sí»="no"; "PPE (uso mixto sin VR fiable: sección 17)"; "Propiedad de inversión (parte)"); IF(AND(«No»="No"; AND(0,00<>""; 0,00>0; 0,00<100); (vacío)="Sí"); "Propiedad de inversión (parte)"; IF(AND(0,00<>""; 0,00>10,00); "PPE (uso propio significativo)"; "Propiedad de inversión"))))) → Propiedad de inversión | E23: «Uso actual» (esta hoja), «% uso propio» (esta hoja), «Separable» (esta hoja), «Umbral (%)» (esta hoja), hoja «Parámetros y ruta por marco» | F23: —
A24: ¿Propiedad de inversión? | B24: '=IF(K5>0,"Sí","No") | C24: Marca «Sí» cuando la parte que es propiedad de inversión (última columna de esta hoja) es mayor que cero, y «No» en caso contrario. | D24: Fila 1: IF(100,00 %>0; "Sí"; "No") → Sí | E24: «Parte que es propiedad de inversión» (esta hoja) | F24: —
A25: Importe en libros | B25: '='03_Inmuebles'!Q5 | C25: Trae de la hoja 03 (Registro de inmuebles) el importe en libros que el cliente tiene registrado al corte para este inmueble. | D25: Fila 1: 700.000,00 → 700.000,00 | E25: hoja «Registro de inmuebles» | F25: —
A26: Reclasificación | B26: '=IF(K5=1,"",-I5*(1-K5)) | C26: Si el inmueble no es propiedad de inversión en su totalidad, calcula con signo negativo la parte del importe en libros que debe salir de la cuenta: importe en libros × (1 − parte que es PI). Si todo es PI, queda en blanco. | D26: Fila 1: IF(100,00 %=1; ""; -700.000,00*(1-100,00 %)) → (en blanco) | E26: «Parte que es propiedad de inversión» (esta hoja), «Importe en libros» (esta hoja) | F26: —
A27: Parte que es propiedad de inversión | B27: '=IF(G5="Propiedad de inversión",1,IF(G5="Propiedad de inversión (parte)",1-D5/100,0)) | C27: Es 100 % si la clasificación auditada es propiedad de inversión, 100 % menos el porcentaje de uso propio si solo una parte lo es, y 0 % en cualquier otra clasificación. | D27: Fila 1: IF(«Propiedad de inversión»="Propiedad de inversión"; 1; IF(«Propiedad de inversión»="Propiedad de inversión (parte)"; 1-0,00/100; 0)) → 100,00 % | E27: «Clasificación auditada» (esta hoja), «% uso propio» (esta hoja) | F27: —

Sheet 05_Costo_inicial
A1: Costo inicial | H1: ⟵ Inicio | I1: ◀ Anterior | J1: Siguiente ▶
A2: Propiedades de inversión · Cliente de muestra S.A. · corte 2025-12-31
A4: Código | B4: Fecha de adquisición | C4: Precio de compra | D4: Desembolsos atribuibles | E4: Costo recalculado | F4: Costo registrado | G4: Diferencia | H4: Costo auditado
A5: IP-01 | B5: 43160 | C5: =IF('03_Inmuebles'!H5="","",'03_Inmuebles'!H5) | D5: =IF('03_Inmuebles'!I5="","",'03_Inmuebles'!I5) | E5: =IF(C5="","",C5+IF(D5="",0,D5)) | F5: ='03_Inmuebles'!F5 | G5: =IF(E5="","",E5-F5) | H5: =IF(E5<>"",E5,F5)
A6: IP-02 | C6: =IF('03_Inmuebles'!H6="","",'03_Inmuebles'!H6) | D6: =IF('03_Inmuebles'!I6="","",'03_Inmuebles'!I6) | E6: =IF(C6="","",C6+IF(D6="",0,D6)) | F6: ='03_Inmuebles'!F6 | G6: =IF(E6="","",E6-F6) | H6: =IF(E6<>"",E6,F6)
A7: IP-03 | B7: 44012 | C7: =IF('03_Inmuebles'!H7="","",'03_Inmuebles'!H7) | D7: =IF('03_Inmuebles'!I7="","",'03_Inmuebles'!I7) | E7: =IF(C7="","",C7+IF(D7="",0,D7)) | F7: ='03_Inmuebles'!F7 | G7: =IF(E7="","",E7-F7) | H7: =IF(E7<>"",E7,F7)
A8: IP-04 | B8: 43830 | C8: =IF('03_Inmuebles'!H8="","",'03_Inmuebles'!H8) | D8: =IF('03_Inmuebles'!I8="","",'03_Inmuebles'!I8) | E8: =IF(C8="","",C8+IF(D8="",0,D8)) | F8: ='03_Inmuebles'!F8 | G8: =IF(E8="","",E8-F8) | H8: =IF(E8<>"",E8,F8)
A9: IP-05 | C9: =IF('03_Inmuebles'!H9="","",'03_Inmuebles'!H9) | D9: =IF('03_Inmuebles'!I9="","",'03_Inmuebles'!I9) | E9: =IF(C9="","",C9+IF(D9="",0,D9)) | F9: ='03_Inmuebles'!F9 | G9: =IF(E9="","",E9-F9) | H9: =IF(E9<>"",E9,F9)
A10: IP-06 | B10: 45839 | C10: =IF('03_Inmuebles'!H10="","",'03_Inmuebles'!H10) | D10: =IF('03_Inmuebles'!I10="","",'03_Inmuebles'!I10) | E10: =IF(C10="","",C10+IF(D10="",0,D10)) | F10: ='03_Inmuebles'!F10 | G10: =IF(E10="","",E10-F10) | H10: =IF(E10<>"",E10,F10)
A11: IP-07 | B11: 42369 | C11: =IF('03_Inmuebles'!H11="","",'03_Inmuebles'!H11) | D11: =IF('03_Inmuebles'!I11="","",'03_Inmuebles'!I11) | E11: =IF(C11="","",C11+IF(D11="",0,D11)) | F11: ='03_Inmuebles'!F11 | G11: =IF(E11="","",E11-F11) | H11: =IF(E11<>"",E11,F11)
A12: IP-08 | B12: 42005 | C12: =IF('03_Inmuebles'!H12="","",'03_Inmuebles'!H12) | D12: =IF('03_Inmuebles'!I12="","",'03_Inmuebles'!I12) | E12: =IF(C12="","",C12+IF(D12="",0,D12)) | F12: ='03_Inmuebles'!F12 | G12: =IF(E12="","",E12-F12) | H12: =IF(E12<>"",E12,F12)
A13: IP-09 | B13: 43830 | C13: =IF('03_Inmuebles'!H13="","",'03_Inmuebles'!H13) | D13: =IF('03_Inmuebles'!I13="","",'03_Inmuebles'!I13) | E13: =IF(C13="","",C13+IF(D13="",0,D13)) | F13: ='03_Inmuebles'!F13 | G13: =IF(E13="","",E13-F13) | H13: =IF(E13<>"",E13,F13)
A14: IP-10 | B14: 43100 | C14: =IF('03_Inmuebles'!H14="","",'03_Inmuebles'!H14) | D14: =IF('03_Inmuebles'!I14="","",'03_Inmuebles'!I14) | E14: =IF(C14="","",C14+IF(D14="",0,D14)) | F14: ='03_Inmuebles'!F14 | G14: =IF(E14="","",E14-F14) | H14: =IF(E14<>"",E14,F14)
A15: TOTAL | F15: =SUM(F5:F14) | G15: =SUM(G5:G14) | H15: =SUM(H5:H14)
A17: ⓘ Cómo se calcula esta hoja
A18: Columna | B18: Fórmula (Excel) | C18: Cómo se calcula (sencillo) | D18: Ejemplo con números reales | E18: De dónde viene | F18: Norma
A19: Precio de compra | B19: '=IF('03_Inmuebles'!H5="","",'03_Inmuebles'!H5) | C19: Trae el precio de compra según escritura de la hoja 03 (Registro de inmuebles); si el cliente no lo informó, queda en blanco. | D19: Fila 1: IF((vacío)=""; ""; (vacío)) → (en blanco) | E19: hoja «Registro de inmuebles» | F19: —
A20: Desembolsos atribuibles | B20: '=IF('03_Inmuebles'!I5="","",'03_Inmuebles'!I5) | C20: Trae de la hoja 03 (Registro de inmuebles) los honorarios, impuestos de transferencia y demás desembolsos directamente atribuibles; en blanco si no se informaron. | D20: Fila 1: IF((vacío)=""; ""; (vacío)) → (en blanco) | E20: hoja «Registro de inmuebles» | F20: —
A21: Costo recalculado | B21: '=IF(C5="","",C5+IF(D5="",0,D5)) | C21: Suma el precio de compra y los desembolsos atribuibles (sin desembolsos cuenta cero). Si falta el precio de compra queda en blanco, porque no se puede recalcular. | D21: Fila 1: IF((vacío)=""; ""; (vacío)+IF((vacío)=""; 0; (vacío))) → (en blanco) | E21: «Precio de compra» (esta hoja), «Desembolsos atribuibles» (esta hoja) | F21: —
A22: Costo registrado | B22: '='03_Inmuebles'!F5 | C22: Trae de la hoja 03 (Registro de inmuebles) el costo que el cliente tiene registrado para el inmueble. | D22: Fila 1: 500.000,00 → 500.000,00 | E22: hoja «Registro de inmuebles» | F22: —
A23: Diferencia | B23: '=IF(E5="","",E5-F5) | C23: Resta el costo registrado del costo recalculado; queda en blanco cuando no hubo costo recalculado. | D23: Fila 1: IF((vacío)=""; ""; (vacío)-500.000,00) → (en blanco) | E23: «Costo recalculado» (esta hoja), «Costo registrado» (esta hoja) | F23: —
A24: Costo auditado | B24: '=IF(E5<>"",E5,F5) | C24: Toma el costo recalculado cuando existe y, si no se pudo recalcular, acepta el costo registrado por el cliente. | D24: Fila 1: IF((vacío)<>""; (vacío); 500.000,00) → 500.000,00 | E24: «Costo recalculado» (esta hoja), «Costo registrado» (esta hoja) | F24: —

Sheet 06_Valor_razonable
A1: Valor razonable | H1: ⟵ Inicio | I1: ◀ Anterior | J1: Siguiente ▶
A2: Propiedades de inversión · Cliente de muestra S.A. · corte 2025-12-31
A4: Código | B4: ¿PI? | C4: Medición | D4: VR año anterior | E4: VR al corte | F4: Variación del año | G4: Importe en libros | H4: Ajuste VR no reconocido (VR − libros) | I4: Fuente / tasador | J4: Nivel
A5: IP-01 | B5: ='04_Clasificacion'!H5 | C5: =IF(B5="No","No es PI",IF('02_Parametros'!$B$11="valor_razonable",IF(E5<>"","Valor razonable","Costo (VR no fiable)"),"Costo")) | D5: =IF('03_Inmuebles'!M5="","",'03_Inmuebles'!M5) | E5: =IF('03_Inmuebles'!N5="","",'03_Inmuebles'!N5) | F5: =IF(OR(D5="",E5=""),"",E5-D5) | G5: ='03_Inmuebles'!Q5 | H5: =IF(C5="Valor razonable",(E5-G5)*'04_Clasificacion'!K5,"") | I5: =IF('03_Inmuebles'!O5="","",'03_Inmuebles'!O5) | J5: =IF('03_Inmuebles'!P5="","",'03_Inmuebles'!P5)
A6: IP-02 | B6: ='04_Clasificacion'!H6 | C6: =IF(B6="No","No es PI",IF('02_Parametros'!$B$11="valor_razonable",IF(E6<>"","Valor razonable","Costo (VR no fiable)"),"Costo")) | D6: =IF('03_Inmuebles'!M6="","",'03_Inmuebles'!M6) | E6: =IF('03_Inmuebles'!N6="","",'03_Inmuebles'!N6) | F6: =IF(OR(D6="",E6=""),"",E6-D6) | G6: ='03_Inmuebles'!Q6 | H6: =IF(C6="Valor razonable",(E6-G6)*'04_Clasificacion'!K6,"") | I6: =IF('03_Inmuebles'!O6="","",'03_Inmuebles'!O6) | J6: =IF('03_Inmuebles'!P6="","",'03_Inmuebles'!P6)
A7: IP-03 | B7: ='04_Clasificacion'!H7 | C7: =IF(B7="No","No es PI",IF('02_Parametros'!$B$11="valor_razonable",IF(E7<>"","Valor razonable","Costo (VR no fiable)"),"Costo")) | D7: =IF('03_Inmuebles'!M7="","",'03_Inmuebles'!M7) | E7: =IF('03_Inmuebles'!N7="","",'03_Inmuebles'!N7) | F7: =IF(OR(D7="",E7=""),"",E7-D7) | G7: ='03_Inmuebles'!Q7 | H7: =IF(C7="Valor razonable",(E7-G7)*'04_Clasificacion'!K7,"") | I7: =IF('03_Inmuebles'!O7="","",'03_Inmuebles'!O7) | J7: =IF('03_Inmuebles'!P7="","",'03_Inmuebles'!P7)
A8: IP-04 | B8: ='04_Clasificacion'!H8 | C8: =IF(B8="No","No es PI",IF('02_Parametros'!$B$11="valor_razonable",IF(E8<>"","Valor razonable","Costo (VR no fiable)"),"Costo")) | D8: =IF('03_Inmuebles'!M8="","",'03_Inmuebles'!M8) | E8: =IF('03_Inmuebles'!N8="","",'03_Inmuebles'!N8) | F8: =IF(OR(D8="",E8=""),"",E8-D8) | G8: ='03_Inmuebles'!Q8 | H8: =IF(C8="Valor razonable",(E8-G8)*'04_Clasificacion'!K8,"") | I8: =IF('03_Inmuebles'!O8="","",'03_Inmuebles'!O8) | J8: =IF('03_Inmuebles'!P8="","",'03_Inmuebles'!P8)
A9: IP-05 | B9: ='04_Clasificacion'!H9 | C9: =IF(B9="No","No es PI",IF('02_Parametros'!$B$11="valor_razonable",IF(E9<>"","Valor razonable","Costo (VR no fiable)"),"Costo")) | D9: =IF('03_Inmuebles'!M9="","",'03_Inmuebles'!M9) | E9: =IF('03_Inmuebles'!N9="","",'03_Inmuebles'!N9) | F9: =IF(OR(D9="",E9=""),"",E9-D9) | G9: ='03_Inmuebles'!Q9 | H9: =IF(C9="Valor razonable",(E9-G9)*'04_Clasificacion'!K9,"") | I9: =IF('03_Inmuebles'!O9="","",'03_Inmuebles'!O9) | J9: =IF('03_Inmuebles'!P9="","",'03_Inmuebles'!P9)
A10: IP-06 | B10: ='04_Clasificacion'!H10 | C10: =IF(B10="No","No es PI",IF('02_Parametros'!$B$11="valor_razonable",IF(E10<>"","Valor razonable","Costo (VR no fiable)"),"Costo")) | D10: =IF('03_Inmuebles'!M10="","",'03_Inmuebles'!M10) | E10: =IF('03_Inmuebles'!N10="","",'03_Inmuebles'!N10) | F10: =IF(OR(D10="",E10=""),"",E10-D10) | G10: ='03_Inmuebles'!Q10 | H10: =IF(C10="Valor razonable",(E10-G10)*'04_Clasificacion'!K10,"") | I10: =IF('03_Inmuebles'!O10="","",'03_Inmuebles'!O10) | J10: =IF('03_Inmuebles'!P10="","",'03_Inmuebles'!P10)
A11: IP-07 | B11: ='04_Clasificacion'!H11 | C11: =IF(B11="No","No es PI",IF('02_Parametros'!$B$11="valor_razonable",IF(E11<>"","Valor razonable","Costo (VR no fiable)"),"Costo")) | D11: =IF('03_Inmuebles'!M11="","",'03_Inmuebles'!M11) | E11: =IF('03_Inmuebles'!N11="","",'03_Inmuebles'!N11) | F11: =IF(OR(D11="",E11=""),"",E11-D11) | G11: ='03_Inmuebles'!Q11 | H11: =IF(C11="Valor razonable",(E11-G11)*'04_Clasificacion'!K11,"") | I11: =IF('03_Inmuebles'!O11="","",'03_Inmuebles'!O11) | J11: =IF('03_Inmuebles'!P11="","",'03_Inmuebles'!P11)
A12: IP-08 | B12: ='04_Clasificacion'!H12 | C12: =IF(B12="No","No es PI",IF('02_Parametros'!$B$11="valor_razonable",IF(E12<>"","Valor razonable","Costo (VR no fiable)"),"Costo")) | D12: =IF('03_Inmuebles'!M12="","",'03_Inmuebles'!M12) | E12: =IF('03_Inmuebles'!N12="","",'03_Inmuebles'!N12) | F12: =IF(OR(D12="",E12=""),"",E12-D12) | G12: ='03_Inmuebles'!Q12 | H12: =IF(C12="Valor razonable",(E12-G12)*'04_Clasificacion'!K12,"") | I12: =IF('03_Inmuebles'!O12="","",'03_Inmuebles'!O12) | J12: =IF('03_Inmuebles'!P12="","",'03_Inmuebles'!P12)
A13: IP-09 | B13: ='04_Clasificacion'!H13 | C13: =IF(B13="No","No es PI",IF('02_Parametros'!$B$11="valor_razonable",IF(E13<>"","Valor razonable","Costo (VR no fiable)"),"Costo")) | D13: =IF('03_Inmuebles'!M13="","",'03_Inmuebles'!M13) | E13: =IF('03_Inmuebles'!N13="","",'03_Inmuebles'!N13) | F13: =IF(OR(D13="",E13=""),"",E13-D13) | G13: ='03_Inmuebles'!Q13 | H13: =IF(C13="Valor razonable",(E13-G13)*'04_Clasificacion'!K13,"") | I13: =IF('03_Inmuebles'!O13="","",'03_Inmuebles'!O13) | J13: =IF('03_Inmuebles'!P13="","",'03_Inmuebles'!P13)
A14: IP-10 | B14: ='04_Clasificacion'!H14 | C14: =IF(B14="No","No es PI",IF('02_Parametros'!$B$11="valor_razonable",IF(E14<>"","Valor razonable","Costo (VR no fiable)"),"Costo")) | D14: =IF('03_Inmuebles'!M14="","",'03_Inmuebles'!M14) | E14: =IF('03_Inmuebles'!N14="","",'03_Inmuebles'!N14) | F14: =IF(OR(D14="",E14=""),"",E14-D14) | G14: ='03_Inmuebles'!Q14 | H14: =IF(C14="Valor razonable",(E14-G14)*'04_Clasificacion'!K14,"") | I14: =IF('03_Inmuebles'!O14="","",'03_Inmuebles'!O14) | J14: =IF('03_Inmuebles'!P14="","",'03_Inmuebles'!P14)
A15: TOTAL | F15: =SUM(F5:F14) | G15: =SUM(G5:G14) | H15: =SUM(H5:H14)
A17: ⓘ Cómo se calcula esta hoja
A18: Columna | B18: Fórmula (Excel) | C18: Cómo se calcula (sencillo) | D18: Ejemplo con números reales | E18: De dónde viene | F18: Norma
A19: ¿PI? | B19: '='04_Clasificacion'!H5 | C19: Trae de la hoja 04 (Clasificación) si el inmueble es, total o parcialmente, propiedad de inversión. | D19: Fila 1: «Sí» → Sí | E19: hoja «Clasificación» | F19: —
A20: Medición | B20: '=IF(B5="No","No es PI",IF('02_Parametros'!$B$11="valor_razonable",IF(E5<>"","Valor razonable","Costo (VR no fiable)"),"Costo")) | C20: Si el inmueble no es propiedad de inversión indica «No es PI». Si la ruta de la hoja 02 (Parámetros) es valor razonable, usa «Valor razonable» cuando hay VR al corte y «Costo (VR no fiable)» cuando falta; si la ruta es el costo, indica «Costo». | D20: Fila 1: IF(«Sí»="No"; "No es PI"; IF(«valor_razonable»="valor_razonable"; IF(720.000,00<>""; "Valor razonable"; "Costo (VR no fiable)"); "Costo")) → Valor razonable | E20: «¿PI?» (esta hoja), «VR al corte» (esta hoja), hoja «Parámetros y ruta por marco» | F20: —
A21: VR año anterior | B21: '=IF('03_Inmuebles'!M5="","",'03_Inmuebles'!M5) | C21: Trae el valor razonable del año anterior de la hoja 03 (Registro de inmuebles); en blanco si el cliente no lo informó. | D21: Fila 1: IF(700.000,00=""; ""; 700.000,00) → 700.000,00 | E21: hoja «Registro de inmuebles» | F21: —
A22: VR al corte | B22: '=IF('03_Inmuebles'!N5="","",'03_Inmuebles'!N5) | C22: Trae el valor razonable a la fecha de corte (avalúo o tasación) de la hoja 03 (Registro de inmuebles); en blanco si no existe. | D22: Fila 1: IF(720.000,00=""; ""; 720.000,00) → 720.000,00 | E22: hoja «Registro de inmuebles» | F22: —
A23: Variación del año | B23: '=IF(OR(D5="",E5=""),"",E5-D5) | C23: Resta el VR del año anterior del VR al corte; si falta cualquiera de los dos, queda en blanco. | D23: Fila 1: IF(OR(700.000,00=""; 720.000,00=""); ""; 720.000,00-700.000,00) → 20.000,00 | E23: «VR año anterior» (esta hoja), «VR al corte» (esta hoja) | F23: —
A24: Importe en libros | B24: '='03_Inmuebles'!Q5 | C24: Trae de la hoja 03 (Registro de inmuebles) el importe en libros al corte, para compararlo con el valor razonable. | D24: Fila 1: 700.000,00 → 700.000,00 | E24: hoja «Registro de inmuebles» | F24: —
A25: Ajuste VR no reconocido (VR − libros) | B25: '=IF(C5="Valor razonable",(E5-G5)*'04_Clasificacion'!K5,"") | C25: Solo para inmuebles medidos a valor razonable: resta el importe en libros del VR al corte y lo multiplica por la parte que es propiedad de inversión (hoja 04, Clasificación). En los demás queda en blanco. | D25: Fila 1: IF(«Valor razonable»="Valor razonable"; (720.000,00-700.000,00)*100,00 %; "") → 20.000,00 | E25: «Medición» (esta hoja), «VR al corte» (esta hoja), «Importe en libros» (esta hoja), hoja «Clasificación» | F25: —
A26: Fuente / tasador | B26: '=IF('03_Inmuebles'!O5="","",'03_Inmuebles'!O5) | C26: Trae de la hoja 03 (Registro de inmuebles) quién determinó el valor razonable (perito, tasador u otra fuente); en blanco si no se informó. | D26: Fila 1: IF(«Perito independiente (tasación dic-2025)»=""; ""; «Perito independiente (tasación dic-2025)») → Perito independiente (tasación dic-2025) | E26: hoja «Registro de inmuebles» | F26: —
A27: Nivel | B27: '=IF('03_Inmuebles'!P5="","",'03_Inmuebles'!P5) | C27: Trae el nivel de jerarquía del valor razonable (1, 2 o 3) declarado en la hoja 03 (Registro de inmuebles); en blanco si falta. | D27: Fila 1: IF(«Nivel 2»=""; ""; «Nivel 2») → Nivel 2 | E27: hoja «Registro de inmuebles» | F27: —

Sheet 07_Modelo_costo
A1: Modelo del costo: depreciación y deterioro | H1: ⟵ Inicio | I1: ◀ Anterior | J1: Siguiente ▶
A2: Propiedades de inversión · Cliente de muestra S.A. · corte 2025-12-31
A4: Código | B4: Medición | C4: ¿Aplica? | D4: Costo del modelo (PYMES 16.8: libros al cesar el VR) | E4: Terreno | F4: Base depreciable | G4: Vida útil (años) | H4: Fecha base de depreciación | I4: Meses completos | J4: Dep. acumulada recalculada | K4: Depreciación del año | L4: Dep. acumulada registrada | M4: Diferencia de depreciación | N4: Valor neto | O4: Importe recuperable | P4: Deterioro | Q4: Medición al costo
A5: IP-01 | B5: ='06_Valor_razonable'!C5 | C5: =IF(LEFT(B5,5)="Costo","Sí","No") | D5: =IF(C5="No","",IF(AND('02_Parametros'!$B$8="Sí",B5="Costo (VR no fiable)",'03_Inmuebles'!V5<>""),'03_Inmuebles'!V5,'05_Costo_inicial'!H5)) | E5: =IF(C5="Sí",IF('03_Inmuebles'!J5="",0,'03_Inmuebles'!J5),"") | F5: =IF(C5="Sí",D5-E5,"") | G5: =IF(C5="Sí",IF('03_Inmuebles'!K5="","",'03_Inmuebles'!K5),"") | I5: =IF(OR(C5="No",H5=""),"",IF(H5>'02_Parametros'!$B$5,0,DATEDIF(H5,'02_Parametros'!$B$5,"m"))) | J5: =IF(C5="No","",IF(F5=0,0,IF(OR(G5="",I5=""),"",F5*MIN(1,I5/(G5*12))))) | K5: =IF(J5="","",IF(F5=0,0,J5-F5*MIN(1,MAX(0,I5-12)/(G5*12)))) | L5: =IF(C5="Sí",IF('03_Inmuebles'!L5="","",'03_Inmuebles'!L5),"") | M5: =IF(OR(J5="",L5=""),"",J5-L5) | N5: =IF(C5="No","",D5-IF(J5<>"",J5,IF(L5<>"",L5,0))) | O5: =IF(C5="Sí",IF('03_Inmuebles'!Y5="","",'03_Inmuebles'!Y5),"") | P5: =IF(OR(C5="No",O5=""),"",MAX(0,N5-O5)) | Q5: =IF(C5="No","",N5-IF(P5="",0,P5))
A6: IP-02 | B6: ='06_Valor_razonable'!C6 | C6: =IF(LEFT(B6,5)="Costo","Sí","No") | D6: =IF(C6="No","",IF(AND('02_Parametros'!$B$8="Sí",B6="Costo (VR no fiable)",'03_Inmuebles'!V6<>""),'03_Inmuebles'!V6,'05_Costo_inicial'!H6)) | E6: =IF(C6="Sí",IF('03_Inmuebles'!J6="",0,'03_Inmuebles'!J6),"") | F6: =IF(C6="Sí",D6-E6,"") | G6: =IF(C6="Sí",IF('03_Inmuebles'!K6="","",'03_Inmuebles'!K6),"") | I6: =IF(OR(C6="No",H6=""),"",IF(H6>'02_Parametros'!$B$5,0,DATEDIF(H6,'02_Parametros'!$B$5,"m"))) | J6: =IF(C6="No","",IF(F6=0,0,IF(OR(G6="",I6=""),"",F6*MIN(1,I6/(G6*12))))) | K6: =IF(J6="","",IF(F6=0,0,J6-F6*MIN(1,MAX(0,I6-12)/(G6*12)))) | L6: =IF(C6="Sí",IF('03_Inmuebles'!L6="","",'03_Inmuebles'!L6),"") | M6: =IF(OR(J6="",L6=""),"",J6-L6) | N6: =IF(C6="No","",D6-IF(J6<>"",J6,IF(L6<>"",L6,0))) | O6: =IF(C6="Sí",IF('03_Inmuebles'!Y6="","",'03_Inmuebles'!Y6),"") | P6: =IF(OR(C6="No",O6=""),"",MAX(0,N6-O6)) | Q6: =IF(C6="No","",N6-IF(P6="",0,P6))
A7: IP-03 | B7: ='06_Valor_razonable'!C7 | C7: =IF(LEFT(B7,5)="Costo","Sí","No") | D7: =IF(C7="No","",IF(AND('02_Parametros'!$B$8="Sí",B7="Costo (VR no fiable)",'03_Inmuebles'!V7<>""),'03_Inmuebles'!V7,'05_Costo_inicial'!H7)) | E7: =IF(C7="Sí",IF('03_Inmuebles'!J7="",0,'03_Inmuebles'!J7),"") | F7: =IF(C7="Sí",D7-E7,"") | G7: =IF(C7="Sí",IF('03_Inmuebles'!K7="","",'03_Inmuebles'!K7),"") | I7: =IF(OR(C7="No",H7=""),"",IF(H7>'02_Parametros'!$B$5,0,DATEDIF(H7,'02_Parametros'!$B$5,"m"))) | J7: =IF(C7="No","",IF(F7=0,0,IF(OR(G7="",I7=""),"",F7*MIN(1,I7/(G7*12))))) | K7: =IF(J7="","",IF(F7=0,0,J7-F7*MIN(1,MAX(0,I7-12)/(G7*12)))) | L7: =IF(C7="Sí",IF('03_Inmuebles'!L7="","",'03_Inmuebles'!L7),"") | M7: =IF(OR(J7="",L7=""),"",J7-L7) | N7: =IF(C7="No","",D7-IF(J7<>"",J7,IF(L7<>"",L7,0))) | O7: =IF(C7="Sí",IF('03_Inmuebles'!Y7="","",'03_Inmuebles'!Y7),"") | P7: =IF(OR(C7="No",O7=""),"",MAX(0,N7-O7)) | Q7: =IF(C7="No","",N7-IF(P7="",0,P7))
A8: IP-04 | B8: ='06_Valor_razonable'!C8 | C8: =IF(LEFT(B8,5)="Costo","Sí","No") | D8: =IF(C8="No","",IF(AND('02_Parametros'!$B$8="Sí",B8="Costo (VR no fiable)",'03_Inmuebles'!V8<>""),'03_Inmuebles'!V8,'05_Costo_inicial'!H8)) | E8: =IF(C8="Sí",IF('03_Inmuebles'!J8="",0,'03_Inmuebles'!J8),"") | F8: =IF(C8="Sí",D8-E8,"") | G8: =IF(C8="Sí",IF('03_Inmuebles'!K8="","",'03_Inmuebles'!K8),"") | I8: =IF(OR(C8="No",H8=""),"",IF(H8>'02_Parametros'!$B$5,0,DATEDIF(H8,'02_Parametros'!$B$5,"m"))) | J8: =IF(C8="No","",IF(F8=0,0,IF(OR(G8="",I8=""),"",F8*MIN(1,I8/(G8*12))))) | K8: =IF(J8="","",IF(F8=0,0,J8-F8*MIN(1,MAX(0,I8-12)/(G8*12)))) | L8: =IF(C8="Sí",IF('03_Inmuebles'!L8="","",'03_Inmuebles'!L8),"") | M8: =IF(OR(J8="",L8=""),"",J8-L8) | N8: =IF(C8="No","",D8-IF(J8<>"",J8,IF(L8<>"",L8,0))) | O8: =IF(C8="Sí",IF('03_Inmuebles'!Y8="","",'03_Inmuebles'!Y8),"") | P8: =IF(OR(C8="No",O8=""),"",MAX(0,N8-O8)) | Q8: =IF(C8="No","",N8-IF(P8="",0,P8))
A9: IP-05 | B9: ='06_Valor_razonable'!C9 | C9: =IF(LEFT(B9,5)="Costo","Sí","No") | D9: =IF(C9="No","",IF(AND('02_Parametros'!$B$8="Sí",B9="Costo (VR no fiable)",'03_Inmuebles'!V9<>""),'03_Inmuebles'!V9,'05_Costo_inicial'!H9)) | E9: =IF(C9="Sí",IF('03_Inmuebles'!J9="",0,'03_Inmuebles'!J9),"") | F9: =IF(C9="Sí",D9-E9,"") | G9: =IF(C9="Sí",IF('03_Inmuebles'!K9="","",'03_Inmuebles'!K9),"") | I9: =IF(OR(C9="No",H9=""),"",IF(H9>'02_Parametros'!$B$5,0,DATEDIF(H9,'02_Parametros'!$B$5,"m"))) | J9: =IF(C9="No","",IF(F9=0,0,IF(OR(G9="",I9=""),"",F9*MIN(1,I9/(G9*12))))) | K9: =IF(J9="","",IF(F9=0,0,J9-F9*MIN(1,MAX(0,I9-12)/(G9*12)))) | L9: =IF(C9="Sí",IF('03_Inmuebles'!L9="","",'03_Inmuebles'!L9),"") | M9: =IF(OR(J9="",L9=""),"",J9-L9) | N9: =IF(C9="No","",D9-IF(J9<>"",J9,IF(L9<>"",L9,0))) | O9: =IF(C9="Sí",IF('03_Inmuebles'!Y9="","",'03_Inmuebles'!Y9),"") | P9: =IF(OR(C9="No",O9=""),"",MAX(0,N9-O9)) | Q9: =IF(C9="No","",N9-IF(P9="",0,P9))
A10: IP-06 | B10: ='06_Valor_razonable'!C10 | C10: =IF(LEFT(B10,5)="Costo","Sí","No") | D10: =IF(C10="No","",IF(AND('02_Parametros'!$B$8="Sí",B10="Costo (VR no fiable)",'03_Inmuebles'!V10<>""),'03_Inmuebles'!V10,'05_Costo_inicial'!H10)) | E10: =IF(C10="Sí",IF('03_Inmuebles'!J10="",0,'03_Inmuebles'!J10),"") | F10: =IF(C10="Sí",D10-E10,"") | G10: =IF(C10="Sí",IF('03_Inmuebles'!K10="","",'03_Inmuebles'!K10),"") | I10: =IF(OR(C10="No",H10=""),"",IF(H10>'02_Parametros'!$B$5,0,DATEDIF(H10,'02_Parametros'!$B$5,"m"))) | J10: =IF(C10="No","",IF(F10=0,0,IF(OR(G10="",I10=""),"",F10*MIN(1,I10/(G10*12))))) | K10: =IF(J10="","",IF(F10=0,0,J10-F10*MIN(1,MAX(0,I10-12)/(G10*12)))) | L10: =IF(C10="Sí",IF('03_Inmuebles'!L10="","",'03_Inmuebles'!L10),"") | M10: =IF(OR(J10="",L10=""),"",J10-L10) | N10: =IF(C10="No","",D10-IF(J10<>"",J10,IF(L10<>"",L10,0))) | O10: =IF(C10="Sí",IF('03_Inmuebles'!Y10="","",'03_Inmuebles'!Y10),"") | P10: =IF(OR(C10="No",O10=""),"",MAX(0,N10-O10)) | Q10: =IF(C10="No","",N10-IF(P10="",0,P10))
A11: IP-07 | B11: ='06_Valor_razonable'!C11 | C11: =IF(LEFT(B11,5)="Costo","Sí","No") | D11: =IF(C11="No","",IF(AND('02_Parametros'!$B$8="Sí",B11="Costo (VR no fiable)",'03_Inmuebles'!V11<>""),'03_Inmuebles'!V11,'05_Costo_inicial'!H11)) | E11: =IF(C11="Sí",IF('03_Inmuebles'!J11="",0,'03_Inmuebles'!J11),"") | F11: =IF(C11="Sí",D11-E11,"") | G11: =IF(C11="Sí",IF('03_Inmuebles'!K11="","",'03_Inmuebles'!K11),"") | H11: 42369 | I11: =IF(OR(C11="No",H11=""),"",IF(H11>'02_Parametros'!$B$5,0,DATEDIF(H11,'02_Parametros'!$B$5,"m"))) | J11: =IF(C11="No","",IF(F11=0,0,IF(OR(G11="",I11=""),"",F11*MIN(1,I11/(G11*12))))) | K11: =IF(J11="","",IF(F11=0,0,J11-F11*MIN(1,MAX(0,I11-12)/(G11*12)))) | L11: =IF(C11="Sí",IF('03_Inmuebles'!L11="","",'03_Inmuebles'!L11),"") | M11: =IF(OR(J11="",L11=""),"",J11-L11) | N11: =IF(C11="No","",D11-IF(J11<>"",J11,IF(L11<>"",L11,0))) | O11: =IF(C11="Sí",IF('03_Inmuebles'!Y11="","",'03_Inmuebles'!Y11),"") | P11: =IF(OR(C11="No",O11=""),"",MAX(0,N11-O11)) | Q11: =IF(C11="No","",N11-IF(P11="",0,P11))
A12: IP-08 | B12: ='06_Valor_razonable'!C12 | C12: =IF(LEFT(B12,5)="Costo","Sí","No") | D12: =IF(C12="No","",IF(AND('02_Parametros'!$B$8="Sí",B12="Costo (VR no fiable)",'03_Inmuebles'!V12<>""),'03_Inmuebles'!V12,'05_Costo_inicial'!H12)) | E12: =IF(C12="Sí",IF('03_Inmuebles'!J12="",0,'03_Inmuebles'!J12),"") | F12: =IF(C12="Sí",D12-E12,"") | G12: =IF(C12="Sí",IF('03_Inmuebles'!K12="","",'03_Inmuebles'!K12),"") | I12: =IF(OR(C12="No",H12=""),"",IF(H12>'02_Parametros'!$B$5,0,DATEDIF(H12,'02_Parametros'!$B$5,"m"))) | J12: =IF(C12="No","",IF(F12=0,0,IF(OR(G12="",I12=""),"",F12*MIN(1,I12/(G12*12))))) | K12: =IF(J12="","",IF(F12=0,0,J12-F12*MIN(1,MAX(0,I12-12)/(G12*12)))) | L12: =IF(C12="Sí",IF('03_Inmuebles'!L12="","",'03_Inmuebles'!L12),"") | M12: =IF(OR(J12="",L12=""),"",J12-L12) | N12: =IF(C12="No","",D12-IF(J12<>"",J12,IF(L12<>"",L12,0))) | O12: =IF(C12="Sí",IF('03_Inmuebles'!Y12="","",'03_Inmuebles'!Y12),"") | P12: =IF(OR(C12="No",O12=""),"",MAX(0,N12-O12)) | Q12: =IF(C12="No","",N12-IF(P12="",0,P12))
A13: IP-09 | B13: ='06_Valor_razonable'!C13 | C13: =IF(LEFT(B13,5)="Costo","Sí","No") | D13: =IF(C13="No","",IF(AND('02_Parametros'!$B$8="Sí",B13="Costo (VR no fiable)",'03_Inmuebles'!V13<>""),'03_Inmuebles'!V13,'05_Costo_inicial'!H13)) | E13: =IF(C13="Sí",IF('03_Inmuebles'!J13="",0,'03_Inmuebles'!J13),"") | F13: =IF(C13="Sí",D13-E13,"") | G13: =IF(C13="Sí",IF('03_Inmuebles'!K13="","",'03_Inmuebles'!K13),"") | I13: =IF(OR(C13="No",H13=""),"",IF(H13>'02_Parametros'!$B$5,0,DATEDIF(H13,'02_Parametros'!$B$5,"m"))) | J13: =IF(C13="No","",IF(F13=0,0,IF(OR(G13="",I13=""),"",F13*MIN(1,I13/(G13*12))))) | K13: =IF(J13="","",IF(F13=0,0,J13-F13*MIN(1,MAX(0,I13-12)/(G13*12)))) | L13: =IF(C13="Sí",IF('03_Inmuebles'!L13="","",'03_Inmuebles'!L13),"") | M13: =IF(OR(J13="",L13=""),"",J13-L13) | N13: =IF(C13="No","",D13-IF(J13<>"",J13,IF(L13<>"",L13,0))) | O13: =IF(C13="Sí",IF('03_Inmuebles'!Y13="","",'03_Inmuebles'!Y13),"") | P13: =IF(OR(C13="No",O13=""),"",MAX(0,N13-O13)) | Q13: =IF(C13="No","",N13-IF(P13="",0,P13))
A14: IP-10 | B14: ='06_Valor_razonable'!C14 | C14: =IF(LEFT(B14,5)="Costo","Sí","No") | D14: =IF(C14="No","",IF(AND('02_Parametros'!$B$8="Sí",B14="Costo (VR no fiable)",'03_Inmuebles'!V14<>""),'03_Inmuebles'!V14,'05_Costo_inicial'!H14)) | E14: =IF(C14="Sí",IF('03_Inmuebles'!J14="",0,'03_Inmuebles'!J14),"") | F14: =IF(C14="Sí",D14-E14,"") | G14: =IF(C14="Sí",IF('03_Inmuebles'!K14="","",'03_Inmuebles'!K14),"") | I14: =IF(OR(C14="No",H14=""),"",IF(H14>'02_Parametros'!$B$5,0,DATEDIF(H14,'02_Parametros'!$B$5,"m"))) | J14: =IF(C14="No","",IF(F14=0,0,IF(OR(G14="",I14=""),"",F14*MIN(1,I14/(G14*12))))) | K14: =IF(J14="","",IF(F14=0,0,J14-F14*MIN(1,MAX(0,I14-12)/(G14*12)))) | L14: =IF(C14="Sí",IF('03_Inmuebles'!L14="","",'03_Inmuebles'!L14),"") | M14: =IF(OR(J14="",L14=""),"",J14-L14) | N14: =IF(C14="No","",D14-IF(J14<>"",J14,IF(L14<>"",L14,0))) | O14: =IF(C14="Sí",IF('03_Inmuebles'!Y14="","",'03_Inmuebles'!Y14),"") | P14: =IF(OR(C14="No",O14=""),"",MAX(0,N14-O14)) | Q14: =IF(C14="No","",N14-IF(P14="",0,P14))
A15: TOTAL | K15: =SUM(K5:K14) | M15: =SUM(M5:M14) | P15: =SUM(P5:P14) | Q15: =SUM(Q5:Q14)
A17: ⓘ Cómo se calcula esta hoja
A18: Columna | B18: Fórmula (Excel) | C18: Cómo se calcula (sencillo) | D18: Ejemplo con números reales | E18: De dónde viene | F18: Norma
A19: Medición | B19: '='06_Valor_razonable'!C5 | C19: Trae la medición que corresponde al inmueble según la hoja 06 (Valor razonable): valor razonable, costo, costo por VR no fiable o no es PI. | D19: Fila 1: «Valor razonable» → Valor razonable | E19: hoja «Valor razonable» | F19: —
A20: ¿Aplica? | B20: '=IF(LEFT(B5,5)="Costo","Sí","No") | C20: Marca «Sí» cuando la medición empieza por «Costo» (modelo del costo o VR no fiable); solo en esos inmuebles se recalculan la depreciación y el deterioro. | D20: Fila 1: IF(LEFT(«Valor razonable»; 5)="Costo"; "Sí"; "No") → No | E20: «Medición» (esta hoja) | F20: —
A21: Costo del modelo (PYMES 16.8: libros al cesar el VR) | B21: '=IF(C5="No","",IF(AND('02_Parametros'!$B$8="Sí",B5="Costo (VR no fiable)",'03_Inmuebles'!V5<>""),'03_Inmuebles'!V5,'05_Costo_inicial'!H5)) | C21: Si aplica el modelo del costo, toma el costo auditado de la hoja 05 (Costo inicial). En PYMES, cuando el VR dejó de ser fiable y la hoja 03 trae el importe en libros a esa fecha («Libros al cambio»), usa ese importe como nuevo costo. Si no aplica, queda en blanco. | D21: Fila 1: IF(«No»="No"; ""; IF(AND(«No»="Sí"; «Valor razonable»="Costo (VR no fiable)"; (vacío)<>""); (vacío); 500.000,00)) → (en blanco) | E21: «¿Aplica?» (esta hoja), «Medición» (esta hoja), hoja «Parámetros y ruta por marco», hoja «Registro de inmuebles», hoja «Costo inicial» | F21: —
A22: Terreno | B22: '=IF(C5="Sí",IF('03_Inmuebles'!J5="",0,'03_Inmuebles'!J5),"") | C22: Si aplica el modelo del costo, trae de la hoja 03 (Registro de inmuebles) la parte del costo que es terreno, que no se deprecia; sin dato cuenta cero. | D22: Fila 1: IF(«No»="Sí"; IF(100.000,00=""; 0; 100.000,00); "") → (en blanco) | E22: «¿Aplica?» (esta hoja), hoja «Registro de inmuebles» | F22: —
A23: Base depreciable | B23: '=IF(C5="Sí",D5-E5,"") | C23: Resta el terreno del costo del modelo: es la parte del inmueble que sí se deprecia. En blanco si no aplica el modelo del costo. | D23: Fila 1: IF(«No»="Sí"; (vacío)-(vacío); "") → (en blanco) | E23: «¿Aplica?» (esta hoja), «Costo del modelo (PYMES 16.8: libros al cesar el VR)» (esta hoja), «Terreno» (esta hoja) | F23: —
A24: Vida útil (años) | B24: '=IF(C5="Sí",IF('03_Inmuebles'!K5="","",'03_Inmuebles'!K5),"") | C24: Si aplica el modelo del costo, trae la vida útil en años de la hoja 03 (Registro de inmuebles); en blanco si falta el dato o si no aplica. | D24: Fila 1: IF(«No»="Sí"; IF(40,00=""; ""; 40,00); "") → (en blanco) | E24: «¿Aplica?» (esta hoja), hoja «Registro de inmuebles» | F24: —
A25: Meses completos | B25: '=IF(OR(C5="No",H5=""),"",IF(H5>'02_Parametros'!$B$5,0,DATEDIF(H5,'02_Parametros'!$B$5,"m"))) | C25: Cuenta los meses completos desde la fecha base de depreciación hasta el corte de la hoja 02 (Parámetros); si la fecha base es posterior al corte da 0, y queda en blanco si no aplica o falta la fecha. | D25: Fila 1: IF(OR(«No»="No"; (vacío)=""); ""; IF((vacío)>«2025-12-31»; 0; DATEDIF((vacío); «2025-12-31»; "m"))) → (en blanco) | E25: «¿Aplica?» (esta hoja), «Fecha base de depreciación» (esta hoja), hoja «Parámetros y ruta por marco» | F25: —
A26: Dep. acumulada recalculada | B26: '=IF(C5="No","",IF(F5=0,0,IF(OR(G5="",I5=""),"",F5*MIN(1,I5/(G5*12))))) | C26: Deprecia la base en línea recta: base depreciable × meses completos ÷ (vida útil × 12), sin pasar del 100 % de la base. Si la base es cero da 0; si falta la vida útil o los meses, queda en blanco. | D26: Fila 1: IF(«No»="No"; ""; IF((vacío)=0; 0; IF(OR((vacío)=""; (vacío)=""); ""; (vacío)*MIN(1; (vacío)/((vacío)*12))))) → (en blanco) | E26: «¿Aplica?» (esta hoja), «Base depreciable» (esta hoja), «Vida útil (años)» (esta hoja), «Meses completos» (esta hoja) | F26: —
A27: Depreciación del año | B27: '=IF(J5="","",IF(F5=0,0,J5-F5*MIN(1,MAX(0,I5-12)/(G5*12)))) | C27: A la depreciación acumulada recalculada le resta la que ya existía 12 meses antes (la misma cuenta con 12 meses menos): es el gasto de depreciación del año. En blanco si no hay acumulada recalculada. | D27: Fila 1: IF((vacío)=""; ""; IF((vacío)=0; 0; (vacío)-(vacío)*MIN(1; MAX(0; (vacío)-12)/((vacío)*12)))) → (en blanco) | E27: «Dep. acumulada recalculada» (esta hoja), «Base depreciable» (esta hoja), «Meses completos» (esta hoja), «Vida útil (años)» (esta hoja) | F27: —
A28: Dep. acumulada registrada | B28: '=IF(C5="Sí",IF('03_Inmuebles'!L5="","",'03_Inmuebles'!L5),"") | C28: Si aplica el modelo del costo, trae la depreciación acumulada que el cliente tiene registrada, de la hoja 03 (Registro de inmuebles); en blanco si no la informó. | D28: Fila 1: IF(«No»="Sí"; IF((vacío)=""; ""; (vacío)); "") → (en blanco) | E28: «¿Aplica?» (esta hoja), hoja «Registro de inmuebles» | F28: —
A29: Diferencia de depreciación | B29: '=IF(OR(J5="",L5=""),"",J5-L5) | C29: Resta la depreciación acumulada registrada de la recalculada; queda en blanco si falta alguna de las dos. | D29: Fila 1: IF(OR((vacío)=""; (vacío)=""); ""; (vacío)-(vacío)) → (en blanco) | E29: «Dep. acumulada recalculada» (esta hoja), «Dep. acumulada registrada» (esta hoja) | F29: —
... A33: Medición al costo | B33: '=IF(C5="No","",N5-IF(P5="",0,P5)) | C33: Valor neto menos el deterioro (sin deterioro no resta nada): es el importe por el que el inmueble debe quedar medido con el modelo del costo. | D33: Fila 1: IF(«No»="No"; ""; (vacío)-IF((vacío)=""; 0; (vacío))) → (en blanco) | E33: «¿Aplica?» (esta hoja), «Valor neto» (esta hoja), «Deterioro» (esta hoja) | F33: —

Sheet 08_Medicion
A1: Medición auditada por inmueble | H1: ⟵ Inicio | I1: ◀ Anterior | J1: Siguiente ▶
A2: Propiedades de inversión · Cliente de muestra S.A. · corte 2025-12-31
A4: Código | B4: Clasificación | C4: Medición | D4: Importe en libros | E4: Auditado en la cuenta | F4: Ajuste | G4: Ajuste VR (resultados) | H4: Efecto modelo del costo | I4: Reclasificación
A5: IP-01 | B5: ='04_Clasificacion'!G5 | C5: ='06_Valor_razonable'!C5 | D5: ='03_Inmuebles'!Q5 | E5: =IF('04_Clasificacion'!H5="No",0,IF(C5="Valor razonable",'06_Valor_razonable'!E5,'07_Modelo_costo'!Q5)*'04_Clasificacion'!K5) | F5: =E5-D5 | G5: =IF('06_Valor_razonable'!H5="","",'06_Valor_razonable'!H5) | H5: =IF('07_Modelo_costo'!C5="Sí",('07_Modelo_costo'!Q5-D5)*'04_Clasificacion'!K5,"") | I5: =IF('04_Clasificacion'!J5="","",'04_Clasificacion'!J5)
A6: IP-02 | B6: ='04_Clasificacion'!G6 | C6: ='06_Valor_razonable'!C6 | D6: ='03_Inmuebles'!Q6 | E6: =IF('04_Clasificacion'!H6="No",0,IF(C6="Valor razonable",'06_Valor_razonable'!E6,'07_Modelo_costo'!Q6)*'04_Clasificacion'!K6) | F6: =E6-D6 | G6: =IF('06_Valor_razonable'!H6="","",'06_Valor_razonable'!H6) | H6: =IF('07_Modelo_costo'!C6="Sí",('07_Modelo_costo'!Q6-D6)*'04_Clasificacion'!K6,"") | I6: =IF('04_Clasificacion'!J6="","",'04_Clasificacion'!J6)
A7: IP-03 | B7: ='04_Clasificacion'!G7 | C7: ='06_Valor_razonable'!C7 | D7: ='03_Inmuebles'!Q7 | E7: =IF('04_Clasificacion'!H7="No",0,IF(C7="Valor razonable",'06_Valor_razonable'!E7,'07_Modelo_costo'!Q7)*'04_Clasificacion'!K7) | F7: =E7-D7 | G7: =IF('06_Valor_razonable'!H7="","",'06_Valor_razonable'!H7) | H7: =IF('07_Modelo_costo'!C7="Sí",('07_Modelo_costo'!Q7-D7)*'04_Clasificacion'!K7,"") | I7: =IF('04_Clasificacion'!J7="","",'04_Clasificacion'!J7)
A8: IP-04 | B8: ='04_Clasificacion'!G8 | C8: ='06_Valor_razonable'!C8 | D8: ='03_Inmuebles'!Q8 | E8: =IF('04_Clasificacion'!H8="No",0,IF(C8="Valor razonable",'06_Valor_razonable'!E8,'07_Modelo_costo'!Q8)*'04_Clasificacion'!K8) | F8: =E8-D8 | G8: =IF('06_Valor_razonable'!H8="","",'06_Valor_razonable'!H8) | H8: =IF('07_Modelo_costo'!C8="Sí",('07_Modelo_costo'!Q8-D8)*'04_Clasificacion'!K8,"") | I8: =IF('04_Clasificacion'!J8="","",'04_Clasificacion'!J8)
A9: IP-05 | B9: ='04_Clasificacion'!G9 | C9: ='06_Valor_razonable'!C9 | D9: ='03_Inmuebles'!Q9 | E9: =IF('04_Clasificacion'!H9="No",0,IF(C9="Valor razonable",'06_Valor_razonable'!E9,'07_Modelo_costo'!Q9)*'04_Clasificacion'!K9) | F9: =E9-D9 | G9: =IF('06_Valor_razonable'!H9="","",'06_Valor_razonable'!H9) | H9: =IF('07_Modelo_costo'!C9="Sí",('07_Modelo_costo'!Q9-D9)*'04_Clasificacion'!K9,"") | I9: =IF('04_Clasificacion'!J9="","",'04_Clasificacion'!J9)
A10: IP-06 | B10: ='04_Clasificacion'!G10 | C10: ='06_Valor_razonable'!C10 | D10: ='03_Inmuebles'!Q10 | E10: =IF('04_Clasificacion'!H10="No",0,IF(C10="Valor razonable",'06_Valor_razonable'!E10,'07_Modelo_costo'!Q10)*'04_Clasificacion'!K10) | F10: =E10-D10 | G10: =IF('06_Valor_razonable'!H10="","",'06_Valor_razonable'!H10) | H10: =IF('07_Modelo_costo'!C10="Sí",('07_Modelo_costo'!Q10-D10)*'04_Clasificacion'!K10,"") | I10: =IF('04_Clasificacion'!J10="","",'04_Clasificacion'!J10)
A11: IP-07 | B11: ='04_Clasificacion'!G11 | C11: ='06_Valor_razonable'!C11 | D11: ='03_Inmuebles'!Q11 | E11: =IF('04_Clasificacion'!H11="No",0,IF(C11="Valor razonable",'06_Valor_razonable'!E11,'07_Modelo_costo'!Q11)*'04_Clasificacion'!K11) | F11: =E11-D11 | G11: =IF('06_Valor_razonable'!H11="","",'06_Valor_razonable'!H11) | H11: =IF('07_Modelo_costo'!C11="Sí",('07_Modelo_costo'!Q11-D11)*'04_Clasificacion'!K11,"") | I11: =IF('04_Clasificacion'!J11="","",'04_Clasificacion'!J11)
A12: IP-08 | B12: ='04_Clasificacion'!G12 | C12: ='06_Valor_razonable'!C12 | D12: ='03_Inmuebles'!Q12 | E12: =IF('04_Clasificacion'!H12="No",0,IF(C12="Valor razonable",'06_Valor_razonable'!E12,'07_Modelo_costo'!Q12)*'04_Clasificacion'!K12) | F12: =E12-D12 | G12: =IF('06_Valor_razonable'!H12="","",'06_Valor_razonable'!H12) | H12: =IF('07_Modelo_costo'!C12="Sí",('07_Modelo_costo'!Q12-D12)*'04_Clasificacion'!K12,"") | I12: =IF('04_Clasificacion'!J12="","",'04_Clasificacion'!J12)
A13: IP-09 | B13: ='04_Clasificacion'!G13 | C13: ='06_Valor_razonable'!C13 | D13: ='03_Inmuebles'!Q13 | E13: =IF('04_Clasificacion'!H13="No",0,IF(C13="Valor razonable",'06_Valor_razonable'!E13,'07_Modelo_costo'!Q13)*'04_Clasificacion'!K13) | F13: =E13-D13 | G13: =IF('06_Valor_razonable'!H13="","",'06_Valor_razonable'!H13) | H13: =IF('07_Modelo_costo'!C13="Sí",('07_Modelo_costo'!Q13-D13)*'04_Clasificacion'!K13,"") | I13: =IF('04_Clasificacion'!J13="","",'04_Clasificacion'!J13)
A14: IP-10 | B14: ='04_Clasificacion'!G14 | C14: ='06_Valor_razonable'!C14 | D14: ='03_Inmuebles'!Q14 | E14: =IF('04_Clasificacion'!H14="No",0,IF(C14="Valor razonable",'06_Valor_razonable'!E14,'07_Modelo_costo'!Q14)*'04_Clasificacion'!K14) | F14: =E14-D14 | G14: =IF('06_Valor_razonable'!H14="","",'06_Valor_razonable'!H14) | H14: =IF('07_Modelo_costo'!C14="Sí",('07_Modelo_costo'!Q14-D14)*'04_Clasificacion'!K14,"") | I14: =IF('04_Clasificacion'!J14="","",'04_Clasificacion'!J14)
A15: TOTAL | D15: =SUM(D5:D14) | E15: =SUM(E5:E14) | F15: =SUM(F5:F14) | G15: =SUM(G5:G14) | H15: =SUM(H5:H14) | I15: =SUM(I5:I14)
A17: ⓘ Cómo se calcula esta hoja
A18: Columna | B18: Fórmula (Excel) | C18: Cómo se calcula (sencillo) | D18: Ejemplo con números reales | E18: De dónde viene | F18: Norma
A19: Clasificación | B19: '='04_Clasificacion'!G5 | C19: Trae de la hoja 04 (Clasificación) la clasificación auditada del inmueble. | D19: Fila 1: «Propiedad de inversión» → Propiedad de inversión | E19: hoja «Clasificación» | F19: —
A20: Medición | B20: '='06_Valor_razonable'!C5 | C20: Trae de la hoja 06 (Valor razonable) la base con que se mide el inmueble: valor razonable, costo o no es PI. | D20: Fila 1: «Valor razonable» → Valor razonable | E20: hoja «Valor razonable» | F20: —
A21: Importe en libros | B21: '='03_Inmuebles'!Q5 | C21: Trae de la hoja 03 (Registro de inmuebles) el importe en libros que el cliente registró al corte. | D21: Fila 1: 700.000,00 → 700.000,00 | E21: hoja «Registro de inmuebles» | F21: —
A22: Auditado en la cuenta | B22: '=IF('04_Clasificacion'!H5="No",0,IF(C5="Valor razonable",'06_Valor_razonable'!E5,'07_Modelo_costo'!Q5)*'04_Clasificacion'!K5) | C22: Si el inmueble no es propiedad de inversión pone 0. Si lo es, toma el VR al corte (hoja 06) o la medición al costo (hoja 07), según su medición, y lo multiplica por la parte que es propiedad de inversión (hoja 04). | D22: Fila 1: IF(«Sí»="No"; 0; IF(«Valor razonable»="Valor razonable"; 720.000,00; (vacío))*100,00 %) → 720.000,00 | E22: «Medición» (esta hoja), hoja «Clasificación», hoja «Valor razonable», hoja «Modelo del costo: depreciación y deterioro» | F22: —
A23: Ajuste | B23: '=E5-D5 | C23: Resta el importe en libros del importe auditado en la cuenta: lo que hay que subir o bajar en propiedades de inversión por este inmueble. | D23: Fila 1: 720.000,00-700.000,00 → 20.000,00 | E23: «Auditado en la cuenta» (esta hoja), «Importe en libros» (esta hoja) | F23: —
A24: Ajuste VR (resultados) | B24: '=IF('06_Valor_razonable'!H5="","",'06_Valor_razonable'!H5) | C24: Trae el ajuste de valor razonable no reconocido calculado en la hoja 06 (Valor razonable); en blanco cuando el inmueble no se mide a valor razonable. | D24: Fila 1: IF(20.000,00=""; ""; 20.000,00) → 20.000,00 | E24: hoja «Valor razonable» | F24: —
A25: Efecto modelo del costo | B25: '=IF('07_Modelo_costo'!C5="Sí",('07_Modelo_costo'!Q5-D5)*'04_Clasificacion'!K5,"") | C25: Si aplica el modelo del costo, resta el importe en libros de la medición al costo (hoja 07) y lo multiplica por la parte que es propiedad de inversión (hoja 04); en blanco en los demás casos. | D25: Fila 1: IF(«No»="Sí"; ((vacío)-700.000,00)*100,00 %; "") → (en blanco) | E25: «Importe en libros» (esta hoja), hoja «Modelo del costo: depreciación y deterioro», hoja «Clasificación» | F25: —
A26: Reclasificación | B26: '=IF('04_Clasificacion'!J5="","",'04_Clasificacion'!J5) | C26: Trae de la hoja 04 (Clasificación) el importe que sale de propiedades de inversión por uso propio, venta o uso mixto; en blanco si no hay reclasificación. | D26: Fila 1: IF((vacío)=""; ""; (vacío)) → (en blanco) | E26: hoja «Clasificación» | F26: —

Sheet 09_Transferencias
A1: Transferencias | H1: ⟵ Inicio | I1: ◀ Anterior | J1: Siguiente ▶
A2: Propiedades de inversión · Cliente de muestra S.A. · corte 2025-12-31
A4: Código | B4: Cambio de uso | C4: Fecha del cambio | D4: ¿En el ejercicio? | E4: Clasificación actual | F4: Libros a la fecha | G4: VR a la fecha | H4: Diferencia VR − libros | I4: Superávit de revaluación a la fecha | J4: Uso del superávit (disminución) | K4: A resultados | L4: A otro resultado integral | M4: Tratamiento | N4: Estado
A5: IP-08 | B5: PPE→PI | C5: 45930 | D5: =IF(C5="","Sin fecha",IF(AND(C5>='02_Parametros'!$B$6,C5<='02_Parametros'!$B$5),"Sí","No")) | E5: ='04_Clasificacion'!G12 | F5: =IF('03_Inmuebles'!V12="","",'03_Inmuebles'!V12) | G5: =IF('03_Inmuebles'!W12="","",'03_Inmuebles'!W12) | H5: =IF(OR('02_Parametros'!$B$8="Sí",'02_Parametros'!$B$11<>"valor_razonable",F5="",G5=""),"",G5-F5) | I5: =IF('03_Inmuebles'!X12="","",'03_Inmuebles'!X12) | J5: =IF(H5="","",IF(B5<>"PPE→PI",0,IF(H5>=0,0,IF(I5="","",MIN(I5,-H5))))) | K5: =IF(OR(H5="",J5=""),"",IF(B5="Inventario→PI",H5,IF(B5="PPE→PI",IF(H5>=0,0,H5+J5),0))) | L5: =IF(OR(H5="",J5=""),"",IF(B5="PPE→PI",IF(H5>=0,H5,-J5),0)) | M5: =IF('02_Parametros'!$B$8="Sí","PYMES 16.9: transferir solo cuando cumple o deja de cumplir la definición de PI; la sección 16 no regula la medición de la diferencia (juicio, sección 10)",IF('02_Parametros'!$B$11<>"valor_razonable","Modelo del costo: sin cambio del importe en libros (NIC 40.59)",IF(B5="PPE→PI","Revaluación NIC 16: el aumento a otro resultado integral (superávit de revaluación) y la disminución contra el superávit de ese inmueble, el exceso a resultados (NIC 40.61-62)",IF(B5="Inventario→PI","Diferencia a resultados (NIC 40.63)",IF(OR(B5="PI→PPE",B5="PI→Inventario"),"Costo atribuido = VR a la fecha del cambio (NIC 40.60)","Transferencia no reconocida"))))) | N5: =IF(AND(B5<>"PPE→PI",B5<>"Inventario→PI",B5<>"PI→PPE",B5<>"PI→Inventario"),"Transferencia no reconocida",IF(C5="","Sin tratamiento: falta la fecha del cambio",IF(AND('02_Parametros'!$B$8="No",'02_Parametros'!$B$11="valor_razonable",OR(F5="",G5="")),"Sin tratamiento: falta importe en libros o VR a la fecha",IF(AND(B5="PPE→PI",H5<>"",H5<0,I5=""),"Sin tratamiento: falta el superávit de revaluación a la fecha",IF(OR(AND(RIGHT(B5,2)="PI",'04_Clasificacion'!H12="No"),AND(LEFT(B5,2)="PI",'04_Clasificacion'!H12="Sí")),"Incoherente con la clasificación actual","Completa")))))
A6: IP-09 | B6: Inventario→PI | C6: 45792 | D6: =IF(C6="","Sin fecha",IF(AND(C6>='02_Parametros'!$B$6,C6<='02_Parametros'!$B$5),"Sí","No")) | E6: ='04_Clasificacion'!G13 | F6: =IF('03_Inmuebles'!V13="","",'03_Inmuebles'!V13) | G6: =IF('03_Inmuebles'!W13="","",'03_Inmuebles'!W13) | H6: =IF(OR('02_Parametros'!$B$8="Sí",'02_Parametros'!$B$11<>"valor_razonable",F6="",G6=""),"",G6-F6) | I6: =IF('03_Inmuebles'!X13="","",'03_Inmuebles'!X13) | J6: =IF(H6="","",IF(B6<>"PPE→PI",0,IF(H6>=0,0,IF(I6="","",MIN(I6,-H6))))) | K6: =IF(OR(H6="",J6=""),"",IF(B6="Inventario→PI",H6,IF(B6="PPE→PI",IF(H6>=0,0,H6+J6),0))) | L6: =IF(OR(H6="",J6=""),"",IF(B6="PPE→PI",IF(H6>=0,H6,-J6),0)) | M6: =IF('02_Parametros'!$B$8="Sí","PYMES 16.9: transferir solo cuando cumple o deja de cumplir la definición de PI; la sección 16 no regula la medición de la diferencia (juicio, sección 10)",IF('02_Parametros'!$B$11<>"valor_razonable","Modelo del costo: sin cambio del importe en libros (NIC 40.59)",IF(B6="PPE→PI","Revaluación NIC 16: el aumento a otro resultado integral (superávit de revaluación) y la disminución contra el superávit de ese inmueble, el exceso a resultados (NIC 40.61-62)",IF(B6="Inventario→PI","Diferencia a resultados (NIC 40.63)",IF(OR(B6="PI→PPE",B6="PI→Inventario"),"Costo atribuido = VR a la fecha del cambio (NIC 40.60)","Transferencia no reconocida"))))) | N6: =IF(AND(B6<>"PPE→PI",B6<>"Inventario→PI",B6<>"PI→PPE",B6<>"PI→Inventario"),"Transferencia no reconocida",IF(C6="","Sin tratamiento: falta la fecha del cambio",IF(AND('02_Parametros'!$B$8="No",'02_Parametros'!$B$11="valor_razonable",OR(F6="",G6="")),"Sin tratamiento: falta importe en libros o VR a la fecha",IF(AND(B6="PPE→PI",H6<>"",H6<0,I6=""),"Sin tratamiento: falta el superávit de revaluación a la fecha",IF(OR(AND(RIGHT(B6,2)="PI",'04_Clasificacion'!H13="No"),AND(LEFT(B6,2)="PI",'04_Clasificacion'!H13="Sí")),"Incoherente con la clasificación actual","Completa")))))
A7: TOTAL | H7: =SUM(H5:H6) | I7: =SUM(I5:I6) | J7: =SUM(J5:J6) | K7: =SUM(K5:K6) | L7: =SUM(L5:L6)
A9: ⓘ Cómo se calcula esta hoja
A10: Columna | B10: Fórmula (Excel) | C10: Cómo se calcula (sencillo) | D10: Ejemplo con números reales | E10: De dónde viene | F10: Norma
A11: ¿En el ejercicio? | B11: '=IF(C5="","Sin fecha",IF(AND(C5>='02_Parametros'!$B$6,C5<='02_Parametros'!$B$5),"Sí","No")) | C11: Revisa si la fecha del cambio de uso cae entre el inicio y el corte del ejercicio (hoja 02, Parámetros) y marca «Sí» o «No»; si falta la fecha, indica «Sin fecha». | D11: Fila 1: IF(«2025-09-30»=""; "Sin fecha"; IF(AND(«2025-09-30»>=«2025-01-01»; «2025-09-30»<=«2025-12-31»); "Sí"; "No")) → Sí | E11: «Fecha del cambio» (esta hoja), hoja «Parámetros y ruta por marco» | F11: —
A12: Clasificación actual | B12: '='04_Clasificacion'!G12 | C12: Trae de la hoja 04 (Clasificación) la clasificación auditada al corte del inmueble transferido, para compararla con el sentido del cambio de uso. | D12: Fila 1: «Propiedad de inversión» → Propiedad de inversión | E12: hoja «Clasificación» | F12: —
A13: Libros a la fecha | B13: '=IF('03_Inmuebles'!V12="","",'03_Inmuebles'!V12) | C13: Trae de la hoja 03 (Registro de inmuebles) el importe en libros a la fecha del cambio de uso; en blanco si no se informó. | D13: Fila 1: IF(125.000,00=""; ""; 125.000,00) → 125.000,00 | E13: hoja «Registro de inmuebles» | F13: —
A14: VR a la fecha | B14: '=IF('03_Inmuebles'!W12="","",'03_Inmuebles'!W12) | C14: Trae de la hoja 03 (Registro de inmuebles) el valor razonable a la fecha del cambio de uso; en blanco si no se informó. | D14: Fila 1: IF(205.000,00=""; ""; 205.000,00) → 205.000,00 | E14: hoja «Registro de inmuebles» | F14: —
A15: Diferencia VR − libros | B15: '=IF(OR('02_Parametros'!$B$8="Sí",'02_Parametros'!$B$11<>"valor_razonable",F5="",G5=""),"",G5-F5) | C15: Resta los libros del VR a la fecha del cambio. Solo se calcula en NIIF completas con la ruta de valor razonable (hoja 02) y con ambos datos; en PYMES, con modelo del costo o sin datos, queda en blanco. | D15: Fila 1: IF(OR(«No»="Sí"; «valor_razonable»<>"valor_razonable"; 125.000,00=""; 205.000,00=""); ""; 205.000,00-125.000,00) → 80.000,00 | E15: «Libros a la fecha» (esta hoja), «VR a la fecha» (esta hoja), hoja «Parámetros y ruta por marco» | F15: —
A16: Superávit de revaluación a la fecha | B16: '=IF('03_Inmuebles'!X12="","",'03_Inmuebles'!X12) | C16: Trae de la hoja 03 (Registro de inmuebles) el superávit de revaluación acumulado de este inmueble a la fecha del cambio; en blanco si no se informó. | D16: Fila 1: IF(30.000,00=""; ""; 30.000,00) → 30.000,00 | E16: hoja «Registro de inmuebles» | F16: —
A17: Uso del superávit (disminución) | B17: '=IF(H5="","",IF(B5<>"PPE→PI",0,IF(H5>=0,0,IF(I5="","",MIN(I5,-H5))))) | C17: Solo en cambios PPE→PI con disminución (diferencia negativa): usa el superávit del inmueble hasta cubrir la disminución, sin pasar de lo disponible. En otros cambios o con aumento es 0; en blanco si no hay diferencia o falta el superávit que se necesita. | D17: Fila 1: IF(80.000,00=""; ""; IF(«PPE→PI»<>"PPE→PI"; 0; IF(80.000,00>=0; 0; IF(30.000,00=""; ""; MIN(30.000,00; -80.000,00))))) → 0,00 | E17: «Diferencia VR − libros» (esta hoja), «Cambio de uso» (esta hoja), «Superávit de revaluación a la fecha» (esta hoja) | F17: —
A18: A resultados | B18: '=IF(OR(H5="",J5=""),"",IF(B5="Inventario→PI",H5,IF(B5="PPE→PI",IF(H5>=0,0,H5+J5),0))) | C18: Desde inventario, toda la diferencia va a resultados. Desde PPE, un aumento no va a resultados (0) y una disminución solo por el exceso no cubierto con el superávit (diferencia + uso del superávit); en los demás cambios es 0. | D18: Fila 1: IF(OR(80.000,00=""; 0,00=""); ""; IF(«PPE→PI»="Inventario→PI"; 80.000,00; IF(«PPE→PI»="PPE→PI"; IF(80.000,00>=0; 0; 80.000,00+0,00); 0))) → 0,00 | E18: «Diferencia VR − libros» (esta hoja), «Uso del superávit (disminución)» (esta hoja), «Cambio de uso» (esta hoja) | F18: —
A19: A otro resultado integral | B19: '=IF(OR(H5="",J5=""),"",IF(B5="PPE→PI",IF(H5>=0,H5,-J5),0)) | C19: Solo en cambios PPE→PI: el aumento va completo a otro resultado integral y, si es disminución, registra con signo negativo el superávit usado. En otros cambios es 0; en blanco si falta la diferencia o el uso del superávit. | D19: Fila 1: IF(OR(80.000,00=""; 0,00=""); ""; IF(«PPE→PI»="PPE→PI"; IF(80.000,00>=0; 80.000,00; -0,00); 0)) → 80.000,00 | E19: «Diferencia VR − libros» (esta hoja), «Uso del superávit (disminución)» (esta hoja), «Cambio de uso» (esta hoja) | F19: —
A20: Tratamiento | B20: '=IF('02_Parametros'!$B$8="Sí","PYMES 16.9: transferir solo cuando cumple o deja de cumplir la definición de PI; la sección 16 no regula la medición de la diferencia (juicio, sección 10)",IF('02_Parametros'!$B$11<>"valor_razonable","Modelo del costo: sin cambio del importe en libros (NIC 40.59)",IF(B5="PPE→PI","Revaluación NIC 16: el aumento a otro resultado integral (superávit de revaluación) y la disminución contra el superávit de ese inmueble, el exceso a resultados (NIC 40.61-62)",IF(B5="Inventario→PI","Diferencia a resultados (NIC 40.63)",IF(OR(B5="PI→PPE",B5="PI→Inventario"),"Costo atribuido = VR a la fecha del cambio (NIC 40.60)","Transferencia no reconocida"))))) | C20: Escribe el tratamiento contable que corresponde: en PYMES, la regla de transferencias de la sección 16; con modelo del costo, sin cambio del importe en libros; y con valor razonable, según el sentido del cambio (desde PPE, desde inventario o al salir de propiedades de inversión). | D20: Fila 1: IF(«No»="Sí"; "PYMES 16.9: transferir solo cuando cumple o deja de cumplir la definición de PI; la sección 16 no regula la medición de la diferencia (juicio, sección 10)"; IF(«valor_razonable»<>"valor_razonable"; "Modelo del costo: sin cambio del importe en libros (NIC 40.59)"; IF(«PPE→PI»="PPE→PI"; "Revaluación NIC 16: el aumento a otro resultado integral (superávit de revaluación) y la disminución contra el superávit de ese inmueble, el exceso a resultados (NIC 40.61-62)"; IF(«PPE→PI»="Inventario→PI"; "Diferencia a resultados (NIC 40.63)"; IF(OR(«PPE→PI»="PI→PPE"; «PPE→PI»="PI→Inventario"); "Costo atribuido = VR a la fecha del cambio (NIC 40.60)"; "Transferencia no reconocida"))))) → Revaluación NIC 16: el aumento a otro resultado integral (superávit de revaluación) y la disminución contra el superávit de ese inmueble, el exceso a resultados (NIC 40.61-62) | E20: «Cambio de uso» (esta hoja), hoja «Parámetros y ruta por marco» | F20: —
A21: Estado | B21: '=IF(AND(B5<>"PPE→PI",B5<>"Inventario→PI",B5<>"PI→PPE",B5<>"PI→Inventario"),"Transferencia no reconocida",IF(C5="","Sin tratamiento: falta la fecha del cambio",IF(AND('02_Parametros'!$B$8="No",'02_Parametros'!$B$11="valor_razonable",OR(F5="",G5="")),"Sin tratamiento: falta importe en libros o VR a la fecha",IF(AND(B5="PPE→PI",H5<>"",H5<0,I5=""),"Sin tratamiento: falta el superávit de revaluación a la fecha",IF(OR(AND(RIGHT(B5,2)="PI",'04_Clasificacion'!H12="No"),AND(LEFT(B5,2)="PI",'04_Clasificacion'!H12="Sí")),"Incoherente con la clasificación actual","Completa"))))) | C21: Revisa si la transferencia se puede tratar: señala si el tipo de cambio no se reconoce, si falta la fecha, los importes a la fecha o el superávit necesario, o si es incoherente con la clasificación actual de la hoja 04; si todo cuadra, indica «Completa». | D21: Fila 1: IF(AND(«PPE→PI»<>"PPE→PI"; «PPE→PI»<>"Inventario→PI"; «PPE→PI»<>"PI→PPE"; «PPE→PI»<>"PI→Inventario"); "Transferencia no reconocida"; IF(«2025-09-30»=""; "Sin tratamiento: falta la fecha del cambio"; IF(AND(«No»="No"; «valor_razonable»="valor_razonable"; OR(125.000,00=""; 205.000,00="")); "Sin tratamiento: falta importe en libros o VR a la fecha"; IF(AND(«PPE→PI»="PPE→PI"; 80.000,00<>""; 80.000,00<0; 30.000,00=""); "Sin tratamiento: falta el superávit de revaluación a la fecha"; IF(OR(AND(RIGHT(«PPE→PI»; 2)="PI"; «Sí»="No"); AND(LEFT(«PPE→PI»; 2)="PI"; «Sí»="Sí")); "Incoherente con la clasificación actual"; "Completa"))))) → Completa | E21: «Cambio de uso» (esta hoja), «Fecha del cambio» (esta hoja), «Libros a la fecha» (esta hoja), «VR a la fecha» (esta hoja), «Diferencia VR − libros» (esta hoja), «Superávit de revaluación a la fecha» (esta hoja), hoja «Parámetros y ruta por marco», hoja «Clasificación» | F21: —

Sheet 10_Superavit
A1: Historial del superávit de revaluación | H1: ⟵ Inicio | I1: ◀ Anterior | J1: Siguiente ▶
A2: Propiedades de inversión · Cliente de muestra S.A. · corte 2025-12-31
A4: Código | B4: Cambio de uso | C4: Fecha del cambio | D4: Saldo inicial en otro resultado integral | E4: Movimiento de la transferencia (aumento) | F4: Uso contra la disminución | G4: Saldo final | H4: Destino
A5: IP-08 | B5: ='09_Transferencias'!B5 | C5: 45930 | D5: =IF('03_Inmuebles'!X12="","",'03_Inmuebles'!X12) | E5: =IF(AND('02_Parametros'!$B$8="No",'02_Parametros'!$B$11<>"valor_razonable"),0,IF('09_Transferencias'!L5="","",MAX(0,'09_Transferencias'!L5))) | F5: =IF(AND('02_Parametros'!$B$8="No",'02_Parametros'!$B$11<>"valor_razonable"),0,IF('09_Transferencias'!J5="","",'09_Transferencias'!J5)) | G5: =IF(OR(D5="",E5="",F5=""),"",D5+E5-F5) | H5: =IF(G5="","",IF(G5>0.005,"Permanece en patrimonio: transferible a resultados acumulados, nunca a resultados del ejercicio (NIC 40.62 b ii y NIC 16.41)","Sin saldo de superávit al cierre"))
A6: TOTAL | D6: =SUM(D5:D5) | E6: =SUM(E5:E5) | F6: =SUM(F5:F5) | G6: =SUM(G5:G5)
A8: ⓘ Cómo se calcula esta hoja
A9: Columna | B9: Fórmula (Excel) | C9: Cómo se calcula (sencillo) | D9: Ejemplo con números reales | E9: De dónde viene | F9: Norma
A10: Cambio de uso | B10: '='09_Transferencias'!B5 | C10: Trae de la hoja 09 (Transferencias) el cambio de uso de este inmueble, para seguir su superávit de revaluación. | D10: Fila 1: «PPE→PI» → PPE→PI | E10: hoja «Transferencias» | F10: —
A11: Saldo inicial en otro resultado integral | B11: '=IF('03_Inmuebles'!X12="","",'03_Inmuebles'!X12) | C11: Trae de la hoja 03 (Registro de inmuebles) el superávit de revaluación acumulado del inmueble a la fecha del cambio; en blanco si no se informó. | D11: Fila 1: IF(30.000,00=""; ""; 30.000,00) → 30.000,00 | E11: hoja «Registro de inmuebles» | F11: —
A12: Movimiento de la transferencia (aumento) | B12: '=IF(AND('02_Parametros'!$B$8="No",'02_Parametros'!$B$11<>"valor_razonable"),0,IF('09_Transferencias'!L5="","",MAX(0,'09_Transferencias'!L5))) | C12: Toma lo que la hoja 09 (Transferencias) envió a otro resultado integral, solo si es positivo (un aumento). En NIIF completas con modelo del costo, o si no hubo transferencia, es 0. | D12: Fila 1: IF(AND(«No»="No"; «valor_razonable»<>"valor_razonable"); 0; IF(80.000,00=""; ""; MAX(0; 80.000,00))) → 80.000,00 | E12: hoja «Parámetros y ruta por marco», hoja «Transferencias» | F12: —
A13: Uso contra la disminución | B13: '=IF(AND('02_Parametros'!$B$8="No",'02_Parametros'!$B$11<>"valor_razonable"),0,IF('09_Transferencias'!J5="","",'09_Transferencias'!J5)) | C13: Trae de la hoja 09 (Transferencias) el superávit usado para absorber una disminución. En NIIF completas con modelo del costo, o si no hubo transferencia, es 0. | D13: Fila 1: IF(AND(«No»="No"; «valor_razonable»<>"valor_razonable"); 0; IF(0,00=""; ""; 0,00)) → 0,00 | E13: hoja «Parámetros y ruta por marco», hoja «Transferencias» | F13: —
A14: Saldo final | B14: '=IF(OR(D5="",E5="",F5=""),"",D5+E5-F5) | C14: Saldo inicial más el aumento menos el uso contra disminuciones: es el superávit que queda en patrimonio al cierre. En blanco si falta alguno de los tres datos. | D14: Fila 1: IF(OR(30.000,00=""; 80.000,00=""; 0,00=""); ""; 30.000,00+80.000,00-0,00) → 110.000,00 | E14: «Saldo inicial en otro resultado integral» (esta hoja), «Movimiento de la transferencia (aumento)» (esta hoja), «Uso contra la disminución» (esta hoja) | F14: —
A15: Destino | B15: '=IF(G5="","",IF(G5>0.005,"Permanece en patrimonio: transferible a resultados acumulados, nunca a resultados del ejercicio (NIC 40.62 b ii y NIC 16.41)","Sin saldo de superávit al cierre")) | C15: Si queda saldo de superávit al cierre, recuerda que permanece en patrimonio y solo puede pasar a resultados acumulados, nunca al resultado del ejercicio; si no queda saldo, lo indica. | D15: Fila 1: IF(110.000,00=""; ""; IF(110.000,00>0.005; "Permanece en patrimonio: transferible a resultados acumulados, nunca a resultados del ejercicio (NIC 40.62 b ii y NIC 16.41)"; "Sin saldo de superávit al cierre")) → Permanece en patrimonio: transferible a resultados acumulados, nunca a resultados del ejercicio (NIC 40.62 b ii y NIC 16.41) | E15: «Saldo final» (esta hoja) | F15: —

Sheet 11_Alquileres
A1: Ingresos por alquiler | H1: ⟵ Inicio | I1: ◀ Anterior | J1: Siguiente ▶
A2: Propiedades de inversión · Cliente de muestra S.A. · corte 2025-12-31
A4: Código | B4: Uso actual | C4: Ingresos según contratos | D4: Ingresos registrados | E4: Diferencia
A5: IP-01 | B5: ='03_Inmuebles'!C5 | C5: =IF('03_Inmuebles'!R5="","",'03_Inmuebles'!R5) | D5: =IF('03_Inmuebles'!S5="","",'03_Inmuebles'!S5) | E5: =IF(OR(C5="",D5=""),"",C5-D5)
A6: IP-02 | B6: ='03_Inmuebles'!C6 | C6: =IF('03_Inmuebles'!R6="","",'03_Inmuebles'!R6) | D6: =IF('03_Inmuebles'!S6="","",'03_Inmuebles'!S6) | E6: =IF(OR(C6="",D6=""),"",C6-D6)
A7: IP-03 | B7: ='03_Inmuebles'!C7 | C7: =IF('03_Inmuebles'!R7="","",'03_Inmuebles'!R7) | D7: =IF('03_Inmuebles'!S7="","",'03_Inmuebles'!S7) | E7: =IF(OR(C7="",D7=""),"",C7-D7)
A8: IP-04 | B8: ='03_Inmuebles'!C8 | C8: =IF('03_Inmuebles'!R8="","",'03_Inmuebles'!R8) | D8: =IF('03_Inmuebles'!S8="","",'03_Inmuebles'!S8) | E8: =IF(OR(C8="",D8=""),"",C8-D8)
A9: IP-05 | B9: ='03_Inmuebles'!C9 | C9: =IF('03_Inmuebles'!R9="","",'03_Inmuebles'!R9) | D9: =IF('03_Inmuebles'!S9="","",'03_Inmuebles'!S9) | E9: =IF(OR(C9="",D9=""),"",C9-D9)
A10: IP-06 | B10: ='03_Inmuebles'!C10 | C10: =IF('03_Inmuebles'!R10="","",'03_Inmuebles'!R10) | D10: =IF('03_Inmuebles'!S10="","",'03_Inmuebles'!S10) | E10: =IF(OR(C10="",D10=""),"",C10-D10)
A11: IP-07 | B11: ='03_Inmuebles'!C11 | C11: =IF('03_Inmuebles'!R11="","",'03_Inmuebles'!R11) | D11: =IF('03_Inmuebles'!S11="","",'03_Inmuebles'!S11) | E11: =IF(OR(C11="",D11=""),"",C11-D11)
A12: IP-08 | B12: ='03_Inmuebles'!C12 | C12: =IF('03_Inmuebles'!R12="","",'03_Inmuebles'!R12) | D12: =IF('03_Inmuebles'!S12="","",'03_Inmuebles'!S12) | E12: =IF(OR(C12="",D12=""),"",C12-D12)
A13: IP-09 | B13: ='03_Inmuebles'!C13 | C13: =IF('03_Inmuebles'!R13="","",'03_Inmuebles'!R13) | D13: =IF('03_Inmuebles'!S13="","",'03_Inmuebles'!S13) | E13: =IF(OR(C13="",D13=""),"",C13-D13)
A14: IP-10 | B14: ='03_Inmuebles'!C14 | C14: =IF('03_Inmuebles'!R14="","",'03_Inmuebles'!R14) | D14: =IF('03_Inmuebles'!S14="","",'03_Inmuebles'!S14) | E14: =IF(OR(C14="",D14=""),"",C14-D14)
A15: TOTAL | C15: =SUM(C5:C14) | D15: =SUM(D5:D14) | E15: =SUM(E5:E14)
A17: ⓘ Cómo se calcula esta hoja
A18: Columna | B18: Fórmula (Excel) | C18: Cómo se calcula (sencillo) | D18: Ejemplo con números reales | E18: De dónde viene | F18: Norma
A19: Uso actual | B19: '='03_Inmuebles'!C5 | C19: Trae el uso actual del inmueble de la hoja 03 (Registro de inmuebles), para ver cuáles deberían generar ingresos por alquiler. | D19: Fila 1: «Alquiler» → Alquiler | E19: hoja «Registro de inmuebles» | F19: —
A20: Ingresos según contratos | B20: '=IF('03_Inmuebles'!R5="","",'03_Inmuebles'!R5) | C20: Trae de la hoja 03 (Registro de inmuebles) los ingresos por alquiler del año según los contratos; en blanco si no se informaron. | D20: Fila 1: IF(48.000,00=""; ""; 48.000,00) → 48.000,00 | E20: hoja «Registro de inmuebles» | F20: —
A21: Ingresos registrados | B21: '=IF('03_Inmuebles'!S5="","",'03_Inmuebles'!S5) | C21: Trae de la hoja 03 (Registro de inmuebles) los ingresos por alquiler que el cliente registró en contabilidad; en blanco si no hay dato. | D21: Fila 1: IF(48.000,00=""; ""; 48.000,00) → 48.000,00 | E21: hoja «Registro de inmuebles» | F21: —
A22: Diferencia | B22: '=IF(OR(C5="",D5=""),"",C5-D5) | C22: Resta los ingresos registrados de los ingresos según contratos; queda en blanco si falta alguno de los dos. | D22: Fila 1: IF(OR(48.000,00=""; 48.000,00=""); ""; 48.000,00-48.000,00) → 0,00 | E22: «Ingresos según contratos» (esta hoja), «Ingresos registrados» (esta hoja) | F22: —

Sheet 12_Bajas
A1: Bajas | H1: ⟵ Inicio | I1: ◀ Anterior | J1: Siguiente ▶
A2: Propiedades de inversión · Cliente de muestra S.A. · corte 2025-12-31
A4: Código | B4: Descripción | C4: Fecha de baja | D4: Producto neto | E4: Importe en libros | F4: Resultado recalculado | G4: Resultado registrado | H4: Diferencia
A5: B-01 | B5: Local Quevedo | C5: 45900 | D5: 130000 | E5: 110000 | F5: =D5-E5 | G5: 20000 | H5: =IF(G5="","",F5-G5)
A6: B-02 | B6: Terreno Manta | C6: 45991 | D6: 85000 | E6: 95000 | F6: =D6-E6 | G6: 0 | H6: =IF(G6="","",F6-G6)
A7: TOTAL | D7: =SUM(D5:D6) | E7: =SUM(E5:E6) | F7: =SUM(F5:F6) | H7: =SUM(H5:H6)
A9: ⓘ Cómo se calcula esta hoja
A10: Columna | B10: Fórmula (Excel) | C10: Cómo se calcula (sencillo) | D10: Ejemplo con números reales | E10: De dónde viene | F10: Norma
A11: Resultado recalculado | B11: '=D5-E5 | C11: Resta el importe en libros a la fecha de baja del producto neto de la venta: ganancia (positivo) o pérdida (negativo) que debió reconocerse. | D11: Fila 1: 130.000,00-110.000,00 → 20.000,00 | E11: «Producto neto» (esta hoja), «Importe en libros» (esta hoja) | F11: —
A12: Diferencia | B12: '=IF(G5="","",F5-G5) | C12: Resta el resultado registrado por el cliente del resultado recalculado; en blanco si el cliente no informó su resultado. | D12: Fila 1: IF(20.000,00=""; ""; 20.000,00-20.000,00) → 0,00 | E12: «Resultado registrado» (esta hoja), «Resultado recalculado» (esta hoja) | F12: —

Sheet 13_Conciliacion
A1: Sumaria y conciliación | H1: ⟵ Inicio | I1: ◀ Anterior | J1: Siguiente ▶
A2: Propiedades de inversión · Cliente de muestra S.A. · corte 2025-12-31
A4: Concepto | B4: Importe
A5: Saldo según el mayor | B5: =IF('02_Parametros'!$B$13="",SUM('03_Inmuebles'!$Q$5:$Q$14),'02_Parametros'!$B$13)
A6: Importe en libros según el detalle | B6: =SUM('03_Inmuebles'!$Q$5:$Q$14)
A7: Diferencia detalle − mayor | B7: =B6-B5
A8: (+) Ajuste de valor razonable no reconocido | B8: =SUM('06_Valor_razonable'!$H$5:$H$14)
A9: (+) Efecto de la medición al costo | B9: =SUM('08_Medicion'!$H$5:$H$14)
A10: (−) Reclasificación fuera de propiedades de inversión | B10: =SUM('04_Clasificacion'!$J$5:$J$14)
A11: Propiedades de inversión auditadas (puente desde el detalle) | B11: =B6+B8+B9+B10
A12: Control: medición auditada según 08 | B12: =SUM('08_Medicion'!$E$5:$E$14)
A13: Diferencia de control (debe ser 0) | B13: =B11-B12
A14: Ajuste propuesto (auditado − mayor) | B14: =B12-B5
A16: ⓘ Cómo se calcula esta hoja
A17: Columna | B17: Fórmula (Excel) | C17: Cómo se calcula (sencillo) | D17: Ejemplo con números reales | E17: De dónde viene | F17: Norma
A18: Importe | B18: '=IF('02_Parametros'!$B$13="",SUM('03_Inmuebles'!$Q$5:$Q$14),'02_Parametros'!$B$13) | C18: Arma el puente concepto por concepto: compara el saldo del mayor (hoja 02, o la suma del detalle si no se informó) con el importe en libros de la hoja 03, le suma los ajustes de las hojas 06, 08 y 04, controla que el puente iguale la medición auditada de la hoja 08 y calcula el ajuste propuesto (auditado − mayor). | D18: Fila 1: IF(2.785.000,00=""; SUM([«Importe en libros» de «Registro de inmuebles», 10 filas]); 2.785.000,00) → 2.785.000,00 | E18: hoja «Parámetros y ruta por marco», hoja «Registro de inmuebles» | F18: —

Sheet 14_Problemas
A1: Problemas encontrados | H1: ⟵ Inicio | I1: ◀ Anterior | J1: Siguiente ▶
A2: Propiedades de inversión · Cliente de muestra S.A. · corte 2025-12-31
A4: Código | B4: Descripción | C4: Importe
A5: MAL_CLASIFICADO | B5: Inmuebles que no son propiedad de inversión: IP-05 (Inventario (NIC 2)). Reclasificar 150.000,00 fuera de la cuenta y medirlos con su norma (NIC 40.9 y 40.10; si venían a VR, el costo atribuido es el VR a la fecha del cambio, 40.60). | C5: -216500
A6: USO_MIXTO_SEPARADO | B6: Uso mixto separado en partes: IP-04 (35,00 % de uso propio). NIC 40.10: las partes pueden venderse por separado, así que se contabilizan por separado. La parte de uso propio se reclasifica a PPE por 66.500,00 y la de inversión se mide como propiedad de inversión. La herramienta separa a prorrata del % de uso propio: divida la fila del anexo y mida cada parte por separado. | C6: -66500
A7: VR_NO_RECONOCIDO | B7: Diferencia entre el valor razonable al corte y el importe en libros no reconocida en IP-01, IP-03, IP-04, IP-06, IP-08, IP-09: 48.000,00, a resultados del ejercicio (NIC 40.35). | C7: 48000
A8: VR_NO_FIABLE | B8: IP-07 sin valor razonable con modelo de VR: se miden al costo. Solo procede si al adquirirlo o cambiar su uso el VR no podía medirse de forma fiable y continua (NIC 40.53); el resto sigue a VR (40.54) y se revela 78. | C8: 0
A9: SIN_FUENTE_VR | B9: Valor razonable sin fuente ni tasador en IP-09: documente la tasación (NIC 40.32 y 75 e; NIIF 13) y evalúe el trabajo del experto (NIA 500.8; NIA 620 si el experto es del auditor). | C9: 0
A10: SIN_NIVEL_VR | B10: Falta el nivel de la jerarquía del VR en IP-09 (NIIF 13.72 y 93 b). | C10: 0
A11: COSTO_INICIAL | B11: El costo registrado no es precio de compra + desembolsos directamente atribuibles en IP-06: 12.000,00 (NIC 40.20-21). | C11: 12000
A12: DEP_DIFERENCIA | B12: La depreciación acumulada recalculada difiere de la registrada en IP-07: 3.000,00 (NIC 40.56 → NIC 16). | C12: 3000
A13: DETERIORO | B13: Modelo del costo: el importe recuperable es menor que el valor neto en IP-07: deterioro 22.000,00 (NIC 36.9 y 59). | C13: 22000
A14: ALQUILER_NO_CONCILIADO | B14: Ingresos por alquiler según contratos distintos de los registrados en IP-03, IP-06: 8.000,00 (NIIF 16.81 y NIC 40.75 f). | C14: 8000
A15: ALQUILER_SIN_CONTRATO | B15: Inmuebles en alquiler sin ingresos según contrato en IP-09: no se concilian las rentas. | C15: 0
A16: TRANSFERENCIA_SIN_TRATAMIENTO | B16: Cambios de uso sin tratamiento completo: IP-09 (Sin tratamiento: falta importe en libros o VR a la fecha) (NIC 40.57-65). | C16: 0
... A22: AJUSTE | B22: Las propiedades de inversión auditadas (2.586.500,00) difieren del mayor (2.785.000,00). | C22: -198500

Sheet 13_Conclusion
A1: Conclusión | H1: ⟵ Inicio | I1: ◀ Anterior | J1: Siguiente ▶
A2: Propiedades de inversión · Cliente de muestra S.A. · corte 2025-12-31
A4: Concepto | B4: Detalle
A5: Conciliación con el mayor | B5: Población None · mayor None · diferencia None
A6: Evaluación de excepciones
A7: Análisis
A8: Conclusión

Sheet 14_Control_Revision
A1: Control de revisión | H1: ⟵ Inicio | I1: ◀ Anterior
A2: Propiedades de inversión · Cliente de muestra S.A. · corte 2025-12-31
A4: Fecha | B4: Acción | C4: Estado anterior | D4: Estado nuevo | E4: Actor | F4: Comentario
