Workbook

Sheet 00_Inicio
B2: AuditConsulting Auditores Cía. Ltda. · AUDIT-IA
B4: Provisiones y contingencias
B6: Cliente | C6: Cliente de muestra S.A. | D6: RUC | E6: 1790000000001
B7: Marco contable | C7: NIIF completas | D7: Fecha de corte | E7: 2025-12-31
B8: Preparó | C8: Ejercicio modelo | D8: Revisó | E8: Pendiente
B10: INDICADORES CLAVE
B11: Ajuste propuesto (requerida − libros) | C11: Problemas encontrados
B12: 38758.9 | C12: 21
B15: IR A LA CÉDULA
B16: Carátula | C16: Programa | D16: Base técnica | E16: Resumen
B17: Parámetros | C17: Provisiones y contingencias (datos del cliente) | D17: Garantías (datos del cliente) | E17: Obligación presente y probabilidad
B18: Mejor estimación | C18: Valor presente (descuento) | D18: Actualización financiera (reversión del descuento) | E18: Litigios y cartas de abogados
B19: Garantías: cálculo | C19: Contratos onerosos | D19: Desmantelamiento | E19: Provisión requerida vs libros
B20: Contingencias a revelar | C20: Ajustes propuestos y conciliación | D20: Problemas encontrados | E20: Conclusión
B21: Control de revisión
B23: PANORAMA | N23: Datos de los gráficos (fórmulas a las cédulas)
N24: Cifras del resumen | O24: Importe (USD)
N25: ='01_Resumen'!A5 | O25: ='01_Resumen'!B5
N26: ='01_Resumen'!A6 | O26: ='01_Resumen'!B6
N27: ='01_Resumen'!A7 | O27: ='01_Resumen'!B7
N28: ='01_Resumen'!A8 | O28: ='01_Resumen'!B8
N29: ='01_Resumen'!A9 | O29: ='01_Resumen'!B9
N30: ='01_Resumen'!A10 | O30: ='01_Resumen'!B10
N31: ='01_Resumen'!A11 | O31: ='01_Resumen'!B11
N32: ='01_Resumen'!A12 | O32: ='01_Resumen'!B12
N33: ='01_Resumen'!A13 | O33: ='01_Resumen'!B13
N34: ='01_Resumen'!A14 | O34: ='01_Resumen'!B14
N35: ='01_Resumen'!A15 | O35: ='01_Resumen'!B15
N36: ='01_Resumen'!A16 | O36: ='01_Resumen'!B16
N37: ='01_Resumen'!A17 | O37: ='01_Resumen'!B17
N39: Hallazgos de mayor impacto | O39: Importe (USD)
N40: Diferencia provision (×5) | O40: =SUMIFS('16_Problemas'!$C$5:$C$25,'16_Problemas'!$A$5:$A$25,"DIFERENCIA_PROVISION",'16_Problemas'!$C$5:$C$25,">0")-SUMIFS('16_Problemas'!$C$5:$C$25,'16_Problemas'!$A$5:$A$25,"DIFERENCIA_PROVISION",'16_Problemas'!$C$5:$C$25,"<0")
N41: Diferencia carta abogado (×2) | O41: =SUMIFS('16_Problemas'!$C$5:$C$25,'16_Problemas'!$A$5:$A$25,"DIFERENCIA_CARTA_ABOGADO",'16_Problemas'!$C$5:$C$25,">0")-SUMIFS('16_Problemas'!$C$5:$C$25,'16_Problemas'!$A$5:$A$25,"DIFERENCIA_CARTA_ABOGADO",'16_Problemas'!$C$5:$C$25,"<0")
N42: Descuento no aplicado | O42: =SUMIFS('16_Problemas'!$C$5:$C$25,'16_Problemas'!$A$5:$A$25,"DESCUENTO_NO_APLICADO",'16_Problemas'!$C$5:$C$25,">0")-SUMIFS('16_Problemas'!$C$5:$C$25,'16_Problemas'!$A$5:$A$25,"DESCUENTO_NO_APLICADO",'16_Problemas'!$C$5:$C$25,"<0")
N43: Provision no registrada | O43: =SUMIFS('16_Problemas'!$C$5:$C$25,'16_Problemas'!$A$5:$A$25,"PROVISION_NO_REGISTRADA",'16_Problemas'!$C$5:$C$25,">0")-SUMIFS('16_Problemas'!$C$5:$C$25,'16_Problemas'!$A$5:$A$25,"PROVISION_NO_REGISTRADA",'16_Problemas'!$C$5:$C$25,"<0")
N44: Activo contingente reconocido | O44: =SUMIFS('16_Problemas'!$C$5:$C$25,'16_Problemas'!$A$5:$A$25,"ACTIVO_CONTINGENTE_RECONOCIDO",'16_Problemas'!$C$5:$C$25,">0")-SUMIFS('16_Problemas'!$C$5:$C$25,'16_Problemas'!$A$5:$A$25,"ACTIVO_CONTINGENTE_RECONOCIDO",'16_Problemas'!$C$5:$C$25,"<0")
N45: Activo contingente sin revelar | O45: =SUMIFS('16_Problemas'!$C$5:$C$25,'16_Problemas'!$A$5:$A$25,"ACTIVO_CONTINGENTE_SIN_REVELAR",'16_Problemas'!$C$5:$C$25,">0")-SUMIFS('16_Problemas'!$C$5:$C$25,'16_Problemas'!$A$5:$A$25,"ACTIVO_CONTINGENTE_SIN_REVELAR",'16_Problemas'!$C$5:$C$25,"<0")
N46: Provision posible o remota | O46: =SUMIFS('16_Problemas'!$C$5:$C$25,'16_Problemas'!$A$5:$A$25,"PROVISION_POSIBLE_O_REMOTA",'16_Problemas'!$C$5:$C$25,">0")-SUMIFS('16_Problemas'!$C$5:$C$25,'16_Problemas'!$A$5:$A$25,"PROVISION_POSIBLE_O_REMOTA",'16_Problemas'!$C$5:$C$25,"<0")
N47: Otros (7 tipos) | O47: =SUMIF('16_Problemas'!$C$5:$C$25,">0")-SUMIF('16_Problemas'!$C$5:$C$25,"<0")-((SUMIFS('16_Problemas'!$C$5:$C$25,'16_Problemas'!$A$5:$A$25,"DIFERENCIA_PROVISION",'16_Problemas'!$C$5:$C$25,">0")-SUMIFS('16_Problemas'!$C$5:$C$25,'16_Problemas'!$A$5:$A$25,"DIFERENCIA_PROVISION",'16_Problemas'!$C$5:$C$25,"<0"))+(SUMIFS('16_Problemas'!$C$5:$C$25,'16_Problemas'!$A$5:$A$25,"DIFERENCIA_CARTA_ABOGADO",'16_Problemas'!$C$5:$C$25,">0")-SUMIFS('16_Problemas'!$C$5:$C$25,'16_Problemas'!$A$5:$A$25,"DIFERENCIA_CARTA_ABOGADO",'16_Problemas'!$C$5:$C$25,"<0"))+(SUMIFS('16_Problemas'!$C$5:$C$25,'16_Problemas'!$A$5:$A$25,"DESCUENTO_NO_APLICADO",'16_Problemas'!$C$5:$C$25,">0")-SUMIFS('16_Problemas'!$C$5:$C$25,'16_Problemas'!$A$5:$A$25,"DESCUENTO_NO_APLICADO",'16_Problemas'!$C$5:$C$25,"<0"))+(SUMIFS('16_Problemas'!$C$5:$C$25,'16_Problemas'!$A$5:$A$25,"PROVISION_NO_REGISTRADA",'16_Problemas'!$C$5:$C$25,">0")-SUMIFS('16_Problemas'!$C$5:$C$25,'16_Problemas'!$A$5:$A$25,"PROVISION_NO_REGISTRADA",'16_Problemas'!$C$5:$C$25,"<0"))+(SUMIFS('16_Problemas'!$C$5:$C$25,'16_Problemas'!$A$5:$A$25,"ACTIVO_CONTINGENTE_RECONOCIDO",'16_Problemas'!$C$5:$C$25,">0")-SUMIFS('16_Problemas'!$C$5:$C$25,'16_Problemas'!$A$5:$A$25,"ACTIVO_CONTINGENTE_RECONOCIDO",'16_Problemas'!$C$5:$C$25,"<0"))+(SUMIFS('16_Problemas'!$C$5:$C$25,'16_Problemas'!$A$5:$A$25,"ACTIVO_CONTINGENTE_SIN_REVELAR",'16_Problemas'!$C$5:$C$25,">0")-SUMIFS('16_Problemas'!$C$5:$C$25,'16_Problemas'!$A$5:$A$25,"ACTIVO_CONTINGENTE_SIN_REVELAR",'16_Problemas'!$C$5:$C$25,"<0"))+(SUMIFS('16_Problemas'!$C$5:$C$25,'16_Problemas'!$A$5:$A$25,"PROVISION_POSIBLE_O_REMOTA",'16_Problemas'!$C$5:$C$25,">0")-SUMIFS('16_Problemas'!$C$5:$C$25,'16_Problemas'!$A$5:$A$25,"PROVISION_POSIBLE_O_REMOTA",'16_Problemas'!$C$5:$C$25,"<0")))

Sheet 00_Caratula
A1: Carátula | H1: ⟵ Inicio | J1: Siguiente ▶
A2: Provisiones y contingencias · Cliente de muestra S.A. · corte 2025-12-31
A4: Concepto | B4: Detalle
A5: Firma | B5: AuditConsulting Auditores Cía. Ltda.
A6: Cliente | B6: Cliente de muestra S.A.
A7: RUC | B7: 1790000000001
A8: Ejercicio | B8: 2025
A9: Fecha de corte | B9: 2025-12-31
A10: Marco contable | B10: NIIF completas
A11: Herramienta | B11: Provisiones y contingencias
A12: Rubro | B12: Provisiones
A13: Motor | B13: provisiones_contingencias 1.0
A14: Versión del papel | B14: v1
A15: Estado | B15: MUESTRA
... A17: Revisó | B17: Pendiente
A18: Aprobó
A19: Fecha de aprobación
A20: Huella de la ejecución (SHA-256)

Sheet 00_Programa
A1: Programa | H1: ⟵ Inicio | I1: ◀ Anterior | J1: Siguiente ▶
A2: Provisiones y contingencias · Cliente de muestra S.A. · corte 2025-12-31
A4: Código | B4: Objetivo | C4: Afirmación | D4: Procedimiento | E4: Evidencia | F4: Criterio | G4: Referencia
A5: PROV-01 | B5: Obligación presente | C5: Existencia | D5: Revisar el suceso que origina cada partida y la existencia de obligación legal o implícita | E5: Contratos, demandas, actas | F5: NIC 37.14–16; PYMES 21.4–21.6 | G5: NIC 37 · Sección 21
A6: PROV-02 | B6: Probabilidad | C6: Existencia / Integridad | D6: Comparar la evaluación del abogado y de la gerencia y clasificar (probable/posible/remota) | E6: Cartas de abogados, informe de gerencia | F6: Probable = más probable que no (NIC 37.23) | G6: NIC 37.23 · NIA 501
A7: PROV-03 | B7: Mejor estimación | C7: Valoración | D7: Recalcular valor esperado, desenlace más probable o punto medio y comparar con libros | E7: Escenarios, rango, cálculo de la gerencia | F7: NIC 37.36–40; PYMES 21.7 | G7: NIC 37 · NIA 540
A8: PROV-04 | B8: Cartas de abogados y litigios | C8: Integridad | D8: Enviar cartas a los abogados, obtener respuesta posterior al corte y conciliar importes con libros | E8: Respuestas de abogados | F8: Respuesta recibida y concordante | G8: NIA 501 · NIA 560
A9: PROV-05 | B9: Garantías | C9: Valoración | D9: Recalcular unidades con garantía × % de reclamos × costo medio | E9: Ventas con garantía, reclamos históricos | F9: NIC 37.24, 39; PYMES 21A.4 | G9: NIC 37 · Sección 21
A10: PROV-06 | B10: Contratos onerosos | C10: Integridad / Valoración | D10: Restar los beneficios esperados del costo de cumplir, comparar con la penalización y provisionar el menor (previo deterioro de activos, NIC 37.69) | E10: Contratos, presupuestos, ingresos esperados del contrato | F10: NIC 37.66–69; PYMES 21A.2 | G10: NIC 37
A11: PROV-07 | B11: Desmantelamiento y descuento | C11: Valoración / Presentación | D11: Recalcular el valor presente a la tasa antes de impuestos y la reversión del descuento del período | E11: Estudio técnico, tasas | F11: NIC 37.45–47, 60; CINIIF 1; PYMES 21.7, 21.11 | G11: NIC 37 · CINIIF 1
A12: PROV-08 | B12: Contingencias y revelación | C12: Presentación y revelación | D12: Listar pasivos y activos contingentes y verificar su revelación; obtener manifestaciones escritas | E12: Notas, carta de manifestaciones | F12: NIC 37.86, 89; PYMES 21.15–21.16 | G12: NIC 37 · NIA 580

Sheet 00_Fuentes
A1: Base técnica | H1: ⟵ Inicio | I1: ◀ Anterior | J1: Siguiente ▶
A2: Provisiones y contingencias · Cliente de muestra S.A. · corte 2025-12-31
A4: Categoría | B4: Documento | C4: Párrafos | D4: URL | E4: Verificada
A5: NIA · NIA 501 | B5: Litigios y reclamaciones: indagación y carta a los abogados externos; negativa o falta de respuesta → opinión modificada (NIA 705). | C5: párr. 9–12
A6: NIA · NIA 540 (Revisada) | B6: Estimaciones contables: método, supuestos (probabilidades, tasa) y datos; rango del auditor. | C6: párr. 13, 22–26, 28–29 y 37
A7: NIA · NIA 560 | B7: Hechos posteriores: sentencias o acuerdos después del corte que confirman la obligación. | C7: párr. 6–9
A8: NIA · NIA 501 y NIA 580 | B8: Manifestaciones escritas sobre litigios, reclamaciones y contingencias conocidas. | C8: NIA 501 párr. 12; NIA 580 párr. 13
A9: NIA · NIA 500 | B9: Exactitud e integridad del detalle de provisiones frente al mayor. | C9: párr. 9

Sheet 01_Resumen
A1: Resumen | H1: ⟵ Inicio | I1: ◀ Anterior | J1: Siguiente ▶
A2: Provisiones y contingencias · Cliente de muestra S.A. · corte 2025-12-31
A4: Concepto | B4: Importe
A5: Provisiones registradas en libros | B5: ='15_Ajustes'!B5
A6: Provisión requerida (NIC 37 · Secc. 21) | B6: ='15_Ajustes'!B6
A7: Ajuste propuesto (requerida − libros) | B7: ='15_Ajustes'!B7
A8: Efecto del descuento a valor presente | B8: ='15_Ajustes'!B8
A9: Reversión del descuento calculada | B9: ='15_Ajustes'!B9
A10: Reversión del descuento registrada | B10: ='15_Ajustes'!B10
A11: Reversión: calculada − registrada (reclasificación) | B11: ='15_Ajustes'!B11
A12: Garantías calculadas | B12: ='15_Ajustes'!B12
A13: Pasivos contingentes a revelar (efecto estimado) | B13: ='15_Ajustes'!B13
A14: Pasivos contingentes sin revelar | B14: ='15_Ajustes'!B14
A15: Activo contingente reconocido indebidamente | B15: ='15_Ajustes'!B15
A16: Ajuste del activo contingente | B16: ='15_Ajustes'!B16
A17: Diferencia detalle − mayor | B17: ='15_Ajustes'!B18
A19: ⓘ Cómo se calcula esta hoja
A20: Columna | B20: Fórmula (Excel) | C20: Cómo se calcula (sencillo) | D20: Ejemplo con números reales | E20: De dónde viene | F20: Norma
A21: Importe | B21: '='15_Ajustes'!B5 | C21: Trae cada importe de la hoja 15 (Ajustes propuestos y conciliación), concepto por concepto, para que el resumen y el detalle coincidan siempre. | D21: Fila 1: 725.000,00 → 725.000,00 | E21: hoja «Ajustes propuestos y conciliación» | F21: —

Sheet 02_Parametros
A1: Parámetros | H1: ⟵ Inicio | I1: ◀ Anterior | J1: Siguiente ▶
A2: Provisiones y contingencias · Cliente de muestra S.A. · corte 2025-12-31
A4: Parámetro | B4: Valor | C4: Sustento
A5: Corte del ejercicio | B5: 46022 | C5: Ficha del encargo
A6: Marco contable | B6: NIIF completas | C6: Mismo cálculo en NIIF completas (NIC 37) y PYMES (Sección 21): no se enruta
A7: Edición PYMES | C7: 2015 y 2025: misma numeración en los párrafos citados y sin diferencias de cálculo (leído en PYMES 2015 ES y 2025 EN)
A8: Tasa de descuento por defecto (%) | B8: 8 | C8: Tasa antes de impuestos, riesgos específicos (NIC 37.47; PYMES 21.7)
A9: Descontar si el plazo supera (años) | B9: 1 | C9: Efecto material del valor temporal (NIC 37.45–46): juicio del auditor
A10: Materialidad (importe) | B10: 50000 | C10: Plan de auditoría (NIA 320)
A11: Tolerancia (importe) | B11: 1 | C11: Materialidad de ejecución / diferencias triviales
A12: Mayor: provisiones al corte | B12: 730000 | C12: Mayor contable

Sheet 03_Provisiones
A1: Provisiones y contingencias (datos del cliente) | H1: ⟵ Inicio | I1: ◀ Anterior | J1: Siguiente ▶
A2: Provisiones y contingencias · Cliente de muestra S.A. · corte 2025-12-31
A4: Código de la provisión o contingencia | B4: Descripción | C4: Tipo (Litigio/Garantía/Oneroso/Desmantelamiento/Reestructuración/Otro/Activo contingente) | D4: ¿Existe obligación presente? (Sí/No) | E4: Probabilidad según el abogado (Probable/Posible/Remota) | F4: Probabilidad según la gerencia (Probable/Posible/Remota) | G4: Importe según la carta del abogado | H4: Estimación de la gerencia (sin descontar) | I4: Importe mínimo del rango | J4: Importe máximo del rango | K4: Escenario 1: importe | L4: Escenario 1: probabilidad (%) | M4: Escenario 2: importe | N4: Escenario 2: probabilidad (%) | O4: Escenario 3: importe | P4: Escenario 3: probabilidad (%) | Q4: Método para escenarios (Valor esperado/Más probable) | R4: Oneroso: costo de cumplir | S4: Oneroso: penalización por incumplir | T4: Oneroso: beneficios económicos esperados del contrato | U4: Importe fijado después del corte (sentencia o acuerdo) | V4: Plazo esperado de salida (años) | W4: Tasa de descuento antes de impuestos (%) | X4: Saldo registrado en libros al corte | Y4: Saldo inicial del período | Z4: Reversión del descuento registrada en el período | AA4: ¿Se recibió respuesta del abogado? (Sí/No) | AB4: Fecha de la carta del abogado | AC4: ¿Revelado en notas? (Sí/No)
A5: LIT-01 | B5: Demanda laboral ex gerente | C5: Litigio | D5: Sí | E5: Probable | F5: Probable | G5: 120000 | K5: 150000 | L5: 60 | M5: 80000 | N5: 30 | O5: 0 | P5: 10 | V5: 1 | X5: 100000 | AA5: Sí | AB5: 46063 | AC5: Sí
A6: LIT-02 | B6: Juicio de impugnación tributaria | C6: Litigio | D6: Sí | E6: Probable | F6: Posible | G6: 85000 | I6: 60000 | J6: 100000 | V6: 2.5 | X6: 0 | AA6: Sí | AB6: 46006 | AC6: No
A7: LIT-03 | B7: Demanda civil de proveedor | C7: Litigio | D7: Sí | E7: Posible | G7: 40000 | V7: 1 | X7: 40000 | AA7: Sí | AB7: 46065 | AC7: Sí
A8: LIT-04 | B8: Reclamo de cliente por entrega tardía | C8: Litigio | D8: No | F8: Posible | I8: 10000 | J8: 30000 | X8: 0 | AA8: No | AC8: No
A9: GAR-01 | B9: Garantías de electrodomésticos | C9: Garantía | D9: Sí | F9: Probable | V9: 1 | X9: 30000
A10: ONE-01 | B10: Contrato de suministro con pérdida | C10: Oneroso | D10: Sí | F10: Probable | R10: 75000 | S10: 45000 | T10: 40000 | V10: 0.5 | X10: 0
A11: DES-01 | B11: Desmantelamiento de planta en terreno arrendado | C11: Desmantelamiento | D11: Sí | F11: Probable | H11: 500000 | V11: 10 | W11: 7 | X11: 240000 | Y11: 225000
A12: REE-01 | B12: Reestructuración de la línea textil (plan comunicado) | C12: Reestructuración | D12: Sí | F12: Probable | H12: 60000 | V12: 0.5 | X12: 60000
A13: AMB-01 | B13: Remediación ambiental de relaves | C13: Otro | D13: Sí | F13: Probable | H13: 200000 | V13: 5 | W13: 9 | X13: 200000 | Y13: 190000 | Z13: 5000
A14: LIT-05 | B14: Juicio laboral de operario | C14: Litigio | D14: Sí | E14: Probable | G14: 25000 | U14: 32000 | V14: 0.25 | X14: 25000 | AA14: Sí | AB14: 46063
A15: LIT-06 | B15: Demanda por uso de marca | C15: Litigio | D15: No | E15: Remota | X15: 0 | AA15: Sí | AB15: 46063
A16: OTR-01 | B16: Multa de la autoridad ambiental | C16: Otro | D16: Sí | F16: Probable | K16: 30000 | L16: 50 | M16: 60000 | N16: 30 | O16: 90000 | P16: 20 | Q16: Más probable | V16: 1 | X16: 30000
A17: ACT-01 | B17: Demanda a la aseguradora por siniestro | C17: Activo contingente | E17: Probable | G17: 50000 | X17: 50000 | AA17: Sí | AB17: 46063 | AC17: No

Sheet 04_Garantias
A1: Garantías (datos del cliente) | H1: ⟵ Inicio | I1: ◀ Anterior | J1: Siguiente ▶
A2: Provisiones y contingencias · Cliente de muestra S.A. · corte 2025-12-31
A4: Línea | B4: Provisión | C4: Descripción | D4: Unidades con garantía | E4: % reclamos | F4: Costo medio
A5: GA-A | B5: GAR-01 | C5: Refrigeradoras | D5: 12000 | E5: 3 | F5: 85
A6: GA-B | B6: GAR-01 | C6: Lavadoras | D6: 5000 | E6: 2 | F6: 120
A7: GA-C | B7: GAR-09 | C7: Microondas | D7: 2000 | E7: 5 | F7: 50

Sheet 05_Obligacion_prob
A1: Obligación presente y probabilidad | H1: ⟵ Inicio | I1: ◀ Anterior | J1: Siguiente ▶
A2: Provisiones y contingencias · Cliente de muestra S.A. · corte 2025-12-31
A4: Código | B4: Tipo | C4: Obligación presente | D4: Prob. abogado | E4: Prob. gerencia | F4: Probabilidad usada | G4: Clasificación (NIC 37.14, 23, 27–35) | H4: Discrepancia
A5: LIT-01 | B5: ='03_Provisiones'!C5 | C5: =IF('03_Provisiones'!D5="","",'03_Provisiones'!D5) | D5: =IF('03_Provisiones'!E5="","",'03_Provisiones'!E5) | E5: =IF('03_Provisiones'!F5="","",'03_Provisiones'!F5) | F5: =IF(D5<>"",D5,E5) | G5: =IF(B5="Activo contingente",IF(F5="","Sin evaluación",IF(F5="Prácticamente cierta","Activo reconocible",IF(F5="Probable","Activo contingente: revelar","Activo contingente: no revelar"))),IF(OR(F5="",C5=""),"Sin evaluación",IF(F5="Remota","Remota: no revelar",IF(AND(C5="Sí",OR(F5="Probable",F5="Prácticamente cierta")),"Reconocer provisión","Pasivo contingente: revelar")))) | H5: =IF(AND(D5<>"",E5<>"",D5<>E5),"Discrepancia","")
A6: LIT-02 | B6: ='03_Provisiones'!C6 | C6: =IF('03_Provisiones'!D6="","",'03_Provisiones'!D6) | D6: =IF('03_Provisiones'!E6="","",'03_Provisiones'!E6) | E6: =IF('03_Provisiones'!F6="","",'03_Provisiones'!F6) | F6: =IF(D6<>"",D6,E6) | G6: =IF(B6="Activo contingente",IF(F6="","Sin evaluación",IF(F6="Prácticamente cierta","Activo reconocible",IF(F6="Probable","Activo contingente: revelar","Activo contingente: no revelar"))),IF(OR(F6="",C6=""),"Sin evaluación",IF(F6="Remota","Remota: no revelar",IF(AND(C6="Sí",OR(F6="Probable",F6="Prácticamente cierta")),"Reconocer provisión","Pasivo contingente: revelar")))) | H6: =IF(AND(D6<>"",E6<>"",D6<>E6),"Discrepancia","")
A7: LIT-03 | B7: ='03_Provisiones'!C7 | C7: =IF('03_Provisiones'!D7="","",'03_Provisiones'!D7) | D7: =IF('03_Provisiones'!E7="","",'03_Provisiones'!E7) | E7: =IF('03_Provisiones'!F7="","",'03_Provisiones'!F7) | F7: =IF(D7<>"",D7,E7) | G7: =IF(B7="Activo contingente",IF(F7="","Sin evaluación",IF(F7="Prácticamente cierta","Activo reconocible",IF(F7="Probable","Activo contingente: revelar","Activo contingente: no revelar"))),IF(OR(F7="",C7=""),"Sin evaluación",IF(F7="Remota","Remota: no revelar",IF(AND(C7="Sí",OR(F7="Probable",F7="Prácticamente cierta")),"Reconocer provisión","Pasivo contingente: revelar")))) | H7: =IF(AND(D7<>"",E7<>"",D7<>E7),"Discrepancia","")
A8: LIT-04 | B8: ='03_Provisiones'!C8 | C8: =IF('03_Provisiones'!D8="","",'03_Provisiones'!D8) | D8: =IF('03_Provisiones'!E8="","",'03_Provisiones'!E8) | E8: =IF('03_Provisiones'!F8="","",'03_Provisiones'!F8) | F8: =IF(D8<>"",D8,E8) | G8: =IF(B8="Activo contingente",IF(F8="","Sin evaluación",IF(F8="Prácticamente cierta","Activo reconocible",IF(F8="Probable","Activo contingente: revelar","Activo contingente: no revelar"))),IF(OR(F8="",C8=""),"Sin evaluación",IF(F8="Remota","Remota: no revelar",IF(AND(C8="Sí",OR(F8="Probable",F8="Prácticamente cierta")),"Reconocer provisión","Pasivo contingente: revelar")))) | H8: =IF(AND(D8<>"",E8<>"",D8<>E8),"Discrepancia","")
A9: GAR-01 | B9: ='03_Provisiones'!C9 | C9: =IF('03_Provisiones'!D9="","",'03_Provisiones'!D9) | D9: =IF('03_Provisiones'!E9="","",'03_Provisiones'!E9) | E9: =IF('03_Provisiones'!F9="","",'03_Provisiones'!F9) | F9: =IF(D9<>"",D9,E9) | G9: =IF(B9="Activo contingente",IF(F9="","Sin evaluación",IF(F9="Prácticamente cierta","Activo reconocible",IF(F9="Probable","Activo contingente: revelar","Activo contingente: no revelar"))),IF(OR(F9="",C9=""),"Sin evaluación",IF(F9="Remota","Remota: no revelar",IF(AND(C9="Sí",OR(F9="Probable",F9="Prácticamente cierta")),"Reconocer provisión","Pasivo contingente: revelar")))) | H9: =IF(AND(D9<>"",E9<>"",D9<>E9),"Discrepancia","")
A10: ONE-01 | B10: ='03_Provisiones'!C10 | C10: =IF('03_Provisiones'!D10="","",'03_Provisiones'!D10) | D10: =IF('03_Provisiones'!E10="","",'03_Provisiones'!E10) | E10: =IF('03_Provisiones'!F10="","",'03_Provisiones'!F10) | F10: =IF(D10<>"",D10,E10) | G10: =IF(B10="Activo contingente",IF(F10="","Sin evaluación",IF(F10="Prácticamente cierta","Activo reconocible",IF(F10="Probable","Activo contingente: revelar","Activo contingente: no revelar"))),IF(OR(F10="",C10=""),"Sin evaluación",IF(F10="Remota","Remota: no revelar",IF(AND(C10="Sí",OR(F10="Probable",F10="Prácticamente cierta")),"Reconocer provisión","Pasivo contingente: revelar")))) | H10: =IF(AND(D10<>"",E10<>"",D10<>E10),"Discrepancia","")
A11: DES-01 | B11: ='03_Provisiones'!C11 | C11: =IF('03_Provisiones'!D11="","",'03_Provisiones'!D11) | D11: =IF('03_Provisiones'!E11="","",'03_Provisiones'!E11) | E11: =IF('03_Provisiones'!F11="","",'03_Provisiones'!F11) | F11: =IF(D11<>"",D11,E11) | G11: =IF(B11="Activo contingente",IF(F11="","Sin evaluación",IF(F11="Prácticamente cierta","Activo reconocible",IF(F11="Probable","Activo contingente: revelar","Activo contingente: no revelar"))),IF(OR(F11="",C11=""),"Sin evaluación",IF(F11="Remota","Remota: no revelar",IF(AND(C11="Sí",OR(F11="Probable",F11="Prácticamente cierta")),"Reconocer provisión","Pasivo contingente: revelar")))) | H11: =IF(AND(D11<>"",E11<>"",D11<>E11),"Discrepancia","")
A12: REE-01 | B12: ='03_Provisiones'!C12 | C12: =IF('03_Provisiones'!D12="","",'03_Provisiones'!D12) | D12: =IF('03_Provisiones'!E12="","",'03_Provisiones'!E12) | E12: =IF('03_Provisiones'!F12="","",'03_Provisiones'!F12) | F12: =IF(D12<>"",D12,E12) | G12: =IF(B12="Activo contingente",IF(F12="","Sin evaluación",IF(F12="Prácticamente cierta","Activo reconocible",IF(F12="Probable","Activo contingente: revelar","Activo contingente: no revelar"))),IF(OR(F12="",C12=""),"Sin evaluación",IF(F12="Remota","Remota: no revelar",IF(AND(C12="Sí",OR(F12="Probable",F12="Prácticamente cierta")),"Reconocer provisión","Pasivo contingente: revelar")))) | H12: =IF(AND(D12<>"",E12<>"",D12<>E12),"Discrepancia","")
A13: AMB-01 | B13: ='03_Provisiones'!C13 | C13: =IF('03_Provisiones'!D13="","",'03_Provisiones'!D13) | D13: =IF('03_Provisiones'!E13="","",'03_Provisiones'!E13) | E13: =IF('03_Provisiones'!F13="","",'03_Provisiones'!F13) | F13: =IF(D13<>"",D13,E13) | G13: =IF(B13="Activo contingente",IF(F13="","Sin evaluación",IF(F13="Prácticamente cierta","Activo reconocible",IF(F13="Probable","Activo contingente: revelar","Activo contingente: no revelar"))),IF(OR(F13="",C13=""),"Sin evaluación",IF(F13="Remota","Remota: no revelar",IF(AND(C13="Sí",OR(F13="Probable",F13="Prácticamente cierta")),"Reconocer provisión","Pasivo contingente: revelar")))) | H13: =IF(AND(D13<>"",E13<>"",D13<>E13),"Discrepancia","")
A14: LIT-05 | B14: ='03_Provisiones'!C14 | C14: =IF('03_Provisiones'!D14="","",'03_Provisiones'!D14) | D14: =IF('03_Provisiones'!E14="","",'03_Provisiones'!E14) | E14: =IF('03_Provisiones'!F14="","",'03_Provisiones'!F14) | F14: =IF(D14<>"",D14,E14) | G14: =IF(B14="Activo contingente",IF(F14="","Sin evaluación",IF(F14="Prácticamente cierta","Activo reconocible",IF(F14="Probable","Activo contingente: revelar","Activo contingente: no revelar"))),IF(OR(F14="",C14=""),"Sin evaluación",IF(F14="Remota","Remota: no revelar",IF(AND(C14="Sí",OR(F14="Probable",F14="Prácticamente cierta")),"Reconocer provisión","Pasivo contingente: revelar")))) | H14: =IF(AND(D14<>"",E14<>"",D14<>E14),"Discrepancia","")
A15: LIT-06 | B15: ='03_Provisiones'!C15 | C15: =IF('03_Provisiones'!D15="","",'03_Provisiones'!D15) | D15: =IF('03_Provisiones'!E15="","",'03_Provisiones'!E15) | E15: =IF('03_Provisiones'!F15="","",'03_Provisiones'!F15) | F15: =IF(D15<>"",D15,E15) | G15: =IF(B15="Activo contingente",IF(F15="","Sin evaluación",IF(F15="Prácticamente cierta","Activo reconocible",IF(F15="Probable","Activo contingente: revelar","Activo contingente: no revelar"))),IF(OR(F15="",C15=""),"Sin evaluación",IF(F15="Remota","Remota: no revelar",IF(AND(C15="Sí",OR(F15="Probable",F15="Prácticamente cierta")),"Reconocer provisión","Pasivo contingente: revelar")))) | H15: =IF(AND(D15<>"",E15<>"",D15<>E15),"Discrepancia","")
A16: OTR-01 | B16: ='03_Provisiones'!C16 | C16: =IF('03_Provisiones'!D16="","",'03_Provisiones'!D16) | D16: =IF('03_Provisiones'!E16="","",'03_Provisiones'!E16) | E16: =IF('03_Provisiones'!F16="","",'03_Provisiones'!F16) | F16: =IF(D16<>"",D16,E16) | G16: =IF(B16="Activo contingente",IF(F16="","Sin evaluación",IF(F16="Prácticamente cierta","Activo reconocible",IF(F16="Probable","Activo contingente: revelar","Activo contingente: no revelar"))),IF(OR(F16="",C16=""),"Sin evaluación",IF(F16="Remota","Remota: no revelar",IF(AND(C16="Sí",OR(F16="Probable",F16="Prácticamente cierta")),"Reconocer provisión","Pasivo contingente: revelar")))) | H16: =IF(AND(D16<>"",E16<>"",D16<>E16),"Discrepancia","")
A17: ACT-01 | B17: ='03_Provisiones'!C17 | C17: =IF('03_Provisiones'!D17="","",'03_Provisiones'!D17) | D17: =IF('03_Provisiones'!E17="","",'03_Provisiones'!E17) | E17: =IF('03_Provisiones'!F17="","",'03_Provisiones'!F17) | F17: =IF(D17<>"",D17,E17) | G17: =IF(B17="Activo contingente",IF(F17="","Sin evaluación",IF(F17="Prácticamente cierta","Activo reconocible",IF(F17="Probable","Activo contingente: revelar","Activo contingente: no revelar"))),IF(OR(F17="",C17=""),"Sin evaluación",IF(F17="Remota","Remota: no revelar",IF(AND(C17="Sí",OR(F17="Probable",F17="Prácticamente cierta")),"Reconocer provisión","Pasivo contingente: revelar")))) | H17: =IF(AND(D17<>"",E17<>"",D17<>E17),"Discrepancia","")
A19: ⓘ Cómo se calcula esta hoja
A20: Columna | B20: Fórmula (Excel) | C20: Cómo se calcula (sencillo) | D20: Ejemplo con números reales | E20: De dónde viene | F20: Norma
A21: Tipo | B21: '='03_Provisiones'!C5 | C21: Copia el tipo de la partida (litigio, garantía, oneroso, etc.) desde la hoja 03 (datos del cliente), en la misma fila. | D21: Fila 1: «Litigio» → Litigio | E21: hoja «Provisiones y contingencias (datos del cliente)» | F21: —
A22: Obligación presente | B22: '=IF('03_Provisiones'!D5="","",'03_Provisiones'!D5) | C22: Copia de la hoja 03 (datos del cliente) si existe obligación presente (Sí/No); si el cliente la dejó vacía, queda en blanco. | D22: Fila 1: IF(«Sí»=""; ""; «Sí») → Sí | E22: hoja «Provisiones y contingencias (datos del cliente)» | F22: —
A23: Prob. abogado | B23: '=IF('03_Provisiones'!E5="","",'03_Provisiones'!E5) | C23: Copia la probabilidad que asigna el abogado desde la hoja 03 (datos del cliente); si no la informó, queda en blanco. | D23: Fila 1: IF(«Probable»=""; ""; «Probable») → Probable | E23: hoja «Provisiones y contingencias (datos del cliente)» | F23: —
A24: Prob. gerencia | B24: '=IF('03_Provisiones'!F5="","",'03_Provisiones'!F5) | C24: Copia la probabilidad que asigna la gerencia desde la hoja 03 (datos del cliente); si no la informó, queda en blanco. | D24: Fila 1: IF(«Probable»=""; ""; «Probable») → Probable | E24: hoja «Provisiones y contingencias (datos del cliente)» | F24: —
A25: Probabilidad usada | B25: '=IF(D5<>"",D5,E5) | C25: Usa la probabilidad del abogado y, si no la hay, la probabilidad de la gerencia. | D25: Fila 1: IF(«Probable»<>""; «Probable»; «Probable») → Probable | E25: «Prob. abogado» (esta hoja), «Prob. gerencia» (esta hoja) | F25: —
A26: Clasificación (NIC 37.14, 23, 27–35) | B26: '=IF(B5="Activo contingente",IF(F5="","Sin evaluación",IF(F5="Prácticamente cierta","Activo reconocible",IF(F5="Probable","Activo contingente: revelar","Activo contingente: no revelar"))),IF(OR(F5="",C5=""),"Sin evaluación",IF(F5="Remota","Remota: no revelar",IF(AND(C5="Sí",OR(F5="Probable",F5="Prácticamente cierta")),"Reconocer provisión","Pasivo contingente: revelar")))) | C26: En un activo contingente: prácticamente cierto → reconocible, probable → revelar y lo demás → no revelar. En el resto: sin obligación o sin probabilidad queda «Sin evaluación»; remota → no revelar; obligación presente y probable (o prácticamente cierta) → reconocer provisión; si no, pasivo contingente a revelar. | D26: Fila 1: IF(«Litigio»="Activo contingente"; IF(«Probable»=""; "Sin evaluación"; IF(«Probable»="Prácticamente cierta"; "Activo reconocible"; IF(«Probable»="Probable"; "Activo contingente: revelar"; "Activo contingente: no revelar"))); IF(OR(«Probable»=""; «Sí»=""); "Sin evaluación"; IF(«Probable»="Remota"; "Remota: no revelar"; IF(AND(«Sí»="Sí"; OR(«Probable»="Probable"; «Probable»="Prácticamente cierta")); "Reconocer provisión"; "Pasivo contingente: revelar")))) → Reconocer provisión | E26: «Tipo» (esta hoja), «Probabilidad usada» (esta hoja), «Obligación presente» (esta hoja) | F26: —
A27: Discrepancia | B27: '=IF(AND(D5<>"",E5<>"",D5<>E5),"Discrepancia","") | C27: Marca «Discrepancia» cuando el abogado y la gerencia informaron probabilidades distintas; si coinciden o falta alguna, queda vacío. | D27: Fila 1: IF(AND(«Probable»<>""; «Probable»<>""; «Probable»<>«Probable»); "Discrepancia"; "") → (en blanco) | E27: «Prob. abogado» (esta hoja), «Prob. gerencia» (esta hoja) | F27: —

Sheet 06_Mejor_estimacion
A1: Mejor estimación | H1: ⟵ Inicio | I1: ◀ Anterior | J1: Siguiente ▶
A2: Provisiones y contingencias · Cliente de muestra S.A. · corte 2025-12-31
A4: Código | B4: Hecho posterior | C4: Oneroso: mín(costo neto, penalización) | D4: Garantías | E4: Σ probabilidades % | F4: Valor esperado | G4: Más probable | H4: Punto medio del rango | I4: Carta del abogado | J4: Estimación gerencia | K4: Base usada | L4: Mejor estimación
A5: LIT-01 | B5: =IF('03_Provisiones'!U5="","",'03_Provisiones'!U5) | C5: =IF('03_Provisiones'!C5<>"Oneroso","",IF(AND('03_Provisiones'!R5="",'03_Provisiones'!S5=""),"",IF('03_Provisiones'!R5="",'03_Provisiones'!S5,IF('03_Provisiones'!S5="",MAX('03_Provisiones'!R5-N('03_Provisiones'!T5),0),MIN(MAX('03_Provisiones'!R5-N('03_Provisiones'!T5),0),'03_Provisiones'!S5))))) | D5: =IF('03_Provisiones'!C5="Garantía",IF(COUNTIF('04_Garantias'!$B$5:$B$7,A5)=0,"",SUMIF('04_Garantias'!$B$5:$B$7,A5,'10_Garantias_calculo'!$F$5:$F$7)),"") | E5: =N('03_Provisiones'!L5)+N('03_Provisiones'!N5)+N('03_Provisiones'!P5) | F5: =IF(E5=0,"",(N('03_Provisiones'!K5)*N('03_Provisiones'!L5)+N('03_Provisiones'!M5)*N('03_Provisiones'!N5)+N('03_Provisiones'!O5)*N('03_Provisiones'!P5))/(N('03_Provisiones'!L5)+N('03_Provisiones'!N5)+N('03_Provisiones'!P5))) | G5: =IF(E5=0,"",IF(AND(N('03_Provisiones'!L5)>=N('03_Provisiones'!N5),N('03_Provisiones'!L5)>=N('03_Provisiones'!P5)),'03_Provisiones'!K5,IF(N('03_Provisiones'!N5)>=N('03_Provisiones'!P5),'03_Provisiones'!M5,'03_Provisiones'!O5))) | H5: =IF(AND('03_Provisiones'!I5<>"",'03_Provisiones'!J5<>""),('03_Provisiones'!I5+'03_Provisiones'!J5)/2,"") | I5: =IF('03_Provisiones'!G5="","",'03_Provisiones'!G5) | J5: =IF('03_Provisiones'!H5="","",'03_Provisiones'!H5) | K5: =IF(B5<>"","Hecho posterior (NIC 10.9 a)",IF(C5<>"","Oneroso: menor costo (37.68)",IF(D5<>"","Garantías: valor esperado (37.39)",IF(E5>0,IF('03_Provisiones'!Q5="Más probable","Desenlace más probable (37.40)","Valor esperado (37.39)"),IF(H5<>"","Punto medio del rango (37.39)",IF(I5<>"","Carta del abogado",IF(J5<>"","Estimación de la gerencia","Sin estimación"))))))) | L5: =IF(B5<>"",B5,IF(C5<>"",C5,IF(D5<>"",D5,IF(E5>0,IF('03_Provisiones'!Q5="Más probable",G5,F5),IF(H5<>"",H5,IF(I5<>"",I5,IF(J5<>"",J5,"")))))))
A6: LIT-02 | B6: =IF('03_Provisiones'!U6="","",'03_Provisiones'!U6) | C6: =IF('03_Provisiones'!C6<>"Oneroso","",IF(AND('03_Provisiones'!R6="",'03_Provisiones'!S6=""),"",IF('03_Provisiones'!R6="",'03_Provisiones'!S6,IF('03_Provisiones'!S6="",MAX('03_Provisiones'!R6-N('03_Provisiones'!T6),0),MIN(MAX('03_Provisiones'!R6-N('03_Provisiones'!T6),0),'03_Provisiones'!S6))))) | D6: =IF('03_Provisiones'!C6="Garantía",IF(COUNTIF('04_Garantias'!$B$5:$B$7,A6)=0,"",SUMIF('04_Garantias'!$B$5:$B$7,A6,'10_Garantias_calculo'!$F$5:$F$7)),"") | E6: =N('03_Provisiones'!L6)+N('03_Provisiones'!N6)+N('03_Provisiones'!P6) | F6: =IF(E6=0,"",(N('03_Provisiones'!K6)*N('03_Provisiones'!L6)+N('03_Provisiones'!M6)*N('03_Provisiones'!N6)+N('03_Provisiones'!O6)*N('03_Provisiones'!P6))/(N('03_Provisiones'!L6)+N('03_Provisiones'!N6)+N('03_Provisiones'!P6))) | G6: =IF(E6=0,"",IF(AND(N('03_Provisiones'!L6)>=N('03_Provisiones'!N6),N('03_Provisiones'!L6)>=N('03_Provisiones'!P6)),'03_Provisiones'!K6,IF(N('03_Provisiones'!N6)>=N('03_Provisiones'!P6),'03_Provisiones'!M6,'03_Provisiones'!O6))) | H6: =IF(AND('03_Provisiones'!I6<>"",'03_Provisiones'!J6<>""),('03_Provisiones'!I6+'03_Provisiones'!J6)/2,"") | I6: =IF('03_Provisiones'!G6="","",'03_Provisiones'!G6) | J6: =IF('03_Provisiones'!H6="","",'03_Provisiones'!H6) | K6: =IF(B6<>"","Hecho posterior (NIC 10.9 a)",IF(C6<>"","Oneroso: menor costo (37.68)",IF(D6<>"","Garantías: valor esperado (37.39)",IF(E6>0,IF('03_Provisiones'!Q6="Más probable","Desenlace más probable (37.40)","Valor esperado (37.39)"),IF(H6<>"","Punto medio del rango (37.39)",IF(I6<>"","Carta del abogado",IF(J6<>"","Estimación de la gerencia","Sin estimación"))))))) | L6: =IF(B6<>"",B6,IF(C6<>"",C6,IF(D6<>"",D6,IF(E6>0,IF('03_Provisiones'!Q6="Más probable",G6,F6),IF(H6<>"",H6,IF(I6<>"",I6,IF(J6<>"",J6,"")))))))
A7: LIT-03 | B7: =IF('03_Provisiones'!U7="","",'03_Provisiones'!U7) | C7: =IF('03_Provisiones'!C7<>"Oneroso","",IF(AND('03_Provisiones'!R7="",'03_Provisiones'!S7=""),"",IF('03_Provisiones'!R7="",'03_Provisiones'!S7,IF('03_Provisiones'!S7="",MAX('03_Provisiones'!R7-N('03_Provisiones'!T7),0),MIN(MAX('03_Provisiones'!R7-N('03_Provisiones'!T7),0),'03_Provisiones'!S7))))) | D7: =IF('03_Provisiones'!C7="Garantía",IF(COUNTIF('04_Garantias'!$B$5:$B$7,A7)=0,"",SUMIF('04_Garantias'!$B$5:$B$7,A7,'10_Garantias_calculo'!$F$5:$F$7)),"") | E7: =N('03_Provisiones'!L7)+N('03_Provisiones'!N7)+N('03_Provisiones'!P7) | F7: =IF(E7=0,"",(N('03_Provisiones'!K7)*N('03_Provisiones'!L7)+N('03_Provisiones'!M7)*N('03_Provisiones'!N7)+N('03_Provisiones'!O7)*N('03_Provisiones'!P7))/(N('03_Provisiones'!L7)+N('03_Provisiones'!N7)+N('03_Provisiones'!P7))) | G7: =IF(E7=0,"",IF(AND(N('03_Provisiones'!L7)>=N('03_Provisiones'!N7),N('03_Provisiones'!L7)>=N('03_Provisiones'!P7)),'03_Provisiones'!K7,IF(N('03_Provisiones'!N7)>=N('03_Provisiones'!P7),'03_Provisiones'!M7,'03_Provisiones'!O7))) | H7: =IF(AND('03_Provisiones'!I7<>"",'03_Provisiones'!J7<>""),('03_Provisiones'!I7+'03_Provisiones'!J7)/2,"") | I7: =IF('03_Provisiones'!G7="","",'03_Provisiones'!G7) | J7: =IF('03_Provisiones'!H7="","",'03_Provisiones'!H7) | K7: =IF(B7<>"","Hecho posterior (NIC 10.9 a)",IF(C7<>"","Oneroso: menor costo (37.68)",IF(D7<>"","Garantías: valor esperado (37.39)",IF(E7>0,IF('03_Provisiones'!Q7="Más probable","Desenlace más probable (37.40)","Valor esperado (37.39)"),IF(H7<>"","Punto medio del rango (37.39)",IF(I7<>"","Carta del abogado",IF(J7<>"","Estimación de la gerencia","Sin estimación"))))))) | L7: =IF(B7<>"",B7,IF(C7<>"",C7,IF(D7<>"",D7,IF(E7>0,IF('03_Provisiones'!Q7="Más probable",G7,F7),IF(H7<>"",H7,IF(I7<>"",I7,IF(J7<>"",J7,"")))))))
A8: LIT-04 | B8: =IF('03_Provisiones'!U8="","",'03_Provisiones'!U8) | C8: =IF('03_Provisiones'!C8<>"Oneroso","",IF(AND('03_Provisiones'!R8="",'03_Provisiones'!S8=""),"",IF('03_Provisiones'!R8="",'03_Provisiones'!S8,IF('03_Provisiones'!S8="",MAX('03_Provisiones'!R8-N('03_Provisiones'!T8),0),MIN(MAX('03_Provisiones'!R8-N('03_Provisiones'!T8),0),'03_Provisiones'!S8))))) | D8: =IF('03_Provisiones'!C8="Garantía",IF(COUNTIF('04_Garantias'!$B$5:$B$7,A8)=0,"",SUMIF('04_Garantias'!$B$5:$B$7,A8,'10_Garantias_calculo'!$F$5:$F$7)),"") | E8: =N('03_Provisiones'!L8)+N('03_Provisiones'!N8)+N('03_Provisiones'!P8) | F8: =IF(E8=0,"",(N('03_Provisiones'!K8)*N('03_Provisiones'!L8)+N('03_Provisiones'!M8)*N('03_Provisiones'!N8)+N('03_Provisiones'!O8)*N('03_Provisiones'!P8))/(N('03_Provisiones'!L8)+N('03_Provisiones'!N8)+N('03_Provisiones'!P8))) | G8: =IF(E8=0,"",IF(AND(N('03_Provisiones'!L8)>=N('03_Provisiones'!N8),N('03_Provisiones'!L8)>=N('03_Provisiones'!P8)),'03_Provisiones'!K8,IF(N('03_Provisiones'!N8)>=N('03_Provisiones'!P8),'03_Provisiones'!M8,'03_Provisiones'!O8))) | H8: =IF(AND('03_Provisiones'!I8<>"",'03_Provisiones'!J8<>""),('03_Provisiones'!I8+'03_Provisiones'!J8)/2,"") | I8: =IF('03_Provisiones'!G8="","",'03_Provisiones'!G8) | J8: =IF('03_Provisiones'!H8="","",'03_Provisiones'!H8) | K8: =IF(B8<>"","Hecho posterior (NIC 10.9 a)",IF(C8<>"","Oneroso: menor costo (37.68)",IF(D8<>"","Garantías: valor esperado (37.39)",IF(E8>0,IF('03_Provisiones'!Q8="Más probable","Desenlace más probable (37.40)","Valor esperado (37.39)"),IF(H8<>"","Punto medio del rango (37.39)",IF(I8<>"","Carta del abogado",IF(J8<>"","Estimación de la gerencia","Sin estimación"))))))) | L8: =IF(B8<>"",B8,IF(C8<>"",C8,IF(D8<>"",D8,IF(E8>0,IF('03_Provisiones'!Q8="Más probable",G8,F8),IF(H8<>"",H8,IF(I8<>"",I8,IF(J8<>"",J8,"")))))))
A9: GAR-01 | B9: =IF('03_Provisiones'!U9="","",'03_Provisiones'!U9) | C9: =IF('03_Provisiones'!C9<>"Oneroso","",IF(AND('03_Provisiones'!R9="",'03_Provisiones'!S9=""),"",IF('03_Provisiones'!R9="",'03_Provisiones'!S9,IF('03_Provisiones'!S9="",MAX('03_Provisiones'!R9-N('03_Provisiones'!T9),0),MIN(MAX('03_Provisiones'!R9-N('03_Provisiones'!T9),0),'03_Provisiones'!S9))))) | D9: =IF('03_Provisiones'!C9="Garantía",IF(COUNTIF('04_Garantias'!$B$5:$B$7,A9)=0,"",SUMIF('04_Garantias'!$B$5:$B$7,A9,'10_Garantias_calculo'!$F$5:$F$7)),"") | E9: =N('03_Provisiones'!L9)+N('03_Provisiones'!N9)+N('03_Provisiones'!P9) | F9: =IF(E9=0,"",(N('03_Provisiones'!K9)*N('03_Provisiones'!L9)+N('03_Provisiones'!M9)*N('03_Provisiones'!N9)+N('03_Provisiones'!O9)*N('03_Provisiones'!P9))/(N('03_Provisiones'!L9)+N('03_Provisiones'!N9)+N('03_Provisiones'!P9))) | G9: =IF(E9=0,"",IF(AND(N('03_Provisiones'!L9)>=N('03_Provisiones'!N9),N('03_Provisiones'!L9)>=N('03_Provisiones'!P9)),'03_Provisiones'!K9,IF(N('03_Provisiones'!N9)>=N('03_Provisiones'!P9),'03_Provisiones'!M9,'03_Provisiones'!O9))) | H9: =IF(AND('03_Provisiones'!I9<>"",'03_Provisiones'!J9<>""),('03_Provisiones'!I9+'03_Provisiones'!J9)/2,"") | I9: =IF('03_Provisiones'!G9="","",'03_Provisiones'!G9) | J9: =IF('03_Provisiones'!H9="","",'03_Provisiones'!H9) | K9: =IF(B9<>"","Hecho posterior (NIC 10.9 a)",IF(C9<>"","Oneroso: menor costo (37.68)",IF(D9<>"","Garantías: valor esperado (37.39)",IF(E9>0,IF('03_Provisiones'!Q9="Más probable","Desenlace más probable (37.40)","Valor esperado (37.39)"),IF(H9<>"","Punto medio del rango (37.39)",IF(I9<>"","Carta del abogado",IF(J9<>"","Estimación de la gerencia","Sin estimación"))))))) | L9: =IF(B9<>"",B9,IF(C9<>"",C9,IF(D9<>"",D9,IF(E9>0,IF('03_Provisiones'!Q9="Más probable",G9,F9),IF(H9<>"",H9,IF(I9<>"",I9,IF(J9<>"",J9,"")))))))
A10: ONE-01 | B10: =IF('03_Provisiones'!U10="","",'03_Provisiones'!U10) | C10: =IF('03_Provisiones'!C10<>"Oneroso","",IF(AND('03_Provisiones'!R10="",'03_Provisiones'!S10=""),"",IF('03_Provisiones'!R10="",'03_Provisiones'!S10,IF('03_Provisiones'!S10="",MAX('03_Provisiones'!R10-N('03_Provisiones'!T10),0),MIN(MAX('03_Provisiones'!R10-N('03_Provisiones'!T10),0),'03_Provisiones'!S10))))) | D10: =IF('03_Provisiones'!C10="Garantía",IF(COUNTIF('04_Garantias'!$B$5:$B$7,A10)=0,"",SUMIF('04_Garantias'!$B$5:$B$7,A10,'10_Garantias_calculo'!$F$5:$F$7)),"") | E10: =N('03_Provisiones'!L10)+N('03_Provisiones'!N10)+N('03_Provisiones'!P10) | F10: =IF(E10=0,"",(N('03_Provisiones'!K10)*N('03_Provisiones'!L10)+N('03_Provisiones'!M10)*N('03_Provisiones'!N10)+N('03_Provisiones'!O10)*N('03_Provisiones'!P10))/(N('03_Provisiones'!L10)+N('03_Provisiones'!N10)+N('03_Provisiones'!P10))) | G10: =IF(E10=0,"",IF(AND(N('03_Provisiones'!L10)>=N('03_Provisiones'!N10),N('03_Provisiones'!L10)>=N('03_Provisiones'!P10)),'03_Provisiones'!K10,IF(N('03_Provisiones'!N10)>=N('03_Provisiones'!P10),'03_Provisiones'!M10,'03_Provisiones'!O10))) | H10: =IF(AND('03_Provisiones'!I10<>"",'03_Provisiones'!J10<>""),('03_Provisiones'!I10+'03_Provisiones'!J10)/2,"") | I10: =IF('03_Provisiones'!G10="","",'03_Provisiones'!G10) | J10: =IF('03_Provisiones'!H10="","",'03_Provisiones'!H10) | K10: =IF(B10<>"","Hecho posterior (NIC 10.9 a)",IF(C10<>"","Oneroso: menor costo (37.68)",IF(D10<>"","Garantías: valor esperado (37.39)",IF(E10>0,IF('03_Provisiones'!Q10="Más probable","Desenlace más probable (37.40)","Valor esperado (37.39)"),IF(H10<>"","Punto medio del rango (37.39)",IF(I10<>"","Carta del abogado",IF(J10<>"","Estimación de la gerencia","Sin estimación"))))))) | L10: =IF(B10<>"",B10,IF(C10<>"",C10,IF(D10<>"",D10,IF(E10>0,IF('03_Provisiones'!Q10="Más probable",G10,F10),IF(H10<>"",H10,IF(I10<>"",I10,IF(J10<>"",J10,"")))))))
A11: DES-01 | B11: =IF('03_Provisiones'!U11="","",'03_Provisiones'!U11) | C11: =IF('03_Provisiones'!C11<>"Oneroso","",IF(AND('03_Provisiones'!R11="",'03_Provisiones'!S11=""),"",IF('03_Provisiones'!R11="",'03_Provisiones'!S11,IF('03_Provisiones'!S11="",MAX('03_Provisiones'!R11-N('03_Provisiones'!T11),0),MIN(MAX('03_Provisiones'!R11-N('03_Provisiones'!T11),0),'03_Provisiones'!S11))))) | D11: =IF('03_Provisiones'!C11="Garantía",IF(COUNTIF('04_Garantias'!$B$5:$B$7,A11)=0,"",SUMIF('04_Garantias'!$B$5:$B$7,A11,'10_Garantias_calculo'!$F$5:$F$7)),"") | E11: =N('03_Provisiones'!L11)+N('03_Provisiones'!N11)+N('03_Provisiones'!P11) | F11: =IF(E11=0,"",(N('03_Provisiones'!K11)*N('03_Provisiones'!L11)+N('03_Provisiones'!M11)*N('03_Provisiones'!N11)+N('03_Provisiones'!O11)*N('03_Provisiones'!P11))/(N('03_Provisiones'!L11)+N('03_Provisiones'!N11)+N('03_Provisiones'!P11))) | G11: =IF(E11=0,"",IF(AND(N('03_Provisiones'!L11)>=N('03_Provisiones'!N11),N('03_Provisiones'!L11)>=N('03_Provisiones'!P11)),'03_Provisiones'!K11,IF(N('03_Provisiones'!N11)>=N('03_Provisiones'!P11),'03_Provisiones'!M11,'03_Provisiones'!O11))) | H11: =IF(AND('03_Provisiones'!I11<>"",'03_Provisiones'!J11<>""),('03_Provisiones'!I11+'03_Provisiones'!J11)/2,"") | I11: =IF('03_Provisiones'!G11="","",'03_Provisiones'!G11) | J11: =IF('03_Provisiones'!H11="","",'03_Provisiones'!H11) | K11: =IF(B11<>"","Hecho posterior (NIC 10.9 a)",IF(C11<>"","Oneroso: menor costo (37.68)",IF(D11<>"","Garantías: valor esperado (37.39)",IF(E11>0,IF('03_Provisiones'!Q11="Más probable","Desenlace más probable (37.40)","Valor esperado (37.39)"),IF(H11<>"","Punto medio del rango (37.39)",IF(I11<>"","Carta del abogado",IF(J11<>"","Estimación de la gerencia","Sin estimación"))))))) | L11: =IF(B11<>"",B11,IF(C11<>"",C11,IF(D11<>"",D11,IF(E11>0,IF('03_Provisiones'!Q11="Más probable",G11,F11),IF(H11<>"",H11,IF(I11<>"",I11,IF(J11<>"",J11,"")))))))
A12: REE-01 | B12: =IF('03_Provisiones'!U12="","",'03_Provisiones'!U12) | C12: =IF('03_Provisiones'!C12<>"Oneroso","",IF(AND('03_Provisiones'!R12="",'03_Provisiones'!S12=""),"",IF('03_Provisiones'!R12="",'03_Provisiones'!S12,IF('03_Provisiones'!S12="",MAX('03_Provisiones'!R12-N('03_Provisiones'!T12),0),MIN(MAX('03_Provisiones'!R12-N('03_Provisiones'!T12),0),'03_Provisiones'!S12))))) | D12: =IF('03_Provisiones'!C12="Garantía",IF(COUNTIF('04_Garantias'!$B$5:$B$7,A12)=0,"",SUMIF('04_Garantias'!$B$5:$B$7,A12,'10_Garantias_calculo'!$F$5:$F$7)),"") | E12: =N('03_Provisiones'!L12)+N('03_Provisiones'!N12)+N('03_Provisiones'!P12) | F12: =IF(E12=0,"",(N('03_Provisiones'!K12)*N('03_Provisiones'!L12)+N('03_Provisiones'!M12)*N('03_Provisiones'!N12)+N('03_Provisiones'!O12)*N('03_Provisiones'!P12))/(N('03_Provisiones'!L12)+N('03_Provisiones'!N12)+N('03_Provisiones'!P12))) | G12: =IF(E12=0,"",IF(AND(N('03_Provisiones'!L12)>=N('03_Provisiones'!N12),N('03_Provisiones'!L12)>=N('03_Provisiones'!P12)),'03_Provisiones'!K12,IF(N('03_Provisiones'!N12)>=N('03_Provisiones'!P12),'03_Provisiones'!M12,'03_Provisiones'!O12))) | H12: =IF(AND('03_Provisiones'!I12<>"",'03_Provisiones'!J12<>""),('03_Provisiones'!I12+'03_Provisiones'!J12)/2,"") | I12: =IF('03_Provisiones'!G12="","",'03_Provisiones'!G12) | J12: =IF('03_Provisiones'!H12="","",'03_Provisiones'!H12) | K12: =IF(B12<>"","Hecho posterior (NIC 10.9 a)",IF(C12<>"","Oneroso: menor costo (37.68)",IF(D12<>"","Garantías: valor esperado (37.39)",IF(E12>0,IF('03_Provisiones'!Q12="Más probable","Desenlace más probable (37.40)","Valor esperado (37.39)"),IF(H12<>"","Punto medio del rango (37.39)",IF(I12<>"","Carta del abogado",IF(J12<>"","Estimación de la gerencia","Sin estimación"))))))) | L12: =IF(B12<>"",B12,IF(C12<>"",C12,IF(D12<>"",D12,IF(E12>0,IF('03_Provisiones'!Q12="Más probable",G12,F12),IF(H12<>"",H12,IF(I12<>"",I12,IF(J12<>"",J12,"")))))))
A13: AMB-01 | B13: =IF('03_Provisiones'!U13="","",'03_Provisiones'!U13) | C13: =IF('03_Provisiones'!C13<>"Oneroso","",IF(AND('03_Provisiones'!R13="",'03_Provisiones'!S13=""),"",IF('03_Provisiones'!R13="",'03_Provisiones'!S13,IF('03_Provisiones'!S13="",MAX('03_Provisiones'!R13-N('03_Provisiones'!T13),0),MIN(MAX('03_Provisiones'!R13-N('03_Provisiones'!T13),0),'03_Provisiones'!S13))))) | D13: =IF('03_Provisiones'!C13="Garantía",IF(COUNTIF('04_Garantias'!$B$5:$B$7,A13)=0,"",SUMIF('04_Garantias'!$B$5:$B$7,A13,'10_Garantias_calculo'!$F$5:$F$7)),"") | E13: =N('03_Provisiones'!L13)+N('03_Provisiones'!N13)+N('03_Provisiones'!P13) | F13: =IF(E13=0,"",(N('03_Provisiones'!K13)*N('03_Provisiones'!L13)+N('03_Provisiones'!M13)*N('03_Provisiones'!N13)+N('03_Provisiones'!O13)*N('03_Provisiones'!P13))/(N('03_Provisiones'!L13)+N('03_Provisiones'!N13)+N('03_Provisiones'!P13))) | G13: =IF(E13=0,"",IF(AND(N('03_Provisiones'!L13)>=N('03_Provisiones'!N13),N('03_Provisiones'!L13)>=N('03_Provisiones'!P13)),'03_Provisiones'!K13,IF(N('03_Provisiones'!N13)>=N('03_Provisiones'!P13),'03_Provisiones'!M13,'03_Provisiones'!O13))) | H13: =IF(AND('03_Provisiones'!I13<>"",'03_Provisiones'!J13<>""),('03_Provisiones'!I13+'03_Provisiones'!J13)/2,"") | I13: =IF('03_Provisiones'!G13="","",'03_Provisiones'!G13) | J13: =IF('03_Provisiones'!H13="","",'03_Provisiones'!H13) | K13: =IF(B13<>"","Hecho posterior (NIC 10.9 a)",IF(C13<>"","Oneroso: menor costo (37.68)",IF(D13<>"","Garantías: valor esperado (37.39)",IF(E13>0,IF('03_Provisiones'!Q13="Más probable","Desenlace más probable (37.40)","Valor esperado (37.39)"),IF(H13<>"","Punto medio del rango (37.39)",IF(I13<>"","Carta del abogado",IF(J13<>"","Estimación de la gerencia","Sin estimación"))))))) | L13: =IF(B13<>"",B13,IF(C13<>"",C13,IF(D13<>"",D13,IF(E13>0,IF('03_Provisiones'!Q13="Más probable",G13,F13),IF(H13<>"",H13,IF(I13<>"",I13,IF(J13<>"",J13,"")))))))
A14: LIT-05 | B14: =IF('03_Provisiones'!U14="","",'03_Provisiones'!U14) | C14: =IF('03_Provisiones'!C14<>"Oneroso","",IF(AND('03_Provisiones'!R14="",'03_Provisiones'!S14=""),"",IF('03_Provisiones'!R14="",'03_Provisiones'!S14,IF('03_Provisiones'!S14="",MAX('03_Provisiones'!R14-N('03_Provisiones'!T14),0),MIN(MAX('03_Provisiones'!R14-N('03_Provisiones'!T14),0),'03_Provisiones'!S14))))) | D14: =IF('03_Provisiones'!C14="Garantía",IF(COUNTIF('04_Garantias'!$B$5:$B$7,A14)=0,"",SUMIF('04_Garantias'!$B$5:$B$7,A14,'10_Garantias_calculo'!$F$5:$F$7)),"") | E14: =N('03_Provisiones'!L14)+N('03_Provisiones'!N14)+N('03_Provisiones'!P14) | F14: =IF(E14=0,"",(N('03_Provisiones'!K14)*N('03_Provisiones'!L14)+N('03_Provisiones'!M14)*N('03_Provisiones'!N14)+N('03_Provisiones'!O14)*N('03_Provisiones'!P14))/(N('03_Provisiones'!L14)+N('03_Provisiones'!N14)+N('03_Provisiones'!P14))) | G14: =IF(E14=0,"",IF(AND(N('03_Provisiones'!L14)>=N('03_Provisiones'!N14),N('03_Provisiones'!L14)>=N('03_Provisiones'!P14)),'03_Provisiones'!K14,IF(N('03_Provisiones'!N14)>=N('03_Provisiones'!P14),'03_Provisiones'!M14,'03_Provisiones'!O14))) | H14: =IF(AND('03_Provisiones'!I14<>"",'03_Provisiones'!J14<>""),('03_Provisiones'!I14+'03_Provisiones'!J14)/2,"") | I14: =IF('03_Provisiones'!G14="","",'03_Provisiones'!G14) | J14: =IF('03_Provisiones'!H14="","",'03_Provisiones'!H14) | K14: =IF(B14<>"","Hecho posterior (NIC 10.9 a)",IF(C14<>"","Oneroso: menor costo (37.68)",IF(D14<>"","Garantías: valor esperado (37.39)",IF(E14>0,IF('03_Provisiones'!Q14="Más probable","Desenlace más probable (37.40)","Valor esperado (37.39)"),IF(H14<>"","Punto medio del rango (37.39)",IF(I14<>"","Carta del abogado",IF(J14<>"","Estimación de la gerencia","Sin estimación"))))))) | L14: =IF(B14<>"",B14,IF(C14<>"",C14,IF(D14<>"",D14,IF(E14>0,IF('03_Provisiones'!Q14="Más probable",G14,F14),IF(H14<>"",H14,IF(I14<>"",I14,IF(J14<>"",J14,"")))))))
A15: LIT-06 | B15: =IF('03_Provisiones'!U15="","",'03_Provisiones'!U15) | C15: =IF('03_Provisiones'!C15<>"Oneroso","",IF(AND('03_Provisiones'!R15="",'03_Provisiones'!S15=""),"",IF('03_Provisiones'!R15="",'03_Provisiones'!S15,IF('03_Provisiones'!S15="",MAX('03_Provisiones'!R15-N('03_Provisiones'!T15),0),MIN(MAX('03_Provisiones'!R15-N('03_Provisiones'!T15),0),'03_Provisiones'!S15))))) | D15: =IF('03_Provisiones'!C15="Garantía",IF(COUNTIF('04_Garantias'!$B$5:$B$7,A15)=0,"",SUMIF('04_Garantias'!$B$5:$B$7,A15,'10_Garantias_calculo'!$F$5:$F$7)),"") | E15: =N('03_Provisiones'!L15)+N('03_Provisiones'!N15)+N('03_Provisiones'!P15) | F15: =IF(E15=0,"",(N('03_Provisiones'!K15)*N('03_Provisiones'!L15)+N('03_Provisiones'!M15)*N('03_Provisiones'!N15)+N('03_Provisiones'!O15)*N('03_Provisiones'!P15))/(N('03_Provisiones'!L15)+N('03_Provisiones'!N15)+N('03_Provisiones'!P15))) | G15: =IF(E15=0,"",IF(AND(N('03_Provisiones'!L15)>=N('03_Provisiones'!N15),N('03_Provisiones'!L15)>=N('03_Provisiones'!P15)),'03_Provisiones'!K15,IF(N('03_Provisiones'!N15)>=N('03_Provisiones'!P15),'03_Provisiones'!M15,'03_Provisiones'!O15))) | H15: =IF(AND('03_Provisiones'!I15<>"",'03_Provisiones'!J15<>""),('03_Provisiones'!I15+'03_Provisiones'!J15)/2,"") | I15: =IF('03_Provisiones'!G15="","",'03_Provisiones'!G15) | J15: =IF('03_Provisiones'!H15="","",'03_Provisiones'!H15) | K15: =IF(B15<>"","Hecho posterior (NIC 10.9 a)",IF(C15<>"","Oneroso: menor costo (37.68)",IF(D15<>"","Garantías: valor esperado (37.39)",IF(E15>0,IF('03_Provisiones'!Q15="Más probable","Desenlace más probable (37.40)","Valor esperado (37.39)"),IF(H15<>"","Punto medio del rango (37.39)",IF(I15<>"","Carta del abogado",IF(J15<>"","Estimación de la gerencia","Sin estimación"))))))) | L15: =IF(B15<>"",B15,IF(C15<>"",C15,IF(D15<>"",D15,IF(E15>0,IF('03_Provisiones'!Q15="Más probable",G15,F15),IF(H15<>"",H15,IF(I15<>"",I15,IF(J15<>"",J15,"")))))))
A16: OTR-01 | B16: =IF('03_Provisiones'!U16="","",'03_Provisiones'!U16) | C16: =IF('03_Provisiones'!C16<>"Oneroso","",IF(AND('03_Provisiones'!R16="",'03_Provisiones'!S16=""),"",IF('03_Provisiones'!R16="",'03_Provisiones'!S16,IF('03_Provisiones'!S16="",MAX('03_Provisiones'!R16-N('03_Provisiones'!T16),0),MIN(MAX('03_Provisiones'!R16-N('03_Provisiones'!T16),0),'03_Provisiones'!S16))))) | D16: =IF('03_Provisiones'!C16="Garantía",IF(COUNTIF('04_Garantias'!$B$5:$B$7,A16)=0,"",SUMIF('04_Garantias'!$B$5:$B$7,A16,'10_Garantias_calculo'!$F$5:$F$7)),"") | E16: =N('03_Provisiones'!L16)+N('03_Provisiones'!N16)+N('03_Provisiones'!P16) | F16: =IF(E16=0,"",(N('03_Provisiones'!K16)*N('03_Provisiones'!L16)+N('03_Provisiones'!M16)*N('03_Provisiones'!N16)+N('03_Provisiones'!O16)*N('03_Provisiones'!P16))/(N('03_Provisiones'!L16)+N('03_Provisiones'!N16)+N('03_Provisiones'!P16))) | G16: =IF(E16=0,"",IF(AND(N('03_Provisiones'!L16)>=N('03_Provisiones'!N16),N('03_Provisiones'!L16)>=N('03_Provisiones'!P16)),'03_Provisiones'!K16,IF(N('03_Provisiones'!N16)>=N('03_Provisiones'!P16),'03_Provisiones'!M16,'03_Provisiones'!O16))) | H16: =IF(AND('03_Provisiones'!I16<>"",'03_Provisiones'!J16<>""),('03_Provisiones'!I16+'03_Provisiones'!J16)/2,"") | I16: =IF('03_Provisiones'!G16="","",'03_Provisiones'!G16) | J16: =IF('03_Provisiones'!H16="","",'03_Provisiones'!H16) | K16: =IF(B16<>"","Hecho posterior (NIC 10.9 a)",IF(C16<>"","Oneroso: menor costo (37.68)",IF(D16<>"","Garantías: valor esperado (37.39)",IF(E16>0,IF('03_Provisiones'!Q16="Más probable","Desenlace más probable (37.40)","Valor esperado (37.39)"),IF(H16<>"","Punto medio del rango (37.39)",IF(I16<>"","Carta del abogado",IF(J16<>"","Estimación de la gerencia","Sin estimación"))))))) | L16: =IF(B16<>"",B16,IF(C16<>"",C16,IF(D16<>"",D16,IF(E16>0,IF('03_Provisiones'!Q16="Más probable",G16,F16),IF(H16<>"",H16,IF(I16<>"",I16,IF(J16<>"",J16,"")))))))
A17: ACT-01 | B17: =IF('03_Provisiones'!U17="","",'03_Provisiones'!U17) | C17: =IF('03_Provisiones'!C17<>"Oneroso","",IF(AND('03_Provisiones'!R17="",'03_Provisiones'!S17=""),"",IF('03_Provisiones'!R17="",'03_Provisiones'!S17,IF('03_Provisiones'!S17="",MAX('03_Provisiones'!R17-N('03_Provisiones'!T17),0),MIN(MAX('03_Provisiones'!R17-N('03_Provisiones'!T17),0),'03_Provisiones'!S17))))) | D17: =IF('03_Provisiones'!C17="Garantía",IF(COUNTIF('04_Garantias'!$B$5:$B$7,A17)=0,"",SUMIF('04_Garantias'!$B$5:$B$7,A17,'10_Garantias_calculo'!$F$5:$F$7)),"") | E17: =N('03_Provisiones'!L17)+N('03_Provisiones'!N17)+N('03_Provisiones'!P17) | F17: =IF(E17=0,"",(N('03_Provisiones'!K17)*N('03_Provisiones'!L17)+N('03_Provisiones'!M17)*N('03_Provisiones'!N17)+N('03_Provisiones'!O17)*N('03_Provisiones'!P17))/(N('03_Provisiones'!L17)+N('03_Provisiones'!N17)+N('03_Provisiones'!P17))) | G17: =IF(E17=0,"",IF(AND(N('03_Provisiones'!L17)>=N('03_Provisiones'!N17),N('03_Provisiones'!L17)>=N('03_Provisiones'!P17)),'03_Provisiones'!K17,IF(N('03_Provisiones'!N17)>=N('03_Provisiones'!P17),'03_Provisiones'!M17,'03_Provisiones'!O17))) | H17: =IF(AND('03_Provisiones'!I17<>"",'03_Provisiones'!J17<>""),('03_Provisiones'!I17+'03_Provisiones'!J17)/2,"") | I17: =IF('03_Provisiones'!G17="","",'03_Provisiones'!G17) | J17: =IF('03_Provisiones'!H17="","",'03_Provisiones'!H17) | K17: =IF(B17<>"","Hecho posterior (NIC 10.9 a)",IF(C17<>"","Oneroso: menor costo (37.68)",IF(D17<>"","Garantías: valor esperado (37.39)",IF(E17>0,IF('03_Provisiones'!Q17="Más probable","Desenlace más probable (37.40)","Valor esperado (37.39)"),IF(H17<>"","Punto medio del rango (37.39)",IF(I17<>"","Carta del abogado",IF(J17<>"","Estimación de la gerencia","Sin estimación"))))))) | L17: =IF(B17<>"",B17,IF(C17<>"",C17,IF(D17<>"",D17,IF(E17>0,IF('03_Provisiones'!Q17="Más probable",G17,F17),IF(H17<>"",H17,IF(I17<>"",I17,IF(J17<>"",J17,"")))))))
A19: ⓘ Cómo se calcula esta hoja
A20: Columna | B20: Fórmula (Excel) | C20: Cómo se calcula (sencillo) | D20: Ejemplo con números reales | E20: De dónde viene | F20: Norma
A21: Hecho posterior | B21: '=IF('03_Provisiones'!U5="","",'03_Provisiones'!U5) | C21: Copia de la hoja 03 (datos del cliente) el importe fijado después del corte por sentencia o acuerdo; vacío si no lo hay. | D21: Fila 1: IF((vacío)=""; ""; (vacío)) → (en blanco) | E21: hoja «Provisiones y contingencias (datos del cliente)» | F21: —
A22: Oneroso: mín(costo neto, penalización) | B22: '=IF('03_Provisiones'!C5<>"Oneroso","",IF(AND('03_Provisiones'!R5="",'03_Provisiones'!S5=""),"",IF('03_Provisiones'!R5="",'03_Provisiones'!S5,IF('03_Provisiones'!S5="",MAX('03_Provisiones'!R5-N('03_Provisiones'!T5),0),MIN(MAX('03_Provisiones'!R5-N('03_Provisiones'!T5),0),'03_Provisiones'!S5))))) | C22: Solo en contratos onerosos, con datos de la hoja 03 (datos del cliente): costo de cumplir menos beneficios esperados (nunca negativo) y, si hay penalización, el menor entre ese costo neto y la penalización; si falta uno, usa el otro. | D22: Fila 1: IF(«Litigio»<>"Oneroso"; ""; IF(AND((vacío)=""; (vacío)=""); ""; IF((vacío)=""; (vacío); IF((vacío)=""; MAX((vacío)-N((vacío)); 0); MIN(MAX((vacío)-N((vacío)); 0); (vacío)))))) → (en blanco) | E22: hoja «Provisiones y contingencias (datos del cliente)» | F22: —
A23: Garantías | B23: '=IF('03_Provisiones'!C5="Garantía",IF(COUNTIF('04_Garantias'!$B$5:$B$7,A5)=0,"",SUMIF('04_Garantias'!$B$5:$B$7,A5,'10_Garantias_calculo'!$F$5:$F$7)),"") | C23: Solo en provisiones de tipo garantía: suma la provisión calculada en la hoja 10 (Garantías: cálculo) de las líneas de la hoja 04 vinculadas a este código; vacío si no tiene líneas. | D23: Fila 1: IF(«Litigio»="Garantía"; IF(COUNTIF([«Provisión» de «Garantías (datos del cliente)», 3 filas]; «LIT-01»)=0; ""; SUMIF([«Provisión» de «Garantías (datos del cliente)», 3 filas]; «LIT-01»; [«Provisión calculada» de «Garantías: cálculo», 3 filas])); "") → (en blanco) | E23: «Código» (esta hoja), hoja «Provisiones y contingencias (datos del cliente)», hoja «Garantías (datos del cliente)», hoja «Garantías: cálculo» | F23: —
A24: Σ probabilidades % | B24: '=N('03_Provisiones'!L5)+N('03_Provisiones'!N5)+N('03_Provisiones'!P5) | C24: Suma las probabilidades (%) de los tres escenarios informados en la hoja 03 (datos del cliente); las vacías cuentan como cero. | D24: Fila 1: N(60,00)+N(30,00)+N(10,00) → 100,00 | E24: hoja «Provisiones y contingencias (datos del cliente)» | F24: —
A25: Valor esperado | B25: '=IF(E5=0,"",(N('03_Provisiones'!K5)*N('03_Provisiones'!L5)+N('03_Provisiones'!M5)*N('03_Provisiones'!N5)+N('03_Provisiones'!O5)*N('03_Provisiones'!P5))/(N('03_Provisiones'!L5)+N('03_Provisiones'!N5)+N('03_Provisiones'!P5))) | C25: Pondera el importe de cada escenario de la hoja 03 por su probabilidad y divide para la suma de probabilidades; en blanco si ningún escenario tiene probabilidad. | D25: Fila 1: IF(100,00=0; ""; (N(150.000,00)*N(60,00)+N(80.000,00)*N(30,00)+N(0,00)*N(10,00))/(N(60,00)+N(30,00)+N(10,00))) → 114.000,00 | E25: «Σ probabilidades %» (esta hoja), hoja «Provisiones y contingencias (datos del cliente)» | F25: —
A26: Más probable | B26: '=IF(E5=0,"",IF(AND(N('03_Provisiones'!L5)>=N('03_Provisiones'!N5),N('03_Provisiones'!L5)>=N('03_Provisiones'!P5)),'03_Provisiones'!K5,IF(N('03_Provisiones'!N5)>=N('03_Provisiones'!P5),'03_Provisiones'!M5,'03_Provisiones'!O5))) | C26: Toma el importe del escenario con mayor probabilidad (en empate gana el de menor número); en blanco si ningún escenario tiene probabilidad. | D26: Fila 1: IF(100,00=0; ""; IF(AND(N(60,00)>=N(30,00); N(60,00)>=N(10,00)); 150.000,00; IF(N(30,00)>=N(10,00); 80.000,00; 0,00))) → 150.000,00 | E26: «Σ probabilidades %» (esta hoja), hoja «Provisiones y contingencias (datos del cliente)» | F26: —
A27: Punto medio del rango | B27: '=IF(AND('03_Provisiones'!I5<>"",'03_Provisiones'!J5<>""),('03_Provisiones'!I5+'03_Provisiones'!J5)/2,"") | C27: Promedia el importe mínimo y el máximo del rango informado en la hoja 03; en blanco si falta alguno de los dos. | D27: Fila 1: IF(AND((vacío)<>""; (vacío)<>""); ((vacío)+(vacío))/2; "") → (en blanco) | E27: hoja «Provisiones y contingencias (datos del cliente)» | F27: —
A28: Carta del abogado | B28: '=IF('03_Provisiones'!G5="","",'03_Provisiones'!G5) | C28: Copia el importe que indica la carta del abogado en la hoja 03 (datos del cliente); vacío si no lo informó. | D28: Fila 1: IF(120.000,00=""; ""; 120.000,00) → 120.000,00 | E28: hoja «Provisiones y contingencias (datos del cliente)» | F28: —
A29: Estimación gerencia | B29: '=IF('03_Provisiones'!H5="","",'03_Provisiones'!H5) | C29: Copia la estimación de la gerencia (sin descontar) de la hoja 03 (datos del cliente); vacío si no la informó. | D29: Fila 1: IF((vacío)=""; ""; (vacío)) → (en blanco) | E29: hoja «Provisiones y contingencias (datos del cliente)» | F29: —
A30: Base usada | B30: '=IF(B5<>"","Hecho posterior (NIC 10.9 a)",IF(C5<>"","Oneroso: menor costo (37.68)",IF(D5<>"","Garantías: valor esperado (37.39)",IF(E5>0,IF('03_Provisiones'!Q5="Más probable","Desenlace más probable (37.40)","Valor esperado (37.39)"),IF(H5<>"","Punto medio del rango (37.39)",IF(I5<>"","Carta del abogado",IF(J5<>"","Estimación de la gerencia","Sin estimación"))))))) | C30: Indica qué dato se tomó como mejor estimación, en este orden: hecho posterior, contrato oneroso, garantías, escenarios (valor esperado o más probable según el método), punto medio del rango, carta del abogado y estimación de la gerencia. | D30: Fila 1: IF((vacío)<>""; "Hecho posterior (NIC 10.9 a)"; IF((vacío)<>""; "Oneroso: menor costo (37.68)"; IF((vacío)<>""; "Garantías: valor esperado (37.39)"; IF(100,00>0; IF((vacío)="Más probable"; "Desenlace más probable (37.40)"; "Valor esperado (37.39)"); IF((vacío)<>""; "Punto medio del rango (37.39)"; IF(120.000,00<>""; "Carta del abogado"; IF((vacío)<>""; "Estimación de la gerencia"; "Sin estimación"))))))) → Valor esperado (37.39) | E30: «Hecho posterior» (esta hoja), «Oneroso: mín(costo neto, penalización)» (esta hoja), «Garantías» (esta hoja), «Σ probabilidades %» (esta hoja), «Punto medio del rango» (esta hoja), «Carta del abogado» (esta hoja), «Estimación gerencia» (esta hoja), hoja «Provisiones y contingencias (datos del cliente)» | F30: —
A31: Mejor estimación | B31: '=IF(B5<>"",B5,IF(C5<>"",C5,IF(D5<>"",D5,IF(E5>0,IF('03_Provisiones'!Q5="Más probable",G5,F5),IF(H5<>"",H5,IF(I5<>"",I5,IF(J5<>"",J5,""))))))) | C31: Toma el importe de la primera base disponible en ese mismo orden; con escenarios usa el más probable si el método de la hoja 03 lo pide y, si no, el valor esperado; vacío si no hay ninguna base. | D31: Fila 1: IF((vacío)<>""; (vacío); IF((vacío)<>""; (vacío); IF((vacío)<>""; (vacío); IF(100,00>0; IF((vacío)="Más probable"; 150.000,00; 114.000,00); IF((vacío)<>""; (vacío); IF(120.000,00<>""; 120.000,00; IF((vacío)<>""; (vacío); ""))))))) → 114.000,00 | E31: «Hecho posterior» (esta hoja), «Oneroso: mín(costo neto, penalización)» (esta hoja), «Garantías» (esta hoja), «Σ probabilidades %» (esta hoja), «Más probable» (esta hoja), «Valor esperado» (esta hoja), «Punto medio del rango» (esta hoja), «Carta del abogado» (esta hoja), «Estimación gerencia» (esta hoja), hoja «Provisiones y contingencias (datos del cliente)» | F31: —

Sheet 07_Valor_presente
A1: Valor presente (descuento) | H1: ⟵ Inicio | I1: ◀ Anterior | J1: Siguiente ▶
A2: Provisiones y contingencias · Cliente de muestra S.A. · corte 2025-12-31
A4: Código | B4: Mejor estimación | C4: Plazo (años) | D4: Tasa antes de impuestos % | E4: ¿Descontar? | F4: Factor de descuento | G4: Valor presente | H4: Efecto del descuento
A5: LIT-01 | B5: =IF('06_Mejor_estimacion'!L5="","",'06_Mejor_estimacion'!L5) | C5: =IF('03_Provisiones'!V5="","",'03_Provisiones'!V5) | D5: =IF('03_Provisiones'!W5<>"",'03_Provisiones'!W5,IF('02_Parametros'!$B$8<>"",'02_Parametros'!$B$8,"")) | E5: =IF(AND(C5<>"",C5>'02_Parametros'!$B$9),"Sí","No") | F5: =IF(E5="No",1,IF(D5="","",1/(1+D5/100)^C5)) | G5: =IF(OR(B5="",F5=""),"",B5*F5) | H5: =IF(G5="","",B5-G5)
A6: LIT-02 | B6: =IF('06_Mejor_estimacion'!L6="","",'06_Mejor_estimacion'!L6) | C6: =IF('03_Provisiones'!V6="","",'03_Provisiones'!V6) | D6: =IF('03_Provisiones'!W6<>"",'03_Provisiones'!W6,IF('02_Parametros'!$B$8<>"",'02_Parametros'!$B$8,"")) | E6: =IF(AND(C6<>"",C6>'02_Parametros'!$B$9),"Sí","No") | F6: =IF(E6="No",1,IF(D6="","",1/(1+D6/100)^C6)) | G6: =IF(OR(B6="",F6=""),"",B6*F6) | H6: =IF(G6="","",B6-G6)
A7: LIT-03 | B7: =IF('06_Mejor_estimacion'!L7="","",'06_Mejor_estimacion'!L7) | C7: =IF('03_Provisiones'!V7="","",'03_Provisiones'!V7) | D7: =IF('03_Provisiones'!W7<>"",'03_Provisiones'!W7,IF('02_Parametros'!$B$8<>"",'02_Parametros'!$B$8,"")) | E7: =IF(AND(C7<>"",C7>'02_Parametros'!$B$9),"Sí","No") | F7: =IF(E7="No",1,IF(D7="","",1/(1+D7/100)^C7)) | G7: =IF(OR(B7="",F7=""),"",B7*F7) | H7: =IF(G7="","",B7-G7)
A8: LIT-04 | B8: =IF('06_Mejor_estimacion'!L8="","",'06_Mejor_estimacion'!L8) | C8: =IF('03_Provisiones'!V8="","",'03_Provisiones'!V8) | D8: =IF('03_Provisiones'!W8<>"",'03_Provisiones'!W8,IF('02_Parametros'!$B$8<>"",'02_Parametros'!$B$8,"")) | E8: =IF(AND(C8<>"",C8>'02_Parametros'!$B$9),"Sí","No") | F8: =IF(E8="No",1,IF(D8="","",1/(1+D8/100)^C8)) | G8: =IF(OR(B8="",F8=""),"",B8*F8) | H8: =IF(G8="","",B8-G8)
A9: GAR-01 | B9: =IF('06_Mejor_estimacion'!L9="","",'06_Mejor_estimacion'!L9) | C9: =IF('03_Provisiones'!V9="","",'03_Provisiones'!V9) | D9: =IF('03_Provisiones'!W9<>"",'03_Provisiones'!W9,IF('02_Parametros'!$B$8<>"",'02_Parametros'!$B$8,"")) | E9: =IF(AND(C9<>"",C9>'02_Parametros'!$B$9),"Sí","No") | F9: =IF(E9="No",1,IF(D9="","",1/(1+D9/100)^C9)) | G9: =IF(OR(B9="",F9=""),"",B9*F9) | H9: =IF(G9="","",B9-G9)
A10: ONE-01 | B10: =IF('06_Mejor_estimacion'!L10="","",'06_Mejor_estimacion'!L10) | C10: =IF('03_Provisiones'!V10="","",'03_Provisiones'!V10) | D10: =IF('03_Provisiones'!W10<>"",'03_Provisiones'!W10,IF('02_Parametros'!$B$8<>"",'02_Parametros'!$B$8,"")) | E10: =IF(AND(C10<>"",C10>'02_Parametros'!$B$9),"Sí","No") | F10: =IF(E10="No",1,IF(D10="","",1/(1+D10/100)^C10)) | G10: =IF(OR(B10="",F10=""),"",B10*F10) | H10: =IF(G10="","",B10-G10)
A11: DES-01 | B11: =IF('06_Mejor_estimacion'!L11="","",'06_Mejor_estimacion'!L11) | C11: =IF('03_Provisiones'!V11="","",'03_Provisiones'!V11) | D11: =IF('03_Provisiones'!W11<>"",'03_Provisiones'!W11,IF('02_Parametros'!$B$8<>"",'02_Parametros'!$B$8,"")) | E11: =IF(AND(C11<>"",C11>'02_Parametros'!$B$9),"Sí","No") | F11: =IF(E11="No",1,IF(D11="","",1/(1+D11/100)^C11)) | G11: =IF(OR(B11="",F11=""),"",B11*F11) | H11: =IF(G11="","",B11-G11)
A12: REE-01 | B12: =IF('06_Mejor_estimacion'!L12="","",'06_Mejor_estimacion'!L12) | C12: =IF('03_Provisiones'!V12="","",'03_Provisiones'!V12) | D12: =IF('03_Provisiones'!W12<>"",'03_Provisiones'!W12,IF('02_Parametros'!$B$8<>"",'02_Parametros'!$B$8,"")) | E12: =IF(AND(C12<>"",C12>'02_Parametros'!$B$9),"Sí","No") | F12: =IF(E12="No",1,IF(D12="","",1/(1+D12/100)^C12)) | G12: =IF(OR(B12="",F12=""),"",B12*F12) | H12: =IF(G12="","",B12-G12)
A13: AMB-01 | B13: =IF('06_Mejor_estimacion'!L13="","",'06_Mejor_estimacion'!L13) | C13: =IF('03_Provisiones'!V13="","",'03_Provisiones'!V13) | D13: =IF('03_Provisiones'!W13<>"",'03_Provisiones'!W13,IF('02_Parametros'!$B$8<>"",'02_Parametros'!$B$8,"")) | E13: =IF(AND(C13<>"",C13>'02_Parametros'!$B$9),"Sí","No") | F13: =IF(E13="No",1,IF(D13="","",1/(1+D13/100)^C13)) | G13: =IF(OR(B13="",F13=""),"",B13*F13) | H13: =IF(G13="","",B13-G13)
A14: LIT-05 | B14: =IF('06_Mejor_estimacion'!L14="","",'06_Mejor_estimacion'!L14) | C14: =IF('03_Provisiones'!V14="","",'03_Provisiones'!V14) | D14: =IF('03_Provisiones'!W14<>"",'03_Provisiones'!W14,IF('02_Parametros'!$B$8<>"",'02_Parametros'!$B$8,"")) | E14: =IF(AND(C14<>"",C14>'02_Parametros'!$B$9),"Sí","No") | F14: =IF(E14="No",1,IF(D14="","",1/(1+D14/100)^C14)) | G14: =IF(OR(B14="",F14=""),"",B14*F14) | H14: =IF(G14="","",B14-G14)
A15: LIT-06 | B15: =IF('06_Mejor_estimacion'!L15="","",'06_Mejor_estimacion'!L15) | C15: =IF('03_Provisiones'!V15="","",'03_Provisiones'!V15) | D15: =IF('03_Provisiones'!W15<>"",'03_Provisiones'!W15,IF('02_Parametros'!$B$8<>"",'02_Parametros'!$B$8,"")) | E15: =IF(AND(C15<>"",C15>'02_Parametros'!$B$9),"Sí","No") | F15: =IF(E15="No",1,IF(D15="","",1/(1+D15/100)^C15)) | G15: =IF(OR(B15="",F15=""),"",B15*F15) | H15: =IF(G15="","",B15-G15)
A16: OTR-01 | B16: =IF('06_Mejor_estimacion'!L16="","",'06_Mejor_estimacion'!L16) | C16: =IF('03_Provisiones'!V16="","",'03_Provisiones'!V16) | D16: =IF('03_Provisiones'!W16<>"",'03_Provisiones'!W16,IF('02_Parametros'!$B$8<>"",'02_Parametros'!$B$8,"")) | E16: =IF(AND(C16<>"",C16>'02_Parametros'!$B$9),"Sí","No") | F16: =IF(E16="No",1,IF(D16="","",1/(1+D16/100)^C16)) | G16: =IF(OR(B16="",F16=""),"",B16*F16) | H16: =IF(G16="","",B16-G16)
A17: ACT-01 | B17: =IF('06_Mejor_estimacion'!L17="","",'06_Mejor_estimacion'!L17) | C17: =IF('03_Provisiones'!V17="","",'03_Provisiones'!V17) | D17: =IF('03_Provisiones'!W17<>"",'03_Provisiones'!W17,IF('02_Parametros'!$B$8<>"",'02_Parametros'!$B$8,"")) | E17: =IF(AND(C17<>"",C17>'02_Parametros'!$B$9),"Sí","No") | F17: =IF(E17="No",1,IF(D17="","",1/(1+D17/100)^C17)) | G17: =IF(OR(B17="",F17=""),"",B17*F17) | H17: =IF(G17="","",B17-G17)
A18: TOTAL | H18: =SUM(H5:H17)
A20: ⓘ Cómo se calcula esta hoja
A21: Columna | B21: Fórmula (Excel) | C21: Cómo se calcula (sencillo) | D21: Ejemplo con números reales | E21: De dónde viene | F21: Norma
A22: Mejor estimación | B22: '=IF('06_Mejor_estimacion'!L5="","",'06_Mejor_estimacion'!L5) | C22: Trae la mejor estimación de la hoja 06 (Mejor estimación), en la misma fila; vacío si no hay. | D22: Fila 1: IF(114.000,00=""; ""; 114.000,00) → 114.000,00 | E22: hoja «Mejor estimación» | F22: —
A23: Plazo (años) | B23: '=IF('03_Provisiones'!V5="","",'03_Provisiones'!V5) | C23: Copia de la hoja 03 (datos del cliente) el plazo esperado de salida de recursos, en años; vacío si no se informó. | D23: Fila 1: IF(1,00=""; ""; 1,00) → 1,00 | E23: hoja «Provisiones y contingencias (datos del cliente)» | F23: —
A24: Tasa antes de impuestos % | B24: '=IF('03_Provisiones'!W5<>"",'03_Provisiones'!W5,IF('02_Parametros'!$B$8<>"",'02_Parametros'!$B$8,"")) | C24: Usa la tasa antes de impuestos informada para la partida en la hoja 03 y, si falta, la tasa por defecto de la hoja 02 (Parámetros); vacío si no hay ninguna. | D24: Fila 1: IF((vacío)<>""; (vacío); IF(8,00<>""; 8,00; "")) → 8,00 | E24: hoja «Provisiones y contingencias (datos del cliente)», hoja «Parámetros» | F24: —
A25: ¿Descontar? | B25: '=IF(AND(C5<>"",C5>'02_Parametros'!$B$9),"Sí","No") | C25: Marca «Sí» cuando el plazo de salida supera los años a partir de los cuales se descuenta, fijados en la hoja 02 (Parámetros). | D25: Fila 1: IF(AND(1,00<>""; 1,00>1,00); "Sí"; "No") → No | E25: «Plazo (años)» (esta hoja), hoja «Parámetros» | F25: —
A26: Factor de descuento | B26: '=IF(E5="No",1,IF(D5="","",1/(1+D5/100)^C5)) | C26: Si no se descuenta, el factor es 1; si se descuenta, es 1 ÷ (1 + tasa)^plazo; queda en blanco si falta la tasa. | D26: Fila 1: IF(«No»="No"; 1; IF(8,00=""; ""; 1/(1+8,00/100)^1,00)) → 1,00 | E26: «¿Descontar?» (esta hoja), «Tasa antes de impuestos %» (esta hoja), «Plazo (años)» (esta hoja) | F26: —
A27: Valor presente | B27: '=IF(OR(B5="",F5=""),"",B5*F5) | C27: Multiplica la mejor estimación por el factor de descuento; en blanco si falta alguno de los dos. | D27: Fila 1: IF(OR(114.000,00=""; 1,00=""); ""; 114.000,00*1,00) → 114.000,00 | E27: «Mejor estimación» (esta hoja), «Factor de descuento» (esta hoja) | F27: —
A28: Efecto del descuento | B28: '=IF(G5="","",B5-G5) | C28: Resta el valor presente a la mejor estimación: es cuánto baja la provisión por descontarla. | D28: Fila 1: IF(114.000,00=""; ""; 114.000,00-114.000,00) → 0,00 | E28: «Valor presente» (esta hoja), «Mejor estimación» (esta hoja) | F28: —

Sheet 08_Reversion_descuento
A1: Actualización financiera (reversión del descuento) | H1: ⟵ Inicio | I1: ◀ Anterior | J1: Siguiente ▶
A2: Provisiones y contingencias · Cliente de muestra S.A. · corte 2025-12-31
A4: Código | B4: Saldo inicial | C4: Tasa % | D4: ¿Descontada? | E4: Reversión calculada | F4: Reversión registrada | G4: Calculada − registrada
A5: LIT-01 | B5: =IF('03_Provisiones'!Y5="","",'03_Provisiones'!Y5) | C5: ='07_Valor_presente'!D5 | D5: ='07_Valor_presente'!E5 | E5: =IF(AND(B5<>"",C5<>"",D5="Sí"),B5*C5/100,"") | F5: =IF('03_Provisiones'!Z5="","",'03_Provisiones'!Z5) | G5: =IF(OR(E5="",F5=""),"",E5-F5)
A6: LIT-02 | B6: =IF('03_Provisiones'!Y6="","",'03_Provisiones'!Y6) | C6: ='07_Valor_presente'!D6 | D6: ='07_Valor_presente'!E6 | E6: =IF(AND(B6<>"",C6<>"",D6="Sí"),B6*C6/100,"") | F6: =IF('03_Provisiones'!Z6="","",'03_Provisiones'!Z6) | G6: =IF(OR(E6="",F6=""),"",E6-F6)
A7: LIT-03 | B7: =IF('03_Provisiones'!Y7="","",'03_Provisiones'!Y7) | C7: ='07_Valor_presente'!D7 | D7: ='07_Valor_presente'!E7 | E7: =IF(AND(B7<>"",C7<>"",D7="Sí"),B7*C7/100,"") | F7: =IF('03_Provisiones'!Z7="","",'03_Provisiones'!Z7) | G7: =IF(OR(E7="",F7=""),"",E7-F7)
A8: LIT-04 | B8: =IF('03_Provisiones'!Y8="","",'03_Provisiones'!Y8) | C8: ='07_Valor_presente'!D8 | D8: ='07_Valor_presente'!E8 | E8: =IF(AND(B8<>"",C8<>"",D8="Sí"),B8*C8/100,"") | F8: =IF('03_Provisiones'!Z8="","",'03_Provisiones'!Z8) | G8: =IF(OR(E8="",F8=""),"",E8-F8)
A9: GAR-01 | B9: =IF('03_Provisiones'!Y9="","",'03_Provisiones'!Y9) | C9: ='07_Valor_presente'!D9 | D9: ='07_Valor_presente'!E9 | E9: =IF(AND(B9<>"",C9<>"",D9="Sí"),B9*C9/100,"") | F9: =IF('03_Provisiones'!Z9="","",'03_Provisiones'!Z9) | G9: =IF(OR(E9="",F9=""),"",E9-F9)
A10: ONE-01 | B10: =IF('03_Provisiones'!Y10="","",'03_Provisiones'!Y10) | C10: ='07_Valor_presente'!D10 | D10: ='07_Valor_presente'!E10 | E10: =IF(AND(B10<>"",C10<>"",D10="Sí"),B10*C10/100,"") | F10: =IF('03_Provisiones'!Z10="","",'03_Provisiones'!Z10) | G10: =IF(OR(E10="",F10=""),"",E10-F10)
A11: DES-01 | B11: =IF('03_Provisiones'!Y11="","",'03_Provisiones'!Y11) | C11: ='07_Valor_presente'!D11 | D11: ='07_Valor_presente'!E11 | E11: =IF(AND(B11<>"",C11<>"",D11="Sí"),B11*C11/100,"") | F11: =IF('03_Provisiones'!Z11="","",'03_Provisiones'!Z11) | G11: =IF(OR(E11="",F11=""),"",E11-F11)
A12: REE-01 | B12: =IF('03_Provisiones'!Y12="","",'03_Provisiones'!Y12) | C12: ='07_Valor_presente'!D12 | D12: ='07_Valor_presente'!E12 | E12: =IF(AND(B12<>"",C12<>"",D12="Sí"),B12*C12/100,"") | F12: =IF('03_Provisiones'!Z12="","",'03_Provisiones'!Z12) | G12: =IF(OR(E12="",F12=""),"",E12-F12)
A13: AMB-01 | B13: =IF('03_Provisiones'!Y13="","",'03_Provisiones'!Y13) | C13: ='07_Valor_presente'!D13 | D13: ='07_Valor_presente'!E13 | E13: =IF(AND(B13<>"",C13<>"",D13="Sí"),B13*C13/100,"") | F13: =IF('03_Provisiones'!Z13="","",'03_Provisiones'!Z13) | G13: =IF(OR(E13="",F13=""),"",E13-F13)
A14: LIT-05 | B14: =IF('03_Provisiones'!Y14="","",'03_Provisiones'!Y14) | C14: ='07_Valor_presente'!D14 | D14: ='07_Valor_presente'!E14 | E14: =IF(AND(B14<>"",C14<>"",D14="Sí"),B14*C14/100,"") | F14: =IF('03_Provisiones'!Z14="","",'03_Provisiones'!Z14) | G14: =IF(OR(E14="",F14=""),"",E14-F14)
A15: LIT-06 | B15: =IF('03_Provisiones'!Y15="","",'03_Provisiones'!Y15) | C15: ='07_Valor_presente'!D15 | D15: ='07_Valor_presente'!E15 | E15: =IF(AND(B15<>"",C15<>"",D15="Sí"),B15*C15/100,"") | F15: =IF('03_Provisiones'!Z15="","",'03_Provisiones'!Z15) | G15: =IF(OR(E15="",F15=""),"",E15-F15)
A16: OTR-01 | B16: =IF('03_Provisiones'!Y16="","",'03_Provisiones'!Y16) | C16: ='07_Valor_presente'!D16 | D16: ='07_Valor_presente'!E16 | E16: =IF(AND(B16<>"",C16<>"",D16="Sí"),B16*C16/100,"") | F16: =IF('03_Provisiones'!Z16="","",'03_Provisiones'!Z16) | G16: =IF(OR(E16="",F16=""),"",E16-F16)
A17: ACT-01 | B17: =IF('03_Provisiones'!Y17="","",'03_Provisiones'!Y17) | C17: ='07_Valor_presente'!D17 | D17: ='07_Valor_presente'!E17 | E17: =IF(AND(B17<>"",C17<>"",D17="Sí"),B17*C17/100,"") | F17: =IF('03_Provisiones'!Z17="","",'03_Provisiones'!Z17) | G17: =IF(OR(E17="",F17=""),"",E17-F17)
A18: TOTAL | E18: =SUM(E5:E17) | F18: =SUM(F5:F17) | G18: =SUM(G5:G17)
A20: ⓘ Cómo se calcula esta hoja
A21: Columna | B21: Fórmula (Excel) | C21: Cómo se calcula (sencillo) | D21: Ejemplo con números reales | E21: De dónde viene | F21: Norma
A22: Saldo inicial | B22: '=IF('03_Provisiones'!Y5="","",'03_Provisiones'!Y5) | C22: Copia de la hoja 03 (datos del cliente) el saldo de la provisión al inicio del período; vacío si no se informó. | D22: Fila 1: IF((vacío)=""; ""; (vacío)) → (en blanco) | E22: hoja «Provisiones y contingencias (datos del cliente)» | F22: —
A23: Tasa % | B23: '='07_Valor_presente'!D5 | C23: Trae la tasa de descuento aplicada a la partida en la hoja 07 (Valor presente). | D23: Fila 1: 8,00 → 8,00 | E23: hoja «Valor presente (descuento)» | F23: —
A24: ¿Descontada? | B24: '='07_Valor_presente'!E5 | C24: Trae de la hoja 07 (Valor presente) si la partida se descuenta o no (Sí/No). | D24: Fila 1: «No» → No | E24: hoja «Valor presente (descuento)» | F24: —
A25: Reversión calculada | B25: '=IF(AND(B5<>"",C5<>"",D5="Sí"),B5*C5/100,"") | C25: Si la partida se descuenta y hay saldo inicial y tasa, multiplica el saldo inicial por la tasa: es el aumento de la provisión por el paso del tiempo. | D25: Fila 1: IF(AND((vacío)<>""; 8,00<>""; «No»="Sí"); (vacío)*8,00/100; "") → (en blanco) | E25: «Saldo inicial» (esta hoja), «Tasa %» (esta hoja), «¿Descontada?» (esta hoja) | F25: —
A26: Reversión registrada | B26: '=IF('03_Provisiones'!Z5="","",'03_Provisiones'!Z5) | C26: Copia de la hoja 03 (datos del cliente) la reversión del descuento que el cliente registró en el período; vacío si no la informó. | D26: Fila 1: IF((vacío)=""; ""; (vacío)) → (en blanco) | E26: hoja «Provisiones y contingencias (datos del cliente)» | F26: —
A27: Calculada − registrada | B27: '=IF(OR(E5="",F5=""),"",E5-F5) | C27: Resta la reversión registrada a la calculada; en blanco si falta cualquiera de las dos. | D27: Fila 1: IF(OR((vacío)=""; (vacío)=""); ""; (vacío)-(vacío)) → (en blanco) | E27: «Reversión calculada» (esta hoja), «Reversión registrada» (esta hoja) | F27: —

Sheet 09_Litigios_abogados
A1: Litigios y cartas de abogados | H1: ⟵ Inicio | I1: ◀ Anterior | J1: Siguiente ▶
A2: Provisiones y contingencias · Cliente de muestra S.A. · corte 2025-12-31
A4: Código | B4: Descripción | C4: Respuesta del abogado | D4: Fecha de la carta | E4: Días desde el corte | F4: Prob. abogado | G4: Prob. gerencia | H4: Importe carta | I4: Libros | J4: Libros − carta | K4: Evaluación
A5: LIT-01 | B5: Demanda laboral ex gerente | C5: =IF('03_Provisiones'!AA5="","",'03_Provisiones'!AA5) | D5: 46063 | E5: =IF(D5="","",D5-'02_Parametros'!$B$5) | F5: ='05_Obligacion_prob'!D5 | G5: ='05_Obligacion_prob'!E5 | H5: =IF('03_Provisiones'!G5="","",'03_Provisiones'!G5) | I5: ='03_Provisiones'!X5 | J5: =IF(H5="","",I5-H5) | K5: =IF(C5<>"Sí","Sin respuesta: limitación (NIA 501)",IF(AND(E5<>"",E5<0),"Carta anterior al corte","Respuesta recibida"))
A6: LIT-02 | B6: Juicio de impugnación tributaria | C6: =IF('03_Provisiones'!AA6="","",'03_Provisiones'!AA6) | D6: 46006 | E6: =IF(D6="","",D6-'02_Parametros'!$B$5) | F6: ='05_Obligacion_prob'!D6 | G6: ='05_Obligacion_prob'!E6 | H6: =IF('03_Provisiones'!G6="","",'03_Provisiones'!G6) | I6: ='03_Provisiones'!X6 | J6: =IF(H6="","",I6-H6) | K6: =IF(C6<>"Sí","Sin respuesta: limitación (NIA 501)",IF(AND(E6<>"",E6<0),"Carta anterior al corte","Respuesta recibida"))
A7: LIT-03 | B7: Demanda civil de proveedor | C7: =IF('03_Provisiones'!AA7="","",'03_Provisiones'!AA7) | D7: 46065 | E7: =IF(D7="","",D7-'02_Parametros'!$B$5) | F7: ='05_Obligacion_prob'!D7 | G7: ='05_Obligacion_prob'!E7 | H7: =IF('03_Provisiones'!G7="","",'03_Provisiones'!G7) | I7: ='03_Provisiones'!X7 | J7: =IF(H7="","",I7-H7) | K7: =IF(C7<>"Sí","Sin respuesta: limitación (NIA 501)",IF(AND(E7<>"",E7<0),"Carta anterior al corte","Respuesta recibida"))
A8: LIT-04 | B8: Reclamo de cliente por entrega tardía | C8: =IF('03_Provisiones'!AA8="","",'03_Provisiones'!AA8) | E8: =IF(D8="","",D8-'02_Parametros'!$B$5) | F8: ='05_Obligacion_prob'!D8 | G8: ='05_Obligacion_prob'!E8 | H8: =IF('03_Provisiones'!G8="","",'03_Provisiones'!G8) | I8: ='03_Provisiones'!X8 | J8: =IF(H8="","",I8-H8) | K8: =IF(C8<>"Sí","Sin respuesta: limitación (NIA 501)",IF(AND(E8<>"",E8<0),"Carta anterior al corte","Respuesta recibida"))
A9: LIT-05 | B9: Juicio laboral de operario | C9: =IF('03_Provisiones'!AA14="","",'03_Provisiones'!AA14) | D9: 46063 | E9: =IF(D9="","",D9-'02_Parametros'!$B$5) | F9: ='05_Obligacion_prob'!D14 | G9: ='05_Obligacion_prob'!E14 | H9: =IF('03_Provisiones'!G14="","",'03_Provisiones'!G14) | I9: ='03_Provisiones'!X14 | J9: =IF(H9="","",I9-H9) | K9: =IF(C9<>"Sí","Sin respuesta: limitación (NIA 501)",IF(AND(E9<>"",E9<0),"Carta anterior al corte","Respuesta recibida"))
A10: LIT-06 | B10: Demanda por uso de marca | C10: =IF('03_Provisiones'!AA15="","",'03_Provisiones'!AA15) | D10: 46063 | E10: =IF(D10="","",D10-'02_Parametros'!$B$5) | F10: ='05_Obligacion_prob'!D15 | G10: ='05_Obligacion_prob'!E15 | H10: =IF('03_Provisiones'!G15="","",'03_Provisiones'!G15) | I10: ='03_Provisiones'!X15 | J10: =IF(H10="","",I10-H10) | K10: =IF(C10<>"Sí","Sin respuesta: limitación (NIA 501)",IF(AND(E10<>"",E10<0),"Carta anterior al corte","Respuesta recibida"))
A12: ⓘ Cómo se calcula esta hoja
A13: Columna | B13: Fórmula (Excel) | C13: Cómo se calcula (sencillo) | D13: Ejemplo con números reales | E13: De dónde viene | F13: Norma
A14: Respuesta del abogado | B14: '=IF('03_Provisiones'!AA5="","",'03_Provisiones'!AA5) | C14: Copia de la hoja 03 (datos del cliente) si se recibió respuesta del abogado (Sí/No); vacío si no se informó. | D14: Fila 1: IF(«Sí»=""; ""; «Sí») → Sí | E14: hoja «Provisiones y contingencias (datos del cliente)» | F14: —
A15: Días desde el corte | B15: '=IF(D5="","",D5-'02_Parametros'!$B$5) | C15: Resta la fecha de corte de la hoja 02 (Parámetros) a la fecha de la carta: un número negativo indica una carta anterior al corte. | D15: Fila 1: IF(«2026-02-10»=""; ""; «2026-02-10»-«2025-12-31») → 41 | E15: «Fecha de la carta» (esta hoja), hoja «Parámetros» | F15: —
A16: Prob. abogado | B16: '='05_Obligacion_prob'!D5 | C16: Trae la probabilidad del abogado de la hoja 05 (Obligación presente y probabilidad) para este litigio. | D16: Fila 1: «Probable» → Probable | E16: hoja «Obligación presente y probabilidad» | F16: —
A17: Prob. gerencia | B17: '='05_Obligacion_prob'!E5 | C17: Trae la probabilidad de la gerencia de la hoja 05 (Obligación presente y probabilidad) para este litigio. | D17: Fila 1: «Probable» → Probable | E17: hoja «Obligación presente y probabilidad» | F17: —
A18: Importe carta | B18: '=IF('03_Provisiones'!G5="","",'03_Provisiones'!G5) | C18: Copia el importe que el abogado indica en su carta, tomado de la hoja 03 (datos del cliente); vacío si no lo hay. | D18: Fila 1: IF(120.000,00=""; ""; 120.000,00) → 120.000,00 | E18: hoja «Provisiones y contingencias (datos del cliente)» | F18: —
A19: Libros | B19: '='03_Provisiones'!X5 | C19: Copia el saldo registrado en libros al corte para este litigio desde la hoja 03 (datos del cliente). | D19: Fila 1: 100.000,00 → 100.000,00 | E19: hoja «Provisiones y contingencias (datos del cliente)» | F19: —
A20: Libros − carta | B20: '=IF(H5="","",I5-H5) | C20: Resta el importe de la carta del abogado al saldo en libros; en blanco si la carta no trae importe. | D20: Fila 1: IF(120.000,00=""; ""; 100.000,00-120.000,00) → -20.000,00 | E20: «Importe carta» (esta hoja), «Libros» (esta hoja) | F20: —
A21: Evaluación | B21: '=IF(C5<>"Sí","Sin respuesta: limitación (NIA 501)",IF(AND(E5<>"",E5<0),"Carta anterior al corte","Respuesta recibida")) | C21: Sin respuesta del abogado marca una limitación; si la carta tiene fecha anterior al corte lo advierte; en otro caso, «Respuesta recibida». | D21: Fila 1: IF(«Sí»<>"Sí"; "Sin respuesta: limitación (NIA 501)"; IF(AND(41<>""; 41<0); "Carta anterior al corte"; "Respuesta recibida")) → Respuesta recibida | E21: «Respuesta del abogado» (esta hoja), «Días desde el corte» (esta hoja) | F21: —

Sheet 10_Garantias_calculo
A1: Garantías: cálculo | H1: ⟵ Inicio | I1: ◀ Anterior | J1: Siguiente ▶
A2: Provisiones y contingencias · Cliente de muestra S.A. · corte 2025-12-31
A4: Línea | B4: Provisión | C4: Unidades | D4: % reclamos | E4: Costo medio | F4: Provisión calculada | G4: Vínculo
A5: GA-A | B5: ='04_Garantias'!B5 | C5: ='04_Garantias'!D5 | D5: ='04_Garantias'!E5 | E5: ='04_Garantias'!F5 | F5: =C5*D5/100*E5 | G5: =IF(COUNTIF('03_Provisiones'!$A$5:$A$17,B5)=0,"Sin provisión en el detalle","Vinculada")
A6: GA-B | B6: ='04_Garantias'!B6 | C6: ='04_Garantias'!D6 | D6: ='04_Garantias'!E6 | E6: ='04_Garantias'!F6 | F6: =C6*D6/100*E6 | G6: =IF(COUNTIF('03_Provisiones'!$A$5:$A$17,B6)=0,"Sin provisión en el detalle","Vinculada")
A7: GA-C | B7: ='04_Garantias'!B7 | C7: ='04_Garantias'!D7 | D7: ='04_Garantias'!E7 | E7: ='04_Garantias'!F7 | F7: =C7*D7/100*E7 | G7: =IF(COUNTIF('03_Provisiones'!$A$5:$A$17,B7)=0,"Sin provisión en el detalle","Vinculada")
A8: TOTAL | F8: =SUM(F5:F7)
A10: ⓘ Cómo se calcula esta hoja
A11: Columna | B11: Fórmula (Excel) | C11: Cómo se calcula (sencillo) | D11: Ejemplo con números reales | E11: De dónde viene | F11: Norma
A12: Provisión | B12: '='04_Garantias'!B5 | C12: Trae de la hoja 04 (Garantías) el código de la provisión a la que pertenece esta línea de producto. | D12: Fila 1: «GAR-01» → GAR-01 | E12: hoja «Garantías (datos del cliente)» | F12: —
A13: Unidades | B13: '='04_Garantias'!D5 | C13: Trae de la hoja 04 (Garantías) las unidades vendidas con garantía vigente al corte. | D13: Fila 1: 12.000,00 → 12.000,00 | E13: hoja «Garantías (datos del cliente)» | F13: —
A14: % reclamos | B14: '='04_Garantias'!E5 | C14: Trae de la hoja 04 (Garantías) el porcentaje histórico de reclamos de esta línea. | D14: Fila 1: 3,00 → 3,00 | E14: hoja «Garantías (datos del cliente)» | F14: —
A15: Costo medio | B15: '='04_Garantias'!F5 | C15: Trae de la hoja 04 (Garantías) lo que cuesta, en promedio, atender cada reclamo. | D15: Fila 1: 85,00 → 85,00 | E15: hoja «Garantías (datos del cliente)» | F15: —
A16: Provisión calculada | B16: '=C5*D5/100*E5 | C16: Multiplica las unidades por el % de reclamos y por el costo medio por reclamo: es el costo esperado de las garantías. | D16: Fila 1: 12.000,00*3,00/100*85,00 → 30.600,00 | E16: «Unidades» (esta hoja), «% reclamos» (esta hoja), «Costo medio» (esta hoja) | F16: —
A17: Vínculo | B17: '=IF(COUNTIF('03_Provisiones'!$A$5:$A$17,B5)=0,"Sin provisión en el detalle","Vinculada") | C17: Revisa si el código de la provisión existe en la hoja 03 (datos del cliente): «Vinculada» si existe; si no, «Sin provisión en el detalle». | D17: Fila 1: IF(COUNTIF([«Código de la provisión o contingencia» de «Provisiones y contingencias (datos del cliente)», 13 filas]; «GAR-01»)=0; "Sin provisión en el detalle"; "Vinculada") → Vinculada | E17: «Provisión» (esta hoja), hoja «Provisiones y contingencias (datos del cliente)» | F17: —

Sheet 11_Onerosos
A1: Contratos onerosos | H1: ⟵ Inicio | I1: ◀ Anterior | J1: Siguiente ▶
A2: Provisiones y contingencias · Cliente de muestra S.A. · corte 2025-12-31
A4: Código | B4: Descripción | C4: Costo de cumplir | D4: Beneficios esperados (37.10) | E4: Costo neto de cumplir | F4: Penalización | G4: Costos inevitables (37.68) | H4: Valor presente | I4: Libros | J4: Ajuste
A5: ONE-01 | B5: Contrato de suministro con pérdida | C5: =IF('03_Provisiones'!R10="","",'03_Provisiones'!R10) | D5: =IF('03_Provisiones'!T10="","",'03_Provisiones'!T10) | E5: =IF(C5="","",MAX(C5-N(D5),0)) | F5: =IF('03_Provisiones'!S10="","",'03_Provisiones'!S10) | G5: =IF(AND(E5="",F5=""),"",IF(E5="",F5,IF(F5="",E5,MIN(E5,F5)))) | H5: ='07_Valor_presente'!G10 | I5: ='03_Provisiones'!X10 | J5: ='13_Reconocimiento'!G10
A7: ⓘ Cómo se calcula esta hoja
A8: Columna | B8: Fórmula (Excel) | C8: Cómo se calcula (sencillo) | D8: Ejemplo con números reales | E8: De dónde viene | F8: Norma
A9: Costo de cumplir | B9: '=IF('03_Provisiones'!R10="","",'03_Provisiones'!R10) | C9: Copia de la hoja 03 (datos del cliente) el costo de cumplir el contrato; vacío si no se informó. | D9: Fila 1: IF(75.000,00=""; ""; 75.000,00) → 75.000,00 | E9: hoja «Provisiones y contingencias (datos del cliente)» | F9: —
A10: Beneficios esperados (37.10) | B10: '=IF('03_Provisiones'!T10="","",'03_Provisiones'!T10) | C10: Copia de la hoja 03 (datos del cliente) los beneficios económicos que se esperan del contrato; vacío si no se informaron. | D10: Fila 1: IF(40.000,00=""; ""; 40.000,00) → 40.000,00 | E10: hoja «Provisiones y contingencias (datos del cliente)» | F10: —
A11: Costo neto de cumplir | B11: '=IF(C5="","",MAX(C5-N(D5),0)) | C11: Resta los beneficios esperados al costo de cumplir, sin bajar de cero; en blanco si no hay costo de cumplir. | D11: Fila 1: IF(75.000,00=""; ""; MAX(75.000,00-N(40.000,00); 0)) → 35.000,00 | E11: «Costo de cumplir» (esta hoja), «Beneficios esperados (37.10)» (esta hoja) | F11: —
A12: Penalización | B12: '=IF('03_Provisiones'!S10="","",'03_Provisiones'!S10) | C12: Copia de la hoja 03 (datos del cliente) la penalización por incumplir el contrato; vacío si no se informó. | D12: Fila 1: IF(45.000,00=""; ""; 45.000,00) → 45.000,00 | E12: hoja «Provisiones y contingencias (datos del cliente)» | F12: —
A13: Costos inevitables (37.68) | B13: '=IF(AND(E5="",F5=""),"",IF(E5="",F5,IF(F5="",E5,MIN(E5,F5)))) | C13: Toma el menor entre el costo neto de cumplir y la penalización; si solo hay uno de los dos, usa ese; vacío si faltan ambos. | D13: Fila 1: IF(AND(35.000,00=""; 45.000,00=""); ""; IF(35.000,00=""; 45.000,00; IF(45.000,00=""; 35.000,00; MIN(35.000,00; 45.000,00)))) → 35.000,00 | E13: «Costo neto de cumplir» (esta hoja), «Penalización» (esta hoja) | F13: —
A14: Valor presente | B14: '='07_Valor_presente'!G10 | C14: Trae el valor presente de esta partida desde la hoja 07 (Valor presente). | D14: Fila 1: 35.000,00 → 35.000,00 | E14: hoja «Valor presente (descuento)» | F14: —
A15: Libros | B15: '='03_Provisiones'!X10 | C15: Copia el saldo registrado en libros al corte para este contrato desde la hoja 03 (datos del cliente). | D15: Fila 1: 0,00 → 0,00 | E15: hoja «Provisiones y contingencias (datos del cliente)» | F15: —
A16: Ajuste | B16: '='13_Reconocimiento'!G10 | C16: Trae el ajuste (provisión requerida − libros) calculado para este contrato en la hoja 13 (Provisión requerida vs libros). | D16: Fila 1: 35.000,00 → 35.000,00 | E16: hoja «Provisión requerida vs libros» | F16: —

Sheet 12_Desmantelamiento
A1: Desmantelamiento | H1: ⟵ Inicio | I1: ◀ Anterior | J1: Siguiente ▶
A2: Provisiones y contingencias · Cliente de muestra S.A. · corte 2025-12-31
A4: Código | B4: Descripción | C4: Costo estimado | D4: Plazo (años) | E4: Tasa % | F4: Valor presente | G4: Libros | H4: Ajuste contra el costo (CINIIF 1) | I4: Reversión calculada | J4: Reversión registrada
A5: DES-01 | B5: Desmantelamiento de planta en terreno arrendado | C5: ='07_Valor_presente'!B11 | D5: ='07_Valor_presente'!C11 | E5: ='07_Valor_presente'!D11 | F5: ='07_Valor_presente'!G11 | G5: ='03_Provisiones'!X11 | H5: ='13_Reconocimiento'!G11 | I5: ='08_Reversion_descuento'!E11 | J5: ='08_Reversion_descuento'!F11
A7: ⓘ Cómo se calcula esta hoja
A8: Columna | B8: Fórmula (Excel) | C8: Cómo se calcula (sencillo) | D8: Ejemplo con números reales | E8: De dónde viene | F8: Norma
A9: Costo estimado | B9: '='07_Valor_presente'!B11 | C9: Trae de la hoja 07 (Valor presente) la mejor estimación del costo de desmantelar, antes de descontarla. | D9: Fila 1: 500.000,00 → 500.000,00 | E9: hoja «Valor presente (descuento)» | F9: —
A10: Plazo (años) | B10: '='07_Valor_presente'!C11 | C10: Trae de la hoja 07 (Valor presente) el plazo en años hasta el desmantelamiento. | D10: Fila 1: 10,00 → 10,00 | E10: hoja «Valor presente (descuento)» | F10: —
A11: Tasa % | B11: '='07_Valor_presente'!D11 | C11: Trae de la hoja 07 (Valor presente) la tasa de descuento aplicada a esta partida. | D11: Fila 1: 7,00 → 7,00 | E11: hoja «Valor presente (descuento)» | F11: —
A12: Valor presente | B12: '='07_Valor_presente'!G11 | C12: Trae de la hoja 07 (Valor presente) el costo estimado ya descontado a la fecha de corte. | D12: Fila 1: 254.174,65 → 254.174,65 | E12: hoja «Valor presente (descuento)» | F12: —
A13: Libros | B13: '='03_Provisiones'!X11 | C13: Copia el saldo registrado en libros al corte para esta obligación desde la hoja 03 (datos del cliente). | D13: Fila 1: 240.000,00 → 240.000,00 | E13: hoja «Provisiones y contingencias (datos del cliente)» | F13: —
A14: Ajuste contra el costo (CINIIF 1) | B14: '='13_Reconocimiento'!G11 | C14: Trae el ajuste (provisión requerida − libros) de la hoja 13 (Provisión requerida vs libros); en desmantelamiento se registra contra el costo del activo. | D14: Fila 1: 14.174,65 → 14.174,65 | E14: hoja «Provisión requerida vs libros» | F14: —
A15: Reversión calculada | B15: '='08_Reversion_descuento'!E11 | C15: Trae de la hoja 08 (Reversión del descuento) el aumento de la provisión por el paso del tiempo que calcula el auditor. | D15: Fila 1: 15.750,00 → 15.750,00 | E15: hoja «Actualización financiera (reversión del descuento)» | F15: —
A16: Reversión registrada | B16: '='08_Reversion_descuento'!F11 | C16: Trae de la hoja 08 (Reversión del descuento) la reversión que el cliente registró en el período. | D16: Fila 1: (vacío) → (en blanco) | E16: hoja «Actualización financiera (reversión del descuento)» | F16: —

Sheet 13_Reconocimiento
A1: Provisión requerida vs libros | H1: ⟵ Inicio | I1: ◀ Anterior | J1: Siguiente ▶
A2: Provisiones y contingencias · Cliente de muestra S.A. · corte 2025-12-31
A4: Código | B4: Tipo | C4: Clasificación | D4: Valor presente | E4: Provisión requerida | F4: Libros | G4: Ajuste (requerida − libros) | H4: Contrapartida
A5: LIT-01 | B5: ='05_Obligacion_prob'!B5 | C5: ='05_Obligacion_prob'!G5 | D5: ='07_Valor_presente'!G5 | E5: =IF(C5="Sin evaluación","",IF(OR(C5="Reconocer provisión",C5="Activo reconocible"),D5,0)) | F5: ='03_Provisiones'!X5 | G5: =IF(E5="","",E5-F5) | H5: Gasto del período (provisión)
A6: LIT-02 | B6: ='05_Obligacion_prob'!B6 | C6: ='05_Obligacion_prob'!G6 | D6: ='07_Valor_presente'!G6 | E6: =IF(C6="Sin evaluación","",IF(OR(C6="Reconocer provisión",C6="Activo reconocible"),D6,0)) | F6: ='03_Provisiones'!X6 | G6: =IF(E6="","",E6-F6) | H6: Gasto del período (provisión)
A7: LIT-03 | B7: ='05_Obligacion_prob'!B7 | C7: ='05_Obligacion_prob'!G7 | D7: ='07_Valor_presente'!G7 | E7: =IF(C7="Sin evaluación","",IF(OR(C7="Reconocer provisión",C7="Activo reconocible"),D7,0)) | F7: ='03_Provisiones'!X7 | G7: =IF(E7="","",E7-F7) | H7: Reversión contra resultados (NIC 37.59)
A8: LIT-04 | B8: ='05_Obligacion_prob'!B8 | C8: ='05_Obligacion_prob'!G8 | D8: ='07_Valor_presente'!G8 | E8: =IF(C8="Sin evaluación","",IF(OR(C8="Reconocer provisión",C8="Activo reconocible"),D8,0)) | F8: ='03_Provisiones'!X8 | G8: =IF(E8="","",E8-F8) | H8: Reversión contra resultados (NIC 37.59)
A9: GAR-01 | B9: ='05_Obligacion_prob'!B9 | C9: ='05_Obligacion_prob'!G9 | D9: ='07_Valor_presente'!G9 | E9: =IF(C9="Sin evaluación","",IF(OR(C9="Reconocer provisión",C9="Activo reconocible"),D9,0)) | F9: ='03_Provisiones'!X9 | G9: =IF(E9="","",E9-F9) | H9: Gasto del período (provisión)
A10: ONE-01 | B10: ='05_Obligacion_prob'!B10 | C10: ='05_Obligacion_prob'!G10 | D10: ='07_Valor_presente'!G10 | E10: =IF(C10="Sin evaluación","",IF(OR(C10="Reconocer provisión",C10="Activo reconocible"),D10,0)) | F10: ='03_Provisiones'!X10 | G10: =IF(E10="","",E10-F10) | H10: Gasto del período (provisión)
A11: DES-01 | B11: ='05_Obligacion_prob'!B11 | C11: ='05_Obligacion_prob'!G11 | D11: ='07_Valor_presente'!G11 | E11: =IF(C11="Sin evaluación","",IF(OR(C11="Reconocer provisión",C11="Activo reconocible"),D11,0)) | F11: ='03_Provisiones'!X11 | G11: =IF(E11="","",E11-F11) | H11: Costo del activo (NIC 16.16 c, 16.18; CINIIF 1)
A12: REE-01 | B12: ='05_Obligacion_prob'!B12 | C12: ='05_Obligacion_prob'!G12 | D12: ='07_Valor_presente'!G12 | E12: =IF(C12="Sin evaluación","",IF(OR(C12="Reconocer provisión",C12="Activo reconocible"),D12,0)) | F12: ='03_Provisiones'!X12 | G12: =IF(E12="","",E12-F12) | H12: Gasto del período (provisión)
A13: AMB-01 | B13: ='05_Obligacion_prob'!B13 | C13: ='05_Obligacion_prob'!G13 | D13: ='07_Valor_presente'!G13 | E13: =IF(C13="Sin evaluación","",IF(OR(C13="Reconocer provisión",C13="Activo reconocible"),D13,0)) | F13: ='03_Provisiones'!X13 | G13: =IF(E13="","",E13-F13) | H13: Gasto del período (provisión)
A14: LIT-05 | B14: ='05_Obligacion_prob'!B14 | C14: ='05_Obligacion_prob'!G14 | D14: ='07_Valor_presente'!G14 | E14: =IF(C14="Sin evaluación","",IF(OR(C14="Reconocer provisión",C14="Activo reconocible"),D14,0)) | F14: ='03_Provisiones'!X14 | G14: =IF(E14="","",E14-F14) | H14: Gasto del período (provisión)
A15: LIT-06 | B15: ='05_Obligacion_prob'!B15 | C15: ='05_Obligacion_prob'!G15 | D15: ='07_Valor_presente'!G15 | E15: =IF(C15="Sin evaluación","",IF(OR(C15="Reconocer provisión",C15="Activo reconocible"),D15,0)) | F15: ='03_Provisiones'!X15 | G15: =IF(E15="","",E15-F15) | H15: Reversión contra resultados (NIC 37.59)
A16: OTR-01 | B16: ='05_Obligacion_prob'!B16 | C16: ='05_Obligacion_prob'!G16 | D16: ='07_Valor_presente'!G16 | E16: =IF(C16="Sin evaluación","",IF(OR(C16="Reconocer provisión",C16="Activo reconocible"),D16,0)) | F16: ='03_Provisiones'!X16 | G16: =IF(E16="","",E16-F16) | H16: Gasto del período (provisión)
A17: ACT-01 | B17: ='05_Obligacion_prob'!B17 | C17: ='05_Obligacion_prob'!G17 | D17: ='07_Valor_presente'!G17 | E17: =IF(C17="Sin evaluación","",IF(OR(C17="Reconocer provisión",C17="Activo reconocible"),D17,0)) | F17: ='03_Provisiones'!X17 | G17: =IF(E17="","",E17-F17) | H17: Otros ingresos / cuenta por cobrar (NIC 37.33)
A18: TOTAL | E18: =SUM(E5:E17) | F18: =SUM(F5:F17) | G18: =SUM(G5:G17)
A20: ⓘ Cómo se calcula esta hoja
A21: Columna | B21: Fórmula (Excel) | C21: Cómo se calcula (sencillo) | D21: Ejemplo con números reales | E21: De dónde viene | F21: Norma
A22: Tipo | B22: '='05_Obligacion_prob'!B5 | C22: Trae el tipo de la partida desde la hoja 05 (Obligación presente y probabilidad). | D22: Fila 1: «Litigio» → Litigio | E22: hoja «Obligación presente y probabilidad» | F22: —
A23: Clasificación | B23: '='05_Obligacion_prob'!G5 | C23: Trae la clasificación (reconocer, revelar o no revelar) de la hoja 05 (Obligación presente y probabilidad). | D23: Fila 1: «Reconocer provisión» → Reconocer provisión | E23: hoja «Obligación presente y probabilidad» | F23: —
A24: Valor presente | B24: '='07_Valor_presente'!G5 | C24: Trae el valor presente de la mejor estimación desde la hoja 07 (Valor presente). | D24: Fila 1: 114.000,00 → 114.000,00 | E24: hoja «Valor presente (descuento)» | F24: —
A25: Provisión requerida | B25: '=IF(C5="Sin evaluación","",IF(OR(C5="Reconocer provisión",C5="Activo reconocible"),D5,0)) | C25: Si la partida se clasificó como «Reconocer provisión» o «Activo reconocible», toma su valor presente; si solo se revela o es remota, cero; en blanco si está sin evaluación. | D25: Fila 1: IF(«Reconocer provisión»="Sin evaluación"; ""; IF(OR(«Reconocer provisión»="Reconocer provisión"; «Reconocer provisión»="Activo reconocible"); 114.000,00; 0)) → 114.000,00 | E25: «Clasificación» (esta hoja), «Valor presente» (esta hoja) | F25: —
A26: Libros | B26: '='03_Provisiones'!X5 | C26: Copia el saldo registrado en libros al corte desde la hoja 03 (datos del cliente). | D26: Fila 1: 100.000,00 → 100.000,00 | E26: hoja «Provisiones y contingencias (datos del cliente)» | F26: —
A27: Ajuste (requerida − libros) | B27: '=IF(E5="","",E5-F5) | C27: Resta el saldo en libros a la provisión requerida: positivo significa que falta provisión y negativo que sobra; en blanco si está sin evaluación. | D27: Fila 1: IF(114.000,00=""; ""; 114.000,00-100.000,00) → 14.000,00 | E27: «Provisión requerida» (esta hoja), «Libros» (esta hoja) | F27: —

Sheet 14_Contingencias
A1: Contingencias a revelar | H1: ⟵ Inicio | I1: ◀ Anterior | J1: Siguiente ▶
A2: Provisiones y contingencias · Cliente de muestra S.A. · corte 2025-12-31
A4: Código | B4: Descripción | C4: Clasificación | D4: Probabilidad | E4: Efecto estimado | F4: Revelado | G4: Evaluación | H4: Registrado en libros
A5: LIT-03 | B5: Demanda civil de proveedor | C5: ='05_Obligacion_prob'!G7 | D5: ='05_Obligacion_prob'!F7 | E5: ='07_Valor_presente'!G7 | F5: =IF('03_Provisiones'!AC7="","",'03_Provisiones'!AC7) | G5: =IF(C5="Activo contingente: no revelar","No revelar (no probable); no reconocer (37.31)",IF(F5="Sí",IF(LEFT(C5,6)="Pasivo","Revelado (NIC 37.86)","Revelado (NIC 37.89)"),IF(LEFT(C5,6)="Pasivo","Revelar: NIC 37.86 · PYMES 21.15","Revelar: NIC 37.89 · PYMES 21.16"))) | H5: ='03_Provisiones'!X7
A6: LIT-04 | B6: Reclamo de cliente por entrega tardía | C6: ='05_Obligacion_prob'!G8 | D6: ='05_Obligacion_prob'!F8 | E6: ='07_Valor_presente'!G8 | F6: =IF('03_Provisiones'!AC8="","",'03_Provisiones'!AC8) | G6: =IF(C6="Activo contingente: no revelar","No revelar (no probable); no reconocer (37.31)",IF(F6="Sí",IF(LEFT(C6,6)="Pasivo","Revelado (NIC 37.86)","Revelado (NIC 37.89)"),IF(LEFT(C6,6)="Pasivo","Revelar: NIC 37.86 · PYMES 21.15","Revelar: NIC 37.89 · PYMES 21.16"))) | H6: ='03_Provisiones'!X8
A7: ACT-01 | B7: Demanda a la aseguradora por siniestro | C7: ='05_Obligacion_prob'!G17 | D7: ='05_Obligacion_prob'!F17 | E7: ='07_Valor_presente'!G17 | F7: =IF('03_Provisiones'!AC17="","",'03_Provisiones'!AC17) | G7: =IF(C7="Activo contingente: no revelar","No revelar (no probable); no reconocer (37.31)",IF(F7="Sí",IF(LEFT(C7,6)="Pasivo","Revelado (NIC 37.86)","Revelado (NIC 37.89)"),IF(LEFT(C7,6)="Pasivo","Revelar: NIC 37.86 · PYMES 21.15","Revelar: NIC 37.89 · PYMES 21.16"))) | H7: ='03_Provisiones'!X17
A9: ⓘ Cómo se calcula esta hoja
A10: Columna | B10: Fórmula (Excel) | C10: Cómo se calcula (sencillo) | D10: Ejemplo con números reales | E10: De dónde viene | F10: Norma
A11: Clasificación | B11: '='05_Obligacion_prob'!G7 | C11: Trae la clasificación de la partida desde la hoja 05 (Obligación presente y probabilidad); aquí solo aparecen pasivos y activos contingentes. | D11: Fila 1: «Pasivo contingente: revelar» → Pasivo contingente: revelar | E11: hoja «Obligación presente y probabilidad» | F11: —
A12: Probabilidad | B12: '='05_Obligacion_prob'!F7 | C12: Trae la probabilidad usada (la del abogado o, si falta, la de la gerencia) de la hoja 05 (Obligación presente y probabilidad). | D12: Fila 1: «Posible» → Posible | E12: hoja «Obligación presente y probabilidad» | F12: —
A13: Efecto estimado | B13: '='07_Valor_presente'!G7 | C13: Trae el valor presente de la mejor estimación de la hoja 07 (Valor presente): es el efecto financiero que se revela. | D13: Fila 1: 40.000,00 → 40.000,00 | E13: hoja «Valor presente (descuento)» | F13: —
A14: Revelado | B14: '=IF('03_Provisiones'!AC7="","",'03_Provisiones'!AC7) | C14: Copia de la hoja 03 (datos del cliente) si la contingencia está revelada en notas (Sí/No); vacío si no se informó. | D14: Fila 1: IF(«Sí»=""; ""; «Sí») → Sí | E14: hoja «Provisiones y contingencias (datos del cliente)» | F14: —
A15: Evaluación | B15: '=IF(C5="Activo contingente: no revelar","No revelar (no probable); no reconocer (37.31)",IF(F5="Sí",IF(LEFT(C5,6)="Pasivo","Revelado (NIC 37.86)","Revelado (NIC 37.89)"),IF(LEFT(C5,6)="Pasivo","Revelar: NIC 37.86 · PYMES 21.15","Revelar: NIC 37.89 · PYMES 21.16"))) | C15: Si es un activo contingente que no se revela, lo indica; si no, dice «Revelado» cuando la nota ya lo incluye o «Revelar» cuando falta, distinguiendo pasivo de activo contingente. | D15: Fila 1: IF(«Pasivo contingente: revelar»="Activo contingente: no revelar"; "No revelar (no probable); no reconocer (37.31)"; IF(«Sí»="Sí"; IF(LEFT(«Pasivo contingente: revelar»; 6)="Pasivo"; "Revelado (NIC 37.86)"; "Revelado (NIC 37.89)"); IF(LEFT(«Pasivo contingente: revelar»; 6)="Pasivo"; "Revelar: NIC 37.86 · PYMES 21.15"; "Revelar: NIC 37.89 · PYMES 21.16"))) → Revelado (NIC 37.86) | E15: «Clasificación» (esta hoja), «Revelado» (esta hoja) | F15: —
A16: Registrado en libros | B16: '='03_Provisiones'!X7 | C16: Copia el saldo que el cliente tiene en libros para esta contingencia, desde la hoja 03 (datos del cliente). | D16: Fila 1: 40.000,00 → 40.000,00 | E16: hoja «Provisiones y contingencias (datos del cliente)» | F16: —

Sheet 15_Ajustes
A1: Ajustes propuestos y conciliación | H1: ⟵ Inicio | I1: ◀ Anterior | J1: Siguiente ▶
A2: Provisiones y contingencias · Cliente de muestra S.A. · corte 2025-12-31
A4: Concepto | B4: Importe | C4: Débito (si positivo) | D4: Crédito (si positivo) | E4: Base
A5: Provisiones registradas en libros (pasivos) | B5: =SUMIFS('13_Reconocimiento'!$F$5:$F$17,'13_Reconocimiento'!$B$5:$B$17,"<>Activo contingente") | E5: Detalle del cliente
A6: Provisión requerida (NIC 37.36–47; PYMES 21.7) | B6: =SUMIFS('13_Reconocimiento'!$E$5:$E$17,'13_Reconocimiento'!$B$5:$B$17,"<>Activo contingente") | E6: 13_Reconocimiento
A7: Ajuste propuesto = requerida − libros | B7: =SUMIFS('13_Reconocimiento'!$G$5:$G$17,'13_Reconocimiento'!$B$5:$B$17,"<>Activo contingente") | C7: Gasto / costo del activo | D7: Provisión | E7: Si es negativo: débito a la provisión y crédito a resultados (NIC 37.59)
A8: Efecto del descuento a valor presente | B8: =SUM('07_Valor_presente'!$H$5:$H$17) | E8: NIC 37.45–47; PYMES 21.7
A9: Reversión del descuento calculada (saldo inicial × tasa) | B9: =SUM('08_Reversion_descuento'!$E$5:$E$17) | E9: NIC 37.60; PYMES 21.11
A10: Reversión del descuento registrada | B10: =SUM('08_Reversion_descuento'!$F$5:$F$17) | E10: Mayor de gastos financieros
A11: Reversión: calculada − registrada (reclasificación) | B11: =SUM('08_Reversion_descuento'!$G$5:$G$17) | C11: Costo financiero | D11: Gasto operativo / provisión | E11: Reclasificación dentro de resultados
A12: Garantías calculadas (unidades × % reclamos × costo) | B12: =SUM('10_Garantias_calculo'!$F$5:$F$7) | E12: NIC 37.24, 39; PYMES 21A.4
A13: Pasivos contingentes a revelar (efecto estimado) | B13: =SUMIF('13_Reconocimiento'!$C$5:$C$17,"Pasivo contingente: revelar",'13_Reconocimiento'!$D$5:$D$17) | E13: NIC 37.86; PYMES 21.15
A14: Pasivos contingentes sin revelar | B14: =SUMIFS('14_Contingencias'!$E$5:$E$7,'14_Contingencias'!$C$5:$C$7,"Pasivo contingente: revelar",'14_Contingencias'!$G$5:$G$7,"Revelar*") | E14: Revelación en notas
A15: Activo contingente reconocido indebidamente | B15: =SUMIFS('13_Reconocimiento'!$F$5:$F$17,'13_Reconocimiento'!$B$5:$B$17,"Activo contingente",'13_Reconocimiento'!$C$5:$C$17,"<>Activo reconocible") | E15: NIC 37.31, 33; PYMES 21.13
A16: Ajuste del activo contingente = −(reconocido indebidamente) | B16: =-B15 | C16: Resultados | D16: Activo contingente | E16: Revertir el activo
A17: Provisiones según el mayor | B17: =IF('02_Parametros'!$B$12="","",'02_Parametros'!$B$12) | E17: Mayor contable
A18: Diferencia detalle − mayor | B18: =IF(B17="","",B5-B17)
A19: Materialidad | B19: =IF('02_Parametros'!$B$10="","",'02_Parametros'!$B$10) | E19: NIA 320
A20: ¿El ajuste propuesto supera la materialidad? | E20: =IF(B19="","",IF(ABS(B7)>B19,"Sí","No"))
A22: ⓘ Cómo se calcula esta hoja
A23: Columna | B23: Fórmula (Excel) | C23: Cómo se calcula (sencillo) | D23: Ejemplo con números reales | E23: De dónde viene | F23: Norma
A24: Importe | B24: '=SUMIFS('13_Reconocimiento'!$F$5:$F$17,'13_Reconocimiento'!$B$5:$B$17,"<>Activo contingente") | C24: Libros, requerida y ajuste suman la hoja 13 (Provisión requerida vs libros) sin los activos contingentes; descuento, reversiones y garantías traen los totales de las hojas 07, 08 y 10; los contingentes salen de las hojas 13 y 14; mayor y materialidad vienen de la hoja 02 y la diferencia es detalle − mayor. | D24: Fila 1: SUMIFS([«Libros» de «Provisión requerida vs libros», 13 filas]; [«Tipo» de «Provisión requerida vs libros», 13 filas]; "<>Activo contingente") → 725.000,00 | E24: hoja «Provisión requerida vs libros» | F24: —
A25: Base | B25: '=IF(B19="","",IF(ABS(B7)>B19,"Sí","No")) | C25: Solo en la última fila: indica «Sí» si el ajuste propuesto, en valor absoluto, supera la materialidad; vacío si no hay materialidad. | D25: Fila 16: IF(50.000,00=""; ""; IF(ABS(38.758,90)>50.000,00; "Sí"; "No")) → No | E25: «Importe» (esta hoja) | F25: —

Sheet 16_Problemas
A1: Problemas encontrados | H1: ⟵ Inicio | I1: ◀ Anterior | J1: Siguiente ▶
A2: Provisiones y contingencias · Cliente de muestra S.A. · corte 2025-12-31
A4: Código | B4: Descripción | C4: Importe
A5: DIFERENCIA_PROVISION | B5: LIT-01: provisión requerida 114.000,00 (Valor esperado (37.39)) ≠ libros 100.000,00; ajuste contra gasto del período (provisión). | C5: 14000
A6: DIFERENCIA_CARTA_ABOGADO | B6: LIT-01: libros 100.000,00 ≠ importe de la carta del abogado 120.000,00 (NIA 501). | C6: -20000
A7: DISCREPANCIA_PROBABILIDAD | B7: LIT-02: el abogado evalúa «Probable» y la gerencia «Posible»; se usó la del abogado. Discuta la diferencia con la gerencia (NIA 501, NIA 540). | C7: 0
A8: CARTA_ANTERIOR_AL_CORTE | B8: LIT-02: la carta del abogado es del 2025-12-15, anterior al corte; pida una actualización cercana a la fecha del informe (NIA 501, NIA 560). | C8: 0
A9: PROVISION_NO_REGISTRADA | B9: LIT-02 (Juicio de impugnación tributaria): obligación probable no registrada; provisión requerida 65.997,97 (Punto medio del rango (37.39)). | C9: 65997.97
A10: DIFERENCIA_CARTA_ABOGADO | B10: LIT-02: libros 0,00 ≠ importe de la carta del abogado 85.000,00 (NIA 501). | C10: -85000
A11: PROVISION_POSIBLE_O_REMOTA | B11: LIT-03: provisión registrada por 40.000,00 con salida «Posible» (no probable); revertir (NIC 37.14, 23, 59; PYMES 21.4). | C11: 40000
A12: SIN_RESPUESTA_ABOGADO | B12: LIT-04: no hay respuesta del abogado a la carta de confirmación; posible limitación al alcance (NIA 501 párr. 10–11; NIA 705). | C12: 20000
A13: CONTINGENCIA_SIN_REVELAR | B13: LIT-04 (Reclamo de cliente por entrega tardía): pasivo contingente «Posible» sin revelación en notas (NIC 37.28, 86; PYMES 21.15). | C13: 20000
A14: DIFERENCIA_PROVISION | B14: GAR-01: provisión requerida 42.600,00 (Garantías: valor esperado (37.39)) ≠ libros 30.000,00; ajuste contra gasto del período (provisión). | C14: 12600
A15: ONEROSO_NO_PROVISIONADO | B15: ONE-01 (Contrato de suministro con pérdida): obligación probable no registrada; provisión requerida 35.000,00 (Oneroso: menor costo (37.68)). Costos inevitables = menor entre el costo neto de cumplir (costo − beneficios esperados) y la penalización (NIC 37.10, 66–68; PYMES 21A.2). | C15: 35000
A16: DIFERENCIA_PROVISION | B16: DES-01: provisión requerida 254.174,65 (Estimación de la gerencia) ≠ libros 240.000,00; ajuste contra costo del activo (nic 16.16 c, 16.18; ciniif 1). | C16: 14174.65
... A25: CONCILIACION_MAYOR | B25: Provisiones del detalle 725.000,00 ≠ mayor 730.000,00. | C25: -5000

Sheet 13_Conclusion
A1: Conclusión | H1: ⟵ Inicio | I1: ◀ Anterior | J1: Siguiente ▶
A2: Provisiones y contingencias · Cliente de muestra S.A. · corte 2025-12-31
A4: Concepto | B4: Detalle
A5: Conciliación con el mayor | B5: Población None · mayor None · diferencia None
A6: Evaluación de excepciones
A7: Análisis
A8: Conclusión

Sheet 14_Control_Revision
A1: Control de revisión | H1: ⟵ Inicio | I1: ◀ Anterior
A2: Provisiones y contingencias · Cliente de muestra S.A. · corte 2025-12-31
A4: Fecha | B4: Acción | C4: Estado anterior | D4: Estado nuevo | E4: Actor | F4: Comentario
